{"https://www.argenprop.com/departamento-en-alquiler-en-caballito-2-ambientes--16146589": {"id": "19553375", "date": "05-09-2024\n", "index": 3, "content": "1\n/13\n180\n$ 300.000 + $95.000 expensas\nSan Ireneo 300, Piso 5\nDepartamento en Alquiler en Caballito, Capital Federal\n36 m\u00b2 cubie.\n1 dorm.\n45 a\u00f1os\nAlquiler 2 ambientes laterales Pje San Ireneo al 300 Caballito\nMuy buen departamento de dos ambientes lateral muy luminoso en muy buen estado. Excelente ubicacion a pocas cuadras de acoyte y rivadavia y de primera junta. Gran zona comercial y de transportes. Subte a. Se deja constancia que la superficie y medidas son aproximadas requisitos: demostraci\u00f3n de ingresos - garant\u00eda propietaria o seguro de cauci\u00f3n. Condiciones: contrato dos a\u00f1os - mes adelantado -\nWhatsApp\nContactar", "revised": false, "rejected": false, "data": {"precio": "$ 300.000 + $95.000 expensas", "expensas": "+ $95.000 expensas", "direccion": "San Ireneo 300, Piso 5", "metros": "36 m\u00b2 cubie.", "habitaciones": "1 dorm."}, "image": "https://static1.sosiva451.com/98564161/e59e8d08-25a6-4349-ba98-dcb7611f1c86_u_small.jpg", "title": "Alquiler 2 ambientes laterales Pje San Ireneo al 300 Caballito"}, "https://www.argenprop.com/departamento-en-alquiler-en-constitucion-2-ambientes--15974253": {"id": "19390583", "date": "05-09-2024\n", "index": 8, "content": "1\n/6\n2\n$ 300.000\nSalta 2000, Piso 2\nDepartamento en Alquiler en Constitucion, Capital Federal\n39 m\u00b2 cubie.\n1 dorm.\n1 ba\u00f1o\nDepartamento 2 amb , excelente ubicacion\nDepartamento muy luminoso, todo externo, living-comedor 1 dormitorio c/placard, otro placard en el paso, ba\u00f1o completo, cocina y lavadero cubierto. Agua caliente y calefacci\u00f3n individual pintado a nuevo. Contrato a dos a\u00f1os ajuste cada 4 meses es necesario demostrar ingresos y presentar un garante living: 4.00 x 3.00 dormitorio: 3.00 x 3.00 c/placard cocina: 2.00 x 1.60 lavadero 1.60 x 1.00\nWhatsApp\nContactar", "revised": false, "rejected": false, "data": {"precio": "$ 300.000", "direccion": "Salta 2000, Piso 2", "metros": "39 m\u00b2 cubie.", "habitaciones": "1 dorm."}, "image": "https://static1.sosiva451.com/35247951/553d6a9d-e993-4ac6-93e8-ab2b78221db1_u_small.jpg", "title": "Departamento 2 amb , excelente ubicacion "}, "https://www.argenprop.com/departamento-en-alquiler-en-caballito-2-ambientes--16149419": {"id": "19556198", "date": "05-09-2024\n", "index": 29, "content": "1\n/12\n0\n$ 300.000 + $83.000 expensas\nCachimayo al 100\nDepartamento en Alquiler en Caballito, Capital Federal\n37 m\u00b2 cubie.\n1 dorm.\n50 a\u00f1os\nDEPTO 2 AMB EXCELENTE UBICACION LATERAL M/B/ESTADO\nDepto 2 amb en inmejorable ubicaci\u00f3n/ apto liv/com: 4.7 x 3 dorm1: 3.4 x 3 c/plac hall/intim: 1 c/plac cocina: 4 x 1.5 lav/cub: 1.3 x 0.9 b\u00f1o/compl: 1 cant. Pisos: 15 deptos x piso: 6 observaciones: lateral / excelente ubicacion / recien pintado/ 1/2 av. Rivadavia alt 5400 / 1/2 av. J.B. Alberdi alt 900 / 1 c. Estacion primera junta subte \"a\" / las medidas expresadas\nContactar", "revised": false, "rejected": false, "data": {"precio": "$ 300.000 + $83.000 expensas", "expensas": "+ $83.000 expensas", "direccion": "Cachimayo al 100", "metros": "37 m\u00b2 cubie.", "habitaciones": "1 dorm."}, "image": "https://static1.sosiva451.com/91494161/eebd49c3-1089-4c81-950a-dc37f3fe7c7d_u_small.jpg", "title": "DEPTO 2 AMB EXCELENTE UBICACION LATERAL M/B/ESTADO"}, "https://www.argenprop.com/departamento-en-alquiler-en-constitucion-2-ambientes--16151207": {"id": "19557975", "date": "05-09-2024\n", "index": 49, "content": "1\n/18\n9\n$ 250.000 + $120.000 expensas\n15 De Noviembre 1600, Piso 4\nDepartamento en Alquiler en Constitucion, Capital Federal\n38 m\u00b2 cubie.\n1 dorm.\n50 a\u00f1os\nMuy buen departamento de dos ambientes.\nMuy buen departamento de dos ambientes, cuarto piso con ascensor, cocina con muebles bajo mesada y alto mesada, ba\u00f1o, lavadero, ambientes muy luminosos. 40 mts\u00b2 totales. #Dosambiente #alquiler #constitucion #inmobiliariatraboulsi #tucorredorinmobiliario #departamento #venta #administraci\u00f3n #administramostupropiedad #bot\u00e1nicosur #laboca #barracas concrete entrevista a los tel\u00e9fonos /2566\nWhatsApp\nContactar", "revised": false, "rejected": false, "data": {"precio": "$ 250.000 + $120.000 expensas", "expensas": "+ $120.000 expensas", "direccion": "15 De Noviembre 1600, Piso 4", "metros": "38 m\u00b2 cubie.", "habitaciones": "1 dorm."}, "image": "https://static1.sosiva451.com/70215161/b46aabec-dabc-45ec-b243-77a4671f5d46_u_small.jpg", "title": "Muy buen departamento de dos ambientes."}, "https://www.argenprop.com/departamento-en-alquiler-en-chacarita-1-ambiente--15933173": {"id": "19349534", "date": "05-09-2024\n", "index": 55, "content": "1\n/11\n900\n$ 300.000 + $92.700 expensas\nAvenida Olleros 3500, Piso 2\nDepartamento en Alquiler en Chacarita, Capital Federal\n30 m\u00b2 cubie.\n4 a\u00f1os\nMonoam.\nMonoambiente - Frente - Balc\u00f3n\nAlquiler departamento monoambiente, semipiso, al frente, con balc\u00f3n corrido, termotanque el\u00e9ctrico, anafe de 2 hornallas, cocina con desayunador, expensas con aysa incluidas, excelente ubicaci\u00f3n olleros y c\u00f3rdoba, a 1 cuadra de av. Lacroze y a 1 cuadra de av. Alvarez thomas.- Frery propiedades \u2013 m\u00f3nica l. Dest\u00e9fanis - cucicba 1145 / tel\u00e9fonos de contacto / / ley 5115: propiedad apta para\nWhatsApp\nContactar", "revised": false, "rejected": false, "data": {"precio": "$ 300.000 + $92.700 expensas", "expensas": "+ $92.700 expensas", "direccion": "Avenida Olleros 3500, Piso 2", "metros": "30 m\u00b2 cubie.", "habitaciones": "4 a\u00f1os"}, "image": "https://static1.sosiva451.com/37133951/2816da79-9660-44e2-9120-8f3168d50ea2_u_small.jpg", "title": "Monoambiente - Frente - Balc\u00f3n "}, "https://www.argenprop.com/departamento-en-alquiler-en-belgrano-2-ambientes--16126121": {"id": "19533049", "date": "05-09-2024\n", "index": 66, "content": "1\n/14\n0\n$ 550 + $110.000 expensas\nCr\u00e1mer 1600\nDepartamento en Alquiler en Belgrano, Capital Federal\n40 m\u00b2 cubie.\n1 dorm.\n18 a\u00f1os\nALQUILER DEPARTAMENTO 2 AMBIENTES C/COCHERA\nEl equipo de remax ofrece en alquiler departamento dos ambientes en la preciada zona de belgrano, cramer al 1600. Es un cuarto piso con una vista espectacular abierta a cramer y av elcano. La cocina es el\u00e9ctrica e integrada con barra desayunadora. El living tiene salida al balc\u00f3n con amplia vista. Todo en impecable estado. El edificio tiene amenities, pileta, terraza y parrilla y dispone de sala\nContactar", "revised": false, "rejected": false, "data": {"precio": "$ 550 + $110.000 expensas", "expensas": "+ $110.000 expensas", "direccion": "Cr\u00e1mer 1600", "metros": "40 m\u00b2 cubie.", "habitaciones": "1 dorm."}, "image": "https://static1.sosiva451.com/12162161/45eda0e0-8b31-4258-a048-5ff2737adbfc_u_small.jpg", "title": "ALQUILER DEPARTAMENTO 2 AMBIENTES C/COCHERA"}, "https://www.argenprop.com/departamento-en-alquiler-en-caballito-2-ambientes--16150630": {"id": "19557401", "date": "05-09-2024\n", "index": 75, "content": "1\n/17\n2\n$ 530 + $115.000 expensas\nMorelos al 100\nDepartamento en Alquiler en Caballito, Capital Federal\n43 m\u00b2 cubie.\n1 dorm.\n10 a\u00f1os\nD\u00b4Odorico Propiedades\nDepartamento de 1 dormitorio en alquiler en caballito. Al frente, con balc\u00f3n, orientaci\u00f3n este, living comedor con equipo split, dormitorio con placard, cocina y ba\u00f1o completo. Cochera fija en primer subsuelo no 12.- Edificio con sum, pileta, parrilla, solarium y laundry , vigilancia 24 hs requisitos 1) ingresos demostrables que tripliquen del valor locativo, antiguedad laboral\nContactar", "revised": false, "rejected": false, "data": {"precio": "$ 530 + $115.000 expensas", "expensas": "+ $115.000 expensas", "direccion": "Morelos al 100", "metros": "43 m\u00b2 cubie.", "habitaciones": "1 dorm."}, "image": "https://static1.sosiva451.com/03605161/e3294974-8670-4863-9af2-ac6858ebaaab_u_small.jpg", "title": "D\u00b4Odorico Propiedades"}, "https://www.argenprop.com/departamento-en-alquiler-en-caballito-1-ambiente--6675859": {"id": "10367401", "date": "05-09-2024\n", "index": 78, "content": "1\n/12\n2\nConsultar precio + $55.000 expensas\nAv. Rivadavia 6100, Piso 11\nDepartamento en Alquiler en Caballito, Capital Federal\n37 m\u00b2 cubie.\n5 a\u00f1os\n1 ba\u00f1o\nCABALLITO - MONOAMBIENTE NUEVO - 40 m2 al frente con blac\u00f2n\nHermoso monoambiente, superluminoso, amplia vista al frente con balc\u00f3n. Av. Rivadavia y malvinas argentinas, a 3 cuadras del subte a estaci\u00f3n carabobo. Requisitos: garant\u00eda propietaria o seguro de alquiler , comprobantes de ingresos. Un mes adelantado y un mes de dep\u00f3sito. Gastos de informes si es garant\u00eda propietaria\nWhatsApp\nContactar", "revised": false, "rejected": false, "data": {"precio": "Consultar precio + $55.000 expensas", "expensas": "+ $55.000 expensas", "direccion": "Av. Rivadavia 6100, Piso 11", "metros": "37 m\u00b2 cubie.", "habitaciones": "5 a\u00f1os"}, "image": "https://static1.sosiva451.com/9585766/ac2f6e48-3c73-4b3a-982a-36545cb366ad_u_small.jpg", "title": "CABALLITO - MONOAMBIENTE NUEVO - 40 m2 al frente con blac\u00f2n"}, "https://www.argenprop.com/departamento-en-alquiler-en-caballito-1-ambiente--15689213": {"id": "19105925", "date": "05-09-2024\n", "index": 95, "content": "1\n/28\n50\n$ 250.000 + $20.000 expensas\nRojas 100, Piso 6\nDepartamento en Alquiler en Caballito, Capital Federal\n33 m\u00b2 cubie.\nMonoam.\nMuy Bueno\nMONOAMBIENTE AL FRENTE LUMINOSO A 1 CUADRA ESTACION SUBTE LINEA \"A\"\nExcelente monoambiente en perfectas condiciones de conservacion, superluminoso, cuenta con una puerta balcon con balcon frances al contrafrente y una ventana al frente con vista a la calle rojas.-El ambiente tiene un placard de 2 puertas con cajoneras y una estufa de tiro balanceado.-La cocina permite poner una mesita para comer, cuenta con mueble bajo mesada y alacenas de 3 puertas.-El ba\u00f1o\nContactar", "revised": false, "rejected": false, "data": {"precio": "$ 250.000 + $20.000 expensas", "expensas": "+ $20.000 expensas", "direccion": "Rojas 100, Piso 6", "metros": "33 m\u00b2 cubie.", "habitaciones": "Monoam."}, "image": "https://static1.sosiva451.com/31298651/63f720ba-35cc-48f0-a8fe-1700b7a6cc73_u_small.jpg", "title": "MONOAMBIENTE AL FRENTE LUMINOSO A 1 CUADRA ESTACION SUBTE LINEA \"A\""}}