{"https://www.argenprop.com/casa-en-venta-en-constitucion-2-ambientes--16043051": {"id": "19450201", "date": "07-09-2024\n", "index": 3, "content": "1\n/21\n1\nUSD 58.000\nVirrey Cevallos 1100\nCasa en Venta en Constitucion, Capital Federal\n42 m\u00b2 cubie.\n1 dorm.\n54 a\u00f1os\n2 Ambientes con Balcon Super Luminoso\n2 ambientes con balcon super luminoso hermoso departamento, 6to piso frente 2 ambientes con balc\u00f3n frente ubicado en virrey cevallos esquina av. San juan, a dos cuadras de la av. Entre r\u00edos. S\u00faper luminoso y en excelente estado. Cuenta con gran living comedor con salida al balc\u00f3n, cocina amplia, dormitorio con placard y ba\u00f1o completo. M\u00faltiples medios de transporte : 6, 8, 12, 23, 37, 39, 46, 50,\nContactar", "revised": false, "rejected": false, "data": {"precio": "USD 58.000", "direccion": "Virrey Cevallos 1100", "metros": "42 m\u00b2 cubie.", "habitaciones": "1 dorm."}, "image": "https://static1.sosiva451.com/15034061/1c744a4f-baf4-4fa3-8f75-fa10eed1d30b_u_small.jpg", "title": "2 Ambientes con Balcon Super Luminoso"}, "https://www.argenprop.com/departamento-en-venta-en-balvanera-2-ambientes--15935367": {"id": "19351727", "date": "07-09-2024\n", "index": 4, "content": "1\n/17\n0\nUSD 80.000\nAV JUJUY 1000\nDepartamento en Venta en Balvanera, Capital Federal\n42 m\u00b2 cubie.\n1 dorm.\n40 a\u00f1os\nDepartamento - Venta - Argentina, Capital Federal - AV JUJUY 1000\nVenta departamento 2 ambientes listo para mudarse,  super luminoso apto credito. Departamento de \u00e9poca, se puede modernizar. Se encuentra en piso alto con vista panor\u00e1mica. Contrafrente. Muy luminoso, silencioso, todos los ambientes con luz natural y mucha ventilaci\u00f3n. Cuenta con living comedor con salida al gran balc\u00f3n corrido, con vista abierta.  Dormitorio amplio con mucho lugar de\nWhatsApp\nContactar", "revised": false, "rejected": false, "data": {"precio": "USD 80.000", "direccion": "AV JUJUY 1000", "metros": "42 m\u00b2 cubie.", "habitaciones": "1 dorm."}, "image": "https://static1.sosiva451.com/76353951/f1fcaa6c-3238-4448-be4d-9cd89be615ef_u_small.jpg", "title": "Departamento - Venta - Argentina, Capital Federal - AV JUJUY 1000"}, "https://www.argenprop.com/departamento-en-venta-en-balvanera-2-ambientes--7941273": {"id": "11533856", "date": "07-09-2024\n", "index": 5, "content": "1\n/7\n0\nUSD 100.000 + $3.200 expensas\nRIVADAVIA 3300\nDepartamento en Venta en Balvanera, Capital Federal\n45 m\u00b2 cubie.\n1 dorm.\n40 a\u00f1os\nDepartamento de 2 ambientes en Venta en Balvanera\nExcelente departamento en venta ubicado en el piso 9 con muy buena luminosidad y ventilaci\u00f3n. Amplias ventanas, c\u00f3moda distribuci\u00f3n. Edificio bien conservado. Balcon de aproximadamente 9 mts2. Vista de primer nivel. Muy bien conectado cerca de los principales medios de transporte publicos. No dude en consultar! Oportunidad se deja constancia que las caracteristicas, medidas, expensas y\nWhatsApp\nContactar", "revised": false, "rejected": false, "data": {"precio": "USD 100.000 + $3.200 expensas", "expensas": "+ $3.200 expensas", "direccion": "RIVADAVIA 3300", "metros": "45 m\u00b2 cubie.", "habitaciones": "1 dorm."}, "image": "https://static1.sosiva451.com/3721497/05eda7e9-0e7d-4f15-a8a5-671a70a3522c_u_small.jpg", "title": "Departamento de 2 ambientes en Venta en Balvanera "}, "https://www.argenprop.com/departamento-en-venta-en-balvanera-2-ambientes--15658767": {"id": "19075566", "date": "07-09-2024\n", "index": 6, "content": "1\n/15\n0\nUSD 105.000 + $40.000 expensas\nHIPOLITO YRIGOYEN 2400\nDepartamento en Venta en Balvanera, Capital Federal\n42 m\u00b2 cubie.\n1 dorm.\nA Estrenar\nDepartamento de 2 ambientes en Venta en Balvanera\nUn nuevo concepto en viviendas.... Unidades duplex tipo lofts en pleno coraz\u00f2n de buenos aires. Un resurgimiento elegante de dos ambientes. Excelente como inversi\u00f3n para alquiler, airbnb, turismo desde 42 m2 hasta 120 m2. Con balc\u00f3n. Precios entre 102mil d\u00f3lares, hasta 399.700usd. Complejo residencial con diversidad de amenities, como piscina, coworking, loundry bar, solarium, gimnasio, snack\nWhatsApp\nContactar", "revised": false, "rejected": false, "data": {"precio": "USD 105.000 + $40.000 expensas", "expensas": "+ $40.000 expensas", "direccion": "HIPOLITO YRIGOYEN 2400", "metros": "42 m\u00b2 cubie.", "habitaciones": "1 dorm."}, "image": "https://static1.sosiva451.com/76785651/58b11e61-76c6-43ac-bbd3-4b4375bac4cc_u_small.jpg", "title": "Departamento de 2 ambientes en Venta en Balvanera "}, "https://www.argenprop.com/departamento-en-venta-en-balvanera-2-ambientes--11642021": {"id": "15134193", "date": "07-09-2024\n", "index": 8, "content": "1\n/18\n0\nUSD 69.000 + $12.500 expensas\nCORRIENTES 1800\nDepartamento en Venta en Balvanera, Capital Federal\n44 m\u00b2 cubie.\n1 dorm.\n35 a\u00f1os\nDepartamento de 2 ambientes en Venta en Balvanera\n2 amb contrafrente convertido en tres amb con un gran balcon ideal inversores para alquiler temporario el edificio muy bien conservado se encuentra en pleno centro de corrientes y callao, con todas las atracciones de la av. Que nunca duerme, con teatros , cines , shoppings, comercios de todo rubro y un excelente corredor gastronomico de las variedades que uno busque, haciendose\nWhatsApp\nContactar", "revised": false, "rejected": false, "data": {"precio": "USD 69.000 + $12.500 expensas", "expensas": "+ $12.500 expensas", "direccion": "CORRIENTES 1800", "metros": "44 m\u00b2 cubie.", "habitaciones": "1 dorm."}, "image": "https://static1.sosiva451.com/12024611/272f6e5c-ab52-4e1d-b932-da0197cadebf_u_small.jpg", "title": "Departamento de 2 ambientes en Venta en Balvanera "}, "https://www.argenprop.com/departamento-en-venta-en-balvanera-2-ambientes--16173344": {"id": "19571049", "date": "07-09-2024\n", "index": 9, "content": "1\n/58\n0\nUSD 110.000\nAlberti 300\nDepartamento en Venta en Balvanera, Capital Federal\n44 m\u00b2 cubie.\n1 dorm.\n17 a\u00f1os\nVENTA DEPTO BALVANERA 2 AMBIENTES A ESTRENAR\n\u00a1Exclusiva oportunidad! Venta de departamento a estrenar de 2 ambientes en balvanera con sum y pileta descripci\u00f3n: te presentamos este moderno departamento de 2 ambientes a estrenar, ubicado en el din\u00e1mico barrio de balvanera. Con una combinaci\u00f3n perfecta de dise\u00f1o contempor\u00e1neo y comodidades de primer nivel, este departamento es ideal para quienes buscan un hogar sofisticado en una ubicaci\u00f3n\nWhatsApp\nContactar", "revised": false, "rejected": false, "data": {"precio": "USD 110.000", "direccion": "Alberti 300", "metros": "44 m\u00b2 cubie.", "habitaciones": "1 dorm."}, "image": null, "title": "VENTA DEPTO BALVANERA 2 AMBIENTES A ESTRENAR"}, "https://www.argenprop.com/departamento-en-venta-en-balvanera-2-ambientes--16144581": {"id": "19551487", "date": "07-09-2024\n", "index": 12, "content": "1\n/21\n1\nUSD 52.000 + $70.000 expensas\nSarmiento al 2000\nDepartamento en Venta en Balvanera, Capital Federal\n57 m\u00b2 cubie.\n1 dorm.\n95 a\u00f1os\nVenta departamento de 2 ambientes en Balvanera\nUnidad interna conformada por living comedor, cocina a reciclar, un dormitorio y ba\u00f1o completo a reciclar. Excelente ubicaci\u00f3n en el centro porte\u00f1o. El edificio no cuenta con acceso por rampa para personas con movilidad reducida. Karina curotto cucicba matricula - 671- to1 - fo26 las superficies indicadas\nWhatsApp\nContactar", "revised": false, "rejected": false, "data": {"precio": "USD 52.000 + $70.000 expensas", "expensas": "+ $70.000 expensas", "direccion": "Sarmiento al 2000", "metros": "57 m\u00b2 cubie.", "habitaciones": "1 dorm."}, "image": "https://static1.sosiva451.com/18544161/220c0cf2-5342-4fe6-b7af-32bb7a77b308_u_small.jpg", "title": "Venta departamento de 2 ambientes en Balvanera"}, "https://www.argenprop.com/departamento-en-venta-en-balvanera-2-ambientes--16124151": {"id": "19531078", "date": "07-09-2024\n", "index": 14, "content": "1\n/12\n0\nUSD 57.000 + $72.000 expensas\nAvenida Hip\u00f3lito Yrigoyen 2900\nDepartamento en Venta en Balvanera, Capital Federal\n52 m\u00b2 cubie.\n1 dorm.\n54 a\u00f1os\nVenta depto 2 ambientes al frente APTO CREDITO\nHermoso dpto de 2 amb al frente, todo luz, en edificio de solida construccion, hecho por el conocido arquitecto virasoro. Ubicado a solo una cuadra y media av pueyrredon, una de av rivadavia y una de subte linea a (plaza miserere). Es por ascensor. Se ingresa a un amplio living con pisos de pinotea, cocina separada con lavadero, ba\u00f1o completo y dormitorio amplias dimensiones, tambien con pisos\nContactar", "revised": false, "rejected": false, "data": {"precio": "USD 57.000 + $72.000 expensas", "expensas": "+ $72.000 expensas", "direccion": "Avenida Hip\u00f3lito Yrigoyen 2900", "metros": "52 m\u00b2 cubie.", "habitaciones": "1 dorm."}, "image": "https://static1.sosiva451.com/15142161/820479a3-22f4-4fb2-b60f-4fe704975b4d_u_small.jpg", "title": "Venta depto 2 ambientes al frente APTO CREDITO"}, "https://www.argenprop.com/departamento-en-venta-en-balvanera-2-ambientes--15655553": {"id": "19072350", "date": "07-09-2024\n", "index": 15, "content": "1\n/20\n7.110\nUSD 105.000\nAlberti 300\nDepartamento en Venta en Balvanera, Capital Federal\n46 m\u00b2 cubie.\n1 dorm.\nA Estrenar\nDepartamento 2 Ambientes a Estrenar posesi\u00f3n ya - Amenities.\nDavo propiedades: alberti al 300. Excelente departamento de 2 ambientes al frente con balc\u00f3n corrido, con posesi\u00f3n inmediata. Dispone de: amplio living - comedor, cocina equipada, muebles altos bajo mesada con conexi\u00f3n de lavarropas. Dormitorio con placard e interiores terminados. Dos equipos de aire acondicionado frio calor instalado. Ba\u00f1o completo. El edificio: excelentes detalles de buen gusto\nWhatsApp\nContactar", "revised": false, "rejected": false, "data": {"precio": "USD 105.000", "direccion": "Alberti 300", "metros": "46 m\u00b2 cubie.", "habitaciones": "1 dorm."}, "image": "https://static1.sosiva451.com/35555651/90d72b87-de94-4c13-a9a9-e7da735edd22_u_small.jpg", "title": "Departamento 2 Ambientes a Estrenar posesi\u00f3n ya - Amenities."}, "https://www.argenprop.com/departamento-en-venta-en-balvanera-2-ambientes--15238140": {"id": "18672941", "date": "07-09-2024\n", "index": 16, "content": "1\n/14\n15\nUSD 105.000\nAlberti 300\nDepartamento en Venta en Balvanera, Capital Federal\n46 m\u00b2 cubie.\n1 dorm.\n1 ba\u00f1o\nDepartamento 2 Ambientes en el Edificio A 360\nDavo propiedades presenta alberti al 300. Departamentos 1, 2, 3 y 4 ambientes. Apto profesional. Departamento: 2 ambientes con balcon al frente. Obra terminada el departamento dispone de: amplio living - comedor, cocina equipada con muebles altos y bajo mesada, anafe , horno y conexi\u00f3n para lavarropas. Dormitorio con placard e interiores terminados. Ba\u00f1o completo. Dos equipos de aire\nContactar", "revised": false, "rejected": false, "data": {"precio": "USD 105.000", "direccion": "Alberti 300", "metros": "46 m\u00b2 cubie.", "habitaciones": "1 dorm."}, "image": "https://static1.sosiva451.com/04183251/8756b586-1d49-4e80-990e-662f050d76a3_u_small.jpg", "title": "Departamento 2 Ambientes en el Edificio A 360"}, "https://www.argenprop.com/departamento-en-venta-en-balvanera-2-ambientes--16049455": {"id": "19456558", "date": "07-09-2024\n", "index": 19, "content": "1\n/13\n0\nUSD 63.000 + $94.000 expensas\nRivadavia al 2200\nDepartamento en Venta en Balvanera, Capital Federal\n40 m\u00b2 cubie.\n1 dorm.\n51 a\u00f1os\nVenta Departamento 2 ambientes en Duplex con Baulera en Balvanera\nUnico duplex 2 ambientes en la zona! Ideal inversion! Muy luminoso, con excelente distribuci\u00f3n y ambientes espaciosos. Ubicado en una zona comercial y c\u00e9ntrica estrat\u00e9gica, con el subte en la puerta y numerosos medios de transporte, cerca de las principales avenidas. +Info pb -living c\u00f3modo con gran ventanal, pisos de parquet y persianas. -Cocina independiente, con horno a gas, termotanque a gas,\nContactar", "revised": false, "rejected": false, "data": {"precio": "USD 63.000 + $94.000 expensas", "expensas": "+ $94.000 expensas", "direccion": "Rivadavia al 2200", "metros": "40 m\u00b2 cubie.", "habitaciones": "1 dorm."}, "image": "https://static1.sosiva451.com/55494061/2d5620c1-70bf-46c6-9c56-f4e63b2f0797_u_small.jpg", "title": "Venta Departamento 2 ambientes en Duplex con Baulera en Balvanera"}, "https://www.argenprop.com/departamento-en-venta-en-balvanera-2-ambientes--15564690": {"id": "18981611", "date": "07-09-2024\n", "index": 20, "content": "1\n/51\n0\nUSD 68.000 + $89.000 expensas\nRinc\u00f3n 157\nDepartamento en Venta en Balvanera, Capital Federal\n46 m\u00b2 cubie.\n1 dorm.\n20 a\u00f1os\n2AMB \u00b7 46M\u00b2 \u00b7 2 patios! td a nuevo! ba\u00f1o y cocina reciclados! impecable unidad!\n2 ambientes c/2 patios ! Todo a nuevo, ideal primera vivienda o inversi\u00f3n ! #Venta | #departamento | #balvanera | #2amb | #contrafrente | #patios rinc\u00f3n 100, piso 1 - ciudad aut\u00f3noma de buenos aires caracter\u00edsticas: ~ departamento de dos (2) ambientes dispuesto hacia el contrafrente, con dos (2) patios, ubicado c\u00e9ntricamente en la ciudad aut\u00f3noma de buenos aires. ~ Orientaci\u00f3n hacia el no\nWhatsApp\nContactar", "revised": false, "rejected": false, "data": {"precio": "USD 68.000 + $89.000 expensas", "expensas": "+ $89.000 expensas", "direccion": "Rinc\u00f3n 157", "metros": "46 m\u00b2 cubie.", "habitaciones": "1 dorm."}, "image": "https://static1.sosiva451.com/09646551/6fc8fb76-079d-42c7-894f-4e650790d1b4_u_small.jpg", "title": "2AMB \u00b7 46M\u00b2 \u00b7 2 patios! td a nuevo! ba\u00f1o y cocina reciclados! impecable unidad!"}, "https://www.argenprop.com/departamento-en-venta-en-constitucion-2-ambientes--16159823": {"id": "19566549", "date": "07-09-2024\n", "index": 22, "content": "1\n/38\n0\nUSD 49.000\nSANTIAGO DEL ESTERO 1200\nDepartamento en Venta en Constitucion, Capital Federal\n43 m\u00b2 cubie.\n1 dorm.\n40 a\u00f1os\nDepartamento en Venta en Constituci\u00f3n, Capital Federal, Buenos Aires\nVenta. Departamento de dos ambientes apto credito. Luminoso departamento de dos ambientes lateral, ingreso principal a recibidor, cocina separada con espacio para lavadero, un dormitorio con amplio placard, cuenta con ba\u00f1o completo. La propiedad se encuentra bien ubicada con una excelente conectividad a m\u00faltiples medios de transporte y arterias principales y a cuadras de la universidad de\nWhatsApp\nContactar", "revised": false, "rejected": false, "data": {"precio": "USD 49.000", "direccion": "SANTIAGO DEL ESTERO 1200", "metros": "43 m\u00b2 cubie.", "habitaciones": "1 dorm."}, "image": "https://static1.sosiva451.com/32895161/42347d34-ce0a-4dc5-a527-b51d616213ee_u_small.jpg", "title": "Departamento  en Venta en Constituci\u00f3n, Capital Federal, Buenos Aires"}, "https://www.argenprop.com/departamento-en-venta-en-balvanera-2-ambientes--16110092": {"id": "19517053", "date": "07-09-2024\n", "index": 23, "content": "1\n/17\n1\nUSD 72.000 + $62.000 expensas\nTUCUM\u00c1N entre JUNIN y URIBURU\nDepartamento en Venta en Balvanera, Capital Federal\n40 m\u00b2 cubie.\n1 dorm.\n40 a\u00f1os\nVenta Depto 2 ambientes - Coc c/lav m/lum - Fac Medicina\nEn venta | impecable dpto. 2 amb | zona de facultades living/comedor y dormitorio con pisos de madera parquet en optimo estado cocina separada. Conexi\u00f3n para lavarropas dormitorio con amplio placard. Otro placard en el hall distribuci\u00f3n. Excelente estado apto cr\u00e9dito a 1 cdra. De la facultad de cs. Econ\u00f3micas y medicina.\nWhatsApp\nContactar", "revised": false, "rejected": false, "data": {"precio": "USD 72.000 + $62.000 expensas", "expensas": "+ $62.000 expensas", "direccion": "TUCUM\u00c1N entre JUNIN y URIBURU", "metros": "40 m\u00b2 cubie.", "habitaciones": "1 dorm."}, "image": "https://static1.sosiva451.com/29001161/79c08f9f-c1e2-4a6a-95bb-7f3cba037758_u_small.jpg", "title": "Venta Depto 2 ambientes - Coc c/lav  m/lum - Fac Medicina"}, "https://www.argenprop.com/departamento-en-venta-en-constitucion-2-ambientes--15970506": {"id": "19386834", "date": "07-09-2024\n", "index": 24, "content": "1\n/10\n0\nUSD 38.000 + $20.000 expensas\nSantiago del Estero 1400\nDepartamento en Venta en Constitucion, Capital Federal\n47 m\u00b2 cubie.\n1 dorm.\n74 a\u00f1os\nVENTA DEPARTAMENTO CONSTITUCION 2 AMBIENTES\nVenta departamento constitucion 2 ambientes venta departamento constitucion 2 ambientes el departamento esta ubicado en la zona de constituci\u00f3n, a 2 cuadras de plaza constituci\u00f3n y muy f\u00e1cil acceso a microcentro. Ingresando al edificio en la planta baja accedemos al departamento el cual cuenta con un living comedor con salida al patio descubierto, y acceso a la habitaci\u00f3n. Por la misma\nContactar", "revised": false, "rejected": false, "data": {"precio": "USD 38.000 + $20.000 expensas", "expensas": "+ $20.000 expensas", "direccion": "Santiago del Estero 1400", "metros": "47 m\u00b2 cubie.", "habitaciones": "1 dorm."}, "image": "https://static1.sosiva451.com/60507951/c32c3bb4-bcdf-4316-b7f6-e6b469d63f74_u_small.jpg", "title": "VENTA DEPARTAMENTO CONSTITUCION 2 AMBIENTES"}, "https://www.argenprop.com/departamento-en-venta-en-balvanera-2-ambientes--16158804": {"id": "19565543", "date": "07-09-2024\n", "index": 25, "content": "1\n/16\n0\nUSD 65.000 + $49.000 expensas\nCalle Rincon 100\nDepartamento en Venta en Balvanera, Capital Federal\n40 m\u00b2 cubie.\n1 dorm.\n58 a\u00f1os\nDepartamento - Venta - Argentina, Capital Federal - Calle Rincon 100\nVenta de departamento 2 ambientes en balvanera, capital federal la unidad se encuentra en un 4to piso con vista lateral. Tiene un ba\u00f1o completo, 1 dormitorio, 1 living/comedor y una cocina separada con lavadero. La ubicaci\u00f3n es muy funcional por que se encuentra a 30 mts de av. Rivadavia, a 300 mts de av. Entre rios, a 700 mts de av jujuy, a 200 mts\nWhatsApp\nContactar", "revised": false, "rejected": false, "data": {"precio": "USD 65.000 + $49.000 expensas", "expensas": "+ $49.000 expensas", "direccion": "Calle Rincon 100", "metros": "40 m\u00b2 cubie.", "habitaciones": "1 dorm."}, "image": "https://static1.sosiva451.com/40885161/f456a5d5-deaa-41ed-a630-1daa4c4cb2d2_u_small.jpg", "title": "Departamento - Venta - Argentina, Capital Federal - Calle Rincon 100"}, "https://www.argenprop.com/departamento-en-venta-en-balvanera-2-ambientes--16157147": {"id": "19563883", "date": "07-09-2024\n", "index": 30, "content": "1\n/16\n0\nUSD 114.000 + $33.000 expensas\nAv. Rivadavia 3200\nDepartamento en Venta en Balvanera, Capital Federal\n48 m\u00b2 cubie.\n1 dorm.\nA Estrenar\nVENTA 2 AMBIENTES/BALCON ATERRAZADO/A ESTRENAR\n\u00a1Tu nuevo hogar te espera en aralis rivadavia! - 2 ambientes al frente a estrenar - 1 ba\u00f1o - 1 toilette - cocina integrada - balc\u00f3n aterrazado de 5 m2 - living comedor de m ubicaci\u00f3n estrat\u00e9gica: descubre el encanto de vivir en av. Rivadavia 3269, en el l\u00edmite entre almagro y balvanera. Este emprendimiento de 15 pisos ofrece departamentos de 1, 2, 3 y 4 ambientes, brindando una\nContactar", "revised": false, "rejected": false, "data": {"precio": "USD 114.000 + $33.000 expensas", "expensas": "+ $33.000 expensas", "direccion": "Av. Rivadavia 3200", "metros": "48 m\u00b2 cubie.", "habitaciones": "1 dorm."}, "image": "https://static1.sosiva451.com/74175161/55ace501-eb55-41e5-a204-f6ad80df3625_u_small.jpg", "title": "VENTA 2 AMBIENTES/BALCON ATERRAZADO/A ESTRENAR"}, "https://www.argenprop.com/departamento-en-venta-en-balvanera-2-ambientes--16145984": {"id": "19552774", "date": "07-09-2024\n", "index": 31, "content": "1\n/10\n500\nUSD 62.000 + $50.000 expensas\nEcuador 800, Piso 1\nDepartamento en Venta en Balvanera, Capital Federal\n41 m\u00b2 cubie.\n1 dorm.\n50 a\u00f1os\nDepto 2 amb. Ecuador al 800\nPh 2 amb., 41 m2, contrafrente, 1er. Piso por escalera cocina separada ba\u00f1o completo ba\u00f1o y cocina en estado original de su \u00e9poca buen estado general aire acondicionado en ambos ambientes expensas razonables muchos supermercados y comercio barrial en general plaza monse\u00f1or d\u00b4\u00e1ndrea a 2 cuadras, con juegos infantiles, canil y postas aer\u00f3bicas pocas cuadras del recoleta mal, paseo del pilar, y\nWhatsApp\nContactar", "revised": false, "rejected": false, "data": {"precio": "USD 62.000 + $50.000 expensas", "expensas": "+ $50.000 expensas", "direccion": "Ecuador 800, Piso 1", "metros": "41 m\u00b2 cubie.", "habitaciones": "1 dorm."}, "image": "https://static1.sosiva451.com/48954161/93d70f69-0a52-442a-8b2a-fd4b4c9ef57a_u_small.jpg", "title": "Depto 2 amb. Ecuador al 800"}, "https://www.argenprop.com/departamento-en-venta-en-constitucion-2-ambientes--16082193": {"id": "19489210", "date": "07-09-2024\n", "index": 32, "content": "1\n/11\n16\nUSD 78.000 + $45.000 expensas\nTacuari 1400, Piso 2\nDepartamento en Venta en Constitucion, Capital Federal\n47 m\u00b2 cubie.\n1 dorm.\n70 a\u00f1os\n2 amb con terraza ppia.\n2 ambientes amplios con terraza. Cocina independiente + lavadero. Pisos parquet. Por escalera. Zona en crecimiento hacia san telmo. Cerca de puerto madero, subte y estacion constitucion. Acceso rapido a autopista.\nWhatsApp\nContactar", "revised": false, "rejected": false, "data": {"precio": "USD 78.000 + $45.000 expensas", "expensas": "+ $45.000 expensas", "direccion": "Tacuari 1400, Piso 2", "metros": "47 m\u00b2 cubie.", "habitaciones": "1 dorm."}, "image": null, "title": "2 amb con terraza ppia."}, "https://www.argenprop.com/departamento-en-venta-en-balvanera-2-ambientes--16156651": {"id": "19563393", "date": "07-09-2024\n", "index": 33, "content": "1\n/12\n0\nUSD 65.000 + $30.000 expensas\nTeniente General Juan Domingo Per\u00f3n 1800\nDepartamento en Venta en Balvanera, Capital Federal\n45 m\u00b2 cubie.\n1 dorm.\n50 a\u00f1os\nDepartamento 2 Ambientes - Balvanera\nDepartamento 2 ambientes en balvanera, excelente ubicaci\u00f3n. Media cuadra av. Callao. Muy conectado con microcentro. Living comedor amplio y luminoso, cocina independiente. Dormitorio con amplio placard. Ba\u00f1o con ba\u00f1era. Apto credito la unidad funcional es accesible para personas con discapacidades f\u00edsicas. Las medidas son estimativas, otorgadas por el propietario y solo a efecto orientativo.\nWhatsApp\nContactar", "revised": false, "rejected": false, "data": {"precio": "USD 65.000 + $30.000 expensas", "expensas": "+ $30.000 expensas", "direccion": "Teniente General Juan Domingo Per\u00f3n 1800", "metros": "45 m\u00b2 cubie.", "habitaciones": "1 dorm."}, "image": "https://static1.sosiva451.com/15665161/1566af49-1019-407d-b5cc-2f59e09389b0_u_small.jpg", "title": "Departamento 2 Ambientes - Balvanera"}, "https://www.argenprop.com/departamento-en-venta-en-balvanera-2-ambientes--16156508": {"id": "19563252", "date": "07-09-2024\n", "index": 34, "content": "1\n/30\n0\nUSD 64.000 + $85.000 expensas\nSan Luis al 2400\nDepartamento en Venta en Balvanera, Capital Federal\n41 m\u00b2 cubie.\n1 dorm.\n50 a\u00f1os\nSan Luis al 2400 - 2 amb - FACULTAD - Venta\nSan luis al 2400 - 2 amb - facultad - venta contrafrente luminoso a metros de av. C\u00f3rdoba cercano a subte \"d\" facultad de medicina pisos de parquet cocina y ba\u00f1o modernizados hall living con aire acondicionado cocina con barra desayunador espacio para lavarropas calef\u00f3n a gas alacena y bajo mesada placard en pasillo dormitorio con amplio placard incorporado ba\u00f1o completo con ba\u00f1era\nContactar", "revised": false, "rejected": false, "data": {"precio": "USD 64.000 + $85.000 expensas", "expensas": "+ $85.000 expensas", "direccion": "San Luis al 2400", "metros": "41 m\u00b2 cubie.", "habitaciones": "1 dorm."}, "image": "https://static1.sosiva451.com/80565161/a149f397-822c-44a1-b8e9-b78867e11919_u_small.jpg", "title": "San Luis al 2400 - 2 amb - FACULTAD - Venta"}}