{"https://www.argenprop.com/ph-en-alquiler-en-parque-chacabuco-2-ambientes--9022663": {"id": "12535899", "date": "08-05-2024\n", "index": 5, "content": "1\n/7\n0\n$ 280.000 + $10.000 expensas\nJose Maria Moreno 1300\nPH en Alquiler en Parque Chacabuco, Capital Federal\n40 m\u00b2 cubie.\n1 dorm.\n1 ba\u00f1o\nAlquiler 2 ambientes 1er piso por escalera Jose Maria Moreno\nAlquiler 2 ambiente 1er piso por escalera, living, cocina, ba\u00f1o , patio requisitos garant\u00eda propietaria o seguro de cauci\u00f3n\nWhatsApp\nContactar", "revised": false, "rejected": true, "data": {"precio": "$ 280.000 + $10.000 expensas", "expensas": "+ $10.000 expensas", "direccion": "Jose Maria Moreno 1300", "metros": "40 m\u00b2 cubie.", "habitaciones": "1 dorm."}, "image": "https://static1.sosiva451.com/3662209/355f1908-2719-4643-824d-205f4b998702_u_small.jpg", "title": "Alquiler 2 ambientes 1er piso por escalera Jose Maria Moreno"}, "https://www.argenprop.com/departamento-en-alquiler-en-boedo-2-ambientes--15659365": {"id": "19076163", "date": "08-05-2024\n", "index": 7, "content": "1\n/9\n6\n$ 270.000 + $44.000 expensas\nCochabamba 4300, Piso 1\nDepartamento en Alquiler en Boedo, Capital Federal\n39 m\u00b2 cubie.\n1 dorm.\n12 a\u00f1os\nALQUILER 2 AMBIENTES AL FRENTE EN BOEDO\nExcelente 2 ambientes con cocina integrada al frente con balc\u00f3n corrido, a metros de caballito, situado a 1 cuadra de las intersecciones de av. La plata y av. Directorio en la zona podemos encontrar, muchos medios de transporte, destac\u00e1ndose entre ellos, el subte \"e\" que posibilita a su vez combinar con todas las l\u00ednea restantes. Adem\u00e1s en las inmediaciones, hay gran variedad de\nWhatsApp\nContactar", "revised": true, "rejected": false, "data": {"precio": "$ 270.000 + $44.000 expensas", "expensas": "+ $44.000 expensas", "direccion": "Cochabamba 4300, Piso 1", "metros": "39 m\u00b2 cubie.", "habitaciones": "1 dorm."}, "image": "https://static1.sosiva451.com/56395651/2426c828-2613-4e9f-8ebd-d5adab90f003_u_small.jpg", "title": "ALQUILER  2 AMBIENTES AL FRENTE EN BOEDO"}, "https://www.argenprop.com/departamento-en-alquiler-en-villa-urquiza-2-ambientes--15659069": {"id": "19075867", "date": "08-05-2024\n", "index": 13, "content": "1\n/17\n11\n$ 450 + $56.000 expensas\nTomas Le Breton 5000\nDepartamento en Alquiler en Villa Urquiza, Capital Federal\n50 m\u00b2 cubie.\n1 dorm.\n9 a\u00f1os\nTomas Lebreton al 5000 alquiler temporario\nDepartamento de dos ambientes con balcon corrido muy luminoso ubicado sobre la calle le breton al 5000 y diaz colodredo, proximo a la av. Triunvirato y av. Monroe, estacion de subte linea b proxima. Rodeado de servicios en general, zona con mucha actividad comercial. El edificio cuenta con piscina, parque y baulera. Comodidades. Balcon corrido hacia el frente con vista abierta, living comedor con\nContactar", "revised": false, "rejected": true, "data": {"precio": "$ 450 + $56.000 expensas", "expensas": "+ $56.000 expensas", "direccion": "Tomas Le Breton 5000", "metros": "50 m\u00b2 cubie.", "habitaciones": "1 dorm."}, "image": null, "title": "Tomas  Lebreton  al  5000 alquiler temporario "}, "https://www.argenprop.com/departamento-en-alquiler-en-san-cristobal-2-ambientes--15626443": {"id": "19043402", "date": "08-05-2024\n", "index": 18, "content": "1\n/8\n175\n$ 260.000 + $36.500 expensas\nSaavedra 1100\nDepartamento en Alquiler en San Cristobal, Capital Federal\n30 m\u00b2 cubie.\n1 dorm.\n1 ba\u00f1o\nDpto 2 ambientes Placard Conexi\u00f3n p/lavarropas ba\u00f1o completo\nSobre calle saavedra al 1100, entre av. San juan y humberto i\u00ba. Pr\u00f3ximo a subtes e y h. Pr\u00f3ximo a subidas y bajadas de la au1 25 de mayo. Varias l\u00edneas de colectivos. Dpto de 2 ambientes de unos 30m2. Interno, luminoso, conexi\u00f3n para lavarropas en la cocina, pisos de parquet en el dormitorio (con placard). Ba\u00f1o completo. Garant\u00edas aceptadas: fi naer, garan t\u00eda ya, pre mium o propietaria de\nContactar", "revised": true, "rejected": false, "data": {"precio": "$ 260.000 + $36.500 expensas", "expensas": "+ $36.500 expensas", "direccion": "Saavedra 1100", "metros": "30 m\u00b2 cubie.", "habitaciones": "1 dorm."}, "image": "https://static1.sosiva451.com/34462651/a19c376f-2aa9-4ace-96b0-0e0e4e894763_u_small.jpg", "title": "Dpto 2 ambientes Placard Conexi\u00f3n p/lavarropas ba\u00f1o completo"}, "https://www.argenprop.com/departamento-en-alquiler-en-san-cristobal-2-ambientes--15658606": {"id": "19075404", "date": "08-05-2024\n", "index": 21, "content": "1\n/3\n0\n$ 300.000 + $50.000 expensas\nAVENIDA JUJUY al 900\nDepartamento en Alquiler en San Cristobal, Capital Federal\n37 m\u00b2 cubie.\n1 dorm.\n10 a\u00f1os\nDepartamento en SAN CRISTOBAL\nWhatsApp\nContactar", "revised": false, "rejected": true, "data": {"precio": "$ 300.000 + $50.000 expensas", "expensas": "+ $50.000 expensas", "direccion": "AVENIDA JUJUY al 900", "metros": "37 m\u00b2 cubie.", "habitaciones": "1 dorm."}, "image": "https://static1.sosiva451.com/60685651/6c0ccd2c-3520-4106-8d6d-4532eaad5ce2_u_small.jpg", "title": "Departamento en SAN CRISTOBAL"}, "https://www.argenprop.com/departamento-en-alquiler-en-san-cristobal-2-ambientes--15653453": {"id": "19070252", "date": "08-05-2024\n", "index": 27, "content": "1\n/12\n0\n$ 250.000 + $40.000 expensas\nLa Rioja al 1100\nDepartamento en Alquiler en San Cristobal, Capital Federal\n31 m\u00b2 cubie.\n1 dorm.\n35 a\u00f1os\nDepartamento en Alquiler\nSe trata de un departamento de 2 ambientes al frente, living, cocina comedor con muebles completos, dormitorio con placard. Ba\u00f1o completo, agua caliente central. La propiedad se encuentra en excelente estado, a metros de av. San juan y subte e. No se aceptan mascotas. Ll 106 condiciones y requisitos - 1 mes por adelantado + 1 mes deposito (igual al valor del primer mes) -\nWhatsApp\nContactar", "revised": false, "rejected": true, "data": {"precio": "$ 250.000 + $40.000 expensas", "expensas": "+ $40.000 expensas", "direccion": "La Rioja al 1100", "metros": "31 m\u00b2 cubie.", "habitaciones": "1 dorm."}, "image": "https://static1.sosiva451.com/35435651/7d59271e-bb8c-4621-9811-d127f6de31c1_u_small.jpg", "title": "Departamento en  Alquiler"}, "https://www.argenprop.com/departamento-en-alquiler-en-parque-chacabuco-2-ambientes--15472090": {"id": "18897968", "date": "08-05-2024\n", "index": 29, "content": "1\n/7\n175\n$ 300.000 + $34.000 expensas\nPuan 600, Piso 6\nDepartamento en Alquiler en Parque Chacabuco, Capital Federal\n30 m\u00b2 cubie.\n1 dorm.\n2 ambientes\nDos amb luminoso balcon a la calle\nContrato a dos a\u00f1os ajuste trimestral ipc\nWhatsApp\nContactar", "revised": true, "rejected": false, "data": {"precio": "$ 300.000 + $34.000 expensas", "expensas": "+ $34.000 expensas", "direccion": "Puan 600, Piso 6", "metros": "30 m\u00b2 cubie.", "habitaciones": "1 dorm."}, "image": "https://static1.sosiva451.com/09027451/239d1a34-c94a-4992-ad1c-0e64fab36a82_u_small.jpg", "title": "Dos amb luminoso balcon a la calle"}, "https://www.argenprop.com/departamento-en-alquiler-en-san-cristobal-2-ambientes--15649976": {"id": "19066776", "date": "08-05-2024\n", "index": 32, "content": "1\n/19\n0\n$ 265.000 + $16.000 expensas\nEstados Unidos 2200\nDepartamento en Alquiler en San Cristobal, Capital Federal\n36 m\u00b2 cubie.\n1 dorm.\n18 a\u00f1os\nALQUILER DEPARTAMENTO 2 AMBIENTES SAN CRIST\u00d3BAL\nAlquiler departamento 2 ambientes san crist\u00f3bal alquiler departamento de 2 ambientes con baulera en san crist\u00f3bal. Departamento 2 ambientes en alquiler! Se encuentra en el 3er piso por escalera. Sobre estados unidos al 2200 caracteristicas cocina equipada y amoblada living/comedor con aire acondicionado y calefactor habitaci\u00f3n con placar ba\u00f1o completo con ba\u00f1era. Baulera se ingresa al\nContactar", "revised": false, "rejected": true, "data": {"precio": "$ 265.000 + $16.000 expensas", "expensas": "+ $16.000 expensas", "direccion": "Estados Unidos 2200", "metros": "36 m\u00b2 cubie.", "habitaciones": "1 dorm."}, "image": "https://static1.sosiva451.com/67994651/ff2d5d52-996c-4ffb-9039-df172939dd25_u_small.jpg", "title": "ALQUILER DEPARTAMENTO 2 AMBIENTES SAN CRIST\u00d3BAL"}, "https://www.argenprop.com/departamento-en-alquiler-en-parque-chacabuco-2-ambientes--15651583": {"id": "19068383", "date": "08-05-2024\n", "index": 34, "content": "1\n/16\n0\n$ 280.000 + $20.000 expensas\nCentenera 700\nDepartamento en Alquiler en Parque Chacabuco, Capital Federal\n37 m\u00b2 cubie.\n1 dorm.\n65 a\u00f1os\n2 amb. Fte. Blc\u00f3n. 1er.piso p/Esc. Bajas expensas. Reciclado\nAlquiler de departamento 2 ambientes en parque chacabuco, capital federal.  2 ambientes. Primer piso por escalera al frente con balc\u00f3n. Cocina con horno el\u00e9ctrico. Amplio dormitorio y ba\u00f1o completo con ducha. El dpto.se encuentra reciclado a  nuevo. Pisos alfombrados. Buena luminosidad. Situado a mts.de av. Directorio, cercano a l\u00edneas de subte \"e y a\". Alemany propiedades c.U.C.I..B.A.\nWhatsApp\nContactar", "revised": false, "rejected": true, "data": {"precio": "$ 280.000 + $20.000 expensas", "expensas": "+ $20.000 expensas", "direccion": "Centenera 700", "metros": "37 m\u00b2 cubie.", "habitaciones": "1 dorm."}, "image": "https://static1.sosiva451.com/38515651/3a00ddcb-0f80-4de3-bfb6-98636c8966c8_u_small.jpg", "title": "2 amb. Fte. Blc\u00f3n. 1er.piso p/Esc. Bajas expensas. Reciclado"}, "https://www.argenprop.com/departamento-en-alquiler-en-san-cristobal-2-ambientes--8124043": {"id": "11698535", "date": "08-05-2024\n", "index": 39, "content": "1\n/12\n94\n$ 280.000 + $22.000 expensas\nLa Rioja 1600, Piso 5\nDepartamento en Alquiler en San Cristobal, Capital Federal\n36 m\u00b2 cubie.\n1 dorm.\n40 a\u00f1os\nDepartamento 2 ambientes Reciclado a metros del Metrobus\n\u00a1Descubre tu nuevo departamento en el vibrante barrio de san crist\u00f3bal! Este departamento de 2 ambientes, se ofrece en alquiler completamente reciclado, te brinda la oportunidad de disfrutar de la comodidad y la belleza en un solo lugar. Ubicado a pocos metros del metrob\u00fas y a unas cuadras del subte h, tendr\u00e1s un acceso inigualable a todas las atracciones que la ciudad tiene para ofrecer. Desde\nWhatsApp\nContactar", "revised": false, "rejected": true, "data": {"precio": "$ 280.000 + $22.000 expensas", "expensas": "+ $22.000 expensas", "direccion": "La Rioja 1600, Piso 5", "metros": "36 m\u00b2 cubie.", "habitaciones": "1 dorm."}, "image": "https://static1.sosiva451.com/3404218/8927491e-9d32-49b6-a6e7-aeb2180fec14_u_small.jpg", "title": "Departamento 2 ambientes Reciclado a metros del Metrobus"}, "https://www.argenprop.com/departamento-en-alquiler-en-villa-urquiza-2-ambientes--15531121": {"id": "18957038", "date": "08-05-2024\n", "index": 55, "content": "1\n/13\n0\n$ 650 + $40.000 expensas\nAvenida Congreso al 5000\nDepartamento en Alquiler en Villa Urquiza, Capital Federal\n55 m\u00b2 cubie.\n1 dorm.\n1 a\u00f1o\nDepartamento 2 Ambientes amoblado a estrenar.\nExcelente 2 ambientes en alquiler a estrenar en avenida congreso y diaz coldrero. 6to piso al frente con orientaci\u00f3n noroeste! Living comedor super amplio con cocina semi-integrada (conexi\u00f3n para lavarropa), salida a amplio balc\u00f3n. Ba\u00f1o completo con muy buen tama\u00f1o. Dormitorio al frente con vestidor y salida a balc\u00f3n con excelente vistas. Se encuentra totalmente ambolado\nWhatsApp\nContactar", "revised": false, "rejected": true, "data": {"precio": "$ 650 + $40.000 expensas", "expensas": "+ $40.000 expensas", "direccion": "Avenida Congreso al 5000", "metros": "55 m\u00b2 cubie.", "habitaciones": "1 dorm."}, "image": "https://static1.sosiva451.com/12113551/9af64ad1-5a06-43b6-b601-9b50c5f6ed43_u_small.jpg", "title": "Departamento 2 Ambientes amoblado a estrenar."}, "https://www.argenprop.com/departamento-en-alquiler-en-villa-urquiza-2-ambientes--15322823": {"id": "18757701", "date": "08-05-2024\n", "index": 61, "content": "1\n/11\n0\n$ 270.000 + $50.000 expensas\nROOSEVELT FRANKLIN D. 5000\nDepartamento en Alquiler en Villa Urquiza, Capital Federal\n45 m\u00b2 cubie.\n1 dorm.\n1 ba\u00f1o\nDEPARTAMENTO 2 AMBIENTES - VILLA URQUIZA, CAPITAL FEDERAL\nAtencion: esta oferta se encuentra reservada. Muy buen departamento dos ambientes a dos cuadras de estacion rosas subte b y estacion general urquiza del tren mitre. Pleno centro comercial de villa urquiza. Departamento lateral muy luminoso.Contrato a dos a\u00f1os ajuste semestral por ipc expensas $ 50.000.- Abl $ 3.300.- Superficie total uso propio uf: 45 m2 luminosidad: 6 categor\u00eda del edificio:\nContactar", "revised": true, "rejected": false, "data": {"precio": "$ 270.000 + $50.000 expensas", "expensas": "+ $50.000 expensas", "direccion": "ROOSEVELT FRANKLIN D. 5000", "metros": "45 m\u00b2 cubie.", "habitaciones": "1 dorm."}, "image": "https://static1.sosiva451.com/32822351/f2236701-868b-48a4-a6af-2cd23f0eaefa_u_small.jpg", "title": "DEPARTAMENTO 2 AMBIENTES - VILLA URQUIZA, CAPITAL FEDERAL"}}