{"https://www.argenprop.com/departamento-en-alquiler-en-san-nicolas-3-ambientes--15594907": {"date": "04-05-2024\n", "content": "1\n/13\n501\n$ 400.000 + $130.000 expensas\nTte. Gral. JUAN DOMINGO PERON al 1700\nDepartamento en Alquiler en San Nicol\u00e1s, Centro\n60 m\u00b2 cubie.\n2 dorm.\nA Estrenar\nTte. Gral. JUAN DOMINGO PERON 1700 Departamento en Alquiler 3 ambientes al frente\nDepartamento 3 ambientes al frente, en el piso 13 excelente vista abierta a ciudad. Se ingresa por un elegante hall que te lleva a los 3 ascensores. Apto profesional el edificio cuenta con encargado permanente y personal de seguridad nocturno. Al ingresar al departamento te encontras con un espacioso living comedor con un amplio ventanal que da\nWhatsApp\nContactar", "revised": false, "rejected": true, "data": {"price": "$ 400.000 + $130.000 expensas", "expenses": "+ $130.000 expensas", "address": "Tte. Gral. JUAN DOMINGO PERON al 1700", "meters": "60 m\u00b2 cubie.", "bedrooms": "2 dorm."}}, "https://www.argenprop.com/departamento-en-alquiler-en-san-nicolas-3-ambientes--15594901": {"date": "04-05-2024\n", "content": "1\n/13\n0\n$ 400.000 + $130.000 expensas\nTte. Gral. JUAN DOMINGO PERON al 1700\nDepartamento en Alquiler en San Nicol\u00e1s, Centro\n60 m\u00b2 cubie.\n2 dorm.\nA Estrenar\nTte. Gral. JUAN DOMINGO PERON 1700 Departamento en Alquiler 3 ambientes al frente\nDepartamento 3 ambientes al frente, en el piso 13 excelente vista abierta a ciudad. Se ingresa por un elegante hall que te lleva a los 3 ascensores. Apto profesional el edificio cuenta con encargado permanente y personal de seguridad nocturno. Al ingresar al departamento te encontras con un espacioso living comedor con un amplio ventanal que da\nWhatsApp\nContactar", "revised": false, "rejected": true, "data": {"price": "$ 400.000 + $130.000 expensas", "expenses": "+ $130.000 expensas", "address": "Tte. Gral. JUAN DOMINGO PERON al 1700", "meters": "60 m\u00b2 cubie.", "bedrooms": "2 dorm."}}, "https://www.argenprop.com/departamento-en-alquiler-en-parque-patricios-4-ambientes--15642262": {"date": "04-05-2024\n", "content": "1\n/19\n345\n$ 550.000 + $70.000 expensas\nAv Jujuy 2000, Piso 7\nDepartamento en Alquiler en Parque Patricios, Capital Federal\n63 m\u00b2 cubie.\n3 dorm.\n1 ba\u00f1o\nDepartamento con ambientes luminosos y excelente cocina\nExcelente departamento de 4 ambientes en alquiler en parque patricios. 63 mts cts y balcon sobre av. Caseros de 8 x 1,10 mts.todo con proteccion de red plastica al igual que en todas las ventanas de los ambientes. Para ingresar: mes de adelanto $ 550.000 + mes de deposito de garantia $ 550.000. Presentar sistema de garantia () o ( garantia ya)\nWhatsApp\nContactar", "revised": true, "rejected": false, "data": {"price": "$ 550.000 + $70.000 expensas", "expenses": "+ $70.000 expensas", "address": "Av Jujuy 2000, Piso 7", "meters": "68 m\u00b2 cubie.", "bedrooms": "3 dorm."}, "comment": "buen estado, pisos frios, balcon"}, "https://www.argenprop.com/departamento-en-alquiler-en-almagro-3-ambientes--5984886": {"date": "04-05-2024\n", "content": "1\n/19\n27\n$ 550.000 + $58.000 expensas\nCOLOMBRES 100, Piso 5\nDepartamento en Alquiler en Almagro, Capital Federal\n47,79 m\u00b2 cubie.\n2 dorm.\n30 a\u00f1os\nDEPARTAMENTO EN BUEN ESTADO Y UBICACION, A.ACOND. S.U.M. FRENTE. TODO AIRE Y LUZ. PARQUET.\nDepartamento de tres ambientes muy conservado, con excelente iluminacion, buena ubicacion a pocos metros de la estaci\u00f3n castro barros, subte \"a\", locaci\u00f3n con o sin mobiliario. Pisos parquet y cer\u00e1micos. Aire acondicionado, edificio cuenta con s.U.M. Nota: \u201clas medidas son aproximadas y orientativas. Las medidas exactas surgir\u00edan del t\u00edtulo de propiedad\" \u201cpara los casos de alquiler de vivienda,\nWhatsApp\nContactar", "revised": false, "rejected": true, "data": {"price": "$ 550.000 + $58.000 expensas", "expenses": "+ $58.000 expensas", "address": "COLOMBRES 100, Piso 5", "meters": "47,79 m\u00b2 cubie.", "bedrooms": "2 dorm."}}, "https://www.argenprop.com/departamento-en-alquiler-en-parque-patricios-3-ambientes--15522708": {"date": "04-05-2024\n", "content": "1\n/13\n332\n$ 330.000 + $73.000 expensas\nMatheu 1700\nDepartamento en Alquiler en Parque Patricios, Capital Federal\n60 m\u00b2 cubie.\n2 dorm.\n3 ambientes\nDEPARTAMENTO 3 Ambientes luminoso\nAmplio departamento en buen estado es necesario garantia propietaria y comprobantes de ingresos amley 5115: no accesible para las personas con discapacidades f\u00edsicas. Cumpliendo con la ley 5859: \"para los casos de alquiler de vivienda, el monto m\u00e1ximo de comisi\u00f3n que se le puede requerir a los propietarios ser\u00e1 el equivalente al cuatro con\nContactar", "revised": false, "rejected": true}, "https://www.argenprop.com/departamento-en-alquiler-en-san-cristobal-4-ambientes--15640810": {"date": "04-05-2024\n", "content": "1\n/12\n175\n$ 400.000 + $45.000 expensas\nSarand\u00ed 1400, Piso 8\nDepartamento en Alquiler en San Cristobal, Capital Federal\n78 m\u00b2 cubie.\n3 dorm.\n50 a\u00f1os\nDepto de 4 ambientes, 2 ba\u00f1os y cocina con comedor diario\nSemipiso de 4 ambientes, 2 ba\u00f1os y cocina con comedor diario, en la calle sarand\u00ed al 1400. En un 8vo piso muy luminoso. Orientado al oeste y al este simult\u00e1neamente, muy buen aireaci\u00f3n. Amplios placards con bauleras en los 3 dormitorios. Conexi\u00f3n para lavarropas en la cocina. Reci\u00e9n pintado. Garant\u00edas aceptadas: fi naer, garan t\u00eda ya, pre mium o propietaria de caba y demostrar ingresos. 1 mes de\nContactar", "revised": false, "rejected": true, "data": {"price": "$ 400.000 + $45.000 expensas", "expenses": "+ $45.000 expensas", "address": "Sarand\u00ed 1400, Piso 8", "meters": "78 m\u00b2 cubie.", "bedrooms": "3 dorm."}}, "https://www.argenprop.com/departamento-en-alquiler-en-balvanera-4-ambientes--15617750": {"date": "04-05-2024\n", "content": "1\n/58\n0\n$ 650.000 + $180.000 expensas\nLarrea al 700\nDepartamento en Alquiler en Balvanera, Capital Federal\n80 m\u00b2 cubie.\n3 dorm.\n40 a\u00f1os\nLarrea al 700 - 3 amb c/dep y balc\u00f3n - FACULTAD - Alquiler\nDepartamento de 4 amb c/balc\u00f3n contrafrente semi-piso muy luminoso encargado diurno seguridad nocturna palier semi-privado living-comedor con aire acondicionado balc\u00f3n al contrafrente dormitorio con placard dormitorio con placard dormitorio con placard amplia cocina completa a nueva comedor diario cocina el\u00e9ctrica vitrocer\u00e1mica a nuevo horno el\u00e9ctrico a nuevo termotanque a\nContactar", "revised": false, "rejected": true, "data": {"price": "$ 650.000 + $180.000 expensas", "expenses": "+ $180.000 expensas", "address": "Larrea al 700", "meters": "80 m\u00b2 cubie.", "bedrooms": "3 dorm."}}, "https://www.argenprop.com/departamento-en-alquiler-en-almagro-4-ambientes--5827366": {"date": "04-05-2024\n", "content": "1\n/28\n175\n$ 630.000 + $63.000 expensas\nAv Belgrano 3500, Piso 1\nDepartamento en Alquiler en Almagro, Capital Federal\n90 m\u00b2 cubie.\n3 dorm.\n40 a\u00f1os\nPiso de 4 ambientes al frente con balc\u00f3n corrido y patio\nMuy buen piso, frente orientado al norte, balc\u00f3n corrido con protector de red y buena vista. Es un inmueble t\u00edpico de la d\u00e9cada del 70, con pisos de escalla de m\u00e1rmol en el living comedor, cortinas tipo barrio (la del living el\u00e9ctrica), azulejos de color en el ba\u00f1o principal, etc. La cocina comedor es muy amplia con muebles sobre y bajo mesada de 17 puertas amplias, artefacto de cocina domec de\nWhatsApp\nContactar", "revised": true, "rejected": false, "data": {"price": "$ 630.000 + $63.000 expensas", "expenses": "+ $63.000 expensas", "address": "Av Belgrano 3500, Piso 1", "meters": "90 m\u00b2 cubie.", "bedrooms": "3 dorm."}, "comment": "Esquina Boedo. Buena cocina. Patio"}, "https://www.argenprop.com/departamento-en-alquiler-en-san-cristobal-3-ambientes--15578112": {"date": "04-05-2024\n", "content": "1\n/19\n0\n$ 400.000 + $80.000 expensas\nAv. Garay al 2200\nDepartamento en Alquiler en San Cristobal, Capital Federal\n65 m\u00b2 cubie.\n2 dorm.\n40 a\u00f1os\n3AMB AL FRENTE CON BALCON EN PLENA AV. GARAY! VISTA ABIERTA Y PURA LUZ\nDepartamento de 3 ambientes en torre con sum y pileta av. Garay entre pichincha y pasco. Piso alto con vista abierta, balc\u00f3n y luz natural. Asimismo, posee una amplia cocina con lavadero incorporado y placard en dormitorios. Excelente estado de conservaci\u00f3n. Transportes cercanos colectivos: 4, 6, 8, 12, 37, 46, 50, 53, 56, 57, 61, 62, 84, 86, 90, 91, 95, 96, 97, 118, 129, 133, 143, 150, 151,\nWhatsApp\nContactar", "revised": false, "rejected": true, "data": {"price": "$ 400.000 + $80.000 expensas", "expenses": "+ $80.000 expensas", "address": "Av. Garay al 2200", "meters": "65 m\u00b2 cubie.", "bedrooms": "2 dorm."}}, "https://www.argenprop.com/departamento-en-alquiler-en-san-nicolas-3-ambientes--15585654": {"date": "04-05-2024\n", "content": "1\n/23\n0\n$ 450.000 + $56.000 expensas\nViamonte 300\nDepartamento en Alquiler en San Nicol\u00e1s, Centro\n82 m\u00b2 cubie.\n2 dorm.\n85 a\u00f1os\nDEPARTAMENTO 3 AMBIENTES - SAN NICOL\u00c1S (CENTRO VIVIENDA), CAPITAL FEDERAL\nAtencion: esta oferta se encuentra reservada. Centro - bajo porte\u00f1o - excelentes accesos - a pocas cuadras de puerto madero. Edificio antig\u00fco de estilo, muy buena categor\u00eda y estado de mantenimiento. Es apto profesional. El departamento se encuentra en el segundo cuerpo, tercer piso, s\u00faper tranquilo. Amplios ambientes, techos altos, pisos de parquet. Consta de hall de entrada, amplia cocina con\nWhatsApp\nContactar", "revised": true, "rejected": true, "data": {"price": "$ 450.000 + $56.000 expensas", "expenses": "+ $56.000 expensas", "address": "Viamonte 300", "meters": "82 m\u00b2 cubie.", "bedrooms": "2 dorm."}}, "https://www.argenprop.com/departamento-en-alquiler-en-almagro-4-ambientes--15621362": {"date": "04-05-2024\n", "content": "1\n/16\n0\n$ 550.000 + $90.000 expensas\nSARMIENTO 4300\nDepartamento en Alquiler en Almagro, Capital Federal\n90 m\u00b2 cubie.\n3 dorm.\n40 a\u00f1os\nDepartamento de 4 ambientes en Alquiler en Almagro\nDepartamento de 4 ambientes con dependencia, en alquiler. Al frente, con balcon. Luminoso. Semipiso. Muy buena superficie. Cerca avdas. Corrientes, medrano, diaz velez. Subte, colectivos. Parque centenario, hospital italiano. Comercializa migliorisi de corrientes 4599 srl profesional responsable jorge daniel gomez cpi 261 a30101 se deja constancia que las caracteristicas, medidas, expensas y\nWhatsApp\nContactar", "revised": true, "rejected": false, "data": {"price": "$ 550.000 + $90.000 expensas", "expenses": "+ $90.000 expensas", "address": "SARMIENTO 4300", "meters": "90 m\u00b2 cubie.", "bedrooms": "3 dorm."}, "comment": "Hospital italiano. Falta cocina"}, "https://www.argenprop.com/departamento-en-alquiler-en-almagro-3-ambientes--15520222": {"date": "04-05-2024\n", "content": "1\n/7\n175\n$ 380.000 + $90.000 expensas\nDon Bosco 3600, Piso 5\nDepartamento en Alquiler en Almagro, Capital Federal\n60 m\u00b2 cubie.\n2 dorm.\n50 a\u00f1os\nBUEN DEPARTAMENTO DE 3 AMBS AL FRENTE\nEe trata de un muy buendepartamento de 3 ambientes en muy buena ubicacion. Al tratarse de un edificio en esquina, todos los ambientes son externos, por lo que se trata de una unidad muy luminosa y ventilada. Los pisos de living y dormitorios son de parquet y ambos cuentan con placard. El estado general tanto del edificio como de la unidad es bueno. La ubicaci\u00f3n es muy buena ya que se encuentra a\nWhatsApp\nContactar", "revised": false, "rejected": true, "data": {"price": "$ 380.000 + $90.000 expensas", "expenses": "+ $90.000 expensas", "address": "Don Bosco 3600, Piso 5", "meters": "60 m\u00b2 cubie.", "bedrooms": "2 dorm."}}, "https://www.argenprop.com/departamento-en-alquiler-en-almagro-3-ambientes--15637524": {"date": "04-05-2024\n", "content": "1\n/27\n2.151\n$ 590.000 + $40.753 expensas\nAvenida Estado De Israel 4200, Piso 5\nDepartamento en Alquiler en Almagro, Capital Federal\n64 m\u00b2 cubie.\n2 dorm.\n2 ba\u00f1os\nSEMIPISO 5to. BALC\u00d3N AL FRENTE en ESQUINA, expensas ABRIL $ 48.700, SIN ABL, 2 ba\u00f1os, lavadero\nAlquiler semipiso todo al frente en esquina, 3 y 1/2 ambientes, amplio balc\u00f3n, ba\u00f1o completo m\u00e1s ba\u00f1o de servicio, muy bajas expensas $ 48.700 abril 2024 - no se paga abl (a cargo del due\u00f1o) muy luminoso departamento en semipiso de tres ambientes: con balc\u00f3n y vista abierta al frente hacia las esquinas - dos dormitorios superficie total: 64 m2. (Como corresponde, en esta superficie no\nWhatsApp\nContactar", "revised": false, "rejected": true, "data": {"price": "$ 590.000 + $40.753 expensas", "expenses": "+ $40.753 expensas", "address": "Avenida Estado De Israel 4200, Piso 5", "meters": "64 m\u00b2 cubie.", "bedrooms": "2 dorm."}}, "https://www.argenprop.com/departamento-en-alquiler-en-san-nicolas-4-ambientes--15612390": {"date": "04-05-2024\n", "content": "1\n/13\n5\n$ 350.000 + $90.000 expensas\nSarmiento 1300\nDepartamento en Alquiler en San Nicol\u00e1s, Centro\n87 m\u00b2 cubie.\n3 dorm.\n70 a\u00f1os\nDepartamento en Alquiler. 4 Ambientes . Apto Profesional\nDepartamento 4 ambientes. 3 dormitorios . Living comedor. 2 ba\u00f1os. Apto profesional. Muy buen estado y ubicaci\u00f3n ep propiedades uruguay 116-caba cucicba matricula n\u00b0 1800 aviso legal: las descripciones arquitect\u00f3nicas y funcionales, valores de expensas, impuestos y servicios, fotos y medidas de este inmueble son aproximados. Los datos fueron proporcionados por el propietario y pueden no\nContactar", "revised": false, "rejected": true, "data": {"price": "$ 350.000 + $90.000 expensas", "expenses": "+ $90.000 expensas", "address": "Sarmiento 1300", "meters": "87 m\u00b2 cubie.", "bedrooms": "3 dorm."}}, "https://www.argenprop.com/departamento-en-alquiler-en-almagro-3-ambientes--15517826": {"date": "04-05-2024\n", "content": "1\n/29\n0\n$ 580.000 + $101.800 expensas\nVenezuela al 4400\nDepartamento en Alquiler en Almagro, Capital Federal\n88 m\u00b2 cubie.\n2 dorm.\n60 a\u00f1os\nVenezuela al 4400 Departamento de 3 ambientes con dependencia en Alquiler en Almagro\nAlquiler departamento de 3 ambientes con dependencia en almagro excelente departamento en alquiler ubicado en la zona de almagro. Esta espaciosa propiedad de 3 ambientes con dependencia ofrece comodidades ideales para vivir c\u00f3modamente. Caracter\u00edsticas principales 2 dormitorios con placard dependencia de servicio ba\u00f1o de servicio comedor diario amplio living y\nWhatsApp\nContactar", "revised": false, "rejected": true, "data": {"price": "$ 580.000 + $101.800 expensas", "expenses": "+ $101.800 expensas", "address": "Venezuela al 4400", "meters": "88 m\u00b2 cubie.", "bedrooms": "2 dorm."}}, "https://www.argenprop.com/departamento-en-alquiler-en-almagro-4-ambientes--15630536": {"date": "04-05-2024\n", "content": "1\n/34\n1\n$ 600.000 + $91.200 expensas\nAv. Hip\u00f3lito Yrigoyen 4000, Piso PB\nDepartamento en Alquiler en Almagro, Capital Federal\n78 m\u00b2 cubie.\n3 dorm.\n45 a\u00f1os\nDepartamento en alquiler en Almagro s\u00f3lo uso profesional\nDepartamento de 4 ambientes con dependencia en pb al frente, se alquila exclusivamente para uso profesional. 2 ventanas a la calle. Living comedor, 3 dormitorios con placares, ba\u00f1o completo, cocina equipada, lavadero, dependencia de servicio o comedor diario, toilette de servicio, patio, baulera. Puerta blindada. Pisos de parquet. Expensas con agua incluida. Ubicado en edificio de esquina a metros\nContactar", "revised": false, "rejected": true, "data": {"price": "$ 600.000 + $91.200 expensas", "expenses": "+ $91.200 expensas", "address": "Av. Hip\u00f3lito Yrigoyen 4000, Piso PB", "meters": "78 m\u00b2 cubie.", "bedrooms": "3 dorm."}}, "https://www.argenprop.com/departamento-en-alquiler-en-almagro-4-ambientes--15604742": {"date": "04-05-2024\n", "content": "1\n/21\n61\n$ 550.000 + $50.000 expensas\nMedrano 300, Piso 5\nDepartamento en Alquiler en Almagro, Capital Federal\n75 m\u00b2 cubie.\n3 dorm.\n40 a\u00f1os\nDepartamento 4 ambientes luminoso con balc\u00f3n al contrafrente\nExcelente departamento tres ambientes con dependencia de servicio, living comedor con salida al balc\u00f3n 2 dormitorios con placard y salida al balc\u00f3n cocina con comedor diario habitaci\u00f3n de servicio, ba\u00f1o y entrada de servicio, lavadero. Muy buena ubicaci\u00f3n cerca de multiples negocios y medios de transportes. Aviso legal: excepto para alquileres temporales, el monto m\u00e1ximo de comisi\u00f3n que se le\nContactar", "revised": false, "rejected": true, "data": {"price": "$ 550.000 + $50.000 expensas", "expenses": "+ $50.000 expensas", "address": "Medrano 300, Piso 5", "meters": "75 m\u00b2 cubie.", "bedrooms": "3 dorm."}}, "https://www.argenprop.com/departamento-en-alquiler-en-san-cristobal-3-ambientes--15638681": {"date": "04-05-2024\n", "content": "1\n/22\n0\n$ 550.000 + $80.000 expensas\nEstados Unidos 3100\nDepartamento en Alquiler en San Cristobal, Capital Federal\n67 m\u00b2 cubie.\n2 dorm.\n26 a\u00f1os\nSEMIPISO 3 AMBIENTES AMOBLADO MUY LUMINOSO\nContrafrente en 8vo piso, contando con un gran caudal de ventilaci\u00f3n y luz natural durante todo el d\u00eda. Totalmente amoblado y equipado. Amplio balc\u00f3n hacia el este y balc\u00f3n franc\u00e9s hacia el norte. Se aceptan hasta 4 personas actualizaci\u00f3n trimestral acorde a ley 27.551 (icl) zona con amplia oferta de lugares gastron\u00f3micos, educativos y de salud. A 1 cuadra de av. Independencia y a 3 cuadras de\nContactar", "revised": false, "rejected": true, "data": {"price": "$ 550.000 + $80.000 expensas", "expenses": "+ $80.000 expensas", "address": "Estados Unidos 3100", "meters": "67 m\u00b2 cubie.", "bedrooms": "2 dorm."}}, "https://www.argenprop.com/departamento-en-alquiler-en-san-nicolas-4-ambientes--15615454": {"date": "04-05-2024\n", "content": "1\n/19\n1\n$ 600.000\nSan Martin 500\nDepartamento en Alquiler en San Nicol\u00e1s, Centro\n72 m\u00b2 cubie.\n3 dorm.\n74 a\u00f1os\nConsultorio Medico, Estetica, Showroom, Oficina, Varios Consulte\nExcelente oficina / consultorios /apto profesional y/o oficina comercial varios rubros san martin entre lavalle y tucuman total 92mts. 72 mts cubiertos + patio 18mts y balc\u00f3n frente corrido pisos de parquet plastificado, 4 ambientes + patio y balc\u00f3n, 3 ba\u00f1os,1 ducha, timbre con visor , 3 aires acondicionados edificio con encargado permanente y control y monitoreo 24hs por camaras, llaves\nContactar", "revised": false, "rejected": true}, "https://www.argenprop.com/departamento-en-alquiler-en-congreso-3-ambientes--15510580": {"date": "04-05-2024\n", "content": "1\n/24\n0\n$ 420.000 + $78.600 expensas\nHipolito Yrigoyen y Rincon\nDepartamento en Alquiler en Congreso, Capital Federal\n105 m\u00b2 cubie.\n2 dorm.\n80 a\u00f1os\nDepartamento de 3 ambientes con dependencia en primer piso - Apto profesional\nAmplio departamento de tres ambientes con dependencia. Al ingreso c\u00f3moda recepci\u00f3n de 4,5 x 3.4 con pisos plastificados. En paralelo otro ambiente de 3.4 x 2.4 que podr\u00eda destinarse a comedor. Sala de grandes dimensiones de 8,5 x 3,7. Ideal para clases o exposiciones. Posibilidad de subidividir para hacer otra habitaci\u00f3n. Sector de cocina separada. Ba\u00f1o con\nWhatsApp\nContactar", "revised": false, "rejected": true}, "https://www.argenprop.com/departamento-en-alquiler-en-congreso-3-ambientes--15644927": {"date": "04-05-2024\n", "content": "1\n/24\n0\n$ 380.000 + $78.600 expensas\nHipolito Yrigoyen y Rincon\nDepartamento en Alquiler en Congreso, Capital Federal\n105 m\u00b2 cubie.\n2 dorm.\n80 a\u00f1os\nDepartamento de 3 ambientes con dependencia en primer piso - Apto profesional\nAmplio departamento de tres ambientes con dependencia. Al ingreso c\u00f3moda recepci\u00f3n de 4,5 x 3.4 con pisos plastificados. En paralelo otro ambiente de 3.4 x 2.4 que podr\u00eda destinarse a comedor. Sala de grandes dimensiones de 8,5 x 3,7. Ideal para clases o exposiciones. Posibilidad de subidividir para hacer otra habitaci\u00f3n. Sector de cocina separada. Ba\u00f1o con\nWhatsApp\nContactar", "revised": false, "rejected": true, "data": {"price": "$ 380.000 + $78.600 expensas", "expenses": "+ $78.600 expensas", "address": "Hipolito Yrigoyen y Rincon", "meters": "105 m\u00b2 cubie.", "bedrooms": "2 dorm."}}, "https://www.argenprop.com/ph-en-alquiler-en-parque-patricios-4-ambientes--15645561": {"date": "04-05-2024\n", "content": "1\n/17\n2\n$ 600.000\nAv La Plata 2400, Piso 1\nPH en Alquiler en Parque Patricios, Capital Federal\n90 m\u00b2 cubie.\n3 dorm.\n45 a\u00f1os\nAMPLIO PH 4AMB C BALCON FRENTE- PATIO- SIN EXPENSAS- AV LA PLATA 2462 INFO\nCorredora cucicba mat. 76 art 4 ley 5859 caba \"para los casos de alquiler de vivienda, el monto m\u00e1ximo de comisi\u00f3n que se le puede requerir a los propietarios ser\u00e1 el equivalente al cuatro con quince cent\u00e9simos por ciento (4,15%) del valor total del respectivo contrato. Se encuentra prohibido cobrar a los inquilinos que sean personas f\u00edsicas comisiones inmobiliarias y gastos de gestor\u00eda de\nWhatsApp\nContactar", "revised": false, "rejected": true, "data": {"price": "$ 600.000", "address": "Av La Plata 2400, Piso 1", "meters": "90 m\u00b2 cubie.", "bedrooms": "3 dorm."}}, "https://www.argenprop.com/departamento-en-alquiler-en-parque-centenario-3-ambientes--15520552": {"date": "04-05-2024\n", "content": "1\n/7\n0\n$ 350.000 + $110.000 expensas\nEUSTOQUI FRIAS GRAL 200\nDepartamento en Alquiler en Parque Centenario, Capital Federal\n61 m\u00b2 cubie.\n2 dorm.\n45 a\u00f1os\nDepartamento de 3 ambientes en Alquiler en P.centenario\nDepartamento de 3 ambientes en alquiler en parque centenario\nWhatsApp\nContactar", "revised": false, "rejected": true, "data": {"price": "$ 350.000 + $110.000 expensas", "expenses": "+ $110.000 expensas", "address": "EUSTOQUI FRIAS GRAL 200", "meters": "61 m\u00b2 cubie.", "bedrooms": "2 dorm."}}, "https://www.argenprop.com/departamento-en-alquiler-en-villa-crespo-4-ambientes--15640882": {"date": "04-05-2024\n", "content": "1\n/7\n200\n$ 600.000 + $150.000 expensas\nAr\u00e1oz 300, Piso 2\nDepartamento en Alquiler en Villa Crespo, Capital Federal\n83 m\u00b2 cubie.\n3 dorm.\n40 a\u00f1os\nDEPARTAMENTO 4 AMBIENTES CON BALC\u00d3N AL FRENTE EN ALQUILER\nDepartamento 4 ambientes en alquielr living comedor tres dormitorios ba\u00f1o completo toilette cocina lavadero balc\u00f3n a doscientos metros estacion malabia subte linea b la propiedad se va entregar reci\u00e9n pintada y con pisos pulidos requisitos: demostraci\u00f3n ingresos.Garant\u00eda propietaria de caba o seguro de caucion aprobado de\nWhatsApp\nContactar", "revised": false, "rejected": true, "data": {"price": "$ 600.000 + $150.000 expensas", "expenses": "+ $150.000 expensas", "address": "Ar\u00e1oz 300, Piso 2", "meters": "83 m\u00b2 cubie.", "bedrooms": "3 dorm."}}, "https://www.argenprop.com/departamento-en-alquiler-en-san-cristobal-3-ambientes--15635995": {"date": "04-05-2024\n", "content": "1\n/58\n350\n$ 500.000 + $80.000 expensas\nAv San Juan 2767\nDepartamento en Alquiler en San Cristobal, Capital Federal\n89 m\u00b2 cubie.\n2 dorm.\n40 a\u00f1os\nAlquiler de Semipiso de 3 ambientes con dependencia en San Crist\u00f3bal\nAlquiler de departamento de 3 ambientes con dependencia en san crist\u00f3bal. El departamento se encuentra en un noveno piso al contrafrente con vista panor\u00e1mica ubicado sobre la av. San juan muy cercano a l\u00ednea e y h de subte, zona s\u00faper comercial y cercano a todo. El inmueble cuenta con ambientes muy luminosos y espaciosos, cocina completa, lavadero independiente, living comedor con salida al\nWhatsApp\nContactar", "revised": true, "rejected": false, "data": {"price": "$ 500.000 + $80.000 expensas", "expenses": "+ $80.000 expensas", "address": "Av San Juan 2767", "meters": "89 m\u00b2 cubie.", "bedrooms": "2 dorm."}, "comment": "4amb. dependencia y doble entrada"}, "https://www.argenprop.com/departamento-en-alquiler-en-almagro-3-ambientes--15645655": {"date": "04-05-2024\n", "content": "0\n$ 700.000 + $120.000 expensas\nRAWON 100, Piso 3\nDepartamento en Alquiler en Almagro, Capital Federal\n60,89 m\u00b2 cubie.\n2 dorm.\n16 a\u00f1os\nAL FRENTE CON BALCON IMPECABLE 3 AMBIENTES CON COCHERA\nWhatsApp\nContactar", "revised": false, "rejected": true, "data": {"price": "$ 700.000 + $120.000 expensas", "expenses": "+ $120.000 expensas", "address": "RAWON 100, Piso 3", "meters": "60,89 m\u00b2 cubie.", "bedrooms": "2 dorm."}}, "https://www.argenprop.com/departamento-en-alquiler-en-villa-crespo-3-ambientes--15601784": {"date": "05-05-2024\n", "content": "1\n/11\n2\n$ 390.000 + $37.000 expensas\nLeopoldo Marechal 1200, Piso 3\nDepartamento en Alquiler en Villa Crespo, Capital Federal\n67 m\u00b2 cubie.\n2 dorm.\n49 a\u00f1os\nBalcon Cerrado - Lavarropas (opcional) - Muy Luminoso - 200 m Parque Centenario\nUbicado a 200 m del parque centenario. Piso 3\u00b0, contrafrente, balc\u00f3n cerrado, muy luminoso. Lavadero incorporado. Lavarropas. Expensas: $ 37.000 seguinos por instagram arguellesasociadosinmobiliaria visita nuestro sitio web\nWhatsApp\nContactar", "revised": false, "rejected": true, "data": {"price": "$ 390.000 + $37.000 expensas", "expenses": "+ $37.000 expensas", "address": "Leopoldo Marechal 1200, Piso 3", "meters": "67 m\u00b2 cubie.", "bedrooms": "2 dorm."}}, "https://www.argenprop.com/departamento-en-alquiler-en-parque-centenario-3-ambientes--15601707": {"date": "05-05-2024\n", "content": "1\n/11\n2\n$ 390.000 + $37.000 expensas\nLeopoldo Marechal 1200, Piso 3\nDepartamento en Alquiler en Parque Centenario, Capital Federal\n67 m\u00b2 cubie.\n2 dorm.\n49 a\u00f1os\nBalcon Cerrado - Lavarropas (opcional) - Muy Luminoso - 200 m Parque Centenario\nUbicado a 200 m del parque centenario. Piso 3\u00b0, contrafrente, balc\u00f3n cerrado, muy luminoso. Lavadero incorporado. Lavarropas. Expensas: $ 37.000 seguinos por instagram arguellesasociadosinmobiliaria visita nuestro sitio web\nWhatsApp\nContactar", "revised": false, "rejected": true, "data": {"price": "$ 390.000 + $37.000 expensas", "expenses": "+ $37.000 expensas", "address": "Leopoldo Marechal 1200, Piso 3", "meters": "67 m\u00b2 cubie.", "bedrooms": "2 dorm."}}, "https://www.argenprop.com/departamento-en-alquiler-en-monserrat-4-ambientes--6085132": {"date": "05-05-2024\n", "content": "1\n/15\n2\n$ 540.000 + $110.000 expensas\nDr M Moreno 800, Piso 7\nDepartamento en Alquiler en Monserrat, Centro\n74 m\u00b2 cubie.\n3 dorm.\n20 a\u00f1os\nVIGILANCIA 24HS - RECIEN PINTADO\nApto profesional. Vigilancia 24hs. Piso 7 al contrafrente, balc\u00f3n, muy luminosa. Reci\u00e9n pintada. 3 dormitorios, cocina con comedor diario, 2 ba\u00f1os (1 completo y 1 toilete). Expensas: $ 110.000. Servicios individuales. Seguinos en instagram argeullesasociadosinmobiliaria\nWhatsApp\nContactar", "revised": false, "rejected": true, "data": {"price": "$ 540.000 + $110.000 expensas", "expenses": "+ $110.000 expensas", "address": "Dr M Moreno 800, Piso 7", "meters": "74 m\u00b2 cubie.", "bedrooms": "3 dorm."}}, "https://www.argenprop.com/departamento-en-alquiler-en-once-4-ambientes--15623337": {"date": "05-05-2024\n", "content": "1\n/12\n720\n$ 450.000 + $76.700 expensas\nAvenida Corrientes 2600, Piso 7\nDepartamento en Alquiler en Once, Capital Federal\n86 m\u00b2 cubie.\n3 dorm.\n45 a\u00f1os\nOnce 4 amb frente due\u00f1o Av. Corrientes esq. Paso.\nAv. Corrientes al 2600 esquina paso 422, a una cuadra de la avda. Pueyrred\u00f3n y el cruce del subte b (estaci\u00f3n pueyrred\u00f3n) y del subte h (estaci\u00f3n corrientes). Departamento de 4 amb. Todos al frente en 7mo piso; dos entradas, doble circulaci\u00f3n, hall de recepci\u00f3n, living comedor, dormitorios con placard, todos a la calle con ventanales sobre paso al 400. Ba\u00f1o completo, toilette y ba\u00f1o de servicio,\nWhatsApp\nContactar", "revised": false, "rejected": true, "data": {"precio": "$ 450.000 + $76.700 expensas", "expensas": "+ $76.700 expensas", "direccion": "Avenida Corrientes 2600, Piso 7", "metros": "86 m\u00b2 cubie.", "habitaciones": "3 dorm."}}}