{"https://www.argenprop.com/departamento-en-alquiler-en-san-cristobal-3-ambientes--15647574": {"id": "19064372", "date": "07-05-2024\n", "index": 5, "content": "1\n/15\n0\n$ 400.000 + $80.000 expensas\nAv. Garay al 2200\nDepartamento en Alquiler en San Cristobal, Capital Federal\n65 m\u00b2 cubie.\n2 dorm.\n40 a\u00f1os\n3AMB AL FRENTE CON BALCON EN PLENA AV. GARAY! VISTA ABIERTA Y PURA LUZ\nDepartamento de 3 ambientes en torre con sum y pileta av. Garay entre pichincha y pasco. Piso alto con vista abierta, balc\u00f3n y luz natural. Asimismo, posee una amplia cocina con lavadero incorporado y placard en dormitorios. Excelente estado de conservaci\u00f3n. Transportes cercanos colectivos: 4, 6, 8, 12, 37, 46, 50, 53, 56, 57, 61, 62, 84, 86, 90, 91, 95, 96, 97, 118, 129, 133, 143, 150, 151,\nWhatsApp\nContactar", "revised": false, "rejected": false, "data": {"precio": "$ 400.000 + $80.000 expensas", "expensas": "+ $80.000 expensas", "direccion": "Av. Garay al 2200", "metros": "65 m\u00b2 cubie.", "habitaciones": "2 dorm."}, "image": "https://static1.sosiva451.com/47574651/f74f32d2-10ee-4ddb-8fc3-3724d71379b1_u_small.jpg", "title": "3AMB AL FRENTE CON BALCON EN PLENA AV. GARAY! VISTA ABIERTA Y PURA LUZ"}, "https://www.argenprop.com/ph-en-alquiler-en-parque-patricios-4-ambientes--15645561": {"id": "19062508", "date": "07-05-2024\n", "index": 6, "content": "1\n/17\n2\n$ 600.000\nAv La Plata 2400, Piso 1\nPH en Alquiler en Parque Patricios, Capital Federal\n90 m\u00b2 cubie.\n3 dorm.\n45 a\u00f1os\nAMPLIO PH 4AMB C BALCON FRENTE- PATIO- SIN EXPENSAS- AV LA PLATA 2462 INFO\nCorredora cucicba mat. 76 art 4 ley 5859 caba \"para los casos de alquiler de vivienda, el monto m\u00e1ximo de comisi\u00f3n que se le puede requerir a los propietarios ser\u00e1 el equivalente al cuatro con quince cent\u00e9simos por ciento (4,15%) del valor total del respectivo contrato. Se encuentra prohibido cobrar a los inquilinos que sean personas f\u00edsicas comisiones inmobiliarias y gastos de gestor\u00eda de\nWhatsApp\nContactar", "revised": false, "rejected": false, "data": {"precio": "$ 600.000", "direccion": "Av La Plata 2400, Piso 1", "metros": "90 m\u00b2 cubie.", "habitaciones": "3 dorm."}, "image": "https://static1.sosiva451.com/16554651/9df63443-af90-479c-a98e-7130c78c17a2_u_small.jpg", "title": "AMPLIO PH 4AMB C BALCON FRENTE- PATIO- SIN EXPENSAS- AV LA PLATA 2462 INFO "}, "https://www.argenprop.com/departamento-en-alquiler-en-parque-patricios-4-ambientes--15642262": {"id": "19059211", "date": "07-05-2024\n", "index": 7, "content": "1\n/19\n315\n$ 550.000 + $70.000 expensas\nAv Jujuy 2000, Piso 7\nDepartamento en Alquiler en Parque Patricios, Capital Federal\n68 m\u00b2 cubie.\n3 dorm.\n1 ba\u00f1o\nDepartamento con ambientes luminosos y excelente cocina\nExcelente departamento de 4 ambientes en alquiler en parque patricios. A pocos metros de estacion subte linea \"h\". 68 mts cts y+ balcon sobre av. Jujuy de 8 x 1,10 mts.total 77 mts.el balcon y cada una de las ventanas de los ambientes tienen red plastica para proteccion. Para ingresar a la locacion se requiere: 1 mes de adelanto $ 550.000 + 1 mes de deposito de garantia $ 550.000. Presentar\nWhatsApp\nContactar", "revised": false, "rejected": false, "data": {"precio": "$ 550.000 + $70.000 expensas", "expensas": "+ $70.000 expensas", "direccion": "Av Jujuy 2000, Piso 7", "metros": "68 m\u00b2 cubie.", "habitaciones": "3 dorm."}, "image": "https://static1.sosiva451.com/26224651/aa3f9535-3e24-43ca-9bf6-585c8a19269f_u_small.jpg", "title": "Departamento con ambientes luminosos y excelente cocina "}, "https://www.argenprop.com/departamento-en-alquiler-en-san-cristobal-4-ambientes--15640810": {"id": "19057762", "date": "07-05-2024\n", "index": 12, "content": "1\n/12\n175\n$ 400.000 + $45.000 expensas\nSarand\u00ed 1400, Piso 8\nDepartamento en Alquiler en San Cristobal, Capital Federal\n78 m\u00b2 cubie.\n3 dorm.\n50 a\u00f1os\nDepto de 4 ambientes, 2 ba\u00f1os y cocina con comedor diario\nSemipiso de 4 ambientes, 2 ba\u00f1os y cocina con comedor diario, en la calle sarand\u00ed al 1400. En un 8vo piso muy luminoso. Orientado al oeste y al este simult\u00e1neamente, muy buen aireaci\u00f3n. Amplios placards con bauleras en los 3 dormitorios. Conexi\u00f3n para lavarropas en la cocina. Reci\u00e9n pintado. Garant\u00edas aceptadas: fi naer, garan t\u00eda ya \u00f3 pre mium solamente 1 mes de dep\u00f3sito. 1 mes de alquiler.\nContactar", "revised": false, "rejected": true, "data": {"precio": "$ 400.000 + $45.000 expensas", "expensas": "+ $45.000 expensas", "direccion": "Sarand\u00ed 1400, Piso 8", "metros": "78 m\u00b2 cubie.", "habitaciones": "3 dorm."}, "image": "https://static1.sosiva451.com/01804651/9ef7ad22-0f11-4b86-b65d-7f937dce0c99_u_small.jpg", "title": "Depto de 4 ambientes, 2 ba\u00f1os y cocina con comedor diario"}, "https://www.argenprop.com/departamento-en-alquiler-en-san-cristobal-3-ambientes--15638681": {"id": "19055633", "date": "07-05-2024\n", "index": 14, "content": "1\n/22\n0\n$ 550.000 + $80.000 expensas\nEstados Unidos 3100\nDepartamento en Alquiler en San Cristobal, Capital Federal\n67 m\u00b2 cubie.\n2 dorm.\n26 a\u00f1os\nSEMIPISO 3 AMBIENTES AMOBLADO MUY LUMINOSO\nContrafrente en 8vo piso, contando con un gran caudal de ventilaci\u00f3n y luz natural durante todo el d\u00eda. Totalmente amoblado y equipado. Amplio balc\u00f3n hacia el este y balc\u00f3n franc\u00e9s hacia el norte. Se aceptan hasta 4 personas actualizaci\u00f3n trimestral acorde a ley 27.551 (icl) zona con amplia oferta de lugares gastron\u00f3micos, educativos y de salud. A 1 cuadra de av. Independencia y a 3 cuadras de\nContactar", "revised": false, "rejected": true, "data": {"precio": "$ 550.000 + $80.000 expensas", "expensas": "+ $80.000 expensas", "direccion": "Estados Unidos 3100", "metros": "67 m\u00b2 cubie.", "habitaciones": "2 dorm."}, "image": "https://static1.sosiva451.com/18683651/86aa4019-de98-4492-9fcd-d7b0134afd8f_u_small.jpg", "title": "SEMIPISO 3 AMBIENTES AMOBLADO MUY LUMINOSO"}, "https://www.argenprop.com/departamento-en-alquiler-en-san-cristobal-3-ambientes--15503688": {"id": "18929557", "date": "07-05-2024\n", "index": 15, "content": "1\n/13\n2\n$ 700.000 + $37.000 expensas\nALBERTI 1200\nDepartamento en Alquiler en San Cristobal, Capital Federal\n65 m\u00b2 cubie.\n2 dorm.\nA Estrenar\nDEPARTAMENTOS DE 3 AMBIENTES EN ALQUILER ZONA SAN CRISTOBAL\n\u2022Hermosos departamentos 3 ambientes en alquiler ubicado en el barrio de san crist\u00f3bal edificio con entrada y frente muy bueno (moderno) (orientaci\u00f3n oeste) excelente unidad a estrenar super luminosa con balc\u00f3n corrido ,vista al frente y detalles de categor\u00eda. \u2022Pisos de porcelanato \u2022revestimiento: pintura y cer\u00e1mico (en ba\u00f1os) listo para mudarte ( 2 unidades disponibles ) \u2022ambientes:\nWhatsApp\nContactar", "revised": false, "rejected": false, "data": {"precio": "$ 700.000 + $37.000 expensas", "expensas": "+ $37.000 expensas", "direccion": "ALBERTI 1200", "metros": "65 m\u00b2 cubie.", "habitaciones": "2 dorm."}, "image": "https://static1.sosiva451.com/88630551/75bbe565-6b8d-4765-8ca7-34f420afc3eb_u_small.jpg", "title": "DEPARTAMENTOS DE 3 AMBIENTES EN ALQUILER ZONA SAN CRISTOBAL "}, "https://www.argenprop.com/departamento-en-alquiler-en-parque-patricios-4-ambientes--15626588": {"id": "19043548", "date": "07-05-2024\n", "index": 16, "content": "1\n/23\n0\n$ 650.000 + $88.000 expensas\nMafalda 900\nDepartamento en Alquiler en Parque Patricios, Capital Federal\n105 m\u00b2 cubie.\n3 dorm.\n3 a\u00f1os\nALQUILER 4 AMBIENTES + COCHERA. 120 M2 EXP $88.000\nAlquiler departamento de 4 ambientes con cochera en el barrio nuevo de parque patricios. Esta propiedad es una excelente opci\u00f3n para aquellos que buscan amplitud, comodidad y la conveniencia de tener un lugar para estacionar su veh\u00edculo. Al ingresar a la propiedad, te encontrar\u00e1s con un amplio y luminoso living-comedor, ideal para recibir visitas o disfrutar de momentos en familia. La cocina,\nContactar", "revised": false, "rejected": true, "data": {"precio": "$ 650.000 + $88.000 expensas", "expensas": "+ $88.000 expensas", "direccion": "Mafalda 900", "metros": "105 m\u00b2 cubie.", "habitaciones": "3 dorm."}, "image": "https://static1.sosiva451.com/88562651/893788d3-d4b0-4b80-a959-11cbd437a145_u_small.jpg", "title": "ALQUILER 4 AMBIENTES + COCHERA. 120 M2 EXP $88.000"}, "https://www.argenprop.com/departamento-en-alquiler-en-san-cristobal-3-ambientes--15633546": {"id": "19050508", "date": "07-05-2024\n", "index": 17, "content": "1\n/49\n0\n$ 370.000 + $20.000 expensas\nAvenida San Juan 3500\nDepartamento en Alquiler en San Cristobal, Capital Federal\n61 m\u00b2 cubie.\n2 dorm.\n20 a\u00f1os\n3AMB s/av! ubic ideal! sj y boe! coc recic lav! b\u00f1o! bjas exp! listo p/hab!\n3 ambientes en san juan y boedo ! Listo para ser habitado ! #Departamento | #est\u00e1ndar | #3amb | #lateral | #sanjuanyboedo avenida san juan 3500, piso 2 - ciudad aut\u00f3noma de buenos aires caracter\u00edsticas: ~ departamento de tres (3) ambientes, en un segundo (2o) piso por escalera, dispuesto hacia el lateral, ubicado en el centro neur\u00e1lgico del barrio de boedo. ~ Orientaci\u00f3n n\nWhatsApp\nContactar", "revised": false, "rejected": false, "data": {"precio": "$ 370.000 + $20.000 expensas", "expensas": "+ $20.000 expensas", "direccion": "Avenida San Juan 3500", "metros": "61 m\u00b2 cubie.", "habitaciones": "2 dorm."}, "image": "https://static1.sosiva451.com/64533651/9375abf1-be83-477b-a673-361321764b6f_u_small.jpg", "title": "3AMB s/av! ubic ideal! sj y boe! coc recic lav! b\u00f1o! bjas exp! listo p/hab!"}, "https://www.argenprop.com/departamento-en-alquiler-en-san-cristobal-3-ambientes--15630767": {"id": "19047728", "date": "07-05-2024\n", "index": 18, "content": "1\n/14\n101\n$ 400.000 + $86.000 expensas\nAv San Juan 2100, Piso 1\nDepartamento en Alquiler en San Cristobal, Capital Federal\n63 m\u00b2 cubie.\n2 dorm.\n60 a\u00f1os\nAlquiler depto 3 ambientes c\u00f3modo + escritorio por escalera!\nDepartamento de 3 ambientes muy c\u00f3modo! * Living comedor amplio con pisos en madera. * Dormitorio ppal con placard y pisos en madera * 2do dormitorio sin placard y pisos en madera. * Escritorio del tama\u00f1o de un 3er dormitorio con amplio placard. * Ba\u00f1o y cocina completos. * Lavadero independiente. * Reci\u00e9n pintado * subte y varios medios de transporte. Consulte para los casos de\nWhatsApp\nContactar", "revised": false, "rejected": false, "data": {"precio": "$ 400.000 + $86.000 expensas", "expensas": "+ $86.000 expensas", "direccion": "Av San Juan 2100, Piso 1", "metros": "63 m\u00b2 cubie.", "habitaciones": "2 dorm."}, "image": "https://static1.sosiva451.com/76703651/fe4b7428-5fdd-4233-a328-d0a7ec97f19f_u_small.jpg", "title": "Alquiler depto 3 ambientes c\u00f3modo + escritorio por escalera!"}, "https://www.argenprop.com/departamento-en-alquiler-en-parque-patricios-3-ambientes--15618295": {"id": "19035245", "date": "07-05-2024\n", "index": 19, "content": "1\n/12\n0\n$ 370.000\nFinochietto 2046 2 piso\nDepartamento en Alquiler en Parque Patricios, Capital Federal\n60 m\u00b2 cubie.\n2 dorm.\n45 a\u00f1os\nDepartamento en Barracas\nDepartamento de 3 ambientes sin expensas amplio y luminoso living - comedor con acceso a balc\u00f3n cocina completa con alacenas y muebles bajo mesada. Espacio para lavarropas. 2 dormitorios con placards de piso a techo ba\u00f1o completo para los casos de alquiler de vivienda, el monto m\u00e1ximo de comisi\u00f3n que se le puede requerir a los propietarios ser\u00e1 el equivalente al cuatro\nWhatsApp\nContactar", "revised": false, "rejected": false, "data": {"precio": "$ 370.000", "direccion": "Finochietto 2046 2 piso", "metros": "60 m\u00b2 cubie.", "habitaciones": "2 dorm."}, "image": "https://static1.sosiva451.com/59281651/959716ea-ef4e-40cb-bf19-77e5cc6ebe71_u_small.jpg", "title": "Departamento en Barracas"}, "https://www.argenprop.com/departamento-en-alquiler-en-parque-patricios-3-ambientes--15264735": {"id": "18699582", "date": "07-05-2024\n", "index": 21, "content": "1\n/27\n2\n$ 350.000 + $52.000 expensas\nAvenida Caseros 3500\nDepartamento en Alquiler en Parque Patricios, Capital Federal\n60 m\u00b2 cubie.\n2 dorm.\n3 ambientes\n3 Ambientes lateral de 60 m2 cubiertos\n3 ambientes al lateral con vista a jardin. Muy luminoso, 60 m2 cubiertos. Segundo piso por escalera. Dormitorios con placard y pisos de parquet de 3,2 x 3. Living 6 x 3,5. Ba\u00f1o completo con ba\u00f1era. Cocina 3,5 x 1,5 se entrega con alacenas instaladas y bajo mesada nuevo. Lavadero independiente 1,5 x 1. Artefactos electricos. Muy buen estado. No acepta mascotas. Expensas $ 52.000.- (Marzo 2024) se\nContactar", "revised": false, "rejected": false, "data": {"precio": "$ 350.000 + $52.000 expensas", "expensas": "+ $52.000 expensas", "direccion": "Avenida Caseros 3500", "metros": "60 m\u00b2 cubie.", "habitaciones": "2 dorm."}, "image": "https://static1.sosiva451.com/53746251/e9728474-9048-4a19-843c-94984df534ba_u_small.jpg", "title": "3 Ambientes lateral de 60 m2 cubiertos"}, "https://www.argenprop.com/departamento-en-alquiler-en-san-cristobal-3-ambientes--15289895": {"id": "18724789", "date": "07-05-2024\n", "index": 22, "content": "1\n/34\n30\n$ 430.000 + $36.000 expensas\nCARLOS CALVO al 2000\nDepartamento en Alquiler en San Cristobal, Capital Federal\n62 m\u00b2 cubie.\n2 dorm.\n40 a\u00f1os\nCARLOS CALVO AL 2000 - T/AL CONTRAFRENTE 62 M2 T/A NUEVO BALCON V/ABIERTA T/SOL APTO PROF\n3 ambientes. Todo al contrafrente. 62 m2. Todo a nuevo. Balcon con red y en todas las aberturas. Vista abierta. Todo sol. Todo externo. Apto profesional. Ba\u00f1o completo. Cocina comedor. 2 placards. Lavadero independiente cubierto. Pisos de madera. Edificio de 9 pisos, 4 por piso, 2 ascensores. Expensas: $ 36.000.- Abl: $ 3.104.- Aysa: $ 4.846.- Entre rincon y\nWhatsApp\nContactar", "revised": false, "rejected": false, "data": {"precio": "$ 430.000 + $36.000 expensas", "expensas": "+ $36.000 expensas", "direccion": "CARLOS CALVO al 2000", "metros": "62 m\u00b2 cubie.", "habitaciones": "2 dorm."}, "image": "https://static1.sosiva451.com/59898251/be7af608-0a0b-484d-baa1-42f8e44d7aa7_u_small.jpg", "title": "CARLOS CALVO AL 2000 - T/AL CONTRAFRENTE 62 M2 T/A NUEVO BALCON V/ABIERTA T/SOL APTO PROF"}, "https://www.argenprop.com/departamento-en-alquiler-en-parque-patricios-3-ambientes--15613698": {"id": "19030640", "date": "07-05-2024\n", "index": 23, "content": "1\n/12\n6\n$ 340.000 + $60.000 expensas\nAvenida Caseros 3500, Piso 2\nDepartamento en Alquiler en Parque Patricios, Capital Federal\n64 m\u00b2 cubie.\n2 dorm.\n3 ambientes\n3 Ambientes amplios RECICLADO A NUEVO\n3 ambientes amplios de 64 m2 cubiertos. Reciclado a nuevo. Cocina independiente 4 x 2,2. Lavadero independiente. Living 3,3 x 6. Dormitorios de 3 x 3 con placards. Pisos de parquet en los ambientes. Segundo piso por escalera. Balcon frances con vista a jardin. Excelente estado. Inmobiliaria jorge miguel contrato por 2 a\u00f1os con aumentos trimestrales por icl. Consultas al 49 12 14 64 / 30 13.\nContactar", "revised": false, "rejected": false, "data": {"precio": "$ 340.000 + $60.000 expensas", "expensas": "+ $60.000 expensas", "direccion": "Avenida Caseros 3500, Piso 2", "metros": "64 m\u00b2 cubie.", "habitaciones": "2 dorm."}, "image": "https://static1.sosiva451.com/89631651/ab061468-b209-4dbd-a229-8e6912c7803d_u_small.jpg", "title": "3 Ambientes amplios RECICLADO A NUEVO"}, "https://www.argenprop.com/ph-en-alquiler-en-parque-patricios-3-ambientes--14573636": {"id": "18018582", "date": "07-05-2024\n", "index": 24, "content": "2\n$ 420.000\nAlagon 100, Piso PB\nPH en Alquiler en Parque Patricios, Capital Federal\n65 m\u00b2 cubie.\n2 dorm.\n1 ba\u00f1o\nPH. AL FRENTE ,RECICLADO ,SIN EXPENSAS\nPh al fte.Totalmente reciclado, aysa incluido en el precio\nContactar", "revised": false, "rejected": false, "data": {"precio": "$ 420.000", "direccion": "Alagon 100, Piso PB", "metros": "65 m\u00b2 cubie.", "habitaciones": "2 dorm."}, "image": "https://www.argenprop.com/content/images/listing-camera.svg", "title": "PH. AL FRENTE ,RECICLADO ,SIN EXPENSAS"}, "https://www.argenprop.com/departamento-en-alquiler-en-san-cristobal-3-ambientes--15589270": {"id": "19006195", "date": "07-05-2024\n", "index": 26, "content": "1\n/14\n180\n$ 450.000 + $54.000 expensas\nAv Independencia 2700, Piso 5\nDepartamento en Alquiler en San Cristobal, Capital Federal\n61 m\u00b2 cubie.\n2 dorm.\n15 a\u00f1os\nSemipiso, palier privado, 3 ambientes con 2 ba\u00f1os y 2 balcones.\nImportante semipiso con palier privado. Puerta blindada. En un 5to piso al contrafrente. Sobre av. Independencia entre av. Jujuy y catamarca. Proximidad de subtes h y e, autopista 25 de mayo y m\u00faltiples l\u00edneas de colectivos. 2 ba\u00f1os completos (1 con ducha). Gran cocina, con lavadero incorporado. Calefacci\u00f3n por caldera individual. Baulera.\nContactar", "revised": false, "rejected": false, "data": {"precio": "$ 450.000 + $54.000 expensas", "expensas": "+ $54.000 expensas", "direccion": "Av Independencia 2700, Piso 5", "metros": "61 m\u00b2 cubie.", "habitaciones": "2 dorm."}, "image": "https://static1.sosiva451.com/07298551/50bcbea6-5f45-4d95-9339-ddec4d96e7da_u_small.jpg", "title": "Semipiso, palier privado, 3 ambientes con 2 ba\u00f1os y 2 balcones."}, "https://www.argenprop.com/departamento-en-alquiler-en-san-cristobal-4-ambientes--15516116": {"id": "18941989", "date": "07-05-2024\n", "index": 28, "content": "1\n/28\n1\n$ 380.000 + $68.000 expensas\nVirrey Cevallos al 900\nDepartamento en Alquiler en San Cristobal, Capital Federal\n60 m\u00b2 cubie.\n2 dorm.\n60 a\u00f1os\nDepartamento en San Cristobal\nAlquiler monserrat 4 ambientes al frente. Luminoso living comedor amplio 2 dormitorios con placard. 3er dormitorio o escritorio. Cocina separada. Ba\u00f1o completo. Galeria con cerramiento. Pintura a nuevo solo con garantia y recibo de sueldo. Contrato por 2 a\u00f1os con ajuste trimestral no apto mascotas. No accesible. Para los casos de alquiler de\nWhatsApp\nContactar", "revised": false, "rejected": false, "data": {"precio": "$ 380.000 + $68.000 expensas", "expensas": "+ $68.000 expensas", "direccion": "Virrey Cevallos al 900", "metros": "60 m\u00b2 cubie.", "habitaciones": "2 dorm."}, "image": "https://static1.sosiva451.com/61161551/a523af8d-d149-4bef-aaad-61603f847816_u_small.jpg", "title": "Departamento en San Cristobal"}, "https://www.argenprop.com/departamento-en-alquiler-en-parque-patricios-4-ambientes--15561948": {"id": "18978860", "date": "07-05-2024\n", "index": 29, "content": "1\n/23\n0\n$ 620.000 + $57.000 expensas\nMirav\u00e9 3000\nDepartamento en Alquiler en Parque Patricios, Capital Federal\n69 m\u00b2 cubie.\n3 dorm.\n12 a\u00f1os\nALQUILER DEPARTAMENTO 4 AMB EN PARQUE PATRICIOS\nAlquiler departamento de 4 ambientes con balc\u00f3n en parque patricios ubicado en sexto piso al frente. Consta de: 3 dormitorios cocina semi integrada balc\u00f3n living - comedor ba\u00f1o completo edificio de 8 pisos, tiene un solo ascensor, son 2 departamentos por piso. Requisitos para entrar: -un mes de adelanto -un mes de dep\u00f3sito -seguro de cauci\u00f3n de o garantia ya o garantia propietaria de caba -no\nContactar", "revised": false, "rejected": false, "data": {"precio": "$ 620.000 + $57.000 expensas", "expensas": "+ $57.000 expensas", "direccion": "Mirav\u00e9 3000", "metros": "69 m\u00b2 cubie.", "habitaciones": "3 dorm."}, "image": "https://static1.sosiva451.com/84916551/e029adca-1ffe-4acb-a3aa-0d673971a7a1_u_small.jpg", "title": "ALQUILER DEPARTAMENTO 4 AMB EN PARQUE PATRICIOS"}, "https://www.argenprop.com/departamento-en-alquiler-en-parque-patricios-3-ambientes--15577375": {"id": "18994299", "date": "07-05-2024\n", "index": 31, "content": "1\n/28\n3\n$ 400.000 + $52.000 expensas\nAvenida S\u00e1enz 200\nDepartamento en Alquiler en Parque Patricios, Capital Federal\n61 m\u00b2 cubie.\n2 dorm.\n3 ambientes\n3 Ambientes al frente - Excelente\n3 ambientes amplios frente con balcon frances en inmejorable estado. Orientacion norte, muy luminoso. Cocina con lavadero incorporado 3 x 2 + 2 x 2,5 totalmente instalada. Dormitorios de 3,2 x 3,5 , y de 3,2 x 3,2 ambos con placards y con ventiladores de techo y aire acondicionado. Ba\u00f1o completo con ba\u00f1era. Living 6 x 3,5. Expensas $ 52.000.- (Marzo 2024). Se requiere: ingresos demostrables, y\nContactar", "revised": false, "rejected": false, "data": {"precio": "$ 400.000 + $52.000 expensas", "expensas": "+ $52.000 expensas", "direccion": "Avenida S\u00e1enz 200", "metros": "61 m\u00b2 cubie.", "habitaciones": "2 dorm."}, "image": "https://static1.sosiva451.com/57377551/19effe4b-97cc-42c5-8253-4a2044cb22c6_u_small.jpg", "title": "3 Ambientes al frente - Excelente"}, "https://www.argenprop.com/departamento-en-alquiler-en-parque-patricios-3-ambientes--15568271": {"id": "18985187", "date": "07-05-2024\n", "index": 32, "content": "1\n/27\n8\n$ 320.000 + $48.000 expensas\nAvenida S\u00e1enz 200\nDepartamento en Alquiler en Parque Patricios, Capital Federal\n61 m\u00b2 cubie.\n2 dorm.\n3 ambientes\n3 Ambientes al frente muy amplio\n3 ambientes amplios frente con balcon frances. Orientacion norte y este, super luminoso. Cocina con lavadero incorporado 5 x 1,8. Dormitorios de 2,8 x 3,4 , y de 3,2 x 3,4 uno de ellos con placards. Ba\u00f1o completo con ba\u00f1era. Living 6,5 x 3,2. Buen estado, falta pintura. Expensas $ 48.000.- (Marzo 2024). Se requiere: ingresos demostrables, y garantia propietaria propietaria en caba o seguro de\nContactar", "revised": false, "rejected": false, "data": {"precio": "$ 320.000 + $48.000 expensas", "expensas": "+ $48.000 expensas", "direccion": "Avenida S\u00e1enz 200", "metros": "61 m\u00b2 cubie.", "habitaciones": "2 dorm."}, "image": "https://static1.sosiva451.com/17286551/e94c34a0-d65a-461a-a33c-cb2de27724b2_u_small.jpg", "title": "3 Ambientes al frente muy amplio"}, "https://www.argenprop.com/departamento-en-alquiler-en-san-cristobal-4-ambientes--15561701": {"id": "18978611", "date": "07-05-2024\n", "index": 33, "content": "1\n/51\n0\n$ 460.000 + $65.000 expensas\nEduardo Acevedo 72\nDepartamento en Alquiler en San Cristobal, Capital Federal\n80 m\u00b2 cubie.\n3 dorm.\n50 a\u00f1os\n4AMB \u00b7 80M\u00b2 \u00b7 frente! b\u00f1 toiltte! coc indep lavad! ubic \u00fanica! parque rivadavia!\n4 ambientes al frente ! En la zona m\u00e1s c\u00e9ntrica de caballito ! #Departamento | #est\u00e1ndar | #4amb | #caballito | #frente | #parquerivadavia eduardo acevedo y avenida rivadavia, piso 1 - ciudad aut\u00f3noma de buenos aires caracter\u00edsticas: ~ departamento de cuatro (4) ambientes, dispuesto hacia el frente, en la ubicaci\u00f3n m\u00e1s c\u00e9ntrica y comercial del barrio de caballito. ~ Orientaci\u00f3n hacia el e\nWhatsApp\nContactar", "revised": false, "rejected": false, "data": {"precio": "$ 460.000 + $65.000 expensas", "expensas": "+ $65.000 expensas", "direccion": "Eduardo Acevedo 72", "metros": "80 m\u00b2 cubie.", "habitaciones": "3 dorm."}, "image": null, "title": "4AMB \u00b7 80M\u00b2 \u00b7 frente! b\u00f1 toiltte! coc indep lavad! ubic \u00fanica! parque rivadavia!"}, "https://www.argenprop.com/departamento-en-alquiler-en-san-cristobal-4-ambientes--15524849": {"id": "18950713", "date": "07-05-2024\n", "index": 35, "content": "1\n/23\n0\n$ 435.000 + $60.000 expensas\nCombate De Los Pozos 900, Piso 3\nDepartamento en Alquiler en San Cristobal, Capital Federal\n73 m\u00b2 cubie.\n3 dorm.\n68 a\u00f1os\nALQUILER - MONSERRAT - 4 AMBIENTES - CONTRAFRENTE - MUY LUMINOSO - COCINA COMEDOR - LAVADERO\nAlquiler @san crist\u00f3bal - c. De los pozos / avenidas cercanas: e. R\u00edos . San juan - independencia #regia.Ubicacion cuenta con: 3 dormitorios todos con placard - living comedor - cocina con comedor de diario - lavadero separado - ba\u00f1o principal completo y ba\u00f1o de servicio (en sector lavadero). Pisos de parquet - paredes pintadas (reci\u00e9n) en blanco - revestimientos cer\u00e1micos - muebles de cocina\nContactar", "revised": false, "rejected": false, "data": {"precio": "$ 435.000 + $60.000 expensas", "expensas": "+ $60.000 expensas", "direccion": "Combate De Los Pozos 900, Piso 3", "metros": "73 m\u00b2 cubie.", "habitaciones": "3 dorm."}, "image": "https://static1.sosiva451.com/94842551/14e2c281-bcee-4126-a112-c59a8e6022e8_u_small.jpg", "title": "ALQUILER - MONSERRAT - 4 AMBIENTES - CONTRAFRENTE - MUY LUMINOSO - COCINA COMEDOR - LAVADERO "}, "https://www.argenprop.com/departamento-en-alquiler-en-parque-patricios-3-ambientes--15497889": {"id": "18923765", "date": "07-05-2024\n", "index": 37, "content": "1\n/48\n0\n$ 500.000 + $57.000 expensas\nAvenida Juan de Garay al 3200\nDepartamento en Alquiler en Parque Patricios, Capital Federal\n60 m\u00b2 cubie.\n2 dorm.\n10 a\u00f1os\n3AMB nuevo fte 2 balcones \u00b7 60m\u00b2 \u00b7 muebles! AA! heladera! cama! parr! amenities!\n3 amb nuevo c/amenities ! 2 balcones, frente c/vista panor\u00e1mica ! #Alquiler | #departamento | #amenities | #parquepatricios | #3amb | #frente avenida juan de garay 3200, piso 7 - ciudad aut\u00f3noma de buenos aires caracter\u00edsticas: ~ departamento nuevo de tres (3) ambientes nuevo, dispuesto hacia el frente, con dos (2) balcones corridos, ubicado centricamente en el barrio de parque patricios. ~\nWhatsApp\nContactar", "revised": false, "rejected": false, "data": {"precio": "$ 500.000 + $57.000 expensas", "expensas": "+ $57.000 expensas", "direccion": "Avenida Juan de Garay al 3200", "metros": "60 m\u00b2 cubie.", "habitaciones": "2 dorm."}, "image": "https://static1.sosiva451.com/98879451/28ae446f-cd39-4f54-8434-3487d4a813d3_u_small.jpg", "title": "3AMB nuevo fte 2 balcones \u00b7 60m\u00b2 \u00b7 muebles! AA! heladera! cama! parr! amenities!"}, "https://www.argenprop.com/departamento-en-alquiler-en-san-cristobal-3-ambientes--15497888": {"id": "18923766", "date": "07-05-2024\n", "index": 38, "content": "1\n/48\n0\n$ 500.000 + $57.000 expensas\nAvenida Juan de Garay al 3200\nDepartamento en Alquiler en San Cristobal, Capital Federal\n60 m\u00b2 cubie.\n2 dorm.\n10 a\u00f1os\n3AMB nuevo fte 2 balcones \u00b7 60m\u00b2 \u00b7 muebles! AA! heladera! cama! parr! amenities!\n3 amb nuevo c/amenities ! 2 balcones, frente c/vista panor\u00e1mica ! #Alquiler | #departamento | #amenities | #parquepatricios | #3amb | #frente avenida juan de garay 3200, piso 7 - ciudad aut\u00f3noma de buenos aires caracter\u00edsticas: ~ departamento nuevo de tres (3) ambientes nuevo, dispuesto hacia el frente, con dos (2) balcones corridos, ubicado centricamente en el barrio de parque patricios. ~\nWhatsApp\nContactar", "revised": false, "rejected": false, "data": {"precio": "$ 500.000 + $57.000 expensas", "expensas": "+ $57.000 expensas", "direccion": "Avenida Juan de Garay al 3200", "metros": "60 m\u00b2 cubie.", "habitaciones": "2 dorm."}, "image": "https://static1.sosiva451.com/88879451/4bf9b2e2-1451-40fe-b62d-ea0abc637ee0_u_small.jpg", "title": "3AMB nuevo fte 2 balcones \u00b7 60m\u00b2 \u00b7 muebles! AA! heladera! cama! parr! amenities!"}, "https://www.argenprop.com/departamento-en-alquiler-en-parque-patricios-3-ambientes--15497885": {"id": "18923762", "date": "07-05-2024\n", "index": 39, "content": "1\n/48\n0\n$ 500.000 + $57.000 expensas\nAvenida Juan de Garay al 3200\nDepartamento en Alquiler en Parque Patricios, Capital Federal\n60 m\u00b2 cubie.\n2 dorm.\n10 a\u00f1os\n3AMB nuevo fte 2 balcones \u00b7 60m\u00b2 \u00b7 muebles! AA! heladera! cama! parr! amenities!\n3 amb nuevo c/amenities ! 2 balcones, frente c/vista panor\u00e1mica ! #Alquiler | #departamento | #amenities | #parquepatricios | #3amb | #frente avenida juan de garay 3200, piso 7 - ciudad aut\u00f3noma de buenos aires caracter\u00edsticas: ~ departamento nuevo de tres (3) ambientes nuevo, dispuesto hacia el frente, con dos (2) balcones corridos, ubicado centricamente en el barrio de parque patricios. ~\nWhatsApp\nContactar", "revised": false, "rejected": false, "data": {"precio": "$ 500.000 + $57.000 expensas", "expensas": "+ $57.000 expensas", "direccion": "Avenida Juan de Garay al 3200", "metros": "60 m\u00b2 cubie.", "habitaciones": "2 dorm."}, "image": "https://static1.sosiva451.com/58879451/9820bf69-a4b8-4ee0-ba1c-220eae400e42_u_small.jpg", "title": "3AMB nuevo fte 2 balcones \u00b7 60m\u00b2 \u00b7 muebles! AA! heladera! cama! parr! amenities!"}, "https://www.argenprop.com/departamento-en-alquiler-en-parque-patricios-3-ambientes--15491685": {"id": "18917571", "date": "08-05-2024\n", "index": 40, "content": "1\n/28\n3\n$ 400.000 + $45.000 expensas\nCastro Barros 2200\nDepartamento en Alquiler en Parque Patricios, Capital Federal\n65 m\u00b2 cubie.\n2 dorm.\n3 ambientes\n3 Ambientes al Frente con Balcon\n3 ambientes al frente con balcon de 3 x 1. Living 6,5 x 3,2. Cocina independiente 2,5 x 3,5. Lavadero independiente, dormitorios con placards de 3,5 x 3,2, y 3,2 x 3. Ba\u00f1o completo con ba\u00f1era. Expensas $ 45000.- (Febrero 2024). Buen estado de conservacion. Contrato por 2 a\u00f1os con aumentos cuatrimestrales por ipc. Consultas al 49 12 14 64. Inmobiliaria jorge miguel encuentre nuestro telefono en\nContactar", "revised": false, "rejected": false, "data": {"precio": "$ 400.000 + $45.000 expensas", "expensas": "+ $45.000 expensas", "direccion": "Castro Barros 2200", "metros": "65 m\u00b2 cubie.", "habitaciones": "2 dorm."}, "image": "https://static1.sosiva451.com/58619451/f3e671b4-870d-4d5d-9edd-d6105b2af768_u_small.jpg", "title": "3 Ambientes al Frente con Balcon"}}