{"https://www.argenprop.com/departamento-en-alquiler-en-almagro-3-ambientes--15655396": {"id": "19072193", "date": "07-05-2024\n", "index": 2, "content": "1\n/11\n0\n$ 450.000 + $51.000 expensas\nHipolito Yrigoyen 4200\nDepartamento en Alquiler en Almagro, Capital Federal\n62 m\u00b2 cubie.\n2 dorm.\n50 a\u00f1os\nAlquiler 3 ambientes contra frente Sin Balc\u00f3n Sin Mascotas\nMuy buen departamento en alquiler de 3 ambientes al contra frente sin balc\u00f3n - ubicado a 1 cuadra de avenida rivadavi y a dos cuadras de avenida la plata todos los medios de transportes piso de parquet - puerta blindada pent\u00e1gono - living comedor con gran ventanal con sus cortinas y ventilador de techo con apliques y espejo empotrado en pared cocina c\u00f3moda con muebles completos lavadero\nContactar", "revised": false, "rejected": false, "data": {"precio": "$ 450.000 + $51.000 expensas", "expensas": "+ $51.000 expensas", "direccion": "Hipolito Yrigoyen 4200", "metros": "62 m\u00b2 cubie.", "habitaciones": "2 dorm."}, "image": "https://static1.sosiva451.com/69355651/63b13a01-e6e0-4bb7-af28-986db6160c70_u_small.jpg", "title": "Alquiler 3 ambientes contra frente Sin Balc\u00f3n Sin Mascotas"}, "https://www.argenprop.com/departamento-en-alquiler-en-parque-centenario-3-ambientes--15520552": {"id": "18946422", "date": "07-05-2024\n", "index": 4, "content": "1\n/7\n0\n$ 350.000 + $110.000 expensas\nEUSTOQUI FRIAS GRAL 200\nDepartamento en Alquiler en Parque Centenario, Capital Federal\n61 m\u00b2 cubie.\n2 dorm.\n45 a\u00f1os\nDepartamento de 3 ambientes en Alquiler en P.centenario\nDepartamento de 3 ambientes en alquiler en parque centenario\nWhatsApp\nContactar", "revised": false, "rejected": false, "data": {"precio": "$ 350.000 + $110.000 expensas", "expensas": "+ $110.000 expensas", "direccion": "EUSTOQUI FRIAS GRAL 200", "metros": "61 m\u00b2 cubie.", "habitaciones": "2 dorm."}, "image": "https://static1.sosiva451.com/25502551/ee04c801-308a-4c0b-9e38-9ec2c67441b9_u_small.jpg", "title": "Departamento de 3 ambientes en Alquiler en P.centenario "}, "https://www.argenprop.com/departamento-en-alquiler-en-almagro-4-ambientes--15621362": {"id": "19038317", "date": "07-05-2024\n", "index": 8, "content": "1\n/16\n0\n$ 550.000 + $90.000 expensas\nSARMIENTO 4300\nDepartamento en Alquiler en Almagro, Capital Federal\n90 m\u00b2 cubie.\n3 dorm.\n40 a\u00f1os\nDepartamento de 4 ambientes en Alquiler en Almagro\nDepartamento de 4 ambientes con dependencia, en alquiler. Al frente, con balcon. Luminoso. Semipiso. Muy buena superficie. Cerca avdas. Corrientes, medrano, diaz velez. Subte, colectivos. Parque centenario, hospital italiano. Comercializa migliorisi de corrientes 4599 srl profesional responsable jorge daniel gomez cpi 261 a30101 se deja constancia que las caracteristicas, medidas, expensas y\nWhatsApp\nContactar", "revised": false, "rejected": false, "data": {"precio": "$ 550.000 + $90.000 expensas", "expensas": "+ $90.000 expensas", "direccion": "SARMIENTO 4300", "metros": "90 m\u00b2 cubie.", "habitaciones": "3 dorm."}, "image": "https://static1.sosiva451.com/26312651/ddc9ec09-250b-4e20-afaf-c06132eba34b_u_small.jpg", "title": "Departamento de 4 ambientes en Alquiler en Almagro "}, "https://www.argenprop.com/departamento-en-alquiler-en-almagro-4-ambientes--15652825": {"id": "19069624", "date": "07-05-2024\n", "index": 11, "content": "1\n/19\n0\n$ 520.000 + $92.000 expensas\nPanama al 900\nDepartamento en Alquiler en Almagro, Capital Federal\n70 m\u00b2 cubie.\n3 dorm.\nA Estrenar\nDepartamento en Almagro\nComodo departamento de 4 ambientes a media cuadra de av corrientes al 4600. En piso 10a con vista abierta cuenta con tres habitaciones, un ba\u00f1o completo, cocina separada con lavadero, living comendor con balc\u00f3n y toilete de recepci\u00f3n. Edificio con dos ascensores. Comercializa gomez servicios inmobiliarios cucicba mat. 7397 cmcpsi mat. 6629 realizamos tasaciones en caba, gba norte.\nWhatsApp\nContactar", "revised": false, "rejected": false, "data": {"precio": "$ 520.000 + $92.000 expensas", "expensas": "+ $92.000 expensas", "direccion": "Panama al 900", "metros": "70 m\u00b2 cubie.", "habitaciones": "3 dorm."}, "image": "https://static1.sosiva451.com/52825651/5bf9a40c-0cc4-45eb-8a06-aa11fd677c2b_u_small.jpg", "title": "Departamento en Almagro"}, "https://www.argenprop.com/departamento-en-alquiler-en-boedo-3-ambientes--15654094": {"id": "19070894", "date": "07-05-2024\n", "index": 12, "content": "1\n/16\n0\n$ 480.000 + $40.000 expensas\nCastro Barros al 900\nDepartamento en Alquiler en Boedo, Capital Federal\n60 m\u00b2 cubie.\n2 dorm.\n20 a\u00f1os\nDepartamento en Alquiler\nSe trata de un departamento de 3 ambientes al frente con balc\u00f3n. Orientaci\u00f3n este, muy luminoso, muy buena vista. Amplio living, ba\u00f1o completo, cocina con muebles completos, lavadero incorporado, dormitorios con placard. Muy buen estado. No se aceptan mascotas. Ll 111 condiciones y requisitos - 1 mes por adelantado + 1 mes deposito (igual al valor del primer mes) - garant\u00eda -el monto de\nWhatsApp\nContactar", "revised": false, "rejected": false, "data": {"precio": "$ 480.000 + $40.000 expensas", "expensas": "+ $40.000 expensas", "direccion": "Castro Barros al 900", "metros": "60 m\u00b2 cubie.", "habitaciones": "2 dorm."}, "image": "https://static1.sosiva451.com/49045651/d27b2ae6-f8b3-4412-83cf-9360cf83b594_u_small.jpg", "title": "Departamento en  Alquiler"}, "https://www.argenprop.com/ph-en-alquiler-en-almagro-4-ambientes--15653850": {"id": "19070649", "date": "07-05-2024\n", "index": 14, "content": "1\n/13\n0\n$ 650.000\nZelaya al 3100\nPH en Alquiler en Almagro, Capital Federal\n90 m\u00b2 cubie.\n3 dorm.\n70 a\u00f1os\nPH en Almagro\nAlquiler 4 ambientes ph con terraza, amueblado sin expensas excelente ph t/casa en almagro alquiler 4 ambientes ph con terraza, amueblado sin expensas! Excelente ph / casa con patio y terraza en una ubicaci\u00f3n estrat\u00e9gica, sobre el pasaje zelaya al 3100, a 1 cuadra del shopping abasto y del subte l\u00ednea \"b\", a 3 cuadras de av. C\u00f3rdoba, a 6 cuadras del subte d, a solo\nContactar", "revised": false, "rejected": false, "data": {"precio": "$ 650.000", "direccion": "Zelaya al 3100", "metros": "90 m\u00b2 cubie.", "habitaciones": "3 dorm."}, "image": "https://static1.sosiva451.com/05835651/92701f34-b91b-43db-8d18-53bbe266bdd0_u_small.jpg", "title": "PH en Almagro"}, "https://www.argenprop.com/departamento-en-alquiler-en-villa-crespo-3-ambientes--15541574": {"id": "18967493", "date": "07-05-2024\n", "index": 16, "content": "1\n/23\n176\n$ 550.000\nLavalleja 200\nDepartamento en Alquiler en Villa Crespo, Capital Federal\n70 m\u00b2 cubie.\n2 dorm.\n1 ba\u00f1o\nDepartamento en alquiler de 2 dormitorios en Villa Crespo\nLibre ya ! Lo maneja leo oportuinidad retasado almagro, 3 amb, 70m,, lavalleja 200, $550.000 x mes garant\u00eda de capital o seguro de cauci\u00f3n justificaci\u00f3n de ingresos m\u00e1ximo 3 personas no mascotas departamento en alquiler en villa crespo, capital federal, ubicado en lavalleja. Esta exclusiva propiedad de 3 ambientes cuenta con 2 dormitorios, 1 ba\u00f1o y una cocina equipada. Con una\nWhatsApp\nContactar", "revised": false, "rejected": false, "data": {"precio": "$ 550.000", "direccion": "Lavalleja 200", "metros": "70 m\u00b2 cubie.", "habitaciones": "2 dorm."}, "image": "https://static1.sosiva451.com/47514551/48535fc4-aee3-4623-9c09-c98ef9032b9d_u_small.jpg", "title": "Departamento en alquiler de 2 dormitorios en Villa Crespo"}, "https://www.argenprop.com/departamento-en-alquiler-en-almagro-3-ambientes--15541575": {"id": "18967494", "date": "07-05-2024\n", "index": 17, "content": "1\n/23\n721\n$ 600.000\nLavalleja 200\nDepartamento en Alquiler en Almagro, Capital Federal\n70 m\u00b2 cubie.\n2 dorm.\n1 ba\u00f1o\nDepartamento en alquiler de 2 dormitorios en Villa Crespo\nLibre ya ! Lo maneja leo oportuinidad retasado almagro, 3 amb, 70m,, lavalleja 200, $550.000 x mes garant\u00eda de capital o seguro de cauci\u00f3n justificaci\u00f3n de ingresos m\u00e1ximo 3 personas no mascotas departamento en alquiler en villa crespo, capital federal, ubicado en lavalleja. Esta exclusiva propiedad de 3 ambientes cuenta con 2 dormitorios, 1 ba\u00f1o y una cocina equipada. Con una\nWhatsApp\nContactar", "revised": false, "rejected": false, "data": {"precio": "$ 600.000", "direccion": "Lavalleja 200", "metros": "70 m\u00b2 cubie.", "habitaciones": "2 dorm."}, "image": "https://static1.sosiva451.com/57514551/91adf8c8-f9a6-4f7c-bf1f-6520400de899_u_small.jpg", "title": "Departamento en alquiler de 2 dormitorios en Villa Crespo"}, "https://www.argenprop.com/departamento-en-alquiler-en-villa-crespo-3-ambientes--15648123": {"id": "19064920", "date": "07-05-2024\n", "index": 20, "content": "1\n/19\n1\n$ 450.000\nLuis drago 200\nDepartamento en Alquiler en Villa Crespo, Capital Federal\n65 m\u00b2 cubie.\n2 dorm.\n1 ba\u00f1o\nAlquiler de tres ambientes muy luminoso\nHermoso de departamento de tres ambientes muy lluminoso con lavadero medidas aproximadas contacto transportes cercanos colectivos:15, 19, 24, 36, 55, 57, 65, 71, 76, 90, 92, 99, 105, 106, 109, 110, 119, 124, 127, 141, 146 subtes (metro):malabia (l\u00ednea b) datos \u00fatiles barrio:villa crespo comuna:comuna 15 \u00e1rea hospitalaria:htal. Dr. C.G. Durand - kp322030 - kpd050710 - - publicado v\u00eda\nContactar", "revised": false, "rejected": false, "data": {"precio": "$ 450.000", "direccion": "Luis drago 200", "metros": "65 m\u00b2 cubie.", "habitaciones": "2 dorm."}, "image": "https://static1.sosiva451.com/32184651/aa0ad647-a256-4a6d-b05f-1e07868a2b89_u_small.jpg", "title": "Alquiler de tres ambientes muy luminoso"}, "https://www.argenprop.com/departamento-en-alquiler-en-parque-centenario-3-ambientes--11626664": {"id": "15118715", "date": "07-05-2024\n", "index": 22, "content": "1\n/13\n31\n$ 550.000 + $150.000 expensas\nOtamendi 600, Piso 2\nDepartamento en Alquiler en Parque Centenario, Capital Federal\n75 m\u00b2 cubie.\n2 dorm.\n53 a\u00f1os\n3 AMB CON DEPENDENCIA-METROS PARQUE CENTENARIO\nDepartamento amplio, comodo y luminoso. A metros de parque centenario. Amplia variedad de medios de transporte living mitad alfombra mitad parquet. Mueble de cocina altos y bajos lugar para lavaropa (sin lavaropas) aire acondicionado no funciona se acepta seguro de cauci\u00f3n matricula: cpi n\u00b0: 2185 \"para los casos de alquiler de vivienda, el monto m\u00e1ximo de comisi\u00f3n que se le puede requerir a\nWhatsApp\nContactar", "revised": false, "rejected": false, "data": {"precio": "$ 550.000 + $150.000 expensas", "expensas": "+ $150.000 expensas", "direccion": "Otamendi 600, Piso 2", "metros": "75 m\u00b2 cubie.", "habitaciones": "2 dorm."}, "image": "https://static1.sosiva451.com/46662611/cb368ca7-8139-4d19-8ea9-b0f4770906f1_u_small.jpg", "title": "3 AMB CON DEPENDENCIA-METROS PARQUE CENTENARIO"}, "https://www.argenprop.com/departamento-en-alquiler-en-almagro-3-ambientes--15353337": {"id": "18788219", "date": "07-05-2024\n", "index": 23, "content": "1\n/16\n1\n$ 600.000 + $49.000 expensas\nSarmiento al 4600\nDepartamento en Alquiler en Almagro, Capital Federal\n65 m\u00b2 cubie.\n2 dorm.\n30 a\u00f1os\nDepartamento 3 ambientes con dependencias al frente con balcon - Almagro\nSemipiso de 3 ambientes con dependencias al frente, con aire luz y sol. Consta de living comedor, balc\u00f3n corrido, 2 dormitorios con placards, cocina con muebles altos y bajos, lavadero cubierto. Excelente ubicaci\u00f3n sarmiento 4600 esquina lambar\u00e9, proximo a parque centenario, avda. Corrientes, comercios, colectivos, subte b estaci\u00f3n angel gallardo. Pida tasaci\u00f3n: efectuada por profesionales, que\nContactar", "revised": false, "rejected": false, "data": {"precio": "$ 600.000 + $49.000 expensas", "expensas": "+ $49.000 expensas", "direccion": "Sarmiento al 4600", "metros": "65 m\u00b2 cubie.", "habitaciones": "2 dorm."}, "image": "https://static1.sosiva451.com/73335351/fe6accb6-ca49-45b8-b96b-81b644400dc4_u_small.jpg", "title": "Departamento 3 ambientes con dependencias al frente con balcon  - Almagro"}, "https://www.argenprop.com/departamento-en-alquiler-en-almagro-4-ambientes--15560013": {"id": "18976937", "date": "07-05-2024\n", "index": 25, "content": "1\n/28\n0\n$ 600.000 + $52.000 expensas\nLambare 1100, Piso 2\nDepartamento en Alquiler en Almagro, Capital Federal\n65 m\u00b2 cubie.\n3 dorm.\n50 a\u00f1os\nExcelente tres dormitorios en Almagro\nMuy buen departamento de tres dormitorios en excelente zona a metros de av corrientes. Subte b y todo se los medios de transporte, luminoso, living comedor con salida a balcon, tres dormitorios, ba\u00f1o y toilette, cocina con comedor d\u00edario y lavadero, segundo piso al frente, pisos de parquet. Condiciones mes adelantado mes de deposito y garant\u00eda caba o seguro de caucion, ajustes trimestrales por\nWhatsApp\nContactar", "revised": false, "rejected": false, "data": {"precio": "$ 600.000 + $52.000 expensas", "expensas": "+ $52.000 expensas", "direccion": "Lambare 1100, Piso 2", "metros": "65 m\u00b2 cubie.", "habitaciones": "3 dorm."}, "image": "https://static1.sosiva451.com/31006551/6b6f437c-063a-4902-bddc-c7b618c94d6a_u_small.jpg", "title": "Excelente tres dormitorios en Almagro"}, "https://www.argenprop.com/departamento-en-alquiler-en-almagro-3-ambientes--5984886": {"id": "9710815", "date": "07-05-2024\n", "index": 26, "content": "1\n/19\n150\n$ 550.000 + $58.000 expensas\nCOLOMBRES 100, Piso 5\nDepartamento en Alquiler en Almagro, Capital Federal\n47,79 m\u00b2 cubie.\n2 dorm.\n30 a\u00f1os\nDEPARTAMENTO EN BUEN ESTADO Y UBICACION, A.ACOND. S.U.M. FRENTE. TODO AIRE Y LUZ. PARQUET.\nDepartamento de tres ambientes muy conservado, con excelente iluminacion, buena ubicacion a pocos metros de la estaci\u00f3n castro barros, subte \"a\", locaci\u00f3n con o sin mobiliario. Pisos parquet y cer\u00e1micos. Aire acondicionado, edificio cuenta con s.U.M. Nota: \u201clas medidas son aproximadas y orientativas. Las medidas exactas surgir\u00edan del t\u00edtulo de propiedad\" \u201cpara los casos de alquiler de vivienda,\nWhatsApp\nContactar", "revised": false, "rejected": false, "data": {"precio": "$ 550.000 + $58.000 expensas", "expensas": "+ $58.000 expensas", "direccion": "COLOMBRES 100, Piso 5", "metros": "47,79 m\u00b2 cubie.", "habitaciones": "2 dorm."}, "image": "https://static1.sosiva451.com/6884895/a2b493c5-4059-4ea7-8e7b-a3aa8fc2f1da_u_small.jpg", "title": "DEPARTAMENTO EN BUEN ESTADO Y UBICACION, A.ACOND. S.U.M. FRENTE. TODO AIRE Y LUZ. PARQUET."}, "https://www.argenprop.com/departamento-en-alquiler-en-parque-centenario-4-ambientes--15518461": {"id": "18944327", "date": "07-05-2024\n", "index": 31, "content": "1\n/13\n100\n$ 480.000 + $60.000 expensas\nDiaz Velez 4500, Piso 5\nDepartamento en Alquiler en Parque Centenario, Capital Federal\n100 m\u00b2 cubie.\n3 dorm.\n40 a\u00f1os\nAlquiler 4 ambientes de Epoca Parque centenario\nDepartamento de \u00e9poca sin balc\u00f3n. Cuenta con 3 dormitorios, living de 6 x 3.5, cocina comedor , lavadero, ba\u00f1o y toilette disponible\nWhatsApp\nContactar", "revised": false, "rejected": false, "data": {"precio": "$ 480.000 + $60.000 expensas", "expensas": "+ $60.000 expensas", "direccion": "Diaz Velez 4500, Piso 5", "metros": "100 m\u00b2 cubie.", "habitaciones": "3 dorm."}, "image": null, "title": "Alquiler 4 ambientes de Epoca Parque centenario"}, "https://www.argenprop.com/departamento-en-alquiler-en-parque-centenario-3-ambientes--15601582": {"id": "19018508", "date": "07-05-2024\n", "index": 32, "content": "1\n/20\n1\n$ 470.000 + $53.000 expensas\nAVENIDA ANGEL GALLARDO 349 6 - B\nDepartamento en Alquiler en Parque Centenario, Capital Federal\n66 m\u00b2 cubie.\n2 dorm.\n48 a\u00f1os\nAMPLIO 3 AMBIENTES AL FRENTE CON BALCON FRENTE AL PARQUE CENTENARIO\nAmplio 3 ambientes con balcon - al frente - vista abierta al parque centenario cocina con lavadero independiente doble circulacion - puerta pentagono en comedor muy luminoso - buena ventilacion ambos dormitorios con placares - dormitorio principal con balcon frances frente al parque centenario - a 3 cuadras de avenida corrientes acceso a medios de transportes las medidas son aproximadas_ dorm.\nContactar", "revised": false, "rejected": false, "data": {"precio": "$ 470.000 + $53.000 expensas", "expensas": "+ $53.000 expensas", "direccion": "AVENIDA ANGEL GALLARDO 349 6 - B", "metros": "66 m\u00b2 cubie.", "habitaciones": "2 dorm."}, "image": "https://static1.sosiva451.com/28510651/e5500157-1dda-43ad-9d7b-0ec4cc7bdf95_u_small.jpg", "title": "AMPLIO 3 AMBIENTES AL FRENTE CON BALCON FRENTE AL PARQUE CENTENARIO"}, "https://www.argenprop.com/departamento-en-alquiler-en-almagro-4-ambientes--15151533": {"id": "18586630", "date": "07-05-2024\n", "index": 33, "content": "1\n/14\n0\n$ 540.000 + $85.000 expensas\nJunin 600\nDepartamento en Alquiler en Almagro, Capital Federal\n99 m\u00b2 cubie.\n3 dorm.\n25 a\u00f1os\nDepartamento - Almagro\nReservado departamento de 4 ambientes, torre, muy luminoso, 3 dormitorios con excelente vista, 2 vestidores, ba\u00f1o completo, toilette, living comedor con salida al balc\u00f3n, cocina completa muy luminosa . Reci\u00e9n pintado. Seguridad las 24 hs. - El valor de las expensas corresponde al \u00faltimo mes en curso, las mismas podr\u00e1n sufrir modificaciones de acuerdo el respectivo consorcio. -\nWhatsApp\nContactar", "revised": false, "rejected": false, "data": {"precio": "$ 540.000 + $85.000 expensas", "expensas": "+ $85.000 expensas", "direccion": "Junin 600", "metros": "99 m\u00b2 cubie.", "habitaciones": "3 dorm."}, "image": "https://static1.sosiva451.com/33515151/0b02e8b1-1e8c-40e2-91e9-0aa38a692863_u_small.jpg", "title": "Departamento - Almagro"}, "https://www.argenprop.com/departamento-en-alquiler-en-boedo-3-ambientes--15533948": {"id": "18959866", "date": "07-05-2024\n", "index": 34, "content": "1\n/15\n0\n$ 390.000 + $60.000 expensas\nMu\u00f1iz al 1100\nDepartamento en Alquiler en Boedo, Capital Federal\n60 m\u00b2 cubie.\n2 dorm.\n40 a\u00f1os\nDepartamento en Boedo\nDepartamento ubicado en boedo calle mu\u00f1iz esquina san juan a metros del subte e living comedor, 2 dormitorios ba\u00f1o y cocina completa, piso alto vista panor\u00e1mica super luminoso valor alquiler $ 390.000.-, Expensas $ 60.000., Abl $ 8.000.- Aysa $ 5.000.- Contrato 24 meses, incrementos trimestrales por inflaci\u00f3n. Requisitos: demostraci\u00f3n de\nWhatsApp\nContactar", "revised": false, "rejected": false, "data": {"precio": "$ 390.000 + $60.000 expensas", "expensas": "+ $60.000 expensas", "direccion": "Mu\u00f1iz al 1100", "metros": "60 m\u00b2 cubie.", "habitaciones": "2 dorm."}, "image": "https://static1.sosiva451.com/84933551/6b24ba6d-53b3-4cf0-8126-7c70454a0162_u_small.jpg", "title": "Departamento en Boedo"}, "https://www.argenprop.com/departamento-en-alquiler-en-almagro-4-ambientes--15604743": {"id": "19021681", "date": "07-05-2024\n", "index": 39, "content": "1\n/21\n252\n$ 600.000 + $50.000 expensas\nMedrano 300, Piso 5\nDepartamento en Alquiler en Almagro, Capital Federal\n75 m\u00b2 cubie.\n3 dorm.\n40 a\u00f1os\nDepartamento 4 ambientes luminoso con balc\u00f3n al contrafrente\nExcelente departamento tres ambientes con dependencia de servicio, living comedor con salida al balc\u00f3n 2 dormitorios con placard y salida al balc\u00f3n cocina con comedor diario habitaci\u00f3n de servicio, ba\u00f1o y entrada de servicio, lavadero. Muy buena ubicaci\u00f3n cerca de multiples negocios y medios de transportes. Aviso legal: excepto para alquileres temporales, el monto m\u00e1ximo de comisi\u00f3n que se le\nContactar", "revised": false, "rejected": false, "data": {"precio": "$ 600.000 + $50.000 expensas", "expensas": "+ $50.000 expensas", "direccion": "Medrano 300, Piso 5", "metros": "75 m\u00b2 cubie.", "habitaciones": "3 dorm."}, "image": "https://static1.sosiva451.com/34740651/b89d4cd5-5063-4d08-97c3-f7eeff14779f_u_small.jpg", "title": "Departamento 4 ambientes luminoso con balc\u00f3n al contrafrente"}, "https://www.argenprop.com/departamento-en-alquiler-en-almagro-3-ambientes--15522319": {"id": "18948186", "date": "07-05-2024\n", "index": 42, "content": "1\n/21\n0\n$ 600.000 + $30.000 expensas\nLezica 3900\nDepartamento en Alquiler en Almagro, Capital Federal\n73 m\u00b2 cubie.\n2 dorm.\n64 a\u00f1os\nDEPTO 3 AMB ALQUILER LEZICA AL 3900 ALMAGRO,CABA\nExcelente departamento/\u00fanico piso de categor\u00eda. Luminoso, bien ubicado, a cuadra de medrano y rivadvia. Todoslos transportes, subte,etc tiene doble acceso con puertas blindadas, por una de ellas se ingresa directamente al comedor diario, cocina y lavadero. Por la otra a un hall de recepci\u00f3n, living, dormitorio principal con amplio placard y balc\u00f3n al frente vista hermosa. El otro dormitorio con\nContactar", "revised": false, "rejected": false, "data": {"precio": "$ 600.000 + $30.000 expensas", "expensas": "+ $30.000 expensas", "direccion": "Lezica 3900", "metros": "73 m\u00b2 cubie.", "habitaciones": "2 dorm."}, "image": "https://static1.sosiva451.com/91322551/84cced33-8223-4444-8519-12f1086c3df6_u_small.jpg", "title": "DEPTO 3 AMB ALQUILER LEZICA AL 3900 ALMAGRO,CABA"}, "https://www.argenprop.com/departamento-en-alquiler-en-villa-crespo-3-ambientes--15633328": {"id": "19050285", "date": "07-05-2024\n", "index": 47, "content": "1\n/21\n1\n$ 550.000 + $86.000 expensas\nRamirez De Velasco, Juan al 500\nDepartamento en Alquiler en Villa Crespo, Capital Federal\n80 m\u00b2 cubie.\n2 dorm.\n40 a\u00f1os\nDepartamento en Villa Crespo\n3 ambientes al contra frente super luminoso. Consta de comodo living comedor con salida al balcon, 2 dormitorios con placards, ba\u00f1o y toillete, cocina con muebles altos y bajos, puerta blindada pent\u00e1gono, calefaccion por estufa. Excelente ubicacion velasco al 500 entre malabia y avda. R. S. Ortiz, colecitvos, subte b estaci\u00f3n malabia, comercios. Visitas combinar 24 hs antes\nContactar", "revised": false, "rejected": false, "data": {"precio": "$ 550.000 + $86.000 expensas", "expensas": "+ $86.000 expensas", "direccion": "Ramirez De Velasco, Juan al 500", "metros": "80 m\u00b2 cubie.", "habitaciones": "2 dorm."}, "image": "https://static1.sosiva451.com/82333651/070f9f33-d33f-4d2e-a342-22b3ccf26ab7_u_small.jpg", "title": "Departamento en Villa Crespo"}, "https://www.argenprop.com/departamento-en-alquiler-en-villa-crespo-3-ambientes--15638644": {"id": "19055596", "date": "07-05-2024\n", "index": 48, "content": "1\n/9\n2\n$ 490.000 + $25.000 expensas\nSerrano al 800\nDepartamento en Alquiler en Villa Crespo, Capital Federal\n70 m\u00b2 cubie.\n2 dorm.\n98 a\u00f1os\nAlquiler 3 ambientes en Villa Crespo\nAlquiler hermoso departamento en villa crespo. Departamento en edificio de estilo ubicado al frente, sobre calle serrano esquina loyola. El departamento cuenta con dos dormitorios amplios con pisos de pinoteas pulidos y plastificados, living con pisos de pinotea, distribuidor con pisos de cemento alisado, dos ba\u00f1o, uno completo y un toilette, cocina con barra desayunador.\nWhatsApp\nContactar", "revised": false, "rejected": false, "data": {"precio": "$ 490.000 + $25.000 expensas", "expensas": "+ $25.000 expensas", "direccion": "Serrano al 800", "metros": "70 m\u00b2 cubie.", "habitaciones": "2 dorm."}, "image": "https://static1.sosiva451.com/44683651/0479cdd5-20d4-4e57-a612-6a04f86a2d15_u_small.jpg", "title": "alquiler 3 ambientes en Villa Crespo"}, "https://www.argenprop.com/departamento-en-alquiler-en-almagro-3-ambientes--15645655": {"id": "19062602", "date": "07-05-2024\n", "index": 52, "content": "922\n$ 700.000 + $120.000 expensas\nRAWON 100, Piso 3\nDepartamento en Alquiler en Almagro, Capital Federal\n60,89 m\u00b2 cubie.\n2 dorm.\n16 a\u00f1os\nAL FRENTE CON BALCON IMPECABLE 3 AMBIENTES CON COCHERA\nWhatsApp\nContactar", "revised": false, "rejected": false, "data": {"precio": "$ 700.000 + $120.000 expensas", "expensas": "+ $120.000 expensas", "direccion": "RAWON 100, Piso 3", "metros": "60,89 m\u00b2 cubie.", "habitaciones": "2 dorm."}, "image": "https://www.argenprop.com/content/images/listing-camera.svg", "title": "AL FRENTE CON BALCON IMPECABLE 3 AMBIENTES CON COCHERA"}, "https://www.argenprop.com/departamento-en-alquiler-en-almagro-4-ambientes--5827366": {"id": "9552725", "date": "07-05-2024\n", "index": 57, "content": "1\n/28\n175\n$ 630.000 + $63.000 expensas\nAv Belgrano 3500, Piso 1\nDepartamento en Alquiler en Almagro, Capital Federal\n90 m\u00b2 cubie.\n3 dorm.\n40 a\u00f1os\nPiso de 4 ambientes al frente con balc\u00f3n corrido y patio\nMuy buen piso, frente orientado al norte, balc\u00f3n corrido con protector de red y buena vista. Es un inmueble t\u00edpico de la d\u00e9cada del 70, con pisos de escalla de m\u00e1rmol en el living comedor, cortinas tipo barrio (la del living el\u00e9ctrica), azulejos de color en el ba\u00f1o principal, etc. La cocina comedor es muy amplia con muebles sobre y bajo mesada de 17 puertas amplias, artefacto de cocina domec de\nWhatsApp\nContactar", "revised": false, "rejected": false, "data": {"precio": "$ 630.000 + $63.000 expensas", "expensas": "+ $63.000 expensas", "direccion": "Av Belgrano 3500, Piso 1", "metros": "90 m\u00b2 cubie.", "habitaciones": "3 dorm."}, "image": "https://static1.sosiva451.com/6637285/b98f2b46-abef-4171-8fba-4dc7cb184354_u_small.jpg", "title": "piso de 4 ambientes al frente con balc\u00f3n corrido y patio"}, "https://www.argenprop.com/departamento-en-alquiler-en-villa-crespo-4-ambientes--15640882": {"id": "19057833", "date": "07-05-2024\n", "index": 58, "content": "1\n/7\n200\n$ 600.000 + $150.000 expensas\nAr\u00e1oz 300, Piso 2\nDepartamento en Alquiler en Villa Crespo, Capital Federal\n83 m\u00b2 cubie.\n3 dorm.\n40 a\u00f1os\nDEPARTAMENTO 4 AMBIENTES CON BALC\u00d3N AL FRENTE EN ALQUILER\nDepartamento 4 ambientes en alquielr living comedor tres dormitorios ba\u00f1o completo toilette cocina lavadero balc\u00f3n a doscientos metros estacion malabia subte linea b la propiedad se va entregar reci\u00e9n pintada y con pisos pulidos requisitos: demostraci\u00f3n ingresos.Garant\u00eda propietaria de caba o seguro de caucion aprobado de\nWhatsApp\nContactar", "revised": false, "rejected": false, "data": {"precio": "$ 600.000 + $150.000 expensas", "expensas": "+ $150.000 expensas", "direccion": "Ar\u00e1oz 300, Piso 2", "metros": "83 m\u00b2 cubie.", "habitaciones": "3 dorm."}, "image": "https://static1.sosiva451.com/28804651/dce95978-e37e-47ba-bfbb-f37ed1cad554_u_small.jpg", "title": "DEPARTAMENTO 4 AMBIENTES CON BALC\u00d3N AL FRENTE EN ALQUILER"}, "https://www.argenprop.com/departamento-en-alquiler-en-almagro-3-ambientes--15520222": {"id": "18946092", "date": "07-05-2024\n", "index": 59, "content": "1\n/7\n175\n$ 380.000 + $90.000 expensas\nDon Bosco 3600, Piso 5\nDepartamento en Alquiler en Almagro, Capital Federal\n60 m\u00b2 cubie.\n2 dorm.\n50 a\u00f1os\nBUEN DEPARTAMENTO DE 3 AMBS AL FRENTE\nEe trata de un muy buendepartamento de 3 ambientes en muy buena ubicacion. Al tratarse de un edificio en esquina, todos los ambientes son externos, por lo que se trata de una unidad muy luminosa y ventilada. Los pisos de living y dormitorios son de parquet y ambos cuentan con placard. El estado general tanto del edificio como de la unidad es bueno. La ubicaci\u00f3n es muy buena ya que se encuentra a\nWhatsApp\nContactar", "revised": false, "rejected": false, "data": {"precio": "$ 380.000 + $90.000 expensas", "expensas": "+ $90.000 expensas", "direccion": "Don Bosco 3600, Piso 5", "metros": "60 m\u00b2 cubie.", "habitaciones": "2 dorm."}, "image": "https://static1.sosiva451.com/22202551/b8397a85-e771-42e9-aca1-a05c1fec2526_u_small.jpg", "title": "BUEN DEPARTAMENTO DE 3 AMBS AL FRENTE "}, "https://www.argenprop.com/departamento-en-alquiler-en-almagro-3-ambientes--15637524": {"id": "19054479", "date": "08-05-2024\n", "index": 60, "content": "1\n/27\n2.151\n$ 590.000 + $40.753 expensas\nAvenida Estado De Israel 4200, Piso 5\nDepartamento en Alquiler en Almagro, Capital Federal\n64 m\u00b2 cubie.\n2 dorm.\n2 ba\u00f1os\nSEMIPISO 5to. BALC\u00d3N AL FRENTE en ESQUINA, expensas ABRIL $ 48.700, SIN ABL, 2 ba\u00f1os, lavadero\nAlquiler semipiso todo al frente en esquina, 3 y 1/2 ambientes, amplio balc\u00f3n, ba\u00f1o completo m\u00e1s ba\u00f1o de servicio, muy bajas expensas $ 48.700 abril 2024 - no se paga abl (a cargo del due\u00f1o) muy luminoso departamento en semipiso de tres ambientes: con balc\u00f3n y vista abierta al frente hacia las esquinas - dos dormitorios superficie total: 64 m2. (Como corresponde, en esta superficie no\nWhatsApp\nContactar", "revised": false, "rejected": false, "data": {"precio": "$ 590.000 + $40.753 expensas", "expensas": "+ $40.753 expensas", "direccion": "Avenida Estado De Israel 4200, Piso 5", "metros": "64 m\u00b2 cubie.", "habitaciones": "2 dorm."}, "image": "https://static1.sosiva451.com/42573651/0d27c423-4a2c-4f43-bb33-15c7f6c06b2f_u_small.jpg", "title": "SEMIPISO 5to. BALC\u00d3N AL FRENTE en ESQUINA, expensas ABRIL $ 48.700, SIN ABL, 2 ba\u00f1os, lavadero "}}