{"https://www.argenprop.com/departamento-en-alquiler-en-villa-general-mitre-2-ambientes--15665831": {"id": "19082621", "date": "16-05-2024\n", "index": 2, "content": "1\n/23\n462\n$ 300.000 + $65.000 expensas\nMAGARI\u00d1OS CERVANTES 1800, Piso 6\nDepartamento en Alquiler en Villa General Mitre, Capital Federal\n40 m\u00b2 cubie.\n1 dorm.\n2 ambientes\nDEPARTAMENTO DOS AMBIENTES CON BALCON\nDisponible departamento dos ambientes con balcon al frente. Muy luminoso. Un dormitorio con placard, pisos en parquet. Living comedor pisos en parquet platificado cocina con bajo mesadas y alacena. Espacio para instalar lavarropas. Ba\u00f1o completo con ba\u00f1era y espejo. El departamento se encuentra en impecable estado y fue recientemente pintado el edificio cuenta con generador el\u00e9ctrico propio para\nContactar", "revised": false, "rejected": false, "data": {"precio": "$ 300.000 + $65.000 expensas", "expensas": "+ $65.000 expensas", "direccion": "MAGARI\u00d1OS CERVANTES 1800, Piso 6", "metros": "40 m\u00b2 cubie.", "habitaciones": "1 dorm."}, "image": "https://static1.sosiva451.com/13856651/f3d0f0f0-ce61-410b-9ab4-9776277f4598_u_small.jpg", "title": "DEPARTAMENTO DOS AMBIENTES CON BALCON"}, "https://www.argenprop.com/departamento-en-alquiler-en-velez-sarsfield-2-ambientes--15598492": {"id": "19015414", "date": "16-05-2024\n", "index": 3, "content": "1\n/18\n2\n$ 220.000 + $33.100 expensas\nDr S Segurola 200, Piso 3\nDepartamento en Alquiler en Velez Sarsfield, Capital Federal\n43 m\u00b2 cubie.\n1 dorm.\n1 ba\u00f1o\n2Amb M.Bueno Amplio Gran cocina+lavadero independiente Importante L/Comedor+Opci\u00f3n Cochera cubierta\nBarrio velez sarsfield propiamente floresta edificio en esquina de buen estilo cerca a av. Avellaneda - gaona - rivadavia - zona de comercios y vivienda familiar t\u00edpicas de la zona. - 2 ambientes de caracter\u00edsticas grandes lateral vista interna semiluminosos con importante living comedor, con puerta balc\u00f3n (tipo franc\u00e9s), pasillo intimo que comunica a dormitorio muy amplio con grandes placard,\nWhatsApp\nContactar", "revised": true, "rejected": false, "data": {"precio": "$ 220.000 + $33.100 expensas", "expensas": "+ $33.100 expensas", "direccion": "Dr S Segurola 200, Piso 3", "metros": "43 m\u00b2 cubie.", "habitaciones": "1 dorm."}, "image": "https://static1.sosiva451.com/29489551/ea7240c7-c680-4b1c-af60-67b0ef7768a7_u_small.jpg", "title": "2Amb M.Bueno Amplio Gran cocina+lavadero independiente Importante L/Comedor+Opci\u00f3n Cochera cubierta "}, "https://www.argenprop.com/departamento-en-alquiler-en-floresta-2-ambientes--15598486": {"id": "19015408", "date": "16-05-2024\n", "index": 4, "content": "1\n/18\n2\n$ 220.000 + $33.100 expensas\nDr S Segurola 200, Piso 3\nDepartamento en Alquiler en Floresta, Capital Federal\n43 m\u00b2 cubie.\n1 dorm.\n1 ba\u00f1o\n2Amb M.Bueno Amplio Gran cocina+lavadero independiente Importante L/Comedor+Opci\u00f3n Cochera cubierta\nVisitas a convenir en breve por disponibilidad barrio velez sarsfield propiamente floresta edificio en esquina de buen estilo cerca a av. Avellaneda - gaona - rivadavia - zona de comercios y vivienda familiar t\u00edpicas de la zona. - 2 ambientes de caracter\u00edsticas grandes lateral vista interna semiluminosos con importante living comedor, con puerta balc\u00f3n (tipo franc\u00e9s), pasillo intimo que\nWhatsApp\nContactar", "revised": false, "rejected": true, "data": {"precio": "$ 220.000 + $33.100 expensas", "expensas": "+ $33.100 expensas", "direccion": "Dr S Segurola 200, Piso 3", "metros": "43 m\u00b2 cubie.", "habitaciones": "1 dorm."}, "image": "https://static1.sosiva451.com/68489551/c13dd966-bb99-47ab-93c7-efc099f5e937_u_small.jpg", "title": "2Amb M.Bueno Amplio Gran cocina+lavadero independiente Importante L/Comedor+Opci\u00f3n Cochera cubierta "}, "https://www.argenprop.com/departamento-en-alquiler-en-floresta-norte-2-ambientes--15597697": {"id": "19014619", "date": "16-05-2024\n", "index": 10, "content": "1\n/23\n2\n$ 280.000 + $48.000 expensas\nSegurola 200, Piso 12\nDepartamento en Alquiler en Floresta Norte, Floresta\n40 m\u00b2 cubie.\n1 dorm.\n48 a\u00f1os\nExcelente dpto 2 ambientes, todo sol -Im-Pe-ca-ble\nExcelente dto. De 2 amb. Amplios . Ideal 2 personas- luz y sol- detalles: duracion de contrato 2 a\u00f1os- ajuste semestral x ipc .- Garantia real o seguro de cauci\u00f3n .- Ingresos comprobables. - Para ingresar un mes dep\u00f3sito y el mes de adelanto- gastos certificacion y pedidos de informes a cargo del inquilino\nWhatsApp\nContactar", "revised": false, "rejected": false, "data": {"precio": "$ 280.000 + $48.000 expensas", "expensas": "+ $48.000 expensas", "direccion": "Segurola 200, Piso 12", "metros": "40 m\u00b2 cubie.", "habitaciones": "1 dorm."}, "image": "https://static1.sosiva451.com/79679551/41070817-543b-49a5-9917-0151892a673c_u_small.jpg", "title": "Excelente dpto 2 ambientes, todo sol -Im-Pe-ca-ble"}, "https://www.argenprop.com/departamento-en-alquiler-en-floresta-2-ambientes--15584349": {"id": "19001276", "date": "16-05-2024\n", "index": 11, "content": "1\n/9\n1\n$ 280.000 + $25.000 expensas\nDolores 100, Piso 2\nDepartamento en Alquiler en Floresta, Capital Federal\n40 m\u00b2 cubie.\n1 dorm.\n40 a\u00f1os\nDepartamento en alquiler en Floresta\nAlquiler - departamento de dos ambientes - interno - cocina separada - living comedor - dormitorio con placard - ba\u00f1o completo con ducha. A metros de av. Rivadavia\nWhatsApp\nContactar", "revised": false, "rejected": false, "data": {"precio": "$ 280.000 + $25.000 expensas", "expensas": "+ $25.000 expensas", "direccion": "Dolores 100, Piso 2", "metros": "40 m\u00b2 cubie.", "habitaciones": "1 dorm."}, "image": "https://static1.sosiva451.com/94348551/0c57a071-23d0-422c-ae29-1e19e1b03e35_u_small.jpg", "title": "Departamento en alquiler en Floresta"}, "https://www.argenprop.com/departamento-en-alquiler-en-almagro-2-ambientes--15590015": {"id": "19006940", "date": "16-05-2024\n", "index": 16, "content": "1\n/12\n667\n$ 280.000 + $55.000 expensas\nAv. Rivadavia 4400, Piso 10\nDepartamento en Alquiler en Almagro, Capital Federal\n39 m\u00b2 cubie.\n1 dorm.\n1 ba\u00f1o\nRivadavia 4400\nDepartamento en alquiler. 39 m2. Almagro. Piso 10. Lateral con magn\u00edfica vista abierta, a av. Rivadavia. Dos ambientes. S\u00faper luminoso y soleado. Reci\u00e9n pintado. Excelente estdo, todo funcionando correctamente. Puerta blindada. Cocina y ba\u00f1o completos. Agua caliente central. Dormitorio con placard. Baulera y ropero. Vitroconvector, ventilador de techo. Pisos parquet. 3 ascensores automatizados.\nWhatsApp\nContactar", "revised": false, "rejected": true, "data": {"precio": "$ 280.000 + $55.000 expensas", "expensas": "+ $55.000 expensas", "direccion": "Av. Rivadavia 4400, Piso 10", "metros": "39 m\u00b2 cubie.", "habitaciones": "1 dorm."}, "image": "https://static1.sosiva451.com/51009551/9353e034-777c-4688-8528-7368d132330b_u_small.jpg", "title": "Rivadavia 4400"}, "https://www.argenprop.com/departamento-en-alquiler-en-balvanera-2-ambientes--15532925": {"id": "18958842", "date": "16-05-2024\n", "index": 21, "content": "1\n/14\n1\n$ 280.000 + $52.000 expensas\nRivadavia al 2200\nDepartamento en Alquiler en Balvanera, Capital Federal\n42 m\u00b2 cubie.\n1 dorm.\n45 a\u00f1os\nDepartamento - Balvanera\nAlquiler dos ambientes amplios lateral luminoso, vista a peque\u00f1o jard\u00edn del edificio, en piso 1o por ascensor , un dormitorio de 3x3,60mts con amplio placard, living-comedor de 5,60x3,50mts, cocina con lavadero incorporado de 4x1,80mts, un ba\u00f1o completo, y una baulera de 1x2x2,50mts. - Se alquila con algunos muebles vigilancia permanente - buen edificio es apto\nWhatsApp\nContactar", "revised": false, "rejected": true, "data": {"precio": "$ 280.000 + $52.000 expensas", "expensas": "+ $52.000 expensas", "direccion": "Rivadavia al 2200", "metros": "42 m\u00b2 cubie.", "habitaciones": "1 dorm."}, "image": "https://static1.sosiva451.com/52923551/f9d126e9-d90d-4dd7-b3e2-f74a2de9211e_u_small.jpg", "title": "Departamento - Balvanera"}, "https://www.argenprop.com/departamento-en-alquiler-en-flores-2-ambientes--5795231": {"id": "9520447", "date": "16-05-2024\n", "index": 22, "content": "1\n/11\n369\n$ 240.000 + $36.000 expensas\nYerbal 2700, Piso 1\nDepartamento en Alquiler en Flores, Capital Federal\n38 m\u00b2 cubie.\n1 dorm.\n40 a\u00f1os\nDepartamento de 2 ambientes en muy buen estado.\nDepartamento de 2 ambientes luminoso y bien ventilado posee living comedor de 4.20 x 2.90 con pisos de ceramicos, cocina de 3.30 x 1.50 con amoblaje bajo sobre mesada y lavadero incorporado, dormitorio de 3.40 x 2.90 con placard empotrado de doble hoja tambi\u00e9n con pisos de parquet y ventanal con vista hacia lateral, ba\u00f1o en suite completo con ba\u00f1era de 1.40 x 2 en correcto estado de\nWhatsApp\nContactar", "revised": false, "rejected": true, "data": {"precio": "$ 240.000 + $36.000 expensas", "expensas": "+ $36.000 expensas", "direccion": "Yerbal 2700, Piso 1", "metros": "38 m\u00b2 cubie.", "habitaciones": "1 dorm."}, "image": "https://static1.sosiva451.com/1325975/d5fbc1a9-a91b-45f8-9798-4326d6479b51_u_small.jpg", "title": "Departamento de 2 ambientes en muy buen estado."}, "https://www.argenprop.com/departamento-en-alquiler-en-flores-2-ambientes--15683606": {"id": "19100317", "date": "16-05-2024\n", "index": 23, "content": "1\n/16\n1.351\n$ 300.000\nAvenida Gaona 3600, Piso 8\nDepartamento en Alquiler en Flores, Capital Federal\n44 m\u00b2 cubie.\n1 dorm.\n40 a\u00f1os\nDepartamento 2 ambientes con balcon terraza.\nExcelente 2 ambientes al frente con balc\u00f3n terraza, cuenta con el siguiente detalle: living-comedor con pisos ceramicos de dimensiones de 5,45 x 2,48 y balc\u00f3n terraza de 8,00 x 2,00. -La cocina cuenta con mueble de bajo/sobre mesada y bacha de acero inoxidable con dimensiones de 3,37 x 1,72. - El lavadero es independiente y contiene pileta e instalacion para lavarropas. - El ba\u00f1o es completo con\nWhatsApp\nContactar", "revised": false, "rejected": true, "data": {"precio": "$ 300.000", "direccion": "Avenida Gaona 3600, Piso 8", "metros": "44 m\u00b2 cubie.", "habitaciones": "1 dorm."}, "image": "https://static1.sosiva451.com/60638651/3fabec31-6fc2-4858-b374-b7a4650ea386_u_small.jpg", "title": "Departamento 2 ambientes con balcon terraza."}, "https://www.argenprop.com/departamento-en-alquiler-en-floresta-2-ambientes--15684326": {"id": "19101036", "date": "16-05-2024\n", "index": 25, "content": "1\n/10\n0\n$ 290.000 + $30.000 expensas\nGualeguaychu al 2000\nDepartamento en Alquiler en Floresta, Capital Federal\n40 m\u00b2 cubie.\n1 dorm.\nA Estrenar\nDepartamento en alquiler\nUbicado sobre gualeguaychu al 2000 entre av alvarez jonte y lascano - pleno centro comercial de monte castro departamento 2 ambientes lateral living comedor cocina independiente hall distribuci\u00f3n dormitorio con placard ba\u00f1o completo edificio cuenta con estrada para discapacitaos, y terraza en comun alquiler $290.000.- Expensas $30.000.- ( El valor de las\nWhatsApp\nContactar", "revised": false, "rejected": false, "data": {"precio": "$ 290.000 + $30.000 expensas", "expensas": "+ $30.000 expensas", "direccion": "Gualeguaychu al 2000", "metros": "40 m\u00b2 cubie.", "habitaciones": "1 dorm."}, "image": "https://static1.sosiva451.com/62348651/fdc37d7a-a4fb-45b2-b077-4bbae3c1620a_u_small.jpg", "title": "Departamento en alquiler"}, "https://www.argenprop.com/departamento-en-alquiler-en-balvanera-2-ambientes--15673815": {"id": "19090608", "date": "16-05-2024\n", "index": 27, "content": "1\n/12\n2\n$ 210.000 + $35.000 expensas\nViamonte 2800, Piso 3\nDepartamento en Alquiler en Balvanera, Capital Federal\n35 m\u00b2 cubie.\n1 dorm.\n50 a\u00f1os\nExcelente ubicacion 2 Ambientes interno\nLiving 5,30 x 3,10 \u2013 dormitorios 3,00 x 3,10- cocina 4,80 x 1,70 agua caliente y calefaccion individual- ba\u00f1o con multifas antig\u00fcedad 50 a\u00f1os superficie 35 m2 expensas $ 35.000.- Precio $ 210.000 condiciones: un mes deposito \u2013 un mes adelantado \u2013 garantia propietaria en capital \u2013 informes garantia\nContactar", "revised": false, "rejected": true, "data": {"precio": "$ 210.000 + $35.000 expensas", "expensas": "+ $35.000 expensas", "direccion": "Viamonte 2800, Piso 3", "metros": "35 m\u00b2 cubie.", "habitaciones": "1 dorm."}, "image": "https://static1.sosiva451.com/51837651/21d60e6d-a58a-428e-87b8-fc2e38d5b45f_u_small.jpg", "title": "Excelente ubicacion 2 Ambientes interno"}, "https://www.argenprop.com/departamento-en-alquiler-en-almagro-2-ambientes--15397076": {"id": "18831971", "date": "16-05-2024\n", "index": 33, "content": "1\n/10\n0\n$ 300.000 + $30.000 expensas\nAvenida D\u00edaz V\u00e9lez 3700, Piso 4\nDepartamento en Alquiler en Almagro, Capital Federal\n40 m\u00b2 cubie.\n1 dorm.\n40 a\u00f1os\nDepartamento 2 ambientes zona Almagro\nHermoso departamento de 2 ambientes 4to piso c/fte con balc\u00f3n corrido -living comedor de 5 x 3 mts con modular, mesa con sillas y m\u00e1s comodidades -dormitorio de 3,10 x 3 mts con placard empotrado juego de dormitorio con colch\u00f3n nuevo - ba\u00f1o con ducha - cocina con mesa libro utensilios de cocina - lavadero independiente consultas: (no se aceptan mascotas) mariela alberto diego (solo\nWhatsApp\nContactar", "revised": false, "rejected": true, "data": {"precio": "$ 300.000 + $30.000 expensas", "expensas": "+ $30.000 expensas", "direccion": "Avenida D\u00edaz V\u00e9lez 3700, Piso 4", "metros": "40 m\u00b2 cubie.", "habitaciones": "1 dorm."}, "image": "https://static1.sosiva451.com/67079351/e5dc0cf0-ee92-4105-9907-88bd9893e1c9_u_small.jpg", "title": "Departamento 2 ambientes zona Almagro"}, "https://www.argenprop.com/departamento-en-alquiler-en-congreso-2-ambientes--15603643": {"id": "19020579", "date": "16-05-2024\n", "index": 39, "content": "1\n/1\n0\n$ 300.000 + $35.000 expensas\nRIVADAVIA 2300\nDepartamento en Alquiler en Congreso, Capital Federal\n45 m\u00b2 cubie.\n1 dorm.\n50 a\u00f1os\nDepartamento de 2 ambientes en Alquiler en Congreso\nEn alquiler, interesante 2 ambientes de generosa superficie. Ventilacion en todos los ambientes. Sobre avenida. Acceso a transporte a todas direcciones,por la zona. Amplio movimiento comercial,peatonal,vehicular. Comercializa corrientes 721894/..A28196 se deja constancia que las caracteristicas, medidas, expensas y superficies consignadas son aproximadas, sujetos a verificaci\u00f3n y/o ajuste. El\nWhatsApp\nContactar", "revised": false, "rejected": true, "data": {"precio": "$ 300.000 + $35.000 expensas", "expensas": "+ $35.000 expensas", "direccion": "RIVADAVIA 2300", "metros": "45 m\u00b2 cubie.", "habitaciones": "1 dorm."}, "image": "https://static1.sosiva451.com/34630651/7e6bde07-4c60-44dd-a743-7933d3eb358b_u_small.jpg", "title": "Departamento de 2 ambientes en Alquiler en Congreso "}, "https://www.argenprop.com/ph-en-alquiler-en-flores-2-ambientes--15682861": {"id": "19099571", "date": "16-05-2024\n", "index": 47, "content": "1\n/9\n0\n$ 300.000\nPergamino 1700\nPH en Alquiler en Flores, Capital Federal\n45 m\u00b2 cubie.\n1 dorm.\n1 ba\u00f1o\nAlquiler de departamento tipo casa de 2 ambientes en Flores.\nSe alquila casa en capital federal, en el barrio de flores. La propiedad tiene una superficie total de 50.00 metros cuadrados y consta de 2 ambientes, patio semicubierto y  ba\u00f1o. No cuenta con cochera. Se acepta la convivencia con mascotas. El valor de alquiler es de $300.000. (Qbm-qb1-568)\nWhatsApp\nContactar", "revised": false, "rejected": true, "data": {"precio": "$ 300.000", "direccion": "Pergamino 1700", "metros": "45 m\u00b2 cubie.", "habitaciones": "1 dorm."}, "image": "https://static1.sosiva451.com/16828651/a39f7628-9455-41ff-96ee-258161089aea_u_small.jpg", "title": "Alquiler de departamento tipo casa de 2 ambientes en Flores."}, "https://www.argenprop.com/departamento-en-alquiler-en-san-nicolas-2-ambientes--15613349": {"id": "19030293", "date": "16-05-2024\n", "index": 54, "content": "1\n/7\n500\n$ 300.000 + $76.000 expensas\nUruguay 800, Piso 1\nDepartamento en Alquiler en San Nicol\u00e1s, Centro\n35 m\u00b2 cubie.\n1 dorm.\n50 a\u00f1os\n3290ID- alquiler/venta 2 ambientes Uruguay 800 San Nicolas\nDepartamento de dos ambientes amoblados con quitchenette y ba\u00f1o completo. Interno, luz 8. Se alquila por 1 a\u00f1o con opci\u00f3n a m\u00e1s. Dos personas solas. Sin chicos y sin mascotas. Reajustable cada tres meses por el \u00edndice de precios al consumidor. Venta u$s 80.000\nWhatsApp\nContactar", "revised": false, "rejected": true, "data": {"precio": "$ 300.000 + $76.000 expensas", "expensas": "+ $76.000 expensas", "direccion": "Uruguay 800, Piso 1", "metros": "35 m\u00b2 cubie.", "habitaciones": "1 dorm."}, "image": "https://static1.sosiva451.com/94331651/42cf286a-2a9c-49a5-848b-5be186c5cfec_u_small.jpg", "title": "3290ID- alquiler/venta 2 ambientes Uruguay 800 San Nicolas"}, "https://www.argenprop.com/departamento-en-alquiler-en-almagro-norte-2-ambientes--15638402": {"id": "19055355", "date": "16-05-2024\n", "index": 60, "content": "1\n/6\n1\n$ 300.000\nTucuman 2800\nDepartamento en Alquiler en Almagro Norte, Almagro\n40 m\u00b2 cubie.\n1 dorm.\n30 a\u00f1os\n2 Ambientes, Tucuman 2801 Almagro\nCon una ubicaci\u00f3n privilegiada cerca de una variedad de servicios, tiendas, restaurantes y transporte p\u00fablico, este hogar ofrece conveniencia y accesibilidad para satisfacer todas tus necesidades, un espacio bien distribuido - kp321449 - kpd051510 - - publicado v\u00eda kiteprop crm inmobiliario.\nContactar", "revised": false, "rejected": false, "data": {"precio": "$ 300.000", "direccion": "Tucuman 2800", "metros": "40 m\u00b2 cubie.", "habitaciones": "1 dorm."}, "image": "https://static1.sosiva451.com/20483651/2c9a744b-619b-4af4-b647-edf62a421dd3_u_small.jpg", "title": "2 Ambientes, Tucuman 2801 Almagro"}, "https://www.argenprop.com/departamento-en-alquiler-en-almagro-2-ambientes--15633080": {"id": "19050037", "date": "16-05-2024\n", "index": 66, "content": "1\n/11\n0\n$ 300.000 + $38.000 expensas\nCamargo 700\nDepartamento en Alquiler en Almagro, Capital Federal\n42 m\u00b2 cubie.\n1 dorm.\n60 a\u00f1os\nDepartamento - Alquiler - Argentina, Capital Federal - Camargo 700\nAlquiler de departamento 2 ambientes en almagro, capital federal. Este departamento de 2 ambientes ubicado en el s\u00e9ptimo piso en almagro, capital federal, ofrece comodidad y funcionalidad en un espacio bien distribuido. Al ingresar, te encuentras con una cocina separada equipada con muebles de alacena y bajo mesada, perfecta para aquellos que disfrutan cocinar. Adem\u00e1s, cuenta con conexi\u00f3n para\nWhatsApp\nContactar", "revised": false, "rejected": false, "data": {"precio": "$ 300.000 + $38.000 expensas", "expensas": "+ $38.000 expensas", "direccion": "Camargo 700", "metros": "42 m\u00b2 cubie.", "habitaciones": "1 dorm."}, "image": "https://static1.sosiva451.com/08033651/9c55752c-3d7a-454c-bd6d-b4f22946ee9f_u_small.jpg", "title": "Departamento - Alquiler - Argentina, Capital Federal - Camargo 700"}, "https://www.argenprop.com/departamento-en-alquiler-en-floresta-2-ambientes--15619685": {"id": "19036637", "date": "16-05-2024\n", "index": 71, "content": "1\n/7\n1\n$ 280.000 + $45.000 expensas\nGoya 200, Piso 8\nDepartamento en Alquiler en Floresta, Capital Federal\n49 m\u00b2 cubie.\n1 dorm.\n50 a\u00f1os\n2 amb amplio lateral luminoso\n2 amb con gran living comedor con pisos de parquet, cocina independiente con instalacion de lavarropas, dormitorio con pisos de parquet y placard, ba\u00f1o completo. Se entrega con dos aires frio calor nuevos. Excelente ubicacion, a tan solo 1 cuadra av rivadavia, 2 de av segurola y cercano a centros comerciales varios contrato a 24meses, ajuste trimestral por icl requisitos mes de adelanto, dos\nWhatsApp\nContactar", "revised": false, "rejected": false, "data": {"precio": "$ 280.000 + $45.000 expensas", "expensas": "+ $45.000 expensas", "direccion": "Goya 200, Piso 8", "metros": "49 m\u00b2 cubie.", "habitaciones": "1 dorm."}, "image": "https://static1.sosiva451.com/58691651/c7a50228-bac7-41d8-b42e-88db0433d636_u_small.jpg", "title": "2 amb amplio lateral luminoso"}, "https://www.argenprop.com/departamento-en-alquiler-en-velez-sarsfield-2-ambientes--15601963": {"id": "19018890", "date": "16-05-2024\n", "index": 81, "content": "1\n/21\n4\n$ 300.000 + $34.404 expensas\nSegurola al 200\nDepartamento en Alquiler en Velez Sarsfield, Capital Federal\n40 m\u00b2 cubie.\n1 dorm.\n45 a\u00f1os\nDepartamento en Velez Sarsfield\nDepartamento 2 ambientes - segurola 294 - alquiler en el l\u00edmite de los barrios velez sarfield y floresta hall de ingreso living comedor amplio cocina comedor amplia lavadero separado hall \u00edntimo con placard ba\u00f1o completo dormitorio con placard el estado general es muy bueno pisos de parquet pulidos y plastificados (no acepta mascotas) pintado en su totalidad. Requisitos y\nWhatsApp\nContactar", "revised": false, "rejected": false, "data": {"precio": "$ 300.000 + $34.404 expensas", "expensas": "+ $34.404 expensas", "direccion": "Segurola al 200", "metros": "40 m\u00b2 cubie.", "habitaciones": "1 dorm."}, "image": "https://static1.sosiva451.com/36910651/d4d9866a-5ce2-405b-b114-51c46c72b16b_u_small.jpg", "title": "Departamento en Velez Sarsfield"}, "https://www.argenprop.com/departamento-en-alquiler-en-almagro-2-ambientes--15677956": {"id": "19094753", "date": "16-05-2024\n", "index": 88, "content": "1\n/11\n1\n$ 280.000 + $58.000 expensas\nLAVALLE 3700, Piso 8\nDepartamento en Alquiler en Almagro, Capital Federal\n35 m\u00b2 cubie.\n1 dorm.\n1 ba\u00f1o\nALQUILER 2 AMBIENTES\nAlquiler de departamento 2 ambientes en almagro, capital federal   departamento de 2 ambientes lateral muy luminoso, el mismo cuenta con living comedor, cocina separada, un dormitorio con placard y ba\u00f1o completo. Contrato por 24 meses, incremento cuatrimestral con \u00edndice ipc. Requisitos - un mes de adelanto y un mes de dep\u00f3sito  - garant\u00eda propietaria de caba o seguro de cauci\u00f3n - ingresos\nWhatsApp\nContactar", "revised": false, "rejected": false, "data": {"precio": "$ 280.000 + $58.000 expensas", "expensas": "+ $58.000 expensas", "direccion": "LAVALLE 3700, Piso 8", "metros": "35 m\u00b2 cubie.", "habitaciones": "1 dorm."}, "image": "https://static1.sosiva451.com/65977651/851b3d5f-4801-449e-a1f2-fb5be252fea2_u_small.jpg", "title": "ALQUILER 2 AMBIENTES "}, "https://www.argenprop.com/departamento-en-alquiler-en-floresta-2-ambientes--15677782": {"id": "19094579", "date": "16-05-2024\n", "index": 91, "content": "1\n/11\n0\n$ 240.000 + $45.000 expensas\nAV RIVADAVIA 8900\nDepartamento en Alquiler en Floresta, Capital Federal\n36 m\u00b2 cubie.\n1 dorm.\n1 ba\u00f1o\nAlquiler 2 ambientes floresta\nAlquiler de departamento en floresta, capital federal alquiler dos ambientes al frente piso 2 por escalera (en 60 dias ya funciona el ascensor) sobre av rivadavia 8966 excelente ubicaci\u00f3n cuenta con cocina integrada al living, un ba\u00f1o completo, un dormitorio, balcon y lavadero no dudes en contactarnos para agendar una visita fedele\nWhatsApp\nContactar", "revised": false, "rejected": true, "data": {"precio": "$ 240.000 + $45.000 expensas", "expensas": "+ $45.000 expensas", "direccion": "AV RIVADAVIA 8900", "metros": "36 m\u00b2 cubie.", "habitaciones": "1 dorm."}, "image": null, "title": "alquiler 2 ambientes floresta"}, "https://www.argenprop.com/departamento-en-alquiler-en-almagro-norte-2-ambientes--15619084": {"id": "19036036", "date": "16-05-2024\n", "index": 92, "content": "1\n/17\n1\n$ 300.000 + $48.000 expensas\nAv. Corrientes al 4500\nDepartamento en Alquiler en Almagro Norte, Almagro\n37 m\u00b2 cubie.\n1 dorm.\n40 a\u00f1os\nAlquiler Departamento 2 ambientes en Almagro Caba\nSe ofrece para alquilar departamento 2 ambientes , en un 4to piso , almagro living comedor amplio con ventanal al pulm\u00f3n del edificio, con orientaci\u00f3n norte. Pisos de madera, en todo el departamento. Habitaci\u00f3n con placard empotrado doble de pared a pared , ba\u00f1o completo , cocina independiente con mueble alto y bajo mesada, espacio\nWhatsApp\nContactar", "revised": false, "rejected": true, "data": {"precio": "$ 300.000 + $48.000 expensas", "expensas": "+ $48.000 expensas", "direccion": "Av. Corrientes al 4500", "metros": "37 m\u00b2 cubie.", "habitaciones": "1 dorm."}, "image": null, "title": "Alquiler Departamento 2 ambientes en Almagro Caba"}, "https://www.argenprop.com/departamento-en-alquiler-en-almagro-2-ambientes--15528254": {"id": "18954158", "date": "16-05-2024\n", "index": 102, "content": "1\n/8\n0\n$ 270.000 + $60.000 expensas\nMITRE, BARTOLOME 4400, Piso 1\nDepartamento en Alquiler en Almagro, Capital Federal\n35 m\u00b2 cubie.\n1 dorm.\n40 a\u00f1os\nImpecable 2 ambientes cercano a Hospital Italiano\nAlquiler de departamento 2 ambientes en almagro, capital federal. Su ubicacion: excelente  a una cuadra de av. Diaz v\u00e9lez y rio de janeiro, cercania a parque centenario, al hospital italiano, a tan solo 3 cuadras del subte linea \"a\" , zona con variedad de comercios y conexiones. El departamento: comoda unidad de 2 ambientes interno en impecable estado!, Sus ambientes ventilan al pulmon del\nWhatsApp\nContactar", "revised": false, "rejected": false, "data": {"precio": "$ 270.000 + $60.000 expensas", "expensas": "+ $60.000 expensas", "direccion": "MITRE, BARTOLOME 4400, Piso 1", "metros": "35 m\u00b2 cubie.", "habitaciones": "1 dorm."}, "image": "https://static1.sosiva451.com/45282551/0fff7f1e-6569-4fac-9fac-ced3a3adaa28_u_small.jpg", "title": "Impecable 2 ambientes cercano a Hospital Italiano"}, "https://www.argenprop.com/ph-en-alquiler-en-flores-2-ambientes--14126346": {"id": "17584121", "date": "16-05-2024\n", "index": 106, "content": "1\n/13\n0\n$ 300.000\nCnel J Terrada 1100, Piso PB\nPH en Alquiler en Flores, Capital Federal\n40 m\u00b2 cubie.\n1 dorm.\n60 a\u00f1os\nPH. POR PASILLO ,CON PATIO. Lateral Sin expensas.\nAntig\u00fcedad del edificio :60 a\u00f1os.(Aprox). Entre l.Viale y av.Gaona (al 3000) -departamento de 2 ambientes lateral por pasillo . (Tipo ph , con dormitorio muy amplio y patio con techo rebatible. ) , Ba\u00f1o y cocina. Sin expensas. Total de unidades : 5 -medidas: patio cubierto : 3.50 x 3.50m. Dormitorio: 4 m x 6 m( pisos madera) ,. Cocina: 2 m x 2 m (ventana ). Ba\u00f1o . -Superficie total 40 m2\nContactar", "revised": false, "rejected": true, "data": {"precio": "$ 300.000", "direccion": "Cnel J Terrada 1100, Piso PB", "metros": "40 m\u00b2 cubie.", "habitaciones": "1 dorm."}, "image": "https://static1.sosiva451.com/64362141/3e0dbf6f-87ca-4fc5-9acc-a58627794c35_u_small.jpg", "title": "PH. POR PASILLO ,CON PATIO. Lateral Sin expensas. "}, "https://www.argenprop.com/ph-en-alquiler-en-villa-general-mitre-2-ambientes--14126215": {"id": "17583990", "date": "16-05-2024\n", "index": 107, "content": "1\n/13\n0\n$ 300.000\nCnel J Terrada 1100, Piso PB\nPH en Alquiler en Villa General Mitre, Capital Federal\n40 m\u00b2 cubie.\n1 dorm.\n60 a\u00f1os\nPH. POR PASILLO , Con PATIO .Lateral Sin expensas.\nAntig\u00fcedad del edificio :60 a\u00f1os.(Aprox). Entre l.Viale y av.Gaona (al 3000) -departamento de 2 ambientes lateral por pasillo . (Tipo ph , con dormitorio muy amplio y patio con techo rebatible. ) , Ba\u00f1o y cocina. Sin expensas. Total de unidades : 5 -medidas: patio cubierto : 3.50 x 3.50m. Dormitorio: 4 m x 6 m( pisos madera) ,. Cocina: 2 m x 2 m (ventana ). Ba\u00f1o . -Superficie total 40 m2\nContactar", "revised": false, "rejected": true, "data": {"precio": "$ 300.000", "direccion": "Cnel J Terrada 1100, Piso PB", "metros": "40 m\u00b2 cubie.", "habitaciones": "1 dorm."}, "image": "https://static1.sosiva451.com/51262141/7f33bd54-12af-42f5-8240-1e7614925ea9_u_small.jpg", "title": "PH. POR PASILLO , Con PATIO .Lateral Sin expensas. "}, "https://www.argenprop.com/departamento-en-alquiler-en-monte-castro-2-ambientes--15596848": {"id": "19013771", "date": "16-05-2024\n", "index": 108, "content": "1\n/16\n0\nConsultar precio\nGualeguaych\u00fa 2000, Piso 1\nDepartamento en Alquiler en Monte Castro, Floresta\n44 m\u00b2 cubie.\n1 dorm.\n10 a\u00f1os\nDepartamento de 2 Ambientes, Sin Expensas!\nExcelente departamento de 2 ambientes muy luminoso en una ubicaci\u00f3n privilegiada. Ubicado en el contrafrente del edificio, proporciona tranquilidad y privacidad. Con dos balcones, ofreciendo una excelente ventilaci\u00f3n. La propiedad se destaca por no tener expensas, lo cual es una ventaja significativa. Adem\u00e1s, su luminosidad es excepcional, gracias a su dise\u00f1o que permite la entrada abundante de\nWhatsApp\nContactar", "revised": false, "rejected": true, "data": {"precio": "Consultar precio", "direccion": "Gualeguaych\u00fa 2000, Piso 1", "metros": "44 m\u00b2 cubie.", "habitaciones": "1 dorm."}, "image": "https://static1.sosiva451.com/84869551/c1779cfa-364c-4e45-9f2e-6110e4caa13b_u_small.jpg", "title": "Departamento de 2 Ambientes, Sin Expensas!"}, "https://www.argenprop.com/departamento-en-alquiler-en-almagro-2-ambientes--15595475": {"id": "19012395", "date": "16-05-2024\n", "index": 119, "content": "1\n/15\n83\n$ 300.000 + $34.000 expensas\nJos\u00e9 M\u00e1rmol 800, Piso 8\nDepartamento en Alquiler en Almagro, Capital Federal\n40 m\u00b2 cubie.\n1 dorm.\n50 a\u00f1os\nALQUILER - DEPARTAMENTO 2 AMBIENTES - SUBTE LINEA \"E\" - BAJAS EXPENSAS\nAlquiler departamento de 2 ambientes, lateral, reci\u00e9n pintado, muy luminoso. Expensas $34.000. Living comedor con piso de parquet plastificado, aire acondicionado fr\u00edo/calor y ventilador de techo. Dormitorio con placard, ventilador de techo y piso de parquet plastificado. Cocina completa con muebles bajo mesada y alacena. Lavadero independiente con mueble e instalaci\u00f3n para lavarropas ba\u00f1o\nWhatsApp\nContactar", "revised": false, "rejected": false, "data": {"precio": "$ 300.000 + $34.000 expensas", "expensas": "+ $34.000 expensas", "direccion": "Jos\u00e9 M\u00e1rmol 800, Piso 8", "metros": "40 m\u00b2 cubie.", "habitaciones": "1 dorm."}, "image": "https://static1.sosiva451.com/57459551/5f7cc058-0fa1-476b-bc77-1b353af6dd9b_u_small.jpg", "title": "ALQUILER - DEPARTAMENTO 2 AMBIENTES - SUBTE LINEA \"E\" - BAJAS EXPENSAS"}, "https://www.argenprop.com/departamento-en-alquiler-en-balvanera-2-ambientes--15635683": {"id": "19052643", "date": "16-05-2024\n", "index": 121, "content": "1\n/8\n0\n$ 260.000 + $38.000 expensas\nCatamarca al 200\nDepartamento en Alquiler en Balvanera, Capital Federal\n54 m\u00b2 cubie.\n1 dorm.\n50 a\u00f1os\nALQUILER DPTO 2 AMB EN BALVANERA\nDepartamento de 2 ambientes en alquiler alquiler $260.000.- Expensas $38.000.- Depto ubicado en un sexto piso, interno. Reci\u00e9n pintado. Totalmente el\u00e9ctrico. Al ingresar lo hacemos al comedor diarios, que nos conecta directamente con la cocina independiente y el lavadero. Desde el comedor tambi\u00e9n accedemos a la habitaci\u00f3n principal con placard y desde la misma tambi\u00e9n\nWhatsApp\nContactar", "revised": false, "rejected": false, "data": {"precio": "$ 260.000 + $38.000 expensas", "expensas": "+ $38.000 expensas", "direccion": "Catamarca al 200", "metros": "54 m\u00b2 cubie.", "habitaciones": "1 dorm."}, "image": "https://static1.sosiva451.com/38653651/196a61e9-07d6-433d-acd5-3cf21d4a347a_u_small.jpg", "title": "ALQUILER DPTO 2 AMB EN BALVANERA"}, "https://www.argenprop.com/departamento-en-alquiler-en-floresta-sur-2-ambientes--15674716": {"id": "19091509", "date": "16-05-2024\n", "index": 127, "content": "1\n/9\n0\n$ 240.000\nPergamino 100\nDepartamento en Alquiler en Floresta Sur, Floresta\n48 m\u00b2 cubie.\n1 dorm.\n2 ambientes\nALQUILER DPTO 2 AMB AL FRENTE C/BALCON EN FLORESTA\nAlquiler departamento de 2 amplios ambientes al frente con balcon, primer piso, sobre calle pergamino y ramon l. Falcon, con lavadero, muy buenas medidas, ba\u00f1o completo con ba\u00f1era, buen estado general. Para mayor informaci\u00f3n unicamente por whatsapp persona de contacto: daniel ramos \u201cpara los casos de alquiler de vivienda, el monto m\u00e1ximo de comisi\u00f3n que se le puede requerir a los propietarios\nWhatsApp\nContactar", "revised": true, "rejected": false, "data": {"precio": "$ 240.000", "direccion": "Pergamino 100", "metros": "48 m\u00b2 cubie.", "habitaciones": "1 dorm."}, "image": "https://static1.sosiva451.com/61747651/ad28ca73-9adb-427e-98fe-086653e101bf_u_small.jpg", "title": "ALQUILER DPTO 2 AMB AL FRENTE C/BALCON EN FLORESTA"}, "https://www.argenprop.com/departamento-en-alquiler-en-floresta-2-ambientes--15672397": {"id": "19089193", "date": "16-05-2024\n", "index": 135, "content": "1\n/19\n2\n$ 250.000 + $41.187 expensas\nMercedes 600, Piso 1\nDepartamento en Alquiler en Floresta, Capital Federal\n40 m\u00b2 cubie.\n1 dorm.\n50 a\u00f1os\nDepartamento 2 ambientes frente con balcon muy luminoso\nHermoso 2 ambientes frente con balcon muy luminoso. Requisitos: garantia propietaria o seguro de caucion ajuste cada 4 meses x icl 1 mes de deposito 1 mes de adelanto m\u00e1s gastos administrativos\nWhatsApp\nContactar", "revised": false, "rejected": false, "data": {"precio": "$ 250.000 + $41.187 expensas", "expensas": "+ $41.187 expensas", "direccion": "Mercedes 600, Piso 1", "metros": "40 m\u00b2 cubie.", "habitaciones": "1 dorm."}, "image": "https://static1.sosiva451.com/79327651/30401b56-d4e3-4659-9c6e-165b2053dfed_u_small.jpg", "title": "Departamento 2 ambientes frente con balcon muy luminoso"}, "https://www.argenprop.com/departamento-en-alquiler-en-almagro-2-ambientes--12688613": {"id": "16181100", "date": "16-05-2024\n", "index": 136, "content": "1\n/9\n0\n$ 290.000\nRawson 100\nDepartamento en Alquiler en Almagro, Capital Federal\n36 m\u00b2 cubie.\n1 dorm.\n1 ba\u00f1o\n2 Ambientes en Almagro Rawson y Rivadavia\nAlquiler 2 ambientes, cocina living, ba\u00f1o completo y dormitorio con placard. En excelente ubicaci\u00f3n a media cuadra de av. Rivadavia con numerosas l\u00edneas de transporte y cercano al subte a.\nWhatsApp\nContactar", "revised": false, "rejected": false, "data": {"precio": "$ 290.000", "direccion": "Rawson 100", "metros": "36 m\u00b2 cubie.", "habitaciones": "1 dorm."}, "image": "https://static1.sosiva451.com/31688621/6a92993f-b818-4e40-ba8d-8b85a2afa7cf_u_small.jpg", "title": "2 Ambientes en Almagro Rawson y Rivadavia"}, "https://www.argenprop.com/departamento-en-alquiler-en-floresta-2-ambientes--15674464": {"id": "19091255", "date": "16-05-2024\n", "index": 138, "content": "1\n/7\n0\n$ 230.000 + $52.000 expensas\nOlivera al 100\nDepartamento en Alquiler en Floresta, Capital Federal\n38 m\u00b2 cubie.\n1 dorm.\n45 a\u00f1os\nOlivera 100 Departamento de 2 ambientes 38m Esquina en Floresta ALQUILER\nDepartamento de 2 ambientes al frente. Living -comedor. Dormitorio con placard. Cocina con muebles completos y lavadero incorporado. Ba\u00f1o completo. Muy buen estado. Pisos de parquet. Muy buena iluminaci\u00f3n. Edificio en esquina de 8 pisos y 28 unidades funcionales. Colectivos: 1, 2, 4, 5, 8, 36, 46, 49, 55, 63, 86, 88, 92, 96, 104, 107, 113, 114, 126, 136, 163, 180, 182 condiciones de\nWhatsApp\nContactar", "revised": true, "rejected": false, "data": {"precio": "$ 230.000 + $52.000 expensas", "expensas": "+ $52.000 expensas", "direccion": "Olivera al 100", "metros": "38 m\u00b2 cubie.", "habitaciones": "1 dorm."}, "image": "https://static1.sosiva451.com/46447651/90e7376c-d9f7-47d4-b295-39922f82d1a9_u_small.jpg", "title": "Olivera 100 Departamento de 2 ambientes 38m Esquina en Floresta ALQUILER"}, "https://www.argenprop.com/departamento-en-alquiler-en-balvanera-2-ambientes--11396425": {"id": "14887208", "date": "17-05-2024\n", "index": 5, "content": "1\n/6\n175\nConsultar precio\nPasco 500\nDepartamento en Alquiler en Balvanera, Capital Federal\n35 m\u00b2 cubie.\n1 dorm.\nA Estrenar\n2 AMB AESTRENAR SEMIPISOS 35 m2 frernte con balcon\nSemipisos de 2 amb. Ba\u00f1o completo, revestidos en porcelanatos todas las unidades al frente, amplios balcones, agua caliente individual a gas, d\nWhatsApp\nContactar", "revised": false, "rejected": false, "data": {"precio": "Consultar precio", "direccion": "Pasco 500", "metros": "35 m\u00b2 cubie.", "habitaciones": "1 dorm."}, "image": "https://static1.sosiva451.com/52469311/bf6eb0ec-1394-4b6e-85f5-63a6fd2c828a_u_small.jpg", "title": " 2 AMB AESTRENAR SEMIPISOS  35 m2 frernte con balcon  "}, "https://www.argenprop.com/departamento-en-alquiler-en-villa-general-mitre-2-ambientes--15573088": {"id": "18989996", "date": "17-05-2024\n", "index": 8, "content": "1\n/17\n0\n$ 300.000 + $50.000 expensas\nDoctor Luis Bel\u00e1ustegui 1100, Piso 6\nDepartamento en Alquiler en Villa General Mitre, Capital Federal\n36 m\u00b2 cubie.\n1 dorm.\n50 a\u00f1os\nDepartamento 2 Ambientes en Alquiler\nDepartamento de 2 ambientes al contrafrente con balc\u00f3n corrido a pulm\u00f3n de manzana. Hall de entrada 1.80x1.00 living comedor 4.50x3.00 dormitorio con placard 3.00x2.90 cocina con alacenas y bajo mesada 3.30x2.90 lavadero separado, ba\u00f1o completo luminoso requisitos: mes inicial $ 300.000 - dep\u00f3sito 2 meses - recibos de sueldo o justificaci\u00f3n de ingresos - garant\u00eda propietaria de capital federal o\nWhatsApp\nContactar", "revised": false, "rejected": false, "data": {"precio": "$ 300.000 + $50.000 expensas", "expensas": "+ $50.000 expensas", "direccion": "Doctor Luis Bel\u00e1ustegui 1100, Piso 6", "metros": "36 m\u00b2 cubie.", "habitaciones": "1 dorm."}, "image": "https://static1.sosiva451.com/88037551/0bae5326-fbe4-4ab4-a9b8-e58de1fa1c69_u_small.jpg", "title": "Departamento 2 Ambientes en Alquiler"}, "https://www.argenprop.com/departamento-en-alquiler-en-monte-castro-2-ambientes--15581052": {"id": "18997976", "date": "17-05-2024\n", "index": 11, "content": "1\n/17\n816\n$ 240.000 + $50.000 expensas\nAvenida \u00c1lvarez Jonte 4800, Piso 2\nDepartamento en Alquiler en Monte Castro, Floresta\n47 m\u00b2 cubie.\n1 dorm.\n30 a\u00f1os\nEXCELENTE 2 AMB MODERNIZADO 50 M2\n2 amb en excelente estado y ubicacion lateral luminoso amplias mediads con placard y aire acond. Centro comercial montecastro\nContactar", "revised": false, "rejected": false, "data": {"precio": "$ 240.000 + $50.000 expensas", "expensas": "+ $50.000 expensas", "direccion": "Avenida \u00c1lvarez Jonte 4800, Piso 2", "metros": "47 m\u00b2 cubie.", "habitaciones": "1 dorm."}, "image": null, "title": "EXCELENTE 2 AMB MODERNIZADO 50 M2 "}, "https://www.argenprop.com/departamento-en-alquiler-en-congreso-2-ambientes--15641036": {"id": "19057988", "date": "17-05-2024\n", "index": 14, "content": "1\n/7\n100\n$ 290.000\nBartolom\u00e9 Mitre 1900, Piso 9\nDepartamento en Alquiler en Congreso, Capital Federal\n35 m\u00b2 cubie.\n1 dorm.\n1 ba\u00f1o\n2 AMB BARTOLOME MITRE 1949 9 ( BARRIO:CONGRESO)\n2 amb bartolome mitre 1949 9 ( barrio:congreso), departamento con vista panoramica, 100%luminoso, entre ayacucho y riobamba, pisos parquet, living comedor, dormitorio y, cocina y ba\u00f1o completo.\nContactar", "revised": false, "rejected": false, "data": {"precio": "$ 290.000", "direccion": "Bartolom\u00e9 Mitre 1900, Piso 9", "metros": "35 m\u00b2 cubie.", "habitaciones": "1 dorm."}, "image": "https://static1.sosiva451.com/63014651/f128539f-7835-40c8-9fa6-d21d34a55b6a_u_small.jpg", "title": "2 AMB BARTOLOME MITRE 1949 9 ( BARRIO:CONGRESO)"}, "https://www.argenprop.com/departamento-en-alquiler-en-almagro-sur-2-ambientes--15542415": {"id": "18968335", "date": "17-05-2024\n", "index": 18, "content": "1\n/19\n20\n$ 260.000 + $65.000 expensas\nAvenida Boedo 100, Piso 2\nDepartamento en Alquiler en Almagro Sur, Almagro\n38 m\u00b2 cubie.\n1 dorm.\n60 a\u00f1os\nEXCELENTE UBICACI\u00d3N \"Boedo 105\", DEPARTAMENTO 2 AMBIENTES CON BALC\u00d3N FRANCES AL FRENTE\nHermoso departamento 2 ambientes, 2do. Piso por escalera, living comedor, 1 habitaci\u00f3n con gran disponibilidad de placares, cocina completa con anafe y horno el\u00e9ctricos, barra desayunadora, ba\u00f1o completo, pisos de parquet y flotante. Excelente ubicaci\u00f3n, a 1 cuadra de av. Rivadavia, a 2 cuadras del subte linea a estaci\u00f3n \"castro barros\" m\u00e1s de 10 lineas de colectivo por la\nWhatsApp\nContactar", "revised": false, "rejected": false, "data": {"precio": "$ 260.000 + $65.000 expensas", "expensas": "+ $65.000 expensas", "direccion": "Avenida Boedo 100, Piso 2", "metros": "38 m\u00b2 cubie.", "habitaciones": "1 dorm."}, "image": "https://static1.sosiva451.com/51424551/667dfb9f-0396-4b54-8fde-61266f5b7e3b_u_small.jpg", "title": "EXCELENTE UBICACI\u00d3N \"Boedo 105\", DEPARTAMENTO 2 AMBIENTES CON BALC\u00d3N FRANCES AL FRENTE"}, "https://www.argenprop.com/departamento-en-alquiler-en-almagro-2-ambientes--15691643": {"id": "19108355", "date": "17-05-2024\n", "index": 31, "content": "1\n/25\n0\n$ 300.000 + $43.470 expensas\nJer\u00f3nimo Salguero 200\nDepartamento en Alquiler en Almagro, Capital Federal\n36 m\u00b2 cubie.\n1 dorm.\n51 a\u00f1os\nALQUILER DEPARTAMENTO 2 AMBIENTES ALMAGRO\nAlquiler departamento 2 ambientes, 6\u00b0 piso ubicaci\u00f3n frente, con balc\u00f3n cuenta con: cocina separada dormitorio peque\u00f1o con placard ba\u00f1o completo con ba\u00f1era. Expensas abril: 43470 seguro abril: 2150 aysa abril: 11940 abl 4700 corredor responsable: jorge salafia cucicba 5666 / csi 5888 - contacto: luc\u00eda olmedo - mls id # -114 remax argentina s.R.L. No ejerce el corretaje inmobiliario. El\nContactar", "revised": false, "rejected": false, "data": {"precio": "$ 300.000 + $43.470 expensas", "expensas": "+ $43.470 expensas", "direccion": "Jer\u00f3nimo Salguero 200", "metros": "36 m\u00b2 cubie.", "habitaciones": "1 dorm."}, "image": null, "title": "ALQUILER DEPARTAMENTO 2 AMBIENTES ALMAGRO"}, "https://www.argenprop.com/departamento-en-alquiler-en-almagro-2-ambientes--15631934": {"id": "19048895", "date": "17-05-2024\n", "index": 32, "content": "1\n/11\n908\n$ 300.000 + $35.000 expensas\nTeniente General Juan Domingo Per\u00f3n 3900, Piso 3\nDepartamento en Alquiler en Almagro, Capital Federal\n36 m\u00b2 cubie.\n1 dorm.\n2 ambientes\n2 amb lateral\n2 ambientes lateral, cocina amplia con espacio para lavarropas. Ba\u00f1o completo. Cercan\u00edas de subtes a y b, estaciones medrano y castro barros. A 2 cuadras del hospital italiano.\nWhatsApp\nContactar", "revised": false, "rejected": false, "data": {"precio": "$ 300.000 + $35.000 expensas", "expensas": "+ $35.000 expensas", "direccion": "Teniente General Juan Domingo Per\u00f3n 3900, Piso 3", "metros": "36 m\u00b2 cubie.", "habitaciones": "1 dorm."}, "image": "https://static1.sosiva451.com/43913651/9c3fe631-7b4a-431b-aaa7-12ca15f09f24_u_small.jpg", "title": "2 amb lateral "}, "https://www.argenprop.com/departamento-en-alquiler-en-flores-2-ambientes--15482216": {"id": "18908097", "date": "17-05-2024\n", "index": 33, "content": "1\n/9\n500\n$ 270.000 + $14.000 expensas\nGranaderos 800, Piso 3\nDepartamento en Alquiler en Flores, Capital Federal\n35 m\u00b2 cubie.\n1 dorm.\n1 ba\u00f1o\n2 AMB LATERAL por escalera - BAJAS EXPENSAS\nEntre neuqu\u00e9n y p\u00e1ez. Departamento de 2 ambientes lateral. 3er piso por escalera. Bajas expensas! A unas cuadras de plaza irlanda. Consta de living- comedor (3,5 x 2,5m2) c/aire acondicionado (s\u00f3lo fr\u00edo), estufa y piso de parquet. Dormitorio (3 x 2,40m2) c/piso de parquet y aire acondicionado (s\u00f3lo fr\u00edo). Pasillo c/placard. Cocina completa c/muebles bajo mesada, estante y salida a peque\u00f1o balc\u00f3n\nWhatsApp\nContactar", "revised": false, "rejected": false, "data": {"precio": "$ 270.000 + $14.000 expensas", "expensas": "+ $14.000 expensas", "direccion": "Granaderos 800, Piso 3", "metros": "35 m\u00b2 cubie.", "habitaciones": "1 dorm."}, "image": "https://static1.sosiva451.com/61228451/3d3f9567-24c4-480c-80bf-851185b7798a_u_small.jpg", "title": "2 AMB LATERAL por escalera - BAJAS EXPENSAS "}, "https://www.argenprop.com/departamento-en-alquiler-en-almagro-2-ambientes--15691479": {"id": "19108191", "date": "17-05-2024\n", "index": 34, "content": "1\n/14\n2\n$ 250.000 + $74.000 expensas\nBillinghurst 400\nDepartamento en Alquiler en Almagro, Capital Federal\n36 m\u00b2 cubie.\n1 dorm.\n1 ba\u00f1o\n2 AMBIENTES CON BALCON FRANCES - AMOBLADO EN ALMAGRO\nAlquiler de departamento 2 ambientes amoblado en almagro, capital federal lindo departamento de 2 ambientes totalmente amoblado como figura en las fotos con cocina integrada, balc\u00f3n frances, piso 5. Ubicado a media cuadra de la importante avenida corrientes,  a metros de innumerables lineas de colectivo.  Aclaraci\u00f3n: - el propietario no acepta perros.  Contacto para visitas: para agendar una\nWhatsApp\nContactar", "revised": false, "rejected": false, "data": {"precio": "$ 250.000 + $74.000 expensas", "expensas": "+ $74.000 expensas", "direccion": "Billinghurst 400", "metros": "36 m\u00b2 cubie.", "habitaciones": "1 dorm."}, "image": "https://static1.sosiva451.com/97419651/6b6ac1b3-59bb-4db8-85b8-ae2cbb1fe176_u_small.jpg", "title": "2 AMBIENTES  CON BALCON FRANCES - AMOBLADO  EN ALMAGRO"}, "https://www.argenprop.com/departamento-en-alquiler-en-flores-2-ambientes--15654190": {"id": "19070990", "date": "17-05-2024\n", "index": 36, "content": "1\n/12\n387\n$ 300.000 + $61.000 expensas\nFray Cayetano Rodr\u00edguez 800, Piso 18\nDepartamento en Alquiler en Flores, Capital Federal\n40 m\u00b2 cubie.\n1 dorm.\n1 ba\u00f1o\nPRECIOSO DEPARTAMENTO DE 2 AMBIENTES CON BALCON, VISTA PANORAMICA- EXCELENTE ESTADO\nHermoso y comodo departamento. Super luminoso. Vista panoramica\nWhatsApp\nContactar", "revised": false, "rejected": false, "data": {"precio": "$ 300.000 + $61.000 expensas", "expensas": "+ $61.000 expensas", "direccion": "Fray Cayetano Rodr\u00edguez 800, Piso 18", "metros": "40 m\u00b2 cubie.", "habitaciones": "1 dorm."}, "image": "https://static1.sosiva451.com/09145651/aab96058-6d5f-4015-b4fa-acfa4d359d56_u_small.jpg", "title": "PRECIOSO DEPARTAMENTO DE 2 AMBIENTES CON BALCON, VISTA PANORAMICA- EXCELENTE ESTADO"}, "https://www.argenprop.com/departamento-en-alquiler-en-balvanera-2-ambientes--15673144": {"id": "19089938", "date": "17-05-2024\n", "index": 44, "content": "1\n/32\n0\n$ 300.000 + $64.000 expensas\nTucuman al 1500\nDepartamento en Alquiler en Balvanera, Capital Federal\n37 m\u00b2 cubie.\n1 dorm.\n60 a\u00f1os\nDepartamento alquiler 2 ambientes con balcon\nAlquiler de departamento de 2 ambientes con balc\u00f3n, ubicado en balvanera, posee hall de entrada, living comedor, dormitorio, cocina, lavadero independiente, ascensor y encargado fijo . Corredor interviniente caba , pablo faija cucicba 3964- corredor interviniente provincia de buenos aires , pablo faija martillero publico cmycpdjq mat 913 folio 105 tomo ii\nWhatsApp\nContactar", "revised": false, "rejected": false, "data": {"precio": "$ 300.000 + $64.000 expensas", "expensas": "+ $64.000 expensas", "direccion": "Tucuman al 1500", "metros": "37 m\u00b2 cubie.", "habitaciones": "1 dorm."}, "image": "https://static1.sosiva451.com/44137651/2d86dbfe-4936-48d7-b78b-722e218262c8_u_small.jpg", "title": "Departamento alquiler 2 ambientes con balcon"}, "https://www.argenprop.com/departamento-en-alquiler-en-flores-2-ambientes--15576502": {"id": "18993426", "date": "17-05-2024\n", "index": 54, "content": "1\n/12\n2\n$ 300.000\nYerbal 2600\nDepartamento en Alquiler en Flores, Capital Federal\n40 m\u00b2 cubie.\n1 dorm.\n10 a\u00f1os\nHermoso 2 amb con \"Patio\" y \"balcon\"\nHermoso 2 amb con \"patio\" y \"balcon\" moderna cocina tipo americana. Dormitorio con placard! Ba\u00f1o completo! Muy buena ubicaci\u00f3n. Importantes accesos!\nWhatsApp\nContactar", "revised": false, "rejected": false, "data": {"precio": "$ 300.000", "direccion": "Yerbal 2600", "metros": "40 m\u00b2 cubie.", "habitaciones": "1 dorm."}, "image": "https://static1.sosiva451.com/20567551/fa6b27e4-92a7-47d8-8a6e-8af2545b29c3_u_small.jpg", "title": "Hermoso 2 amb con \"Patio\" y \"balcon\" "}, "https://www.argenprop.com/departamento-en-alquiler-en-balvanera-2-ambientes--15402184": {"id": "18837094", "date": "17-05-2024\n", "index": 60, "content": "1\n/19\n2\n$ 300.000\nAv. Hip\u00f3lito Yrigoyen 2200\nDepartamento en Alquiler en Balvanera, Capital Federal\n38 m\u00b2 cubie.\n1 dorm.\n1 ba\u00f1o\nDepartamento en alquiler de 1 dormitorio en Balvanera\nHermoso departamento de 2 ambientes amplios en alquiler en la calle av. Hip\u00f3lito yrigoyen, balvanera, capital federal. Con un precio de ar$300.000 y una ubicaci\u00f3n estrat\u00e9gica a solo una cuadra de la av. Rivadavia, el subte \"a\" y diversas l\u00edneas de colectivos, este inmueble ofrece comodidad y accesibilidad. Ideal para estudiantes o profesionales, se encuentra en una zona comercial y cercana a\nContactar", "revised": false, "rejected": false, "data": {"precio": "$ 300.000", "direccion": "Av. Hip\u00f3lito Yrigoyen 2200", "metros": "38 m\u00b2 cubie.", "habitaciones": "1 dorm."}, "image": "https://static1.sosiva451.com/48120451/190ce2ac-a470-482b-88d9-1e5ccfe382bf_u_small.jpg", "title": "Departamento en alquiler de 1 dormitorio en Balvanera"}, "https://www.argenprop.com/departamento-en-alquiler-en-floresta-2-ambientes--15489479": {"id": "18915358", "date": "17-05-2024\n", "index": 62, "content": "1\n/12\n1\n$ 300.000 + $32.000 expensas\nRio Grande 100, Piso 3\nDepartamento en Alquiler en Floresta, Capital Federal\n38 m\u00b2 cubie.\n1 dorm.\n5 a\u00f1os\nEXCELENTE 2 AMBIENTES A LA CALLE CON BALCON 5 A\u00d1OS DE ANTIGUEDAD, A 1 CUADRA DE RIVADAVIA.-\nExcelente departamento de 2 ambientes a la calle con balcon corrido.-Super luminoso, con cocina integrada con muebles bajo mesada y alacenas.-Ba\u00f1o completo con ba\u00f1era.-El departamento cuenta con 5 a\u00f1os de antiguedad y se entrega en perfectas condiciones de mantenimiento y conservacion.-Plazo del contrato de 2 a\u00f1os con actualizacion semestral por indice de precios al consumidor.-Para ingresar se\nContactar", "revised": false, "rejected": false, "data": {"precio": "$ 300.000 + $32.000 expensas", "expensas": "+ $32.000 expensas", "direccion": "Rio Grande 100, Piso 3", "metros": "38 m\u00b2 cubie.", "habitaciones": "1 dorm."}, "image": "https://static1.sosiva451.com/97498451/7c773c9d-327d-40d0-a6a0-61d1b3b01568_u_small.jpg", "title": "EXCELENTE 2 AMBIENTES A LA CALLE CON BALCON 5 A\u00d1OS DE ANTIGUEDAD, A 1 CUADRA DE RIVADAVIA.-"}, "https://www.argenprop.com/departamento-en-alquiler-en-flores-2-ambientes--15429334": {"id": "18864261", "date": "17-05-2024\n", "index": 63, "content": "1\n/17\n794\n$ 280.000 + $23.000 expensas\nCulpina 200, Piso 4\nDepartamento en Alquiler en Flores, Capital Federal\n40 m\u00b2 cubie.\n1 dorm.\n45 a\u00f1os\nAmplio Departamento 2 Ambientes muy bien ubicado.\nLa unidad cuenta con living-comedor de pisos de alfombras y una ventana con balc\u00f3n frances que brinda iluminacion. Sus medidas son de 3,19 x 3,54 -la cocina, por su parte, cuenta con mueble de bajo/sobre mesada y bacha de acero inoxidable con dimensiones de 3,07 x 2,06. - El ba\u00f1o es completo con ba\u00f1era, posee unas medidas de 1,89 x 1,78. -La habitaci\u00f3n, por su parte tiene pisos de alfombras, una\nWhatsApp\nContactar", "revised": false, "rejected": false, "data": {"precio": "$ 280.000 + $23.000 expensas", "expensas": "+ $23.000 expensas", "direccion": "Culpina 200, Piso 4", "metros": "40 m\u00b2 cubie.", "habitaciones": "1 dorm."}, "image": "https://static1.sosiva451.com/43392451/62be475c-a53e-4ac6-83c5-74abc8ea21fd_u_small.jpg", "title": "Amplio Departamento 2 Ambientes muy bien ubicado."}, "https://www.argenprop.com/departamento-en-alquiler-en-flores-2-ambientes--15249868": {"id": "18684691", "date": "17-05-2024\n", "index": 86, "content": "1\n/5\n0\n$ 260.000 + $33.000 expensas\nAvenida Directorio 2500\nDepartamento en Alquiler en Flores, Capital Federal\n43 m\u00b2 cubie.\n1 dorm.\n40 a\u00f1os\nAlquiler Departamento 2 Amb en Flores\nDepartamento de 2 amb en alquiler flores -excelente ubicaci\u00f3n sobre av. Directorio entre av. Varela y padernera -ascensor -cocina independiente y sector de conexi\u00f3n para lavarropas -ba\u00f1o con cuadro de ducha y ba\u00f1era -amplio placard de guardado en la habitacion -ventilado y super luminoso. -Expensas de $27000.- Pesos requisitos: 1 mes de deposito 1 mes por adelantado garantia *reserva del 50%\nContactar", "revised": false, "rejected": false, "data": {"precio": "$ 260.000 + $33.000 expensas", "expensas": "+ $33.000 expensas", "direccion": "Avenida Directorio 2500", "metros": "43 m\u00b2 cubie.", "habitaciones": "1 dorm."}, "image": "https://static1.sosiva451.com/86894251/f58cc324-90b5-435f-a351-5cb42943f617_u_small.jpg", "title": "Alquiler Departamento 2 Amb en Flores "}, "https://www.argenprop.com/departamento-en-alquiler-en-parque-avellaneda-2-ambientes--15686474": {"id": "19103189", "date": "17-05-2024\n", "index": 102, "content": "1\n/5\n0\n$ 280.000\nAlejandro Dumas 1900\nDepartamento en Alquiler en Parque Avellaneda, Floresta\n40 m\u00b2 cubie.\n1 dorm.\n1 ba\u00f1o\nDepartamento en alquiler de 1 dormitorio en Parque Avellaneda\nUbicado en la prestigiosa calle alejandro dumas, en el encantador barrio de parque avellaneda, capital federal, este exclusivo departamento de 2 ambientes es una joya para aquellos que buscan confort y elegancia. Con un precio de ar$280.000, la propiedad se destaca por sus 50 m\u00b2 totales, de los cuales 40 m\u00b2 son cubiertos y 10 m\u00b2 descubiertos, ofreciendo un equilibrio perfecto entre espacio\nWhatsApp\nContactar", "revised": false, "rejected": false, "data": {"precio": "$ 280.000", "direccion": "Alejandro Dumas 1900", "metros": "40 m\u00b2 cubie.", "habitaciones": "1 dorm."}, "image": "https://proxy.sosiva451.com/proxy/9B6C8AA3E44B338D6601817B1B3AA17046D499FDFC4A2EC2FCE6C2F88C9D5A108FC9601DAA91AA5EAD44E38223FDC0D7DD545A43226FD5975664BA1DD82C11CCF62B196E76C114F27C5A87EFC7A60B2A2F7CEA564C0CEB58BDA310EBBC129A6E08DAD36EFB6C75E7D5927D454F532FDE562F3D9DD7C981CD05A0177D3C02EC9E83870EACC9BB0D988A202517BBB21518", "title": "Departamento en alquiler de 1 dormitorio en Parque Avellaneda"}}
