{"https://www.argenprop.com/departamento-en-venta-en-colegiales-4-ambientes--16180072": {"date": "09-09-2024", "index": 1, "content": "1\n/28\n0\nUSD 150.000 + $130.000 expensas\nZabala 3400\nDepartamento en Venta en Colegiales, Capital Federal\n77 m\u00b2 cubie.\n3 dorm.\n46 a\u00f1os\nDEPARTAMENTO DE 4 AMBIENTES EN COLEGIALES, MUY LUMINOSO\nDistribuci\u00f3n de ambientes: - living comedor muy luminoso con acceso al balc\u00f3n -cocina individual amplia con conexi\u00f3n para lavarropas y ventana que brinda gran ventilaci\u00f3n al ambiente. - Habitaci\u00f3n n1 con pisos de cemento alisado muy luminosa y placard empotrado - habitaci\u00f3n n2 con pisos de cemento alisado y placard empotrado - habitaci\u00f3n n3 con pisos de cemento alisado y placard empotrado -ba\u00f1o\nWhatsApp\nContactar", "revised": true, "rejected": false, "data": {"precio": "USD 150.000 + $130.000 expensas", "direccion": "Zabala 3400", "metros": "77 m\u00b2 cubie.", "habitaciones": "3 dorm."}, "image": "https://www.argenprop.com/content/images/listing-camera.svg", "title": "DEPARTAMENTO DE 4 AMBIENTES EN COLEGIALES, MUY LUMINOSO"}, "https://www.argenprop.com/departamento-en-venta-en-belgrano-4-ambientes--16129183": {"date": "09-09-2024", "index": 2, "content": "1\n/100\n1\nUSD 220.000\nMigueletes al 1700\nDepartamento en Venta en Belgrano, Capital Federal\n79 m\u00b2 cubie.\n3 dorm.\nA Estrenar\nDepartamento 4 ambientes con Dependencia y Cochera - Barrancas de Belgrano\nDepartamento 4 ambientes con dependencia y cochera - barrancas de belgrano. Exclusivo departamento de 4 ambientes con dependencia de servicio, ubicado en un piso alto con vistas despejadas. Al ingresar por el palier privado, te recibe un amplio y luminoso living-comedor, con elegantes pisos de parquet de incienso entarugado que destacan por su calidez y estilo. La\nWhatsApp\nContactar", "revised": false, "rejected": false, "data": {"precio": "USD 220.000", "direccion": "Migueletes al 1700", "metros": "79 m\u00b2 cubie.", "habitaciones": "3 dorm."}, "image": "https://proxy.sosiva451.com/proxy/AE2CCE5D897A9F04F7B8A4278491E393EA7672DF9F6C346BC2A29C129213923DEC7D557FFC270B8F913A783517777EE11DB0F6ACB8981F5E573EE88EB25853E9E78C13EF18848A1ECF7F7221D19C66F81B83F236537DEDEFA79EF48995353987A2A3D28B37A7E3B8358796F0331E0D6D49EDA85A2C0660A6A277BC1D19B882118C551C2269410877912AB9FEBFB22269D11D5242E140DBC169E583E4D02F1F4C", "title": "Departamento 4 ambientes con Dependencia y Cochera - Barrancas de Belgrano"}, "https://www.argenprop.com/casa-en-venta-en-belgrano-r-4-ambientes--15606394": {"date": "09-09-2024", "index": 3, "content": "1\n/33\n903\nUSD 495.000\nTRONADOR 1900\nCasa en Venta en Belgrano R, Belgrano\n214 m\u00b2 cubie.\n3 dorm.\n4 ba\u00f1os\nCasa - Venta - Argentina, Capital Federal - TRONADOR 1900\nVenta de casa 4 ambientes con jardin y pileta en belgrano r chalet para reciclar ubicado en muy linda zona de belgrano r. Si bien la casa es para reciclar, permite desarrollar una casa super funcional gracias al plano que presenta. Living comedor con salida al jardin. Cocina comedor diario con vista al jardin. Dependencia de servicio con ba\u00f1o en planta alta con acceso independiente\nContactar", "revised": false, "rejected": false, "data": {"precio": "USD 495.000", "direccion": "TRONADOR 1900", "metros": "214 m\u00b2 cubie.", "habitaciones": "3 dorm."}, "image": "https://proxy.sosiva451.com/proxy/560F6F117375D70097630D38370B14274E0D194BD637F160134481AAB8BDAA8A32B032771B0DC860D1A7868DF31C9B381B79F43E540992C60A88134FF440F6FE3EE4A1D488AEFDA6F16F73AF8090FB68", "title": "Casa - Venta - Argentina, Capital Federal - TRONADOR 1900"}, "https://www.argenprop.com/departamento-en-venta-en-belgrano-4-ambientes--16181029": {"date": "09-09-2024", "index": 4, "content": "1\n/47\n150\nUSD 230.000 + $480.000 expensas\nVenta - Dpto 4 Amb - Semipiso C/cochera Amenabar 1600, Piso 4\nDepartamento en Venta en Belgrano, Capital Federal\n107 m\u00b2 cubie.\n3 dorm.\n65 a\u00f1os\nVENTA - DPTO 4 AMB - SEMIPISO C/COCHERA\nVenta - departamento - 4 amb - balcon y cochera - belgrano depto 4 ambientes - balc\u00f3n - belgrano belgrano sobre amen\u00e1bar y a metros de av cabildo venta departamento 4 ambientes belgrano 107 m\u00b2 cubiertos + 7 m\u00b2 de balc\u00f3n, 114 m\u00b2 totales 4to piso al frente sobre amen\u00e1bar con vista abierta semipiso con dependencia y doble ingreso ingreso principal al living comedor amplio con acceso al\nWhatsApp\nContactar", "revised": false, "rejected": true, "data": {"precio": "USD 230.000 + $480.000 expensas", "direccion": "Venta - Dpto 4 Amb - Semipiso C/cochera Amenabar 1600, Piso 4", "metros": "107 m\u00b2 cubie.", "habitaciones": "3 dorm."}, "image": "https://static1.sosiva451.com/92018161/8269c1ac-552a-4dae-99d9-905bf672bdeb_u_small.jpg", "title": "VENTA - DPTO 4 AMB - SEMIPISO C/COCHERA             "}, "https://www.argenprop.com/departamento-en-venta-en-belgrano-4-ambientes--11991599": {"date": "09-09-2024", "index": 5, "content": "1\n/41\n0\nUSD 350.000 + $290.100 expensas\nZabala al 1700 Piso 1\u00ba\nDepartamento en Venta en Belgrano, Capital Federal\n107 m\u00b2 cubie.\n3 dorm.\n57 a\u00f1os\nDepartamento en venta con jard\u00edn propio y cochera en Belgrano de 3 dormitorios\nSemipiso al contrafrente de 3 dormitorios con dependencia y espacio guardacoche. Amplio jard\u00edn de 117,5 metros cuadrados propios que dan al pulm\u00f3n de manzana. Parrilla. Metros cuadrados cubiertos: 107.07 semi cubiertos: 9.31 (patio, lavadero trasero) superficie\nWhatsApp\nContactar", "revised": false, "rejected": false, "data": {"precio": "USD 350.000 + $290.100 expensas", "direccion": "Zabala al 1700 Piso 1\u00ba", "metros": "107 m\u00b2 cubie.", "habitaciones": "3 dorm."}, "image": "https://static1.sosiva451.com/99519911/427f6a1e-e98f-448c-83f3-7fddc40bfe8d_u_small.jpg", "title": "Departamento en venta con jard\u00edn propio y cochera en Belgrano de 3 dormitorios"}, "https://www.argenprop.com/departamento-en-venta-en-belgrano-4-ambientes--16113390": {"date": "09-09-2024", "index": 6, "content": "1\n/46\n0\nUSD 480.000 + $477.000 expensas\nMigueletes 1600\nDepartamento en Venta en Belgrano, Capital Federal\n158 m\u00b2 cubie.\n4 dorm.\n14 a\u00f1os\nVenta Departamento 4 Ambientes Dependencia Cochera Amenities\nVenta de departamento 4 ambientes con dependencias, amenities y cochera en belgrano hermoso piso de 179 m2 totales. Muy luminoso y con la mejor ubicaci\u00f3n al ingresar por la puerta principal nos encontramos con un living (5x7 m2) y en \u00e9ste un peque\u00f1o toilette (2,5 x 1 m2). Al final del living encontraremos un balc\u00f3n terraza con vista al contrafrente (10 m2). A continuaci\u00f3n el comedor (3,5 x\nWhatsApp\nContactar", "revised": false, "rejected": false, "data": {"precio": "USD 480.000 + $477.000 expensas", "direccion": "Migueletes 1600", "metros": "158 m\u00b2 cubie.", "habitaciones": "4 dorm."}, "image": "https://proxy.sosiva451.com/proxy/9FE935890DD42A25AF4F0ED6E89328DC5F170FE062BA5FFBDC9CFD7CAB717F9CF2275FC60493E059359E68268B54FBB092A27A1055DD32CD3BFD87C8F5E533ED1032E39A7522C448213EF124858EB1D3EDC98B14BED55359D3D168D1245E735A", "title": "Venta Departamento 4 Ambientes Dependencia Cochera Amenities"}, "https://www.argenprop.com/departamento-en-venta-en-belgrano-c-4-ambientes--15766674": {"date": "09-09-2024", "index": 7, "content": "1\n/28\n24.218\nUSD 380.000 + $158.000 expensas\nCiudad De La Paz 2400\nDepartamento en Venta en Belgrano C, Belgrano\n160 m\u00b2 cubie.\n3 dorm.\n50 a\u00f1os\nDe revista! Impec! C/balc\u00f3n aterrazado! M/Lum! T/luz y Sol! C/dependencia! Cochera Fija! Oport!\nSemipiso de revista! Impecable! Balc\u00f3n aterrazado al frente! Muy luminoso! Todo luz y sol! Amplio living-comedor en l! Excelente distribuci\u00f3n! Doble circulaci\u00f3n! Tres dormitorios, uno en suite con vestidor! Cocina completa! Comedor diario! Dependencia de servicio con ba\u00f1o! Lavadero independiente! Todo a nuevo! Aberturas nuevas con doble vidrio! Losa radiante por caldera individual!\nWhatsApp\nContactar", "revised": false, "rejected": false, "data": {"precio": "USD 380.000 + $158.000 expensas", "direccion": "Ciudad De La Paz 2400", "metros": "160 m\u00b2 cubie.", "habitaciones": "3 dorm."}, "image": "https://static1.sosiva451.com/47666751/1bd26df0-5fa7-4936-8565-d93ce4ad7b75_u_small.jpg", "title": "De revista! Impec! C/balc\u00f3n aterrazado! M/Lum! T/luz y Sol! C/dependencia! Cochera Fija! Oport!"}, "https://www.argenprop.com/departamento-en-venta-en-belgrano-4-ambientes--16095359": {"date": "09-09-2024", "index": 8, "content": "1\n/67\n0\nUSD 360.000\nJorge Newbery 2500\nDepartamento en Venta en Belgrano, Capital Federal\n132 m\u00b2 cubie.\n3 dorm.\n29 a\u00f1os\nHermoso Semipiso Balc\u00f3n terraza, Cochera,3 Dorm, Ampl\u00edsimo L\nExcelente ubicaci\u00f3n, a 1 cuadra de av. Cabildo, a tres de federico lacroze, subte, toda la variedad de medios de transporte a pocos metros. 152 metros cuadrados totales, balc\u00f3n aterrazado. Semipiso con palier privado, puerta ppal y de servicio con puerta blindada marca pent\u00e1gono de \u00faltima generaci\u00f3n, nuevas ambas, pisos de viraro paraguayo tarugado, estado excelente. 4 ambientes c/ balc\u00f3n\nWhatsApp\nContactar", "revised": false, "rejected": false, "data": {"precio": "USD 360.000", "direccion": "Jorge Newbery 2500", "metros": "132 m\u00b2 cubie.", "habitaciones": "3 dorm."}, "image": "https://static1.sosiva451.com/95359061/fb9bd405-4bae-464e-b405-a4f02556e038_u_small.jpg", "title": "Hermoso Semipiso Balc\u00f3n terraza, Cochera,3 Dorm, Ampl\u00edsimo L"}, "https://www.argenprop.com/departamento-en-venta-en-belgrano-r-4-ambientes--16145375": {"date": "09-09-2024", "index": 9, "content": "1\n/20\n1\nUSD 195.000 + $180.000 expensas\nJuramento 2800\nDepartamento en Venta en Belgrano R, Belgrano\n66 m\u00b2 cubie.\n3 dorm.\n50 a\u00f1os\n4 Ambientes Con Balc\u00f3n Al Frente BELGRANO R\nDepartamento antiguo con cocina y ba\u00f1o reformados. Doble circulaci\u00f3n con balc\u00f3n mirando hacia la vereda ancha de juramento. Inmejorable ubicaci\u00f3n cerca de todo: subte d, estaci\u00f3n belgrano r, colegios, supermercados, barrancas, etc. Si conoces la zona, no hace falta la descripci\u00f3n. Dos dormitorios con placares y un estudio peque\u00f1o o 3er dormitorio. Living comedor. Lavadero independiente. Cocina\nWhatsApp\nContactar", "revised": false, "rejected": false, "data": {"precio": "USD 195.000 + $180.000 expensas", "direccion": "Juramento 2800", "metros": "66 m\u00b2 cubie.", "habitaciones": "3 dorm."}, "image": "https://static1.sosiva451.com/57354161/70acc9f7-0d34-4522-8b73-d17b8cfcb3a5_u_small.jpg", "title": " 4 Ambientes Con Balc\u00f3n Al Frente BELGRANO R"}, "https://www.argenprop.com/departamento-en-venta-en-belgrano-barrancas-4-ambientes--13919633": {"date": "09-09-2024", "index": 10, "content": "1\n/28\n101\nUSD 223.000 + $75.000 expensas\nIng Antonio Arcos 1900, Piso 3\nDepartamento en Venta en Belgrano Barrancas, Belgrano\n77 m\u00b2 cubie.\n3 dorm.\n40 a\u00f1os\nDepto semipiso 4 ambientes al contrafrente con balcon y 2 ba\u00f1os ! Posee baulera y cochera cubierta !\nDepartamento semipiso 4 ambientes en un tercer piso al contrafrente con balc\u00f3n, cochera fija cubierta y baulera de 5m2. Living comedor de 4,80 x 3,60 con aire acondicionado y salida al balc\u00f3n corrido de 8 x 1, cocina separada de 4 x 2,20 y 1,20 x 1 con lavadero incorporado (posee doble bacha, conexi\u00f3n para lava ropas y lavavajillas y horno, hornallas y calefon a gas), 3 dormitorios (uno de ellos\nWhatsApp\nContactar", "revised": false, "rejected": false, "data": {"precio": "USD 223.000 + $75.000 expensas", "direccion": "Ing Antonio Arcos 1900, Piso 3", "metros": "77 m\u00b2 cubie.", "habitaciones": "3 dorm."}, "image": null, "title": "Depto semipiso 4 ambientes al contrafrente con balcon y 2 ba\u00f1os ! Posee baulera y cochera cubierta !"}, "https://www.argenprop.com/departamento-en-venta-en-belgrano-barrancas-4-ambientes--16180626": {"date": "09-09-2024", "index": 11, "content": "1\n/29\n0\nUSD 420.000 + $500.000 expensas\n11 de Septiembre al 1700\nDepartamento en Venta en Belgrano Barrancas, Belgrano\n130 m\u00b2 cubie.\n3 dorm.\n50 a\u00f1os\nVenta Departamento de 4 amb en barrancas de belgrano.\nVenta departamento de 4 amb en barrancas de belgrano. Departamento 4 ambientes con dependencia en torre de categor\u00eda. Palier privado. Orientaci\u00f3n ne. Muy luminoso. Piso 6 al contrafrente. Entrada principal y de servicio. Living y comedor con salida a balc\u00f3n corrido de 1,50m de ancho. Dormitorio principal con placard. Segundo dormitorio con\nWhatsApp\nContactar", "revised": false, "rejected": false, "data": {"precio": "USD 420.000 + $500.000 expensas", "direccion": "11 de Septiembre al 1700", "metros": "130 m\u00b2 cubie.", "habitaciones": "3 dorm."}, "image": "https://static1.sosiva451.com/62608161/1653f167-a39d-486f-9589-0b16eec3c1fe_u_small.jpg", "title": "Venta Departamento de 4 amb en barrancas de belgrano."}, "https://www.argenprop.com/departamento-en-venta-en-belgrano-4-ambientes--15877524": {"date": "09-09-2024", "index": 12, "content": "1\n/20\n0\nUSD 235.000 + $244.165 expensas\nEcheverria al 2040, \u00danico Patio/Terraza de 50 m2 con plantas a lindisimo pulm\u00f3n verde!\nDepartamento en Venta en Belgrano, Capital Federal\n96 m\u00b2 cubie.\n3 dorm.\n50 a\u00f1os\nDepartamento en Belgrano\nBarrancas de belgrano. Echeverria entre o'higgins y arcos. Cerca de todo! \u00danico patio/terraza de 50 m2 con plantas a lindisimo pulm\u00f3n verde! Orientado al este. Semipiso. Palier privado. Hall. Living comedor, 3 dormitorios con placards. Toilette y ba\u00f1o completo. Cocina con lugar para peque\u00f1o comedor diario. Lavadero. Dependencia anexable. Ba\u00f1o de servicio. Doble circulaci\u00f3n. Pisos de\nWhatsApp\nContactar", "revised": false, "rejected": false, "data": {"precio": "USD 235.000 + $244.165 expensas", "direccion": "Echeverria al 2040, \u00danico Patio/Terraza de 50 m2 con plantas a lindisimo pulm\u00f3n verde!", "metros": "96 m\u00b2 cubie.", "habitaciones": "3 dorm."}, "image": "https://static1.sosiva451.com/42577851/5fbb9104-89e3-4592-8a87-05df3ef467ee_u_small.jpg", "title": "Departamento en Belgrano"}, "https://www.argenprop.com/departamento-en-venta-en-colegiales-4-ambientes--15579519": {"date": "09-09-2024", "index": 13, "content": "1\n/14\n900\nUSD 429.000\nDelgado 1117 2\u00baA\nDepartamento en Venta en Colegiales, Capital Federal\n114 m\u00b2 cubie.\n3 dorm.\nA Estrenar\nDelgado 1117 2\u00baA / Bloom / Semipiso 4 amb. Dorm. ppal. en suite. Balc\u00f3n c/parrilla.\nAmplio departamento de cuatro ambientes (tres ba\u00f1os) y balc\u00f3n aterrazado, dispuesto al frente, con vista a la plaza san miguel de garicoits. Dormitorio principal en suite con vestidor, ba\u00f1o completo y salida a balc\u00f3n corrido. Cocina integrada al living, mobiliario de madera laqueada completo, cocinas a gas de acero inoxidable (anafe y horno por separado), isla central\nWhatsApp\nContactar", "revised": false, "rejected": false, "data": {"precio": "USD 429.000", "direccion": "Delgado 1117 2\u00baA", "metros": "114 m\u00b2 cubie.", "habitaciones": "3 dorm."}, "image": null, "title": "Delgado 1117 2\u00baA / Bloom / Semipiso 4 amb. Dorm. ppal. en suite. Balc\u00f3n c/parrilla."}, "https://www.argenprop.com/departamento-en-venta-en-colegiales-4-ambientes--15579619": {"date": "09-09-2024", "index": 14, "content": "1\n/13\n175\nUSD 389.000\nDelgado 1117 1\u00baA\nDepartamento en Venta en Colegiales, Capital Federal\n114 m\u00b2 cubie.\n3 dorm.\nA Estrenar\nDelgado 1117 1\u00baA/ Bloom / Semipiso 4 Amb. Dorm ppal. en Suite. Balc\u00f3n C/parrilla\nAmplio departamento de cuatro ambientes (tres ba\u00f1os) y balc\u00f3n aterrazado, dispuesto al frente, con vista a la plaza san miguel de garicoits. Dormitorio principal en suite con vestidor, ba\u00f1o completo y salida a balc\u00f3n corrido. Cocina integrada al living, mobiliario de madera laqueada completo, cocinas a gas de acero inoxidable (anafe y horno por separado),\nWhatsApp\nContactar", "revised": false, "rejected": false, "data": {"precio": "USD 389.000", "direccion": "Delgado 1117 1\u00baA", "metros": "114 m\u00b2 cubie.", "habitaciones": "3 dorm."}, "image": null, "title": "Delgado 1117 1\u00baA/ Bloom / Semipiso 4 Amb. Dorm ppal. en Suite. Balc\u00f3n C/parrilla"}, "https://www.argenprop.com/departamento-en-venta-en-belgrano-4-ambientes--16160512": {"date": "09-09-2024", "index": 15, "content": "1\n/45\n0\nUSD 940.000 + $356.200 expensas\nOlleros al 1800 (Luis Maria Campos y Soldado de la Independencia)\nDepartamento en Venta en Belgrano, Capital Federal\n155 m\u00b2 cubie.\n3 dorm.\nA Estrenar\nTerraza propia - semipiso a estrenar terminaciones de lujo - 4 amb. - Full Amenities\n172 mts.totales - 117 mts.cubiertos. - 55 mts.balc\u00f3n terraza. Incre\u00edble semipiso de 4 ambientes con terraza propia y vista al rio, palier privado con detalles en madera, cemento y porcelanatos con mucha categor\u00eda y dise\u00f1o. Dormitorios principal en suite con salida a balc\u00f3n corrido al contra frente con hermosas vistas a pulm\u00f3n de manzana, gran vestidor y ba\u00f1o con\nWhatsApp\nContactar", "revised": false, "rejected": false, "data": {"precio": "USD 940.000 + $356.200 expensas", "direccion": "Olleros al 1800 (Luis Maria Campos y Soldado de la Independencia)", "metros": "155 m\u00b2 cubie.", "habitaciones": "3 dorm."}, "image": "https://static1.sosiva451.com/21506161/859d4ded-8c71-4484-97ad-a4a5bdd1f599_u_small.jpg", "title": "Terraza propia - semipiso a estrenar terminaciones de lujo - 4 amb. - Full Amenities"}, "https://www.argenprop.com/departamento-en-venta-en-belgrano-4-ambientes--14692575": {"date": "09-09-2024", "index": 16, "content": "1\n/51\n0\nUSD 452.870\nOlazabal al 2782\nDepartamento en Venta en Belgrano, Capital Federal\n115 m\u00b2 cubie.\n3 dorm.\n2 ba\u00f1os\nDepartamento en VENTA a Estrenar VAIV OLAZABAL, Belgrano. 4 Ambientes, Cochera, Full Amenities,\nVaiv olazabal financiaci\u00f3n : 40% a la firma del boleto, saldo en cuotas mensuales en pesos ajustadas por el indice cac , \u00edndice de la c\u00e1mara argentina de la construcci\u00f3n . Cocheras: u$s 35.000 fecha entrega estimada: diciembre 2024 tipologia 4 ambientes con dependencia de servicio y patio nuevo emprendimiento en belgrano, uno de\nWhatsApp\nContactar", "revised": false, "rejected": false, "data": {"precio": "USD 452.870", "direccion": "Olazabal al 2782", "metros": "115 m\u00b2 cubie.", "habitaciones": "3 dorm."}, "image": "https://static1.sosiva451.com/57529641/9c830fd0-8436-41d0-b927-a712f2d1a4f3_u_small.jpg", "title": "Departamento en VENTA a Estrenar VAIV OLAZABAL,  Belgrano.  4 Ambientes, Cochera, Full Amenities,"}, "https://www.argenprop.com/ph-en-venta-en-belgrano-r-4-ambientes--16172965": {"date": "09-09-2024", "index": 17, "content": "1\n/43\n0\nUSD 485.000\nHeredia 1300\nPH en Venta en Belgrano R, Belgrano\n184 m\u00b2 cubie.\n3 dorm.\n41 a\u00f1os\nVENTA PH RECICLADO CON TERRAZA PROPIA BELGRANO R\nVenta ph totalmente reciclado con entrada independiente se trata de un ph tipo casa a la calle super luminoso y en inmejorable estado 4 ambientes posibilidad de obtener hasta dos cocheras en el edificio de enfrente planta baja -hall recibidor -toilette -amplio living comedor con ventanales a patio interno -cocina semi integrada con isla y tambi\u00e9n ventanales a patio interno -lavadero primer\nContactar", "revised": false, "rejected": false, "data": {"precio": "USD 485.000", "direccion": "Heredia 1300", "metros": "184 m\u00b2 cubie.", "habitaciones": "3 dorm."}, "image": "https://static1.sosiva451.com/56927161/d7b80f65-04ad-4588-80a9-2188a3a6f667_u_small.jpg", "title": "VENTA PH RECICLADO CON TERRAZA PROPIA BELGRANO R"}, "https://www.argenprop.com/departamento-en-venta-en-belgrano-4-ambientes--16151642": {"date": "09-09-2024", "index": 18, "content": "1\n/16\n0\nUSD 170.000 + $195.000 expensas\nAvenida Olaz\u00e1bal 2500\nDepartamento en Venta en Belgrano, Capital Federal\n69 m\u00b2 cubie.\n3 dorm.\n29 a\u00f1os\nDEPARTAMENTO DE 4 AMB C/COCHERA/ BAULERA / BALCON\nDepartamento al frente con balcon corrido pasillo de doble circulacion living / comedor cocina / comedor lavadero 2 habitaciones al frente 1 habitacion al contrafrente 1 ba\u00f1o completo 1 toilette hermoso balcon al frente corrido luz natural hasta pasado el medio dia datos utiles a una cuadra del metrobus de cabildo y olazabal colectivos: 29, 41, 44, 57, 59, 60, 63, 65, 67, 68,\nWhatsApp\nContactar", "revised": false, "rejected": false, "data": {"precio": "USD 170.000 + $195.000 expensas", "direccion": "Avenida Olaz\u00e1bal 2500", "metros": "69 m\u00b2 cubie.", "habitaciones": "3 dorm."}, "image": "https://static1.sosiva451.com/24615161/ca0e2391-4406-43b9-aa02-2237408d7c2a_u_small.jpg", "title": "DEPARTAMENTO DE 4 AMB C/COCHERA/ BAULERA / BALCON"}, "https://www.argenprop.com/departamento-en-venta-en-belgrano-c-4-ambientes--16106121": {"date": "09-09-2024", "index": 19, "content": "1\n/18\n0\nUSD 195.000 + $100.000 expensas\nRoosevelt al 3000\nDepartamento en Venta en Belgrano C, Belgrano\n74 m\u00b2 cubie.\n3 dorm.\n50 a\u00f1os\nVenta - Departamento - 4 ambientes - Patio - Belgrano\nHermoso departamento en venta todo reciclado a nuevo sobre la calle roosevelt, esquina zapiola. Se trata de una unidad en pb con patio y parrilla. Amplio lugar al aire libre para hacer asados, espacio para bicicletas y recreaci\u00f3n. Ideal para familias numerosas con chicos. Entrada principal y de servicio. Muy buen espacio de guardado en todo el departamento. Pisos de porcelanato en toda la\nWhatsApp\nContactar", "revised": false, "rejected": false, "data": {"precio": "USD 195.000 + $100.000 expensas", "direccion": "Roosevelt al 3000", "metros": "74 m\u00b2 cubie.", "habitaciones": "3 dorm."}, "image": "https://static1.sosiva451.com/12160161/47c3906d-b673-4716-8754-890fa484501e_u_small.jpg", "title": "Venta - Departamento - 4 ambientes - Patio - Belgrano"}, "https://www.argenprop.com/departamento-en-venta-en-belgrano-r-4-ambientes--16180121": {"date": "09-09-2024", "index": 20, "content": "1\n/31\n0\nUSD 135.000 + $65.000 expensas\nConde al 1800 y Pampa . Torre con vista a jardines!! super luminoso. Sup 62 m2\nDepartamento en Venta en Belgrano R, Belgrano\n59 m\u00b2 cubie.\n3 dorm.\n50 a\u00f1os\nDepartamento en Belgrano R\nConde y pampa. Excelente ubicaci\u00f3n en pleno belgrano r. Torre con vista a jardines en todos los ambientes y super luminoso. Amplio living comedor, 3 dormitorios, ba\u00f1o y cocina completos. Lavadero incorporado. Pisos flotantes hechos a nuevo. La zona es exclusiva, cercana a embajadas, lo que garantiza seguridad y prestigio. Adem\u00e1s, est\u00e1 a solo unos pasos de la estaci\u00f3n de\nWhatsApp\nContactar", "revised": false, "rejected": false, "data": {"precio": "USD 135.000 + $65.000 expensas", "direccion": "Conde al 1800 y Pampa . Torre con vista a jardines!! super luminoso. Sup 62 m2", "metros": "59 m\u00b2 cubie.", "habitaciones": "3 dorm."}, "image": "https://static1.sosiva451.com/12108161/bd76c4f2-6764-4cb0-8ee9-5ebe6106cafe_u_small.jpg", "title": "Departamento en Belgrano R"}, "https://www.argenprop.com/departamento-en-venta-en-belgrano-4-ambientes--15872745": {"date": "09-09-2024", "index": 21, "content": "1\n/35\n0\nUSD 440.895\nManuel Ugarte al 2000\nDepartamento en Venta en Belgrano, Capital Federal\n120 m\u00b2 cubie.\n3 dorm.\nA Estrenar\nVenta 4 Amb. en Duplex con Dependencia. Torre con Amenities Belgrano\nVenta 4 amb. En duplex con dependencia. Torre con amenities belgrano duplex 4 ambientes con dependencia. 8 y 9 piso - 4 ambientes muy luminoso, con balc\u00f3n corrido, vista abierta, edificio moderno de categor\u00eda con amenities ( piscina, solarium, gimnasio y sum). - En el corazon de belgrano. Frente a plaza alberti. - Dormitorio principal en suite con amplio placard\nWhatsApp\nContactar", "revised": false, "rejected": false, "data": {"precio": "USD 440.895", "direccion": "Manuel Ugarte al 2000", "metros": "120 m\u00b2 cubie.", "habitaciones": "3 dorm."}, "image": "https://static1.sosiva451.com/54727851/901066c0-12f7-4dee-8cee-be3bbb211909_u_small.jpg", "title": "Venta 4 Amb. en Duplex con Dependencia. Torre con Amenities Belgrano"}, "https://www.argenprop.com/departamento-en-venta-en-belgrano-4-ambientes--12742330": {"date": "09-09-2024", "index": 22, "content": "1\n/44\n1\nUSD 390.000\nO\u00b4higgins 1900 100\nDepartamento en Venta en Belgrano, Capital Federal\n125 m\u00b2 cubie.\n3 dorm.\n2 ba\u00f1os\nEspectacular Semipiso En Barrancas De Belgrano\nBarrancas de belgrano 2\u00b0piso balc\u00f3n terraza con parrilla + 3 dormitorios (family) , dependencia de servicio, cochera, baulera. Excelente estado tanto del edificio como del departamento. Living/comedor en desnivel con chimenea zona de barra/bar/cava de vinos .3 dormitorios (principal en suite) uno de ellos transformado en family room (pero mantiene su utilidad como dormitorio) 2 ba\u00f1os .\nContactar", "revised": false, "rejected": false, "data": {"precio": "USD 390.000", "direccion": "O\u00b4higgins 1900 100", "metros": "125 m\u00b2 cubie.", "habitaciones": "3 dorm."}, "image": "https://static1.sosiva451.com/03324721/96b28d73-7761-4fdc-8c56-b114cce32b20_u_small.jpg", "title": "Espectacular Semipiso En Barrancas De Belgrano"}, "https://www.argenprop.com/departamento-en-venta-en-colegiales-4-ambientes--16160006": {"date": "09-09-2024", "index": 23, "content": "1\n/26\n0\nUSD 255.000 + $300.000 expensas\nAguilar 2800\nDepartamento en Venta en Colegiales, Capital Federal\n125 m\u00b2 cubie.\n3 dorm.\n40 a\u00f1os\nDEPARTAMENTO 3 DOR.C/DEP - COLEGIALES, CAPITAL FEDERAL\nMuy lindo departamento de 4 ambientes todo externo. Muy buena ubicaci\u00f3n a 2 cuadras de la estaci\u00f3n colegiales, 1 cuadra del instituto fleming y 5 cuadras de la avda. Cabildo y subte l\u00ednea d. Amplio living comedor con salida a balc\u00f3n corrido. Aire acondicionado split fr\u00edo/calor. Tres dormitorios todos con placard. Aire acondicionado split fr\u00edo/calor. Doble circulaci\u00f3n. Ba\u00f1o completo mas\nWhatsApp\nContactar", "revised": false, "rejected": false, "data": {"precio": "USD 255.000 + $300.000 expensas", "direccion": "Aguilar 2800", "metros": "125 m\u00b2 cubie.", "habitaciones": "3 dorm."}, "image": "https://static1.sosiva451.com/60006161/729d8d8d-9372-458c-a5d0-308c556085fe_u_small.jpg", "title": "DEPARTAMENTO 3 DOR.C/DEP - COLEGIALES, CAPITAL FEDERAL"}, "https://www.argenprop.com/departamento-en-venta-en-belgrano-4-ambientes--16178212": {"date": "09-09-2024", "index": 24, "content": "1\n/23\n1\nUSD 350.000 + $200.000 expensas\nOlleros 2200\nDepartamento en Venta en Belgrano, Capital Federal\n105 m\u00b2 cubie.\n3 dorm.\nA Estrenar\nDepartamento 4 ambientes con balc\u00f3n al frente\nAlquiler departamento 4 ambientes en belgrano muy amplio corredor inmobiliario responsable: arq. Jorge fernando moscatelli cpi n 4.518 departamento de 3 dormitorios + dependencia en una de las partes m\u00e1s bonitas de belgrano! Amplios ambientes, super luminoso! Balc\u00f3n al frente y sobre la copa de los \u00e1rboles espacio guardacoches\nContactar", "revised": false, "rejected": false, "data": {"precio": "USD 350.000 + $200.000 expensas", "direccion": "Olleros 2200", "metros": "105 m\u00b2 cubie.", "habitaciones": "3 dorm."}, "image": "https://static1.sosiva451.com/21287161/7a537d9c-44a7-4dd7-af80-d01695a2cbcd_u_small.jpg", "title": "Departamento 4 ambientes con balc\u00f3n al frente"}, "https://www.argenprop.com/departamento-en-venta-en-belgrano-4-ambientes--16015005": {"date": "09-09-2024", "index": 25, "content": "1\n/25\n0\nUSD 340.000 + $510.000 expensas\nArcos al 1800\nDepartamento en Venta en Belgrano, Capital Federal\n126 m\u00b2 cubie.\n3 dorm.\n45 a\u00f1os\nExcelente 4 amb al frente en piso alto!\nBelgrano. Arcos y la pampa. Departamento de 4 ambientes con dependencia. Al frente. Cochera fija cubierta. Living comedor con salida a balc\u00f3n aterrazado, tres dormitorios con placard, dos ba\u00f1os completos, cocina con comedor diario, lavadero separado y dependencia con ba\u00f1o. Palier privado. Son 126,65 m2 cubiertos + 2,36 m2 semicubiertos + 8,99 m2 descubiertos =\nWhatsApp\nContactar", "revised": false, "rejected": false, "data": {"precio": "USD 340.000 + $510.000 expensas", "direccion": "Arcos al 1800", "metros": "126 m\u00b2 cubie.", "habitaciones": "3 dorm."}, "image": "https://static1.sosiva451.com/50051061/d6130d2c-b448-4013-b6a4-2016094dabf3_u_small.jpg", "title": "Excelente 4 amb al frente en piso alto!"}, "https://www.argenprop.com/departamento-en-venta-en-belgrano-4-ambientes--15632855": {"date": "09-09-2024", "index": 26, "content": "1\n/17\n0\nUSD 240.000 + $213.000 expensas\nHernandez Jose al 2400\nDepartamento en Venta en Belgrano, Capital Federal\n103 m\u00b2 cubie.\n3 dorm.\n50 a\u00f1os\nDepartamento en Belgrano de 4 ambientes con balc\u00f3n corrido\nBelgrano. Semipiso al frente. Importante \u00e1rea social al frente a balc\u00f3n corrido. Dormitorio principal (3,20 x 3,60) al frente a balc\u00f3n corrido. Segundo y tercer dormitorio, cocina con office y dependencia de servicio. 3 ba\u00f1os. Pisos de parquet. Entrada principal y de servicio. Baulera. Sup. Cubierta: 103,31 m2\nWhatsApp\nContactar", "revised": false, "rejected": false, "data": {"precio": "USD 240.000 + $213.000 expensas", "direccion": "Hernandez Jose al 2400", "metros": "103 m\u00b2 cubie.", "habitaciones": "3 dorm."}, "image": "https://static1.sosiva451.com/55823651/83b3772d-5c60-4e1b-88a6-9c12bf50b744_u_small.jpg", "title": "Departamento en Belgrano de 4 ambientes con balc\u00f3n corrido"}, "https://www.argenprop.com/departamento-en-venta-en-belgrano-4-ambientes--15632854": {"date": "09-09-2024", "index": 27, "content": "1\n/37\n0\nUSD 630.000 + $2.112.216 expensas\nArredondo Virrey al 2200\nDepartamento en Venta en Belgrano, Capital Federal\n160 m\u00b2 cubie.\n2 dorm.\n15 a\u00f1os\nDepartamento de 4 ambientes en Belgrano 8\u00b0 Piso al frente, terraza con quincho y parrilla,\nExclusivo departamento en belgrano, virrey arredondo entre arcos y vuelta de obligado. Tres cocheras, dos cubiertas y una descubierta. Dos dormitorios m\u00e1s escritorio o tercer dormitorio, dos ba\u00f1os completos y toilette. Cocina con barra, habitaci\u00f3n de servicio con ba\u00f1o. Balc\u00f3n aterrazado con jacuzzi y quincho con parrilla. Seguridad 24hs, excelente estado en edificio de categor\u00eda. Piso muy\nWhatsApp\nContactar", "revised": false, "rejected": false, "data": {"precio": "USD 630.000 + $2.112.216 expensas", "direccion": "Arredondo Virrey al 2200", "metros": "160 m\u00b2 cubie.", "habitaciones": "2 dorm."}, "image": "https://static1.sosiva451.com/45823651/22f1a4fd-e503-4906-bdff-d9b749738529_u_small.jpg", "title": "Departamento de 4 ambientes en Belgrano   8\u00b0 Piso al frente, terraza con quincho y parrilla,"}, "https://www.argenprop.com/departamento-en-venta-en-belgrano-barrancas-4-ambientes--16124918": {"date": "09-09-2024", "index": 28, "content": "1\n/14\n505\nUSD 365.000 + $320.000 expensas\nJos\u00e9 Hern\u00e1ndez 2100, Piso 2\nDepartamento en Venta en Belgrano Barrancas, Belgrano\n126 m\u00b2 cubie.\n3 dorm.\n3 ba\u00f1os\nDepartamento en venta de 3 dormitorios c/ cochera en Belgran\nLibre ya lo maneja ariel unico y gran propiedad en la mehor zona de belgrano belgrano, 4 amb, 126m + 11m, jose hernandez 2100 p2, u$s 365.000 con cochera, $320.000 expensas (sep 2024) descripcion: ubicado a 1 cuadra de la av. Cabildo, cerca de las paradas de coletivos y la estacion al subte de jos\u00e9 hernandez. (Excelente ubicacion) cuatro ambientes incre\u00edble departamento ubicado en\nContactar", "revised": false, "rejected": false, "data": {"precio": "USD 365.000 + $320.000 expensas", "direccion": "Jos\u00e9 Hern\u00e1ndez 2100, Piso 2", "metros": "126 m\u00b2 cubie.", "habitaciones": "3 dorm."}, "image": "https://static1.sosiva451.com/81942161/e928a153-b59b-4aa8-a131-16fcf5381980_u_small.jpg", "title": "Departamento en venta de 3 dormitorios c/ cochera en Belgran"}, "https://www.argenprop.com/departamento-en-venta-en-belgrano-4-ambientes--16099810": {"date": "09-09-2024", "index": 29, "content": "1\n/9\n1\nUSD 220.000 + $200.000 expensas\nCramer 2300, Piso 9\nDepartamento en Venta en Belgrano, Capital Federal\n80 m\u00b2 cubie.\n3 dorm.\n50 a\u00f1os\nVENTA DEPARTAMENTO 4 AMBIENTES CON COCHERA EN BELGRANO\nLuminoso 4 ambientes con orientaci\u00f3n este ubicado en el \u00faltimo piso en av. Cramer en el barrio de belgrano con vista abierta. Con 80 metros totales y un balc\u00f3n que conecta el living y el cuarto principal. Este departamento remodelado a nuevo te invita a vivir en la ciudad pero con la posibilidad de tener tranquilidad auditiva y visual, ya que su vista es abierta. Tiene 2 cuartos secundarios con\nWhatsApp\nContactar", "revised": false, "rejected": false, "data": {"precio": "USD 220.000 + $200.000 expensas", "direccion": "Cramer 2300, Piso 9", "metros": "80 m\u00b2 cubie.", "habitaciones": "3 dorm."}, "image": "https://static1.sosiva451.com/01899061/7c18936c-6496-4ceb-bf4e-9de7c5940175_u_small.jpg", "title": "VENTA DEPARTAMENTO 4 AMBIENTES CON COCHERA EN BELGRANO"}, "https://www.argenprop.com/departamento-en-venta-en-belgrano-4-ambientes--15538922": {"date": "09-09-2024", "index": 30, "content": "1\n/25\n2\nUSD 440.900 + $255.000 expensas\nManuel Ugarte 2000\nDepartamento en Venta en Belgrano, Capital Federal\n128 m\u00b2 cubie.\n3 dorm.\nA Estrenar\nDepartamento en Venta ubicado en Belgrano, Capital Federal, Buenos Aires\nDepartamento de 4 ambientes en duplex - balcon al contrafrente con vista abierta al pulmon de manzana - orientacion norte - super luminoso - caldera dual ariston y artefacto de cocina a gas domec - apto profesional - escritura y posesion inmediata! Exclusivos deptos. De 2, 3 y 4 ambientes - ugarte al 2000, entre o\u00b4higgins y arcos - frente a plaza alberti - sectores comunes y amenities: -\nWhatsApp\nContactar", "revised": false, "rejected": false, "data": {"precio": "USD 440.900 + $255.000 expensas", "direccion": "Manuel Ugarte 2000", "metros": "128 m\u00b2 cubie.", "habitaciones": "3 dorm."}, "image": "https://static1.sosiva451.com/22983551/d523ddb5-ce10-4b5c-b2a3-5f88ba98d5d0_u_small.jpg", "title": "Departamento  en Venta ubicado en Belgrano, Capital Federal, Buenos Aires"}, "https://www.argenprop.com/departamento-en-venta-en-belgrano-4-ambientes--14575294": {"date": "09-09-2024", "index": 31, "content": "1\n/38\n500\nUSD 280.000 + $170.000 expensas\nZabala al 2400\nDepartamento en Venta en Belgrano, Capital Federal\n120 m\u00b2 cubie.\n3 dorm.\n24 a\u00f1os\nDepartamento 4 ambientes con cochera y patio - Venta - Belgrano\nDepartamento de cuatro ambientes con gran patio, luminoso y espacioso. Cocina con espacio para comedor diario. Lavadero. Dependencia de servicio con ba\u00f1o con ducha.Tres dormitorios, uno de ellos al frente y dos al contrafrente, uno de ellos en suite. Dos ba\u00f1os completos, uno de ellos con hidromasaje. Toilette. Ubicado a una cuadra de av. Cabildo, con m\u00faltiples l\u00edneas de colectivos y\nWhatsApp\nContactar", "revised": false, "rejected": false, "data": {"precio": "USD 280.000 + $170.000 expensas", "direccion": "Zabala al 2400", "metros": "120 m\u00b2 cubie.", "habitaciones": "3 dorm."}, "image": "https://static1.sosiva451.com/49257541/0f219a03-b27c-4449-abbd-a0cbec9e2661_u_small.jpg", "title": "Departamento 4 ambientes con cochera y patio - Venta - Belgrano "}, "https://www.argenprop.com/departamento-en-venta-en-belgrano-c-4-ambientes--16140041": {"date": "09-09-2024", "index": 32, "content": "1\n/1\n0\nUSD 350.000 + $316.188 expensas\nDEL LIBERTADOR AV. 5000\nDepartamento en Venta en Belgrano C, Belgrano\n139 m\u00b2 cubie.\n3 dorm.\n1 ba\u00f1o\nDEPARTAMENTO 3 DORMITORIOS - BELGRANO C/CHICO/BARRANCAS, CAPITAL FEDERAL\nMuy buen departamento al frente. Palier semi privado. Recepci\u00f3n de hall y living comedor. Toilette. 3 dormitorios (principal en suite). 1 ba\u00f1o completo. Cocina amplia y luminosa y lavadero. Ba\u00f1o de servicio. Orientaci\u00f3n este. Venta supeditada al cumplimiento por parte del propietario de los requisitos de la resoluci\u00f3n general 2371 de la afip. Superficie total uso propio uf: 139 m2 luminosidad: 10\nWhatsApp\nContactar", "revised": false, "rejected": false, "data": {"precio": "USD 350.000 + $316.188 expensas", "direccion": "DEL LIBERTADOR AV. 5000", "metros": "139 m\u00b2 cubie.", "habitaciones": "3 dorm."}, "image": null, "title": "DEPARTAMENTO 3 DORMITORIOS - BELGRANO C/CHICO/BARRANCAS, CAPITAL FEDERAL", "comment": "safsa fsa "}, "https://www.argenprop.com/departamento-en-venta-en-belgrano-4-ambientes--16100411": {"date": "09-09-2024", "index": 33, "content": "1\n/33\n635\nUSD 139.900 + $73.000 expensas\nBlanco Encalada 3300\nDepartamento en Venta en Belgrano, Capital Federal\n64 m\u00b2 cubie.\n3 dorm.\n60 a\u00f1os\nVENTA DEPARTAMENTO 4 AMBIENTES BELGRANO\nRenta en d\u00f3lares hasta diciembre 2025 descubr\u00ed la comodidad de vivir en un departamento de \u00e9poca en el tradicional barrio de belgrano, ubicado en la intersecci\u00f3n de las calles blanco encalada y super\u00ed. El departamento, ubicado en el tercer piso por escalera ofrece un ambiente tranquilo y familiar. Con cocina grande e independiente, es ideal para quienes disfrutan de la cocina y buscan un\nWhatsApp\nContactar", "revised": false, "rejected": false, "data": {"precio": "USD 139.900 + $73.000 expensas", "direccion": "Blanco Encalada 3300", "metros": "64 m\u00b2 cubie.", "habitaciones": "3 dorm."}, "image": null, "title": "VENTA DEPARTAMENTO  4 AMBIENTES   BELGRANO "}, "https://www.argenprop.com/departamento-en-venta-en-belgrano-r-4-ambientes--15883358": {"date": "09-09-2024", "index": 34, "content": "1\n/36\n0\nUSD 320.000 + $200.000 expensas\nAv de los Incas 3000\nDepartamento en Venta en Belgrano R, Belgrano\n100 m\u00b2 cubie.\n3 dorm.\n30 a\u00f1os\nDepartamento Piso en Venta en Belgrano R, Capital Federal, Buenos Aires\nSe vende piso de 4 ambientes ingreso por av de los incas y av elcano a mts de estacion de tren belgrano r a mts de av cramer el piso cuenta con 170 m2 aproximados excelente vista panoramica abierta espacio guarda coches 2 ba\u00f1os, 1 toilette, 3 dormitorios, living, comedor, cocina, ante cocina, lavadero, balco con cerramiento y mucho mas! Coordina tu visita numero de matricula: cucicba 8161 corredor\nWhatsApp\nContactar", "revised": false, "rejected": false, "data": {"precio": "USD 320.000 + $200.000 expensas", "direccion": "Av de los Incas 3000", "metros": "100 m\u00b2 cubie.", "habitaciones": "3 dorm."}, "image": null, "title": "Departamento Piso  en Venta en Belgrano R, Capital Federal, Buenos Aires"}, "https://www.argenprop.com/departamento-en-venta-en-belgrano-4-ambientes--16179489": {"date": "09-09-2024", "index": 35, "content": "1\n/46\n12.713\nUSD 820.000 + $999.146 expensas\nOlleros 2200, Piso 7\nDepartamento en Venta en Belgrano, Capital Federal\n154 m\u00b2 cubie.\n3 dorm.\n20 a\u00f1os\nExclusivo semipiso 4 amb con amenities, 2 cocheras y baulera\n4 amb. De categor\u00eda con vista al frente, ubicado en torre maison olleros. Emplazado en la exclusiva zona de embajadas en el barrio de belgrano, a metros de av. Luis mar\u00eda campos, av. Cabildo y estaci\u00f3n de subte olleros l\u00ednea d. Posee un amplio living comedor apaisado con dos balcones aterrazados en ambos extremos uno de ellos con cerramiento. Toilette de recepci\u00f3n. Uno de los 3 dormitorios en\nWhatsApp\nContactar", "revised": false, "rejected": false, "data": {"precio": "USD 820.000 + $999.146 expensas", "direccion": "Olleros 2200, Piso 7", "metros": "154 m\u00b2 cubie.", "habitaciones": "3 dorm."}, "image": "https://static1.sosiva451.com/98497161/588cdba8-acc0-4511-98bb-cd3258cd3f39_u_small.jpg", "title": "Exclusivo semipiso 4 amb con amenities, 2 cocheras y baulera"}, "https://www.argenprop.com/departamento-en-venta-en-belgrano-4-ambientes--8515444": {"date": "09-09-2024", "index": 36, "content": "1\n/11\n2\nUSD 128.000 + $98.000 expensas\nVirrey Del Pino 3400\nDepartamento en Venta en Belgrano, Capital Federal\n60 m\u00b2 cubie.\n3 dorm.\n45 a\u00f1os\nVirrey Del Pino 3400 Belgrano 4amb a reciclar U$128.000\nApto profesional. Semipiso de 4 ambientes a reciclar, al contrafrente. 1\u00ba piso. Orientaci\u00f3n oeste. Superficie cubierta y total de 60m\u00b2. Tres dormitorios, dos ba\u00f1os. Living-comedor, cocina. Estado a reciclar, luminoso. Pisos de cer\u00e1mica. Antig\u00fcedad 45 a\u00f1os.  Expensas $98.000 (septiembre 2024). Edificio de 6 pisos, 2 departamentos por piso. Apto cr\u00e9dito. Se puede tomar una propiedad en parte de\nWhatsApp\nContactar", "revised": false, "rejected": false, "data": {"precio": "USD 128.000 + $98.000 expensas", "direccion": "Virrey Del Pino 3400", "metros": "60 m\u00b2 cubie.", "habitaciones": "3 dorm."}, "image": "https://static1.sosiva451.com/4445158/8b21c253-a190-4123-9537-fed4946378a6_u_small.jpg", "title": "Virrey Del Pino 3400 Belgrano 4amb a reciclar U$128.000", "comment": "asdsad"}, "https://www.argenprop.com/departamento-en-venta-en-belgrano-4-ambientes--16150408": {"date": "09-09-2024", "index": 37, "content": "1\n/42\n0\nUSD 450.000 + $250.000 expensas\nZapiola 2600\nDepartamento en Venta en Belgrano, Capital Federal\n144 m\u00b2 cubie.\n3 dorm.\n4 a\u00f1os\nVENTA Duplex 4amb c/ balc\u00f3n y cochera en Belgrano!\nEl departamento se trata de un moderno departamento duplex de 156 mt2 totales con doble balc\u00f3n. En planta baja la unidad dispone de un amplio living comedor con salida a balc\u00f3n terraza. Cocina semi-integrada con horno y anafe electrico vitrocer\u00e1mico, conexi\u00f3n para lavavajillas, cesto de residuos incorporado a la mesada. Muebles bajo mesada y alacena y sector de lavadero separado. Pisos de madera\nWhatsApp\nContactar", "revised": false, "rejected": false, "data": {"precio": "USD 450.000 + $250.000 expensas", "direccion": "Zapiola 2600", "metros": "144 m\u00b2 cubie.", "habitaciones": "3 dorm."}, "image": "https://static1.sosiva451.com/80405161/0fb06967-defd-4df2-946a-a9860f71d085_u_small.jpg", "title": "VENTA Duplex 4amb c/ balc\u00f3n y cochera en Belgrano!"}, "https://www.argenprop.com/departamento-en-venta-en-belgrano-4-ambientes--15566433": {"date": "09-09-2024", "index": 38, "content": "1\n/45\n0\nUSD 192.900 + $350.000 expensas\nCIUDAD DE LA PAZ al 600\nDepartamento en Venta en Belgrano, Capital Federal\n92 m\u00b2 cubie.\n3 dorm.\n40 a\u00f1os\nDepartamento en Belgrano\nExcelente semipiso de 4 amb balc\u00f3n al frente todo luz y sol dependencia de servicio c/ ba\u00f1o cochera movil baulera palier privado entrada de servicio amplia cocina office lavadero independiente 3 dormitorios c/ placares ba\u00f1o completo toilette muy buena ubicacion a mts de av cabildo y subte linea\nWhatsApp\nContactar", "revised": false, "rejected": false, "data": {"precio": "USD 192.900 + $350.000 expensas", "direccion": "CIUDAD DE LA PAZ al 600", "metros": "92 m\u00b2 cubie.", "habitaciones": "3 dorm."}, "image": "https://static1.sosiva451.com/33466551/dbed4b4d-5efa-4964-800f-d9b9764a3028_u_small.jpg", "title": "Departamento en Belgrano"}, "https://www.argenprop.com/departamento-en-venta-en-belgrano-4-ambientes--16125891": {"date": "09-09-2024", "index": 39, "content": "1\n/22\n10\nUSD 199.900\nAmenabar 2900\nDepartamento en Venta en Belgrano, Capital Federal\n92 m\u00b2 cubie.\n3 dorm.\n2 ba\u00f1os\nVenta. Departamento. 4 ambientes. Amenabar 2900.\nCaracter\u00edsticas - superficie total: 96 m\u00b2. - Superficie cubierta: 86 m\u00b2 - superficie descubierta: 10 m\u00b2 - ambientes: 4. - Living comedor. - Cocina independiente. - Balc\u00f3n - ba\u00f1o completo: 2 (1 en suite) - dormitorios: 2 (con placard). - Disposici\u00f3n: contrafrente. - Baulera y cochera opcional. - Amenities (sum, parrilla, gimnasio,pileta). - Apto credito. Expensas $120.000.- Otros servicios: sum,\nWhatsApp\nContactar", "revised": false, "rejected": false, "data": {"precio": "USD 199.900", "direccion": "Amenabar 2900", "metros": "92 m\u00b2 cubie.", "habitaciones": "3 dorm."}, "image": "https://static1.sosiva451.com/19852161/d8ae1c0d-a473-4a66-9f4f-e25ae4bce0de_u_small.jpg", "title": "Venta. Departamento. 4 ambientes. Amenabar 2900."}, "https://www.argenprop.com/departamento-en-venta-en-belgrano-r-4-ambientes--14902234": {"date": "09-09-2024", "index": 40, "content": "1\n/109\n1\nUSD 367.725\nFranklin Roosevelt al 3100, entre Av. Dr. R. Balb\u00edn y Zapiola\nDepartamento en Venta en Belgrano R, Belgrano\n109 m\u00b2 cubie.\n3 dorm.\n2 ba\u00f1os\nPalacio Roccatagliata - Venta Departamento 4 Ambientes, en Construcci\u00f3n en Belgrano R\nEtapa final de obra. Piso alto con hermosas vistas en imponente torre de categor\u00eda con amenities premium. Excelente ubicaci\u00f3n de muy f\u00e1cil acceso, sobre franklin roosevelt, entre av. Dr. Ricardo balb\u00edn y zapiola. Amplio living comedor con salida a balc\u00f3n aterrazado corrido al frente con vista sobre av. Dr. Ricardo balb\u00edn. Toilette de recepci\u00f3n. Cocina comedor diario y\nWhatsApp\nContactar", "revised": false, "rejected": false, "data": {"precio": "USD 367.725", "direccion": "Franklin Roosevelt al 3100, entre Av. Dr. R. Balb\u00edn y Zapiola", "metros": "109 m\u00b2 cubie.", "habitaciones": "3 dorm."}, "image": "https://static1.sosiva451.com/43220941/dc3eb1d6-cbaf-4c39-ac31-e7fe37e4ee20_u_small.jpg", "title": "Palacio Roccatagliata - Venta Departamento 4 Ambientes, en Construcci\u00f3n en Belgrano R"}, "https://www.argenprop.com/departamento-en-venta-en-belgrano-r-4-ambientes--14902231": {"date": "09-09-2024", "index": 41, "content": "1\n/110\n1\nUSD 383.255\nFranklin Roosevelt al 3100, entre Av. Dr. R. Balb\u00edn y Zapiola\nDepartamento en Venta en Belgrano R, Belgrano\n100 m\u00b2 cubie.\n3 dorm.\n2 ba\u00f1os\nTorres Roccatagliata - Venta Departamento 4 Ambientes con Terraza en Construcci\u00f3n en Belgrano R\nEtapa final de obra. Piso alt\u00edsimo con hermosas vistas, torre de categor\u00eda con exclusivos amenities premium. Excelente ubicaci\u00f3n de muy f\u00e1cil acceso, sobre franklin roosevelt, entre av. Dr. Ricardo balb\u00edn y zapiola. Amplio living comedor con salida a imponente terraza corrida al frente de 47,23 m2 con vista sobre zapiola. Cocina con muebles completos, mesada de granito y, anafe de 4 hornallas\nWhatsApp\nContactar", "revised": false, "rejected": false, "data": {"precio": "USD 383.255", "direccion": "Franklin Roosevelt al 3100, entre Av. Dr. R. Balb\u00edn y Zapiola", "metros": "100 m\u00b2 cubie.", "habitaciones": "3 dorm."}, "image": "https://static1.sosiva451.com/13220941/0ca890f1-3e86-4c13-af04-7ad9c3d3837c_u_small.jpg", "title": "Torres Roccatagliata - Venta Departamento 4 Ambientes con Terraza en Construcci\u00f3n en Belgrano R"}, "https://www.argenprop.com/departamento-en-venta-en-belgrano-4-ambientes--12658084": {"date": "09-09-2024", "index": 42, "content": "1\n/26\n500\nUSD 235.000 + $215.000 expensas\nJ De Amenabar 2300, Piso 1\nDepartamento en Venta en Belgrano, Capital Federal\n107 m\u00b2 cubie.\n3 dorm.\n2 ba\u00f1os\nSEMIPISO 4 AMBIENTES C/ DEPENDENCIA - AL FRENTE - LUMINOSO - EN EXCELENTE UBICACI\u00d3N\nExcelente ubicacion calle amenabar entre olazabal y moldes, consta de living de 4,10 x 6,50 mts pisos parquet, y amplio ventanal. Balc\u00f3n corrido. Cocina comedor con doble circulaci\u00f3n de 1,70 x 5,30 mts.dormitorio frente de 4,10 x 3,50 con placad. Dormitorio frente de 3,50 x 3,20 dormitorio de 3,3 x 3,50 mts al contrafrente. Dormitorio de servicio de 2,70 x 2,00 con ba\u00f1o de 1,30 x 1 mts.\nWhatsApp\nContactar", "revised": false, "rejected": false, "data": {"precio": "USD 235.000 + $215.000 expensas", "direccion": "J De Amenabar 2300, Piso 1", "metros": "107 m\u00b2 cubie.", "habitaciones": "3 dorm."}, "image": "https://static1.sosiva451.com/48085621/81ff34f3-d66a-4a2c-a278-c46344e1f88e_u_small.jpg", "title": "SEMIPISO 4 AMBIENTES C/ DEPENDENCIA - AL FRENTE - LUMINOSO - EN EXCELENTE UBICACI\u00d3N"}, "https://www.argenprop.com/departamento-en-venta-en-belgrano-4-ambientes--16046496": {"date": "09-09-2024", "index": 43, "content": "1\n/34\n0\nUSD 295.000 + $110.000 expensas\nAvenida Olaz\u00e1bal 3700\nDepartamento en Venta en Belgrano, Capital Federal\n83 m\u00b2 cubie.\n3 dorm.\n49 a\u00f1os\nVenta Dpto Piso Belgrano R 4 amb balc\u00f3n terraza\nVenta de excelente piso, planta 7, espectacular vista panor\u00e1mica por tener balc\u00f3n terraza y corrido en forma de l hacia las calles olaz\u00e1bal y r\u00f3mulo na\u00f3n, donde nace belgrano r. Palier privado, ingreso principal hacia living comedor e ingreso a dependecia / cocina. Ambas puertas blindadas. Al ingresar a la unidad encontramos un amplio living comedor con salida a balc\u00f3n aterrazado a trav\u00e9s de\nContactar", "revised": false, "rejected": false, "data": {"precio": "USD 295.000 + $110.000 expensas", "direccion": "Avenida Olaz\u00e1bal 3700", "metros": "83 m\u00b2 cubie.", "habitaciones": "3 dorm."}, "image": "https://static1.sosiva451.com/69464061/ca8d43c8-81ea-4d4b-8cc7-8c64723dd3a6_u_small.jpg", "title": "Venta Dpto Piso Belgrano R 4 amb balc\u00f3n terraza "}, "https://www.argenprop.com/departamento-en-venta-en-belgrano-4-ambientes--16178750": {"date": "09-09-2024", "index": 44, "content": "1\n/23\n0\nUSD 418.286\nAmen\u00e1bar y Olleros - Unidad 2H\nDepartamento en Venta en Belgrano, Capital Federal\n128 m\u00b2 cubie.\n3 dorm.\n2 ba\u00f1os\nDepartamento - Belgrano\nEspectacular 4 ambientes al contrafrente, con excelente vista a pulm\u00f3n, con luz y sol, gran balc\u00f3n corrido aterrazado. El mismo cuenta con amplia recepci\u00f3n, master suite con vestidor y ba\u00f1o compartimentado, dos dormitorios, ba\u00f1o completo, toilette de recepci\u00f3n y cocina independiente. Consulte por otras unidades de este emprendimiento ( en otro piso, otra ubicaci\u00f3n y otras\nWhatsApp\nContactar", "revised": false, "rejected": false, "data": {"precio": "USD 418.286", "direccion": "Amen\u00e1bar y Olleros - Unidad 2H", "metros": "128 m\u00b2 cubie.", "habitaciones": "3 dorm."}, "image": "https://static1.sosiva451.com/05787161/d442f0c6-2986-4d86-b92e-67291267c73a_u_small.jpg", "title": "Departamento - Belgrano"}, "https://www.argenprop.com/departamento-en-venta-en-belgrano-4-ambientes--15427623": {"date": "09-09-2024", "index": 45, "content": "1\n/26\n0\nUSD 399.000\n3 de Febrero al 2300\nDepartamento en Venta en Belgrano, Capital Federal\n120 m\u00b2 cubie.\n3 dorm.\n15 a\u00f1os\nVENTA DEPARTAMENTO 4 AMBIENTES EN BELGRANO-TERRAZA PROPIA-AMENITIES\nDepartamento de 4 ambiente, se ingresa por palier privado. Amplio living comedor muy luminoso con salida a balc\u00f3n terraza a la calle. Toilette. C\u00f3moda y funcional cocina con generosos espacio de guardado, lavadero y dependencia de servicio con ba\u00f1o. Dormitorio en suite, los otros dos comparten ba\u00f1o. Todos los dormitorios con grades ventanales y\nWhatsApp\nContactar", "revised": false, "rejected": false, "data": {"precio": "USD 399.000", "direccion": "3 de Febrero al 2300", "metros": "120 m\u00b2 cubie.", "habitaciones": "3 dorm."}, "image": "https://static1.sosiva451.com/32672451/c3c7c491-678e-41a0-99ba-7f3e0fcdc742_u_small.jpg", "title": "VENTA DEPARTAMENTO 4 AMBIENTES EN BELGRANO-TERRAZA PROPIA-AMENITIES"}, "https://www.argenprop.com/departamento-en-venta-en-colegiales-4-ambientes--15971090": {"date": "09-09-2024", "index": 46, "content": "1\n/28\n0\nUSD 360.000\nVirrey Olaguer y Feliu 3400\nDepartamento en Venta en Colegiales, Capital Federal\n146 m\u00b2 cubie.\n3 dorm.\n11 a\u00f1os\n3 DORMITORIOS C/ COCHERA Y PILETA\n\u00a1Lujoso departamente en venta en colegiales! \u00a1Escucha ofertas! 4 ambientes en una de las zonas m\u00e1s bonitas de capital federal, a una cuadra de belgrano r. Este departamento tipo d\u00faplex te ofrece un estilo moderno para vivir o una gran oportunidad de inversi\u00f3n para rentar por su alta demanda tanto en pesos como en d\u00f3lares. 3 dormitorios (uno con espacio de vestidor o playroom a elecci\u00f3n) 2\nWhatsApp\nContactar", "revised": false, "rejected": false, "data": {"precio": "USD 360.000", "direccion": "Virrey Olaguer y Feliu 3400", "metros": "146 m\u00b2 cubie.", "habitaciones": "3 dorm."}, "image": "https://static1.sosiva451.com/09017951/2a8a9280-332e-48d0-a9bf-fd05f7420606_u_small.jpg", "title": "3 DORMITORIOS C/ COCHERA Y PILETA "}, "https://www.argenprop.com/departamento-en-venta-en-belgrano-barrancas-4-ambientes--15901375": {"date": "09-09-2024", "index": 47, "content": "1\n/17\n1\nUSD 188.000\nCabildo 3100\nDepartamento en Venta en Belgrano Barrancas, Belgrano\n86 m\u00b2 cubie.\n3 dorm.\n22 a\u00f1os\nVista abierta 3 dormitorios, baulera sobre Avda. Cabildo\nKruger propiedades - ci. Miriam kruger matr. Cucicba 6417 t\u00b01 l\u00b0 239 retasado - sobre avda. Cabildo en nu\u00f1ez a pasos de belgrano. Edificio de 14 pisos, semipiso con balc\u00f3n corrido al frente con vista abierta a la ciudad. Tres dormitorios con living comedor, ba\u00f1o completo y toilette. Cocina separada con comedor diario, lavadero y habitaci\u00f3n de servicio. Baulera. Con todos los transportes del\nContactar", "revised": false, "rejected": false, "data": {"precio": "USD 188.000", "direccion": "Cabildo 3100", "metros": "86 m\u00b2 cubie.", "habitaciones": "3 dorm."}, "image": "https://static1.sosiva451.com/57310951/70217530-39ab-46d5-a067-cbdfe638a375_u_small.jpg", "title": "Vista abierta 3 dormitorios, baulera sobre Avda. Cabildo"}, "https://www.argenprop.com/departamento-en-venta-en-belgrano-barrancas-4-ambientes--15807656": {"date": "09-09-2024", "index": 48, "content": "1\n/16\n502\nUSD 320.000 + $310.000 expensas\nAguilar 2300\nDepartamento en Venta en Belgrano Barrancas, Belgrano\n110 m\u00b2 cubie.\n3 dorm.\n3 ba\u00f1os\nDepartamento en venta de 3 dormitorios c/ cochera en Belgran\nLibre ya lo maneja ariel unico cuatro ambientes con balcon terraza y cochera belgrano, 4 amb, 110m + 10m, ag\u00fcero 2300, u$s 320.000, $310.000 de expensas (sep 2024) descripcion: \u00fanico cuatro ambientes en la mejor zona de belgrano piso de 4 ambientes, muy luminoso con vista abierta. Consta de palier privado, muy amplio living y comedor con salida a balc\u00f3n corrido de 10mts, toilette, 3\nContactar", "revised": false, "rejected": false, "data": {"precio": "USD 320.000 + $310.000 expensas", "direccion": "Aguilar 2300", "metros": "110 m\u00b2 cubie.", "habitaciones": "3 dorm."}, "image": "https://static1.sosiva451.com/65670851/f9edf804-0765-4bf7-a8bf-7214ff644cfb_u_small.jpg", "title": "Departamento en venta de 3 dormitorios c/ cochera en Belgran"}, "https://www.argenprop.com/departamento-en-venta-en-belgrano-4-ambientes--12675972": {"date": "09-09-2024", "index": 49, "content": "1\n/15\n2\nUSD 173.000 + $180.000 expensas\nBlanco Encalada 2300, Piso 11\nDepartamento en Venta en Belgrano, Capital Federal\n67 m\u00b2 cubie.\n3 dorm.\n45 a\u00f1os\nDepto. 4 amb Frente Balcon APTO Prof. Cochera BELGRANO\nVenta.Depto. 4 amb frente 78m2 balc\u00f3n apto profesional cochera fija -belgrano blanco encalada entre av cabildo y v.De obligado 200m subte \"d\" metrob\u00fas \"\" se toma depto, en la zona en parte de pago \"\" disposicion : frente piso : 11\u00b0 superf total: 78m2 aprox superf cub : 67m2 aprox dormitorios : ( 3) 3,00x,30 c/placar* 3,00x2,50 c/pl y el ultimo independiente o abierto\nWhatsApp\nContactar", "revised": false, "rejected": false, "data": {"precio": "USD 173.000 + $180.000 expensas", "direccion": "Blanco Encalada 2300, Piso 11", "metros": "67 m\u00b2 cubie.", "habitaciones": "3 dorm."}, "image": "https://static1.sosiva451.com/27957621/bc319d27-5af9-496e-b62e-06445a627589_u_small.jpg", "title": "Depto. 4 amb Frente Balcon APTO Prof. Cochera BELGRANO"}, "https://www.argenprop.com/departamento-en-venta-en-belgrano-4-ambientes--16159499": {"date": "09-09-2024", "index": 50, "content": "1\n/25\n0\nUSD 210.000 + $150.000 expensas\nBlanco Encalada 2700\nDepartamento en Venta en Belgrano, Capital Federal\n71 m\u00b2 cubie.\n3 dorm.\n47 a\u00f1os\nVENTA 4 AMB /CON BALCON Y PATIO EN BELGRANO\nVenta 4 amb. Amlio con balcon y patio -belgrano descripcion de la propiedad *hermoso departamento semipiso de 4 ambientes en blanco encalada entre moldes y vidal * amplio living -con comedor integrado *cocina con muy buenas medidas con iluminaci\u00f3n natural con vista abierta. *Todos a gas. *Habitaci\u00f3n principal con placad incorporado y con vista y salida al patio. * Segunda habitaci\u00f3n un poco\nContactar", "revised": false, "rejected": false, "data": {"precio": "USD 210.000 + $150.000 expensas", "direccion": "Blanco Encalada 2700", "metros": "71 m\u00b2 cubie.", "habitaciones": "3 dorm."}, "image": "https://static1.sosiva451.com/99495161/22aa5341-c1b8-4cac-851d-b1eb69c9c8ff_u_small.jpg", "title": "VENTA 4 AMB /CON BALCON Y PATIO EN BELGRANO"}, "https://www.argenprop.com/departamento-en-venta-en-belgrano-4-ambientes--16150838": {"date": "09-09-2024", "index": 51, "content": "1\n/22\n0\nUSD 360.000 + $290.000 expensas\nEcheverr\u00eda 2200\nDepartamento en Venta en Belgrano, Capital Federal\n132 m\u00b2 cubie.\n3 dorm.\n50 a\u00f1os\nDepartamento - Venta - Argentina, Capital Federal - Echeverr\u00eda 2200\nVenta de departamento 4 ambientes en belgrano, capital federal semipiso de 4 ambientes, emplazado en quinto piso en la esquina de echeverr\u00eda y cuba. Con palier pivado, balc\u00f3n, cochera y baulera. Ubicaci\u00f3n: - frente a la plaza manuel belgrano - a 100 mts de av juramento - a 200 mts de av cabildo - a 400 mts de barrancas de belgrano - a 700 mts de av libertador - proximidad medios de\nWhatsApp\nContactar", "revised": false, "rejected": false, "data": {"precio": "USD 360.000 + $290.000 expensas", "direccion": "Echeverr\u00eda 2200", "metros": "132 m\u00b2 cubie.", "habitaciones": "3 dorm."}, "image": null, "title": "Departamento - Venta - Argentina, Capital Federal - Echeverr\u00eda 2200"}, "https://www.argenprop.com/departamento-en-venta-en-belgrano-4-ambientes--16004477": {"date": "09-09-2024", "index": 52, "content": "1\n/31\n0\nUSD 550.000 + $500.000 expensas\nAv cramer 2400\nDepartamento en Venta en Belgrano, Capital Federal\n142 m\u00b2 cubie.\n3 dorm.\n3 ba\u00f1os\n4 AMB + 2 COCHERAS BELGRANO\nDepartamento posibilidad 4 ambientes con 2 cocheras, belgrano  metraje - 151 m2 totales - 142 m2 cubiertos - 9 m2 balcon  descripcion - departamento + 2 cocheras + baulera - master suite con vestidor - segundo dormitorio con dos placares doble hoja c/espejo - posibilidad 3er dormitorio en la l del living comedor, originalmente era dormitorio. - Ba\u00f1o completo con ba\u00f1era - cocina\nWhatsApp\nContactar", "revised": false, "rejected": false, "data": {"precio": "USD 550.000 + $500.000 expensas", "direccion": "Av cramer 2400", "metros": "142 m\u00b2 cubie.", "habitaciones": "3 dorm."}, "image": "https://static1.sosiva451.com/77440061/4957dc9f-5155-4c02-b65a-fb7af3a2d519_u_small.jpg", "title": "4 AMB + 2 COCHERAS BELGRANO"}, "https://www.argenprop.com/departamento-en-venta-en-belgrano-r-4-ambientes--16158772": {"date": "09-09-2024", "index": 53, "content": "1\n/18\n0\nUSD 430.000 + $300.000 expensas\nConesa 1900\nDepartamento en Venta en Belgrano R, Belgrano\n125 m\u00b2 cubie.\n3 dorm.\n47 a\u00f1os\nSEMI PISO 4 AMBIENTES CON BALCON COCHERA Y BAULERA\nVta 4 amb. Con dep. Cochera y baulera belgrano r. Vta 4 ambientes con dependencia,cochera, baulera ubicado en el piso 8 sobre la calle conesa entre sucre y echeverr\u00eda. Excelente estado. 3 dormitorios 2 ba\u00f1os completos m\u00e1s dependencia de servicio muy luminoso. Con palier privado. Cercano a subtes d, estaci\u00f3n tren belgrano r y plaza castelli. Dise\u00f1o simple y din\u00e1mico.Ambientes\nContactar", "revised": false, "rejected": false, "data": {"precio": "USD 430.000 + $300.000 expensas", "direccion": "Conesa 1900", "metros": "125 m\u00b2 cubie.", "habitaciones": "3 dorm."}, "image": "https://static1.sosiva451.com/27785161/bcdda65d-30a8-4382-bfbf-2326063bcc75_u_small.jpg", "title": "SEMI PISO 4 AMBIENTES CON BALCON COCHERA Y BAULERA"}, "https://www.argenprop.com/departamento-en-venta-en-belgrano-4-ambientes--15941584": {"date": "09-09-2024", "index": 54, "content": "1\n/33\n0\nUSD 225.000 + $130.000 expensas\nVidal 2000\nDepartamento en Venta en Belgrano, Capital Federal\n86 m\u00b2 cubie.\n2 dorm.\n34 a\u00f1os\nVENTA Departamento 3 A C/D-Cochera-Baulera\nDepartamento en un tercer piso al frente, con balcon corrido. 3 ambientes con dependencia, baulera y cochera ( segun escritura espacio guardacoche) en el edificio que se encuentra frente a esta unidad, 2 dormitorios con placard, amplio living comedor, cocina comedor diario, lavadero aparte, dependencia con ba\u00f1o de servicio, un ba\u00f1o completo, un toilette, muy luminoso al frente y tambien en el\nContactar", "revised": false, "rejected": false, "data": {"precio": "USD 225.000 + $130.000 expensas", "direccion": "Vidal 2000", "metros": "86 m\u00b2 cubie.", "habitaciones": "2 dorm."}, "image": "https://static1.sosiva451.com/48514951/262e8f82-f681-448c-ac9b-9ac874434a7f_u_small.jpg", "title": "VENTA Departamento 3 A C/D-Cochera-Baulera"}, "https://www.argenprop.com/departamento-en-venta-en-belgrano-4-ambientes--15368851": {"date": "09-09-2024", "index": 55, "content": "1\n/55\n0\nUSD 214.000 + $169.000 expensas\nJose Hernandez 2500\nDepartamento en Venta en Belgrano, Capital Federal\n104 m\u00b2 cubie.\n3 dorm.\n50 a\u00f1os\nDepartamento - Venta - Argentina, Capital Federal - Jose Hernandez 2500\nOportunidad venta departamento 4 ambientes en belgrano,( tipo ph ) con dos patios, capital federal. Hermoso 4 ambientes en el barrio de belgrano. Cuenta con:  -2 patios propios. - Living con aire acondicionado. - 2 toilettes  -1 ba\u00f1o ubicaci\u00f3n preferencial, a una cuadra de cabildo, 10 cuadras de plaza barrancas y a 5 de plaza moldes. F\u00e1cil acceso a l\u00edneas de colectivo y al subte l\u00ednea\nWhatsApp\nContactar", "revised": false, "rejected": false, "data": {"precio": "USD 214.000 + $169.000 expensas", "direccion": "Jose Hernandez 2500", "metros": "104 m\u00b2 cubie.", "habitaciones": "3 dorm."}, "image": null, "title": "Departamento - Venta - Argentina, Capital Federal - Jose Hernandez 2500"}, "https://www.argenprop.com/departamento-en-venta-en-colegiales-4-ambientes--15928356": {"date": "09-09-2024", "index": 56, "content": "1\n/14\n0\nUSD 425.000\nZ\u00e1rraga 3600\nDepartamento en Venta en Colegiales, Capital Federal\n150 m\u00b2 cubie.\n3 dorm.\n3 ba\u00f1os\nDepartamento 4 Ambientes Duplex en Colegiales\nDepartamento 4 ambientes en duplex con balcon terraza en pozo a la venta en belgrano bienvenidos a la oportunidad de adquirir la residencia de tus sue\u00f1os en uno de los barrios m\u00e1s deseables de la ciudad. Presentamos una exclusiva selecci\u00f3n de departamentos de 1, 2, 3 y 4 ambientes ubicados en la calle z\u00e1rraga, belgrano, capital federal. Detalles de la propiedad: departamento de 4 ambientes en\nWhatsApp\nContactar", "revised": false, "rejected": false, "data": {"precio": "USD 425.000", "direccion": "Z\u00e1rraga 3600", "metros": "150 m\u00b2 cubie.", "habitaciones": "3 dorm."}, "image": "https://static1.sosiva451.com/65382951/7828dd7a-5dfd-4171-909e-9c9ae4e1c8f9_u_small.jpg", "title": "Departamento 4 Ambientes Duplex en Colegiales"}, "https://www.argenprop.com/departamento-en-venta-en-colegiales-4-ambientes--15995867": {"date": "09-09-2024", "index": 57, "content": "1\n/11\n0\nUSD 290.000\nPalpa 3300\nDepartamento en Venta en Colegiales, Capital Federal\n98 m\u00b2 cubie.\n3 dorm.\n3 ba\u00f1os\nDepartamento - Venta - Argentina, Capital Federal - Palpa 3300\nVenta departamento 4 ambientes con balcon terraza con parrilla en colegiales en construccion se trata de una zona residencial y gastron\u00f3mica, a pocas cuadras de av. Lacroze. Tiene casas bajas, calles arboladas. En este lugar se respira la creatividad y la tendencia en el aire. Cuenta con: -planta baja -4 pisos y terrazas individuales -excelentes terminaciones e instalaciones el departamento\nWhatsApp\nContactar", "revised": false, "rejected": false, "data": {"precio": "USD 290.000", "direccion": "Palpa 3300", "metros": "98 m\u00b2 cubie.", "habitaciones": "3 dorm."}, "image": "https://static1.sosiva451.com/76859951/6e9cb1dc-f8c8-44fb-939d-87b5111c926d_u_small.jpg", "title": "Departamento - Venta - Argentina, Capital Federal - Palpa 3300"}, "https://www.argenprop.com/departamento-en-venta-en-colegiales-4-ambientes--15995737": {"date": "09-09-2024", "index": 58, "content": "1\n/12\n0\nUSD 420.000\nPalpa 3300\nDepartamento en Venta en Colegiales, Capital Federal\n98 m\u00b2 cubie.\n3 dorm.\n3 ba\u00f1os\nDepartamento - Venta - Argentina, Capital Federal - Palpa 3300\nVenta 4 ambientes en duplex con terraza en colegiales - en construcci\u00f3n se encuentra a pocas cuadras de av. Lacroze. Se trata de una zona residencial y gastron\u00f3mica. Tiene casas bajas, calles arboladas. En este lugar se respira la creatividad y la tendencia en el aire. Cuenta con: -planta baja -4 pisos  y terrazas individuales -excelentes  terminaciones e instalaciones el departamento 4\u00bab\nWhatsApp\nContactar", "revised": false, "rejected": false, "data": {"precio": "USD 420.000", "direccion": "Palpa 3300", "metros": "98 m\u00b2 cubie.", "habitaciones": "3 dorm."}, "image": "https://static1.sosiva451.com/73759951/fce34cae-0ce1-4555-8af1-446a6b44af45_u_small.jpg", "title": "Departamento - Venta - Argentina, Capital Federal - Palpa 3300"}, "https://www.argenprop.com/departamento-en-venta-en-belgrano-4-ambientes--15400775": {"date": "09-09-2024", "index": 59, "content": "1\n/17\n0\nUSD 205.000 + $50.000 expensas\nVIRREY DEL PINO 2800\nDepartamento en Venta en Belgrano, Capital Federal\n68 m\u00b2 cubie.\n3 dorm.\n60 a\u00f1os\nDepartamento de 4 ambientes en Venta en Belgrano\n3 ambientes con dependencia. Edificio en esquina. Muy bien ubicado,cerca subte, y varias lineas de colectivo cerca. Zona muy comercial. Comercializa migliorisi de corrientes 4599 srl profesional responsable jorge daniel gomez cpi 261 a29825 se deja constancia que las caracteristicas, medidas, expensas y superficies consignadas son aproximadas, sujetos a verificaci\u00f3n y/o ajuste. El precio del\nWhatsApp\nContactar", "revised": false, "rejected": false, "data": {"precio": "USD 205.000 + $50.000 expensas", "direccion": "VIRREY DEL PINO 2800", "metros": "68 m\u00b2 cubie.", "habitaciones": "3 dorm."}, "image": "https://static1.sosiva451.com/57700451/11616385-dbb1-4528-8597-a09a07688e1d_u_small.jpg", "title": "Departamento de 4 ambientes en Venta en Belgrano "}}