{"https://www.argenprop.com/departamento-en-alquiler-en-balvanera-3-ambientes--15655895": {"id": "19072693", "date": "07-05-2024\n", "index": 1, "content": "1\n/12\n1\n$ 400.000 + $27.000 expensas\nBoulogne Sur Mer 700\nDepartamento en Alquiler en Balvanera, Capital Federal\n68 m\u00b2 cubie.\n2 dorm.\n40 a\u00f1os\nAlquiler - Venta- 3 amb - Balvanera - Bajas expensas - Luminoso- subte linea H y B\nSe entrega en octubre imperdible alquiler 3 ambientes muy luminoso con doble balc\u00f3n! Ba\u00f1o reciclado semi amoblado lavadero y cocina independiente con ventilaci\u00f3n natural. Cercano a todos los medios de transporte, colectivos y subtes (linea h y b) a 1 cuadra de av. Pueyrredon, 2 cuadras de av. Cordoba y 2 de av. Corrientes aceptamos garant\u00eda respaldar,\nWhatsApp\nContactar", "revised": false, "rejected": false, "data": {"precio": "$ 400.000 + $27.000 expensas", "expensas": "+ $27.000 expensas", "direccion": "Boulogne Sur Mer 700", "metros": "68 m\u00b2 cubie.", "habitaciones": "2 dorm."}, "image": "https://static1.sosiva451.com/59855651/29fb7ddb-b287-45f1-8915-5a4b651249a4_u_small.jpg", "title": "Alquiler - Venta- 3 amb - Balvanera - Bajas expensas - Luminoso- subte linea H y B"}, "https://www.argenprop.com/ph-en-alquiler-en-balvanera-3-ambientes--15612992": {"id": "19029936", "date": "07-05-2024\n", "index": 4, "content": "1\n/14\n24\n$ 600.000\nChile 2100, Piso 1\nPH en Alquiler en Balvanera, Capital Federal\n120 m\u00b2 cubie.\n2 dorm.\n30 a\u00f1os\nPh - Alquiler - Argentina, Capital Federal - Chile 2180\nAlquiler de departamento 3 ambientes en balvanera, capital federal divino departamento tipo ph de 123 m2, cuenta con amplio living comedor con ventanal al frente, cocina comedor con muebles en madera, horno y anafes empotrados, dos ba\u00f1os completos y dos dormitorios con placard, primer piso por escalera. No paga expensas, gastos comunes en $20.000\nWhatsApp\nContactar", "revised": false, "rejected": false, "data": {"precio": "$ 600.000", "direccion": "Chile 2100, Piso 1", "metros": "120 m\u00b2 cubie.", "habitaciones": "2 dorm."}, "image": "https://static1.sosiva451.com/29921651/4fa760c2-5ec5-4cae-a1b0-1b441d31464b_u_small.jpg", "title": "Ph - Alquiler - Argentina, Capital Federal - Chile 2180"}, "https://www.argenprop.com/departamento-en-alquiler-en-once-3-ambientes--15621666": {"id": "19038620", "date": "07-05-2024\n", "index": 5, "content": "1\n/6\n101\n$ 300.000\nAvenida Corrientes 2200\nDepartamento en Alquiler en Once, Capital Federal\n80 m\u00b2 cubie.\n2 dorm.\n1 ba\u00f1o\n3 AMB CON 2 PATIOS, FALTA PINTURA Y DETALLES ( BARRIO: ONCE)\n3 amb con 2 patios, falta pintura y detalles ( barrio: once), living comedor , 2 dormitorios grandes, cocina ba\u00f1o completo, dependencia, lavadero y 2 patios.\nContactar", "revised": false, "rejected": true, "data": {"precio": "$ 300.000", "direccion": "Avenida Corrientes 2200", "metros": "80 m\u00b2 cubie.", "habitaciones": "2 dorm."}, "image": "https://static1.sosiva451.com/66612651/1a11ef73-3711-417e-a159-8fc85f03046b_u_small.jpg", "title": "3 AMB CON 2 PATIOS, FALTA PINTURA Y DETALLES ( BARRIO: ONCE)"}, "https://www.argenprop.com/departamento-en-alquiler-en-balvanera-4-ambientes--15572824": {"id": "18989734", "date": "07-05-2024\n", "index": 6, "content": "1\n/24\n0\n$ 700.000 + $103.854 expensas\nViamonte 2500\nDepartamento en Alquiler en Balvanera, Capital Federal\n75 m\u00b2 cubie.\n3 dorm.\n52 a\u00f1os\nAlquiler - AMOBLADO - 3 dormitorios\nAlquiler amoblado departamento ubicado en piso 11, de 75m2 cubiertos distribuidos en un living \u2013 comedor de muy generosas medidas, importante cocina con un abundante alacena y bajo mesada, todo a medida con lavadero incorporado. Amplio pasillo de distribuci\u00f3n a los 3 dormitorios, todos con placares de con mucho espacio, se destaca las bauleras en la parte superior. Ba\u00f1o completo mas toilette de\nContactar", "revised": false, "rejected": true, "data": {"precio": "$ 700.000 + $103.854 expensas", "expensas": "+ $103.854 expensas", "direccion": "Viamonte 2500", "metros": "75 m\u00b2 cubie.", "habitaciones": "3 dorm."}, "image": "https://static1.sosiva451.com/42827551/571f0eea-fa77-4151-9738-b410afd8b7f5_u_small.jpg", "title": "Alquiler - AMOBLADO - 3 dormitorios"}, "https://www.argenprop.com/departamento-en-alquiler-en-balvanera-3-ambientes--15651582": {"id": "19068382", "date": "07-05-2024\n", "index": 9, "content": "1\n/23\n0\n$ 480.000\nViamonte al 2100\nDepartamento en Alquiler en Balvanera, Capital Federal\n70 m\u00b2 cubie.\n2 dorm.\n30 a\u00f1os\nAlquiler de Departamento 3 ambientes en barrio Balvanera\nAlquiler de departamento 3 ambientes muy luminoso apto profesional. Departamento ubicado sobre la calle viamonte entre junin y pdte. Jos\u00e9 evaristo uriburu, a 1 cuadra de la estaci\u00f3n facultad de medicina, linea subte d y a 3 cuadras de la estaci\u00f3n pasteur linea subte b, cercano y con acceso a otros medios de transporte p\u00fablico, cerca de la plaza\nContactar", "revised": false, "rejected": true, "data": {"precio": "$ 480.000", "direccion": "Viamonte al 2100", "metros": "70 m\u00b2 cubie.", "habitaciones": "2 dorm."}, "image": "https://static1.sosiva451.com/28515651/444dbd58-a110-4733-8db3-b3408378b1f0_u_small.jpg", "title": "Alquiler de Departamento 3 ambientes en barrio Balvanera"}, "https://www.argenprop.com/departamento-en-alquiler-en-balvanera-3-ambientes--15622903": {"id": "19039855", "date": "07-05-2024\n", "index": 16, "content": "1\n/12\n0\n$ 400.000 + $50.000 expensas\nIndependencia 1200\nDepartamento en Alquiler en Balvanera, Capital Federal\n70 m\u00b2 cubie.\n2 dorm.\n50 a\u00f1os\nDepartamento en alquiler barrio Balvanera\nDepartamento de 70m2, cuenta con un ba\u00f1o con ducha y adem\u00e1s ba\u00f1o privado. Posee un patio descubierto, buen ingreso de luz natural. Muy buena ubicaci\u00f3n, cercano a avenida 9 de julio y universidad uade. Muy bien conectado con transporte p\u00fablico: transportes cercanos: colectivos: 2, 9, 10, 17, 23, 39, 45, 53, 57, 59, 60, 67, 70, 91, 96, 98, 100, 102, 126, 129, 168, 195 subtes\nWhatsApp\nContactar", "revised": false, "rejected": true, "data": {"precio": "$ 400.000 + $50.000 expensas", "expensas": "+ $50.000 expensas", "direccion": "Independencia 1200", "metros": "70 m\u00b2 cubie.", "habitaciones": "2 dorm."}, "image": "https://static1.sosiva451.com/30922651/e3593ebf-1977-463a-86ff-962d98167d38_u_small.jpg", "title": "Departamento en  alquiler barrio Balvanera "}, "https://www.argenprop.com/departamento-en-alquiler-en-balvanera-3-ambientes--15622904": {"id": "19039856", "date": "07-05-2024\n", "index": 17, "content": "1\n/12\n0\n$ 400.000 + $50.000 expensas\nIndependencia 1200\nDepartamento en Alquiler en Balvanera, Capital Federal\n70 m\u00b2 cubie.\n2 dorm.\n50 a\u00f1os\nDepartamento en alquiler barrio Balvanera\nDepartamento de 70m2, cuenta con un ba\u00f1o con ducha y adem\u00e1s ba\u00f1o privado. Posee un patio descubierto, buen ingreso de luz natural. Muy buena ubicaci\u00f3n, cercano a avenida 9 de julio y universidad uade. Muy bien conectado con transporte p\u00fablico: transportes cercanos: colectivos: 2, 9, 10, 17, 23, 39, 45, 53, 57, 59, 60, 67, 70, 91, 96, 98, 100, 102, 126, 129, 168, 195 subtes\nWhatsApp\nContactar", "revised": false, "rejected": true, "data": {"precio": "$ 400.000 + $50.000 expensas", "expensas": "+ $50.000 expensas", "direccion": "Independencia 1200", "metros": "70 m\u00b2 cubie.", "habitaciones": "2 dorm."}, "image": "https://static1.sosiva451.com/40922651/18f2bff7-1cf2-4d99-81c8-765fcb18c9c0_u_small.jpg", "title": "Departamento en  alquiler barrio Balvanera "}, "https://www.argenprop.com/departamento-en-alquiler-en-balvanera-3-ambientes--15607616": {"id": "19024559", "date": "07-05-2024\n", "index": 20, "content": "1\n/9\n0\n$ 550.000 + $22.000 expensas\nTucuman al 2800\nDepartamento en Alquiler en Balvanera, Capital Federal\n70 m\u00b2 cubie.\n2 dorm.\n40 a\u00f1os\nDepartamento Amueblado con baj\u00edsimas expensas\nDepartamento 3 ambientes en alquiler excelente ubicaci\u00f3n, a unas cuadras de av. Pueyrred\u00f3n y av. Corriente. Cercan\u00eda con varias l\u00edneas de colectivo y subterr\u00e1neos edificio tranquilo, de pocas unidades funcionales. Emplazado en solo 2 pisos. Comparte un patio interno de uso com\u00fan. Ubicado en un primer piso por escalera. Cuenta con cocina equipada con heladera, microondas, pava\nWhatsApp\nContactar", "revised": false, "rejected": true, "data": {"precio": "$ 550.000 + $22.000 expensas", "expensas": "+ $22.000 expensas", "direccion": "Tucuman al 2800", "metros": "70 m\u00b2 cubie.", "habitaciones": "2 dorm."}, "image": "https://static1.sosiva451.com/61670651/be350132-7f07-4ba3-8c5b-4f93b8e2d324_u_small.jpg", "title": "Departamento Amueblado con baj\u00edsimas expensas"}, "https://www.argenprop.com/departamento-en-alquiler-en-congreso-3-ambientes--14883089": {"id": "18327474", "date": "07-05-2024\n", "index": 21, "content": "1\n/17\n500\n$ 400.000 + $52.000 expensas\nSan Jose 300, Piso 5\nDepartamento en Alquiler en Congreso, Capital Federal\n60 m\u00b2 cubie.\n2 dorm.\n1 ba\u00f1o\nDepartamento - Alquiler - Argentina, Capital Federal - San Jose 347\nAlquiler de departamento 3 ambientes en congreso, capital federal. Cuenta con dos dormitorios con placard, ba\u00f1o completo, cocina amplia y luminosa, y living con balcon. No se aceptan mascotas. Requisito: garantia propietaria de caba y provincia de bs.As. (Fliar directo) o seguro de caucion. Lineas de comunicacion: whatsapp: /    maxi luz propiedades (mxp-mxp-1553)\nWhatsApp\nContactar", "revised": false, "rejected": false, "data": {"precio": "$ 400.000 + $52.000 expensas", "expensas": "+ $52.000 expensas", "direccion": "San Jose 300, Piso 5", "metros": "60 m\u00b2 cubie.", "habitaciones": "2 dorm."}, "image": "https://static1.sosiva451.com/98038841/f325e4cf-f0f8-4d22-a244-524d51a4fe7e_u_small.jpg", "title": "Departamento - Alquiler - Argentina, Capital Federal - San Jose 347"}, "https://www.argenprop.com/departamento-en-alquiler-en-once-4-ambientes--15623337": {"id": "19040288", "date": "07-05-2024\n", "index": 22, "content": "1\n/12\n720\n$ 450.000 + $76.700 expensas\nAvenida Corrientes 2600, Piso 7\nDepartamento en Alquiler en Once, Capital Federal\n86 m\u00b2 cubie.\n3 dorm.\n45 a\u00f1os\nOnce 4 amb frente due\u00f1o Av. Corrientes esq. Paso.\nAv. Corrientes al 2600 esquina paso 422, a una cuadra de la avda. Pueyrred\u00f3n y el cruce del subte b (estaci\u00f3n pueyrred\u00f3n) y del subte h (estaci\u00f3n corrientes). Departamento de 4 amb. Todos al frente en 7mo piso; dos entradas, doble circulaci\u00f3n, hall de recepci\u00f3n, living comedor, dormitorios con placard, todos a la calle con ventanales sobre paso al 400. Ba\u00f1o completo, toilette y ba\u00f1o de servicio,\nWhatsApp\nContactar", "revised": false, "rejected": false, "data": {"precio": "$ 450.000 + $76.700 expensas", "expensas": "+ $76.700 expensas", "direccion": "Avenida Corrientes 2600, Piso 7", "metros": "86 m\u00b2 cubie.", "habitaciones": "3 dorm."}, "image": "https://static1.sosiva451.com/73332651/63491695-6269-42ed-9e8a-bd1885ec219f_u_small.jpg", "title": "Once 4 amb frente due\u00f1o Av. Corrientes esq. Paso. "}, "https://www.argenprop.com/departamento-en-alquiler-en-congreso-3-ambientes--15644927": {"id": "19061871", "date": "07-05-2024\n", "index": 24, "content": "1\n/24\n0\n$ 380.000 + $78.600 expensas\nHipolito Yrigoyen y Rincon\nDepartamento en Alquiler en Congreso, Capital Federal\n105 m\u00b2 cubie.\n2 dorm.\n80 a\u00f1os\nDepartamento de 3 ambientes con dependencia en primer piso - Apto profesional\nAmplio departamento de tres ambientes con dependencia. Al ingreso c\u00f3moda recepci\u00f3n de 4,5 x 3.4 con pisos plastificados. En paralelo otro ambiente de 3.4 x 2.4 que podr\u00eda destinarse a comedor. Sala de grandes dimensiones de 8,5 x 3,7. Ideal para clases o exposiciones. Posibilidad de subidividir para hacer otra habitaci\u00f3n. Sector de cocina separada. Ba\u00f1o con\nWhatsApp\nContactar", "revised": false, "rejected": true, "data": {"precio": "$ 380.000 + $78.600 expensas", "expensas": "+ $78.600 expensas", "direccion": "Hipolito Yrigoyen y Rincon", "metros": "105 m\u00b2 cubie.", "habitaciones": "2 dorm."}, "image": "https://static1.sosiva451.com/72944651/51f3993f-08db-4a14-9952-d5ba6f524b95_u_small.jpg", "title": "Departamento de 3 ambientes con dependencia en primer piso - Apto profesional"}, "https://www.argenprop.com/departamento-en-alquiler-en-balvanera-4-ambientes--15617750": {"id": "19034700", "date": "07-05-2024\n", "index": 27, "content": "1\n/58\n0\n$ 650.000 + $180.000 expensas\nLarrea al 700\nDepartamento en Alquiler en Balvanera, Capital Federal\n80 m\u00b2 cubie.\n3 dorm.\n40 a\u00f1os\nLarrea al 700 - 3 amb c/dep y balc\u00f3n - FACULTAD - Alquiler\nDepartamento de 4 amb c/balc\u00f3n contrafrente semi-piso muy luminoso encargado diurno seguridad nocturna palier semi-privado living-comedor con aire acondicionado balc\u00f3n al contrafrente dormitorio con placard dormitorio con placard dormitorio con placard amplia cocina completa a nueva comedor diario cocina el\u00e9ctrica vitrocer\u00e1mica a nuevo horno el\u00e9ctrico a nuevo termotanque a\nContactar", "revised": false, "rejected": true, "data": {"precio": "$ 650.000 + $180.000 expensas", "expensas": "+ $180.000 expensas", "direccion": "Larrea al 700", "metros": "80 m\u00b2 cubie.", "habitaciones": "3 dorm."}, "image": "https://static1.sosiva451.com/05771651/9e13857e-2891-4bad-ae53-a5bf86605b21_u_small.jpg", "title": "Larrea al 700 - 3 amb c/dep y balc\u00f3n - FACULTAD - Alquiler"}, "https://www.argenprop.com/departamento-en-alquiler-en-balvanera-4-ambientes--15627739": {"id": "19044698", "date": "07-05-2024\n", "index": 29, "content": "1\n/23\n0\n$ 430.000 + $65.000 expensas\nM\u00e9xico al 1800\nDepartamento en Alquiler en Balvanera, Capital Federal\n78 m\u00b2 cubie.\n3 dorm.\n70 a\u00f1os\nDepartamento en Balvanera\nDepartamento en alquiler en balvanera ubicado en una planta baja, de tres ambientes con posibilidad de un cuarto ambiente (altillo adaptable para descanso o almacenamiento) y baulera. La habitaci\u00f3n principal cuenta con un amplio placard empotrado nuevo. Cocina reciclada a nueva. Patio interno con lavadero. La unidad se entrega sin pintar, pero con todos los materiales necesarios\nWhatsApp\nContactar", "revised": false, "rejected": true, "data": {"precio": "$ 430.000 + $65.000 expensas", "expensas": "+ $65.000 expensas", "direccion": "M\u00e9xico al 1800", "metros": "78 m\u00b2 cubie.", "habitaciones": "3 dorm."}, "image": "https://static1.sosiva451.com/93772651/3870de0a-c4a2-4e9e-9dd9-a9f2a2f2d141_u_small.jpg", "title": "Departamento en  Balvanera"}, "https://www.argenprop.com/departamento-en-alquiler-en-balvanera-3-ambientes--15631761": {"id": "19048722", "date": "07-05-2024\n", "index": 31, "content": "1\n/22\n200\n$ 440.000 + $46.000 expensas\nAlberti 300, Piso 10\nDepartamento en Alquiler en Balvanera, Capital Federal\n72 m\u00b2 cubie.\n2 dorm.\n28 a\u00f1os\nA MTS AV. BELGRANO y EST SUBTE H, AMPLIO 3 AMBIENTES CON BALCON AL CFTE, VISTA ABIERTA C/AIRE SPLIT\nSuper luminoso departamento de 3 ambientes en contra-frente, moderno, con 2 equipos de aire acondicionado split frio-calor amplio living comedor con salida al balc\u00f3n, 2 dormitorios con placard, ba\u00f1o completo, cocina amplia con comedor diario, lavadero. Adem\u00e1s cuenta con una puerta de acceso blindada, pisos de parquet plastificados. Oportunidad precio: $ 440.000 mensuales el primer\nWhatsApp\nContactar", "revised": false, "rejected": false, "data": {"precio": "$ 440.000 + $46.000 expensas", "expensas": "+ $46.000 expensas", "direccion": "Alberti 300, Piso 10", "metros": "72 m\u00b2 cubie.", "habitaciones": "2 dorm."}, "image": "https://static1.sosiva451.com/16713651/dad3e9ad-f01d-4f83-b225-e90dcd014854_u_small.jpg", "title": "A MTS AV. BELGRANO y EST SUBTE H, AMPLIO 3 AMBIENTES CON BALCON AL CFTE, VISTA ABIERTA C/AIRE SPLIT "}, "https://www.argenprop.com/departamento-en-alquiler-en-balvanera-3-ambientes--15631222": {"id": "19048183", "date": "07-05-2024\n", "index": 34, "content": "1\n/18\n0\n$ 580.000 + $60.000 expensas\nLavalle al 2900\nDepartamento en Alquiler en Balvanera, Capital Federal\n80 m\u00b2 cubie.\n2 dorm.\nA Estrenar\nDepartamento en alquiler 3 ambientes con balcon\nSe alquila departamento de 3 ambientes con balcon. Se encuentra en un 9no piso, amplio departamento de 3 ambientes: cuenta con living comedor con salida al balc\u00f3n, cocina separada, sala comedor, lavadero con ba\u00f1o, dormitorio principal con salida al balc\u00f3n y placard, dormitorio secundario con placard, ba\u00f1o completo. Expensas $60.000 requisitos comerciales *garantia propietaria o garant\u00eda\nWhatsApp\nContactar", "revised": false, "rejected": true, "data": {"precio": "$ 580.000 + $60.000 expensas", "expensas": "+ $60.000 expensas", "direccion": "Lavalle al 2900", "metros": "80 m\u00b2 cubie.", "habitaciones": "2 dorm."}, "image": "https://static1.sosiva451.com/22213651/51efe552-3b3e-4622-a997-839fcdc24470_u_small.jpg", "title": "Departamento en alquiler 3 ambientes con balcon"}, "https://www.argenprop.com/departamento-en-alquiler-en-congreso-3-ambientes--15619169": {"id": "19036121", "date": "07-05-2024\n", "index": 37, "content": "1\n/33\n2\n$ 450.000 + $110.000 expensas\nIndependencia al 1800\nDepartamento en Alquiler en Congreso, Capital Federal\n95 m\u00b2 cubie.\n2 dorm.\n50 a\u00f1os\nDepartamento - Congreso\nAlquiler amplio y c\u00f3modo depto de 3 ambientes mas escritorio y dependencia de servicio al frente con balc\u00f3n , mucha luz! 2 dormitorios con c\u00f3modos placards caja de seguridad empotrada. 1 ba\u00f1o completo m\u00e1s ba\u00f1o de servicio amplio living comedor,cocina con comedor de diario y\nWhatsApp\nContactar", "revised": false, "rejected": false, "data": {"precio": "$ 450.000 + $110.000 expensas", "expensas": "+ $110.000 expensas", "direccion": "Independencia al 1800", "metros": "95 m\u00b2 cubie.", "habitaciones": "2 dorm."}, "image": "https://static1.sosiva451.com/96191651/a1b21a7a-a593-49cf-ad72-fa1e74c17099_u_small.jpg", "title": "Departamento - Congreso"}, "https://www.argenprop.com/departamento-en-alquiler-en-balvanera-4-ambientes--15521180": {"id": "18947048", "date": "07-05-2024\n", "index": 38, "content": "1\n/14\n0\n$ 550.000 + $74.000 expensas\nCORRIENTES 2400\nDepartamento en Alquiler en Balvanera, Capital Federal\n106 m\u00b2 cubie.\n3 dorm.\n68 a\u00f1os\nDepartamento - Alquiler - Argentina, Capital Federal - CORRIENTES 2400\nAlquiler de departamento 4 ambientes en balvanera, capital federal alquiler tradicional a 2 a\u00f1os bienvenido a tu nuevo hogar en balvanera! Este encantador departamento de 4 ambientes de 106 m2, ubicado en el segundo piso con vista al cruce de las calles larrea y corrientes, te ofrece una experiencia de vida \u00fanica en uno de los barrios m\u00e1s vibrantes\nWhatsApp\nContactar", "revised": false, "rejected": false, "data": {"precio": "$ 550.000 + $74.000 expensas", "expensas": "+ $74.000 expensas", "direccion": "CORRIENTES 2400", "metros": "106 m\u00b2 cubie.", "habitaciones": "3 dorm."}, "image": "https://static1.sosiva451.com/08112551/98a4c0c8-2f9f-4b59-94b1-b6b8c157df2f_u_small.jpg", "title": "Departamento - Alquiler - Argentina, Capital Federal - CORRIENTES 2400"}, "https://www.argenprop.com/departamento-en-alquiler-en-congreso-3-ambientes--15593641": {"id": "19010563", "date": "07-05-2024\n", "index": 40, "content": "1\n/8\n0\n$ 500.000 + $100.000 expensas\nAvenida Corrientes 2000\nDepartamento en Alquiler en Congreso, Capital Federal\n74 m\u00b2 cubie.\n2 dorm.\n44 a\u00f1os\nALQUILER DEPARTAMENTO 3 AMB Dependencia BALCON\nDepartamento 3 ambientes con dependencia balcon contrafrente   luminoso ideal estudiantes - zona facultad no se aceptan mascotas.  Corredor responsable: veronica grela reina cucicba 4731 / cmcpsi 6470 - contacto: olga helguera - mls id # -126 remax argentina s.R.L. No ejerce el corretaje inmobiliario. El presente sitio web es una plataforma en donde cada oficina inmobiliaria independiente que\nContactar", "revised": false, "rejected": false, "data": {"precio": "$ 500.000 + $100.000 expensas", "expensas": "+ $100.000 expensas", "direccion": "Avenida Corrientes 2000", "metros": "74 m\u00b2 cubie.", "habitaciones": "2 dorm."}, "image": "https://static1.sosiva451.com/14639551/5d24724c-0e7f-48b8-9dc6-e127d8923705_u_small.jpg", "title": "ALQUILER DEPARTAMENTO 3 AMB Dependencia BALCON"}, "https://www.argenprop.com/departamento-en-alquiler-en-balvanera-3-ambientes--15277808": {"id": "18712693", "date": "07-05-2024\n", "index": 43, "content": "1\n/13\n201\n$ 690.000 + $90.000 expensas\nJuncal 3000\nDepartamento en Alquiler en Balvanera, Capital Federal\n70 m\u00b2 cubie.\n3 dorm.\n3 ambientes\nDEPTO 3 AMB CON DEPENDENCIA EN BUEN ESTADO AL FRENTE CON BALCON\nExcelente depto de 3 amb con balcon al frente en buena ubicacion en la zona de barrio norte - living comedor .Cocina independiente - 2 dormitorios con placard / 1 dependencia de servicio / 2 ba\u00f1o - acceso a balcon desde el living -expensas $ 90000 consultas x what saap al consulte info por favor aclarar en el mensaje de whatsapp si es con mascotas - si tiene seguro de caucion o\nWhatsApp\nContactar", "revised": false, "rejected": true, "data": {"precio": "$ 690.000 + $90.000 expensas", "expensas": "+ $90.000 expensas", "direccion": "Juncal 3000", "metros": "70 m\u00b2 cubie.", "habitaciones": "3 dorm."}, "image": "https://static1.sosiva451.com/80877251/5deeca07-cc26-45af-b2da-5440a3a53bd0_u_small.jpg", "title": "DEPTO 3 AMB CON DEPENDENCIA EN  BUEN ESTADO AL FRENTE CON BALCON "}, "https://www.argenprop.com/departamento-en-alquiler-en-balvanera-3-ambientes--15623757": {"id": "19040713", "date": "07-05-2024\n", "index": 45, "content": "1\n/20\n0\n$ 550.000 + $98.000 expensas\nPichincha 500\nDepartamento en Alquiler en Balvanera, Capital Federal\n65 m\u00b2 cubie.\n2 dorm.\n39 a\u00f1os\nALQUILER DEPARTAMENTO 3 AMBIENTES BALVANERA\nExcelente departamento al frente, con balcon corrido de tres ambientes con dependencia muy luminoso. Pisos de madera ba\u00f1o completo ba\u00f1o de servicio cocina separda lavadero excelente ubicacion, cerca de medios de transporte. Requisitos: mes de alquiler mes de deposito de garantia seguro de caucion por , garantor o garantia ya transportes cercanos colectivos: 2, 8, 23, 56, 57, 61, 62, 64, 84, 86,\nContactar", "revised": false, "rejected": false, "data": {"precio": "$ 550.000 + $98.000 expensas", "expensas": "+ $98.000 expensas", "direccion": "Pichincha 500", "metros": "65 m\u00b2 cubie.", "habitaciones": "2 dorm."}, "image": "https://static1.sosiva451.com/75732651/bbd2a1e1-d02a-40e9-8ee4-62aa9b8d051c_u_small.jpg", "title": "ALQUILER DEPARTAMENTO 3 AMBIENTES  BALVANERA"}, "https://www.argenprop.com/departamento-en-alquiler-en-once-3-ambientes--15590611": {"id": "19007534", "date": "07-05-2024\n", "index": 46, "content": "1\n/20\n1\n$ 350.000 + $49.000 expensas\nTucuman al 2600\nDepartamento en Alquiler en Once, Capital Federal\n64 m\u00b2 cubie.\n2 dorm.\n60 a\u00f1os\nDepartamento en Once\nDepartamento de 3 ambientes lateral, amplio y luminoso. Esta ubicado en la calle tucuman al 2600, entre avda. Pueyrred\u00f3n y paso, proximo a avda. Corrientes, avda. Rivadavia, colectivos, comercios, subte linea a, b y h. Pida tasaci\u00f3n: efectuada por profesionales, que analizan permanentemente el desenvolvimiento del mercado. Conf\u00ede su\nContactar", "revised": false, "rejected": false, "data": {"precio": "$ 350.000 + $49.000 expensas", "expensas": "+ $49.000 expensas", "direccion": "Tucuman al 2600", "metros": "64 m\u00b2 cubie.", "habitaciones": "2 dorm."}, "image": "https://static1.sosiva451.com/11609551/26137739-82bc-4bbc-a43c-b7e5bae673ec_u_small.jpg", "title": "Departamento en Once"}, "https://www.argenprop.com/departamento-en-alquiler-en-once-3-ambientes--15590652": {"id": "19007574", "date": "07-05-2024\n", "index": 47, "content": "1\n/20\n1\n$ 350.000 + $49.000 expensas\nTucuman al 2600\nDepartamento en Alquiler en Once, Capital Federal\n64 m\u00b2 cubie.\n2 dorm.\n60 a\u00f1os\nDepartamento en Once\nDepartamento de 3 ambientes lateral, amplio y luminoso. Esta ubicado en la calle tucuman al 2600, entre avda. Pueyrred\u00f3n y paso, proximo a avda. Corrientes, avda. Rivadavia, colectivos, comercios, subte linea a, b y h. Pida tasaci\u00f3n: efectuada por profesionales, que analizan permanentemente el desenvolvimiento del mercado. Conf\u00ede su\nContactar", "revised": false, "rejected": true, "data": {"precio": "$ 350.000 + $49.000 expensas", "expensas": "+ $49.000 expensas", "direccion": "Tucuman al 2600", "metros": "64 m\u00b2 cubie.", "habitaciones": "2 dorm."}, "image": "https://static1.sosiva451.com/25609551/a04f1ec5-9c32-4be4-aa02-529bb03d7bec_u_small.jpg", "title": "Departamento en Once"}, "https://www.argenprop.com/departamento-en-alquiler-en-congreso-3-ambientes--15620554": {"id": "19037509", "date": "07-05-2024\n", "index": 48, "content": "1\n/18\n500\n$ 480.000 + $65.000 expensas\nRincon al 400\nDepartamento en Alquiler en Congreso, Capital Federal\n63 m\u00b2 cubie.\n2 dorm.\n65 a\u00f1os\nRincon al 400 - Depto 3 amb. en alquiler, Congreso - Excelente estado!\nMuy lindo depto 3 ambientes, en excelente estado. Ubicado en muy buen edifcio. El depto se compone de: - living comedor - amplia cocina con bajo mesada y alacena, con espacio para comedor diario - lavadero exterior - habitacion de generosas medidas - 2da habitacion con gran placard - ba\u00f1o completo. Todo en buen estado, recien pintado. Muy luminoso. Silencioso. Requisitos de alquiler: mes de\nWhatsApp\nContactar", "revised": false, "rejected": false, "data": {"precio": "$ 480.000 + $65.000 expensas", "expensas": "+ $65.000 expensas", "direccion": "Rincon al 400", "metros": "63 m\u00b2 cubie.", "habitaciones": "2 dorm."}, "image": "https://static1.sosiva451.com/45502651/def24efe-4d12-4c4f-8d96-51aeb15a1b14_u_small.jpg", "title": "Rincon al 400  - Depto 3 amb. en alquiler, Congreso - Excelente estado! "}, "https://www.argenprop.com/departamento-en-alquiler-en-balvanera-4-ambientes--15582584": {"id": "18999510", "date": "07-05-2024\n", "index": 49, "content": "1\n/22\n1\n$ 400.000 + $75.000 expensas\nJunin al 700\nDepartamento en Alquiler en Balvanera, Capital Federal\n62 m\u00b2 cubie.\n3 dorm.\nA Estrenar\nDepto. Exclusivo Uso Comercial / Oficina / Consultorio - Facultad de Medicina - Balvanera\nDepto. Exclusivo uso comercial, oficina, consultorio en facultad de medicina - balvanera la unidad se encuentra en perfectas condiciones, equipada con aire acondicionado y placas de calefacci\u00f3n el\u00e9ctricas. La recepci\u00f3n cuenta con escritorio y placares. Ba\u00f1o completo y toilette reciclados. 3 ambientes/oficinas/consultorios, 2 de ellos con placares y salida al patio, que cuenta con\nWhatsApp\nContactar", "revised": false, "rejected": true, "data": {"precio": "$ 400.000 + $75.000 expensas", "expensas": "+ $75.000 expensas", "direccion": "Junin al 700", "metros": "62 m\u00b2 cubie.", "habitaciones": "3 dorm."}, "image": "https://static1.sosiva451.com/48528551/ec2d0e65-15a3-459d-8801-d1594ca98fe8_u_small.jpg", "title": "Depto. Exclusivo Uso Comercial / Oficina / Consultorio - Facultad de Medicina - Balvanera"}, "https://www.argenprop.com/departamento-en-alquiler-en-balvanera-3-ambientes--15593723": {"id": "19010644", "date": "07-05-2024\n", "index": 50, "content": "1\n/15\n10\n$ 550.000 + $84.000 expensas\nAdolfo Alsina 2000, Piso 8\nDepartamento en Alquiler en Balvanera, Capital Federal\n63 m\u00b2 cubie.\n2 dorm.\n45 a\u00f1os\nALQUILER 3 AMBIENTES AMPLIO LUMINOSO ZONA CONGRESO\nLindo departamento de 3 ambientes, al fente, con balc\u00f3n, amplio y luminoso, vista abierta, cocina y lavadero, 2 dormitorios con placards, recien pintado, muy buen estado. Proximo a av. Belgrano y callao. Condiciones del alquiler: ingresos comprobables y garantia en caba. Contrato 2 a\u00f1os con ajustes trimestrales por ipc. 1 mes de adelanto, 1 mes de dep\u00f3sito, gastos de averiguaci\u00f3n de garant\u00eda y\nContactar", "revised": false, "rejected": false, "data": {"precio": "$ 550.000 + $84.000 expensas", "expensas": "+ $84.000 expensas", "direccion": "Adolfo Alsina 2000, Piso 8", "metros": "63 m\u00b2 cubie.", "habitaciones": "2 dorm."}, "image": "https://static1.sosiva451.com/32739551/90d7268e-6133-4160-bfcd-49856691d518_u_small.jpg", "title": "ALQUILER 3 AMBIENTES AMPLIO LUMINOSO ZONA CONGRESO"}, "https://www.argenprop.com/departamento-en-alquiler-en-balvanera-3-ambientes--15588915": {"id": "19005840", "date": "07-05-2024\n", "index": 52, "content": "1\n/17\n0\n$ 490.000 + $95.000 expensas\nSarmiento al 2100\nDepartamento en Alquiler en Balvanera, Capital Federal\n75 m\u00b2 cubie.\n2 dorm.\n60 a\u00f1os\nSarmiento al 2100 - 3 amb c/escritorio -\nC\u00f3modo departamento de 3 amb con escritorio (posible 3er dormitorio) al frente muy luminoso. Amplia cocina con espacio de comedor diario pisos de parquet. Agua caliente central. Pr\u00f3ximo de facultad de medicina. Cercano a subtes b, a y d. Dormitorio dormitorio living escritorio/3er dormitorio . Cocina con espacio comedor diario lavadero en cocina. Ba\u00f1o.\nContactar", "revised": false, "rejected": false, "data": {"precio": "$ 490.000 + $95.000 expensas", "expensas": "+ $95.000 expensas", "direccion": "Sarmiento al 2100", "metros": "75 m\u00b2 cubie.", "habitaciones": "2 dorm."}, "image": "https://static1.sosiva451.com/51988551/9aeae362-926a-44f8-929c-bf009201c1a8_u_small.jpg", "title": "Sarmiento al 2100 - 3 amb c/escritorio -"}, "https://www.argenprop.com/departamento-en-alquiler-en-congreso-3-ambientes--15589882": {"id": "19006807", "date": "07-05-2024\n", "index": 54, "content": "1\n/23\n101\n$ 550.000 + $70.000 expensas\nAvenida Rivadavia 1500\nDepartamento en Alquiler en Congreso, Capital Federal\n80 m\u00b2 cubie.\n2 dorm.\n50 a\u00f1os\n80 m, 2 o 3 Dor Recicl Cfte Sol y Luz Coc, Lav. Excelente Ubicacion m Sbte\nExcelente departamento contrafrente de 80 m2 reciclado a nuevo. Ubicado enfrente de la plaza de los 2 congresos, a mts del subte y a un paso de todos. El departamento tiene luz, sol y vista en todos los ambientes. Tiene excelente living y comedor, 2 grandes dormitorios y una dependencia, ba\u00f1o completo con ventana, muy buena cocina con comedor o family,ba\u00f1o de servicio o toilette, lavadero. Los\nWhatsApp\nContactar", "revised": false, "rejected": false, "data": {"precio": "$ 550.000 + $70.000 expensas", "expensas": "+ $70.000 expensas", "direccion": "Avenida Rivadavia 1500", "metros": "80 m\u00b2 cubie.", "habitaciones": "2 dorm."}, "image": "https://static1.sosiva451.com/28898551/e0ab3e78-8e3c-4ee7-a0c6-eeacacb9ec44_u_small.jpg", "title": "80 m, 2 o 3 Dor Recicl Cfte Sol y Luz Coc, Lav. Excelente Ubicacion m Sbte"}, "https://www.argenprop.com/departamento-en-alquiler-en-balvanera-3-ambientes--15527485": {"id": "18953382", "date": "07-05-2024\n", "index": 55, "content": "1\n/25\n501\n$ 500.000 + $60.000 expensas\nEcuador 900, Piso 1\nDepartamento en Alquiler en Balvanera, Capital Federal\n65 m\u00b2 cubie.\n2 dorm.\n3 ambientes\nDepartamento 3 ambientes en Alquiler\nDepartamento de 3 ambientes en alquiler consta de un amplio living comedor con balcon al contrafrente cocina separada con muebles altos y bajo mesada lavadero separado con pileta y espacio de lavarropas 2 dormitorios con placard empotrado, ba\u00f1o completo excelente ubicacion a metros de av cordoba 2 cuadras de av pueyrredon y subte cordoba requisitos: demostracion de ingresos, seguro de caucion,\nWhatsApp\nContactar", "revised": false, "rejected": false, "data": {"precio": "$ 500.000 + $60.000 expensas", "expensas": "+ $60.000 expensas", "direccion": "Ecuador 900, Piso 1", "metros": "65 m\u00b2 cubie.", "habitaciones": "2 dorm."}, "image": "https://static1.sosiva451.com/58472551/2a14e775-7405-4b3f-bc2d-103f349b07db_u_small.jpg", "title": "Departamento 3 ambientes en Alquiler"}, "https://www.argenprop.com/departamento-en-alquiler-en-balvanera-3-ambientes--15614101": {"id": "19031038", "date": "07-05-2024\n", "index": 56, "content": "1\n/14\n0\n$ 450.000\nAvenida Rivadavia 3000\nDepartamento en Alquiler en Balvanera, Capital Federal\n72 m\u00b2 cubie.\n2 dorm.\n61 a\u00f1os\nAlquiler Residencial 3 Amb. 71 m2. Balvanera\nAlquiler residencial departamento de tres ambientes en edificio de estilo,de 71 mts 2 . El estado de la propiedad es muy bueno, luminoso en en todos sus ambientes, buena ventilaci\u00f3n. Ubicada en el 2do piso \u201cfrente\u201d balc\u00f3n con vista abierta sobre avenida, cuenta con: - amplio hall de entrada - living / comedor - cocina amplia con mesa (comedor diario) - lavadero integrado en cocina. -\nContactar", "revised": false, "rejected": false, "data": {"precio": "$ 450.000", "direccion": "Avenida Rivadavia 3000", "metros": "72 m\u00b2 cubie.", "habitaciones": "2 dorm."}, "image": "https://static1.sosiva451.com/10141651/69010ff7-42f0-4da8-b3d1-5006729af1ea_u_small.jpg", "title": "Alquiler Residencial 3 Amb. 71 m2. Balvanera"}, "https://www.argenprop.com/departamento-en-alquiler-en-balvanera-3-ambientes--15507132": {"id": "18932996", "date": "07-05-2024\n", "index": 57, "content": "1\n/18\n2\n$ 500.000\nVenezuela 1700, Piso 1\nDepartamento en Alquiler en Balvanera, Capital Federal\n70 m\u00b2 cubie.\n2 dorm.\n50 a\u00f1os\nALQUILER ANUAL 3 Ambientes amoblado. Gran cocina. Balc\u00f3n. FUNDACION FAVALORO\nAlquiler anual amoblado de 3 ambientes a metros fundaci\u00f3n favaloro. Departamento de estilo cl\u00e1sico. Este acogedor 3 ambientes, con su encanto de \u00e9poca, te invita a disfrutar de una experiencia aut\u00e9ntica. Living comedor, con salida a un balc\u00f3n al frente, te ofrece un espacio luminoso y confortable. La luz natural que entra por las ventanas ilumina todo el ambiente. La cocina, completa y funcional,\nWhatsApp\nContactar", "revised": false, "rejected": false, "data": {"precio": "$ 500.000", "direccion": "Venezuela 1700, Piso 1", "metros": "70 m\u00b2 cubie.", "habitaciones": "2 dorm."}, "image": "https://static1.sosiva451.com/23170551/296c8f7a-6155-4d76-b2af-1a75794066ad_u_small.jpg", "title": "ALQUILER ANUAL 3 Ambientes amoblado. Gran cocina. Balc\u00f3n. FUNDACION FAVALORO"}, "https://www.argenprop.com/casa-en-alquiler-en-balvanera-4-ambientes--15606536": {"id": "19023476", "date": "07-05-2024\n", "index": 58, "content": "1\n/11\n0\n$ 400.000\nAgrelo al 3085\nCasa en Alquiler en Balvanera, Capital Federal\n195 m\u00b2 cubie.\n2 dorm.\n40 a\u00f1os\nCasa - Balvanera\nLocal en alquiler a metros de la entrada al hospital ramos mejia, siempre funciono gastronomia (bar-restaurante) cocina completa con 2 ba\u00f1os\nWhatsApp\nContactar", "revised": false, "rejected": false, "data": {"precio": "$ 400.000", "direccion": "Agrelo al 3085", "metros": "195 m\u00b2 cubie.", "habitaciones": "2 dorm."}, "image": "https://static1.sosiva451.com/63560651/00a9f4a5-0408-4b13-beca-5b37476e2fa0_u_small.jpg", "title": "Casa - Balvanera"}, "https://www.argenprop.com/departamento-en-alquiler-en-congreso-3-ambientes--15563634": {"id": "18980550", "date": "07-05-2024\n", "index": 59, "content": "1\n/19\n500\n$ 500.000 + $24.700 expensas\nRincon al 100\nDepartamento en Alquiler en Congreso, Capital Federal\n79 m\u00b2 cubie.\n2 dorm.\n91 a\u00f1os\nRincon al 100 - Depto 3 ambientes en alquiler, Barrio de Congreso - Generosas medidas!\nHermoso departamento de estilo al frente. Se compone de: - hall de entrada - habitacion al frente, con salida a balcon frances. - Living comedor, amplio con salida a balc\u00f3n, - 2da habitacion con ropero - ba\u00f1o completo - amplia cocina comedor con espacio para lavarropas ubicado a 100mts de av. Rivadavia y s\u00f3lo 3 cuadras del congreso nacional. Muy buen estado. Pisos de\nWhatsApp\nContactar", "revised": false, "rejected": false, "data": {"precio": "$ 500.000 + $24.700 expensas", "expensas": "+ $24.700 expensas", "direccion": "Rincon al 100", "metros": "79 m\u00b2 cubie.", "habitaciones": "2 dorm."}, "image": "https://static1.sosiva451.com/43636551/0d1998e3-3dde-48d0-9ced-6ef086d741b1_u_small.jpg", "title": "Rincon al 100 - Depto 3 ambientes en alquiler, Barrio de Congreso - Generosas medidas!"}}