{"https://www.argenprop.com/departamento-en-alquiler-en-parque-patricios-2-ambientes--15646143": {"date": "05-05-2024\n", "content": "1\n/7\n1.150\n$ 280.000 + $38.000 expensas\nSanta cruz 100, Piso 1\nDepartamento en Alquiler en Parque Patricios, Capital Federal\n40 m\u00b2 cubie.\n1 dorm.\n50 a\u00f1os\nDepartamento en alquiler en Parque Patricios\nDepartamento 2 ambientes amplios, muy luminoso, con ba\u00f1o a estrenar. Primer piso por escaleras y en excelente estado. Due\u00f1o directo con 1 mes de deposito y mes por adelantado con garantia o similar\nWhatsApp\nContactar", "revised": true, "rejected": false, "data": {"precio": "$ 280.000 + $38.000 expensas", "expensas": "+ $38.000 expensas", "direccion": "Santa cruz 100, Piso 1", "metros": "40 m\u00b2 cubie.", "habitaciones": "1 dorm."}, "comment": "bien. sin balcon. parque patricios. 2 amb"}, "https://www.argenprop.com/departamento-en-alquiler-en-parque-centenario-1-ambiente--15204728": {"date": "05-05-2024\n", "content": "1\n/7\n0\n$ 270.000 + $20.000 expensas\nAGUIRRE 100\nDepartamento en Alquiler en Parque Centenario, Capital Federal\n30 m\u00b2 cubie.\n7 a\u00f1os\n1 ba\u00f1o\nDepartamento de 1 ambiente en Alquiler en Parque centenario\n1 ambientes nuevo, moderno edificio de viviendas y estudios apto profesional . Edificado sobre un lote de 20 metros de frente . Importante hall de acceso. Todas las unidades dan al frente. Ubicado a pasos de av corrientes y estado de israel . Subte b y parque centenario. Comercializa migliorisi corrientes 5500 srl direccion legal corrientes 5500 caba - se deja constancia que las caracteristicas,\nWhatsApp\nContactar", "revised": true, "rejected": true, "data": {"precio": "$ 270.000 + $20.000 expensas", "expensas": "+ $20.000 expensas", "direccion": "AGUIRRE 100", "metros": "30 m\u00b2 cubie.", "habitaciones": "7 a\u00f1os"}, "comment": "mono lindo. no hay gas"}, "https://www.argenprop.com/departamento-en-alquiler-en-balvanera-1-ambiente--15446033": {"date": "05-05-2024\n", "content": "1\n/10\n0\n$ 300.000 + $50.000 expensas\nCORRIENTES 3300\nDepartamento en Alquiler en Balvanera, Capital Federal\n30 m\u00b2 cubie.\n8 a\u00f1os\n1 ba\u00f1o\nDepartamento de 1 ambiente en Alquiler en Balvanera\nHermosa y moderna unidad monoambiente al frente de 34m2 totales con balcon - cocina con anafe electrico integrada al ambiente - ba\u00f1o completo - edificio con piscina, gym, s.U.M. - A metros del shopping abasto - ideal alquiler a estudiante - amplios medios de transporte - para visitas - comercializa migliorisi palermo av. Cordoba 3401 - comercializa migliorisi ,profesional responsable pablo\nWhatsApp\nContactar", "revised": true, "rejected": true, "data": {"precio": "$ 300.000 + $50.000 expensas", "expensas": "+ $50.000 expensas", "direccion": "CORRIENTES 3300", "metros": "30 m\u00b2 cubie.", "habitaciones": "8 a\u00f1os"}, "comment": "Caro. Ni lo vi"}, "https://www.argenprop.com/departamento-en-alquiler-en-almagro-1-ambiente--15446021": {"date": "05-05-2024\n", "content": "1\n/10\n0\n$ 300.000 + $50.000 expensas\nCORRIENTES 3300\nDepartamento en Alquiler en Almagro, Capital Federal\n30 m\u00b2 cubie.\n8 a\u00f1os\n1 ba\u00f1o\nDepartamento de 1 ambiente en Alquiler en Almagro\nHermosa y moderna unidad monoambiente al frente de 34m2 totales con balcon - cocina con anafe electrico integrada al ambiente - ba\u00f1o completo - edificio con piscina, gym y s.U.M. - A metros del shopping abasto - ideal alquiler a estudiante - amplios medios de transporte - comercializa migliorisi av. Cordoba 3401 - comercializa migliorisi ,profesional responsable pablo sebastian migliorisi cpi\nWhatsApp\nContactar", "revised": false, "rejected": true, "data": {"precio": "$ 300.000 + $50.000 expensas", "expensas": "+ $50.000 expensas", "direccion": "CORRIENTES 3300", "metros": "30 m\u00b2 cubie.", "habitaciones": "8 a\u00f1os"}}, "https://www.argenprop.com/departamento-en-alquiler-en-almagro-1-ambiente--15617755": {"date": "05-05-2024\n", "content": "1\n/10\n0\n$ 250.000 + $25.000 expensas\nPRINGLES 700\nDepartamento en Alquiler en Almagro, Capital Federal\n30 m\u00b2 cubie.\n40 a\u00f1os\n1 ba\u00f1o\nDepartamento de 1 ambiente en Alquiler en Almagro\nMonoambiente en alquiler, 30 m2, a 3 cuadras de subte b, con placard amplio, cocina independiente, ba\u00f1o completo con ba\u00f1era y ventilacion natural, expensas: $ 25.000 - comercializa migliorisi de corrientes 4599 srl profesional responsable jorge daniel gomez cpi 261 a30112 se deja constancia que las caracteristicas, medidas, expensas y superficies consignadas son aproximadas, sujetos a\nWhatsApp\nContactar", "revised": true, "rejected": true, "data": {"precio": "$ 250.000 + $25.000 expensas", "expensas": "+ $25.000 expensas", "direccion": "PRINGLES 700", "metros": "30 m\u00b2 cubie.", "habitaciones": "40 a\u00f1os"}, "comment": "Bien. Fr\u00edo. Oscuro"}, "https://www.argenprop.com/departamento-en-alquiler-en-congreso-2-ambientes--15603643": {"date": "05-05-2024\n", "content": "1\n/1\n0\n$ 300.000 + $35.000 expensas\nRIVADAVIA 2300\nDepartamento en Alquiler en Congreso, Capital Federal\n45 m\u00b2 cubie.\n1 dorm.\n50 a\u00f1os\nDepartamento de 2 ambientes en Alquiler en Congreso\nEn alquiler, interesante 2 ambientes de generosa superficie. Ventilacion en todos los ambientes. Sobre avenida. Acceso a transporte a todas direcciones,por la zona. Amplio movimiento comercial,peatonal,vehicular. Comercializa corrientes 721894/..A28196 se deja constancia que las caracteristicas, medidas, expensas y superficies consignadas son aproximadas, sujetos a verificaci\u00f3n y/o ajuste. El\nWhatsApp\nContactar", "revised": false, "rejected": true, "data": {"precio": "$ 300.000 + $35.000 expensas", "expensas": "+ $35.000 expensas", "direccion": "RIVADAVIA 2300", "metros": "45 m\u00b2 cubie.", "habitaciones": "1 dorm."}}, "https://www.argenprop.com/departamento-en-alquiler-en-almagro-norte-1-ambiente--14684945": {"date": "05-05-2024\n", "content": "1\n/12\n0\n$ 300.000 + $67.000 expensas\nValent\u00edn G\u00f3mez 3700, Piso 3\nDepartamento en Alquiler en Almagro Norte, Almagro\n33 m\u00b2 cubie.\n15 a\u00f1os\n1 ba\u00f1o\nAlmagro Valentin Gomez 3700 5\u00b0 Todo Luz y Sol Coc Barra Lav\nHermoso monoambiente sumamente luminoso y soleado al contrafrente (orientaci\u00f3n ne), ubicado en valent\u00edn gomez entre bulnes y mario bravo, 3\u00b0 piso. Edificio de 15 a\u00f1os es excelente estado. Posee 33mts cubiertos y 2 mts de balc\u00f3n. Se compone de hall de ingreso, acceso a cocina semintegrada con barra (posee lugar para lavarropas), ambiente amplio f\u00e1cilmente divisible, vestidor con c\u00f3modo lugar de\nWhatsApp\nContactar", "revised": true, "rejected": false, "data": {"precio": "$ 300.000 + $67.000 expensas", "expensas": "+ $67.000 expensas", "direccion": "Valent\u00edn G\u00f3mez 3700, Piso 3", "metros": "33 m\u00b2 cubie.", "habitaciones": "15 a\u00f1os"}, "comment": "Lindo. Luz. Cerca de plaza Almagro. Mono"}, "https://www.argenprop.com/departamento-en-alquiler-en-almagro-2-ambientes--15397076": {"date": "05-05-2024\n", "content": "1\n/10\n2\n$ 320.000 + $30.000 expensas\nAvenida D\u00edaz V\u00e9lez 3700, Piso 4\nDepartamento en Alquiler en Almagro, Capital Federal\n40 m\u00b2 cubie.\n1 dorm.\n40 a\u00f1os\nDepartamento 2 ambientes zona Almagro\nHermoso departamento de 2 ambientes 4to piso c/fte con balc\u00f3n corrido -living comedor de 5 x 3 mts con modular, mesa con sillas y m\u00e1s comodidades -dormitorio de 3,10 x 3 mts con placard empotrado juego de dormitorio con colch\u00f3n nuevo - ba\u00f1o con ducha - cocina con mesa libro utensilios de cocina - lavadero independiente consultas: (no se aceptan mascotas) mariela alberto diego (solo\nWhatsApp\nContactar", "revised": false, "rejected": true, "data": {"precio": "$ 320.000 + $30.000 expensas", "expensas": "+ $30.000 expensas", "direccion": "Avenida D\u00edaz V\u00e9lez 3700, Piso 4", "metros": "40 m\u00b2 cubie.", "habitaciones": "1 dorm."}}, "https://www.argenprop.com/departamento-en-alquiler-en-villa-crespo-2-ambientes--15645326": {"date": "05-05-2024\n", "content": "1\n/9\n0\n$ 250.000\nLEOPOLDO MARECHAL 1300\nDepartamento en Alquiler en Villa Crespo, Capital Federal\n37 m\u00b2 cubie.\n1 dorm.\n40 a\u00f1os\nDepartamento de 2 ambientes en Alquiler en Villa crespo\nDepartamento 2 ambientes lateral - excelente ubicacion - se deja constancia que las caracteristicas, medidas, expensas y superficies consignadas son aproximadas, sujetos a verificacion y/o ajuste. El precio del inmueble puede ser modificado sin previo aviso. Fotos de caracter no contractual. Las unidades publicadas estan sujetas a migliorisi de corrientes 4599 srl profesional responsable jorge\nWhatsApp\nContactar", "revised": false, "rejected": true, "data": {"precio": "$ 250.000", "direccion": "LEOPOLDO MARECHAL 1300", "metros": "37 m\u00b2 cubie.", "habitaciones": "1 dorm."}}, "https://www.argenprop.com/departamento-en-alquiler-en-almagro-2-ambientes--15417859": {"date": "05-05-2024\n", "content": "1\n/9\n0\n$ 300.000 + $45.000 expensas\nHUMAHUACA 4300\nDepartamento en Alquiler en Almagro, Capital Federal\n35 m\u00b2 cubie.\n1 dorm.\n45 a\u00f1os\nDepartamento de 2 ambientes en Alquiler en Almagro\nDepartamento 2 ambientes a frente con balcon - apto profesional - luz y sol en todos los ambientes- excelente ubiacion - multiples medios de transporte -\nWhatsApp\nContactar", "revised": true, "rejected": false, "data": {"precio": "$ 300.000 + $45.000 expensas", "expensas": "+ $45.000 expensas", "direccion": "HUMAHUACA 4300", "metros": "35 m\u00b2 cubie.", "habitaciones": "1 dorm."}, "comment": "Fiero. 2amb"}, "https://www.argenprop.com/departamento-en-alquiler-en-villa-crespo-2-ambientes--15633344": {"date": "05-05-2024\n", "content": "1\n/6\n0\n$ 300.000 + $70.000 expensas\nLEMOS 100\nDepartamento en Alquiler en Villa Crespo, Capital Federal\n35 m\u00b2 cubie.\n1 dorm.\n40 a\u00f1os\nDepartamento de 2 ambientes en Alquiler en Villa crespo\nDos ambientes muy luminoso, contrafrente con excelente vista, en pleno corredor de corrientes. Cocina y lavadero independiente. Cerca del subte b. Sin mascotas y solo con garantia propietaria de caba, propia o de garante. Comercializa migliorisi de corrientes 5500 srl profesional responsable diego f migliorisi cpi263 a30141 se deja constancia que las caracteristicas, medidas, expensas y\nWhatsApp\nContactar", "revised": true, "rejected": true, "data": {"precio": "$ 300.000 + $70.000 expensas", "expensas": "+ $70.000 expensas", "direccion": "LEMOS 100", "metros": "35 m\u00b2 cubie.", "habitaciones": "1 dorm."}}, "https://www.argenprop.com/departamento-en-alquiler-en-villa-crespo-1-ambiente--15623890": {"date": "05-05-2024\n", "content": "1\n/11\n0\n$ 245.000 + $37.300 expensas\nCORRIENTES 5700\nDepartamento en Alquiler en Villa Crespo, Capital Federal\n41 m\u00b2 cubie.\n30 a\u00f1os\n1 ba\u00f1o\nDepartamento de 1 ambiente en Alquiler en Villa crespo\n..........................Muy buen departamento de 1 y 1/2 amb con cocina independiente. Living en l divisible. Lavadero independiente, el edificio siempre muy bien conservado se encuentra ubcado en pleno centro comercial de villa crespo con numerosos comercio, medios de transporte a todos los puntos y a 4 cuadras de subte \"b\". Najas expensas . Se acepta seguro de caucion acreditado por la\nWhatsApp\nContactar", "revised": false, "rejected": true, "data": {"precio": "$ 245.000 + $37.300 expensas", "expensas": "+ $37.300 expensas", "direccion": "CORRIENTES 5700", "metros": "41 m\u00b2 cubie.", "habitaciones": "30 a\u00f1os"}}, "https://www.argenprop.com/departamento-en-alquiler-en-villa-crespo-2-ambientes--15620925": {"date": "05-05-2024\n", "content": "1\n/11\n0\n$ 350.000\nCASTILLO 500\nDepartamento en Alquiler en Villa Crespo, Capital Federal\n35 m\u00b2 cubie.\n1 dorm.\n45 a\u00f1os\nDepartamento de 2 ambientes en Alquiler en Villa crespo\n2 luminosos ambientes con vista panoramica 2 aires acondic muy buenos placards proximo avenidas y diversos medio de transportes castillo al 500 informes comercializa migliorisi de corrientes 5500 srl profesional responsable diego f migliorisi cpi263 a30153 se deja constancia que las caracteristicas, medidas, expensas y superficies consignadas son aproximadas, sujetos a verificaci\u00f3n y/o ajuste.\nWhatsApp\nContactar", "revised": true, "rejected": true, "data": {"precio": "$ 350.000", "direccion": "CASTILLO 500", "metros": "35 m\u00b2 cubie.", "habitaciones": "1 dorm."}, "comment": "2 amb. Sin balc\u00f3n "}, "https://www.argenprop.com/departamento-en-alquiler-en-villa-crespo-2-ambientes--15645984": {"date": "05-05-2024\n", "content": "1\n/6\n500\n$ 250.000\nDiego De Rojas 1800, Piso 2\u00ba\nDepartamento en Alquiler en Villa Crespo, Capital Federal\n35 m\u00b2 cubie.\n1 dorm.\n45 a\u00f1os\nDEPARTAMENTO DE DOS AMBIENTES LUMINOSO\nDeparamento muy luminoso a metros de av. Juan b. Justo recin pintado recepcion 4,50x3,50 dormiotiro c3x3 con placard ba\u00f1o completo cocina 2,90x1,50 con desayunador\nWhatsApp\nContactar", "revised": true, "rejected": true, "data": {"precio": "$ 250.000", "direccion": "Diego De Rojas 1800, Piso 2\u00ba", "metros": "35 m\u00b2 cubie.", "habitaciones": "1 dorm."}}, "https://www.argenprop.com/departamento-en-alquiler-en-almagro-norte-2-ambientes--15529136": {"date": "05-05-2024\n", "content": "1\n/9\n1\n$ 300\nLAVALLE 3700\nDepartamento en Alquiler en Almagro Norte, Almagro\n34 m\u00b2 cubie.\n1 dorm.\n1 ba\u00f1o\nDEPARTAMENTO 2 AMBIENTES EN LAVALLE 3700\nHermoso departamento en alquiler en almagro 2 ambientes contrafrente, muy luminoso, posee placard empotrado. \u00a1Muy buena ubicaci\u00f2n! A 2 cuadras de la utn de medrano, 1 cuadra de c\u00f2rdoba, 4 cuadras de corrientes, subte l\u00ecnea b, varias l\u00ecneas de colectivo, zona comercial. Mariela echeverr\u00eca negocios inmobiliarios matr\u00eccula cucicba n.\u00ba 6.941. - Kp311130 - kpd050510 - - publicado v\u00eda kiteprop crm\nContactar", "revised": false, "rejected": true, "data": {"precio": "$ 300", "direccion": "LAVALLE 3700", "metros": "34 m\u00b2 cubie.", "habitaciones": "1 dorm."}}, "https://www.argenprop.com/departamento-en-alquiler-en-almagro-2-ambientes--6068409": {"date": "05-05-2024\n", "content": "1\n/5\n2\n$ 290.000 + $50.000 expensas\nSan Luis 3300, Piso 4\nDepartamento en Alquiler en Almagro, Capital Federal\n30 m\u00b2 cubie.\n1 dorm.\n35 a\u00f1os\nAMOBLADO\nAmoblado. Piso 4 interno, muy luminoso. Cocina americana, ba\u00f1o completo. Expensas: $ 50.000. A 4 cuadras de la universidad de palermo. Seguinos por instagram arguellesasociadosinmobiliaria visite nuestro sitio web , en donde podr\u00e1 encontrar otras alternativas de departamentos amoblados.\nWhatsApp\nContactar", "revised": true, "rejected": false, "data": {"precio": "$ 290.000 + $50.000 expensas", "expensas": "+ $50.000 expensas", "direccion": "San Luis 3300, Piso 4", "metros": "30 m\u00b2 cubie.", "habitaciones": "1 dorm."}, "comment": "Safa. Sin balc\u00f3n "}, "https://www.argenprop.com/departamento-en-alquiler-en-san-nicolas-2-ambientes--15437576": {"date": "05-05-2024\n", "content": "1\n/9\n3.812\n$ 320.000 + $38.000 expensas\nRodr\u00edguez Pe\u00f1a 400, Piso 9\nDepartamento en Alquiler en San Nicol\u00e1s, Centro\n48 m\u00b2 cubie.\n1 dorm.\n45 a\u00f1os\nAMOBLADO - BALCON CORRIDO - MUY LUMINOSO - COCINA con COMEDOR DIARIO\nAmoblado. Piso 9\u00b0 al frente, muy luminoso. Balc\u00f3n corrido. Cocina con comedor diario. Lavadero independiente. Expensas: $ 38.000. Servicios individuales. Seguinos por instagram arguellesasociadosinmobiliaria visita nuestro sitio web\nWhatsApp\nContactar", "revised": true, "rejected": true, "data": {"precio": "$ 320.000 + $38.000 expensas", "expensas": "+ $38.000 expensas", "direccion": "Rodr\u00edguez Pe\u00f1a 400, Piso 9", "metros": "48 m\u00b2 cubie.", "habitaciones": "1 dorm."}, "comment": "Fea zona"}, "https://www.argenprop.com/departamento-en-alquiler-en-boedo-2-ambientes--15575536": {"date": "05-05-2024\n", "content": "1\n/13\n0\n$ 300.000 + $40.000 expensas\nSanchez de Loria al 1100\nDepartamento en Alquiler en Boedo, Capital Federal\n40 m\u00b2 cubie.\n1 dorm.\n6 a\u00f1os\n2 ambientes alquiler tradicional en Boedo\nSalaya romera propiedades ofrece en alquiler tradicional impecable departamento de 2 ambientes al contrafrente . El edificio, de muy buena calidad constructiva, tiene unos 6 a\u00f1os de antiguedad; es moderno en impecable estado. - 1 ascensor. - Amenities en el edificio ; presenta en la terraza comun : parrilla, solarium, pileta con hidromasaje, laundry con maquinas para lavar y\nWhatsApp\nContactar", "revised": true, "rejected": false, "data": {"precio": "$ 300.000 + $40.000 expensas", "expensas": "+ $40.000 expensas", "direccion": "Sanchez de Loria al 1100", "metros": "40 m\u00b2 cubie.", "habitaciones": "1 dorm."}, "comment": "Moderno. Fr\u00edo. Luminoso. Plaza boedo"}, "https://www.argenprop.com/departamento-en-alquiler-en-almagro-2-ambientes--15568619": {"date": "05-05-2024\n", "content": "1\n/8\n905\n$ 350.000 + $25.000 expensas\nPANAM\u00c1 900\nDepartamento en Alquiler en Almagro, Capital Federal\n32 m\u00b2 cubie.\n1 dorm.\n50 a\u00f1os\nALQUILER DEPARTAMENTO ALMAGRO 2 AMBIENTES\nAlquiler de departamento 2 ambientes en almagro, capital federal c\u00e1lido departamento a dos cuadras de parque centenario, en ante\u00faltimo piso, con buena luz y ventilaci\u00f3n. Cuenta con living comedor con balc\u00f3n franc\u00e9s y habitaci\u00f3n con espacio de guardado incorporado. Ba\u00f1o completo con ventilaci\u00f3n directa y cocina con lavadero incorporado. Ubicaci\u00f3n excepcional  - actualizaci\u00f3n trimestral seg\u00fan\nWhatsApp\nContactar", "revised": true, "rejected": true, "data": {"precio": "$ 350.000 + $25.000 expensas", "expensas": "+ $25.000 expensas", "direccion": "PANAM\u00c1 900", "metros": "32 m\u00b2 cubie.", "habitaciones": "1 dorm."}, "comment": "Est\u00e1 bien pero es caro"}, "https://www.argenprop.com/departamento-en-alquiler-en-balvanera-1-ambiente--15631898": {"date": "05-05-2024\n", "content": "1\n/53\n0\n$ 220.000 + $20.000 expensas\n24 de Noviembre al 1600\nDepartamento en Alquiler en Balvanera, Capital Federal\n30 m\u00b2 cubie.\n1 dorm.\n20 a\u00f1os\n1AMB \u00b7 30M\u00b2 \u00b7 f\u00e1cilmente divisible! placard! abert nvas! coc lav! td a estrenar!\nDepartamento 1 ambiente ! Totalmente reciclado a nuevo! #Alquiler | #departamento | #est\u00e1ndar | #1amb | #parquepatricios | #contrafrente 24 de noviembre y avenida juan de garay - ciudad aut\u00f3noma de buenos aires caracter\u00edsticas: ~departamento de un (1) ambiente totalmente reciclado a nuevo tanto est\u00e9tica como estructuralmente, en el l\u00edmite de los barrios de parque patricios y san\nWhatsApp\nContactar", "revised": false, "rejected": true, "data": {"precio": "$ 220.000 + $20.000 expensas", "expensas": "+ $20.000 expensas", "direccion": "24 de Noviembre al 1600", "metros": "30 m\u00b2 cubie.", "habitaciones": "1 dorm."}}, "https://www.argenprop.com/departamento-en-alquiler-en-boedo-1-ambiente--15631890": {"date": "05-05-2024\n", "content": "1\n/53\n0\n$ 220.000 + $20.000 expensas\n24 de Noviembre al 1600\nDepartamento en Alquiler en Boedo, Capital Federal\n30 m\u00b2 cubie.\n1 dorm.\n20 a\u00f1os\n1AMB \u00b7 30M\u00b2 \u00b7 f\u00e1cilmente divisible! placard! abert nvas! coc lav! td a estrenar!\nDepartamento 1 ambiente ! Totalmente reciclado a nuevo! #Alquiler | #departamento | #est\u00e1ndar | #1amb | #parquepatricios | #contrafrente 24 de noviembre y avenida juan de garay - ciudad aut\u00f3noma de buenos aires caracter\u00edsticas: ~departamento de un (1) ambiente totalmente reciclado a nuevo tanto est\u00e9tica como estructuralmente, en el l\u00edmite de los barrios de parque patricios y san\nWhatsApp\nContactar", "revised": false, "rejected": true, "data": {"precio": "$ 220.000 + $20.000 expensas", "expensas": "+ $20.000 expensas", "direccion": "24 de Noviembre al 1600", "metros": "30 m\u00b2 cubie.", "habitaciones": "1 dorm."}}, "https://www.argenprop.com/departamento-en-alquiler-en-san-cristobal-1-ambiente--15631902": {"date": "05-05-2024\n", "content": "1\n/53\n0\n$ 220.000 + $20.000 expensas\n24 de Noviembre al 1600\nDepartamento en Alquiler en San Cristobal, Capital Federal\n30 m\u00b2 cubie.\n1 dorm.\n20 a\u00f1os\n1AMB \u00b7 30M\u00b2 \u00b7 f\u00e1cilmente divisible! placard! abert nvas! coc lav! td a estrenar!\nDepartamento 1 ambiente ! Totalmente reciclado a nuevo! #Alquiler | #departamento | #est\u00e1ndar | #1amb | #parquepatricios | #contrafrente 24 de noviembre y avenida juan de garay - ciudad aut\u00f3noma de buenos aires caracter\u00edsticas: ~departamento de un (1) ambiente totalmente reciclado a nuevo tanto est\u00e9tica como estructuralmente, en el l\u00edmite de los barrios de parque patricios y san\nWhatsApp\nContactar", "revised": false, "rejected": true, "data": {"precio": "$ 220.000 + $20.000 expensas", "expensas": "+ $20.000 expensas", "direccion": "24 de Noviembre al 1600", "metros": "30 m\u00b2 cubie.", "habitaciones": "1 dorm."}}, "https://www.argenprop.com/departamento-en-alquiler-en-almagro-1-ambiente--15631894": {"date": "05-05-2024\n", "content": "1\n/53\n0\n$ 220.000 + $20.000 expensas\n24 de Noviembre al 1600\nDepartamento en Alquiler en Almagro, Capital Federal\n30 m\u00b2 cubie.\n1 dorm.\n20 a\u00f1os\n1AMB \u00b7 30M\u00b2 \u00b7 f\u00e1cilmente divisible! placard! abert nvas! coc lav! td a estrenar!\nDepartamento 1 ambiente ! Totalmente reciclado a nuevo! #Alquiler | #departamento | #est\u00e1ndar | #1amb | #parquepatricios | #contrafrente 24 de noviembre y avenida juan de garay - ciudad aut\u00f3noma de buenos aires caracter\u00edsticas: ~departamento de un (1) ambiente totalmente reciclado a nuevo tanto est\u00e9tica como estructuralmente, en el l\u00edmite de los barrios de parque patricios y san\nWhatsApp\nContactar", "revised": false, "rejected": true, "data": {"precio": "$ 220.000 + $20.000 expensas", "expensas": "+ $20.000 expensas", "direccion": "24 de Noviembre al 1600", "metros": "30 m\u00b2 cubie.", "habitaciones": "1 dorm."}}, "https://www.argenprop.com/departamento-en-alquiler-en-parque-patricios-1-ambiente--15631889": {"date": "05-05-2024\n", "content": "1\n/53\n0\n$ 220.000 + $20.000 expensas\n24 de Noviembre al 1600\nDepartamento en Alquiler en Parque Patricios, Capital Federal\n30 m\u00b2 cubie.\n1 dorm.\n20 a\u00f1os\n1AMB \u00b7 30M\u00b2 \u00b7 f\u00e1cilmente divisible! placard! abert nvas! coc lav! td a estrenar!\nDepartamento 1 ambiente ! Totalmente reciclado a nuevo! #Alquiler | #departamento | #est\u00e1ndar | #1amb | #parquepatricios | #contrafrente 24 de noviembre y avenida juan de garay - ciudad aut\u00f3noma de buenos aires caracter\u00edsticas: ~departamento de un (1) ambiente totalmente reciclado a nuevo tanto est\u00e9tica como estructuralmente, en el l\u00edmite de los barrios de parque patricios y san\nWhatsApp\nContactar", "revised": false, "rejected": true, "data": {"precio": "$ 220.000 + $20.000 expensas", "expensas": "+ $20.000 expensas", "direccion": "24 de Noviembre al 1600", "metros": "30 m\u00b2 cubie.", "habitaciones": "1 dorm."}}, "https://www.argenprop.com/departamento-en-alquiler-en-villa-crespo-2-ambientes--15646429": {"date": "05-05-2024\n", "content": "1\n/16\n0\n$ 295.000 + $119.000 expensas\nCamargo 300\nDepartamento en Alquiler en Villa Crespo, Capital Federal\n31 m\u00b2 cubie.\n1 dorm.\n44 a\u00f1os\nDEPARTAMENTO 2 AMBIENTES CONTRAFRENTE VILLA CRESPO\nDepartamento de 2 ambientes en alquiler ubicado en villa crespo. Primer piso al contrafrente, por ascensor. Cocina integrada al comedor, separados por una barra desayunadora. Cocina equipada con muebles de bajo mesada y alacena, conexion para lavarropas. Comedor con pisos de ceramico, equipo de aire acondicionado frio. Ba\u00f1o con ba\u00f1era. Dormitorio con pisos de parquet y dos placard\nWhatsApp\nContactar", "revised": false, "rejected": true, "data": {"precio": "$ 295.000 + $119.000 expensas", "expensas": "+ $119.000 expensas", "direccion": "Camargo 300", "metros": "31 m\u00b2 cubie.", "habitaciones": "1 dorm."}}}