{"https://www.argenprop.com/departamento-en-alquiler-en-balvanera-2-ambientes--15655157": {"id": "19071955", "date": "08-05-2024\n", "index": 3, "content": "1\n/16\n0\n$ 300.000 + $40.000 expensas\nMORENO 3000\nDepartamento en Alquiler en Balvanera, Capital Federal\n40 m\u00b2 cubie.\n1 dorm.\n30 a\u00f1os\nEXCELENTE DEPARTAMENTO 3 AMBIENTES C/BALCON DE FRENTE\nMuy lindo departamento de 2 ambientes con balc\u00f3n en la calle moreno al 3000, balvanera consta de living-comedor con cocina incorporada 4.40 x 5.00, dormitorio con placard 2.90 x 3.00, ba\u00f1o completo 2.00 x 1.70, balc\u00f3n 4.45 x 1.00 y pasillo integrador 1.70 x 1.00. Superficie total 40 m2. Muy luminoso y en buen estado. A 3 cuadras de av rivadavia (subte l\u00ednea a) y todos los transportes. A 3 cuadras\nWhatsApp\nContactar", "revised": false, "rejected": false, "data": {"precio": "$ 300.000 + $40.000 expensas", "expensas": "+ $40.000 expensas", "direccion": "MORENO 3000", "metros": "40 m\u00b2 cubie.", "habitaciones": "1 dorm."}, "image": "https://static1.sosiva451.com/75155651/45713206-b8fe-44ee-94bc-3dc9bc5087ec_u_small.jpg", "title": "EXCELENTE DEPARTAMENTO 3 AMBIENTES C/BALCON DE FRENTE"}, "https://www.argenprop.com/departamento-en-alquiler-en-balvanera-2-ambientes--15654597": {"id": "19071397", "date": "08-05-2024\n", "index": 6, "content": "1\n/16\n0\n$ 300.000 + $35.000 expensas\nMORENO 2900\nDepartamento en Alquiler en Balvanera, Capital Federal\n31 m\u00b2 cubie.\n1 dorm.\n30 a\u00f1os\nEXCELENTE DEPARTAMENTO DE 2 AMBIENTES\nMuy lindo departamento de 2 ambientes lateral en la calle moreno al 2900, balvanera consta del living comedor de 3.00 x 3.50, dormitorio con placard 3.00 x 3.00, cocina 3.70 x 1.60 y ba\u00f1o completo 1.60 x 2.20. Superficie total 31 m2. Muy luminoso y en buen estado. No se aceptan mascotas. A 2 cuadras de av jujuy (subte l\u00ednea h) y a 3 cuadras de av rivadavia (subte l\u00ednea a) y todos los transportes.\nWhatsApp\nContactar", "revised": false, "rejected": false, "data": {"precio": "$ 300.000 + $35.000 expensas", "expensas": "+ $35.000 expensas", "direccion": "MORENO 2900", "metros": "31 m\u00b2 cubie.", "habitaciones": "1 dorm."}, "image": "https://static1.sosiva451.com/79545651/0625bd74-8e43-4038-a628-b96f603460d5_u_small.jpg", "title": "EXCELENTE DEPARTAMENTO DE 2 AMBIENTES"}, "https://www.argenprop.com/departamento-en-alquiler-en-balvanera-2-ambientes--15349731": {"id": "18784605", "date": "08-05-2024\n", "index": 7, "content": "1\n/19\n0\n$ 300.000 + $48.300 expensas\nAv. Jujuy al 0\nDepartamento en Alquiler en Balvanera, Capital Federal\n40 m\u00b2 cubie.\n1 dorm.\n30 a\u00f1os\nAv. Jujuy al 0 Departamento de 2 ambientes en Alquiler en Balvanera\nDepartamento de 2 ambientes lateral en balvanera la unidad se encuentra en una ubicaci\u00f3n ideal a pasos de av. Rivadavia con gran acceso a diversos medios de transporte. Accesibilidad por colectivo, tren y subte. Caracter\u00edsticas principales living comedor cocina completa lavadero independiente ba\u00f1o completo con ba\u00f1adera balc\u00f3n tipo franc\u00e9s pisos de parquet muy luminoso condiciones de\nWhatsApp\nContactar", "revised": false, "rejected": true, "data": {"precio": "$ 300.000 + $48.300 expensas", "expensas": "+ $48.300 expensas", "direccion": "Av. Jujuy al 0", "metros": "40 m\u00b2 cubie.", "habitaciones": "1 dorm."}, "image": "https://static1.sosiva451.com/13794351/5f9bd52e-e5e4-4e1b-83b0-4205e8000847_u_small.jpg", "title": "Av. Jujuy al 0 Departamento de 2 ambientes en Alquiler en Balvanera"}, "https://www.argenprop.com/departamento-en-alquiler-en-balvanera-2-ambientes--15540307": {"id": "18966227", "date": "08-05-2024\n", "index": 12, "content": "1\n/14\n0\n$ 290.000 + $65.000 expensas\nViamonte al 2400\nDepartamento en Alquiler en Balvanera, Capital Federal\n34 m\u00b2 cubie.\n1 dorm.\n60 a\u00f1os\nViamonte al 2400 - 2 amb - FACULTAD - Alquiler\nDepartamento de 2 ambientes - facultad - luminoso. Muy buen estado. Pisos parquet plastificados agua caliente central calefaccion por estufas electricas aire acondicionado living con estufa dormitorio con placard y aire acondicionado split cocina con cocina 4 hornallas con horno bajo mesada y alacenas ba\u00f1o completo con ba\u00f1era servicios individuales.\nContactar", "revised": false, "rejected": false, "data": {"precio": "$ 290.000 + $65.000 expensas", "expensas": "+ $65.000 expensas", "direccion": "Viamonte al 2400", "metros": "34 m\u00b2 cubie.", "habitaciones": "1 dorm."}, "image": "https://static1.sosiva451.com/70304551/0f008765-6000-413a-a4d9-ed331905e962_u_small.jpg", "title": "Viamonte al 2400 - 2 amb - FACULTAD - Alquiler"}, "https://www.argenprop.com/departamento-en-alquiler-en-balvanera-2-ambientes--15635683": {"id": "19052643", "date": "08-05-2024\n", "index": 14, "content": "1\n/8\n0\n$ 280.000 + $38.000 expensas\nCatamarca al 200\nDepartamento en Alquiler en Balvanera, Capital Federal\n54 m\u00b2 cubie.\n1 dorm.\n50 a\u00f1os\nALQUILER DPTO 2 AMB EN BALVANERA\nDepartamento de 2 ambientes en alquiler alquiler $280.000.- Expensas $38.000.- Depto ubicado en un sexto piso, interno. Reci\u00e9n pintado. Totalmente el\u00e9ctrico. Al ingresar lo hacemos al comedor diarios, que nos conecta directamente con la cocina independiente y el lavadero. Desde el comedor tambi\u00e9n accedemos a la habitaci\u00f3n principal con placard y desde la misma tambi\u00e9n al ba\u00f1o\nWhatsApp\nContactar", "revised": false, "rejected": false, "data": {"precio": "$ 280.000 + $38.000 expensas", "expensas": "+ $38.000 expensas", "direccion": "Catamarca al 200", "metros": "54 m\u00b2 cubie.", "habitaciones": "1 dorm."}, "image": "https://static1.sosiva451.com/38653651/4fc0a1a6-74cf-47fd-9138-cb63a9078fe8_u_small.jpg", "title": "ALQUILER DPTO 2 AMB EN BALVANERA"}, "https://www.argenprop.com/departamento-en-alquiler-en-balvanera-2-ambientes--15647124": {"id": "19064079", "date": "08-05-2024\n", "index": 15, "content": "1\n/5\n0\n$ 250.000 + $23.000 expensas\nRivadavia al 3000\nDepartamento en Alquiler en Balvanera, Capital Federal\n56 m\u00b2 cubie.\n1 dorm.\n11 a\u00f1os\nDPTO EN 2 AMB. ALQUILER\nAlquiler departamento en importante zona comercial muy luminoso el dpto cuenta con: -living comedor - 1 domitorio - cocina - ba\u00f1o completo -cocina en buen estado de conservaci\u00f3n. El edificio cuenta con seguridad y encargado. Excelente ubicaci\u00f3n con gran variedad de transportes -\nWhatsApp\nContactar", "revised": false, "rejected": true, "data": {"precio": "$ 250.000 + $23.000 expensas", "expensas": "+ $23.000 expensas", "direccion": "Rivadavia al 3000", "metros": "56 m\u00b2 cubie.", "habitaciones": "1 dorm."}, "image": "https://static1.sosiva451.com/42174651/6340653b-3869-4f03-ae06-9de94aaee04d_u_small.jpg", "title": "DPTO EN 2 AMB. ALQUILER"}, "https://www.argenprop.com/departamento-en-alquiler-en-balvanera-2-ambientes--15649067": {"id": "19065865", "date": "08-05-2024\n", "index": 17, "content": "1\n/19\n0\n$ 250.000 + $19.000 expensas\nAV. BELGRANO 2600, Piso 9\nDepartamento en Alquiler en Balvanera, Capital Federal\n33 m\u00b2 cubie.\n1 dorm.\n30 a\u00f1os\nSUPER LUMINOSO EN EXC ESTADO Y EN INMEJORABLE UBICACI\u00d3N\nDos ambientes en alquiler en balvanera ingreso al living comedor, super amplio y luminoso  \u00a1Hall de distribuci\u00f3n el cual nos dirige a la habitaci\u00f3n, muy luminosa con amplio espacio de guardado!  Cocina completa con muebles bajo mesada y alacena, artefacto de cocina a gas, lavadero independiente con conexi\u00f3n para lavaropas ba\u00f1o completo con ventilaci\u00f3n natural  todo en excelente estado,\nContactar", "revised": false, "rejected": true, "data": {"precio": "$ 250.000 + $19.000 expensas", "expensas": "+ $19.000 expensas", "direccion": "AV. BELGRANO 2600, Piso 9", "metros": "33 m\u00b2 cubie.", "habitaciones": "1 dorm."}, "image": "https://static1.sosiva451.com/76094651/478f11d8-a7d5-46b5-a920-3d3e4a464706_u_small.jpg", "title": " SUPER LUMINOSO EN EXC ESTADO Y EN INMEJORABLE UBICACI\u00d3N "}, "https://www.argenprop.com/departamento-en-alquiler-en-balvanera-2-ambientes--15603332": {"id": "19020263", "date": "08-05-2024\n", "index": 19, "content": "1\n/18\n0\n$ 295.000 + $96.000 expensas\nSan Luis al 2700\nDepartamento en Alquiler en Balvanera, Capital Federal\n40 m\u00b2 cubie.\n1 dorm.\n42 a\u00f1os\nAlquiler departamento de 2 ambientes en Balvanera\nAlquiler departamento 2 ambientes muy luminoso en balvanera (existe la posibilidad de alquilar la unidad amoblada a $/mes 350.000) - el valor mensual del alquiler se ajustar\u00e1 cada tres meses seg\u00fan \u00edndice ipc. - Departamento de 2 ambientes semipiso. Muy luminoso. Piso alto. Excelente ubicaci\u00f3n en la esquina de san luis y av. Pueyrred\u00f3n. - Medios de transportes\nWhatsApp\nContactar", "revised": false, "rejected": false, "data": {"precio": "$ 295.000 + $96.000 expensas", "expensas": "+ $96.000 expensas", "direccion": "San Luis al 2700", "metros": "40 m\u00b2 cubie.", "habitaciones": "1 dorm."}, "image": null, "title": "Alquiler departamento de 2 ambientes en Balvanera"}}