{"https://www.zonaprop.com.ar/propiedades/clasificado/alclapin-tres-amb-y-depcias-al-frente.-pueyrredon-y-pena.-53571286.html": {"date": "06-05-2024\n", "index": 55, "content": "$ 650.000\n$ 160.000 Expensas\nAv Pueyrred\u00f3n 1913 3\u00b0 \"C\" - CABA -\nBarrio Norte, Capital Federal\n70 m\u00b2 tot.\n3 amb.\n2 dorm.\n2 ba\u00f1os\nExcelente tres ambientes con depcias al frente. -Todo luz y sol. -Amplio Balc\u00f3n corrido. -Cocina comedor diario con entrada de servicio. -Dos dormitorios con placard. -Un ba\u00f1o completo con ba\u00f1adera (luz y ventilaci\u00f3n natural). -Lavadero cubierto independiente. -Ba\u00f1o de servicio. -Pisos de parquet plastificados. -Agua caliente individual por calef\u00f3n. -Calefacci\u00f3n central por losa radiante. -Categor\u00eda. -Impecable. -(villafa\u00f1e propiedades Ver datos Ver datos). -\nDestacado\nPublicado hace 3 d\u00edas\nContactar", "revised": false, "rejected": true, "data": {"precio": "$ 650.000", "expensas": "$ 160.000 Expensas", "direccion": "Av Pueyrred\u00f3n 1913 3\u00b0 \"C\" - CABA -", "metros": "70 m\u00b2 tot.", "habitaciones": "3 amb.", "hace": "Contactar"}, "image": "https://imgar.zonapropcdn.com/avisos/1/00/53/57/12/86/360x266/1909335342.jpg?isFirstImage=true", "title": "Departamento de 3 ambientes, Barrio Norte \u00b7 Tres Amb y Depcias Al Frente. - Pueyrred\u00f3n y Pe\u00f1a. - Balc\u00f3n Corrido. - Todo Luz. - Impec"}, "https://www.zonaprop.com.ar/propiedades/clasificado/alclapin-semipiso-3-ambientes-amoblado-muy-luminoso-53572410.html": {"date": "06-05-2024\n", "index": 60, "content": "$ 550.000\n$ 80.000 Expensas\nEstados Unidos 3100\nSan Cristobal, Capital Federal\n72 m\u00b2 tot.\n3 amb.\n2 dorm.\n1 ba\u00f1o\nCorredor Responsable: Rene Vera cucicba 6778 / csi 5848- Contacto: Enrique Barzanti - mls id # Ver datos-9. Contrafrente en 8vo piso, contando con un gran caudal de ventilaci\u00f3n y luz natural durante todo el d\u00eda. Totalmente amoblado y equipado. Amplio balc\u00f3n hacia el este y balc\u00f3n franc\u00e9s hacia el norte. Se aceptan hasta 4 personas!! Actualizaci\u00f3n trimestral acorde a Ley 27. 551 (icl) Zona con amplia oferta de lugares gastron\u00f3micos, educativos y de salud. A 1 cuadra de Av. Independencia y a 3 cuadras de Av. San Juan! Educaci\u00f3n. Facultad De Psicolog\u00eda uba, Sede Independencia_a 150mts. instituto santa cruz_ a 100mts. Instituto Secundario El Taller_a 150mts. colegio mater ter admirabilis_a 200mts. Escuela N\u00b0 15 - Jorge Luis Chinetti_ a 30mts. Escuela Primaria Com\u00fan N\u00b0 03 - Rufino S\u00e1nchez_a 250mts. Escuela Infantil San Francisco de As\u00eds_ a 350mts. Escuela N\u00b011 D. E. 6 - Jos\u00e9 Federico Moreno_a 350mts. Esc. Primaria Com\u00fan N\u00b0 12 Rep\u00fablica del Paraguay_ a 600mts. salud. Hospital C\u00e9sar Milstein_ a 250mts. Hospital General de Agudos Jos\u00e9 Mar\u00eda Ramos Mej\u00eda_a 350mts. Hospital Espa\u00f1ol_a 850mts. colectivos: 31, 31, 88, 41, 101, 75, subte: l\u00ednea \"E\", estaci\u00f3n general urquiza, a 450mts. Remax Argentina S. R. L. No ejerce el corretaje inmobiliario. El presente sitio web es una plataforma en donde cada oficina inmobiliaria independiente que contrata los servicios re/max puede publicar las propiedades a su cargo. Cada oficina es de propiedad y gesti\u00f3n independiente, por lo que Remax Argentina S. R. L no interviene en los datos de la publicaci\u00f3n, en la operaci\u00f3n inmobiliaria, ni en la confecci\u00f3n y/o firma del boleto de compraventa y/o escritura y/o contrato de alquiler. En cumplimiento de las leyes vigentes que regulan el corretaje inmobiliario, Ley Nacional 25. 028, Ley 22. 802 de Lealtad Comercial, Ley 24. 240 de Defensa al Consumidor, las normas del C\u00f3digo Civil y Comercial de la Naci\u00f3n y Constitucionales, los agentes/gestores no ejercen el corretaje inmobiliario. Todas las operaciones inmobiliarias son objeto de intermediaci\u00f3n y conclusi\u00f3n por parte del corredor p\u00fablico inmobiliario colegiado a cargo de la publicaci\u00f3n, cuyos datos se exhiben en la presente. La presente publicaci\u00f3n describe las caracter\u00edsticas esenciales del inmueble, debi\u00e9ndose consultar al corredor p\u00fablico inmobiliario responsable de la operaci\u00f3n por la eventual actualizaci\u00f3n de las medidas, descripciones arquitect\u00f3nicas y funcionales, valores de expensas, servicios, impuestos, precios y dem\u00e1s informaci\u00f3n, cuyos valores son aproximados. Para los casos de alquiler de vivienda, el monto m\u00e1ximo de comisi\u00f3n que se le puede requerir a los propietarios ser\u00e1 el equivalente al cuatro con quince cent\u00e9simos por ciento (4, 15%) del valor total del respectivo contrato. Se encuentra prohibido cobrar a los inquilinos que sean personas f\u00edsicas comisiones inmobiliarias y gastos de gestor\u00eda de informes. El inmueble no es accesible para personas con discapacidades f\u00edsicas.\nPublicado hace 3 d\u00edas\nContactar", "revised": false, "rejected": true, "data": {"precio": "$ 550.000", "expensas": "$ 80.000 Expensas", "direccion": "Estados Unidos 3100", "metros": "72 m\u00b2 tot.", "habitaciones": "3 amb.", "hace": "Contactar"}, "image": "https://imgar.zonapropcdn.com/avisos/1/00/53/57/24/10/360x266/1909358526.jpg?isFirstImage=true", "title": "Departamento \u00b7 67m\u00b2 \u00b7 3 Ambientes \u00b7 Semipiso 3 Ambientes Amoblado Muy Luminoso"}, "https://www.zonaprop.com.ar/propiedades/clasificado/alclapin-av-independencia-y-rincon-3-ambientes-grandes-53571130.html": {"date": "06-05-2024\n", "index": 67, "content": "$ 550.000\n$ 85.000 Expensas\nAvenida Independencia 2000\nSan Cristobal, Capital Federal\n80 m\u00b2 tot.\n3 amb.\n2 dorm.\n1 ba\u00f1o\nDepartamento al frente sobre Avenida Independencia - Ampios ambientes. Balc\u00f3n corrido al frente. Hall de entrada - Living-comedor. 2 dormitorios (ambos con placard) Cocina comedor diario. Ba\u00f1o completo + Ba\u00f1o de servicio. Pisos de parquet. Entrega aproximada 20 d\u00edas. 2 ascensores\nPublicado hace 3 d\u00edas\nContactar", "revised": false, "rejected": true, "data": {"precio": "$ 550.000", "expensas": "$ 85.000 Expensas", "direccion": "Avenida Independencia 2000", "metros": "80 m\u00b2 tot.", "habitaciones": "3 amb.", "hace": "Contactar"}, "image": "https://imgar.zonapropcdn.com/avisos/1/00/53/57/11/30/360x266/1909329328.jpg?isFirstImage=true", "title": "Departamento de 3 ambientes, San Cristobal \u00b7 Av Independencia y Rinc\u00f3n - 3 Ambientes Grandes - Balc\u00f3n"}, "https://www.zonaprop.com.ar/propiedades/clasificado/alclapin-alquiler-semipiso-3-amb-palermo-53570633.html": {"date": "03-05-2024\n", "content": "$ 500.000\n$ 135.000 Expensas\nAraoz al 2800\nBarrio Norte, Capital Federal\n89 m\u00b2 tot.\n3 amb.\n2 dorm.\n1 ba\u00f1o\nExcelente 3 ambientes. PalermoSemipiso al contrafrente con balc\u00f3n corrido, living comedor y dormitorios con pisos de parquet, cocina c/ comedor diario, ba\u00f1o y toillete, lavadero independiente. Excelente ubicaci\u00f3n! A 2 cuadras de Jardin Botanico y Parque Las Heras. A 4 cuadras de Subte D, estaci\u00f3n Scalabrini Ortiz. requisitos*1 mes A delantado + 2 meses de deposito (en dolares) *ingresos comprobables*garantia propietaria (caba, prov. Bs. As. ) O seguro caucion*contrato A 2 a\u00f1os*incremento mensual por ipc\"Para los casos de alquiler de vivienda, el monto m\u00e1ximo de comisi\u00f3n que se le puede requerir a los propietarios ser\u00e1 el equivalente al cuatro con quince cent\u00e9simos por ciento (4, 15%) del valor total del respectivo contrato. Se encuentra prohibido cobrar a los inquilinos que sean personas f\u00edsicas comisiones inmobiliarias y gastos de gestor\u00eda de informes\". -Constructora e Inmobiliaria Crecer S. A. H\u00e9ctor Gonzalez - Matricula Cucicba 5189.\nSuper destacado\nPublicado hoy\nContactar", "revised": true, "rejected": true, "data": {"precio": "$ 500.000", "expensas": "$ 135.000 Expensas", "direccion": "Araoz al 2800", "metros": "89 m\u00b2 tot.", "habitaciones": "3 amb.", "hace": "Super destacado\nPublicado desde ayer"}}, "https://www.zonaprop.com.ar/propiedades/clasificado/alclapin-alquiler-de-semipiso-de-3-ambientes-con-dependencia-en-53567617.html": {"date": "03-05-2024\n", "content": "$ 500.000\n$ 45.000 Expensas\nAv San Juan 2767\nSan Cristobal, Capital Federal\n98 m\u00b2 tot.\n3 amb.\n2 dorm.\n1 ba\u00f1o\nAlquiler de departamento de 3 ambientes con dependencia en San Crist\u00f3bal. El departamento se encuentra en un noveno piso al contrafrente con vista panor\u00e1mica Ubicado sobre la Av. San Juan muy cercano a l\u00ednea E y H de subte, zona s\u00faper comercial y cercano a todo. El inmueble cuenta con ambientes muy luminosos y espaciosos, cocina completa, lavadero independiente, living comedor con salida al balc\u00f3n corrido, ba\u00f1o completo, toilette, y un segundo balc\u00f3n totalmente cubierto. Bajas Expensas. Aumento trimestral por ipc Requisitos. Mes de adelanto, mes de dep\u00f3sito, garant\u00eda de caba / seguro de cauci\u00f3n e ingresos demostrables. Gastos. Certificaciones de firma y si correspondiere informes de dominio e inhibici\u00f3n.\nPublicado desde ayer\nContactar", "revised": true, "rejected": true, "data": {"precio": "$ 500.000", "expensas": "$ 45.000 Expensas", "direccion": "Av San Juan 2767", "metros": "98 m\u00b2 tot.", "habitaciones": "3 amb.", "hace": "Publicado hace 2 d\u00edas"}}, "https://www.zonaprop.com.ar/propiedades/clasificado/alclapin-alquiler-3-ambientes-constitucion-3800-boedo-53565447.html": {"date": "06-05-2024\n", "index": 96, "content": "$ 490.000\nConstitucion 3800 1\u00b0\nBoedo, Capital Federal\n85 m\u00b2 tot.\n3 amb.\n2 dorm.\n1 ba\u00f1o\nExcelente departamento 3 ambientes en alquiler en boedo. living comedor c\u00f3modo con balc\u00f3n corrido A la calle. cocina amplia con lavadero (conexi\u00f3n P/lavarropas) hall distribuci\u00f3n con cerramiento. habitaci\u00f3n principal con A/A. ambas habitaciones con placard. ba\u00f1o completo. ambientes ventilados. excelente luminosidad. pisos parquet. bajas expensas. pr\u00f3ximo A avenida san juan - subte. requisitos: . Actualizaci\u00f3n trimestral por indice ipc. . 1 mes dep\u00f3sito. . 1 mes alquiler adelantado. . Garant\u00eda propietaria caba o seguro de garant\u00eda Finaer (aprobado). . Antig\u00fcedad 1 a\u00f1o en relaci\u00f3n de dependencia. . Justificativo de ingresos que triplique valor de alquiler. . Contrato por 2 a\u00f1os. . No apto mascota. Comunicate Y agend\u00e1 tu visita. ley 5859: Art\u00edculo 4\u00b0. - Incorp\u00f3rase como inciso 8 del art\u00edculo 10 de la Ley 2340 (texto consolidado seg\u00fan Ley N\u00b0 5666) el siguiente texto: Para los casos de alquiler de vivienda, el monto m\u00e1ximo de comisi\u00f3n que se le puede requerir a los propietarios ser\u00e1 el equivalente al cuatro con quince cent\u00e9simos por ciento (4, 15%) del valor total del respectivo contrato. Se encuentra prohibido cobrar a los inquilinos que sean personas f\u00edsicas comisiones inmobiliarias y gastos de gestor\u00eda de informes. - Ley 5115: excepto que en la descripci\u00f3n de la propiedad se indique lo contrario, el edificio puede no contar con rampa para personas con movilidad reducida, y no ser Accesible para personas con discapacidades f\u00edsicas. - Nota importante: Toda la informaci\u00f3n y medidas provistas son aproximadas, deber\u00e1n ratificarse con la documentaci\u00f3n pertinente y no compromete contractualmente a nuestra empresa. Los gastos (expensas, abl) expresados refieren a la \u00faltima informaci\u00f3n recabada y deber\u00e1n confirmarse. Fotograf\u00edas no vinculantes ni contractuales. Torrisi propiedades. eduardo esp\u00edndola. mat. C. U. C. I. C. B. A nro. 26\nPublicado hace 4 d\u00edas\nContactar", "revised": false, "rejected": true, "data": {"precio": "$ 490.000", "expensas": "", "direccion": "Constitucion 3800 1\u00b0", "metros": "85 m\u00b2 tot.", "habitaciones": "3 amb.", "hace": "Contactar"}, "image": "https://imgar.zonapropcdn.com/avisos/1/00/53/56/54/47/360x266/1909200543.jpg?isFirstImage=true", "title": "Departamento \u00b7 83m\u00b2 \u00b7 3 Ambientes \u00b7 Alquiler - 3 Ambientes - Constituci\u00f3n 3800 - Boedo"}, "https://www.zonaprop.com.ar/propiedades/clasificado/alclocin-amplia-y-luminosa-oficina-a-escasos-m-del-congreso-de-53562350.html": {"date": "03-05-2024\n", "content": "$ 160.000\n$ 120.000 Expensas\nHipolito Yrigoyen 1920\nCongreso, Capital Federal\n75 m\u00b2 tot.\n3 amb.\n1 ba\u00f1o\nAmplia y luminosa oficina a escasos metros del Congreso de la Nacion en excelente estado cerca de innumerables medios de comunicacion. Consta de 3 ambientes, ba\u00f1o y cocina.\nDestacado\nPublicado hace 2 d\u00edas\nContactar", "revised": false, "rejected": true, "data": {"precio": "$ 160.000", "expensas": "$ 120.000 Expensas", "direccion": "Hipolito Yrigoyen 1920", "metros": "75 m\u00b2 tot.", "habitaciones": "3 amb.", "hace": "Destacado\nPublicado desde ayer"}}, "https://www.zonaprop.com.ar/propiedades/clasificado/alclapin-3amb-s-av!-ubic-ideal!-sj-y-boe!-coc-recic-lav!-bno!-53562563.html": {"date": "06-05-2024\n", "index": 113, "content": "$ 370.000\n$ 20.000 Expensas\nAvenida San Juan 3500\nSan Cristobal, Capital Federal\n61 m\u00b2 tot.\n3 amb.\n2 dorm.\n1 ba\u00f1o\n\u00a1 3 ambientes en san juan Y boedo! \u00a1 listo para ser habitado! #Departamento | #Est\u00e1ndar | #3amb | #Lateral | #SanJuanyboedoAvenida San Juan 3500, Piso 2 - Ciudad Aut\u00f3noma de Buenos Aires\u00b7 Caracter\u00edsticas: ~ Departamento de tres (3) ambientes, en un segundo (2\u00ba) piso por escalera, dispuesto hacia el lateral, ubicado en el centro neur\u00e1lgico del barrio de Boedo. ~ Orientaci\u00f3n N (Norte). Impecable estado de conservaci\u00f3n interior de cada uno de sus ambientes. Vista interior. Gran ventilaci\u00f3n. Distribuci\u00f3n funcional~ Gran afluencia comercial y residencial en la zona. Ubicado en el coraz\u00f3n del emblem\u00e1tico cruce de calles principal del barrio: San Juan y Boedo. ~ Conectividad con medios de transporte. M\u00faltiples colectivos y subte/metro L\u00ednea E - Estaci\u00f3n Boedo. Cercan\u00eda a subida/bajada Autopista (au) 25 de Mayo. ~ Su oferta comercial incluye actividades recreativas y culturales, locales gastron\u00f3micos, farmacias, paseos, instituciones m\u00e9dicas y educativas. \u00b7 Edificio: ~ Antiguo, entre medianeras. Su fachada combina hormig\u00f3n pintado en color beige con planta baja revestida en m\u00e1rmol negro. ~ pb, m\u00e1s dos (2) pisos. No cuenta con ascensor. Baj\u00edsimas expensas. Previsibles gastos de mantenimiento mensuales. \u00b7 Distribuci\u00f3n: ~ Living comedor. ~ Cocina independiente. ~ Lavadero incorporado en cocina. ~ Distribuidor. ~ Ba\u00f1o completo con ba\u00f1era. ~ Dormitorio principal con placard. ~ Dormitorio secundario. \u00b7 Equipamiento: ~ Paredes pintadas en tonalidades claras conservan su natural luminosidad. Pisos de parquet en living comedor, distribuidor y dormitorios. ~ Ba\u00f1o con pisos revestidos en cer\u00e1micas color beige. Artefactos completos y ba\u00f1era instalados. Vanitory nuevo. Hogar en living comedor. Aire acondicionado de pared. ~ Cocina con pisos revestidos mosaicos color borravino claro con granas blancas y paredes revestidas en azulejos blancos con guarda decorativa. ~ Cocina a gas. Agua caliente suministrada a trav\u00e9s de calef\u00f3n a gas. Mobiliario de cocina (bajo mesada y alacena) de melamina/mdf color blanco. ~ Mesada de granito gris mara. Conexi\u00f3n para lavarropas bajo mesada. Turbina de acero inoxidable instalada en cocina como extractor / purificador de aire. ~ Cuenta con placard empotrado con puertas frontales, divisores, cajoneras, barrales y dem\u00e1s interiores a medida instalados en su dormitorio principal. \u00b7 Requisitos solicitados por la parte propietaria: ~ 1 mes de alquiler por adelantado. ~ 1 mes de dep\u00f3sito de garant\u00eda. ~ De la fianza: garant\u00eda propietaria o sistema de garant\u00edas de cauci\u00f3n (Finaer / Fiancor). ~ De los ingresos: \u00faltimos tres (3) recibos de sueldo o certificaci\u00f3n de ingresos por contador p\u00fablico. \u00b7 Condiciones ofrecidas por la parte propietaria: ~ Duraci\u00f3n del contrato: 12 meses (contrato de alquiler temporario sin muebles). ~ Actualizaci\u00f3n: ipc \u00b7 \u00cdndice de Precios al Consumidor publicado por el indec. ~ Periodicidad de actualizaci\u00f3n: Trimestral. #Nota: El edificio no cuenta con accesibilidad para personas con movilidad reducida (Ley 5115). Las im\u00e1genes en este anuncio publicadas son meramente ilustrativas y no poseen car\u00e1cter contractual. El importe de expensas anunciado ha sido extra\u00eddo de su \u00faltima facturaci\u00f3n, es orientativo, no vinculante y est\u00e1 sujeto a modificaciones y/o variaciones sin previa publicidad. Las medidas expresadas en el presente aviso son aproximadas y a t\u00edtulo informativo. Las medidas originales surgir\u00e1n de los respectivos planos y/o escritura del inmueble. El inmueble no es apto para mascotas por expresa solicitud de sus propietarios en el contrato de comercializaci\u00f3n. Somos especialistas en operaciones simult\u00e1neas. Tasamos en los 48 barrios de la Ciudad de Buenos Aires: . ar/tasaciones/spinelli propiedadeswww. spinelliprop. com. ar#Visitas por WhatsApp al +54 9 11 Ver datos#Reservas al Ver datos Ver datos#Consultas a Ver datos#Oficina en Avenida San Juan 3467 - cabadesde 1921 - #OportunidadesGrandesComoUnaCasa\nPublicado hace 5 d\u00edas\nContactar", "revised": false, "rejected": true, "data": {"precio": "$ 370.000", "expensas": "$ 20.000 Expensas", "direccion": "Avenida San Juan 3500", "metros": "61 m\u00b2 tot.", "habitaciones": "3 amb.", "hace": "Contactar"}, "image": "https://imgar.zonapropcdn.com/avisos/1/00/53/56/25/63/360x266/1909140276.jpg?isFirstImage=true", "title": "Departamento de 3 ambientes, San Cristobal \u00b7 3amb S/av! Ubic Ideal! Sj y Boe! Coc Recic Lav! B\u00f1o! Bjas Exp! Listo P/hab!"}, "https://www.zonaprop.com.ar/propiedades/clasificado/alclapin-3amb-s-av!-ubic-ideal!-sj-y-boe!-coc-recic-lav!-bno!-53562562.html": {"date": "06-05-2024\n", "index": 110, "content": "$ 370.000\n$ 20.000 Expensas\nAvenida San Juan 3500\nBoedo, Capital Federal\n61 m\u00b2 tot.\n3 amb.\n2 dorm.\n1 ba\u00f1o\n\u00a1 3 ambientes en san juan Y boedo! \u00a1 listo para ser habitado! #Departamento | #Est\u00e1ndar | #3amb | #Lateral | #SanJuanyboedoAvenida San Juan 3500, Piso 2 - Ciudad Aut\u00f3noma de Buenos Aires\u00b7 Caracter\u00edsticas: ~ Departamento de tres (3) ambientes, en un segundo (2\u00ba) piso por escalera, dispuesto hacia el lateral, ubicado en el centro neur\u00e1lgico del barrio de Boedo. ~ Orientaci\u00f3n N (Norte). Impecable estado de conservaci\u00f3n interior de cada uno de sus ambientes. Vista interior. Gran ventilaci\u00f3n. Distribuci\u00f3n funcional~ Gran afluencia comercial y residencial en la zona. Ubicado en el coraz\u00f3n del emblem\u00e1tico cruce de calles principal del barrio: San Juan y Boedo. ~ Conectividad con medios de transporte. M\u00faltiples colectivos y subte/metro L\u00ednea E - Estaci\u00f3n Boedo. Cercan\u00eda a subida/bajada Autopista (au) 25 de Mayo. ~ Su oferta comercial incluye actividades recreativas y culturales, locales gastron\u00f3micos, farmacias, paseos, instituciones m\u00e9dicas y educativas. \u00b7 Edificio: ~ Antiguo, entre medianeras. Su fachada combina hormig\u00f3n pintado en color beige con planta baja revestida en m\u00e1rmol negro. ~ pb, m\u00e1s dos (2) pisos. No cuenta con ascensor. Baj\u00edsimas expensas. Previsibles gastos de mantenimiento mensuales. \u00b7 Distribuci\u00f3n: ~ Living comedor. ~ Cocina independiente. ~ Lavadero incorporado en cocina. ~ Distribuidor. ~ Ba\u00f1o completo con ba\u00f1era. ~ Dormitorio principal con placard. ~ Dormitorio secundario. \u00b7 Equipamiento: ~ Paredes pintadas en tonalidades claras conservan su natural luminosidad. Pisos de parquet en living comedor, distribuidor y dormitorios. ~ Ba\u00f1o con pisos revestidos en cer\u00e1micas color beige. Artefactos completos y ba\u00f1era instalados. Vanitory nuevo. Hogar en living comedor. Aire acondicionado de pared. ~ Cocina con pisos revestidos mosaicos color borravino claro con granas blancas y paredes revestidas en azulejos blancos con guarda decorativa. ~ Cocina a gas. Agua caliente suministrada a trav\u00e9s de calef\u00f3n a gas. Mobiliario de cocina (bajo mesada y alacena) de melamina/mdf color blanco. ~ Mesada de granito gris mara. Conexi\u00f3n para lavarropas bajo mesada. Turbina de acero inoxidable instalada en cocina como extractor / purificador de aire. ~ Cuenta con placard empotrado con puertas frontales, divisores, cajoneras, barrales y dem\u00e1s interiores a medida instalados en su dormitorio principal. \u00b7 Requisitos solicitados por la parte propietaria: ~ 1 mes de alquiler por adelantado. ~ 1 mes de dep\u00f3sito de garant\u00eda. ~ De la fianza: garant\u00eda propietaria o sistema de garant\u00edas de cauci\u00f3n (Finaer / Fiancor). ~ De los ingresos: \u00faltimos tres (3) recibos de sueldo o certificaci\u00f3n de ingresos por contador p\u00fablico. \u00b7 Condiciones ofrecidas por la parte propietaria: ~ Duraci\u00f3n del contrato: 12 meses (contrato de alquiler temporario sin muebles). ~ Actualizaci\u00f3n: ipc \u00b7 \u00cdndice de Precios al Consumidor publicado por el indec. ~ Periodicidad de actualizaci\u00f3n: Trimestral. #Nota: El edificio no cuenta con accesibilidad para personas con movilidad reducida (Ley 5115). Las im\u00e1genes en este anuncio publicadas son meramente ilustrativas y no poseen car\u00e1cter contractual. El importe de expensas anunciado ha sido extra\u00eddo de su \u00faltima facturaci\u00f3n, es orientativo, no vinculante y est\u00e1 sujeto a modificaciones y/o variaciones sin previa publicidad. Las medidas expresadas en el presente aviso son aproximadas y a t\u00edtulo informativo. Las medidas originales surgir\u00e1n de los respectivos planos y/o escritura del inmueble. El inmueble no es apto para mascotas por expresa solicitud de sus propietarios en el contrato de comercializaci\u00f3n. Somos especialistas en operaciones simult\u00e1neas. Tasamos en los 48 barrios de la Ciudad de Buenos Aires: . ar/tasaciones/spinelli propiedadeswww. spinelliprop. com. ar#Visitas por WhatsApp al +54 9 11 Ver datos#Reservas al Ver datos Ver datos#Consultas a Ver datos#Oficina en Avenida San Juan 3467 - cabadesde 1921 - #OportunidadesGrandesComoUnaCasa\nPublicado hace 5 d\u00edas\nContactar", "revised": false, "rejected": true, "data": {"precio": "$ 370.000", "expensas": "$ 20.000 Expensas", "direccion": "Avenida San Juan 3500", "metros": "61 m\u00b2 tot.", "habitaciones": "3 amb.", "hace": "Contactar"}, "image": "https://imgar.zonapropcdn.com/avisos/1/00/53/56/25/62/360x266/1909140248.jpg?isFirstImage=true", "title": "Departamento \u00b7 61m\u00b2 \u00b7 3 Ambientes \u00b7 3amb S/av! Ubic Ideal! Sj y Boe! Coc Recic Lav! B\u00f1o! Bjas Exp! Listo P/hab!"}, "https://www.zonaprop.com.ar/propiedades/clasificado/alclapin-alquiler-3-amb-barrio-norte-53562573.html": {"date": "06-05-2024\n", "index": 111, "content": "$ 530.000\n$ 78.000 Expensas\nJuncal al 2700\nBarrio Norte, Capital Federal\n68 m\u00b2 tot.\n3 amb.\n2 dorm.\n1 ba\u00f1o\nSe alquila 3 ambientes contrafrente. Excelente ubicaci\u00f3n. Apto profesional. 2 Aires acondicionados. Contrato de 2 a\u00f1os. Luciano Trajtenbergcucicba 8130\nPublicado hace 5 d\u00edas\nContactar", "revised": false, "rejected": true, "data": {"precio": "$ 530.000", "expensas": "$ 78.000 Expensas", "direccion": "Juncal al 2700", "metros": "68 m\u00b2 tot.", "habitaciones": "3 amb.", "hace": "Contactar"}, "image": "https://imgar.zonapropcdn.com/avisos/1/00/53/56/25/73/360x266/1909140565.jpg?isFirstImage=true", "title": "Departamento \u00b7 68m\u00b2 \u00b7 3 Ambientes \u00b7 Alquiler 3 Amb Barrio Norte"}, "https://www.zonaprop.com.ar/propiedades/clasificado/alclapin-3amb-nuevo-74-m-sup2--cochera-cubiert!-aa!-53560241.html": {"date": "03-05-2024\n", "content": "$ 600.000\n$ 93.760 Expensas\nAvenida San Juan al 3500\nBoedo, Capital Federal\n74 m\u00b2 tot.\n3 amb.\n2 dorm.\n1 ba\u00f1o\n1 coch.\n\u00a1 3 ambientes nuevo! \u00a1 con amenities, cochera fija Y cubierta! #Venta | #Departamento | #3amb | #Cochera | #Boedo | #NuevoAvenida San Juan 3500, Piso 8 - Ciudad Aut\u00f3noma de Buenos Aires\u00b7 Caracter\u00edsticas: ~ Departamento de tres (3) ambientes nuevo, en piso alto, con balc\u00f3n al contrafrente y detalles de categor\u00eda, en ubicaci\u00f3n privilegiada del barrio de Boedo. ~ Orientaci\u00f3n N (Norte). Vista abierta y panor\u00e1mica a Ciudad. Ventilaci\u00f3n cruzada. Luminoso y moderno, ofrece una combinaci\u00f3n perfecta de estilo contempor\u00e1neo y comodidades funcionales. ~ Con una distribuci\u00f3n inteligente, este departamento cuenta con un balc\u00f3n perfecto para disfrutar de un caf\u00e9 por la ma\u00f1ana o contemplar las vistas a la ciudad. ~ Ubicado sobre Avenida San Juan. A 47 metros de Avenida Boedo. A 347 metros de Avenida Pav\u00f3n. A 447 metros de Avenida Juan de Garay. A 447 metros de Avenida Independencia. ~ Conectividad con medios de transporte. M\u00faltiples colectivos y subte/metro L\u00ednea E - Estaci\u00f3n Boedo. Cercan\u00eda a subida/bajada Autopista (au) 25 de Mayo. ~ Su oferta comercial incluye actividades recreativas y culturales, locales gastron\u00f3micos, farmacias, paseos, instituciones m\u00e9dicas y educativas. \u00b7 Edificio: ~ Empezado sobre terreno de doble frente. Su fachada combina hormig\u00f3n revestido en tarquini en diferentes tonalidades de gris y vidrios templados de sus balcones. ~ Su planta baja (pb) se encuentra revestida en lajas modelo San Luis. Cuenta con un local comercial, un acceso vehicular a cocheras y una entrada peatonal con rampa de accesibilidad para personas con movilidadreducida. ~ 12 pisos. 4 departamentos por piso. 2 ascensores autom\u00e1ticos con cabina de acero inoxidable. Garage privado con acceso a trav\u00e9s de port\u00f3n autom\u00e1tico. ~ El monto de expensas especificado en el anuncio incluye el suministro de agua (Aysa), y agua caliente (Metrogas) y el servicio el\u00e9ctrico (Edesur). \u00b7 Distribuci\u00f3n: ~ Living comedor. ~ Cocina semi-integrada estilo americana. ~ Balc\u00f3n corrido hacia el contrafrente. ~ Pasillo de distribuci\u00f3n. ~ Dormitorio principal. ~ Toilette. ~ Dormitorio secundario. ~ Ba\u00f1o completo con ba\u00f1era. \u00b7 Equipamiento: ~ Paredes pintadas en tonalidades claras conservan su natural luminosidad. Pisos revestidos en flotantes de pvc s\u00edmil madera color color Oak. ~ Su cocina cuenta con paredes revestidas en porcelanatos blancos y pisos revestidos en porcelanatos color azul oscuro con terminaci\u00f3n mate. ~ Mobiliario de cocina (bajo-mesada y alacenas) de melamina/mdf color blanco con su respectiva perfiles y tiradores de aluminio. Mesada de granito modelo gris mara. ~ Extractor / purificador de aire marca Spar de acero inoxidable. Artefactos de cocina (anafe con cuatro hornallas y horno empotrado) el\u00e9ctricos. ~ Aire acondicionado split instalado en su living comedor. Calefacci\u00f3n individual a trav\u00e9s de paneles el\u00e9ctricos, uno por cada ambiente. ~ Cuenta con placares empotrados con puertas de piso/techo de apertura corrediza, cajoneras, barrales, divisores, y dem\u00e1s interiores a medida en su pasillo de distribuci\u00f3n y sus dormitorios. \u00b7 Adicionales: ~ Agua caliente central por termotanques de alta recuperaci\u00f3n. ~ C\u00e1maras de monitoreo instaladas en sectores comunes. \u00b7 Amenities: ~ Sal\u00f3n de usos m\u00faltiples (sum). ~ Parrilla. Solarium. \u00b7 Cochera: ~ Fija, cubierta e individual. ~ Ubicada en primer piso. ~ Port\u00f3n autom\u00e1tico. \u00b7 Requisitos solicitados por la parte propietaria: ~ 1 mes de alquiler por adelantado. ~ 1 mes de dep\u00f3sito de garant\u00eda. ~ De la fianza: garant\u00eda propietaria o sistema de garant\u00edas de cauci\u00f3n (Finaer / Fiancor). ~ De los ingresos: \u00faltimos tres (3) recibos de sueldo o certificaci\u00f3n de ingresos por contador p\u00fablico. \u00b7 Condiciones ofrecidas por la parte propietaria: ~ Duraci\u00f3n del contrato: 12 meses (contrato de alquiler temporario sin muebles). ~ Actualizaci\u00f3n: ipc \u00b7 \u00cdndice de Precios al Consumidor publicado por el indec. ~ Periodicidad de actualizaci\u00f3n: Trimestral. #Nota: El edificio no cuenta con accesibilidad para personas con movilidad reducida (Ley 5115). Las im\u00e1genes en este anuncio publicadas son meramente ilustrativas y no poseen car\u00e1cter contractual. El importe de expensas anunciado ha sido extra\u00eddo de su \u00faltima facturaci\u00f3n, es orientativo, no vinculante y est\u00e1 sujeto a modificaciones y/o variaciones sin previa publicidad. Las medidas expresadas en el presente aviso son aproximadas y a t\u00edtulo informativo. Las medidas originales surgir\u00e1n de los respectivos planos y/o escritura del inmueble. El inmueble no es apto para mascotas por expresa solicitud de sus propietarios en el contrato de comercializaci\u00f3n. Somos especialistas en operaciones simult\u00e1neas. Tasamos en los 48 barrios de la Ciudad de Buenos Aires: . ar/tasaciones/spinelli propiedadeswww. spinelliprop. com. ar#Visitas por WhatsApp al +54 9 11 Ver datos#Reservas al Ver datos Ver datos#Consultas a Ver datos#Oficina en Avenida San Juan 3467 - cabadesde 1921 - #OportunidadesGrandesComoUnaCasa\nDestacado\nPublicado hace 2 d\u00edas\nContactar", "revised": false, "rejected": true}, "https://www.zonaprop.com.ar/propiedades/clasificado/alclapin-tres-ambientes-en-congreso-mitre-y-libertad-53560407.html": {"date": "06-05-2024\n", "index": 134, "content": "$ 450.000\n$ 80.000 Expensas\nBARTOLOME MITRE 1200\nCongreso, Capital Federal\n70 m\u00b2 tot.\n3 amb.\n2 dorm.\n1 ba\u00f1o\nEdificio clasico. departamento al contrafrente de tres ambientes. muy luminoso. amplia cocina independiente con conexion lavarropas. dos habitaciones. balcon corrido. comodo living. pisos de madera todos plastificados. amplios placards. requisitos garantia caba O finaer Y constanciasde ingresos. alquiler mas gastos. apto porfesional\nPublicado hace 5 d\u00edas\nContactar", "revised": false, "rejected": true, "data": {"precio": "$ 450.000", "expensas": "$ 80.000 Expensas", "direccion": "BARTOLOME MITRE 1200", "metros": "70 m\u00b2 tot.", "habitaciones": "3 amb.", "hace": "Contactar"}, "image": "https://imgar.zonapropcdn.com/avisos/1/00/53/56/04/07/360x266/1909094792.jpg?isFirstImage=true", "title": "Departamento de 3 ambientes, Congreso \u00b7 Tres Ambientes en Congreso Mitre y Libertad"}, "https://www.zonaprop.com.ar/propiedades/clasificado/alclapin-m-av-belgrano-subte-h-3-amb-con-balcon-cfte-vista-53552379.html": {"date": "06-05-2024\n", "index": 132, "content": "$ 440.000\n$ 46.000 Expensas\nALBERTI 355 10 PISO C\nSan Nicol\u00e1s, Capital Federal\n80 m\u00b2 tot.\n3 amb.\n2 dorm.\n1 ba\u00f1o\nSuper luminoso departamento de 3 ambientes en contra-frente, moderno, con 2 equipos de aire acondicionado split frio-calor! Amplio living comedor con salida al balc\u00f3n, 2 dormitorios con placard, ba\u00f1o completo, cocina amplia con comedor diario, lavadero. Adem\u00e1s cuenta con una puerta de acceso blindada, pisos de parquet plastificados. \u00a1oportunidad! Precio: $ 440. 000 mensuales el primer trimestre; luego se actualiza con el indice de precios al consumidor aplicado al 50% Y el indice de ripte (salarios) al 50% condiciones: 1 mes adelantado, un mes de dep\u00f3sito. El locatario y su garante deber\u00e1n poseer ingresos mensuales en relaci\u00f3n de dependencia equivalentes A 2/3 veces el importe del alquiler mensual, no es una exigencia para el garante ser propietario en la ciudad de buenos aires. Para visitar llamar A R. Besada & asociados - Ver datos y/o Ver datos. \"Para los casos de alquiler de vivienda, el monto m\u00e1ximo de comisi\u00f3n que se le puede requerir a los propietarios ser\u00e1 el equivalente al cuatro con quince cent\u00e9simos por ciento (4, 15%) del valor total del respectivo contrato. Se encuentra prohibido cobrar a los inquilinos que sean personas f\u00edsicas comisiones inmobiliarias y gastos de gestar\u00eda de informes\". Ruben M besada - Matricula cucicba N. \u00ba 2645 -\nPublicado hace 6 d\u00edas\nContactar", "revised": true, "rejected": false, "data": {"precio": "$ 440.000", "expensas": "$ 46.000 Expensas", "direccion": "ALBERTI 355 10 PISO C", "metros": "80 m\u00b2 tot.", "habitaciones": "3 amb.", "hace": "Contactar"}, "image": "https://imgar.zonapropcdn.com/avisos/1/00/53/55/23/79/360x266/1908917751.jpg?isFirstImage=true", "title": "Departamento de 3 ambientes, San Nicol\u00e1s \u00b7 M Av Belgrano, Subte \"H\" 3 Amb con Balcon Cfte, Vista Abierta, 2 Split F/c", "comment": "Cerca de casa"}, "https://www.zonaprop.com.ar/propiedades/clasificado/alclapin-3-ambientes-al-contra-frente-53557131.html": {"date": "06-05-2024\n", "index": 133, "content": "$ 360.000\n$ 45.000 Expensas\nSan Jose 800 6\u00b0\nMonserrat, Capital Federal\n62 m\u00b2 tot.\n3 amb.\n2 dorm.\n1 ba\u00f1o\n3 ambientes comodos al contrafrente. Luz Y sol. cocina amplia con espacio comedor. lavadero independiente con pileta Y espacio para lavarropas. dos amplios doritorios, ambos con placar. living comedor con ventanal al contrafrente. Vista abierta. expensas $Ver datos. aysa. abl. luz. gas. requisitos: garantia propietaria de caba O seguro de caucion argenprop. 1 mes de deposito en garantia. 1 mes adelantado. demostracion de ingresos acordes al alquiler. contrato por 2 a\u00f1os ajustable por ipc cuatrimestralmente. informes comerciales Y laborales. contactenos para visita. Ver datos whatsapp. Ver datos/5. eugenio A ferraro propiedades\nPublicado hace 6 d\u00edas\nContactar", "revised": false, "rejected": true, "data": {"precio": "$ 360.000", "expensas": "$ 45.000 Expensas", "direccion": "San Jose 800 6\u00b0", "metros": "62 m\u00b2 tot.", "habitaciones": "3 amb.", "hace": "Contactar"}, "image": "https://imgar.zonapropcdn.com/avisos/1/00/53/55/71/31/360x266/1909228460.jpg?isFirstImage=true", "title": "Departamento \u00b7 62m\u00b2 \u00b7 3 Ambientes \u00b7 3 Ambientes Al Contra Frente"}, "https://www.zonaprop.com.ar/propiedades/clasificado/alclapin-departamento-en-alquiler-3-ambientes-con-balcon-53556815.html": {"date": "06-05-2024\n", "index": 128, "content": "$ 580.000\n$ 60.000 Expensas\nLavalle al 2900\nBalvanera, Capital Federal\n80 m\u00b2 tot.\n3 amb.\n2 dorm.\n1 ba\u00f1o\n** se alquila **Departamento de 3 ambientes con balcon. Se encuentra en un 9no piso, amplio departamento de 3 ambientes: cuenta con living comedor con salida al balc\u00f3n, cocina separada, sala comedor, lavadero con ba\u00f1o, dormitorio principal con salida al balc\u00f3n y placard, dormitorio secundario con placard, ba\u00f1o completo. Expensas $60. 000requisitos comerciales *garantia propietaria O garant\u00eda de finaer *demostracion de ingresos *contrato por 2 a\u00f1os *aumento trimestral por icl *deposito 2 mesesmuy buena ubicaci\u00f3n sobre la calle Lavalle al 2900 a 1 cuadra de Av. Corrientes. Si te interesa coordinar una visita para ver \u00e9sta y otras propiedades, por favor, no dejes de contactarte. fama PropiedadesCasa Central: Av. Emilio Castro 7371 - caba / Tel. : 4642. 5600\nPublicado hace 6 d\u00edas\nContactar", "revised": false, "rejected": true, "data": {"precio": "$ 580.000", "expensas": "$ 60.000 Expensas", "direccion": "Lavalle al 2900", "metros": "80 m\u00b2 tot.", "habitaciones": "3 amb.", "hace": "Contactar"}, "image": "https://imgar.zonapropcdn.com/avisos/1/00/53/55/68/15/360x266/1909015458.jpg?isFirstImage=true", "title": "LIVING \u00b7 Departamento en Alquiler 3 Ambientes con Balcon"}, "https://www.zonaprop.com.ar/propiedades/clasificado/alclapin-3-ambientes-con-cochera-53544115.html": {"date": "06-05-2024\n", "index": 137, "content": "$ 450.000\n$ 99.500 Expensas\nIndependencia al 2200\nBalvanera, Capital Federal\n62 m\u00b2 tot.\n3 amb.\n2 dorm.\n1 ba\u00f1o\n1 coch.\n3 Ambientes con cochera en Independencia 2200Al frente muy luminoso en 7\u00ba pisoLiving comedor de 4. 72 x 4. 68Pisos de Parquet Balc\u00f3n de 4 M2Dormitorio principal de 3. 03 x 2. 96 con placardSegundo dormitorio de 2. 94 x 3. 02 con placard Ba\u00f1o completoConexi\u00f3n para lavarropas: siservicios Individuales: sicochera fija: sibalc\u00f3n: SiApto mascotas: NoA/A: NoCalefacci\u00f3n: Nocondiciones de alquiler: Contrato de 2 a\u00f1os en pesosAjuste cada 6 meses por ipc (\u00edndice de precios al consumidor) Finaer o garant\u00eda propietaria de capital (familiar directo) 1 mes adelantado y 1 mes de dep\u00f3sitoDemostraci\u00f3n de ingresos por el triple del precio y del garanteGastos de certificaci\u00f3n de firmas a cargo del inquilino\nSuper destacado\nPublicado hace 7 d\u00edas\nContactar", "revised": false, "rejected": true, "data": {"precio": "$ 450.000", "expensas": "$ 99.500 Expensas", "direccion": "Independencia al 2200", "metros": "62 m\u00b2 tot.", "habitaciones": "3 amb.", "hace": "Contactar"}, "image": "https://imgar.zonapropcdn.com/avisos/1/00/53/54/41/15/360x266/1908726456.jpg?isFirstImage=true", "title": "Departamento \u00b7 58m\u00b2 \u00b7 3 Ambientes \u00b7 1 Cochera \u00b7 3 Ambientes con Cochera"}, "https://www.zonaprop.com.ar/propiedades/clasificado/alclapin-departamento-en-alquiler-3-amb-con-dep-y-cochera-53547633.html": {"date": "03-05-2024\n", "content": "$ 700.000\n$ 145.000 Expensas\nLibertad 800\nSan Nicol\u00e1s, Capital Federal\n83 m\u00b2 tot.\n3 amb.\n2 dorm.\n2 ba\u00f1os\n1 coch.\nCorredor Responsable: Diego Mastrangelo cucicba 7615 csi 6609- Contacto: Dalma Manzi Olivera - mls id # Ver datos-37. Alquiler Residencial departamento 3 amb con dependencia y cochera. Requisitos: - Ingresos demostrables para garantizar un acuerdo de alquiler exitoso y sin complicaciones, requerimos que los solicitantes demuestren ingresos suficientes para cumplir con el pago mensual del alquiler. - Fianza garantor. - Mes de Deposito. - Mes de Alquiler Adelantado. Caracteristicas: Living-Comedor integrado. Hall de Distribuci\u00f3n. Cocina independiente. Lavadero incorporado. Un dormitorio con ropero funcional. Segundo dormitorio con ropero funcional. Ba\u00f1o completo con ba\u00f1era. Dependencia de Servicio. Segundo ba\u00f1o completo. Espacio guarda coche cubierto. Para los casos de alquiler de vivienda, el monto m\u00e1ximo de comisi\u00f3n que se le puede requerir a los propietarios ser\u00e1 el equivalente al cuatro con quince cent\u00e9simos por ciento (4, 15%) del valor total del respectivo contrato. Se encuentra prohibido cobrar a los inquilinos que sean personas f\u00edsicas comisiones inmobiliarias y gastos de gestor\u00eda de informes. Remax Argentina S. R. L. No ejerce el corretaje inmobiliario. El presente sitio web es una plataforma en donde cada oficina inmobiliaria independiente que contrata los servicios re/max puede publicar las propiedades a su cargo. Cada oficina es de propiedad y gesti\u00f3n independiente, por lo que Remax Argentina S. R. L no interviene en los datos de la publicaci\u00f3n, en la operaci\u00f3n inmobiliaria, ni en la confecci\u00f3n y/o firma del boleto de compraventa y/o escritura y/o contrato de alquiler. En cumplimiento de las leyes vigentes que regulan el corretaje inmobiliario, Ley Nacional 25. 028, Ley 22. 802 de Lealtad Comercial, Ley 24. 240 de Defensa al Consumidor, las normas del C\u00f3digo Civil y Comercial de la Naci\u00f3n y Constitucionales, los agentes/gestores no ejercen el corretaje inmobiliario. Todas las operaciones inmobiliarias son objeto de intermediaci\u00f3n y conclusi\u00f3n por parte del corredor p\u00fablico inmobiliario colegiado a cargo de la publicaci\u00f3n, cuyos datos se exhiben en la presente. La presente publicaci\u00f3n describe las caracter\u00edsticas esenciales del inmueble, debi\u00e9ndose consultar al corredor p\u00fablico inmobiliario responsable de la operaci\u00f3n por la eventual actualizaci\u00f3n de las medidas, descripciones arquitect\u00f3nicas y funcionales, valores de expensas, servicios, impuestos, precios y dem\u00e1s informaci\u00f3n, cuyos valores son aproximados. Para los casos de alquiler de vivienda, el monto m\u00e1ximo de comisi\u00f3n que se le puede requerir a los propietarios ser\u00e1 el equivalente al cuatro con quince cent\u00e9simos por ciento (4, 15%) del valor total del respectivo contrato. Se encuentra prohibido cobrar a los inquilinos que sean personas f\u00edsicas comisiones inmobiliarias y gastos de gestor\u00eda de informes. El inmueble no es accesible para personas con discapacidades f\u00edsicas.\nPublicado hace 4 d\u00edas\nContactar", "revised": false, "rejected": true, "data": {"precio": "$ 700.000", "expensas": "$ 145.000 Expensas", "direccion": "Libertad 800", "metros": "83 m\u00b2 tot.", "habitaciones": "3 amb.", "hace": "Publicado hace 5 d\u00edas"}}, "https://www.zonaprop.com.ar/propiedades/clasificado/alclappa-alquiler-departamento-3-ambientes-amplios-a-estrenar-53543295.html": {"date": "03-05-2024\n", "content": "$ 400.000\nSan Cristobal, Capital Federal\n76 m\u00b2 tot.\n3 amb.\n2 dorm.\n1 ba\u00f1o\nSe organizaran las visitas desde el lunes 8 de mayo. si esta interesado Y cumple con los requisitos mas abajo detallados se le enviara un link para organizar las visitas. amplios 3 ambientes A estrenar. en 1\u00b0 piso por escalera. Expensas casi inexistentes. living cocina integrada, 2 habitaciones, ba\u00f1o completo con ba\u00f1era, - pisos flotante habitaciones. - piso porcelanato pulido en living. - pisos ceramica en ba\u00f1o. - cocina anafe electrico acero inoxidable, - termotanque electrico, 60 litros. - lugar para lavarropas en ba\u00f1o. - placards en habitaciones principal. requisitos. - comprobacion de ingresos. - garantia finaer O garantia propietaria capital federal. Condiciones. - 1 mes adelanto. - 1 mes de deposito. - ajuste trimestral por ipc\nPublicado hace 4 d\u00edas\nContactar", "revised": false, "rejected": true, "data": {"precio": "$ 400.000", "direccion": "", "metros": "76 m\u00b2 tot.", "habitaciones": "3 amb.", "hace": "Contactar"}}, "https://www.zonaprop.com.ar/propiedades/clasificado/alclapin-departamento-en-alquiler-barrio-balvanera-53542166.html": {"date": "03-05-2024\n", "content": "$ 400.000\n$ 50.000 Expensas\nIndependencia 1200\nBalvanera, Capital Federal\n70 m\u00b2 tot.\n3 amb.\n2 dorm.\n1 ba\u00f1o\nDepartamento de 70m2, cuenta con un ba\u00f1o con ducha y adem\u00e1s ba\u00f1o privado. Posee un patio descubierto, buen ingreso de luz natural. Muy buena ubicaci\u00f3n, cercano a Avenida 9 de Julio y universidad uade. Muy bien conectado con transporte p\u00fablico: Transportes Cercanos: Colectivos: 2, 9, 10, 17, 23, 39, 45, 53, 57, 59, 60, 67, 70, 91, 96, 98, 100, 102, 126, 129, 168, 195Subtes (Metro) : independencia (L\u00ednea C) , independencia (L\u00ednea E) Datos \u00fatiles: \u00c1rea Hospitalaria: htal. Dr. J. M. Ramos mej\u00edadistrito Escolar: Distrito Escolar iiimatriculado responsable: Roberto Barral matr\u00edcula N\u00ba3006 cucicba. ? En el cumplimiento de la ley nacional 25. 028, ley 22. 802 de lealtad comercial. ? Ley 24. 240 de defensa al consumidor, las normas del c\u00f3digo civil y comercial de la naci\u00f3n y constitucionales. Los agentes no ejercen el corretaje inmobiliario. ? Ley 5859 -Art. 4: \"Para los casos de alquiler de vivienda, el monto m\u00e1ximo de comisi\u00f3n que se le puede requerir a los propietarios ser\u00e1 el equivalente al cuatro con quince cent\u00e9simos por ciento (4, 15%) del valor total del contrato. Se encuentra prohibido cobrar a los inquilinos que sean personas f\u00edsicas comisiones inmobiliarias y gastos de gestor\u00eda de informes\". (En caso de ser alquiler) ? Ley 5115 \u2013 Art. 1: El inmueble publicado no es accesible para personas con capacidades f\u00edsicas reducidas. (En caso de no ser accesible) ? Se deja constancia que las medidas, superficies y m2 consignados son aproximados, sujetos a verificaci\u00f3n y/o ajuste. El precio del inmueble puede ser modificado sin previo aviso.\nSuper destacado\nPublicado hace 5 d\u00edas\nContactar", "revised": false, "rejected": true, "data": {"precio": "$ 400.000", "expensas": "$ 50.000 Expensas", "direccion": "Independencia 1200", "metros": "70 m\u00b2 tot.", "habitaciones": "3 amb.", "hace": "Contactar"}}, "https://www.zonaprop.com.ar/propiedades/clasificado/alclapin-departamento-en-alquiler-barrio-balvanera-53542165.html": {"date": "03-05-2024\n", "content": "$ 400.000\n$ 50.000 Expensas\nIndependencia 1200\nMonserrat, Capital Federal\n70 m\u00b2 tot.\n3 amb.\n2 dorm.\n1 ba\u00f1o\nDepartamento de 70m2, cuenta con un ba\u00f1o con ducha y adem\u00e1s ba\u00f1o privado. Posee un patio descubierto, buen ingreso de luz natural. Muy buena ubicaci\u00f3n, cercano a Avenida 9 de Julio y universidad uade. Muy bien conectado con transporte p\u00fablico: Transportes Cercanos: Colectivos: 2, 9, 10, 17, 23, 39, 45, 53, 57, 59, 60, 67, 70, 91, 96, 98, 100, 102, 126, 129, 168, 195Subtes (Metro) : independencia (L\u00ednea C) , independencia (L\u00ednea E) Datos \u00fatiles: \u00c1rea Hospitalaria: htal. Dr. J. M. Ramos mej\u00edadistrito Escolar: Distrito Escolar iiimatriculado responsable: Roberto Barral matr\u00edcula N\u00ba3006 cucicba. ? En el cumplimiento de la ley nacional 25. 028, ley 22. 802 de lealtad comercial. ? Ley 24. 240 de defensa al consumidor, las normas del c\u00f3digo civil y comercial de la naci\u00f3n y constitucionales. Los agentes no ejercen el corretaje inmobiliario. ? Ley 5859 -Art. 4: \"Para los casos de alquiler de vivienda, el monto m\u00e1ximo de comisi\u00f3n que se le puede requerir a los propietarios ser\u00e1 el equivalente al cuatro con quince cent\u00e9simos por ciento (4, 15%) del valor total del contrato. Se encuentra prohibido cobrar a los inquilinos que sean personas f\u00edsicas comisiones inmobiliarias y gastos de gestor\u00eda de informes\". (En caso de ser alquiler) ? Ley 5115 \u2013 Art. 1: El inmueble publicado no es accesible para personas con capacidades f\u00edsicas reducidas. (En caso de no ser accesible) ? Se deja constancia que las medidas, superficies y m2 consignados son aproximados, sujetos a verificaci\u00f3n y/o ajuste. El precio del inmueble puede ser modificado sin previo aviso.\nDestacado\nPublicado hace 5 d\u00edas\nContactar", "revised": false, "rejected": true, "data": {"precio": "$ 400.000", "expensas": "$ 50.000 Expensas", "direccion": "Independencia 1200", "metros": "70 m\u00b2 tot.", "habitaciones": "3 amb.", "hace": "Contactar"}}, "https://www.zonaprop.com.ar/propiedades/clasificado/alclapin-alquiler-departamento-3-ambientes-balvanera-53539391.html": {"date": "03-05-2024\n", "content": "$ 550.000\n$ 98.000 Expensas\nPichincha 500\nBalvanera, Capital Federal\n70 m\u00b2 tot.\n3 amb.\n2 dorm.\n1 ba\u00f1o\nCorredor Responsable: guillermo frimet cucicba 4235 / Pablo Anibal Montenegro cpmcal 552- Contacto: Carla Vasti - mls id # Ver datos. Excelente departamento al frente, con balcon corrido de tres ambientes con dependencia muy luminoso. Pisos de madera. Ba\u00f1o completo. Ba\u00f1o de servicio. Cocina separda. lavadero. Excelente ubicacion, cerca de medios de transporte. Requisitos: Mes de alquiler. Mes de deposito de Garantia. Seguro de caucion por Finaer, Garantor o Garantia Ya. Transportes Cercanos. Colectivos: 2, 8, 23, 56, 57, 61, 62, 64, 84, 86, 88, 95, 96, 98, 101, 103, 118, 129, 168, Remax Argentina S. R. L. No ejerce el corretaje inmobiliario. El presente sitio web es una plataforma en donde cada oficina inmobiliaria independiente que contrata los servicios re/max puede publicar las propiedades a su cargo. Cada oficina es de propiedad y gesti\u00f3n independiente, por lo que Remax Argentina S. R. L no interviene en los datos de la publicaci\u00f3n, en la operaci\u00f3n inmobiliaria, ni en la confecci\u00f3n y/o firma del boleto de compraventa y/o escritura y/o contrato de alquiler. En cumplimiento de las leyes vigentes que regulan el corretaje inmobiliario, Ley Nacional 25. 028, Ley 22. 802 de Lealtad Comercial, Ley 24. 240 de Defensa al Consumidor, las normas del C\u00f3digo Civil y Comercial de la Naci\u00f3n y Constitucionales, los agentes/gestores no ejercen el corretaje inmobiliario. Todas las operaciones inmobiliarias son objeto de intermediaci\u00f3n y conclusi\u00f3n por parte del corredor p\u00fablico inmobiliario colegiado a cargo de la publicaci\u00f3n, cuyos datos se exhiben en la presente. La presente publicaci\u00f3n describe las caracter\u00edsticas esenciales del inmueble, debi\u00e9ndose consultar al corredor p\u00fablico inmobiliario responsable de la operaci\u00f3n por la eventual actualizaci\u00f3n de las medidas, descripciones arquitect\u00f3nicas y funcionales, valores de expensas, servicios, impuestos, precios y dem\u00e1s informaci\u00f3n, cuyos valores son aproximados. Para los casos de alquiler de vivienda, el monto m\u00e1ximo de comisi\u00f3n que se le puede requerir a los propietarios ser\u00e1 el equivalente al cuatro con quince cent\u00e9simos por ciento (4, 15%) del valor total del respectivo contrato. Se encuentra prohibido cobrar a los inquilinos que sean personas f\u00edsicas comisiones inmobiliarias y gastos de gestor\u00eda de informes. El inmueble no es accesible para personas con discapacidades f\u00edsicas.\nPublicado hace 6 d\u00edas\nContactar", "revised": false, "rejected": true}, "https://www.zonaprop.com.ar/propiedades/clasificado/alclcain-4amb-casa-patio-terraza-escritorio-53540115.html": {"date": "03-05-2024\n", "content": "$ 580.000\nCastro Barros 1400\nBoedo, Capital Federal\n178 m\u00b2 tot.\n3 amb.\n1 ba\u00f1o\nCasa de 4ambientes en pb al frente con entrada independiente 180mts. Hall de entrada, Living/comedor diario, cocina, 3 habitaciones de 3, 9x3, 7mts (con pisos de parquet y 2 de ellas al frente) Patio trasero con lavadero, ba\u00f1o completo y cuarto de escritorio de 2, 7x1, 8mts. Terraza completa (toda la superficie de la casa) se pinto recientemente. Falta pintura, se puede descontar la misma a medida que se va haciendo. sobre Castro Barros a mts Av Pavon\nPublicado hace 6 d\u00edas\nContactar", "revised": false, "rejected": true}, "https://www.zonaprop.com.ar/propiedades/clasificado/alclapin-alquiler-tres-ambientes.-recoleta-53532067.html": {"date": "03-05-2024\n", "content": "$ 500.000\n$ 55.000 Expensas\nParaguay 2630\nBarrio Norte, Capital Federal\n68 m\u00b2 tot.\n3 amb.\n2 dorm.\n1 ba\u00f1o\nParaguay 2630 (Ecuador y Jean Jaures) recoleta. * unidad de tres ambientes en alquiler *Ubicado en el barrio de Recoleta, con cercan\u00eda a principales avenidas, subte l\u00ednea D. Todos los medios de transporte. Zona de facultades. Se trata de un tres ambientes, 4to piso orientado al contra frente, cuenta con, - Living comedor, con vista al pulm\u00f3n- Dormitorio principal con placard. Salida al balc\u00f3n, vista abierta- Segundo dormitorio con placard - Ba\u00f1o completo - Cocina separada con artefacto a gas. - Lavadero Buen estado de conservaci\u00f3n. Todos los ambientes cuentan con ventilaci\u00f3n y luz. Disponible. No se aceptan mascotas. requisitos: contar con garantia propietaria O seguro de cauci\u00f3n Y comprobantes de ingresos. ajuste cuatrimestral por ipcingresos, garantia propietaria O finaer. sin mascotas.\nPublicado hace 7 d\u00edas\nContactar", "revised": false, "rejected": true}, "https://www.zonaprop.com.ar/propiedades/clasificado/alclapin-departamento-en-alquiler-con-vista-abierta-53534315.html": {"date": "03-05-2024\n", "content": "$ 400.000\n$ 55.000 Expensas\nIndependencia al 2100\nBalvanera, Capital Federal\n65 m\u00b2 tot.\n3 amb.\n2 dorm.\n1 ba\u00f1o\nDepartamento de 2 habitaciones con placard, ba\u00f1o completo, living comedor con salida a balc\u00f3n y cocina\nPublicado hace 7 d\u00edas\nContactar", "revised": false, "rejected": true}, "https://www.zonaprop.com.ar/propiedades/clasificado/alclapin-rincon-al-400-depto-3-amb.-en-alquiler-congreso-53532664.html": {"date": "03-05-2024\n", "content": "$ 480.000\n$ 65.000 Expensas\nRincon al 400\nCongreso, Capital Federal\n65 m\u00b2 tot.\n3 amb.\n2 dorm.\n1 ba\u00f1o\nMuy lindo depto 3 ambientes, en excelente estado. Ubicado en muy buen edifcio. El depto se compone de: - Living comedor- Amplia cocina con bajo mesada y alacena, con espacio para comedor diario- Lavadero exterior- Habitacion de generosas medidas- 2da habitacion con gran placard- ba\u00f1o completo. Todo en buen estado, recien pintado. Muy luminoso. Silencioso. Requisitos de alquiler: Mes de adelanto, mes de deposito, garantia propietaria o seguro finaer y demostracion de ingresos. Datos \u00fatiles: Barrio: Balvanera -Comuna: Comuna 3 -\u00c1rea Hospitalaria: htal. Dr. J. M. Ramos mej\u00edacomisar\u00eda Comunal: 3 -Comisar\u00eda Vecinal: 3CTransportes Cercanos: Colectivos: 2, 6, 8, 12, 23, 37, 50, 56, 57, 64, 84, 86, 90, 95, 96, 98, 103, 129, 150, 151, 168Ubicado a metros de Av. Belgrano y pocas cuadras de Av. Entre R\u00edos. -Todas las operaciones inmobiliarias se encuentran a cargo del profesional matriculado de la oficina corredor inmobiliario Dario Nievas, Matricula 5252. La intermediaci\u00f3n y la conclusi\u00f3n de las mismas ser\u00e1n llevadas exclusivamente por \u00e9l. Cada oficina es de propiedad y de gesti\u00f3n independiente. En el cumplimiento de la ley nacional 25. 028, ley 22. 802 de lealtad comercial. Ley 24. 240 de defensa al consumidor, las normas del c\u00f3digo civil y comercial de la naci\u00f3n y constitucionales. Los agentes no ejercen el corretaje inmobiliario. Queremos ayudarte con tus sue\u00f1os y proyectos!\nPublicado hace 7 d\u00edas\nContactar", "revised": true, "rejected": false, "comment": "C\u00f3mo casa"}, "https://www.zonaprop.com.ar/propiedades/clasificado/alclapin-juncal-al-2600-3-amb-luminoso-gran-balcon-53534519.html": {"date": "03-05-2024\n", "content": "$ 650.000\nJuncal 2000\nBarrio Norte, Capital Federal\n70 m\u00b2 tot.\n3 amb.\n2 dorm.\n1 ba\u00f1o\nLas medidas, superficies y proporciones consignadas en esta ficha son aproximadas y solo se muestran a titulo informativo. -\nPublicado hace 7 d\u00edas\nContactar", "revised": false, "rejected": true}, "https://www.zonaprop.com.ar/propiedades/clasificado/alclapin-av-pueyrredon-y-av-sta.-fe-2-dorm-escrit.-53525375.html": {"date": "03-05-2024\n", "content": "$ 600.000\n$ 120.000 Expensas\nAV. PUEYRREDON 1400\nBarrio Norte, Capital Federal\n70 m\u00b2 tot.\n3 amb.\n2 dorm.\n1 ba\u00f1o\n1 coch.\nAv. Pueyrredon Y av. Santa fe - piso alto - impecable (recien pintado Y pisos plastificados) - muy luminoso - no acepta mascotas de ningun tipo - cochera fija (2do. Subsuelo) acceso por elevador - se alquila si \u00f3 si C/cochera (inlcuida en el precio) - hall de ingreso C/gran placard, living comedor Y escritorio (vista lateral abierta). 2 dormitorios (3, 20X3 y otro 3X2) ambos con grandes placares (vista abierta al frente). Ba\u00f1o completo C/ante ba\u00f1o. Cocina C/lavadero incorporado. - no acepta mascotas de ningun tipo - valor de alquiler cochera fija incluida! - expensas de depto Y cochera total $120. 000 abril 2024 - condiciones de contrato = 24 meses C/ajuste trimestral ipc + deposito + garantia de caba + demostrar ingresos comprobables C/antiguedad. Bravo basile propiedaes - ricardo Ver datos\nDestacado\nPublicado hace 8 d\u00edas\nContactar", "revised": false, "rejected": true}, "https://www.zonaprop.com.ar/propiedades/clasificado/alclapin-sarmiento-al-2100-3-amb-c-escritorio-53527575.html": {"date": "03-05-2024\n", "content": "$ 490.000\n$ 95.000 Expensas\nSarmiento al 2100\nBalvanera, Capital Federal\n75 m\u00b2 tot.\n3 amb.\n2 dorm.\n1 ba\u00f1o\nC\u00f3modo departamento de 3 amb con escritorio (posible 3er dormitorio) Al frente muy luminoso. Amplia cocina con espacio de comedor diariopisos de parquet. Agua caliente central. Pr\u00f3ximo de Facultad de Medicina. Cercano a Subtes \u201cB\u201d, \u201cA\u201d y \u201cD\u201d. Dormitorio DormitorioLiving Escritorio/3er Dormitorio. Cocina con espacio comedor diario Lavadero en cocina. Ba\u00f1o.\nPublicado hace 8 d\u00edas\nContactar", "revised": false, "rejected": true}, "https://www.zonaprop.com.ar/propiedades/clasificado/alclapin-3amb-al-fte-con-bcom-lum-53528680.html": {"date": "03-05-2024\n", "content": "$ 650.000\n$ 90.000 Expensas\nCharcas 3670\nBarrio Norte, Capital Federal\n72 m\u00b2 tot.\n3 amb.\n2 dorm.\n1 ba\u00f1o\nCharcas 3670. Remodelado a nuevo. Cocina completa. Palier privado. Balc\u00f2n al frente corrido. Patio propio. Muy luminoso. schwartz estudio inmobiliario. J. Alvarez 2410 caba - 1425. 48 21 - 22 00 w w w. S c h w a r t z. C o m. A r. ii5060. 6378Whatsapp. Art. 4\u00b0 - Hacer constar en todo ofrecimiento publicitario de locaci\u00f3n de inmuebles con destino habitacional que se emita v\u00eda p\u00e1ginas web, propias o de terceros, la siguiente leyenda: \"Para los casos de alquiler de vivienda, el monto m\u00e1ximo de comisi\u00f3n que se le puede requerir a los propietarios ser\u00e1 el equivalente al cuatro con quince cent\u00e9simos por ciento (4, 15%) del valor total del respectivo contrato. Se encuentra prohibido cobrar a los inquilinos que sean personas f\u00edsicas comisiones inmobiliarias y gastos de gestor\u00eda de informes \" (incorporado como inciso 8 del art\u00edculo 10 de la Ley 2340). Accesibilidad: Se puede recorrer desde la vereda hasta el ascensor por tramos horizontales o por rampa con anchos adecuados, luego en forma vertical por ascensor que tiene dimensiones adecuadas para circular con sillas de ruedas y luego hasta la propiedad por pasillo con ancho adecuado tambi\u00e9n. Matricula cucicba N\u00ba579 F\u00ba23 L1\nPublicado hace 8 d\u00edas\nContactar", "revised": false, "rejected": true}, "https://www.zonaprop.com.ar/propiedades/clasificado/alclappa-dueno-alquila-hermoso-depto-3-amb.-torre-c-pileta-sum-53530294.html": {"date": "03-05-2024\n", "content": "$ 530.000\n$ 100.000 Expensas\nOnce, Capital Federal\n68 m\u00b2 tot.\n3 amb.\n2 ba\u00f1os\nDue\u00f1o directo alquila hermoso departamento en octavo piso edificio moderno en torre, con pileta, sum, vigilancia 24 hs. Zona once calle Catamarca al 100. Todo externo, luminoso y ventilado. Living, 2 dormitorios, 1 ba\u00f1o completo con hidro, 1 toilette, cochera opcional, balc\u00f3n, cocina con lavadero incorporado. Termotanque el\u00e9ctrico, cocina a gas. Amplio espacio de guardado en habitaciones y cocina. Recien pintado nada para hacerle!! Deposito 1 mes y medio. Se acepta garant\u00eda propietaria o seguro de cauci\u00f3n.\nPublicado hace 8 d\u00edas\nContactar", "revised": true, "rejected": true}, "https://www.zonaprop.com.ar/propiedades/clasificado/alclapin-alquiler-excelente-departamento-en-barrio-norte-3-53524984.html": {"date": "03-05-2024\n", "content": "$ 600.000\n$ 98.000 Expensas\nBarrio Norte, Capital Federal\n78 m\u00b2 tot.\n3 amb.\n2 dorm.\n1 ba\u00f1o\nExcelente departamento en barrio norte gallo al 1500 - edificio de categoria - tres ambientes con dependencias - accesos principal Y de servicio - muy luminoso - muy buena ubicacion A dos cuadras de av. Santa fe Y cuatro del shopping alto palermo - subte linea D - colectivos Ver datos Ver datos 152 - amplio living comedor apaisado con balcon corrido al contrafrente - dos dormitorios, principal al balcon contrafrente con split - segundo dormitorio al aire Y luz - pisos de parquet muy bien mantenidos - un ba\u00f1o completo con ba\u00f1era - dependencia de servicio (actual salita de estar) con ba\u00f1o de servicio - calefaccion individual por calefon regulable desde la unidad - agua caliente individual por calefon - amplia cocina con lugar para mesa com. diaro - lavadero. Las descripciones arquitect\u00f3nicas y funcionales, valores de expensas, impuestos y servicios, fotos y medidas de este inmueble son aproximados. Los datos fueron proporcionados por el propietario y pueden no estar actualizados a la hora de la visualizaci\u00f3n de este aviso por lo cual pueden arrojar inexactitudes y discordancias con las que surgen de los las facturas, t\u00edtulos y planos legales del inmueble. El interesado deber\u00e1 realizar las verificaciones respectivas previamente a la realizaci\u00f3n de cualquier operaci\u00f3n, requiriendo por s\u00ed o sus profesionales las copias necesarias de la documentaci\u00f3n que corresponda.\nPublicado hace 8 d\u00edas\nContactar", "revised": true, "rejected": true}, "https://www.zonaprop.com.ar/propiedades/clasificado/alclapin-alquiler-3-ambientes-con-dos-patios-congreso-53573894.html": {"date": "06-05-2024\n", "index": 53, "content": "$ 400.000\n$ 45.000 Expensas\nTTE GRAL PERON 1300\nCongreso, Capital Federal\n70 m\u00b2 tot.\n3 amb.\n2 dorm.\n1 ba\u00f1o\nAlquiler departamento de 3 ambientes con 2 patios. apto profesional. cocina independiente. ba\u00f1o completo. requisitos: ingresos en blanco + gtia propietaria caba O finaer\nSuper destacado\nPublicado hace 3 d\u00edas\nContactar", "revised": false, "rejected": true, "data": {"precio": "$ 400.000", "expensas": "$ 45.000 Expensas", "direccion": "TTE GRAL PERON 1300", "metros": "70 m\u00b2 tot.", "habitaciones": "3 amb.", "hace": "Contactar"}, "image": "https://imgar.zonapropcdn.com/avisos/1/00/53/57/38/94/360x266/1909389331.jpg?isFirstImage=true", "title": "Departamento de 3 ambientes, Congreso \u00b7 Alquiler 3 Ambientes con Dos Patios Congreso"}, "https://www.zonaprop.com.ar/propiedades/clasificado/alclapin-alquiler-3-ambientes-almagro-frente-balcon-53573547.html": {"date": "06-05-2024\n", "index": 51, "content": "$ 450.000\n$ 82.000 Expensas\nPalestina 600\nAlmagro, Capital Federal\n65 m\u00b2 tot.\n3 amb.\n2 dorm.\n1 ba\u00f1o\nAlquiler departamento de 3 ambientes al frente con balcon. Cuenta con living comedor, dos dormitorios con placard, cocina independiente con lavadero incorporado. Toilette de recepcion Y ba\u00f1o principal completo. Ubicado en palestina al 600 esquina sarmiento. Requisitos: ingresos en blanco + gtia propietaria caba O finaer. no se aceptan mascotas.\nSuper destacado\nPublicado hace 3 d\u00edas\nContactar", "revised": false, "rejected": true, "data": {"precio": "$ 450.000", "expensas": "$ 82.000 Expensas", "direccion": "Palestina 600", "metros": "65 m\u00b2 tot.", "habitaciones": "3 amb.", "hace": "Contactar"}, "image": "https://imgar.zonapropcdn.com/avisos/1/00/53/57/35/47/360x266/1909383962.jpg?isFirstImage=true", "title": "Departamento de 3 ambientes, Almagro \u00b7 Alquiler 3 Ambientes Almagro Frente Balcon"}, "https://www.zonaprop.com.ar/propiedades/clasificado/alclapin-3-ambientes-c-balcon-equipado-en-almagro-53565796.html": {"date": "06-05-2024\n", "index": 81, "content": "30\n$ 700.000\n$ 80.000 Expensas\nDirecci\u00f3n no informada\nAlmagro, Capital Federal\n76 m\u00b2 tot.\n3 amb.\n2 dorm.\n1 ba\u00f1o\nSalguero Propiedades alquila departamento de 3 amb c/ balc\u00f3n, equipado, en Almagro. Ubicado en primer piso, al contrafrente. La unidad se encuentra completamente amoblada. Consta de: Living comedor con pisos de madera, aire acondicionado. Toilette para invitados. Cocina completa con muebles de alto y bajo mesada, espacio para lavarropas. Ba\u00f1o completo con ba\u00f1era. Dos dormitorios, ambos con placard y salida al balc\u00f3n. Patio interno. Edificio con piscina en planta baja. Condiciones: Contrato a 2 a\u00f1os. Ajustes cuatrimestralespor ipc. Disponibilidad inmediata. Capacidad m\u00e1xima: 4personas. Requisitos: Seguro de cauci\u00f3n Respaldar o Finaer y comprobantes de ingreso. 1 mes de deposito. 1 mes adelantado. Para visitas coordinar al Ver datos. - Para los casos de alquiler de vivienda, el monto m\u00e1ximo de comisi\u00f3n que se le puede requerir a los propietarios ser\u00e1 el equivalente al cuatro con quince cent\u00e9simos por ciento (4, 15%) del valor total del respectivo contrato. Se encuentra prohibido cobrar a los inquilinos que sean personas f\u00edsicas comisiones inmobiliarias y gastos de gestor\u00eda de informes\u009d. -\nDestacado\nPublicado hace 4 d\u00edas\nContactar", "revised": false, "rejected": true, "data": {"precio": "$ 700.000", "expensas": "$ 80.000 Expensas", "direccion": "Direcci\u00f3n no informada", "metros": "76 m\u00b2 tot.", "habitaciones": "3 amb.", "hace": "Contactar"}, "image": "https://imgar.zonapropcdn.com/avisos/1/00/53/56/57/96/360x266/1909208220.jpg?isFirstImage=true", "title": "Departamento de 3 ambientes, Almagro \u00b7 3 Ambientes C/ Balc\u00f3n Equipado en Almagro"}, "https://www.zonaprop.com.ar/propiedades/clasificado/alclapin-bulnes-111-3-ambientes-amoblado-y-equipado-en-53565392.html": {"date": "06-05-2024\n", "index": 79, "content": "$ 620.000\n$ 69.000 Expensas\nBulnes 111\nAlmagro, Capital Federal\n64 m\u00b2 tot.\n3 amb.\n2 dorm.\n1 ba\u00f1o\n3 ambientes amoblado y equipado super luminoso. Living comedor con salida al balcon. Cocina separada. 2 dormitorios con amplios placards. Ba\u00f1o completo.\nDestacado\nPublicado hace 4 d\u00edas\nContactar", "revised": false, "rejected": true, "data": {"precio": "$ 620.000", "expensas": "$ 69.000 Expensas", "direccion": "Bulnes 111", "metros": "64 m\u00b2 tot.", "habitaciones": "3 amb.", "hace": "Contactar"}, "image": "https://imgar.zonapropcdn.com/avisos/1/00/53/56/53/92/360x266/1909200087.jpg?isFirstImage=true", "title": "Departamento de 3 ambientes, Almagro \u00b7 Bulnes 111 - 3 Ambientes Amoblado y Equipado en Almagro!"}, "https://www.zonaprop.com.ar/propiedades/clasificado/alclapin-alquiler-dpto-3-amb-hip.-yrigoyen-3700-almagro-53569700.html": {"date": "06-05-2024\n", "index": 94, "content": "$ 600.000\n$ 76.000 Expensas\nHip\u00f3lito Yrigoyen 3700\nAlmagro, Capital Federal\n64 m\u00b2 tot.\n3 amb.\n2 dorm.\n1 ba\u00f1o\nCorredor Responsable: Marcelo Trujillo cucicba 6470 / cmcpdjlm 810- Contacto: Mart\u00edn Orso - mls id # Ver datos. Alquiler de departamento de 3 ambientes con amenities. *posibilidad de alquiler de cochera en el edificio ($45. 000) Hermoso Departamento en Almagro, Apto Profesional, en excelente ubicaci\u00f3n, de 3 ambientes, con balc\u00f3n al frente, en segundo piso. Consta de un living comedor, cocina, 2 dormitorios, ba\u00f1o completo, y toilette. La superficie total es de 64 metros. El edificio, en el amplio hall de entrada, posee 2 ascensores, sum en la terraza, con pileta. Las expensas incluyen Aysa. no se aceptan mascotas. Consultanos y coordinamos una visita. Transportes Cercanos. Colectivos: 2, 5, 7, 8, 19, 26, 84, 86, 88, 90, 103, 104, 105, 115, 127, 128, 132, 151, 160, 165, 180. Subtes (Metro): castro barros (L\u00ednea A) Remax Argentina S. R. L. No ejerce el corretaje inmobiliario. El presente sitio web es una plataforma en donde cada oficina inmobiliaria independiente que contrata los servicios re/max puede publicar las propiedades a su cargo. Cada oficina es de propiedad y gesti\u00f3n independiente, por lo que Remax Argentina S. R. L no interviene en los datos de la publicaci\u00f3n, en la operaci\u00f3n inmobiliaria, ni en la confecci\u00f3n y/o firma del boleto de compraventa y/o escritura y/o contrato de alquiler. En cumplimiento de las leyes vigentes que regulan el corretaje inmobiliario, Ley Nacional 25. 028, Ley 22. 802 de Lealtad Comercial, Ley 24. 240 de Defensa al Consumidor, las normas del C\u00f3digo Civil y Comercial de la Naci\u00f3n y Constitucionales, los agentes/gestores no ejercen el corretaje inmobiliario. Todas las operaciones inmobiliarias son objeto de intermediaci\u00f3n y conclusi\u00f3n por parte del corredor p\u00fablico inmobiliario colegiado a cargo de la publicaci\u00f3n, cuyos datos se exhiben en la presente. La presente publicaci\u00f3n describe las caracter\u00edsticas esenciales del inmueble, debi\u00e9ndose consultar al corredor p\u00fablico inmobiliario responsable de la operaci\u00f3n por la eventual actualizaci\u00f3n de las medidas, descripciones arquitect\u00f3nicas y funcionales, valores de expensas, servicios, impuestos, precios y dem\u00e1s informaci\u00f3n, cuyos valores son aproximados. Para los casos de alquiler de vivienda, el monto m\u00e1ximo de comisi\u00f3n que se le puede requerir a los propietarios ser\u00e1 el equivalente al cuatro con quince cent\u00e9simos por ciento (4, 15%) del valor total del respectivo contrato. Se encuentra prohibido cobrar a los inquilinos que sean personas f\u00edsicas comisiones inmobiliarias y gastos de gestor\u00eda de informes. El inmueble no es accesible para personas con discapacidades f\u00edsicas.\nPublicado hace 4 d\u00edas\nContactar", "revised": false, "rejected": true, "data": {"precio": "$ 600.000", "expensas": "$ 76.000 Expensas", "direccion": "Hip\u00f3lito Yrigoyen 3700", "metros": "64 m\u00b2 tot.", "habitaciones": "3 amb.", "hace": "Contactar"}, "image": "https://imgar.zonapropcdn.com/avisos/1/00/53/56/97/00/360x266/1909293600.jpg?isFirstImage=true", "title": "Departamento \u00b7 58m\u00b2 \u00b7 3 Ambientes \u00b7 Alquiler Dpto 3 Amb Hip. Yrigoyen 3700 (Almagro)"}, "https://www.zonaprop.com.ar/propiedades/clasificado/alclapin-3amb-s-av!-ubic-ideal!-sj-y-boe!-coc-recic-lav!-bno!-53562566.html": {"date": "06-05-2024\n", "index": 112, "content": "$ 370.000\n$ 20.000 Expensas\nAvenida San Juan 3500\nAlmagro, Capital Federal\n61 m\u00b2 tot.\n3 amb.\n2 dorm.\n1 ba\u00f1o\n\u00a1 3 ambientes en san juan Y boedo! \u00a1 listo para ser habitado! #Departamento | #Est\u00e1ndar | #3amb | #Lateral | #SanJuanyboedoAvenida San Juan 3500, Piso 2 - Ciudad Aut\u00f3noma de Buenos Aires\u00b7 Caracter\u00edsticas: ~ Departamento de tres (3) ambientes, en un segundo (2\u00ba) piso por escalera, dispuesto hacia el lateral, ubicado en el centro neur\u00e1lgico del barrio de Boedo. ~ Orientaci\u00f3n N (Norte). Impecable estado de conservaci\u00f3n interior de cada uno de sus ambientes. Vista interior. Gran ventilaci\u00f3n. Distribuci\u00f3n funcional~ Gran afluencia comercial y residencial en la zona. Ubicado en el coraz\u00f3n del emblem\u00e1tico cruce de calles principal del barrio: San Juan y Boedo. ~ Conectividad con medios de transporte. M\u00faltiples colectivos y subte/metro L\u00ednea E - Estaci\u00f3n Boedo. Cercan\u00eda a subida/bajada Autopista (au) 25 de Mayo. ~ Su oferta comercial incluye actividades recreativas y culturales, locales gastron\u00f3micos, farmacias, paseos, instituciones m\u00e9dicas y educativas. \u00b7 Edificio: ~ Antiguo, entre medianeras. Su fachada combina hormig\u00f3n pintado en color beige con planta baja revestida en m\u00e1rmol negro. ~ pb, m\u00e1s dos (2) pisos. No cuenta con ascensor. Baj\u00edsimas expensas. Previsibles gastos de mantenimiento mensuales. \u00b7 Distribuci\u00f3n: ~ Living comedor. ~ Cocina independiente. ~ Lavadero incorporado en cocina. ~ Distribuidor. ~ Ba\u00f1o completo con ba\u00f1era. ~ Dormitorio principal con placard. ~ Dormitorio secundario. \u00b7 Equipamiento: ~ Paredes pintadas en tonalidades claras conservan su natural luminosidad. Pisos de parquet en living comedor, distribuidor y dormitorios. ~ Ba\u00f1o con pisos revestidos en cer\u00e1micas color beige. Artefactos completos y ba\u00f1era instalados. Vanitory nuevo. Hogar en living comedor. Aire acondicionado de pared. ~ Cocina con pisos revestidos mosaicos color borravino claro con granas blancas y paredes revestidas en azulejos blancos con guarda decorativa. ~ Cocina a gas. Agua caliente suministrada a trav\u00e9s de calef\u00f3n a gas. Mobiliario de cocina (bajo mesada y alacena) de melamina/mdf color blanco. ~ Mesada de granito gris mara. Conexi\u00f3n para lavarropas bajo mesada. Turbina de acero inoxidable instalada en cocina como extractor / purificador de aire. ~ Cuenta con placard empotrado con puertas frontales, divisores, cajoneras, barrales y dem\u00e1s interiores a medida instalados en su dormitorio principal. \u00b7 Requisitos solicitados por la parte propietaria: ~ 1 mes de alquiler por adelantado. ~ 1 mes de dep\u00f3sito de garant\u00eda. ~ De la fianza: garant\u00eda propietaria o sistema de garant\u00edas de cauci\u00f3n (Finaer / Fiancor). ~ De los ingresos: \u00faltimos tres (3) recibos de sueldo o certificaci\u00f3n de ingresos por contador p\u00fablico. \u00b7 Condiciones ofrecidas por la parte propietaria: ~ Duraci\u00f3n del contrato: 12 meses (contrato de alquiler temporario sin muebles). ~ Actualizaci\u00f3n: ipc \u00b7 \u00cdndice de Precios al Consumidor publicado por el indec. ~ Periodicidad de actualizaci\u00f3n: Trimestral. #Nota: El edificio no cuenta con accesibilidad para personas con movilidad reducida (Ley 5115). Las im\u00e1genes en este anuncio publicadas son meramente ilustrativas y no poseen car\u00e1cter contractual. El importe de expensas anunciado ha sido extra\u00eddo de su \u00faltima facturaci\u00f3n, es orientativo, no vinculante y est\u00e1 sujeto a modificaciones y/o variaciones sin previa publicidad. Las medidas expresadas en el presente aviso son aproximadas y a t\u00edtulo informativo. Las medidas originales surgir\u00e1n de los respectivos planos y/o escritura del inmueble. El inmueble no es apto para mascotas por expresa solicitud de sus propietarios en el contrato de comercializaci\u00f3n. Somos especialistas en operaciones simult\u00e1neas. Tasamos en los 48 barrios de la Ciudad de Buenos Aires: . ar/tasaciones/spinelli propiedadeswww. spinelliprop. com. ar#Visitas por WhatsApp al +54 9 11 Ver datos#Reservas al Ver datos Ver datos#Consultas a Ver datos#Oficina en Avenida San Juan 3467 - cabadesde 1921 - #OportunidadesGrandesComoUnaCasa\nPublicado hace 5 d\u00edas\nContactar", "revised": false, "rejected": true, "data": {"precio": "$ 370.000", "expensas": "$ 20.000 Expensas", "direccion": "Avenida San Juan 3500", "metros": "61 m\u00b2 tot.", "habitaciones": "3 amb.", "hace": "Contactar"}, "image": "https://imgar.zonapropcdn.com/avisos/1/00/53/56/25/66/360x266/1909140354.jpg?isFirstImage=true", "title": "Departamento 61m\u00b2 Alquiler  \u00b7 3amb S/av! Ubic Ideal! Sj y Boe! Coc Recic Lav! B\u00f1o! Bjas Exp! Listo P/hab!"}, "https://www.zonaprop.com.ar/propiedades/clasificado/alclapin-3amb-nuevo-74-m-sup2--cochera-cubiert!-aa!-53560249.html": {"date": "03-05-2024\n", "content": "42\n$ 600.000\n$ 93.760 Expensas\nAvenida San Juan al 3500\nAlmagro, Capital Federal\n74 m\u00b2 tot.\n3 amb.\n2 dorm.\n1 ba\u00f1o\n1 coch.\n\u00a1 3 ambientes nuevo! \u00a1 con amenities, cochera fija Y cubierta! #Venta | #Departamento | #3amb | #Cochera | #Boedo | #NuevoAvenida San Juan 3500, Piso 8 - Ciudad Aut\u00f3noma de Buenos Aires\u00b7 Caracter\u00edsticas: ~ Departamento de tres (3) ambientes nuevo, en piso alto, con balc\u00f3n al contrafrente y detalles de categor\u00eda, en ubicaci\u00f3n privilegiada del barrio de Boedo. ~ Orientaci\u00f3n N (Norte). Vista abierta y panor\u00e1mica a Ciudad. Ventilaci\u00f3n cruzada. Luminoso y moderno, ofrece una combinaci\u00f3n perfecta de estilo contempor\u00e1neo y comodidades funcionales. ~ Con una distribuci\u00f3n inteligente, este departamento cuenta con un balc\u00f3n perfecto para disfrutar de un caf\u00e9 por la ma\u00f1ana o contemplar las vistas a la ciudad. ~ Ubicado sobre Avenida San Juan. A 47 metros de Avenida Boedo. A 347 metros de Avenida Pav\u00f3n. A 447 metros de Avenida Juan de Garay. A 447 metros de Avenida Independencia. ~ Conectividad con medios de transporte. M\u00faltiples colectivos y subte/metro L\u00ednea E - Estaci\u00f3n Boedo. Cercan\u00eda a subida/bajada Autopista (au) 25 de Mayo. ~ Su oferta comercial incluye actividades recreativas y culturales, locales gastron\u00f3micos, farmacias, paseos, instituciones m\u00e9dicas y educativas. \u00b7 Edificio: ~ Empezado sobre terreno de doble frente. Su fachada combina hormig\u00f3n revestido en tarquini en diferentes tonalidades de gris y vidrios templados de sus balcones. ~ Su planta baja (pb) se encuentra revestida en lajas modelo San Luis. Cuenta con un local comercial, un acceso vehicular a cocheras y una entrada peatonal con rampa de accesibilidad para personas con movilidadreducida. ~ 12 pisos. 4 departamentos por piso. 2 ascensores autom\u00e1ticos con cabina de acero inoxidable. Garage privado con acceso a trav\u00e9s de port\u00f3n autom\u00e1tico. ~ El monto de expensas especificado en el anuncio incluye el suministro de agua (Aysa), y agua caliente (Metrogas) y el servicio el\u00e9ctrico (Edesur). \u00b7 Distribuci\u00f3n: ~ Living comedor. ~ Cocina semi-integrada estilo americana. ~ Balc\u00f3n corrido hacia el contrafrente. ~ Pasillo de distribuci\u00f3n. ~ Dormitorio principal. ~ Toilette. ~ Dormitorio secundario. ~ Ba\u00f1o completo con ba\u00f1era. \u00b7 Equipamiento: ~ Paredes pintadas en tonalidades claras conservan su natural luminosidad. Pisos revestidos en flotantes de pvc s\u00edmil madera color color Oak. ~ Su cocina cuenta con paredes revestidas en porcelanatos blancos y pisos revestidos en porcelanatos color azul oscuro con terminaci\u00f3n mate. ~ Mobiliario de cocina (bajo-mesada y alacenas) de melamina/mdf color blanco con su respectiva perfiles y tiradores de aluminio. Mesada de granito modelo gris mara. ~ Extractor / purificador de aire marca Spar de acero inoxidable. Artefactos de cocina (anafe con cuatro hornallas y horno empotrado) el\u00e9ctricos. ~ Aire acondicionado split instalado en su living comedor. Calefacci\u00f3n individual a trav\u00e9s de paneles el\u00e9ctricos, uno por cada ambiente. ~ Cuenta con placares empotrados con puertas de piso/techo de apertura corrediza, cajoneras, barrales, divisores, y dem\u00e1s interiores a medida en su pasillo de distribuci\u00f3n y sus dormitorios. \u00b7 Adicionales: ~ Agua caliente central por termotanques de alta recuperaci\u00f3n. ~ C\u00e1maras de monitoreo instaladas en sectores comunes. \u00b7 Amenities: ~ Sal\u00f3n de usos m\u00faltiples (sum). ~ Parrilla. Solarium. \u00b7 Cochera: ~ Fija, cubierta e individual. ~ Ubicada en primer piso. ~ Port\u00f3n autom\u00e1tico. \u00b7 Requisitos solicitados por la parte propietaria: ~ 1 mes de alquiler por adelantado. ~ 1 mes de dep\u00f3sito de garant\u00eda. ~ De la fianza: garant\u00eda propietaria o sistema de garant\u00edas de cauci\u00f3n (Finaer / Fiancor). ~ De los ingresos: \u00faltimos tres (3) recibos de sueldo o certificaci\u00f3n de ingresos por contador p\u00fablico. \u00b7 Condiciones ofrecidas por la parte propietaria: ~ Duraci\u00f3n del contrato: 12 meses (contrato de alquiler temporario sin muebles). ~ Actualizaci\u00f3n: ipc \u00b7 \u00cdndice de Precios al Consumidor publicado por el indec. ~ Periodicidad de actualizaci\u00f3n: Trimestral. #Nota: El edificio no cuenta con accesibilidad para personas con movilidad reducida (Ley 5115). Las im\u00e1genes en este anuncio publicadas son meramente ilustrativas y no poseen car\u00e1cter contractual. El importe de expensas anunciado ha sido extra\u00eddo de su \u00faltima facturaci\u00f3n, es orientativo, no vinculante y est\u00e1 sujeto a modificaciones y/o variaciones sin previa publicidad. Las medidas expresadas en el presente aviso son aproximadas y a t\u00edtulo informativo. Las medidas originales surgir\u00e1n de los respectivos planos y/o escritura del inmueble. El inmueble no es apto para mascotas por expresa solicitud de sus propietarios en el contrato de comercializaci\u00f3n. Somos especialistas en operaciones simult\u00e1neas. Tasamos en los 48 barrios de la Ciudad de Buenos Aires: . ar/tasaciones/spinelli propiedadeswww. spinelliprop. com. ar#Visitas por WhatsApp al +54 9 11 Ver datos#Reservas al Ver datos Ver datos#Consultas a Ver datos#Oficina en Avenida San Juan 3467 - cabadesde 1921 - #OportunidadesGrandesComoUnaCasa\nPublicado desde ayer\nContactar", "revised": false, "rejected": true}, "https://www.zonaprop.com.ar/propiedades/clasificado/alclapin-departamento-en-alquiler-almagro-caballito-53534533.html": {"date": "03-05-2024\n", "content": "$ 600.000\n33 Orientales 40\nAlmagro, Capital Federal\n70 m\u00b2 tot.\n3 amb.\n2 dorm.\n2 ba\u00f1os\nAsesor: agustina miranda 11. 4. 475. 7784departamento en alquiler 3 ambientes, Almagro, Caballito - Capital FederalMuy buen estado, excelente luz, en zona residencial, pr\u00f3ximo a satsaid, Av Rivadavia y variedad de medios de transporte. Consta de amplio living comedor, cocina abierta al living, toilette, espacio de lavadero y ventanal, dormitorio grande con amplio placard, ba\u00f1o completo y segundo dormitorio con excelentes vistas, salida al balc\u00f3n. Cuenta con calefacci\u00f3n por radiadores, agua caliente por caldera, pisos cer\u00e1micos. En edificio de 7 pisos, 4 departamentos por piso, 1 ascensor. Valor de Alquiler $ 600. 000 + gastosConsultar condiciones. Llamame o enviame whatsapp. Los metros publicados son aproximados, las medidas exactas surgir\u00e1n de la escritura traslativa de dominio. La venta de este inmueble est\u00e1 sujeta a la tramitaci\u00f3n del C\u00f3digo de Transferencia de Inmuebles (coti), de conformidad con la normativa vigente (Res. Afip 2371/08, 2439/08 y ccs. ) por parte del propietario. En cumplimiento de las leyes provinciales vigentes que regulan elcorretaje inmobiliario, Ley Nacional 25. 028, Ley 22. 802 de Lealtad Comercial, Ley 24. 240 de Defensa al Consumidor, las normas del C\u00f3digo Civil y Comercial de la Naci\u00f3n y Constitucionales, los asesores no ejercen el corretaje inmobiliario. Codigoinmatricula Cucicba 4263\nSuper destacado\nPublicado hace 7 d\u00edas\nContactar", "revised": true, "rejected": true}, "https://www.zonaprop.com.ar/propiedades/clasificado/alclapin-billinghurst-y-corrientes-vista-abierta-3-amb-53533913.html": {"date": "03-05-2024\n", "content": "9\n$ 470.000\n$ 45.200 Expensas\nBILLINGHURST 500\nAlmagro, Capital Federal\n80 m\u00b2 tot.\n3 amb.\n2 dorm.\n1 ba\u00f1o\nDepartamento de 3 amb. + dependencia de servicio- piso alto- vista abierta- muy luminoso Y aireado - cocina separada- lavadero incorporado - living comedor con salida al balc\u00f3n- 2 dormitorios con placard Y dep. De serv. (opci\u00f3n 3\u00b0 dorm. ) - ba\u00f1o completo - agua caliente central - bajas expensas- sobre Av. Corrientes- linea de subte \"B\"- varias lineas de colectivo. - no se aceptan mascotas. - grupo mega recoleta. tel. Ver datos\nSuper destacado\nPublicado hace 7 d\u00edas\nContactar", "revised": false, "rejected": true}, "https://www.zonaprop.com.ar/propiedades/clasificado/alclapin-av-pueyrredon-1700.-alquiler-sin-muebles.-53535022.html": {"date": "03-05-2024\n", "content": "$ 550.000\n$ 116.000 Expensas\nAv. Pueyrredon al 1700\nBarrio Norte, Capital Federal\n63 m\u00b2 tot.\n3 amb.\n2 dorm.\n1 ba\u00f1o\nEdificio racionalista. Techos altos. Muy luminoso. Tres (3) ambientes. Edificio en esquina. Todo externo. Living comedor. Dos dormitorios. Ba\u00f1o completo. Cocina semi-integrada. Valor alquiler $ 550. 000 + expensas + Abl. Actualizaci\u00f3n trimestral ipc. Condiciones: Garant\u00eda y demostraci\u00f3n de ingresos.\nPublicado hace 7 d\u00edas\nContactar", "revised": true, "rejected": true}, "https://www.zonaprop.com.ar/propiedades/clasificado/alclphin-medrano-700-ph-3-ambientes-en-alquiler-almagro-53535858.html": {"date": "03-05-2024\n", "content": "$ 350.000\n$ 21.000 Expensas\nMedrano al 700\nAlmagro, Capital Federal\n70 m\u00b2 tot.\n3 amb.\n2 dorm.\n1 ba\u00f1o\nExcelente ph de Estilo, conn techos altos de 3 Ambientes, Reciclado, Ubicado en Almagro Alquiler Temporal por 1 A\u00f1o, Contratos renovablesRequisito Excluyente Garant\u00eda Propietaria de Capital y Recibo de Sueldo. Living Comedor y + 2 DormitoriosBa\u00f1os Reciclado con DuchaLuminosoPisos de PinoteaCocina Independiente con lavadero integrado2do Piso Por Escalera Excelente Ubicaci\u00f3n, sobre Av Medrano, a 100mts de Av corrientes, Subte btodos los medios de Transportecons\u00faltenosjumo inmobiliariatelf: Ver datos - Ver datos - Ver datos\"Para los casos de alquiler de vivienda, el monto m\u00e1ximo de comisi\u00f3n que se le puede requerir a los propietarios ser\u00e1 el equivalente al cuatro con quince cent\u00e9simos por ciento (4, 15%) del valor total del respectivo contrato. Se encuentra prohibido cobrar a los inquilinos que sean personas f\u00edsicas comisiones inmobiliarias y gastos de gestor\u00eda de informes\".\nPublicado hace 7 d\u00edas\nContactar", "revised": false, "rejected": true}, "https://www.zonaprop.com.ar/propiedades/clasificado/alclapin-departamento-3-ambientes-en-alquiler!-53537746.html": {"date": "03-05-2024\n", "content": "$ 540.000\n$ 75.000 Expensas\nAv. Diaz Velez al 4300\nAlmagro, Capital Federal\n61 m\u00b2 tot.\n3 amb.\n2 dorm.\n1 ba\u00f1o\nDepartamento de 3 ambientes al frente, muy luminoso y en excelente estado. Consta de cocina separada con espacio de lavadero, living comedor de buenas dimensiones, dos dormitorios y ba\u00f1o completo. condiciones de ingreso: -Garantia propietaria y demostracion de ingresos-Un mes de deposito + un mes de adelanto-Contrato por 2 a\u00f1os con aumentos trimestrales por indice icl (indice de contratos de locacion) \"Se deja constancia que los m2 son aproximados, al igual que las medidas parciales y el valor consignado de las expensas mensuales (en caso que corresponda pago de expensas) est\u00e1n sujetos a verificaci\u00f3n y/o ajustes, el precio del inmueble puede ser modificado sin previo aviso. Fotos de car\u00e1cter no contractual. Las unidades publicadas est\u00e1n sujetas a disponibilidad. Gaed Inmobiliaria act\u00faa solamente en car\u00e1cter de comercializadora de los inmuebles ofrecidos. Inmueble no accesible para personas con discapacidad f\u00edsica ley 5115. \u00danicamente en el caso de tratarse de alquiler de vivienda familiar, rige lo indicado en la ley 5859. \"gaed inmobiliaria. Cucicba matricula 226\nPublicado hace 7 d\u00edas\nContactar", "revised": true, "rejected": true}, "https://www.zonaprop.com.ar/propiedades/clasificado/alclapin-departamento-en-barracas-53528858.html": {"date": "03-05-2024\n", "content": "$ 370.000\n$ 1 Expensas\nFinochietto 2046 2 Piso\nParque Patricios, Capital Federal\n64 m\u00b2 tot.\n3 amb.\n2 dorm.\n1 ba\u00f1o\nDepartamento de 3 ambientes Sin expensas Amplio y Luminoso living - comedor con acceso a balc\u00f3n Cocina completa con alacenas y muebles bajo mesada. Espacio para lavarropas. 2 dormitorios con placards de piso a techoBa\u00f1o completo \u201cPara los casos de alquiler de vivienda, el monto m\u00e1ximo de comisi\u00f3n que se le puederequerir a los propietarios ser\u00e1 el equivalente al cuatro con quince cent\u00e9simos porciento (4, 15%) del valor total del respectivo contrato. Se encuentra prohibido cobrar alos inquilinos que sean personas f\u00edsicas comisiones inmobiliarias y gastos de gestor\u00edade informes\u201dNo Cumple con Ley 5115 (accesibilidad)\nPublicado hace 8 d\u00edas\nContactar", "revised": false, "rejected": true}, "https://www.zonaprop.com.ar/propiedades/clasificado/alclapin-3-amb.-apto-prof.-cohera.-balcon-tza.-amoblado.-muy-53502391.html": {"date": "06-05-2024\n", "index": 59, "content": "$ 650.000\n$ 55.000 Expensas\nCHICLANA 3200\nParque Patricios, Capital Federal\n88 m\u00b2 tot.\n3 amb.\n2 dorm.\n2 ba\u00f1os\n1 coch.\n3 amb. Apto prof. cohera. Fte Y cfte. Balcon tza, parrilla Y balcon. 2 ba\u00f1os completos uno es suite. Amoblado. Edificio moderno. Impecable. Muy luminoso. excelente unidad Y zona, proximo A av caseros, av jujuy, av brasil Y subtes Y metrobus.\nDestacado\nPublicado hace 3 d\u00edas\nContactar", "revised": false, "rejected": true, "data": {"precio": "$ 650.000", "expensas": "$ 55.000 Expensas", "direccion": "CHICLANA 3200", "metros": "88 m\u00b2 tot.", "habitaciones": "3 amb.", "hace": "Contactar"}, "image": "https://imgar.zonapropcdn.com/avisos/1/00/53/50/23/91/360x266/1909405518.jpg?isFirstImage=true", "title": "Departamento de 3 ambientes, Parque Patricios \u00b7 3 Amb. Apto Prof. Cohera. Balcon Tza. Amoblado. Muy Luminoso. Excelente Unidad"}, "https://www.zonaprop.com.ar/propiedades/clasificado/alclapin-departamento-en-alquiler-almagro-caballito-53575119.html": {"date": "06-05-2024\n", "index": 52, "content": "$ 600.000\n33 Orientales 40\nAlmagro, Capital Federal\n70 m\u00b2 tot.\n3 amb.\n2 dorm.\n2 ba\u00f1os\nAsesor: agustina miranda 11. 4. 475. 7784departamento en alquiler 3 ambientes, Almagro, Caballito - Capital FederalMuy buen estado, excelente luz, en zona residencial, pr\u00f3ximo a satsaid, Av Rivadavia y variedad de medios de transporte. Consta de amplio living comedor, cocina abierta al living, toilette, espacio de lavadero y ventanal, dormitorio grande con amplio placard, ba\u00f1o completo y segundo dormitorio con excelentes vistas, salida al balc\u00f3n. Cuenta con calefacci\u00f3n por radiadores, agua caliente por caldera, pisos cer\u00e1micos. En edificio de 7 pisos, 4 departamentos por piso, 1 ascensor. Valor de Alquiler $ 600. 000 + gastosConsultar condiciones. Llamame o enviame whatsapp. Los metros publicados son aproximados, las medidas exactas surgir\u00e1n de la escritura traslativa de dominio. La venta de este inmueble est\u00e1 sujeta a la tramitaci\u00f3n del C\u00f3digo de Transferencia de Inmuebles (coti), de conformidad con la normativa vigente (Res. Afip 2371/08, 2439/08 y ccs. ) por parte del propietario. En cumplimiento de las leyes provinciales vigentes que regulan elcorretaje inmobiliario, Ley Nacional 25. 028, Ley 22. 802 de Lealtad Comercial, Ley 24. 240 de Defensa al Consumidor, las normas del C\u00f3digo Civil y Comercial de la Naci\u00f3n y Constitucionales, los asesores no ejercen el corretaje inmobiliario. Codigoinmatricula Cucicba 4263\nSuper destacado\nPublicado hace 3 d\u00edas\nContactar", "revised": false, "rejected": true, "data": {"precio": "$ 600.000", "expensas": "", "direccion": "33 Orientales 40", "metros": "70 m\u00b2 tot.", "habitaciones": "3 amb.", "hace": "Contactar"}, "image": "https://imgar.zonapropcdn.com/avisos/1/00/53/57/51/19/360x266/1909415324.jpg?isFirstImage=true", "title": "Departamento \u00b7 70m\u00b2 \u00b7 3 Ambientes \u00b7 Departamento en Alquiler | Almagro, Caballito - Capital Federal | 3 Ambientes"}, "https://www.zonaprop.com.ar/propiedades/clasificado/alclapin-3amb-al-fte-com-balcon-53576911.html": {"date": "06-05-2024\n", "index": 66, "content": "$ 600.000\n$ 120.000 Expensas\nguemes 3806\nBarrio Norte, Capital Federal\n73 m\u00b2 tot.\n3 amb.\n2 dorm.\n1 ba\u00f1o\nGuemes 3806. 3 ambientes con lavadero. Ba\u00f1o completo. Balcon hacia el frente. schwartz estudio inmobiliario. J. Alvarez 2410 caba - 1425. 48 24 - 70 77 / 48 23 - 82 88 (14hs a 19hs) w w w. S c h w a r t z. C o m. A r. ii5060. 6378Whatsapp. Art. 4\u00b0 - Hacer constar en todo ofrecimiento publicitario de locaci\u00f3n de inmuebles con destino habitacional que se emita v\u00eda p\u00e1ginas web, propias o de terceros, la siguiente leyenda: \"Para los casos de alquiler de vivienda, el monto m\u00e1ximo de comisi\u00f3n que se le puede requerir a los propietarios ser\u00e1 el equivalente al cuatro con quince cent\u00e9simos por ciento (4, 15%) del valor total del respectivo contrato. Se encuentra prohibido cobrar a los inquilinos que sean personas f\u00edsicas comisiones inmobiliarias y gastos de gestor\u00eda de informes \" (incorporado como inciso 8 del art\u00edculo 10 de la Ley 2340). Accesibilidad: Se puede recorrer desde la vereda hasta el ascensor por tramos horizontales o por rampa con anchos adecuados, luego en forma vertical por ascensor que tiene dimensiones adecuadas para circular con sillas de ruedas y luego hasta la propiedad por pasillo con ancho adecuado tambi\u00e9n. Matricula cucicba N\u00ba579 F\u00ba23 L1\nPublicado hace 3 d\u00edas\nContactar", "revised": false, "rejected": true, "data": {"precio": "$ 600.000", "expensas": "$ 120.000 Expensas", "direccion": "guemes 3806", "metros": "73 m\u00b2 tot.", "habitaciones": "3 amb.", "hace": "Contactar"}, "image": "https://imgar.zonapropcdn.com/avisos/1/00/53/57/69/11/360x266/1909454914.jpg?isFirstImage=true", "title": "Departamento de 3 ambientes, Barrio Norte \u00b7 3amb Al Fte Com Balcon"}, "https://www.zonaprop.com.ar/propiedades/clasificado/alclapin-san-luis-2800-balvanera-alquiler-3-amb.-caba-53565352.html": {"date": "06-05-2024\n", "index": 92, "content": "$ 400.000\n$ 100.000 Expensas\nSan Luis\nBalvanera, Capital Federal\n60 m\u00b2 tot.\n3 amb.\n2 dorm.\n1 ba\u00f1o\nAlquiler 3 ambientes contrafrente muy luminoso. Ba\u00f1o y cocina completos. Se entrega con 2 camas de 1 plaza y 1 futon\nPublicado hace 3 d\u00edas\nContactar", "revised": false, "rejected": true, "data": {"precio": "$ 400.000", "expensas": "$ 100.000 Expensas", "direccion": "San Luis", "metros": "60 m\u00b2 tot.", "habitaciones": "3 amb.", "hace": "Contactar"}, "image": "https://imgar.zonapropcdn.com/avisos/1/00/53/56/53/52/360x266/1909341278.jpg?isFirstImage=true", "title": "Departamento de 3 ambientes, Balvanera \u00b7 San Luis 2800 - Balvanera - Alquiler 3 Amb. - Caba"}, "https://www.zonaprop.com.ar/propiedades/clasificado/alclapin-departamento-en-barrio-norte-53559494.html": {"date": "04-05-2024\n", "content": "15\n$ 750.000\n$ 100.000 Expensas\nAvenida Cordoba al 1400\nBarrio Norte, Capital Federal\n88 m\u00b2 tot.\n3 amb.\n2 dorm.\n1 ba\u00f1o\nDepartamento para alquiler tradicional sin muebles en el barrio de San Nicolas. 3 ambientes con dependencia. Departamento para alquiler tradicional sin muebles en el barrio de San Nicolas. 3 ambientes con dependencia. Contrafrente luminoso de 88m2. Con pallier semiprivado. Totalmente reciclado a nuevo con arquitecto. Living comedor con cocina integrada. 2 dormitorios, 1 ba\u00f1o con ba\u00f1era y dependencia de servicio con ba\u00f1o con ducha que se puede usar de toilette. El edificio cuenta con encargado. Accesibilidad C/ Movilidad Reducida. No es apto profesional. Expensas $100. 000 (4/2024) que incluyen Aysa. Abl $4766 (4/2024) Precio por mes mas gastos, Ajuste trimestral por indice ipc acumulado de esos ultimos tres meses. Las medidas, superficies y expensas consignadas en este aviso no resultan vinculantes. Los datos definitivos son los que surgen del t\u00edtulo de propiedad. Los montos de expensas e impuestos son aquellos declarados por el propietario el d\u00eda en que visitamos la propiedad para tomarla. Por favor, verificar el monto actualizado. Precios sujetos a aprobaci\u00f3n del propietario. Para el ingreso al departamento se solicita garant\u00eda de capital o Provincia, pero no de Provincia de Buenos Aires o bien, p\u00f3liza de cauci\u00f3n. Las medidas y superficies consignadas en la presente son aproximadas y no resultan vinculantes. Los datos definitivos son los que surgen del t\u00edtulo de propiedad. Advertencia importante: Los montos especificados de expensas, servicios, tasas e impuestos responden a una declaraci\u00f3n del propietario el d\u00eda que fue visitada la propiedad por nuestro personal. Favor requerir verificaci\u00f3n del monto actualizado antes de concretar la operaci\u00f3n. La venta de este inmueble est\u00e1 sujeta a la tramitaci\u00f3n del C\u00f3digo de Transferencia de Inmuebles (coti) de conformidad con la normativa vigente (Res. Afip 2371/08, 2439/08 y ccs. ) por parte del propietario. Llona San Rom\u00e1n \u2013 cpi 6681 \u2013 cmzc 502\nSuper destacado\nPublicado hace 4 d\u00edas\nContactar", "revised": true, "rejected": true, "data": {"precio": "$ 750.000", "expensas": "$ 100.000 Expensas", "direccion": "Avenida Cordoba al 1400", "metros": "88 m\u00b2 tot.", "habitaciones": "3 amb.", "hace": "Super destacado\nPublicado hace 4 d\u00edas"}, "image": "https://imgar.zonapropcdn.com/avisos/1/00/53/55/94/94/360x266/1909072177.jpg?isFirstImage=true", "title": "Departamento \u00b7 88m\u00b2 \u00b7 3 Ambientes \u00b7 Departamento en Barrio Norte"}, "https://www.zonaprop.com.ar/propiedades/clasificado/alclapin-3amb-nuevo-fte-2-balcones-60-m-sup2--muebles!-aa!-53560258.html": {"date": "06-05-2024\n", "index": 127, "content": "$ 500.000\n$ 57.000 Expensas\nAvenida Juan de Garay al 3200\nParque Patricios, Capital Federal\n60 m\u00b2 tot.\n3 amb.\n2 dorm.\n1 ba\u00f1o\n\u00a1 3 amb nuevo C/amenities! \u00a1 2 balcones, frente C/vista panor\u00e1mica! #Alquiler | #Departamento | #Amenities | #ParquePatricios | #3amb | #FrenteAvenida Juan de Garay 3200, Piso 7 - Ciudad Aut\u00f3noma de Buenos Aires\u00b7 Caracter\u00edsticas: ~ Departamento nuevo de tres (3) ambientes nuevo, dispuesto hacia el frente, con dos (2) balcones corridos, ubicado centricamente en el barrio de Parque Patricios. ~ Orientaci\u00f3n hacia el N (Norte). Vista a Ciudad. Ventilaci\u00f3n cruzada. Todos los ambientes cuentan con ventanas al exterior. ~ A 220 metros de Avenida Chiclana. A 410 metros de Avenida San Juan. A 420 metros de Avenida Boedo. A 610 metros de Avenida Jujuy. ~ Conectividad con medios de transporte. M\u00faltiples colectivos y subte/metro L\u00ednea H \u00b7 Estaci\u00f3n La Rioja. Cercan\u00eda a subida Autopista (au) 25 de Mayo. ~ Su oferta comercial incluye actividades recreativas y culturales, locales gastron\u00f3micos, farmacias, paseos, instituciones m\u00e9dicas y educativas. \u00b7 Edificio: ~ Entre medianeras. Su fachada con ladrillo a la vista y barandas de hierro pintadas en color negro. ~ El edificio cuenta con rampa con accesibilidad para personas de movilidad reducida. Acceso por puerta de blindex. Cerradura electr\u00f3nica para el ingreso. ~ Sus palieres comunes garantizan un habitar pac\u00edfico e integran pisos revestidos en porcelanatos color beige claro con terminaci\u00f3n mate y paredes pintadas en blanco. ~ 12 pisos. 3 departamentos por cada uno de sus pisos. 2 ascensores autom\u00e1ticos con cabina de acero inoxidable. Expensas en valores est\u00e1ndar (incluyen Aysa). \u00b7 Distribuci\u00f3n: ~ Living comedor (5. 10m x 3. 95m). ~ Balc\u00f3n 1 desde living comedor (4. 00m x 0. 90m). ~ Cocina sectorizada (2. 65m x 2. 00m). ~ Ba\u00f1o completo con ba\u00f1era (2. 20m x 1. 50m). ~ Dormitorio secundario (3. 05m x 2. 95m). ~ Dormitorio principal (3. 05m x 2. 95m). ~ Balc\u00f3n 2 desde dormitorio principal (1. 40m x 3. 50m). \u00b7 Equipamiento: ~ Paredes pintadas en tonalidades claras conservan su natural luminosidad. Pisos revestidos en porcelanato color gris. Dormitorios revestidos en alfombra. ~ Su cocina cuenta con pisos y paredes revestidos en porcelanato color gris. Mesada de granito. Bacha de acero inoxidable. Anafe, extractor de aire / purificador y cocina, todos el\u00e9ctricos, de acero inoxidable y de marca Domec. ~ Mobiliario de cocina (bajo-mesada y alacenas) de mdf/melamina color wengue. Mesada de m\u00e1rmol marr\u00f3n. Lavadero incorporado a bajo-mesada. Conexi\u00f3n para carga y descarga de lavarropas. ~ Provisi\u00f3n de agua caliente central por termotanques de alta recuperaci\u00f3n. Aire Acondicionado split en living comedor marca Sanyo. ~ Su ba\u00f1o cuenta con pisos y paredes revestidos en porcelanato color gris. Vanitory, artefactos y ba\u00f1era instalados. Calefacci\u00f3n con loza radiante con regulador de temperatura en dormitorios. ~ Cuenta con placares de piso/techo con puertas de apertura frontal, divisores, estantes, barrales, cajoneras y dem\u00e1s interiores a medida instalados en los dos dormitorios. ~ Heladera marca Samsung. Mesa de comedor y silla, de pl\u00e1stico. Cama instalada en dormitorio. \u00b7 Amenities: ~ Sector para parrilleros con equipamiento. ~ Terraza con solarium y espacio de relax. \u00b7 Adicionales: ~ Agua caliente central por termotanques de alta recuperaci\u00f3n. ~ Control de acceso a trav\u00e9s de cerradura electromagn\u00e9tica. \u00b7 Requisitos solicitados por la parte propietaria: ~ 1 mes de alquiler por adelantado. ~ 1 mes de dep\u00f3sito de garant\u00eda. ~ De la fianza: garant\u00eda propietaria o sistema de garant\u00edas de cauci\u00f3n (Finaer / Fiancor). ~ De los ingresos: \u00faltimos tres (3) recibos de sueldo o certificaci\u00f3n de ingresos por contador p\u00fablico. \u00b7 Condiciones ofrecidas por la parte propietaria: ~ Duraci\u00f3n del contrato: 6 \u00f3 12 meses (contrato de alquiler temporario con muebles). ~ Actualizaci\u00f3n: ipc \u00b7 \u00cdndice de Precios al Consumidor publicado por el indec. ~ Periodicidad de actualizaci\u00f3n: Trimestral. #Nota: El edificio no cuenta con accesibilidad para personas con movilidad reducida (Ley 5115). Las im\u00e1genes en este anuncio publicadas son meramente ilustrativas y no poseen car\u00e1cter contractual. El importe de expensas anunciado ha sido extra\u00eddo de su \u00faltima facturaci\u00f3n, es orientativo, no vinculante y est\u00e1 sujeto a modificaciones y/o variaciones sin previa publicidad. Las medidas expresadas en el presente aviso son aproximadas y a t\u00edtulo informativo. Las medidas originales surgir\u00e1n de los respectivos planos y/o escritura del inmueble. El inmueble no es apto para mascotas por expresa solicitud de sus propietarios en el contrato de comercializaci\u00f3n. Somos especialistas en operaciones simult\u00e1neas. Tasamos en los 48 barrios de la Ciudad de Buenos Aires: . ar/tasaciones/spinelli propiedadeswww. spinelliprop. com. ar#Visitas por WhatsApp al +54 9 11 Ver datos#Reservas al Ver datos Ver datos#Consultas a Ver datos#Oficina en Avenida San Juan 3467 - cabadesde 1921 - #OportunidadesGrandesComoUnaCasa\nPublicado hace 4 d\u00edas\nContactar", "revised": false, "rejected": true, "data": {"precio": "$ 500.000", "expensas": "$ 57.000 Expensas", "direccion": "Avenida Juan de Garay al 3200", "metros": "60 m\u00b2 tot.", "habitaciones": "3 amb.", "hace": "Contactar"}, "image": "https://imgar.zonapropcdn.com/avisos/1/00/53/56/02/58/360x266/1909091604.jpg?isFirstImage=true", "title": "Departamento \u00b7 60m\u00b2 \u00b7 3 Ambientes \u00b7 3amb Nuevo Fte 2 Balcones \u00b7 60 m\u00b2 \u00b7 Muebles! Aa! Heladera! Cama! Parr! Amenities!"}, "https://www.zonaprop.com.ar/propiedades/clasificado/alclapin-3amb-nuevo-fte-2-balcones-60-m-sup2--muebles!-aa!-53560253.html": {"date": "06-05-2024\n", "index": 131, "content": "$ 500.000\n$ 57.000 Expensas\nAvenida Juan de Garay al 3200\nBoedo, Capital Federal\n60 m\u00b2 tot.\n3 amb.\n2 dorm.\n1 ba\u00f1o\n\u00a1 3 amb nuevo C/amenities! \u00a1 2 balcones, frente C/vista panor\u00e1mica! #Alquiler | #Departamento | #Amenities | #ParquePatricios | #3amb | #FrenteAvenida Juan de Garay 3200, Piso 7 - Ciudad Aut\u00f3noma de Buenos Aires\u00b7 Caracter\u00edsticas: ~ Departamento nuevo de tres (3) ambientes nuevo, dispuesto hacia el frente, con dos (2) balcones corridos, ubicado centricamente en el barrio de Parque Patricios. ~ Orientaci\u00f3n hacia el N (Norte). Vista a Ciudad. Ventilaci\u00f3n cruzada. Todos los ambientes cuentan con ventanas al exterior. ~ A 220 metros de Avenida Chiclana. A 410 metros de Avenida San Juan. A 420 metros de Avenida Boedo. A 610 metros de Avenida Jujuy. ~ Conectividad con medios de transporte. M\u00faltiples colectivos y subte/metro L\u00ednea H \u00b7 Estaci\u00f3n La Rioja. Cercan\u00eda a subida Autopista (au) 25 de Mayo. ~ Su oferta comercial incluye actividades recreativas y culturales, locales gastron\u00f3micos, farmacias, paseos, instituciones m\u00e9dicas y educativas. \u00b7 Edificio: ~ Entre medianeras. Su fachada con ladrillo a la vista y barandas de hierro pintadas en color negro. ~ El edificio cuenta con rampa con accesibilidad para personas de movilidad reducida. Acceso por puerta de blindex. Cerradura electr\u00f3nica para el ingreso. ~ Sus palieres comunes garantizan un habitar pac\u00edfico e integran pisos revestidos en porcelanatos color beige claro con terminaci\u00f3n mate y paredes pintadas en blanco. ~ 12 pisos. 3 departamentos por cada uno de sus pisos. 2 ascensores autom\u00e1ticos con cabina de acero inoxidable. Expensas en valores est\u00e1ndar (incluyen Aysa). \u00b7 Distribuci\u00f3n: ~ Living comedor (5. 10m x 3. 95m). ~ Balc\u00f3n 1 desde living comedor (4. 00m x 0. 90m). ~ Cocina sectorizada (2. 65m x 2. 00m). ~ Ba\u00f1o completo con ba\u00f1era (2. 20m x 1. 50m). ~ Dormitorio secundario (3. 05m x 2. 95m). ~ Dormitorio principal (3. 05m x 2. 95m). ~ Balc\u00f3n 2 desde dormitorio principal (1. 40m x 3. 50m). \u00b7 Equipamiento: ~ Paredes pintadas en tonalidades claras conservan su natural luminosidad. Pisos revestidos en porcelanato color gris. Dormitorios revestidos en alfombra. ~ Su cocina cuenta con pisos y paredes revestidos en porcelanato color gris. Mesada de granito. Bacha de acero inoxidable. Anafe, extractor de aire / purificador y cocina, todos el\u00e9ctricos, de acero inoxidable y de marca Domec. ~ Mobiliario de cocina (bajo-mesada y alacenas) de mdf/melamina color wengue. Mesada de m\u00e1rmol marr\u00f3n. Lavadero incorporado a bajo-mesada. Conexi\u00f3n para carga y descarga de lavarropas. ~ Provisi\u00f3n de agua caliente central por termotanques de alta recuperaci\u00f3n. Aire Acondicionado split en living comedor marca Sanyo. ~ Su ba\u00f1o cuenta con pisos y paredes revestidos en porcelanato color gris. Vanitory, artefactos y ba\u00f1era instalados. Calefacci\u00f3n con loza radiante con regulador de temperatura en dormitorios. ~ Cuenta con placares de piso/techo con puertas de apertura frontal, divisores, estantes, barrales, cajoneras y dem\u00e1s interiores a medida instalados en los dos dormitorios. ~ Heladera marca Samsung. Mesa de comedor y silla, de pl\u00e1stico. Cama instalada en dormitorio. \u00b7 Amenities: ~ Sector para parrilleros con equipamiento. ~ Terraza con solarium y espacio de relax. \u00b7 Adicionales: ~ Agua caliente central por termotanques de alta recuperaci\u00f3n. ~ Control de acceso a trav\u00e9s de cerradura electromagn\u00e9tica. \u00b7 Requisitos solicitados por la parte propietaria: ~ 1 mes de alquiler por adelantado. ~ 1 mes de dep\u00f3sito de garant\u00eda. ~ De la fianza: garant\u00eda propietaria o sistema de garant\u00edas de cauci\u00f3n (Finaer / Fiancor). ~ De los ingresos: \u00faltimos tres (3) recibos de sueldo o certificaci\u00f3n de ingresos por contador p\u00fablico. \u00b7 Condiciones ofrecidas por la parte propietaria: ~ Duraci\u00f3n del contrato: 6 \u00f3 12 meses (contrato de alquiler temporario con muebles). ~ Actualizaci\u00f3n: ipc \u00b7 \u00cdndice de Precios al Consumidor publicado por el indec. ~ Periodicidad de actualizaci\u00f3n: Trimestral. #Nota: El edificio no cuenta con accesibilidad para personas con movilidad reducida (Ley 5115). Las im\u00e1genes en este anuncio publicadas son meramente ilustrativas y no poseen car\u00e1cter contractual. El importe de expensas anunciado ha sido extra\u00eddo de su \u00faltima facturaci\u00f3n, es orientativo, no vinculante y est\u00e1 sujeto a modificaciones y/o variaciones sin previa publicidad. Las medidas expresadas en el presente aviso son aproximadas y a t\u00edtulo informativo. Las medidas originales surgir\u00e1n de los respectivos planos y/o escritura del inmueble. El inmueble no es apto para mascotas por expresa solicitud de sus propietarios en el contrato de comercializaci\u00f3n. Somos especialistas en operaciones simult\u00e1neas. Tasamos en los 48 barrios de la Ciudad de Buenos Aires: . ar/tasaciones/spinelli propiedadeswww. spinelliprop. com. ar#Visitas por WhatsApp al +54 9 11 Ver datos#Reservas al Ver datos Ver datos#Consultas a Ver datos#Oficina en Avenida San Juan 3467 - cabadesde 1921 - #OportunidadesGrandesComoUnaCasa\nPublicado hace 5 d\u00edas\nContactar", "revised": false, "rejected": true, "data": {"precio": "$ 500.000", "expensas": "$ 57.000 Expensas", "direccion": "Avenida Juan de Garay al 3200", "metros": "60 m\u00b2 tot.", "habitaciones": "3 amb.", "hace": "Contactar"}, "image": "https://imgar.zonapropcdn.com/avisos/1/00/53/56/02/53/360x266/1909091410.jpg?isFirstImage=true", "title": "Departamento Alquiler de 3 ambientes \u00b7 3amb Nuevo Fte 2 Balcones \u00b7 60 m\u00b2 \u00b7 Muebles! Aa! Heladera! Cama! Parr! Amenities!"}, "https://www.zonaprop.com.ar/propiedades/clasificado/alclapin-3amb-nuevo-fte-2-balcones-60-m-sup2--muebles!-aa!-53560254.html": {"date": "06-05-2024\n", "index": 135, "content": "$ 500.000\n$ 57.000 Expensas\nAvenida Juan de Garay al 3200\nSan Cristobal, Capital Federal\n60 m\u00b2 tot.\n3 amb.\n2 dorm.\n1 ba\u00f1o\n\u00a1 3 amb nuevo C/amenities! \u00a1 2 balcones, frente C/vista panor\u00e1mica! #Alquiler | #Departamento | #Amenities | #ParquePatricios | #3amb | #FrenteAvenida Juan de Garay 3200, Piso 7 - Ciudad Aut\u00f3noma de Buenos Aires\u00b7 Caracter\u00edsticas: ~ Departamento nuevo de tres (3) ambientes nuevo, dispuesto hacia el frente, con dos (2) balcones corridos, ubicado centricamente en el barrio de Parque Patricios. ~ Orientaci\u00f3n hacia el N (Norte). Vista a Ciudad. Ventilaci\u00f3n cruzada. Todos los ambientes cuentan con ventanas al exterior. ~ A 220 metros de Avenida Chiclana. A 410 metros de Avenida San Juan. A 420 metros de Avenida Boedo. A 610 metros de Avenida Jujuy. ~ Conectividad con medios de transporte. M\u00faltiples colectivos y subte/metro L\u00ednea H \u00b7 Estaci\u00f3n La Rioja. Cercan\u00eda a subida Autopista (au) 25 de Mayo. ~ Su oferta comercial incluye actividades recreativas y culturales, locales gastron\u00f3micos, farmacias, paseos, instituciones m\u00e9dicas y educativas. \u00b7 Edificio: ~ Entre medianeras. Su fachada con ladrillo a la vista y barandas de hierro pintadas en color negro. ~ El edificio cuenta con rampa con accesibilidad para personas de movilidad reducida. Acceso por puerta de blindex. Cerradura electr\u00f3nica para el ingreso. ~ Sus palieres comunes garantizan un habitar pac\u00edfico e integran pisos revestidos en porcelanatos color beige claro con terminaci\u00f3n mate y paredes pintadas en blanco. ~ 12 pisos. 3 departamentos por cada uno de sus pisos. 2 ascensores autom\u00e1ticos con cabina de acero inoxidable. Expensas en valores est\u00e1ndar (incluyen Aysa). \u00b7 Distribuci\u00f3n: ~ Living comedor (5. 10m x 3. 95m). ~ Balc\u00f3n 1 desde living comedor (4. 00m x 0. 90m). ~ Cocina sectorizada (2. 65m x 2. 00m). ~ Ba\u00f1o completo con ba\u00f1era (2. 20m x 1. 50m). ~ Dormitorio secundario (3. 05m x 2. 95m). ~ Dormitorio principal (3. 05m x 2. 95m). ~ Balc\u00f3n 2 desde dormitorio principal (1. 40m x 3. 50m). \u00b7 Equipamiento: ~ Paredes pintadas en tonalidades claras conservan su natural luminosidad. Pisos revestidos en porcelanato color gris. Dormitorios revestidos en alfombra. ~ Su cocina cuenta con pisos y paredes revestidos en porcelanato color gris. Mesada de granito. Bacha de acero inoxidable. Anafe, extractor de aire / purificador y cocina, todos el\u00e9ctricos, de acero inoxidable y de marca Domec. ~ Mobiliario de cocina (bajo-mesada y alacenas) de mdf/melamina color wengue. Mesada de m\u00e1rmol marr\u00f3n. Lavadero incorporado a bajo-mesada. Conexi\u00f3n para carga y descarga de lavarropas. ~ Provisi\u00f3n de agua caliente central por termotanques de alta recuperaci\u00f3n. Aire Acondicionado split en living comedor marca Sanyo. ~ Su ba\u00f1o cuenta con pisos y paredes revestidos en porcelanato color gris. Vanitory, artefactos y ba\u00f1era instalados. Calefacci\u00f3n con loza radiante con regulador de temperatura en dormitorios. ~ Cuenta con placares de piso/techo con puertas de apertura frontal, divisores, estantes, barrales, cajoneras y dem\u00e1s interiores a medida instalados en los dos dormitorios. ~ Heladera marca Samsung. Mesa de comedor y silla, de pl\u00e1stico. Cama instalada en dormitorio. \u00b7 Amenities: ~ Sector para parrilleros con equipamiento. ~ Terraza con solarium y espacio de relax. \u00b7 Adicionales: ~ Agua caliente central por termotanques de alta recuperaci\u00f3n. ~ Control de acceso a trav\u00e9s de cerradura electromagn\u00e9tica. \u00b7 Requisitos solicitados por la parte propietaria: ~ 1 mes de alquiler por adelantado. ~ 1 mes de dep\u00f3sito de garant\u00eda. ~ De la fianza: garant\u00eda propietaria o sistema de garant\u00edas de cauci\u00f3n (Finaer / Fiancor). ~ De los ingresos: \u00faltimos tres (3) recibos de sueldo o certificaci\u00f3n de ingresos por contador p\u00fablico. \u00b7 Condiciones ofrecidas por la parte propietaria: ~ Duraci\u00f3n del contrato: 6 \u00f3 12 meses (contrato de alquiler temporario con muebles). ~ Actualizaci\u00f3n: ipc \u00b7 \u00cdndice de Precios al Consumidor publicado por el indec. ~ Periodicidad de actualizaci\u00f3n: Trimestral. #Nota: El edificio no cuenta con accesibilidad para personas con movilidad reducida (Ley 5115). Las im\u00e1genes en este anuncio publicadas son meramente ilustrativas y no poseen car\u00e1cter contractual. El importe de expensas anunciado ha sido extra\u00eddo de su \u00faltima facturaci\u00f3n, es orientativo, no vinculante y est\u00e1 sujeto a modificaciones y/o variaciones sin previa publicidad. Las medidas expresadas en el presente aviso son aproximadas y a t\u00edtulo informativo. Las medidas originales surgir\u00e1n de los respectivos planos y/o escritura del inmueble. El inmueble no es apto para mascotas por expresa solicitud de sus propietarios en el contrato de comercializaci\u00f3n. Somos especialistas en operaciones simult\u00e1neas. Tasamos en los 48 barrios de la Ciudad de Buenos Aires: . ar/tasaciones/spinelli propiedadeswww. spinelliprop. com. ar#Visitas por WhatsApp al +54 9 11 Ver datos#Reservas al Ver datos Ver datos#Consultas a Ver datos#Oficina en Avenida San Juan 3467 - cabadesde 1921 - #OportunidadesGrandesComoUnaCasa\nPublicado hace 4 d\u00edas\nContactar", "revised": false, "rejected": true, "data": {"precio": "$ 500.000", "expensas": "$ 57.000 Expensas", "direccion": "Avenida Juan de Garay al 3200", "metros": "60 m\u00b2 tot.", "habitaciones": "3 amb.", "hace": "Contactar"}, "image": "https://imgar.zonapropcdn.com/avisos/1/00/53/56/02/54/360x266/1909091479.jpg?isFirstImage=true", "title": "Departamento \u00b7 60m\u00b2 \u00b7 3 Ambientes \u00b7 3amb Nuevo Fte 2 Balcones \u00b7 60 m\u00b2 \u00b7 Muebles! Aa! Heladera! Cama! Parr! Amenities!"}, "https://www.zonaprop.com.ar/propiedades/clasificado/alclphin-humahuaca-3800-ph-3-ambientes-en-alquiler-almagro-53545911.html": {"date": "04-05-2024\n", "content": "9\n$ 300.000\nHumahuaca al 3800\nAlmagro, Capital Federal\n60 m\u00b2 tot.\n3 amb.\n2 dorm.\n1 ba\u00f1o\nExcelente ph de Estilo, con techos altos de 3 Ambientes, Ubicado en Almagro 3 Er Piso por EscaleraValor Final, incluye abl y expesas Requisito Excluyente Garant\u00eda Propietaria de Capital y Recibo de Sueldo. Living Comedor y + 2 DormitoriosBa\u00f1o con DuchaCocina Independiente con lavadero integradoNo se aceptan mascotasExcelente Ubicaci\u00f3n, sobre Av Medrano, a 100mts de Av corrientes, Subte btodos los medios de Transportecons\u00faltenosjumo inmobiliariatelf: Ver datos - Ver datos - Ver datos\"Para los casos de alquiler de vivienda, el monto m\u00e1ximo de comisi\u00f3n que se le puede requerir a los propietarios ser\u00e1 el equivalente al cuatro con quince cent\u00e9simos por ciento (4, 15%) del valor total del respectivo contrato. Se encuentra prohibido cobrar a los inquilinos que sean personas f\u00edsicas comisiones inmobiliarias y gastos de gestor\u00eda de informes\".\nPublicado hace 5 d\u00edas\nContactar", "revised": false, "rejected": true, "data": {"precio": "$ 300.000", "direccion": "Humahuaca al 3800", "metros": "60 m\u00b2 tot.", "habitaciones": "3 amb.", "hace": "Publicado hace 5 d\u00edas"}}, "https://www.zonaprop.com.ar/propiedades/clasificado/alclapin-departamento-en-alquiler-de-2-dorm.-en-balvanera-53545171.html": {"date": "04-05-2024\n", "content": "$ 400.000\n$ 40.000 Expensas\nBalvanera, Capital Federal\n60 m\u00b2 tot.\n3 amb.\n2 dorm.\n1 ba\u00f1o\nUbicado en Sarmiento y Montevideo, se encuentra este departamento en alquiler. Con un precio de ar$400. 000. El departamento cuenta con agua corriente, luz, gas natural, y termotanque el\u00e9ctrico. Cocina separada. Ba\u00f1o completo. Pisos porcellanato\nPublicado hace 5 d\u00edas\nContactar", "revised": false, "rejected": true, "data": {"precio": "$ 400.000", "expensas": "$ 40.000 Expensas", "direccion": "", "metros": "60 m\u00b2 tot.", "habitaciones": "3 amb.", "hace": "Publicado hace 5 d\u00edas"}}, "https://www.zonaprop.com.ar/propiedades/clasificado/alclappa-clasico-y-funcional-53546529.html": {"date": "04-05-2024\n", "content": "$ 600\nVenezuela 1100\nMonserrat, Capital Federal\n70 m\u00b2 tot.\n3 amb.\n2 dorm.\n1 ba\u00f1o\nDepartamento luminoso, c\u00f3modo, funcional, a 8 cuadras del obelisco, medios de transporte a mano. Calefacci\u00f3n y Aire acondicionado. Bajas expensas. Ideal\nPublicado hace 5 d\u00edas\nContactar", "revised": false, "rejected": true, "data": {"precio": "$ 600", "direccion": "Venezuela 1100", "metros": "70 m\u00b2 tot.", "habitaciones": "3 amb.", "hace": "Contactar"}}, "https://www.zonaprop.com.ar/propiedades/clasificado/alclapin-departamento-3-ambientes-amplio-y-luminoso-53573112.html": {"date": "06-05-2024\n", "index": 56, "content": "$ 650.000\nRivadavia 4011\nAlmagro, Capital Federal\n120 m\u00b2 tot.\n3 amb.\n2 dorm.\n1 ba\u00f1o\nDepartamento de 3 ambientes. Gran living. Balc\u00f3n con vista abierta. Cocina comedor. Ba\u00f1o y toilette. Muy bueno\nDestacado\nPublicado hace 3 d\u00edas\nContactar", "revised": false, "rejected": true, "data": {"precio": "$ 650.000", "expensas": "", "direccion": "Rivadavia 4011", "metros": "120 m\u00b2 tot.", "habitaciones": "3 amb.", "hace": "Contactar"}, "image": "https://imgar.zonapropcdn.com/avisos/1/00/53/57/31/12/360x266/1909374602.jpg?isFirstImage=true", "title": "Departamento de 3 ambientes, Almagro \u00b7 Departamento 3 Ambientes Amplio y Luminoso"}, "https://www.zonaprop.com.ar/propiedades/clasificado/alclapin-departamento-de-4-ambientes-en-san-nicolas-53574454.html": {"date": "06-05-2024\n", "index": 65, "content": "$ 600.000\n$ 170.000 Expensas\nDirecci\u00f3n no informada\nSan Nicol\u00e1s, Capital Federal\n140 m\u00b2 tot.\n3 amb.\n3 dorm.\n2 ba\u00f1os\nEste impecable departamento de 4 ambientes ofrece una combinaci\u00f3n perfecta de comodidad y estilo en una de las ubicaciones m\u00e1s estrategicas de la Ciudad Aut\u00f3noma de Buenos Aires. Caracter\u00edsticas principales: Amplio living comedor de generosas dimensiones, ideal para disfrutar de momentos inolvidables en familia o con amigos. Cocina completa con espacio para lavarropas. 3 habitaciones espaciosas que te brindan el confort que necesitas para descansar pl\u00e1cidamente. 2 ba\u00f1os completos, uno de ellos con jacuzzi para que puedas relajarte despu\u00e9s de un largo d\u00eda. Balc\u00f3n cubierto en el contrafrente, ideal como jard\u00edn de invierno, donde podr\u00e1s disfrutar de la tranquilidad y el verde sin salir de casa. Condiciones de alquiler: Contrato a dos a\u00f1os con actualizaciones trimestrales. Se requieren ingresos comprobables que tripliquen el monto del alquiler. Garant\u00eda propietaria o seguro de cauci\u00f3n. hay algunos muebles en inventario que quedan dentro del departamento. \u00a1Cont\u00e1ctanos hoy mismo para programar una visita!\nPublicado hace 3 d\u00edas\nContactar", "revised": false, "rejected": true, "data": {"precio": "$ 600.000", "expensas": "$ 170.000 Expensas", "direccion": "Direcci\u00f3n no informada", "metros": "140 m\u00b2 tot.", "habitaciones": "3 amb.", "hace": "Contactar"}, "image": "https://imgar.zonapropcdn.com/avisos/1/00/53/57/44/54/360x266/1909401776.jpg?isFirstImage=true", "title": "Departamento de 3 ambientes, San Nicol\u00e1s \u00b7 Departamento de 4 Ambientes en San Nicolas"}, "https://www.zonaprop.com.ar/propiedades/clasificado/alclapin-almagro:-alquiler-por-24-meses-3-ambientes-con-dep.-y-53558777.html": {"date": "06-05-2024\n", "index": 123, "content": "$ 720.000\n$ 120.000 Expensas\nPanama al 900\nAlmagro, Capital Federal\n120 m\u00b2 tot.\n3 amb.\n2 dorm.\n1 ba\u00f1o\n1 coch.\nAlmagro: Nuevo ingreso: semi piso en alquiler de 3 ambientes mas dependencias de servicio ( originalmente 4 Ambientes con dependencias) Posee Hall de entrada, Amplio Estar Comedor en L con salida amplio balcon con Proteccion para chicos. 2 comodos Dormitorios el principal con salida a balcon y el 2\u00b0 con ventana al lateral. Generosa cocina con entrada de servicio desde el palier mas comedor diario y dependencias con ba\u00f1o de servicioToilette de recepcion y ba\u00f1o completo al igual que la cocina refaccionados hace pocos a\u00f1osopcion alquiler todo amoblado Y equipado como se ve en FotosValor publicado solo alquiler, mas gastos, Incluye espacio Guardacoche en Planta BajaSe alquila por 24 mesesopcion alquiler temporario, consultar plazos Y valores\nDestacado\nPublicado hace 6 d\u00edas\nContactar", "revised": false, "rejected": true, "data": {"precio": "$ 720.000", "expensas": "$ 120.000 Expensas", "direccion": "Panama al 900", "metros": "120 m\u00b2 tot.", "habitaciones": "3 amb.", "hace": "Contactar"}, "image": "https://imgar.zonapropcdn.com/avisos/1/00/53/55/87/77/360x266/1909055621.jpg?isFirstImage=true", "title": "Departamento \u00b7 110m\u00b2 \u00b7 3 Ambientes \u00b7 1 Cochera \u00b7 Almagro: Alquiler por 24 Meses, 3 Ambientes con Dep. y Espacio Guarda Coche"}, "https://www.zonaprop.com.ar/propiedades/clasificado/alclocin-departamento-de-3-ambientes-con-dependencia-en-primer-53579490.html": {"date": "06-05-2024\n", "index": 42, "content": "24\n$ 380.000\n$ 78.600 Expensas\nHipolito Yrigoyen y Rincon\nCongreso, Capital Federal\n105 m\u00b2 tot.\n3 amb.\n2 dorm.\n2 ba\u00f1os\nAmplio departamento de tres ambientes con dependencia. Al ingreso c\u00f3moda recepci\u00f3n de 4, 5 x 3. 4 con pisos plastificados. En paralelo otro ambiente de 3. 4 x 2. 4 que podr\u00eda destinarse a comedor. Sala de grandes dimensiones de 8, 5 x 3, 7. Ideal para clases o exposiciones. Posibilidad de subidividir para hacer otra habitaci\u00f3n. Sector de cocina separada. Ba\u00f1o con ducha y espejo de cuerpo completo. Hacia el fondo del pasillo de distribuci\u00f3n un toilette. En segunda planta, dependencia alfombrada. Edificio se\u00f1orial, ubicado a tres cuadras de la estaci\u00f3n de subte A, a una cuadra de Av. Rivadavia en pleno barrio de Congreso. \u00c1rea con gran desarrollo comercial y variedad de l\u00edneas de transporte hacia toda la ciudad. Apto para uso profesional. No se admiten mascotas. Requisitos: garant\u00eda de Caba o seguro de cauci\u00f3n y justificaci\u00f3n de ingresos. Contrato a 2 a\u00f1os con actualizaci\u00f3n trimestral por ipc (\u00cdndice de precios al consumidor)\nPublicado hace 2 d\u00edas\nContactar", "revised": false, "rejected": true, "data": {"precio": "$ 380.000", "expensas": "$ 78.600 Expensas", "direccion": "Hipolito Yrigoyen y Rincon", "metros": "105 m\u00b2 tot.", "habitaciones": "3 amb.", "hace": "Contactar"}, "image": "https://imgar.zonapropcdn.com/avisos/1/00/53/57/94/90/360x266/1909515513.jpg?isFirstImage=true", "title": "Oficina comercial \u00b7 105m\u00b2 \u00b7 3 Ambientes \u00b7 Departamento de 3 Ambientes con Dependencia en Primer Piso - Apto Profesional"}, "https://www.zonaprop.com.ar/propiedades/clasificado/alclapin-departamento-de-3-ambientes-con-dependencia-en-primer-53579487.html": {"date": "06-05-2024\n", "index": 41, "content": "24\n$ 380.000\n$ 78.600 Expensas\nHipolito Yrigoyen y Rincon\nCongreso, Capital Federal\n105 m\u00b2 tot.\n3 amb.\n2 dorm.\n2 ba\u00f1os\nAmplio departamento de tres ambientes con dependencia. Al ingreso c\u00f3moda recepci\u00f3n de 4, 5 x 3. 4 con pisos plastificados. En paralelo otro ambiente de 3. 4 x 2. 4 que podr\u00eda destinarse a comedor. Sala de grandes dimensiones de 8, 5 x 3, 7. Ideal para clases o exposiciones. Posibilidad de subidividir para hacer otra habitaci\u00f3n. Sector de cocina separada. Ba\u00f1o con ducha y espejo de cuerpo completo. Hacia el fondo del pasillo de distribuci\u00f3n un toilette. En segunda planta, dependencia alfombrada. Edificio se\u00f1orial, ubicado a tres cuadras de la estaci\u00f3n de subte A, a una cuadra de Av. Rivadavia en pleno barrio de Congreso. \u00c1rea con gran desarrollo comercial y variedad de l\u00edneas de transporte hacia toda la ciudad. Apto para uso profesional. No se admiten mascotas. Requisitos: garant\u00eda de Caba o seguro de cauci\u00f3n y justificaci\u00f3n de ingresos. Contrato a 2 a\u00f1os con actualizaci\u00f3n trimestral por ipc (\u00cdndice de precios al consumidor)\nPublicado hace 2 d\u00edas\nContactar", "revised": false, "rejected": true, "data": {"precio": "$ 380.000", "expensas": "$ 78.600 Expensas", "direccion": "Hipolito Yrigoyen y Rincon", "metros": "105 m\u00b2 tot.", "habitaciones": "3 amb.", "hace": "Contactar"}, "image": "https://imgar.zonapropcdn.com/avisos/1/00/53/57/94/87/360x266/1909515483.jpg?isFirstImage=true", "title": "Departamento \u00b7 105m\u00b2 \u00b7 3 Ambientes \u00b7 Departamento de 3 Ambientes con Dependencia en Primer Piso - Apto Profesional"}, "https://www.zonaprop.com.ar/propiedades/clasificado/alclappa-impecable-departamento-con-vista-panoramica-en-torre-53579574.html": {"date": "06-05-2024\n", "index": 50, "content": "$ 700.000\n$ 150.000 Expensas\nGallo 955\nBarrio Norte, Capital Federal\n68 m\u00b2 tot.\n3 amb.\n2 dorm.\n2 ba\u00f1os\nEn Torre Premium con Vigilancia las 24hs, 2 Piscinas, Gimnasio, Parrillas, Jardines, juegos infantiles, sum, sauna Calefaci\u00f2n y agua caliente por caldera individual. Requisitos: Ingresos acordes demostrables-Gtias personales o seguro de cauci\u00f2n. Actualizaci\u00f2n trimestral por icl. M\u00e0ximo 2 adultos y 1 menor.\nPublicado hace 2 d\u00edas\nContactar", "revised": false, "rejected": true, "data": {"precio": "$ 700.000", "expensas": "$ 150.000 Expensas", "direccion": "Gallo 955", "metros": "68 m\u00b2 tot.", "habitaciones": "3 amb.", "hace": "Contactar"}, "image": "https://imgar.zonapropcdn.com/avisos/1/00/53/57/95/74/360x266/1909519502.jpg?isFirstImage=true", "title": "Departamento de 3 ambientes, Barrio Norte \u00b7 Impecable Departamento con Vista Panor\u00e0mica en Torre con Amenities"}, "https://www.zonaprop.com.ar/propiedades/clasificado/alclappa-alquiler-de-hermoso-y-gran-dto.-de-4am.-c-balcon-53579421.html": {"date": "06-05-2024\n", "index": 46, "content": "$ 1.000.000\n$ 100.000 Expensas\nAv. Independencia 3700\nBoedo, Capital Federal\n85 m\u00b2 tot.\n4 amb.\n3 dorm.\n1 ba\u00f1o\n1 coch.\nExcelente Dto. De 4 Amb. Con Balcon al frente. Orientacion Norte s/Avenida, con Puerta de Ingreso blindada, ubicado sobre Av. Independencia, cerca de Av. Boedo, muy luminoso y con muy buena ventilacion cruzada, piso flotante en todos los ambientes y ceramico en la cocina y en los dos ba? os. Cocina Amplia y lavadero. El alquiler incluye la cochera fija y baulera. Contrato por dos a\u00f1os, Actualizaci\u00f3n cuatrimestral, seg\u00fan ipc. Condiciones: Garant\u00eda propietaria de Capital. Recibo de Sueldo. Un mes de deposito y un mes de alquiler. No se admiten mascotas.\nPublicado hace 2 d\u00edas\nContactar", "revised": false, "rejected": true, "data": {"precio": "$ 1.000.000", "expensas": "$ 100.000 Expensas", "direccion": "Av. Independencia 3700", "metros": "85 m\u00b2 tot.", "habitaciones": "4 amb.", "hace": "Contactar"}, "image": "https://imgar.zonapropcdn.com/avisos/1/00/53/57/94/21/360x266/1909518488.jpg?isFirstImage=true", "title": "FOTO 1. ENTRADA AL DTO. \u00b7 Alquiler de Hermoso y Gran Dto. de 4am. C/balcon, Cochera y Baulera"}, "https://www.zonaprop.com.ar/propiedades/clasificado/alclappa-peron-al-2500-4-1-2-ambientes-53580897.html": {"date": "06-05-2024\n", "index": 45, "content": "$ 750.000\nDirecci\u00f3n no informada\nOnce, Capital Federal\n142 m\u00b2 tot.\n5 amb.\n3 dorm.\n1 ba\u00f1o\nDepartamento de 142m2 sobre Peron al 2500 reci\u00e9n pintado en un segundo piso. Cuenta con 4 ambientes y medio con cocina/comedor gigante. Son 3 dormitorios, 1 habitaci\u00f3n de dependencia que podria funcionar como oficina, living, cocina comedor con lavadero, 1 ba\u00f1o principal y 1 toilette. Dos de los dormitorios cuenta con balcones, muy luminoso. Cercan\u00eda con subtes l\u00ednea B, H y A. Las expensas incluye servicio de aysa. Contrato de 2 a\u00f1os, con aumento cada 3 meses por inflaci\u00f3n (\u00edndice ipc). Solicito 2 meses de deposito y seguro de cauci\u00f3n finaer. Recibo de sueldo con ingreso neto superando 1. 25 mill\u00f3n.\nPublicado hace 2 d\u00edas\nContactar", "revised": false, "rejected": true, "data": {"precio": "$ 750.000", "expensas": "", "direccion": "Direcci\u00f3n no informada", "metros": "142 m\u00b2 tot.", "habitaciones": "5 amb.", "hace": "Contactar"}, "image": "https://imgar.zonapropcdn.com/avisos/1/00/53/58/08/97/360x266/1909545240.jpg?isFirstImage=true", "title": "Departamento de 5 ambientes, Once \u00b7 Peron Al 2500, 4 1/2 Ambientes"}, "https://www.zonaprop.com.ar/propiedades/clasificado/alclapin-paraguay-y-ayacucho-muy-luminoso-al-frente-2-dorm.-53575135.html": {"date": "06-05-2024\n", "index": 61, "content": "15\n$ 600.000\n$ 70.000 Expensas\nParaguay 2000\nBarrio Norte, Capital Federal\n81 m\u00b2 tot.\n4 amb.\n3 dorm.\n1 ba\u00f1o\nDepartamento con Living Comedor, muy Luminoso, 2 dormitorios, al frente escritorio o 3er dormitorio al, 1 ba\u00f1o completo, cocina, dependencia de servicio, ba\u00f1o de servicio, impecable, reci\u00e9n pintado. Lavadero. todos los medios de locomocionContrato por 24 meses, Incremento trimestral Acumulativo \u00cdndice ipc. aysa $ 6900agip 6000 / superficies y valores expresados son aproximados, segun informacion suministrada por el propietario. /\nPublicado hace 3 d\u00edas\nContactar", "revised": false, "rejected": true, "data": {"precio": "$ 600.000", "expensas": "$ 70.000 Expensas", "direccion": "Paraguay 2000", "metros": "81 m\u00b2 tot.", "habitaciones": "4 amb.", "hace": "Contactar"}, "image": "https://imgar.zonapropcdn.com/avisos/1/00/53/57/51/35/360x266/1909416004.jpg?isFirstImage=true", "title": "Departamento \u00b7 81m\u00b2 \u00b7 4 Ambientes \u00b7 Paraguay y Ayacucho, Muy Luminoso, Al Frente, 2 Dorm. con Dependencia, Impecable."}, "https://www.zonaprop.com.ar/propiedades/clasificado/alclocin-oficina-en-alquiler-en-almagro-53571713.html": {"date": "06-05-2024\n", "index": 68, "content": "$ 600.000\n$ 91.200 Expensas\nAv. Hip\u00f3lito Yrigoyen 4000 PB\nAlmagro, Capital Federal\n90 m\u00b2 tot.\n4 amb.\n3 dorm.\n2 ba\u00f1os\nDepartamento de 4 ambientes con dependencia en pb al frente exclusivo para uso profesional. 2 ventanas a la calle. Living comedor, 3 dormitorios con placares, ba\u00f1o completo, cocina equipada, lavadero, dependencia de servicio o comedor diario, toilette de servicio, patio, baulera. Puerta blindada. Pisos de parquet. Expensas con agua incluida. Ubicado en edificio de esquina a metros de Av. Rivadavia, cercano al subte l\u00ednea A. Requisitos: - Contrato por 2 a\u00f1os. - Ajuste trimestral seg\u00fan \u00edndice de precios al consumidor publicado por el indec. - Seguro de cauci\u00f3n o garant\u00eda propietaria de caba. - Ingresos demostrables. - 1 mes de dep\u00f3sito. - Comisi\u00f3n inmobiliaria 5% del total del contrato + iva\nPublicado hace 3 d\u00edas\nContactar", "revised": false, "rejected": true, "data": {"precio": "$ 600.000", "expensas": "$ 91.200 Expensas", "direccion": "Av. Hip\u00f3lito Yrigoyen 4000 PB", "metros": "90 m\u00b2 tot.", "habitaciones": "4 amb.", "hace": "Contactar"}, "image": "https://imgar.zonapropcdn.com/avisos/1/00/53/57/17/13/360x266/1909342361.jpg?isFirstImage=true", "title": "Oficina comercial \u00b7 78m\u00b2 \u00b7 4 Ambientes \u00b7 Oficina en Alquiler en Almagro"}, "https://www.zonaprop.com.ar/propiedades/clasificado/alclapin-alq-3-amb-frente-al-parque-las-heras-apto-prof-53573277.html": {"date": "06-05-2024\n", "index": 69, "content": "$ 700.000\n$ 135.000 Expensas\nDirecci\u00f3n no informada\nBarrio Norte, Capital Federal\n79 m\u00b2 tot.\n4 amb.\n3 dorm.\n1 ba\u00f1o\n1 coch.\nExcelente ubicacion, edificio ubicado frente al parque las heras, departamento de 4 ambientes con vista al parque las heras, balcon, muy luminoso, living comedor, 3 dormitorios ( uno es la dependencia, adaptado como 3 dormitorio), cocina office, ba\u00f1o completo Y ba\u00f1o de servicio, cochera fija en planta baja, apto profesional. El valor de las expensas esta sujeto A variacion Y/O ajuste. Las medidas son aproximadas en caracter orientativo.\nPublicado hace 3 d\u00edas\nContactar", "revised": false, "rejected": true, "data": {"precio": "$ 700.000", "expensas": "$ 135.000 Expensas", "direccion": "Direcci\u00f3n no informada", "metros": "79 m\u00b2 tot.", "habitaciones": "4 amb.", "hace": "Contactar"}, "image": "https://imgar.zonapropcdn.com/avisos/1/00/53/57/32/77/360x266/1909378108.jpg?isFirstImage=true", "title": "Departamento de 4 ambientes, Barrio Norte \u00b7 Alq 3 Amb, Frente Al Parque Las Heras, Apto Prof"}, "https://www.zonaprop.com.ar/propiedades/clasificado/alclapin-uriburu-y-av-las-heras-53575186.html": {"date": "06-05-2024\n", "index": 70, "content": "$ 720.000\n$ 119.000 Expensas\nUriburu y Av. Las Heras, 6 Piso al Frente, muy Luminoso. 70 m2. Muy Buen Estado.\nBarrio Norte, Capital Federal\n70 m\u00b2 tot.\n4 amb.\n3 dorm.\n1 ba\u00f1o\nTorre en esquina con vigilancia 24 hs. A mts. Del shopping Mall Recoleta, Universidad Barcelo. Rodeado de museos y parques. Hall, Living comedor(5, 50x3, 10) al frente balc\u00f3n corrido al frente. 3 Dormitorios (3, 05 x 3, 05 - 3, 20 x 2, 70 - 3, 25 x 2, 00 o escritorio). 1 Ba\u00f1o completo y Toillete. Cocina y Lavadero independiente. Muy Luminoso. Muy buen estado. Pisos de parquet. martin llauromat. 121 cucicba - Mat. 5468 C. S. I. La presente oferta de venta est\u00e1 condicionada a la confecci\u00f3n del coti por parte del propietario. Las medidas y expensas son aproximadas y orientativas. Las medidas exactas surgir\u00edan del titulo de propiedad.\nPublicado hace 3 d\u00edas\nContactar", "revised": false, "rejected": true, "data": {"precio": "$ 720.000", "expensas": "$ 119.000 Expensas", "direccion": "Uriburu y Av. Las Heras, 6 Piso al Frente, muy Luminoso. 70 m2. Muy Buen Estado.", "metros": "70 m\u00b2 tot.", "habitaciones": "4 amb.", "hace": "Contactar"}, "image": "https://imgar.zonapropcdn.com/avisos/1/00/53/57/51/86/360x266/1909417193.jpg?isFirstImage=true", "title": "Departamento \u00b7 64m\u00b2 \u00b7 4 Ambientes \u00b7 Uriburu y Av Las Heras"}, "https://www.zonaprop.com.ar/propiedades/clasificado/alclapin-french-y-larrea-frente-125-m-sup2--tres-dorm.-dep.-53569904.html": {"date": "06-05-2024\n", "index": 76, "content": "$ 1.200.000\n$ 110.000 Expensas\nFrench 2400\nBarrio Norte, Capital Federal\n125 m\u00b2 tot.\n4 amb.\n3 dorm.\n2 ba\u00f1os\n1 coch.\nExcelente propiedad de 125 m2 - Palier privado, hall, livingcomedor en L con salida a balc\u00f3n corrido, tres dormitorios (uno en suite) dos ba\u00f1os, toilette, cocina, office, lavadero, dependencia de servicio, tres A/A fr\u00edo/calor, caldera propia para calefacci\u00f3n y agua caliente, guardacoche fijo. Expensas $ 110. 000. - informes Ver datos\nDestacado\nPublicado hace 4 d\u00edas\nContactar", "revised": false, "rejected": true, "data": {"precio": "$ 1.200.000", "expensas": "$ 110.000 Expensas", "direccion": "French 2400", "metros": "125 m\u00b2 tot.", "habitaciones": "4 amb.", "hace": "Contactar"}, "image": "https://imgar.zonapropcdn.com/avisos/1/00/53/56/99/04/360x266/1909301598.jpg?isFirstImage=true", "title": "Departamento de 4 ambientes, Barrio Norte \u00b7 French y Larrea - Frente 125 m\u00b2 - Tres Dorm. Dep. Serv. Guardacoche Fijo"}, "https://www.zonaprop.com.ar/propiedades/clasificado/alclapin-excelente-depto-125-m-sup2--al-frente-tres-dorm.-53567497.html": {"date": "06-05-2024\n", "index": 82, "content": "21\n$ 1.200.000\n$ 110.000 Expensas\nFrench 2400\nBarrio Norte, Capital Federal\n125 m\u00b2 tot.\n4 amb.\n3 dorm.\n2 ba\u00f1os\n1 coch.\nSemipiso al frente de 125 m2, palier privado, hall, recepci\u00f3n en L a balc\u00f3n corrido, tres dormitorios (uno en suite), ventanal doble vidrio, dos ba\u00f1os, toilette, cocina office, lavadero independiente, dependencia de servicio, muy luminoso, profusi\u00f3n de placards, calefacci\u00f3n por losa radiante, caldera individual, tres aparatos de A/A fr\u00edo/calor, guardacoches fijo, excelente estado. Expensas $ 110. 000. - (\u00daltimas) informes cel. Ver datos\nDestacado\nPublicado hace 4 d\u00edas\nContactar", "revised": false, "rejected": true, "data": {"precio": "$ 1.200.000", "expensas": "$ 110.000 Expensas", "direccion": "French 2400", "metros": "125 m\u00b2 tot.", "habitaciones": "4 amb.", "hace": "Contactar"}, "image": "https://imgar.zonapropcdn.com/avisos/1/00/53/56/74/97/360x266/1909248950.jpg?isFirstImage=true", "title": "Departamento de 4 ambientes, Barrio Norte \u00b7 Excelente Depto, 125 m\u00b2 Al Frente, Tres Dorm., Dep. Guardacoches Fijo"}, "https://www.zonaprop.com.ar/propiedades/clasificado/alclapin-departamento-en-alquiler-en-almagro-solo-uso-53566156.html": {"date": "06-05-2024\n", "index": 83, "content": "$ 600.000\n$ 91.200 Expensas\nAv. Hip\u00f3lito Yrigoyen 4000 PB\nAlmagro, Capital Federal\n90 m\u00b2 tot.\n4 amb.\n3 dorm.\n2 ba\u00f1os\nDepartamento de 4 ambientes con dependencia en pb al frente exclusivo para uso profesional. 2 ventanas a la calle. Living comedor, 3 dormitorios con placares, ba\u00f1o completo, cocina equipada, lavadero, dependencia de servicio o comedor diario, toilette de servicio, patio, baulera. Puerta blindada. Pisos de parquet. Expensas con agua incluida. Ubicado en edificio de esquina a metros de Av. Rivadavia, cercano al subte l\u00ednea A. Requisitos: - Contrato por 2 a\u00f1os. - Ajuste trimestral seg\u00fan \u00edndice de precios al consumidor publicado por el indec. - Seguro de cauci\u00f3n o garant\u00eda propietaria de caba. - Ingresos demostrables. - 1 mes de dep\u00f3sito. - Comisi\u00f3n inmobiliaria 5% del total del contrato + iva\nDestacado\nPublicado hace 4 d\u00edas\nContactar", "revised": false, "rejected": true, "data": {"precio": "$ 600.000", "expensas": "$ 91.200 Expensas", "direccion": "Av. Hip\u00f3lito Yrigoyen 4000 PB", "metros": "90 m\u00b2 tot.", "habitaciones": "4 amb.", "hace": "Contactar"}, "image": "https://imgar.zonapropcdn.com/avisos/1/00/53/56/61/56/360x266/1909215247.jpg?isFirstImage=true", "title": "Departamento \u00b7 78m\u00b2 \u00b7 4 Ambientes \u00b7 Departamento en Alquiler en Almagro S\u00f3lo Uso Profesional"}, "https://www.zonaprop.com.ar/propiedades/clasificado/alclocin-piso-de-6-oficinas-luminosas-con-recepcion-y-2-banos-53564778.html": {"date": "06-05-2024\n", "index": 98, "content": "$ 600.000\n$ 296.000 Expensas\nAvenida Presidente Roque S\u00e1enz Pe\u00f1a 852\nSan Nicol\u00e1s, Capital Federal\n155 m\u00b2 tot.\n6 amb.\n6 dorm.\n2 ba\u00f1os\nSemipiso al frente en octavo piso, compuesto por: recepci\u00f3n de 4 x 3. 10 // 4 oficinas al frente de 4. 10 x 3. 30 / 4. 90 x 4. 10 / 4. 10 x 3. 30 / 4. 60 x 4. 10 // 2 oficinas al pulm\u00f3n muy luminosas de 5 x 3. 70. Ba\u00f1os damas y caballeros y peque\u00f1a cocina. Superficies: 154. 97 m2 cubiertos y totales. El edificio es apto profesional y cuenta con vigilancia de lunes a viernes de 7: 30 a 19: 30 Hs. Est\u00e1 conformado por 9 pisos, 2 unidades por piso y 2 ascensores. Sus expensas con vencimiento abril-2024 son de $ 296. 000. - Visitas y mas informaci\u00f3n comunicarse con \"bloise Inmobiliaria desde 1945\" Tel\u00e9fonos 4921. 9984 y 4922. 4683 WhatsApp Ver datos\nPublicado hace 4 d\u00edas\nContactar", "revised": false, "rejected": true, "data": {"precio": "$ 600.000", "expensas": "$ 296.000 Expensas", "direccion": "Avenida Presidente Roque S\u00e1enz Pe\u00f1a 852", "metros": "155 m\u00b2 tot.", "habitaciones": "6 amb.", "hace": "Contactar"}, "image": "https://imgar.zonapropcdn.com/avisos/1/00/53/56/47/78/360x266/1909188912.jpg?isFirstImage=true", "title": "Oficina comercial de 6 ambientes, San Nicol\u00e1s \u00b7 Piso de 6 Oficinas Luminosas con Recepci\u00f3n y 2 Ba\u00f1os"}, "https://www.zonaprop.com.ar/propiedades/clasificado/alclapin-b.-norte-3-amb-c-dep-y-cochera-53566200.html": {"date": "06-05-2024\n", "index": 95, "content": "$ 650.000\n$ 120.014 Expensas\nGallo al 1500\nBarrio Norte, Capital Federal\n78 m\u00b2 tot.\n4 amb.\n2 dorm.\n1 ba\u00f1o\n1 coch.\nC\u00f3modo semipiso C/espacio guardacoche m\u00f3vil. Excelente ubicaci\u00f3n A pasos de av. Santa fe Y subte D. Cfte C/balc\u00f3n A pulm\u00f3n de manzana. Todo luz. Muy buen estado. Lc apaisado C/aa F/C. 2 dormitorios C/placard. Amplia cocina C/comedor diario Y lavadero incorporado. Dependencia O escritorio C/ba\u00f1o de servicio. Entrada principal Y de servicio. Puerta blindada. No es apto prof. sup cub 75m2 + 5m2 balc\u00f3n. expensas vto abril $ 120. 014 aysa vto mayo $ 20. 272 tasa abl $ 4063. *para informaci\u00f3n O coordinar visita, contactarse al +54 9 11 Ver datos*condiciones** - Contrato de 24 meses - Ajuste trimestral por icl (\u00edndice para contratos de locaci\u00f3n bcra) - 1 mes adelantado - 1 mes de dep\u00f3sito en garant\u00eda. *requisitos* -Ingresos comprobables y acordes a los gastos que se asumen. -Garant\u00eda: inmueble de caba \u00f3 pba libre de grav\u00e1menes, o seguro de cauci\u00f3n que cubra todas las obligaciones del inquilino. Ley 5115 Art. 1: Accesible Ley 5859 Art. 4 (inciso 8 del art\u00edculo 10 de la Ley 2340, texto consolidado seg\u00fan Ley Nro. 5666): \"Para los casos de alquiler de vivienda, el monto m\u00e1ximo de comisi\u00f3n que se le puede requerir a los propietarios ser\u00e1 el equivalente al cuatro con quince cent\u00e9simos por ciento (4, 15%) del valor total del respectivo contrato. Se encuentra prohibido obrar a los inquilinos que sean personas f\u00edsicas comisiones inmobiliarias y gastos de gestor\u00eda de informes. \" Ley 2340 Art. 10: Matr\u00edcula cucicba 929 Nota: Las medidas (tanto totales como parciales), superficies, m2 y proporciones indicadas en el presente son aproximadas. El valor de expensas y tasas, var\u00eda mensualmente.\nPublicado hace 4 d\u00edas\nContactar", "revised": false, "rejected": true, "data": {"precio": "$ 650.000", "expensas": "$ 120.014 Expensas", "direccion": "Gallo al 1500", "metros": "78 m\u00b2 tot.", "habitaciones": "4 amb.", "hace": "Contactar"}, "image": "https://imgar.zonapropcdn.com/avisos/1/00/53/56/62/00/360x266/1909216137.jpg?isFirstImage=true", "title": "Departamento \u00b7 75m\u00b2 \u00b7 4 Ambientes \u00b7 1 Cochera \u00b7 B. Norte 3 Amb C/dep y Cochera"}, "https://www.zonaprop.com.ar/propiedades/clasificado/alclcain-departamento-en-alquiler-en-palermo-de-7-ambientes-53569565.html": {"date": "06-05-2024\n", "index": 97, "content": "$ 300.000\nCallao al 2300\nMonserrat, Capital Federal\n400 m\u00b2 tot.\n4 amb.\n3 dorm.\n3 ba\u00f1os\n3 coch.\nLos invitamos a preguntar y a despejar todas las dudas que pudieran surgir respecto al uso de tokko. Pueden depositar sus preguntas en la pesta\u00f1a preguntasestas propiedades son ficticias, no contactar!\nPublicado hace 4 d\u00edas\nContactar", "revised": false, "rejected": true, "data": {"precio": "$ 300.000", "expensas": "", "direccion": "Callao al 2300", "metros": "400 m\u00b2 tot.", "habitaciones": "4 amb.", "hace": "Contactar"}, "image": "https://imgar.zonapropcdn.com/avisos/1/00/53/56/95/65/360x266/1909290579.jpg?isFirstImage=true", "title": "Casa \u00b7 400m\u00b2 \u00b7 4 Ambientes \u00b7 3 Cocheras \u00b7 Departamento en Alquiler, en Palermo de 7 Ambientes"}, "https://www.zonaprop.com.ar/propiedades/clasificado/alclocin-oportunidad-3-despachos-1-area-de-trabajo-bano-53570522.html": {"date": "06-05-2024\n", "index": 90, "content": "$ 360.000\n$ 120.000 Expensas\nDirecci\u00f3n no informada\nMonserrat, Capital Federal\n80 m\u00b2 tot.\n4 amb.\n4 dorm.\n1 ba\u00f1o\nG. S brokes. Ofrece oficina en alquiler muy bien conectada. Comercial. 3 despachos, un area de trabajo, ba\u00f1o, cocina. Edificio cuenta con vigilancia Y recepcion 24 hs. Tambien con un area de sum con mesas, gimnacio, piscina, La ubicacion subte, todos los medios de transporte.\nPublicado hace 3 d\u00edas\nContactar", "revised": false, "rejected": true, "data": {"precio": "$ 360.000", "expensas": "$ 120.000 Expensas", "direccion": "Direcci\u00f3n no informada", "metros": "80 m\u00b2 tot.", "habitaciones": "4 amb.", "hace": "Contactar"}, "image": "https://imgar.zonapropcdn.com/avisos/1/00/53/57/05/22/360x266/1909315432.jpg?isFirstImage=true", "title": "Oficina comercial de 4 ambientes, Monserrat \u00b7 Oportunidad 3 Despachos, 1 Area de Trabajo, Ba\u00f1o, Cocina. Comercial."}, "https://www.zonaprop.com.ar/propiedades/clasificado/alclphpa-ph-sin-expensas-1er-piso-con-gran-terraza.-4-53565890.html": {"date": "06-05-2024\n", "index": 101, "content": "9\n$ 750.000\nPasco 800\nSan Cristobal, Capital Federal\n200 m\u00b2 tot.\n4 amb.\n3 dorm.\n1 ba\u00f1o\nPh sin expensas, en un primer piso por escalera. 4 ambientes en la planta del primer piso. Gran living comedor (divisible). Balc\u00f3n corrido. Orientacion Este. Ba\u00f1o completo y ventilado + Toilette. Lavadero en entrepiso. Amplia terraza 100 mts2 con vista abierta. Requisitos y condiciones: Garant\u00eda propietaria. Ingresos comprobables. 2 a\u00f1os de contrato. Aumentos cuatrimestrales a convenir con el locatario y en la firma del contrato hay que abonar 1 mes de alquiler y otro de dep\u00f3sito.\nPublicado hace 4 d\u00edas\nContactar", "revised": true, "rejected": false, "data": {"precio": "$ 750.000", "expensas": "", "direccion": "Pasco 800", "metros": "200 m\u00b2 tot.", "habitaciones": "4 amb.", "hace": "Contactar"}, "image": "https://imgar.zonapropcdn.com/avisos/1/00/53/56/58/90/360x266/1909229948.jpg?isFirstImage=true", "title": "PH de 4 ambientes, San Cristobal \u00b7 PH Sin Expensas, 1er Piso con Gran Terraza. 4 Ambientes.", "comment": "C\u00f3mo los viejis de emi"}, "https://www.zonaprop.com.ar/propiedades/clasificado/alclocin-oficina-en-balvanera-300-m-53563623.html": {"date": "06-05-2024\n", "index": 107, "content": "$ 400.000\nGeneral Urquiza al 100\nBalvanera, Capital Federal\n350 m\u00b2 tot.\n8 amb.\n8 dorm.\n1 ba\u00f1o\nOficina comercial en primer piso por escalera en excelente ubicacionLa oficina cuenta con varias aulas independientes y ba\u00f1osIdeal Instituto. **Corredor Inmobiliario Responsable Adrian Ridelnik cucicba Mat 197. *Se deja constancia que las medidas y superficies indicados son aproximados y al s\u00f3lo efecto orientativo. Las medidas reales surgir\u00e1n del t\u00edtulo de propiedad respectivo. Las medidas parciales y/o de los ambientes y el valor consignado de expensas mensuales, servicios y abl est\u00e1 sujeto a verificaci\u00f3n y/o ajuste. Art. 4 de la Ley 5. 859 de C. A. B. A \"Para los casos de alquiler de vivienda \u00fanica, el monto m\u00e1ximo de comisi\u00f3n que se le puede requerir a los propietarios ser\u00e1 el equivalente al cuatro con quince cent\u00e9simos por ciento (4, 15%) del valor total del respectivo contrato. Se encuentra prohibido cobrar a los inquilinos que sean personas f\u00edsicas comisiones inmobiliarias cuando el destino sea vivienda \u00fanica y permanente \". -\nPublicado hace 4 d\u00edas\nContactar", "revised": false, "rejected": true, "data": {"precio": "$ 400.000", "expensas": "", "direccion": "General Urquiza al 100", "metros": "350 m\u00b2 tot.", "habitaciones": "8 amb.", "hace": "Contactar"}, "image": "https://imgar.zonapropcdn.com/avisos/1/00/53/56/36/23/360x266/1909160421.jpg?isFirstImage=true", "title": "Oficina comercial \u00b7 350m\u00b2 \u00b7 8 Ambientes \u00b7 Oficina en Balvanera 300 m"}, "https://www.zonaprop.com.ar/propiedades/clasificado/alclapin-alquiler-4-amb-c-dependencia-y-balcon-53554677.html": {"date": "06-05-2024\n", "index": 118, "content": "$ 650.000\n$ 160.000 Expensas\nSarmiento 2090\nBalvanera, Capital Federal\n115 m\u00b2 tot.\n4 amb.\n3 dorm.\n2 ba\u00f1os\nSarmiento Y junin amplio 4 amb en alquiler - piso alto con balc\u00f3n al frente Ubicado sobre la calle Sarmiento entre Junin y Ayacucho, a una cuadra de Av. Corrientes, a tres de Av. Callao, a cinco de Av. Santa Fe y a tres de Av. Rivadavia. Cercan\u00eda con el Subte l\u00ednea D, l\u00ednea B y l\u00ednea A. Inmejorable ubicaci\u00f3n por su f\u00e1cil acceso. Departamento 4 amb con dependencia, cuenta con: -Living comedor amplio con salida al balc\u00f3n-Cocina independiente con espacio para lavarropas -Dependencia de servicio (cuenta con un ba\u00f1o chico) -Dos habitaciones con placard -Ba\u00f1o completo-Toilette de recepci\u00f3n-Dormitorio principal con salida al balc\u00f3n (cuenta con un gran placard) -Balc\u00f3n corrido vista al frente disponible\nSuper destacado\nPublicado hace 6 d\u00edas\nContactar", "revised": false, "rejected": true, "data": {"precio": "$ 650.000", "expensas": "$ 160.000 Expensas", "direccion": "Sarmiento 2090", "metros": "115 m\u00b2 tot.", "habitaciones": "4 amb.", "hace": "Contactar"}, "image": "https://imgar.zonapropcdn.com/avisos/1/00/53/55/46/77/360x266/1908965089.jpg?isFirstImage=true", "title": "Departamento \u00b7 100m\u00b2 \u00b7 4 Ambientes \u00b7 Alquiler 4 Amb C/dependencia y Balc\u00f3n"}, "https://www.zonaprop.com.ar/propiedades/clasificado/alclapin-alquiler-4-amb-c-dependencia-y-balcon-53552300.html": {"date": "06-05-2024\n", "index": 125, "content": "$ 650.000\n$ 160.000 Expensas\nSarmiento 2090\nOnce, Capital Federal\n115 m\u00b2 tot.\n4 amb.\n3 dorm.\n2 ba\u00f1os\nSarmiento Y junin amplio 4 amb en alquiler - piso alto con balc\u00f3n al frente Ubicado sobre la calle Sarmiento entre Junin y Ayacucho, a una cuadra de Av. Corrientes, a tres de Av. Callao, a cinco de Av. Santa Fe y a tres de Av. Rivadavia. Cercan\u00eda con el Subte l\u00ednea D, l\u00ednea B y l\u00ednea A. Inmejorable ubicaci\u00f3n por su f\u00e1cil acceso. Departamento 4 amb con dependencia, cuenta con: -Living comedor amplio con salida al balc\u00f3n-Cocina independiente con espacio para lavarropas -Dependencia de servicio (cuenta con un ba\u00f1o chico) -Dos habitaciones con placard -Ba\u00f1o completo-Toilette de recepci\u00f3n-Dormitorio principal con salida al balc\u00f3n (cuenta con un gran placard) -Balc\u00f3n corrido vista al frente disponible\nPublicado hace 6 d\u00edas\nContactar", "revised": false, "rejected": true, "data": {"precio": "$ 650.000", "expensas": "$ 160.000 Expensas", "direccion": "Sarmiento 2090", "metros": "115 m\u00b2 tot.", "habitaciones": "4 amb.", "hace": "Contactar"}, "image": "https://imgar.zonapropcdn.com/avisos/1/00/53/55/23/00/360x266/1908914402.jpg?isFirstImage=true", "title": "Departamento \u00b7 100m\u00b2 \u00b7 4 Ambientes \u00b7 Alquiler 4 Amb C/dependencia y Balc\u00f3n"}, "https://www.zonaprop.com.ar/propiedades/clasificado/alclapin-alquiler-4-ambientes-cochera.-120-m-sup2--exp-53547158.html": {"date": "04-05-2024\n", "content": "$ 650.000\n$ 88.000 Expensas\nMafalda 900\nParque Patricios, Capital Federal\n120 m\u00b2 tot.\n4 amb.\n3 dorm.\n2 ba\u00f1os\n1 coch.\nCorredor Responsable: Claudio Rudecindo cmcpsi 6807 / Cristian Arnal Ponti cpi 3570- Contacto: Andres Rufino - mls id # Ver datos. Alquiler departamento de 4 ambientes con cochera en el barrio nuevo de Parque Patricios. Esta propiedad es una excelente opci\u00f3n para aquellos que buscan amplitud, comodidad y la conveniencia de tener un lugar para estacionar su veh\u00edculo. Al ingresar a la propiedad, te encontrar\u00e1s con un amplio y luminoso living-comedor, ideal para recibir visitas o disfrutar de momentos en familia. La cocina, totalmente equipada, cuenta con modernos electrodom\u00e9sticos y espacio de almacenamiento m\u00e1s que suficiente para tus utensilios y alimentos. Adem\u00e1s, cuenta con una c\u00f3moda barra desayunadora, perfecta para disfrutar de comidas r\u00e1pidas o tomar un caf\u00e9 por la ma\u00f1ana. La propiedad cuenta con tres dormitorios espaciosos, ideales para descansar y recargar energ\u00edas. Cada uno de ellos cuenta con amplios ventanales que permiten la entrada de luz natural y ofrecen vistas agradables. Adem\u00e1s, la propiedad cuenta con dos ba\u00f1os completos, equipados con todos los elementos necesarios para tu comodidad diaria. La cochera, ubicada en el mismo edificio, te brinda la tranquilidad de tener un lugar seguro y conveniente para estacionar tu veh\u00edculo. En cuanto a la ubicaci\u00f3n, el barrio nuevo de Parque Patricios es una zona en crecimiento y desarrollo, con una gran cantidad de servicios, comercios y espacios verdes cercanos. Adem\u00e1s, cuenta con excelentes conexiones de transporte p\u00fablico, lo que te permitir\u00e1 desplazarte f\u00e1cilmente por la ciudad. En resumen, esta propiedad de 4 ambientes con cochera en el barrio nuevo de Parque Patricios es una excelente opci\u00f3n para aquellos que buscan amplitud, comodidad y una ubicaci\u00f3n conveniente. Cuenta con dos ba\u00f1os completos, lo que brinda mayor comodidad y privacidad para los residentes y sus invitados. Adem\u00e1s, el edificio cuenta con un sum (Sal\u00f3n de Usos M\u00faltiples), un espacio com\u00fan destinado a eventos y reuniones sociales. Este espacio adicional es perfecto para celebrar ocasiones especiales, organizar reuniones con amigos o simplemente disfrutar de momentos de esparcimiento con los vecinos. Pero eso no es todo, la propiedad tambi\u00e9n cuenta con una terraza que ofrece una agradable sorpresa: una plaza con plantas y una vista panor\u00e1mica. Este espacio al aire libre es ideal para relajarse, disfrutar del sol y conectar con la naturaleza sin salir de casa. Puedes aprovecharlo para leer un libro, hacer ejercicio o simplemente contemplar la hermosa vista de los alrededores. En resumen, esta propiedad de 4 ambientes con cochera en el barrio nuevo de Parque Patricios no solo ofrece amplitud y comodidad, sino tambi\u00e9n beneficios adicionales como dos ba\u00f1os completos, un sum para eventos y una terraza con una plaza y una vista encantadora. Si tienes m\u00e1s preguntas o necesitas m\u00e1s detalles, no dudes en consultarme. Expensas $ 68. 000 + $20. 000 de cochera. requisitos para alquilar: * recibo de sueldo O constancia de ingreso ( monotributo) * garantia propietaria O seguro de caucion. * incremetos trimestrales segun el indice ipc ( indicie precio consumidor) Colectivos: 46, 70, 91, 118, 188. Remax Argentina S. R. L. No ejerce el corretaje inmobiliario. El presente sitio web es una plataforma en donde cada oficina inmobiliaria independiente que contrata los servicios re/max puede publicar las propiedades a su cargo. Cada oficina es de propiedad y gesti\u00f3n independiente, por lo que Remax Argentina S. R. L no interviene en los datos de la publicaci\u00f3n, en la operaci\u00f3n inmobiliaria, ni en la confecci\u00f3n y/o firma del boleto de compraventa y/o escritura y/o contrato de alquiler. En cumplimiento de las leyes vigentes que regulan el corretaje inmobiliario, Ley Nacional 25. 028, Ley 22. 802 de Lealtad Comercial, Ley 24. 240 de Defensa al Consumidor, las normas del C\u00f3digo Civil y Comercial de la Naci\u00f3n y Constitucionales, los agentes/gestores no ejercen el corretaje inmobiliario. Todas las operaciones inmobiliarias son objeto de intermediaci\u00f3n y conclusi\u00f3n por parte del corredor p\u00fablico inmobiliario colegiado a cargo de la publicaci\u00f3n, cuyos datos se exhiben en la presente. La presente publicaci\u00f3n describe las caracter\u00edsticas esenciales del inmueble, debi\u00e9ndose consultar al corredor p\u00fablico inmobiliario responsable de la operaci\u00f3n por la eventual actualizaci\u00f3n de las medidas, descripciones arquitect\u00f3nicas y funcionales, valores de expensas, servicios, impuestos, precios y dem\u00e1s informaci\u00f3n, cuyos valores son aproximados. Para los casos de alquiler de vivienda, el monto m\u00e1ximo de comisi\u00f3n que se le puede requerir a los propietarios ser\u00e1 el equivalente al cuatro con quince cent\u00e9simos por ciento (4, 15%) del valor total del respectivo contrato. Se encuentra prohibido cobrar a los inquilinos que sean personas f\u00edsicas comisiones inmobiliarias y gastos de gestor\u00eda de informes. El inmueble es accesible para personas con discapacidades f\u00edsicas.\nPublicado hace 5 d\u00edas\nContactar", "revised": false, "rejected": true, "data": {"precio": "$ 650.000", "expensas": "$ 88.000 Expensas", "direccion": "Mafalda 900", "metros": "120 m\u00b2 tot.", "habitaciones": "4 amb.", "hace": "Publicado hace 5 d\u00edas"}}, "https://www.zonaprop.com.ar/propiedades/clasificado/alclappa-alquiler-3-amb.-frente-balcon-corrido-luminoso-53581036.html": {"date": "06-05-2024\n", "index": 49, "content": "$ 450.000\n$ 70.000 Expensas\nDirecci\u00f3n no informada\nBalvanera, Capital Federal\n71 m\u00b2 tot.\n3 amb.\n2 dorm.\n1 ba\u00f1o\nPeron Y azcuenaga - 71 m totales. 67 m cubiertos. 5to piso con un amplio balc\u00f3n al frente. Vista abierta. Muy luminoso, Dos dormitorios, Ba\u00f1o y Toilete, Cocina, Lavadero. A 300 metros de la estaci\u00f3n de Once. A 200 metros de Av. Rivadavia. (Subte L\u00ednea A). A 200 metros de Av. Corrientes (Subte L\u00ednea B). El valor consignado de expensas est\u00e1 sujeto a variaci\u00f3n y/o ajuste. Las medidas, superficies y los m2 indicados son aproximados y solo a t\u00edtulo informativo.\nPublicado hace 2 d\u00edas\nContactar", "revised": true, "rejected": false, "data": {"precio": "$ 450.000", "expensas": "$ 70.000 Expensas", "direccion": "Direcci\u00f3n no informada", "metros": "71 m\u00b2 tot.", "habitaciones": "3 amb.", "hace": "Contactar"}, "image": "https://imgar.zonapropcdn.com/avisos/1/00/53/58/10/36/360x266/1909549602.jpg?isFirstImage=true", "title": "Living Comedor \u00b7 Alquiler 3 Amb. - Frente - Balc\u00f3n Corrido - Luminoso - Balvanera", "comment": "Fea zona. C\u00f3mo casa"}, "https://www.zonaprop.com.ar/propiedades/clasificado/alclapin-departamento-3-ambientes.-aguirre-al-300-53574488.html": {"date": "06-05-2024\n", "index": 54, "content": "$ 430.000\n$ 32.000 Expensas\nAGUIRRE 300. Entre Araoz y Alvarez julian\nVilla Crespo, Capital Federal\n61 m\u00b2 tot.\n3 amb.\n2 dorm.\n1 ba\u00f1o\n3 ambientes, en alquiler, villa crespo! Excelente ubicaci\u00f3n, a 1 cuadra de Av. Scalabrini Ortiz y a 3 cuadras de Av. Corrientes! Subte B estacion malabia. Living comedor con salida a balc\u00f3n corrido al frente, dos dormitorios con placard, cocina completa con conexi\u00f3n para lavarropas y lavadero independiente y ba\u00f1o completo! Living y dormitorios con pisos de parquet! Muy luminoso! Edificio con entrada y ascensores renovados! \"Se deja constancia que los m2 indicados son aproximados, al igual. que las medidas parciales de los ambientes, y el valor consignado de. expensas mensuales esta sujeta a verificacion y/o ajustes. Fotos de. cartacter no contractual. \"xintel(ber-ber-Ver datos)\nDestacado\nPublicado hace 3 d\u00edas\nContactar", "revised": false, "rejected": true, "data": {"precio": "$ 430.000", "expensas": "$ 32.000 Expensas", "direccion": "AGUIRRE 300. Entre Araoz y Alvarez julian", "metros": "61 m\u00b2 tot.", "habitaciones": "3 amb.", "hace": "Contactar"}, "image": "https://imgar.zonapropcdn.com/avisos/1/00/53/57/44/88/360x266/1909400903.jpg?isFirstImage=true", "title": "BER-BER-14987_2 \u00b7 Departamento 3 Ambientes. | Aguirre Al 300"}, "https://www.zonaprop.com.ar/propiedades/clasificado/alclapin-3-amb-c-dep-en-alq.-villa-crespo-53574058.html": {"date": "06-05-2024\n", "index": 57, "content": "$ 600.000\n$ 45.100 Expensas\nav corrientes 4664\nVilla Crespo, Capital Federal\n71 m\u00b2 tot.\n3 amb.\n3 dorm.\n1 ba\u00f1o\nPintoresco departamento de 3 ambientes con dependencia, al frente con balc\u00f3n. Cuenta con entrada de servicio. Cocina con lavadero independiente. Ba\u00f1o con ducha. Toilette. El edificio se encuentra sobre Av. Corrientes, a una cuadra de \u00c1ngel Gallardo (Estaci\u00f3n Angel Gallardo de la linea B de subtes), pr\u00f3ximo al Parque Centenario. Martillero responsable: nicolas ortiz. Matr\u00edcula cucicba 6337. brokerin servicios inmobiliarios. Conforme la ley 5115 de accesibilidad el inmueble posee acceso para personas con movilidad reducida. Aceptamos garant\u00eda respaldar: -aprobado-express-sin-cargo? i=7fe1f8abaad094e0b5cb1b01d712f708&h=5c86e2d4656c14a3011f3d60b262c35c\nDestacado\nPublicado hace 3 d\u00edas\nContactar", "revised": false, "rejected": true, "data": {"precio": "$ 600.000", "expensas": "$ 45.100 Expensas", "direccion": "av corrientes 4664", "metros": "71 m\u00b2 tot.", "habitaciones": "3 amb.", "hace": "Contactar"}, "image": "https://imgar.zonapropcdn.com/avisos/1/00/53/57/40/58/360x266/1909392691.jpg?isFirstImage=true", "title": "Departamento de 3 ambientes, Villa Crespo \u00b7 3 Amb C/dep en Alq. - Villa Crespo"}, "https://www.zonaprop.com.ar/propiedades/clasificado/alclphin-ph-en-1er-piso-de-3-ambientes-con-patio-y-terraza-53573812.html": {"date": "06-05-2024\n", "index": 58, "content": "$ 550.000\nPADILLA 600. Entre Malabia y Acevedo\nVilla Crespo, Capital Federal\n104 m\u00b2 tot.\n3 amb.\n2 dorm.\n1 ba\u00f1o\nPh 3 ambientes con terraza, en alquiler, en villa crespo!. Excelente ubicaci\u00f3n!. A 1 cuadra de la Av. Scalabrini Ortiz, a 2 cuadras de Av. Corrientes (Subte B) y a 2 cuadras de Av. Warnes. Primer piso por escaleras. Ingreso por amplio living comedor con aire acondicionado. Dos dormitorios con doble acceso. Patio cubierto de 3. 60 x 1. 70. Cocina completa con espacio para comedor diario. Ba\u00f1o completo con ventilaci\u00f3n natural. Todo con doble circulaci\u00f3n. En planta alta: terraza propia de acceso compartido, con quincho y lavadero independiente. Todo en excelente estado. Muy luminoso!. Solo dos unidades en el piso. No apto mascotas, ni piscinaen la terraza! \"Se deja constancia que los m2 indicados son aproximados, al igual que las medidas parciales de los ambientes, y el valor consignado de expensas mensuales est\u00e1 sujeto a verificaci\u00f3n y/o ajustes. Fotos de car\u00e1cter no contractual. \"xintel(ber-ber-Ver datos)\nDestacado\nPublicado hace 3 d\u00edas\nContactar", "revised": false, "rejected": true, "data": {"precio": "$ 550.000", "expensas": "", "direccion": "PADILLA 600. Entre Malabia y Acevedo", "metros": "104 m\u00b2 tot.", "habitaciones": "3 amb.", "hace": "Contactar"}, "image": "https://imgar.zonapropcdn.com/avisos/1/00/53/57/38/12/360x266/1909387670.jpg?isFirstImage=true", "title": "BER-BER-14983_2 \u00b7 PH en 1er Piso de 3 Ambientes con Patio y Terraza Propia!"}, "https://www.zonaprop.com.ar/propiedades/clasificado/alclapin-alquiler-3-ambientes-en-villa-crespo-53572670.html": {"date": "06-05-2024\n", "index": 71, "content": "$ 490.000\n$ 25.000 Expensas\nSerrano al 800\nVilla Crespo, Capital Federal\n70 m\u00b2 tot.\n3 amb.\n2 dorm.\n2 ba\u00f1os\nAlquiler hermoso departamento en Villa Crespo. Departamento en edificio de estilo ubicado al frente, sobre calle Serrano esquina Loyola. El departamento cuenta con dos dormitorios amplios con pisos de pinoteas pulidos y plastificados, living con pisos de pinotea, distribuidor con pisos de cemento alisado, dos ba\u00f1o, uno completo y un toilette, cocina con barra desayunador. Actualmente el departamento es El\u00e9ctrico ya que no cuenta con servicio de gas. Edificio de solo 3 pisos con 2 departamentos por piso y ascensor. Bajas expensas. Requisitos: contar con garant\u00eda en Capital o seguro de cauci\u00f3n y acreditaci\u00f3n de ingresos. Valor Inicial $490. 000Reajuste Trimestral por ipcerranti PropiedadesAlejandra Ver datos.\nPublicado hace 3 d\u00edas\nContactar", "revised": false, "rejected": true, "data": {"precio": "$ 490.000", "expensas": "$ 25.000 Expensas", "direccion": "Serrano al 800", "metros": "70 m\u00b2 tot.", "habitaciones": "3 amb.", "hace": "Contactar"}, "image": "https://imgar.zonapropcdn.com/avisos/1/00/53/57/26/70/360x266/1909363904.jpg?isFirstImage=true", "title": "Departamento \u00b7 70m\u00b2 \u00b7 3 Ambientes \u00b7 Alquiler 3 Ambientes en Villa Crespo"}, "https://www.zonaprop.com.ar/propiedades/clasificado/alclapin-esnaola-600-3-amb-60-m-amoblado-equipado-luminoso-53565338.html": {"date": "06-05-2024\n", "index": 80, "content": "$ 600.000\n$ 70.000 Expensas\nEsnaola 600\nParque Centenario, Capital Federal\n63 m\u00b2 tot.\n3 amb.\n2 dorm.\n1 ba\u00f1o\nEsnaola 600 y Av. Diaz Velez. Parque Centenario. 3 ambientes 60 mts. Living comedor. Balcon luminoso! Dormitorio principal con cama Queen. Dormitorio 2 con 1 cama de 1 plaza. Ba\u00f1o completo. Cocina equipada. Lavadero. Ropa blanca opcional. Losa radiante. Termotanque agua caliente. Aire acondicionado en el living. Ventiladores de techo en los dormitorios. 2 Televisores\nDestacado\nPublicado hace 4 d\u00edas\nContactar", "revised": false, "rejected": true, "data": {"precio": "$ 600.000", "expensas": "$ 70.000 Expensas", "direccion": "Esnaola 600", "metros": "63 m\u00b2 tot.", "habitaciones": "3 amb.", "hace": "Contactar"}, "image": "https://imgar.zonapropcdn.com/avisos/1/00/53/56/53/38/360x266/1909199052.jpg?isFirstImage=true", "title": "Departamento de 3 ambientes, Parque Centenario \u00b7 Esnaola 600 3 Amb 60 m Amoblado Equipado Luminoso"}, "https://www.zonaprop.com.ar/propiedades/clasificado/alclapin-departamento-en-villa-crespo-3-ambientes-con-balcon-53568815.html": {"date": "06-05-2024\n", "index": 88, "content": "$ 500.000\n$ 65.000 Expensas\nPanama al 933 11 A\nVilla Crespo, Capital Federal\n66 m\u00b2 tot.\n3 amb.\n2 dorm.\n1 ba\u00f1o\nPanam\u00e1 933 11\u00b0 AEntre Sarmiento y Avda. Corrientes. Barrio: Almagro. Zona de f\u00e1cil acceso. A 1 cuadra del subte B (estaci\u00f3n Angel Gallardo) y cerca del Parque Centenario. - Living: 4. 45 x 3. 00- Balc\u00f3n: 3. 50 x 1. 20- Pasillo: 4. 00 x 0. 75- Dormitorio 1: 2. 95 x 2. 95- Dormitorio 2: 3. 50 x 2. 45- Cocina: 3. 50 x 1. 45- Lavadero: 1. 45 x 0. 80- 3 Ambientes al frente con balc\u00f3n. - Muy luminoso. - Living comedor. - 2 Dormitorios con placards. - Pisos flotante. - Cocina equipada con alacena y bajo mesada. - Ba\u00f1o completo con una ventana con salida al exterior. - Lavadero independiente. - Agua caliente por termotanque. - Calefacci\u00f3n individual. El edificio tiene 14 pisos. - Del 1\u00b0 al 14\u00b0: 6 deptos por piso. - 2 Ascensores. - Estado gral: Bueno. - Expensas: . - Tiene equipo de aire acondicionado en el living y en las habitaciones. - El termotanque a gas. - El dormitorio principal tiene salida al balc\u00f3n. requisitos: seguro de caucion respaldar finaer O garantiayames de adelanto $500. 000mes de deposito $500. 000contrato A 2 a\u00f1os aumento cuatrimestral por ipccorredor Inmobiliario David L. Polonsky cpi 3275 vremont pronin En el cumplimiento de la ley nacional 25. 028, ley 22. 802 de lealtad comercial. Ley 24. 240 de defensa al consumidor, las normas del c\u00f3digo civil y comercial de la naci\u00f3n y constitucionales. Los agentes no ejercen el corretaje inmobiliario. Ley 5859 - Art. 4: \"Para los casos de alquiler de vivienda, el monto m\u00e1ximo de comisi\u00f3n que se le puede requerir a los propietarios ser\u00e1 el equivalente al cuatro con quince cent\u00e9simos por ciento (4, 15%) del valor total del contrato. Se encuentra prohibido cobrar a los inquilinos que sean personas f\u00edsicas comisiones inmobiliarias y gastos de gestor\u00eda de informes\". (En caso de ser alquiler) Ley 5115 \u2013 Art. 1: El inmueble publicado no es accesible para personas con capacidades f\u00edsicas reducidas. (En caso de no ser accesible) Se deja constancia que las medidas, superficies y m2 consignados son aproximados, sujetos a verificaci\u00f3n y/o ajuste. El precio del inmueble puede ser modificado sin previo aviso.\nPublicado hace 4 d\u00edas\nContactar", "revised": false, "rejected": true, "data": {"precio": "$ 500.000", "expensas": "$ 65.000 Expensas", "direccion": "Panama al 933 11 A", "metros": "66 m\u00b2 tot.", "habitaciones": "3 amb.", "hace": "Contactar"}, "image": "https://imgar.zonapropcdn.com/avisos/1/00/53/56/88/15/360x266/1909275462.jpg?isFirstImage=true", "title": "Departamento \u00b7 60m\u00b2 \u00b7 3 Ambientes \u00b7 Departamento en Villa Crespo 3 Ambientes con Balcon"}, "https://www.zonaprop.com.ar/propiedades/clasificado/alclapin-amplio-3-ambientes-en-villa-crespo-53563925.html": {"date": "06-05-2024\n", "index": 91, "content": "$ 470.000\n$ 43.000 Expensas\nDirecci\u00f3n no informada\nVilla Crespo, Capital Federal\n65 m\u00b2 tot.\n3 amb.\n2 dorm.\n1 ba\u00f1o\nDepartamento de 3 ambientes en excelente ubicaci\u00f3n en Villa Crespo. Dos dormitorios con placard, ba\u00f1o completo, living, cocina y lavadero independiente. No se admiten mascotas. Contrato a 2 a\u00f1os con ajuste trimestral seg\u00fan ipc. Requisitos: Garant\u00eda propietaria de caba o seguro de cauci\u00f3n Finaer. Justificaci\u00f3n de ingresos. Mes + deposito. Para visitar esta propiedad contactarse por whatsapp al 11*4949*8667. Carlos Mario Blum. Corredor Inmobiliario. Matr\u00edcula N\u00ba 88 folio 344 libro 377. cucicba N\u00b0 0272\nPublicado hace 4 d\u00edas\nContactar", "revised": false, "rejected": true, "data": {"precio": "$ 470.000", "expensas": "$ 43.000 Expensas", "direccion": "Direcci\u00f3n no informada", "metros": "65 m\u00b2 tot.", "habitaciones": "3 amb.", "hace": "Contactar"}, "image": "https://imgar.zonapropcdn.com/avisos/1/00/53/56/39/25/360x266/1909167577.jpg?isFirstImage=true", "title": "Departamento de 3 ambientes, Villa Crespo \u00b7 Amplio 3 Ambientes en Villa Crespo"}, "https://www.zonaprop.com.ar/propiedades/clasificado/alclappa-alquiler-departamento-3amb-con-balcon-y-patio-53565001.html": {"date": "06-05-2024\n", "index": 100, "content": "$ 600.000\n$ 140.000 Expensas\nJufr\u00e9 153\nVilla Crespo, Capital Federal\n83 m\u00b2 tot.\n3 amb.\n2 dorm.\n1 ba\u00f1o\nDepartamento de 3 ambientes, primer piso a la calle. Living comedor con salida al balc\u00f3n corrido con protecci\u00f3n. Dormitorio principal con placard empotrado y salida al balc\u00f3n corrido. Segundo dormitorio con ventana al balc\u00f3n corrido y placard empotrado. Ba\u00f1o completo. Cocina completa con espacio para mesa y salida al patio cubierto. Agua caliente central. Requisitos para la renta: - Seguro de cauci\u00f3n finaer. - 1 mes de adelanto de alquiler. - 1 mes de dep\u00f3sito. - Demostraci\u00f3n de ingresos\nPublicado hace 4 d\u00edas\nContactar", "revised": false, "rejected": true, "data": {"precio": "$ 600.000", "expensas": "$ 140.000 Expensas", "direccion": "Jufr\u00e9 153", "metros": "83 m\u00b2 tot.", "habitaciones": "3 amb.", "hace": "Contactar"}, "image": "https://imgar.zonapropcdn.com/avisos/1/00/53/56/50/01/360x266/1909202796.jpg?isFirstImage=true", "title": "Departamento de 3 ambientes, Villa Crespo \u00b7 Alquiler Departamento 3amb con Balc\u00f3n y Patio"}, "https://www.zonaprop.com.ar/propiedades/clasificado/alclbgin-departamento-en-villa-crespo-53561562.html": {"date": "06-05-2024\n", "index": 106, "content": "$ 550.000\n$ 86.000 Expensas\nRamirez De Velasco, Juan al 500\nVilla Crespo, Capital Federal\n87 m\u00b2 tot.\n3 amb.\n2 dorm.\n1 ba\u00f1o\n3 ambientes al contra frente super luminoso. Consta de comodo living comedor con salida al balcon, 2 dormitorios con placards, ba\u00f1o y toillete, cocina con muebles altos y bajos, puerta blindada pent\u00e1gono, calefaccion por estufa. Excelente ubicacion Velasco al 500 entre Malabia y Avda. R. S. Ortiz, colecitvos, subte B estaci\u00f3n Malabia, comercios. Visitascombinar 24 hs antes visitas. Srta Naomi o Sr. Roberto 11 Ver datos. Pida tasaci\u00f3n: Efectuada por profesionales, que analizan permanentemente el desenvolvimiento del mercado. Conf\u00ede su patrimonio en una empresa s\u00f3lida con respaldo y prestigio. Conf\u00ede en el L\u00edder. Goldstein propiedades. Se deja constancia que los m2 son aproximados, al igual que las medidas parciales y el valor consignado de las expensas mensuales (en caso que corresponda pago de expensas) y las caracter\u00edsticas est\u00e1n sujetos a verificaci\u00f3n y/o ajustes, el precio del inmueble puede ser modificado sin previo aviso. En el caso de tratarse de un inmueble en construcci\u00f3n los detalles de terminaci\u00f3n y la fecha de entrega est\u00e1n sujetos a revisi\u00f3n. Fotos de car\u00e1cter no contractual. Las unidades publicadas est\u00e1n sujetas a disponibilidad. Goldstein Propiedades srl con domicilio en Avda. Corrientes 4666 act\u00faa solamente en car\u00e1cter de comercializadora de los inmuebles ofrecidos. En caso de tratarse de un terreno, la informaci\u00f3n de m2 construibles y plusval\u00eda es orientativa, debiendo ser constatada por el interesado. Inmueble no accesible para personas con discapacidad f\u00edsica ley 5115. Cucicba matr\u00edcula 37. Cmcpsi matr\u00edcula 6003. \u00danicamente en el caso de tratarse de alquiler de vivienda familiar, rige lo indicado en la ley 5859. Venta supeditada al cumplimiento por parte del propietario de los requisitos de la resoluci\u00f3n general N\u00ba 2371 de la afip (pedido de coti).\nPublicado hace 5 d\u00edas\nContactar", "revised": false, "rejected": true, "data": {"precio": "$ 550.000", "expensas": "$ 86.000 Expensas", "direccion": "Ramirez De Velasco, Juan al 500", "metros": "87 m\u00b2 tot.", "habitaciones": "3 amb.", "hace": "Contactar"}, "image": "https://imgar.zonapropcdn.com/avisos/1/00/53/56/15/62/360x266/1909118394.jpg?isFirstImage=true", "title": "Bodega-Galp\u00f3n \u00b7 80m\u00b2 \u00b7 3 Ambientes \u00b7 Departamento en Villa Crespo"}, "https://www.zonaprop.com.ar/propiedades/clasificado/alclapin-departamento-villa-crespo-53560404.html": {"date": "06-05-2024\n", "index": 119, "content": "$ 500.000\n$ 53.000 Expensas\nCorrientes al 5600\nVilla Crespo, Capital Federal\n60 m\u00b2 tot.\n3 amb.\n2 dorm.\n1 ba\u00f1o\nDepartamento de 3 ambientes muy bien ubicado, muy luminoso. Gaed negocios inmobiliarios, cucicba mat. 226Contrato por dos a\u00f1os con actualizaci\u00f3n trimestral por icl\"Se deja constancia que los m2 son aproximados, al igual que las medidas parciales y el valor consignado de las expensas mensuales (en caso que corresponda pago de expensas) est\u00e1n sujetos a verificaci\u00f3n y/o ajustes, el precio del inmueble puede ser modificado sin previo aviso. Fotos de car\u00e1cter no contractual. Las unidades publicadas est\u00e1n sujetas a disponibilidad. Gaed Inmobiliaria act\u00faa solamente en car\u00e1cter de comercializadora de los inmuebles ofrecidos. Inmueble no accesible para personas con discapacidad f\u00edsica ley 5115. \u00danicamente en el caso de tratarse de alquiler de vivienda familiar, rige lo indicado en la ley 5859. \"gaed inmobiliaria. Cucicba matricula 226\nSuper destacado\nPublicado hace 5 d\u00edas\nContactar", "revised": false, "rejected": true, "data": {"precio": "$ 500.000", "expensas": "$ 53.000 Expensas", "direccion": "Corrientes al 5600", "metros": "60 m\u00b2 tot.", "habitaciones": "3 amb.", "hace": "Contactar"}, "image": "https://imgar.zonapropcdn.com/avisos/1/00/53/56/04/04/360x266/1909094688.jpg?isFirstImage=true", "title": "Departamento \u00b7 55m\u00b2 \u00b7 3 Ambientes \u00b7 Departamento - Villa Crespo"}, "https://www.zonaprop.com.ar/propiedades/clasificado/alclappa-departamento-en-almagro-3-ambientes-excelente-53581226.html": {"date": "06-05-2024\n", "index": 44, "content": "$ 600.000\n$ 102.000 Expensas\nDirecci\u00f3n no informada\nAlmagro, Capital Federal\n92 m\u00b2 tot.\n3 amb.\n2 dorm.\n1 ba\u00f1o\nDepartamento 3 ambientes en Avenida Corrientes 4700, Almagro. Amplio y c\u00f3modo departamento de 92 m\u00b2 con capacidad para 4 personas totalmente amoblado en un 8no piso. Excelente ubicaci\u00f3n, cerca de Parque Centenario, y de varios medios de transporte, rodeado de comercios, restaurantes, bares y supermercados. El cuenta con: Dormitorio con cama matrimonial. Dormitorio con cama marinera. Cocina completa con cocina a gas, microondas, heladera con freezer y utensilios necesarios. Ba\u00f1o completo con ba\u00f1era y bidet. Living comedor con sof\u00e1, mesa y sillas. Tambi\u00e9n cuenta con calefacci\u00f3n y wifi. Balc\u00f3n con vista al frente. Lavadero con Lavarropas. Valor mensual: $600. 000. - Requisitos: 1er mes de alquiler, mes de dep\u00f3sito en garant\u00eda reembolsable al finalizar el contrato\nPublicado hace 2 d\u00edas\nContactar", "revised": false, "rejected": true, "data": {"precio": "$ 600.000", "expensas": "$ 102.000 Expensas", "direccion": "Direcci\u00f3n no informada", "metros": "92 m\u00b2 tot.", "habitaciones": "3 amb.", "hace": "Contactar"}, "image": "https://imgar.zonapropcdn.com/avisos/1/00/53/58/12/26/360x266/1909554352.jpg?isFirstImage=true", "title": "Departamento de 3 ambientes, Almagro \u00b7 Departamento en Almagro 3 Ambientes, Excelente Ubicaci\u00f3n (Due\u00f1o Directo)"}, "https://www.zonaprop.com.ar/propiedades/clasificado/alclphin-alquiler-de-ph-en-planta-baja-amplio-y-luminoso-53581650.html": {"date": "06-05-2024\n", "index": 35, "content": "$ 350.000\n$ 18.000 Expensas\nDirecci\u00f3n no informada\nSan Cristobal, Capital Federal\n68 m\u00b2 tot.\n4 amb.\n3 dorm.\n1 ba\u00f1o\nMas Propiedades te ofrece en alquiler este confortable ph en planta baja con patio, ubicado en la calle Carlos Calvo 1700. Ubicaci\u00f3n Privilegiada: A pasos de la Avenida Entre R\u00edos y a solo dos cuadras de la Avenida Independencia. F\u00e1cil acceso a la L\u00ednea E de Subte y a numerosas l\u00edneas de colectivo. Ideal para quienes buscan un traslado r\u00e1pido y c\u00f3modo por la ciudad. Caracter\u00edsticas: Superficie: 68m\u00b2 Totales (55m\u00b2 Cubiertos y 13m\u00b2 Descubiertos): Amplio living-comedor con salida al patio. Cocina independiente. Ba\u00f1o completo reciclado a nuevo. Pisos de pinotea. Techos altos. Cerramientos con amplios ventanales que brindan gran luminosidad. Tres ambientes corridos (3. 60 de largo todos) de aproximadamente 4 m de ancho y el central de 2. 50 m. Un ambiente en altos (tercer dormitorio/taller/dependencia). Patio de 13 m\u00b2. Distribuci\u00f3n de piezas corridas y salida al patio. Luminosidad y amplitud en todos los ambientes. Bajas expensas. Requisitos para Alquilar: Ingresos demostrables. Garant\u00eda propietaria o seguro de cauci\u00f3n. Para Concertar Visitas: WhatsApp: 11 Ver datos\nPublicado desde ayer\nContactar", "revised": true, "rejected": false, "data": {"precio": "$ 350.000", "expensas": "$ 18.000 Expensas", "direccion": "Direcci\u00f3n no informada", "metros": "68 m\u00b2 tot.", "habitaciones": "4 amb.", "hace": "Contactar"}, "image": "https://imgar.zonapropcdn.com/avisos/1/00/53/58/16/50/360x266/1909562809.jpg?isFirstImage=true", "title": "PH de 4 ambientes, San Cristobal \u00b7 Alquiler de PH en Planta Baja - Amplio y Luminoso - Carlos Calvo 1700 - 68 m\u00b2", "comment": "Patio descubierto. Es 3amb con escritorio "}, "https://www.argenprop.com/departamento-en-alquiler-en-parque-centenario-3-ambientes--15520552": {"date": "05-05-2024\n", "content": "1\n/7\n0\n$ 350.000 + $110.000 expensas\nEUSTOQUI FRIAS GRAL 200\nDepartamento en Alquiler en Parque Centenario, Capital Federal\n61 m\u00b2 cubie.\n2 dorm.\n45 a\u00f1os\nDepartamento de 3 ambientes en Alquiler en P.centenario\nDepartamento de 3 ambientes en alquiler en parque centenario\nWhatsApp\nContactar", "revised": false, "rejected": true, "data": {"precio": "$ 350.000 + $110.000 expensas", "expensas": "+ $110.000 expensas", "direccion": "EUSTOQUI FRIAS GRAL 200", "metros": "61 m\u00b2 cubie.", "habitaciones": "2 dorm."}}, "https://www.argenprop.com/departamento-en-alquiler-en-once-4-ambientes--15623337": {"date": "05-05-2024\n", "content": "1\n/12\n720\n$ 450.000 + $76.700 expensas\nAvenida Corrientes 2600, Piso 7\nDepartamento en Alquiler en Once, Capital Federal\n86 m\u00b2 cubie.\n3 dorm.\n45 a\u00f1os\nOnce 4 amb frente due\u00f1o Av. Corrientes esq. Paso.\nAv. Corrientes al 2600 esquina paso 422, a una cuadra de la avda. Pueyrred\u00f3n y el cruce del subte b (estaci\u00f3n pueyrred\u00f3n) y del subte h (estaci\u00f3n corrientes). Departamento de 4 amb. Todos al frente en 7mo piso; dos entradas, doble circulaci\u00f3n, hall de recepci\u00f3n, living comedor, dormitorios con placard, todos a la calle con ventanales sobre paso al 400. Ba\u00f1o completo, toilette y ba\u00f1o de servicio,\nWhatsApp\nContactar", "revised": false, "rejected": true, "data": {"precio": "$ 450.000 + $76.700 expensas", "expensas": "+ $76.700 expensas", "direccion": "Avenida Corrientes 2600, Piso 7", "metros": "86 m\u00b2 cubie.", "habitaciones": "3 dorm."}}, "https://www.argenprop.com/departamento-en-alquiler-en-almagro-4-ambientes--15621362": {"date": "05-05-2024\n", "content": "1\n/16\n0\n$ 550.000 + $90.000 expensas\nSARMIENTO 4300\nDepartamento en Alquiler en Almagro, Capital Federal\n90 m\u00b2 cubie.\n3 dorm.\n40 a\u00f1os\nDepartamento de 4 ambientes en Alquiler en Almagro\nDepartamento de 4 ambientes con dependencia, en alquiler. Al frente, con balcon. Luminoso. Semipiso. Muy buena superficie. Cerca avdas. Corrientes, medrano, diaz velez. Subte, colectivos. Parque centenario, hospital italiano. Comercializa migliorisi de corrientes 4599 srl profesional responsable jorge daniel gomez cpi 261 a30101 se deja constancia que las caracteristicas, medidas, expensas y\nWhatsApp\nContactar", "revised": true, "rejected": false, "data": {"precio": "$ 550.000 + $90.000 expensas", "expensas": "+ $90.000 expensas", "direccion": "SARMIENTO 4300", "metros": "90 m\u00b2 cubie.", "habitaciones": "3 dorm."}, "comment": "Grande. Hospital italiano. Falta cocina "}, "https://www.argenprop.com/departamento-en-alquiler-en-villa-crespo-3-ambientes--15601784": {"date": "05-05-2024\n", "content": "1\n/11\n2\n$ 390.000 + $37.000 expensas\nLeopoldo Marechal 1200, Piso 3\nDepartamento en Alquiler en Villa Crespo, Capital Federal\n67 m\u00b2 cubie.\n2 dorm.\n49 a\u00f1os\nBalcon Cerrado - Lavarropas (opcional) - Muy Luminoso - 200 m Parque Centenario\nUbicado a 200 m del parque centenario. Piso 3\u00b0, contrafrente, balc\u00f3n cerrado, muy luminoso. Lavadero incorporado. Lavarropas. Expensas: $ 37.000 seguinos por instagram arguellesasociadosinmobiliaria visita nuestro sitio web\nWhatsApp\nContactar", "revised": false, "rejected": true, "data": {"precio": "$ 390.000 + $37.000 expensas", "expensas": "+ $37.000 expensas", "direccion": "Leopoldo Marechal 1200, Piso 3", "metros": "67 m\u00b2 cubie.", "habitaciones": "2 dorm."}}, "https://www.argenprop.com/departamento-en-alquiler-en-parque-centenario-3-ambientes--15601707": {"date": "05-05-2024\n", "content": "1\n/11\n2\n$ 390.000 + $37.000 expensas\nLeopoldo Marechal 1200, Piso 3\nDepartamento en Alquiler en Parque Centenario, Capital Federal\n67 m\u00b2 cubie.\n2 dorm.\n49 a\u00f1os\nBalcon Cerrado - Lavarropas (opcional) - Muy Luminoso - 200 m Parque Centenario\nUbicado a 200 m del parque centenario. Piso 3\u00b0, contrafrente, balc\u00f3n cerrado, muy luminoso. Lavadero incorporado. Lavarropas. Expensas: $ 37.000 seguinos por instagram arguellesasociadosinmobiliaria visita nuestro sitio web\nWhatsApp\nContactar", "revised": false, "rejected": true, "data": {"precio": "$ 390.000 + $37.000 expensas", "expensas": "+ $37.000 expensas", "direccion": "Leopoldo Marechal 1200, Piso 3", "metros": "67 m\u00b2 cubie.", "habitaciones": "2 dorm."}}, "https://www.argenprop.com/departamento-en-alquiler-en-monserrat-4-ambientes--6085132": {"date": "05-05-2024\n", "content": "1\n/15\n2\n$ 540.000 + $110.000 expensas\nDr M Moreno 800, Piso 7\nDepartamento en Alquiler en Monserrat, Centro\n74 m\u00b2 cubie.\n3 dorm.\n20 a\u00f1os\nVIGILANCIA 24HS - RECIEN PINTADO\nApto profesional. Vigilancia 24hs. Piso 7 al contrafrente, balc\u00f3n, muy luminosa. Reci\u00e9n pintada. 3 dormitorios, cocina con comedor diario, 2 ba\u00f1os (1 completo y 1 toilete). Expensas: $ 110.000. Servicios individuales. Seguinos en instagram argeullesasociadosinmobiliaria\nWhatsApp\nContactar", "revised": false, "rejected": true, "data": {"precio": "$ 540.000 + $110.000 expensas", "expensas": "+ $110.000 expensas", "direccion": "Dr M Moreno 800, Piso 7", "metros": "74 m\u00b2 cubie.", "habitaciones": "3 dorm."}}, "https://www.argenprop.com/departamento-en-alquiler-en-almagro-3-ambientes--15645655": {"date": "05-05-2024\n", "content": "922\n$ 700.000 + $120.000 expensas\nRAWON 100, Piso 3\nDepartamento en Alquiler en Almagro, Capital Federal\n60,89 m\u00b2 cubie.\n2 dorm.\n16 a\u00f1os\nAL FRENTE CON BALCON IMPECABLE 3 AMBIENTES CON COCHERA\nWhatsApp\nContactar", "revised": false, "rejected": true, "data": {"precio": "$ 700.000 + $120.000 expensas", "expensas": "+ $120.000 expensas", "direccion": "RAWON 100, Piso 3", "metros": "60,89 m\u00b2 cubie.", "habitaciones": "2 dorm."}}, "https://www.argenprop.com/departamento-en-alquiler-en-san-cristobal-3-ambientes--15635995": {"date": "05-05-2024\n", "content": "1\n/58\n350\n$ 500.000 + $80.000 expensas\nAv San Juan 2767\nDepartamento en Alquiler en San Cristobal, Capital Federal\n89 m\u00b2 cubie.\n2 dorm.\n40 a\u00f1os\nAlquiler de Semipiso de 3 ambientes con dependencia en San Crist\u00f3bal\nAlquiler de departamento de 3 ambientes con dependencia en san crist\u00f3bal. El departamento se encuentra en un noveno piso al contrafrente con vista panor\u00e1mica ubicado sobre la av. San juan muy cercano a l\u00ednea e y h de subte, zona s\u00faper comercial y cercano a todo. El inmueble cuenta con ambientes muy luminosos y espaciosos, cocina completa, lavadero independiente, living comedor con salida al\nWhatsApp\nContactar", "revised": true, "rejected": false, "data": {"precio": "$ 500.000 + $80.000 expensas", "expensas": "+ $80.000 expensas", "direccion": "Av San Juan 2767", "metros": "89 m\u00b2 cubie.", "habitaciones": "2 dorm."}, "comment": "Esquina catamarca. 3amb y Dependencia con entrada"}, "https://www.argenprop.com/ph-en-alquiler-en-parque-patricios-4-ambientes--15645561": {"date": "05-05-2024\n", "content": "1\n/17\n2\n$ 600.000\nAv La Plata 2400, Piso 1\nPH en Alquiler en Parque Patricios, Capital Federal\n90 m\u00b2 cubie.\n3 dorm.\n45 a\u00f1os\nAMPLIO PH 4AMB C BALCON FRENTE- PATIO- SIN EXPENSAS- AV LA PLATA 2462 INFO\nCorredora cucicba mat. 76 art 4 ley 5859 caba \"para los casos de alquiler de vivienda, el monto m\u00e1ximo de comisi\u00f3n que se le puede requerir a los propietarios ser\u00e1 el equivalente al cuatro con quince cent\u00e9simos por ciento (4,15%) del valor total del respectivo contrato. Se encuentra prohibido cobrar a los inquilinos que sean personas f\u00edsicas comisiones inmobiliarias y gastos de gestor\u00eda de\nWhatsApp\nContactar", "revised": false, "rejected": true, "data": {"precio": "$ 600.000", "direccion": "Av La Plata 2400, Piso 1", "metros": "90 m\u00b2 cubie.", "habitaciones": "3 dorm."}}, "https://www.argenprop.com/departamento-en-alquiler-en-parque-patricios-4-ambientes--15642262": {"date": "05-05-2024\n", "content": "1\n/19\n315\n$ 550.000 + $70.000 expensas\nAv Jujuy 2000, Piso 7\nDepartamento en Alquiler en Parque Patricios, Capital Federal\n68 m\u00b2 cubie.\n3 dorm.\n1 ba\u00f1o\nDepartamento con ambientes luminosos y excelente cocina\nExcelente departamento de 4 ambientes en alquiler en parque patricios. A pocos metros de estacion subte linea \"h\". 68 mts cts y+ balcon sobre av. Jujuy de 8 x 1,10 mts.total 77 mts.el balcon y cada una de las ventanas de los ambientes tienen red plastica para proteccion. Para ingresar a la locacion se requiere: 1 mes de adelanto $ 550.000 + 1 mes de deposito de garantia $ 550.000. Presentar\nWhatsApp\nContactar", "revised": true, "rejected": true, "data": {"precio": "$ 550.000 + $70.000 expensas", "expensas": "+ $70.000 expensas", "direccion": "Av Jujuy 2000, Piso 7", "metros": "68 m\u00b2 cubie.", "habitaciones": "3 dorm."}, "comment": "Bueno. Gran balcon. Entre Brasil y Caseros "}, "https://www.argenprop.com/departamento-en-alquiler-en-san-cristobal-4-ambientes--15640810": {"date": "05-05-2024\n", "content": "1\n/12\n175\n$ 400.000 + $45.000 expensas\nSarand\u00ed 1400, Piso 8\nDepartamento en Alquiler en San Cristobal, Capital Federal\n78 m\u00b2 cubie.\n3 dorm.\n50 a\u00f1os\nDepto de 4 ambientes, 2 ba\u00f1os y cocina con comedor diario\nSemipiso de 4 ambientes, 2 ba\u00f1os y cocina con comedor diario, en la calle sarand\u00ed al 1400. En un 8vo piso muy luminoso. Orientado al oeste y al este simult\u00e1neamente, muy buen aireaci\u00f3n. Amplios placards con bauleras en los 3 dormitorios. Conexi\u00f3n para lavarropas en la cocina. Reci\u00e9n pintado. Garant\u00edas aceptadas: fi naer, garan t\u00eda ya \u00f3 pre mium solamente 1 mes de dep\u00f3sito. 1 mes de alquiler.\nContactar", "revised": false, "rejected": true, "data": {"precio": "$ 400.000 + $45.000 expensas", "expensas": "+ $45.000 expensas", "direccion": "Sarand\u00ed 1400, Piso 8", "metros": "78 m\u00b2 cubie.", "habitaciones": "3 dorm."}}, "https://www.argenprop.com/departamento-en-alquiler-en-congreso-3-ambientes--15644927": {"date": "05-05-2024\n", "content": "1\n/24\n0\n$ 380.000 + $78.600 expensas\nHipolito Yrigoyen y Rincon\nDepartamento en Alquiler en Congreso, Capital Federal\n105 m\u00b2 cubie.\n2 dorm.\n80 a\u00f1os\nDepartamento de 3 ambientes con dependencia en primer piso - Apto profesional\nAmplio departamento de tres ambientes con dependencia. Al ingreso c\u00f3moda recepci\u00f3n de 4,5 x 3.4 con pisos plastificados. En paralelo otro ambiente de 3.4 x 2.4 que podr\u00eda destinarse a comedor. Sala de grandes dimensiones de 8,5 x 3,7. Ideal para clases o exposiciones. Posibilidad de subidividir para hacer otra habitaci\u00f3n. Sector de cocina separada. Ba\u00f1o con\nWhatsApp\nContactar", "revised": false, "rejected": true, "data": {"precio": "$ 380.000 + $78.600 expensas", "expensas": "+ $78.600 expensas", "direccion": "Hipolito Yrigoyen y Rincon", "metros": "105 m\u00b2 cubie.", "habitaciones": "2 dorm."}}, "https://www.argenprop.com/departamento-en-alquiler-en-san-nicolas-3-ambientes--15594907": {"date": "05-05-2024\n", "content": "1\n/13\n501\n$ 400.000 + $130.000 expensas\nTte. Gral. JUAN DOMINGO PERON al 1700\nDepartamento en Alquiler en San Nicol\u00e1s, Centro\n60 m\u00b2 cubie.\n2 dorm.\nA Estrenar\nTte. Gral. JUAN DOMINGO PERON 1700 Departamento en Alquiler 3 ambientes al frente\nDepartamento 3 ambientes al frente, en el piso 13 excelente vista abierta a ciudad. Se ingresa por un elegante hall que te lleva a los 3 ascensores. Apto profesional el edificio cuenta con encargado permanente y personal de seguridad nocturno. Al ingresar al departamento te encontras con un espacioso living comedor con un amplio ventanal que da\nWhatsApp\nContactar", "revised": false, "rejected": true, "data": {"precio": "$ 400.000 + $130.000 expensas", "expensas": "+ $130.000 expensas", "direccion": "Tte. Gral. JUAN DOMINGO PERON al 1700", "metros": "60 m\u00b2 cubie.", "habitaciones": "2 dorm."}}, "https://www.argenprop.com/departamento-en-alquiler-en-san-nicolas-3-ambientes--15594901": {"date": "05-05-2024\n", "content": "1\n/13\n0\n$ 400.000 + $130.000 expensas\nTte. Gral. JUAN DOMINGO PERON al 1700\nDepartamento en Alquiler en San Nicol\u00e1s, Centro\n60 m\u00b2 cubie.\n2 dorm.\nA Estrenar\nTte. Gral. JUAN DOMINGO PERON 1700 Departamento en Alquiler 3 ambientes al frente\nDepartamento 3 ambientes al frente, en el piso 13 excelente vista abierta a ciudad. Se ingresa por un elegante hall que te lleva a los 3 ascensores. Apto profesional el edificio cuenta con encargado permanente y personal de seguridad nocturno. Al ingresar al departamento te encontras con un espacioso living comedor con un amplio ventanal que da\nWhatsApp\nContactar", "revised": false, "rejected": true, "data": {"precio": "$ 400.000 + $130.000 expensas", "expensas": "+ $130.000 expensas", "direccion": "Tte. Gral. JUAN DOMINGO PERON al 1700", "metros": "60 m\u00b2 cubie.", "habitaciones": "2 dorm."}}, "https://www.argenprop.com/departamento-en-alquiler-en-almagro-3-ambientes--5984886": {"date": "05-05-2024\n", "content": "1\n/19\n27\n$ 550.000 + $58.000 expensas\nCOLOMBRES 100, Piso 5\nDepartamento en Alquiler en Almagro, Capital Federal\n47,79 m\u00b2 cubie.\n2 dorm.\n30 a\u00f1os\nDEPARTAMENTO EN BUEN ESTADO Y UBICACION, A.ACOND. S.U.M. FRENTE. TODO AIRE Y LUZ. PARQUET.\nDepartamento de tres ambientes muy conservado, con excelente iluminacion, buena ubicacion a pocos metros de la estaci\u00f3n castro barros, subte \"a\", locaci\u00f3n con o sin mobiliario. Pisos parquet y cer\u00e1micos. Aire acondicionado, edificio cuenta con s.U.M. Nota: \u201clas medidas son aproximadas y orientativas. Las medidas exactas surgir\u00edan del t\u00edtulo de propiedad\" \u201cpara los casos de alquiler de vivienda,\nWhatsApp\nContactar", "revised": false, "rejected": true, "data": {"precio": "$ 550.000 + $58.000 expensas", "expensas": "+ $58.000 expensas", "direccion": "COLOMBRES 100, Piso 5", "metros": "47,79 m\u00b2 cubie.", "habitaciones": "2 dorm."}}, "https://www.argenprop.com/departamento-en-alquiler-en-balvanera-4-ambientes--15617750": {"date": "05-05-2024\n", "content": "1\n/58\n0\n$ 650.000 + $180.000 expensas\nLarrea al 700\nDepartamento en Alquiler en Balvanera, Capital Federal\n80 m\u00b2 cubie.\n3 dorm.\n40 a\u00f1os\nLarrea al 700 - 3 amb c/dep y balc\u00f3n - FACULTAD - Alquiler\nDepartamento de 4 amb c/balc\u00f3n contrafrente semi-piso muy luminoso encargado diurno seguridad nocturna palier semi-privado living-comedor con aire acondicionado balc\u00f3n al contrafrente dormitorio con placard dormitorio con placard dormitorio con placard amplia cocina completa a nueva comedor diario cocina el\u00e9ctrica vitrocer\u00e1mica a nuevo horno el\u00e9ctrico a nuevo termotanque a\nContactar", "revised": false, "rejected": true, "data": {"precio": "$ 650.000 + $180.000 expensas", "expensas": "+ $180.000 expensas", "direccion": "Larrea al 700", "metros": "80 m\u00b2 cubie.", "habitaciones": "3 dorm."}}, "https://www.argenprop.com/departamento-en-alquiler-en-almagro-4-ambientes--5827366": {"date": "05-05-2024\n", "content": "1\n/28\n175\n$ 630.000 + $63.000 expensas\nAv Belgrano 3500, Piso 1\nDepartamento en Alquiler en Almagro, Capital Federal\n90 m\u00b2 cubie.\n3 dorm.\n40 a\u00f1os\nPiso de 4 ambientes al frente con balc\u00f3n corrido y patio\nMuy buen piso, frente orientado al norte, balc\u00f3n corrido con protector de red y buena vista. Es un inmueble t\u00edpico de la d\u00e9cada del 70, con pisos de escalla de m\u00e1rmol en el living comedor, cortinas tipo barrio (la del living el\u00e9ctrica), azulejos de color en el ba\u00f1o principal, etc. La cocina comedor es muy amplia con muebles sobre y bajo mesada de 17 puertas amplias, artefacto de cocina domec de\nWhatsApp\nContactar", "revised": true, "rejected": false, "data": {"precio": "$ 630.000 + $63.000 expensas", "expensas": "+ $63.000 expensas", "direccion": "Av Belgrano 3500, Piso 1", "metros": "90 m\u00b2 cubie.", "habitaciones": "3 dorm."}, "comment": "Piso de piedra. Esquina Masa. Buena cocina. Caro"}, "https://www.zonaprop.com.ar/propiedades/clasificado/alclapin-alquiler-arenales-1600-4-ant.-frances-amplio-y-muy-53563997.html": {"date": "06-05-2024\n", "index": 93, "content": "Consultar precio\n$ 130.000 Expensas\nArenales al 1600 y Montevideo\nBarrio Norte, Capital Federal\n252 m\u00b2 tot.\n6 amb.\n4 dorm.\n3 ba\u00f1os\nEdificio Antiguo Frances de 5 pisos, a media cuadra de Plaza Vicente Lopez. Piso 4 Super amplio y Luminoso!! 252m2. Hall de entrada con una barra, living y comedor amplio al frente sobre la calle Arenales. Pisos de pinotea, aberturas originales, techos altos. Playroom/ escritorio. Toilette de recepci\u00f3n. Doble circulaci\u00f3n. Cocina con comedor diario, lavadero independiente y dependencia de servicio con su ba\u00f1o. Toilette de recepci\u00f3n. 4 dormitorios amplios (dos en suite y los otros dos comparten un ba\u00f1o). Cfte vista verde super silencioso y luminosos. Servicios individuales, aa, calefacci\u00f3n por radiadores individuales y agua caliente individual. Expensas bajas $130. 000, encargado vive en el edificio pero trabaja 4 hrs diarias. Aysa $20. 000. Observaciones: se entrega pintado y artefacto cocina a nuevo. Actualmente alquilan cochera sobre Montevideo a media cuadra en $40. 000. Opci\u00f3n con muebles\nPublicado hace 4 d\u00edas\nContactar", "revised": false, "rejected": true, "data": {"precio": "Consultar precio", "expensas": "$ 130.000 Expensas", "direccion": "Arenales al 1600 y Montevideo", "metros": "252 m\u00b2 tot.", "habitaciones": "6 amb.", "hace": "Contactar"}, "image": "https://imgar.zonapropcdn.com/avisos/1/00/53/56/39/97/360x266/1909168706.jpg?isFirstImage=true", "title": "Departamento \u00b7 252m\u00b2 \u00b7 6 Ambientes \u00b7 Alquiler - Arenales 1600 4 Ant. Frances Amplio y Muy Luminoso 252 m\u00b2 Opc Muebles"}, "https://www.zonaprop.com.ar/propiedades/clasificado/alclapin-departamento-en-almagro-53539538.html": {"date": "05-05-2024\n", "content": "$ 750.000\n$ 129.000 Expensas\nR\u00edo de Janeiro al 1000\nAlmagro, Capital Federal\n64 m\u00b2 tot.\n3 amb.\n2 dorm.\n2 ba\u00f1os\n1 coch.\nSe vende departamento de 3 ambientes con cochera, ubicado en el contrafrente con balc\u00f3n y una hermosa vista a la pileta del edificio. El inmueble cuenta con gran categor\u00eda y est\u00e1 distribuido en dos entradas: la principal y una puerta de servicio. El living comedor tiene acceso a un balc\u00f3n en el contrafrente, ofreciendo una vista abierta y una gran luminosidad. La cocina es amplia, equipada con muebles altos y bajos, y cuenta con un lavadero independiente. El departamento tiene dos dormitorios con placard y pisos flotantes, adem\u00e1s de un toilette y un ba\u00f1o completo. El edificio cuenta con detalles de terminaci\u00f3n y ofrece diversos amenities, como un sum, una pileta y un solarium. La ubicaci\u00f3n del departamento es excelente, en R\u00edo de Janeiro al 1000, entre Avda. Angel Gallardo y Sarmiento, a una cuadra de Av. Corrientes. Adem\u00e1s, se encuentra a 2 cuadras del Parque Centenario y cerca de la estaci\u00f3n de subte B Angel Gallardo, as\u00ed como de diversas paradas de colectivos y comercios. Pida tasaci\u00f3n: Efectuada por profesionales, que analizan permanentemente el desenvolvimiento del mercado. Conf\u00ede su patrimonio en una empresa s\u00f3lida con respaldo y prestigio. Conf\u00ede en el L\u00edder. Goldstein propiedades. Se deja constancia que los m2 son aproximados, al igual que las medidas parciales y el valor consignado de las expensas mensuales (en caso que corresponda pago de expensas) y las caracter\u00edsticas est\u00e1n sujetos a verificaci\u00f3n y/o ajustes, el precio del inmueble puede ser modificado sin previo aviso. En el caso de tratarse de un inmueble en construcci\u00f3n los detalles de terminaci\u00f3n y la fecha de entrega est\u00e1n sujetos a revisi\u00f3n. Fotos de car\u00e1cter no contractual. Las unidades publicadas est\u00e1n sujetas a disponibilidad. Goldstein Propiedades srl con domicilio en Avda. Corrientes 4666 act\u00faa solamente en car\u00e1cter de comercializadora de los inmuebles ofrecidos. En caso de tratarse de un terreno, la informaci\u00f3n de m2 construibles y plusval\u00eda es orientativa, debiendo ser constatada por el interesado. Inmueble no accesible para personas con discapacidad f\u00edsica ley 5115. Cucicba matr\u00edcula 37. Cmcpsi matr\u00edcula 6003. \u00danicamente en el caso de tratarse de alquiler de vivienda familiar, rige lo indicado en la ley 5859. Venta supeditada al cumplimiento por parte del propietario de los requisitos de la resoluci\u00f3n general N\u00ba 2371 de la afip (pedido de coti).\nPublicado hace 8 d\u00edas\nContactar", "revised": false, "rejected": true, "data": {"precio": "$ 750.000", "expensas": "$ 129.000 Expensas", "direccion": "R\u00edo de Janeiro al 1000", "metros": "64 m\u00b2 tot.", "habitaciones": "3 amb.", "hace": "Publicado hace 8 d\u00edas"}}, "https://www.zonaprop.com.ar/propiedades/clasificado/alclphin-villa-crespo-ph-espectacular-3-amb-terraza-propia-53539335.html": {"date": "05-05-2024\n", "content": "$ 680.000\nVICENTE CAMARGO 266\nVilla Crespo, Capital Federal\n140 m\u00b2 tot.\n3 amb.\n2 dorm.\n1 ba\u00f1o\nVilla crespo/parque centenario: 3 ambientes depto tipo casa ph en planta baja entrada por pasillo camargo Y julian alvarez A mts del parque centenario lindo living comedor 4, 50 X 4, 50 mts dos dormitorios con placard dos patios cubiertos con toldo met\u00e1lico cocina amplia con comedor diario ba\u00f1o completo - terraza propia muy grande parrilla Y quincho en terraza sin expensas rodeado de avenidas angel gallardo - warnes - corrientes Y raul scalabrini ortiz - cerca de estaciones subte B zona muy lina barrio residencial. - cel Ver datos jaime \u00d3 Ver datos silvia\nPublicado hace 8 d\u00edas\nContactar", "revised": false, "rejected": true, "data": {"precio": "$ 680.000", "direccion": "VICENTE CAMARGO 266", "metros": "140 m\u00b2 tot.", "habitaciones": "3 amb.", "hace": "Publicado hace 8 d\u00edas"}}, "https://www.zonaprop.com.ar/propiedades/clasificado/alclapin-departamento-de-4-ambientes-en-alquiler-en-almagro-53539310.html": {"date": "05-05-2024\n", "content": "16\n$ 550.000\n$ 90.000 Expensas\nSARMIENTO 4300\nAlmagro, Capital Federal\n100 m\u00b2 tot.\n4 amb.\n3 dorm.\n3 ba\u00f1os\nDepartamento de 4 ambientes con dependencia, en alquiler. Al frente, con balcon. Luminoso. Semipiso. Muy buena superficie. Cerca avdas. Corrientes, medrano, diaz velez. Subte, colectivos. Parque centenario, hospital italiano. Comercializa Migliorisi de Corrientes 4599 srl Profesional responsable Jorge Daniel Gomez cpi 261. Ver datos Se deja constancia que las caracteristicas, medidas, expensas y superficies consignadas son aproximadas, sujetos a verificaci\u00f3n y/o ajuste. El precio del inmueble puede ser modificado sin previo aviso. Fotos de car\u00e1cter no contractual. Las unidades publicadas est\u00e1n sujetas a disponibilidad. . Publicado por Migliorisi Almagro a traves de Inmomap\nPublicado hace 8 d\u00edas\nContactar", "revised": false, "rejected": true, "data": {"precio": "$ 550.000", "expensas": "$ 90.000 Expensas", "direccion": "SARMIENTO 4300", "metros": "100 m\u00b2 tot.", "habitaciones": "4 amb.", "hace": "Publicado hace 8 d\u00edas"}}, "https://www.zonaprop.com.ar/propiedades/clasificado/alclappa-once-4amb-frente-dueno-av-corrientes-esq.-paso-53540355.html": {"date": "05-05-2024\n", "content": "12\n$ 450.000\n$ 76.700 Expensas\nAv. Corrientes 2601\nOnce, Capital Federal\n92 m\u00b2 tot.\n4 amb.\n3 dorm.\n3 ba\u00f1os\nAv. Corrientes al 2600 esquina Paso 422, a una cuadra de la Avda. Pueyrred\u00f3n y el cruce del Subte B (Estaci\u00f3n Pueyrred\u00f3n) y del Subte H (Estaci\u00f3n Corrientes). Departamento de 4 amb. Todos al frente en 7mo piso; Dos entradas, doble circulaci\u00f3n, hall de recepci\u00f3n, Living Comedor, Dormitorios con placard, todos a la calle con ventanales sobre Paso al 400. Ba\u00f1o Completo, Toilette y ba\u00f1o de servicio, Cocina amplia con lavadero Incorporado. Tel\u00e9fono. Apto a Profesional. Expensas Vigentes: $76. 700 por mes. Abl $5. 500 por mes; Aysa $6. 700 por mes. Para Ingresar, primer mes de alquiler y un mes de dep\u00f3sito. Garant\u00eda propietaria en Capital Federal. Contrato por dos a\u00f1os; el valor del alquiler se ajusta trimestralmente por ipc. Para visitar, puede llamar o escribir. Gracias.\nPublicado hace 8 d\u00edas\nContactar", "revised": false, "rejected": true, "data": {"precio": "$ 450.000", "expensas": "$ 76.700 Expensas", "direccion": "Av. Corrientes 2601", "metros": "92 m\u00b2 tot.", "habitaciones": "4 amb.", "hace": "Contactar"}}, "https://www.zonaprop.com.ar/propiedades/clasificado/alclapin-departamento-en-barrio-norte-53531188.html": {"date": "05-05-2024\n", "content": "$ 650.000\n$ 150.000 Expensas\nJunin al 1300\nBarrio Norte, Capital Federal\n90 m\u00b2 tot.\n4 amb.\n3 dorm.\n2 ba\u00f1os\nSemi piso en alquiler en Recoleta. Consta de palier semi privado, hall de distribuci\u00f3n, living comedor, balc\u00f3n corrido, 3 dormitorios con amplios placares, ba\u00f1o completo y toilette, cocina con lavadero. Requiere reparaci\u00f3n de alba\u00f1iler\u00eda y pintura. Esta ubicado en Junin al 1300 entre Pe\u00f1a y French, proximo a Avda. Pueyrred\u00f3n, Avda. Las Heras, Avda. Callao, colectivos, subte, comercios. Pida tasaci\u00f3n: Efectuada por profesionales, que analizan permanentemente el desenvolvimiento del mercado. Conf\u00ede su patrimonio en una empresa s\u00f3lida con respaldo y prestigio. Conf\u00ede en el L\u00edder. Goldstein propiedades. Se deja constancia que los m2 son aproximados, al igual que las medidas parciales y el valor consignado de las expensas mensuales (en caso que corresponda pago de expensas) y las caracter\u00edsticas est\u00e1n sujetos a verificaci\u00f3n y/o ajustes, el precio del inmueble puede ser modificado sin previo aviso. En el caso de tratarse de un inmueble en construcci\u00f3n los detalles de terminaci\u00f3n y la fecha de entrega est\u00e1n sujetos a revisi\u00f3n. Fotos de car\u00e1cter no contractual. Las unidades publicadas est\u00e1n sujetas a disponibilidad. Goldstein Propiedades srl con domicilio en Avda. Corrientes 4666 act\u00faa solamente en car\u00e1cter de comercializadora de los inmuebles ofrecidos. En caso de tratarse de un terreno, la informaci\u00f3n de m2 construibles y plusval\u00eda es orientativa, debiendo ser constatada por el interesado. Inmueble no accesible para personas con discapacidad f\u00edsica ley 5115. Cucicba matr\u00edcula 37. Cmcpsi matr\u00edcula 6003. \u00danicamente en el caso de tratarse de alquiler de vivienda familiar, rige lo indicado en la ley 5859. Venta supeditada al cumplimiento por parte del propietario de los requisitos de la resoluci\u00f3n general N\u00ba 2371 de la afip (pedido de coti).\nSuper destacado\nPublicado hace 9 d\u00edas\nContactar", "revised": false, "rejected": true, "data": {"precio": "$ 650.000", "expensas": "$ 150.000 Expensas", "direccion": "Junin al 1300", "metros": "90 m\u00b2 tot.", "habitaciones": "4 amb.", "hace": "Super destacado\nPublicado hace 9 d\u00edas"}}, "https://www.zonaprop.com.ar/propiedades/clasificado/alclocin-alquiler-oficina-recoleta-53531576.html": {"date": "05-05-2024\n", "content": "$ 550.000\n$ 1 Expensas\nAlquiler Oficina Recoleta\nBarrio Norte, Capital Federal\n70 m\u00b2 tot.\n4 amb.\n3 dorm.\n1 ba\u00f1o\nLocal en arenales 1237, galeria rue des artisans. muy luminoso cuenta con 3 despachos, un ba\u00f1o completo, una baulera O lugar de deposito. cocina con office, Y el piso es de pinotea. -esta en excelentes condiciones para ingresar. - cmpsi 6021/cucicba 6999 mariana lamborizio\nPublicado hace 9 d\u00edas\nContactar", "revised": false, "rejected": true, "data": {"precio": "$ 550.000", "expensas": "$ 1 Expensas", "direccion": "Alquiler Oficina Recoleta", "metros": "70 m\u00b2 tot.", "habitaciones": "4 amb.", "hace": "Publicado hace 9 d\u00edas"}}, "https://www.zonaprop.com.ar/propiedades/clasificado/alclapin-almagro-caballito-alquiler-sin-muebles-tres-53537590.html": {"date": "05-05-2024\n", "content": "$ 500.000\n$ 30.000 Expensas\nLEZICA 4300\nAlmagro, Capital Federal\n65 m\u00b2 tot.\n3 amb.\n2 dorm.\n1 ba\u00f1o\n* excelente ubicacion A una cuadra de av. Rivadavia cerca subte A metrobus tren etc. * departamento de tres ambientes contrafrente primer piso por escalera. * bajas expensas. * techos altos Y amplios ventanales. * dos amplios dormitorios con grandes placares. * ba\u00f1o Y cocina completa. * conexion para lavarropas\nPublicado desde ayer\nContactar", "revised": false, "rejected": true, "data": {"precio": "$ 500.000", "expensas": "$ 30.000 Expensas", "direccion": "LEZICA 4300", "metros": "65 m\u00b2 tot.", "habitaciones": "3 amb.", "hace": "Publicado desde ayer"}}, "https://www.zonaprop.com.ar/propiedades/clasificado/alclapin-3-amb-de-categoria-en-piso-alto-cochera-fija-cubierta-53535830.html": {"date": "05-05-2024\n", "content": "$ 750.000\n$ 150.000 Expensas\nM t alvear 1342\nBarrio Norte, Capital Federal\n87 m\u00b2 tot.\n3 amb.\n2 dorm.\n1 ba\u00f1o\n1 coch.\nExcelente departamento de 3 ambientes. Se alquila con o sin muebles. Edificio de categor\u00eda. Seguridad las 24 hs. Amenities: sum, cancha de squash, parrilla, sauna, gimnasio y salon de juegos para ni\u00f1os. Grupo electr\u00f3geno. Piso Alto. Vista al r\u00edo. Pallier privado. Luz y sol en todos los ambientes. Cocina comedor. schwartz estudio inmobiliario. J. Alvarez 2410 caba - 1425. 48 21 - 22 00 w w w. S c h w a r t z. C o m. A r. ii5060. 6378Whatsapp. Art. 4\u00b0 - Hacer constar en todo ofrecimiento publicitario de locaci\u00f3n de inmuebles con destino habitacional que se emita v\u00eda p\u00e1ginas web, propias o de terceros, la siguiente leyenda: \"Para los casos de alquiler de vivienda, el monto m\u00e1ximo de comisi\u00f3n que se le puede requerir a los propietarios ser\u00e1 el equivalente al cuatro con quince cent\u00e9simos por ciento (4, 15%) del valor total del respectivo contrato. Se encuentra prohibido cobrar a los inquilinos que sean personas f\u00edsicas comisiones inmobiliarias y gastos de gestor\u00eda de informes \" (incorporado como inciso 8 del art\u00edculo 10 de la Ley 2340). Accesibilidad: Se puede recorrer desde la vereda hasta el ascensor por tramos horizontales o por rampa con anchos adecuados, luego en forma vertical por ascensor que tiene dimensiones adecuadas para circular con sillas de ruedas y luego hasta la propiedad por pasillo con ancho adecuado tambi\u00e9n. Matricula cucicba N\u00ba579 F\u00ba23 L1\nPublicado hace 9 d\u00edas\nContactar", "revised": false, "rejected": true, "data": {"precio": "$ 750.000", "expensas": "$ 150.000 Expensas", "direccion": "M t alvear 1342", "metros": "87 m\u00b2 tot.", "habitaciones": "3 amb.", "hace": "Publicado hace 9 d\u00edas"}}, "https://www.zonaprop.com.ar/propiedades/clasificado/alclapin-hermoso-depto-3-ambientes-al-frente-cocina-separada-53533648.html": {"date": "05-05-2024\n", "content": "$ 499.999\n$ 36.200 Expensas\nVera 132\nVilla Crespo, Capital Federal\n65 m\u00b2 tot.\n3 amb.\n2 dorm.\n1 ba\u00f1o\nExcelente depto de 3 ambientes, super luminoso, balcon corrido al frente, cocina seprada, y ba\u00f1o, living y habitacion principal dan al frente. Cerca de todo. A 100 metros de Av corrientes y estacion B Del subte. A 200 metros Parque Centenario. Se muestra y esta disponible para su ingreso a partir del 1-5-24. Contactar x whatsapp\nPublicado hace 9 d\u00edas\nContactar", "revised": false, "rejected": true, "data": {"precio": "$ 499.999", "expensas": "$ 36.200 Expensas", "direccion": "Vera 132", "metros": "65 m\u00b2 tot.", "habitaciones": "3 amb.", "hace": "Publicado hace 9 d\u00edas"}}, "https://www.zonaprop.com.ar/propiedades/clasificado/alclapin-departamento-en-san-cristobal-53523043.html": {"date": "05-05-2024\n", "content": "23\n$ 700.000\n$ 49.000 Expensas\nJujuy Av. al 1100\nSan Cristobal, Capital Federal\n87 m\u00b2 tot.\n4 amb.\n3 dorm.\n1 ba\u00f1o\nAmplio departamento de 4 ambientes contrafrente con balc\u00f3n. Consta de living comedor, balc\u00f3n corrido, 3 dormitorios con placards, ba\u00f1o completo, cocina completa, lavadero cubierto. Es muy luminoso y funcional. Esta ubicado en Avda. Jujuy al 1100, entre Humberto I y Avda. San Juan, colectivos, subte E, comercios. Pida tasaci\u00f3n: Efectuada por profesionales, que analizan permanentemente el desenvolvimiento del mercado. Conf\u00ede su patrimonio en una empresa s\u00f3lida con respaldo y prestigio. Conf\u00ede en el L\u00edder. Goldstein propiedades. Se deja constancia que los m2 son aproximados, al igual que las medidas parciales y el valor consignado de las expensas mensuales (en caso que corresponda pago de expensas) y las caracter\u00edsticas est\u00e1n sujetos a verificaci\u00f3n y/o ajustes, el precio del inmueble puede ser modificado sin previo aviso. En el caso de tratarse de un inmueble en construcci\u00f3n los detalles de terminaci\u00f3n y la fecha de entrega est\u00e1n sujetos a revisi\u00f3n. Fotos de car\u00e1cter no contractual. Las unidades publicadas est\u00e1n sujetas a disponibilidad. Goldstein Propiedades srl con domicilio en Avda. Corrientes 4666 act\u00faa solamente en car\u00e1cter de comercializadora de los inmuebles ofrecidos. En caso de tratarse de un terreno, la informaci\u00f3n de m2 construibles y plusval\u00eda es orientativa, debiendo ser constatada por el interesado. Inmueble no accesible para personas con discapacidad f\u00edsica ley 5115. Cucicba matr\u00edcula 37. Cmcpsi matr\u00edcula 6003. \u00danicamente en el caso de tratarse de alquiler de vivienda familiar, rige lo indicado en la ley 5859. Venta supeditada al cumplimiento por parte del propietario de los requisitos de la resoluci\u00f3n general N\u00ba 2371 de la afip (pedido de coti).\nDestacado\nPublicado hace 10 d\u00edas\nContactar", "revised": false, "rejected": true, "data": {"precio": "$ 700.000", "expensas": "$ 49.000 Expensas", "direccion": "Jujuy Av. al 1100", "metros": "87 m\u00b2 tot.", "habitaciones": "4 amb.", "hace": "Destacado\nPublicado hace 10 d\u00edas"}}, "https://www.zonaprop.com.ar/propiedades/clasificado/alclapin-departamento-de-3-amb-av-cordoba-y-armenia-villa-53525898.html": {"date": "05-05-2024\n", "content": "$ 570.000\n5%\n$ 20.000 Expensas\nVilla Crespo, Capital Federal\n60 m\u00b2 tot.\n3 amb.\n2 dorm.\n1 ba\u00f1o\nDepartamento primer piso por escalera al frente con balcon frances. buen estado. Dormitorio con placard. ba\u00f1o completo y toilette de servicio. Cocina completa con salida a patio cucbierto con toldo. Espacio de lavadero. Pisos de parquet\nDestacado\nPublicado hace 10 d\u00edas\nContactar", "revised": false, "rejected": true, "data": {"precio": "$ 570.000", "expensas": "$ 20.000 Expensas", "direccion": "", "metros": "60 m\u00b2 tot.", "habitaciones": "3 amb.", "hace": "Destacado\nPublicado hace 10 d\u00edas"}}, "https://www.zonaprop.com.ar/propiedades/clasificado/alcllcin-alquiler-local-recoleta-53523997.html": {"date": "05-05-2024\n", "content": "$ 550.000\n$ 1 Expensas\nAlquiler Local Recoleta\nBarrio Norte, Capital Federal\n70 m\u00b2 tot.\n4 amb.\n3 dorm.\n1 ba\u00f1o\nLocal en arenales 1237, galeria rue des artisans. muy luminoso cuenta con 3 despachos, un ba\u00f1o completo, una baulera O lugar de deposito. cocina con office, Y el piso es de pinotea. -esta en excelentes condiciones para ingresar. - cmpsi 6021/cucicba 6999 mariana lamborizio\nPublicado hace 10 d\u00edas\nContactar", "revised": false, "rejected": true, "data": {"precio": "$ 550.000", "expensas": "$ 1 Expensas", "direccion": "Alquiler Local Recoleta", "metros": "70 m\u00b2 tot.", "habitaciones": "4 amb.", "hace": "Publicado hace 10 d\u00edas"}}, "https://www.zonaprop.com.ar/propiedades/clasificado/alclapin-departamento-3-amb.-en-alquiler-boedo-capital-53525066.html": {"date": "05-05-2024\n", "content": "$ 450.000\n$ 73.000 Expensas\nCarlos Calvo\nBoedo, Capital Federal\n60 m\u00b2 tot.\n3 amb.\n2 dorm.\n1 ba\u00f1o\n1 coch.\nC. A. B. aboedo*disponible A partir de 3/5/24*Departamento de tres ambientes con cocina, living comedor, dos habitaciones, una con aire acondicionado fr\u00edo calor y pisos de madera, la otra alfombrada. Placares empotrados en ambas habitaciones. Cochera cubierta y balc\u00f3n, rampa de acceso para discapacitados y grupo electr\u00f3geno en edificio. Ref. 2485- Todas las propiedades que figuran en esta publicaci\u00f3n se encuentran a cargo de los profesionales matriculados comarcomgr N\u00b071 / N\u00b0183 | C. U. C. I. C. B. A N\u00b08496, por lo tanto la intermediaci\u00f3n y la conclusi\u00f3n de las operaciones ser\u00e1n llevadas exclusivamente por los mismos. Todas las medidas son aproximadas al solo efecto orientativo. Las fotograf\u00edas y videos no son contractuales. En cumplimiento de la ley 10. 973 de la Provincia de Buenos Aires, Ley Nacional 25. 028, Ley Nacional 20. 266, Ley 22. 802 de Lealtad Comercial, Ley 24. 240 de Defensa al Consumidor, las normas del C\u00f3digo Civil y Comercial de la Naci\u00f3n y Constitucionales, los asesores, agentes o promotores no ejercen el corretaje inmobiliario. Todas las operaciones inmobiliarias son objeto de intermediaci\u00f3n y conclusi\u00f3n por parte de los martilleros y corredores colegiados. ramirez Mandatos y Negocios Inmobiliarios. comarcomgr N\u00b071 / N\u00b0183 (Hipolito Enrique Ramirez / Carolina Noelia Ramirez) C. U. C. I. C. B. A N\u00b08496 (Hipolito Agustin Alejo Ramirez)\nPublicado hace 10 d\u00edas\nContactar", "revised": false, "rejected": true, "data": {"precio": "$ 450.000", "expensas": "$ 73.000 Expensas", "direccion": "Carlos Calvo", "metros": "60 m\u00b2 tot.", "habitaciones": "3 amb.", "hace": "Publicado hace 10 d\u00edas"}}, "https://www.zonaprop.com.ar/propiedades/clasificado/alclapin-ayacucho-1500-cochera-depcia.-2-banos-balcon-53522518.html": {"date": "05-05-2024\n", "content": "$ 700.000\n$ 190.000 Expensas\nBarrio Norte, Capital Federal\n95 m\u00b2 tot.\n4 amb.\n3 dorm.\n1 ba\u00f1o\n1 coch.\nDepto. Amplio de 3 dormitorios mas dependencia - ba\u00f1o Y toilete - cochera - balcon - lavadero - excelente ubicacion zona universidades - acepta seguro de caucion que gestionamos nosotros mismos - hay video de la unidad. Consultas por whatsapp. Sr. Gustavo Ver datos.\nPublicado hace 10 d\u00edas\nContactar", "revised": false, "rejected": true, "data": {"precio": "$ 700.000", "expensas": "$ 190.000 Expensas", "direccion": "", "metros": "95 m\u00b2 tot.", "habitaciones": "4 amb.", "hace": "Publicado hace 10 d\u00edas"}}, "https://www.zonaprop.com.ar/propiedades/clasificado/alclapin-departamento-congreso-53530726.html": {"date": "05-05-2024\n", "content": "$ 450.000\n$ 110.000 Expensas\nIndependencia al 1800\nCongreso, Capital Federal\n105 m\u00b2 tot.\n3 amb.\n2 dorm.\n2 ba\u00f1os\nAlquiler! Amplio y c\u00f3modo Depto de 3 ambientes mas escritorio y dependencia de servicioAl frente con balc\u00f3n, mucha luz! 2 dormitorios con c\u00f3modos placards caja de seguridad empotrada. 1 ba\u00f1o completo m\u00e1s ba\u00f1o de servicioAmplio living comedor, cocina con comedor de diario y lavadero. Escritorio - Pisos plastificados de pinotea. Split, calefacci\u00f3n centralizada. Cuenta con parqueen pb de uso com\u00fan, quinchos y parrilla! No se aceptan mascotas. ContactoInformes y visitasVer datos Ver datos / Ver datosYacopino Barrio Nortecucicba 5810La unidad no es apta para personas con movilidad reducida. Yacopino InmobiliariasMas de 95 a\u00f1os de Honestidad Profesional\nPublicado hace 9 d\u00edas\nContactar", "revised": true, "rejected": true, "data": {"precio": "$ 450.000", "expensas": "$ 110.000 Expensas", "direccion": "Independencia al 1800", "metros": "105 m\u00b2 tot.", "habitaciones": "3 amb.", "hace": "Contactar"}, "comment": "Cerca de entre r\u00edos. Medio fiero. Jardin com\u00fan. Balcon y dependencia "}, "https://www.zonaprop.com.ar/propiedades/clasificado/alclapin-larrea-al-700-3-amb-c-dep-y-balcon-facultad-53527500.html": {"date": "05-05-2024\n", "content": "$ 650.000\n$ 180.000 Expensas\nLarrea al 700\nBalvanera, Capital Federal\n86 m\u00b2 tot.\n4 amb.\n3 dorm.\n1 ba\u00f1o\nDepartamento de 4 amb c/balc\u00f3nContrafrenteSemi-pisoMuy luminosoEncargado diurno Seguridad NocturnaPalier semi-privadoLiving-comedor con Aire acondicionadoBalc\u00f3n al contrafrenteDormitorio con placard Dormitorio con placardDormitorio con placardAmplia Cocina Completa A nuevacomedor diarioCocina el\u00e9ctrica vitrocer\u00e1mica A nuevohorno el\u00e9ctrico A nuevotermotanque a gasLavadero Ba\u00f1o completoToilette\nPublicado hace 10 d\u00edas\nContactar", "revised": false, "rejected": true, "data": {"precio": "$ 650.000", "expensas": "$ 180.000 Expensas", "direccion": "Larrea al 700", "metros": "86 m\u00b2 tot.", "habitaciones": "4 amb.", "hace": "Publicado hace 10 d\u00edas"}}, "https://www.zonaprop.com.ar/propiedades/clasificado/alclapin-departamento-3-ambientes-frente-balcon-super-luminoso-53524870.html": {"date": "05-05-2024\n", "content": "$ 460.000\n$ 57.000 Expensas\nBULNES 32\nAlmagro, Capital Federal\n60 m\u00b2 tot.\n3 amb.\n2 dorm.\n1 ba\u00f1o\nDepartamento de 3 ambientes semipiso al frente, balcon, super luminoso, cocina comedor diario, lavadero independiente, dormitorios con sus respectivos placares, ba\u00f1o completo, excelente estado Y ubicacion, bulnes 32 A metros de av rivadavia subte A estacion castro barros consulte.. Ver datos adrian\nPublicado hace 10 d\u00edas\nContactar", "revised": true, "rejected": false, "data": {"precio": "$ 460.000", "expensas": "$ 57.000 Expensas", "direccion": "BULNES 32", "metros": "60 m\u00b2 tot.", "habitaciones": "3 amb.", "hace": "Publicado hace 10 d\u00edas"}, "comment": "Buena cocina . Balc\u00f3n. C\u00f3mo casa"}, "https://www.zonaprop.com.ar/propiedades/clasificado/alclapin-hermoso-y-amplio-departamento-en-san-jose-y-belgrano-53582801.html": {"date": "06-05-2024\n", "index": 36, "content": "$ 500.000\n$ 80.000 Expensas\nSAN JOSE 300\nSan Nicol\u00e1s, Capital Federal\n100 m\u00b2 tot.\n3 amb.\n2 dorm.\n1 ba\u00f1o\nSemipiso al frente en edificio de estilo. living Y comedor con pisos de pinotea al frente con balcon frances. escritorio O dormitorio. hall destribuidor. dos habitaciones comodas. amplio placard en pasillo. ba\u00f1o completo con ventilacion. cocina con comedor diario con lavavajillas refaccionado. dependencia con ba\u00f1o. todo en excelente estado. servicios individuales. se requiere sin excepcion garantia caba O finaer Y constancias de ingresos demostrables. contrato con ajuste trimestral\nPublicado hoy\nContactar", "revised": true, "rejected": false, "data": {"precio": "$ 500.000", "expensas": "$ 80.000 Expensas", "direccion": "SAN JOSE 300", "metros": "100 m\u00b2 tot.", "habitaciones": "3 amb.", "hace": "Contactar"}, "image": "https://imgar.zonapropcdn.com/avisos/1/00/53/58/28/01/360x266/1909591447.jpg?isFirstImage=true", "title": "Departamento de 3 ambientes, San Nicol\u00e1s \u00b7 Hermoso y Amplio Departamento en San Jose y Belgrano 100 m de Estilo", "comment": "Sin balc\u00f3n. Grande"}, "https://www.zonaprop.com.ar/propiedades/clasificado/alclapin-av-del-libertador-250-departamento-retiro-53582654.html": {"date": "06-05-2024\n", "index": 37, "content": "$ 650.000\n$ 170.000 Expensas\ndel Libertador al 200\nBarrio Norte, Capital Federal\n85 m\u00b2 tot.\n4 amb.\n3 dorm.\n1 ba\u00f1o\n1 coch.\nRetiro - alquiler Av. Del Libertador 250 piso 7moEntre Esmeralda y Basavilbaso4 Amb con Dependencia y cochera - FrenteSuperficie cubierta: 85m\u00b2Superficie total: 85m\u00b2Plantas: 1Cantidad Ba\u00f1os: 2Balc\u00f3n: FrancesLavadero: SiCochera: sidependencia: SiCantidad Deptos x Piso: 4Cantidad Pisos Edificio: 20cochera Y dependencia. Zarlenga Inmobiliaria - Matricula: 7057 - aviso legal: Las descripciones arquitect\u00f3nicas y funcionales, valores de expensas, impuestos y servicios, fotos y medidas de este inmueble son aproximados. Los datos fueron proporcionados por el propietario y pueden no estar actualizados a la hora de la visualizaci\u00f3n de este aviso por lo cual pueden arrojar inexactitudes y discordancias con las que surgen de las facturas, t\u00ed\u00adtulos y planos legales del inmueble. El interesado deber\u00e1 realizar las verificaciones respectivas previamente a la realizaci\u00f3n de cualquier operaci\u00c3\u00b3n, requiriendo por s\u00fa\u00ad o sus profesionales las copias necesarias de la documentaci\u00f3n que corresponda. Venta supeditada al cumplimiento por parte del propietario de los requisitos de la resoluci\u00f3n general Nro. 2371 de la afip (pedido de coti).\nPublicado desde ayer\nContactar", "revised": false, "rejected": true, "data": {"precio": "$ 650.000", "expensas": "$ 170.000 Expensas", "direccion": "del Libertador al 200", "metros": "85 m\u00b2 tot.", "habitaciones": "4 amb.", "hace": "Contactar"}, "image": "https://imgar.zonapropcdn.com/avisos/1/00/53/58/26/54/360x266/1909588496.jpg?isFirstImage=true", "title": "Departamento \u00b7 85m\u00b2 \u00b7 4 Ambientes \u00b7 1 Cochera \u00b7 Av del Libertador 250 - Departamento - Retiro"}, "https://www.zonaprop.com.ar/propiedades/clasificado/alclapin-excelente-depto-de-3-ambientes-con-quincho-balcon-53584890.html": {"date": "06-05-2024\n", "index": 8, "content": "$ 510.000\n$ 60.000 Expensas\nQuintino bocayuva 1097\nBoedo, Capital Federal\n76 m\u00b2 tot.\n3 amb.\n2 dorm.\n1 ba\u00f1o\nExcelente departamento de 3 amientes. Se ingresa a un living comedor el cual tiene salida a un balcon aterrazado cubierto que sirve como jardin de invierno. Cocina apaisada con muebles completos y salida al lavadero cubierto. 2 dormitorios con placard. Ba\u00f1o completo. Balcon aterrazado descubierto y quincho cubierto con parrilla! Todo luz y ventilacion. Al frente! Buen estado general. Se alquila sin mascotas. Aceptamos seguro de caucion finaer.\nDestacado\nPublicado hoy\nContactar", "revised": false, "rejected": true, "data": {"precio": "$ 510.000", "expensas": "$ 60.000 Expensas", "direccion": "Quintino bocayuva 1097", "metros": "76 m\u00b2 tot.", "habitaciones": "3 amb.", "hace": "Contactar"}, "image": "https://imgar.zonapropcdn.com/avisos/1/00/53/58/48/90/360x266/1909639861.jpg?isFirstImage=true", "title": "Departamento de 3 ambientes, Boedo \u00b7 Excelente Depto de 3 Ambientes con Quincho, Balcon Aterrazado y Excelente Luz!"}, "https://www.zonaprop.com.ar/propiedades/clasificado/alclapin-3amb-al-frente-con-balcon-en-plena-av-garay!-vista-53584578.html": {"date": "06-05-2024\n", "index": 29, "content": "$ 400.000\n$ 80.000 Expensas\nAv. Garay al 2200\nSan Cristobal, Capital Federal\n65 m\u00b2 tot.\n3 amb.\n2 dorm.\n1 ba\u00f1o\nDepartamento de 3 ambientes en torre con sum y PiletaAv. Garay entre Pichincha y Pasco. Piso alto con vista abierta, balc\u00f3n y luz natural. Asimismo, posee una amplia cocina con lavadero incorporado y placard en dormitorios. Excelente estado de conservaci\u00f3n. Transportes CercanosColectivos: 4, 6, 8, 12, 37, 46, 50, 53, 56, 57, 61, 62, 84, 86, 90, 91, 95, 96, 97, 118, 129, 133, 143, 150, 151, 188, 195Adriana Gentile Propiedades le brinda a sus clientes la posibilidad de una financiaci\u00f3n del 50% de la propiedad y el resto hasta en 84 cuotas igual al 1. 2% mensual.\nPublicado hoy\nContactar", "revised": false, "rejected": true, "data": {"precio": "$ 400.000", "expensas": "$ 80.000 Expensas", "direccion": "Av. Garay al 2200", "metros": "65 m\u00b2 tot.", "habitaciones": "3 amb.", "hace": "Contactar"}, "image": "https://imgar.zonapropcdn.com/avisos/1/00/53/58/45/78/360x266/1909630962.jpg?isFirstImage=true", "title": "Departamento \u00b7 65m\u00b2 \u00b7 3 Ambientes \u00b7 3amb Al Frente con Balcon en Plena Av Garay! Vista Abierta y Pura Luz"}, "https://www.zonaprop.com.ar/propiedades/clasificado/alclapin-monserrat-4-ambientes-bano-toillette-interno-53585883.html": {"date": "06-05-2024\n", "index": 11, "content": "$ 500.000\n$ 35.000 Expensas\nHipolito Yrigoyen al 2500\nMonserrat, Capital Federal\n75 m\u00b2 tot.\n4 amb.\n2 dorm.\n1 ba\u00f1o\nMonserrat 4 ambientes ba\u00f1O toillette interno, igualmente luminoso no tiene balcon, amplia cocina. Sup total 75 M2Queda una heladera y un placard. La vista del patio que se ve en fotos es el camino que hay que cruzar para ir el al segundo cuerpo del edificio que es donde se encuentra el departamento. No paga Expensas ya que es Edificio Patrimonial Con bella arquitectura. Incremento Cuatrimestral por ipc **Corredor Inmobiliario Responsable Adrian Ridelnik cucicba Mat 197. *Se deja constancia que las medidas y superficies indicados son aproximados y al s\u00f3lo efecto orientativo. Las medidas reales surgir\u00e1n del t\u00edtulo de propiedad respectivo. Las medidas parciales y/o de los ambientes y el valor consignado de expensas mensuales, servicios y abl est\u00e1 sujeto a verificaci\u00f3n y/o ajuste. Art. 4 de la Ley 5. 859 de C. A. B. A \"Para los casos de alquiler de vivienda \u00fanica, el monto m\u00e1ximo de comisi\u00f3n que se le puede requerir a los propietarios ser\u00e1 el equivalente al cuatro con quince cent\u00e9simos por ciento (4, 15%) del valor total del respectivo contrato. Se encuentra prohibido cobrar a los inquilinos que sean personas f\u00edsicas comisiones inmobiliarias cuando el destino sea vivienda \u00fanica y permanente \". -\nPublicado hoy\nContactar", "revised": true, "rejected": false, "data": {"precio": "$ 500.000", "expensas": "$ 35.000 Expensas", "direccion": "Hipolito Yrigoyen al 2500", "metros": "75 m\u00b2 tot.", "habitaciones": "4 amb.", "hace": "Contactar"}, "image": "https://imgar.zonapropcdn.com/avisos/1/00/53/58/58/83/360x266/1909658948.jpg?isFirstImage=true", "title": "Departamento \u00b7 75m\u00b2 \u00b7 4 Ambientes \u00b7 Monserrat 4 Ambientes Ba\u00f1o Toillette Interno, Igualmente Luminoso No Tiene Balcon", "comment": "Viejo. Grande. Luminoso"}, "https://www.zonaprop.com.ar/propiedades/clasificado/alclapin-hermoso-dpto-3-amb-y-dependencia-super-luminoso-53523598.html": {"date": "06-05-2024\n", "content": "$ 600.000\n$ 75.000 Expensas\nJuan Ramirez de Velazco 115\nVilla Crespo, Capital Federal\n116 m\u00b2 tot.\n3 amb.\n4 dorm.\n1 ba\u00f1o\nHermoso dpto 3 amb y dependencia / Super luminoso / Juan Ram\u00edrez de Velazco 115. Inmejorable ubicaci\u00f3n ( metros de Av. Corrientes y Angel Gallardo, tres cuadras Parque Centenario, metros subte) consultas ser\u00e1n respondidas exclusivamente de lunes A viernes de 10 A 19 hrs; sin excepci\u00f3n. Pisos parquet, cocina comedor, amplios ambientes con placares, living con biblioteca, balc\u00f3n al contra frente, aire acondicionado, habitaci\u00f3n de servicio con toilette, ba\u00f1o completo. se exige garant\u00eda de caba E ingresos comprobables. Contrato de locaci\u00f3n por dos a\u00f1os con aumentos \u00edndice ipc\nPublicado hace 11 d\u00edas\nContactar", "revised": true, "rejected": false, "data": {"precio": "$ 600.000", "expensas": "$ 75.000 Expensas", "direccion": "Juan Ramirez de Velazco 115", "metros": "116 m\u00b2 tot.", "habitaciones": "3 amb.", "hace": "Contactar"}, "comment": "caro"}, "https://www.zonaprop.com.ar/propiedades/clasificado/alclapin-departamento-3-ambientes-con-dependencias-al-frente-53591831.html": {"date": "06-05-2024\n", "index": 1, "content": "15\n$ 600.000\n$ 45.000 Expensas\nSarmiento al 4600\nAlmagro, Capital Federal\n75 m\u00b2 tot.\n3 amb.\n2 dorm.\n1 ba\u00f1o\nSemipiso de 3 ambientes con dependencias al frente, con aire luz y sol. Consta de living comedor, balc\u00f3n corrido, 2 dormitorios con placards, cocina con muebles altos y bajos, lavadero cubierto. Excelente ubicaci\u00f3n Sarmiento 4600 esquina Lambar\u00e9, proximo a Parque Centenario, Avda. Corrientes, comercios, colectivos, subte B estaci\u00f3n Angel Gallardo. pida tasaci\u00f3n: Efectuada por profesionales, que analizan permanentemente el desenvolvimiento del mercado. Conf\u00ede su patrimonio en una empresa s\u00f3lida con respaldo y prestigio. Conf\u00ede en el L\u00edder. Goldstein propiedades. Se deja constancia que los m2 son aproximados, al igual que las medidas parciales y el valor consignado de las expensas mensuales (en caso que corresponda pago de expensas) y las caracter\u00edsticas est\u00e1n sujetos a verificaci\u00f3n y/o ajustes, el precio del inmueble puede ser modificado sin previo aviso. En el caso de tratarse de un inmueble en construcci\u00f3n los detalles de terminaci\u00f3n y la fecha de entrega est\u00e1n sujetos a revisi\u00f3n. Fotos de car\u00e1cter no contractual. Las unidades publicadas est\u00e1n sujetas a disponibilidad. Goldstein Propiedades srl con domicilio en Avda. Corrientes 4666 act\u00faa solamente en car\u00e1cter de comercializadora de los inmuebles ofrecidos. En caso de tratarse de un terreno, la informaci\u00f3n de m2 construibles y plusval\u00eda es orientativa, debiendo ser constatada por el interesado. Inmueble no accesible para personas con discapacidad f\u00edsica ley 5115. Cucicba matr\u00edcula 37. Cmcpsi matr\u00edcula 6003. \u00danicamente en el caso de tratarse de alquiler de vivienda familiar, rige lo indicado en la ley 5859. Venta supeditada al cumplimiento por parte del propietario de los requisitos de la resoluci\u00f3n general N\u00ba 2371 de la afip (pedido de coti).\nSuper destacado\nPublicado hoy\nContactar", "revised": false, "rejected": true, "data": {"precio": "$ 600.000", "expensas": "$ 45.000 Expensas", "direccion": "Sarmiento al 4600", "metros": "75 m\u00b2 tot.", "habitaciones": "3 amb.", "hace": "Contactar"}, "image": "https://imgar.zonapropcdn.com/avisos/1/00/53/59/18/31/360x266/1909788335.jpg?isFirstImage=true", "title": "Departamento \u00b7 65m\u00b2 \u00b7 3 Ambientes \u00b7 Departamento 3 Ambientes con Dependencias Al Frente con Balcon - Almagro"}, "https://www.zonaprop.com.ar/propiedades/clasificado/alclocin-hermoso-4-amb-112-m-sup2--en-balvanera!-bajas-53591141.html": {"date": "06-05-2024\n", "index": 3, "content": "$ 700.000\n$ 45.000 Expensas\nJuan D Peron 2200\nBalvanera, Capital Federal\n112 m\u00b2 tot.\n4 amb.\n3 dorm.\n1 ba\u00f1o\nHermoso departamento de 4 ambientes amplios y luminosos con 112m2 totales en Balvanera! Edificio antiguo con estilo muy bien mantenido. Hall. Sala de estar. Despacho 1 4, 15m x 3, 90m. Despacho 2 4m x 3, 90m con placard. Despacho 3 3m x 3, 90m con placard. Despacho 4 4m x 3m. Ba\u00f1o completo y toilet de servicio. Cocina y lavadero independiente. Excelente Ubicaci\u00f3n: - en el mismo edificio del Instituto Otorrino Arauz. - cercan\u00eda a numerosos sanatorios y cl\u00ednicas. - a 2 cuadras de Estaci\u00f3n Pasteur de Subte B. - a 2 cuadras de Estaci\u00f3n Pasco de Subte A. - cercan\u00eda a numerosos negocios comerciales. muy baja expensas! Uso profesional\nSuper destacado\nPublicado hoy\nContactar", "revised": false, "rejected": true, "data": {"precio": "$ 700.000", "expensas": "$ 45.000 Expensas", "direccion": "Juan D Peron 2200", "metros": "112 m\u00b2 tot.", "habitaciones": "4 amb.", "hace": "Contactar"}, "image": "https://imgar.zonapropcdn.com/avisos/1/00/53/59/11/41/360x266/1909772619.jpg?isFirstImage=true", "title": "Oficina comercial de 4 ambientes, Balvanera \u00b7 Hermoso 4 Amb 112 m\u00b2 en Balvanera! Bajas Expensas! Uso Profesional!"}, "https://www.zonaprop.com.ar/propiedades/clasificado/alclapin-departamento-semi-amoblado-en-av-corrientes-al-2900-53589957.html": {"date": "06-05-2024\n", "index": 5, "content": "$ 400.000\n$ 65.000 Expensas\nAv. Corrientes al 2900\nBalvanera, Capital Federal\n60 m\u00b2 tot.\n3 amb.\n2 dorm.\n1 ba\u00f1o\nBuen departamento de 3 ambientes ubicado en Avenida Corrientes al 2900. Pr\u00f3ximo al Abasto Shopping. Ba\u00f1o completo, cocina y lavadero independiente, dos dormitorios con placar. Pisos de madera en dormitorios y estar comedor. El departamento cuenta con los muebles que se ven en las im\u00e1genes. no se aceptan mascotas\nDestacado\nPublicado hoy\nContactar", "revised": false, "rejected": true, "data": {"precio": "$ 400.000", "expensas": "$ 65.000 Expensas", "direccion": "Av. Corrientes al 2900", "metros": "60 m\u00b2 tot.", "habitaciones": "3 amb.", "hace": "Contactar"}, "image": "https://imgar.zonapropcdn.com/avisos/1/00/53/58/99/57/360x266/1909745311.jpg?isFirstImage=true", "title": "Departamento \u00b7 60m\u00b2 \u00b7 3 Ambientes \u00b7 Departamento Semi - Amoblado en Av Corrientes Al 2900"}, "https://www.zonaprop.com.ar/propiedades/clasificado/alclapin-alquiler-semipiso-3-amb-palermo-53591459.html": {"date": "06-05-2024\n", "index": 12, "content": "$ 600.000\n$ 135.000 Expensas\nAraoz al 2800\nBarrio Norte, Capital Federal\n89 m\u00b2 tot.\n3 amb.\n2 dorm.\n2 ba\u00f1os\nExcelente 3 ambientes. PalermoSemipiso al contrafrente con balc\u00f3n corrido, living comedor y dormitorios con pisos de parquet, cocina c/ comedor diario, 2 ba\u00f1os, lavadero independiente. Excelente ubicaci\u00f3n! A 2 cuadras de Jardin Botanico y Parque Las Heras. A 4 cuadras de Subte D, estaci\u00f3n Scalabrini Ortiz. requisitos*1 mes A delantado + 2 meses de deposito (en dolares) *ingresos comprobables*garantia propietaria (caba, prov. Bs. As. ) O seguro caucion*contrato A 2 a\u00f1os*incremento mensual por ipc\"Para los casos de alquiler de vivienda, el monto m\u00e1ximo de comisi\u00f3n que se le puede requerir a los propietarios ser\u00e1 el equivalente al cuatro con quince cent\u00e9simos por ciento (4, 15%) del valor total del respectivo contrato. Se encuentra prohibido cobrar a los inquilinos que sean personas f\u00edsicas comisiones inmobiliarias y gastos de gestor\u00eda de informes\". - Constructora e Inmobiliaria Crecer S. A. H\u00e9ctor Gonzalez - Matricula Cucicba 5189.\nPublicado hoy\nContactar", "revised": false, "rejected": true, "data": {"precio": "$ 600.000", "expensas": "$ 135.000 Expensas", "direccion": "Araoz al 2800", "metros": "89 m\u00b2 tot.", "habitaciones": "3 amb.", "hace": "Contactar"}, "image": "https://imgar.zonapropcdn.com/avisos/1/00/53/59/14/59/360x266/1909779395.jpg?isFirstImage=true", "title": "Departamento \u00b7 81m\u00b2 \u00b7 3 Ambientes \u00b7 Alquiler Semipiso 3 Amb Palermo"}, "https://www.zonaprop.com.ar/propiedades/clasificado/alclapin-alquiler-dpto-tribunales-3-amb-con-cochera-53589684.html": {"date": "06-05-2024\n", "index": 13, "content": "$ 450.000\n$ 150.000 Expensas\nLavalle 1500\nSan Nicol\u00e1s, Capital Federal\n63 m\u00b2 tot.\n3 amb.\n2 dorm.\n1 ba\u00f1o\n1 coch.\nCorredor Responsable: Marcelo Trujillo cucicba 6470 / cmcpdjlm 810- Contacto: Rodrigo Varela - mls id # Ver datos. El equipo Remax Alquila gran departamento de categoria, con cochera, apto tanto para vivienda como para Oficinas. Caracteristicas del edificio: - Expensas $ 150. 000. - Porteria presencial y encargado/seguridad al ingreso del edificio. - 3 modernos ascensores. - Gran recepci\u00f3n con m\u00e1rmol. - Cochera incluida con el alquiler en edificio enfrente. Caracteristicas del departamento: -Doble circulacion entre pulmon del edificio y el contrafrente al pulmon de manzana. -Apto para vivienda con 2 dormitorios o para 3 oficinas y una recepcion. -Agua caliente por calefon. -Calefaccion mediante estufas tiro balanceado. - Muy Buena luminosidad. -La unidad de encuentra en buen estado de conservacion. -La propiedad se alquila amoblada. Condiciones: * Plazo: 24 meses. * Actualizaci\u00f3n: Trimestral seg\u00fan \u00cdndice de Precios al Consumidor (ipc). * Garantia de Caucion. * 1 mes de deposito y 1 mes de adelanto. No dude en consultar lo que necesite y coordinar una visita. Remax Argentina S. R. L. No ejerce el corretaje inmobiliario. El presente sitio web es una plataforma en donde cada oficina inmobiliaria independiente que contrata los servicios re/max puede publicar las propiedades a su cargo. Cada oficina es de propiedad y gesti\u00f3n independiente, por lo que Remax Argentina S. R. L no interviene en los datos de la publicaci\u00f3n, en la operaci\u00f3n inmobiliaria, ni en la confecci\u00f3n y/o firma del boleto de compraventa y/o escritura y/o contrato de alquiler. En cumplimiento de las leyes vigentes que regulan el corretaje inmobiliario, Ley Nacional 25. 028, Ley 22. 802 de Lealtad Comercial, Ley 24. 240 de Defensa al Consumidor, las normas del C\u00f3digo Civil y Comercial de la Naci\u00f3n y Constitucionales, los agentes/gestores no ejercen el corretaje inmobiliario. Todas las operaciones inmobiliarias son objeto de intermediaci\u00f3n y conclusi\u00f3n por parte del corredor p\u00fablico inmobiliario colegiado a cargo de la publicaci\u00f3n, cuyos datos se exhiben en la presente. La presente publicaci\u00f3n describe las caracter\u00edsticas esenciales del inmueble, debi\u00e9ndose consultar al corredor p\u00fablico inmobiliario responsable de la operaci\u00f3n por la eventual actualizaci\u00f3n de las medidas, descripciones arquitect\u00f3nicas y funcionales, valores de expensas, servicios, impuestos, precios y dem\u00e1s informaci\u00f3n, cuyos valores son aproximados. El inmueble no es accesible para personas con discapacidades f\u00edsicas.\nPublicado hoy\nContactar", "revised": false, "rejected": true, "data": {"precio": "$ 450.000", "expensas": "$ 150.000 Expensas", "direccion": "Lavalle 1500", "metros": "63 m\u00b2 tot.", "habitaciones": "3 amb.", "hace": "Contactar"}, "image": "https://imgar.zonapropcdn.com/avisos/1/00/53/58/96/84/360x266/1909739428.jpg?isFirstImage=true", "title": "Departamento \u00b7 63m\u00b2 \u00b7 3 Ambientes \u00b7 1 Cochera \u00b7 Alquiler Dpto Tribunales 3 Amb con Cochera"}, "https://www.zonaprop.com.ar/propiedades/clasificado/alclapin-departamento-en-uriburu-y-av-corrienters-53590716.html": {"date": "06-05-2024\n", "index": 17, "content": "$ 450.000\n$ 45.000 Expensas\nUriburu 400 y Av. Corrientes. Subte B, 3 Ambientes de 70m2 al Frente. muy Luminoso. Todo El\u00e9ctrico\nOnce, Capital Federal\n70 m\u00b2 tot.\n3 amb.\n2 dorm.\n1 ba\u00f1o\nUriburu y Corrientes. Subte B, 3 ambientes de 70m2 al frente. Muy luminoso. Todo El\u00e9ctricoDepartamento c\u00f3modo y amplio. Doble circulaci\u00f3nLiving Comedor2 Dormitorios, 1 con balc\u00f3nCocina completa todo el\u00e9ctricoTermotanque el\u00e9ctricoBano completoLavadero independienteZona Facultades, Subte, a 5 minutos de zona de Teatrossambra propiedadescarolina L. SternMatr\u00edcula N\u00b05539cucicba\nPublicado hoy\nContactar", "revised": false, "rejected": true, "data": {"precio": "$ 450.000", "expensas": "$ 45.000 Expensas", "direccion": "Uriburu 400 y Av. Corrientes. Subte B, 3 Ambientes de 70m2 al Frente. muy Luminoso. Todo El\u00e9ctrico", "metros": "70 m\u00b2 tot.", "habitaciones": "3 amb.", "hace": "Contactar"}, "image": "https://imgar.zonapropcdn.com/avisos/1/00/53/59/07/16/360x266/1909762928.jpg?isFirstImage=true", "title": "Departamento \u00b7 70m\u00b2 \u00b7 3 Ambientes \u00b7 Departamento en Uriburu y Av Corrienters"}, "https://www.zonaprop.com.ar/propiedades/clasificado/alclapin-departamento-en-alquiler-de-3-dorm.-en-parque-53588872.html": {"date": "06-05-2024\n", "index": 20, "content": "$ 600.000\n$ 140.000 Expensas\nAv. Caseros 2454\nParque Patricios, Capital Federal\n116 m\u00b2 tot.\n4 amb.\n3 dorm.\n2 ba\u00f1os\nUbicado en la exclusiva calle Caseros en Parque Patricios, Capital Federal, se encuentra este departamento en alquiler, una verdadera joya en el coraz\u00f3n de la ciudad. Con un precio de ar$600. 000, esta propiedad. con una superficie total de 146 m2, distribuidos en 4 ambientes que incluyen 3 dormitorios, 2 ba\u00f1os, cocina y un encantador balc\u00f3n, Entre las comodidades que ofrece esta exclusiva propiedad se encuentran servicios como agua corriente, luz, gas natural, aire acondicionado, ascensor y conexi\u00f3n para lavarropas, garantizando una experiencia de vida de primer nivel. La disposici\u00f3n frontal del inmueble permite disfrutar de una luminosidad excepcional, mientras que su ubicaci\u00f3n estrat\u00e9gica lo convierte en una oportunidad \u00fanica para aquellos que buscan lo mejor en t\u00e9rminos de ubicaci\u00f3n, dise\u00f1o y confort. Eeste departamento en alquiler en Parque Patricios es ideal para aquellos que buscan un espacio amplio, moderno y lleno de estilo en una de las zonas m\u00e1s exclusivas de la ciudad. \u00a1Cont\u00e1ctanos hoy mismo para conocer m\u00e1s detalles sobre esta espectacular propiedad! \u00a1Ll\u00e1menos para conocer m\u00e1s en detalle esta propiedad! Tel: Ver datos. Email: Ver datos. De la Torre Propiedades\nPublicado hoy\nContactar", "revised": false, "rejected": true, "data": {"precio": "$ 600.000", "expensas": "$ 140.000 Expensas", "direccion": "Av. Caseros 2454", "metros": "116 m\u00b2 tot.", "habitaciones": "4 amb.", "hace": "Contactar"}, "image": "https://imgar.zonapropcdn.com/avisos/1/00/53/58/88/72/360x266/1909722827.jpg?isFirstImage=true", "title": "Departamento de 4 ambientes, Parque Patricios \u00b7 Departamento en Alquiler de 3 Dorm. en Parque Patricios"}, "https://www.zonaprop.com.ar/propiedades/clasificado/alclapin-alquiler-3amb-al-frente-53588562.html": {"date": "06-05-2024\n", "index": 21, "content": "14\n$ 430.000\n$ 30.000 Expensas\nAguirre 715\nVilla Crespo, Capital Federal\n68 m\u00b2 tot.\n3 amb.\n2 dorm.\n1 ba\u00f1o\n3 ambientes al frente. con balcon. excelente estado. villa crespo. aguirre 715 1 \"A\" entre gurruchaga Y acevedo. A 2 cuadras de scalabrini ortiz. 1 mes de deposito. 1 mes de adelanto. contrato 2 a\u00f1os. garantia caba O recibos de sueldo\nPublicado hoy\nContactar", "revised": false, "rejected": true, "data": {"precio": "$ 430.000", "expensas": "$ 30.000 Expensas", "direccion": "Aguirre 715", "metros": "68 m\u00b2 tot.", "habitaciones": "3 amb.", "hace": "Contactar"}, "image": "https://imgar.zonapropcdn.com/avisos/1/00/53/58/85/62/360x266/1909717977.jpg?isFirstImage=true", "title": "Departamento de 3 ambientes, Villa Crespo \u00b7 Alquiler 3amb Al Frente"}, "https://www.zonaprop.com.ar/propiedades/clasificado/alclapin-departamento-en-alquiler-de-2-dorm.-en-monserrat-53588979.html": {"date": "06-05-2024\n", "index": 25, "content": "$ 450.000\n$ 50.000 Expensas\nAv. Belgrano 1181\nMonserrat, Capital Federal\n69 m\u00b2 tot.\n3 amb.\n2 dorm.\n1 ba\u00f1o\nEn una ubicaci\u00f3n privilegiada en Av. Belgrano, Monserrat, Capital Federal, se encuentra disponible este exclusivo departamento de 3 ambientes para alquiler. Conformado por 2 dormitorios, 1 ba\u00f1o y una cocina equipada, esta propiedad ofrece un espacio elegante y funcional para aquellos que buscan vivir en una zona c\u00e9ntrica de la ciudad. , este departamento se destaca por su disposici\u00f3n contrafrente, brindando tranquilidad y privacidad a sus ocupantes. Adem\u00e1s, cuenta con comodidades como un lavadero, living comedor y conexi\u00f3n para lavarropas, garantizando una experiencia de vida c\u00f3moda y conveniente. Entre las caracter\u00edsticas destacadas de esta propiedad se encuentran la presencia de servicios de agua corriente, gas natural y luz, elementos esenciales para el confort diario. Las expensas mensuales ascienden a $50. 000, lo que asegura el mantenimiento adecuado de las \u00e1reas comunes y servicios del edificio. Con un entorno accesible y una distribuci\u00f3n bien pensada, este departamento en alquiler se presenta como una oportunidad \u00fanica para aquellos que valoran la calidad de vida en un ambiente exclusivo y bien ubicado en la capital. En resumen, este departamento en Av. Belgrano, Monserrat, Capital Federal, ofrece la combinaci\u00f3n perfecta entre elegancia, funcionalidad y ubicaci\u00f3n estrat\u00e9gica. Con sus 3 ambientes bien distribuidos y comodidades modernas, representa una opci\u00f3n ideal para quienes buscan un estilo de vida sofisticado en el coraz\u00f3n de la ciudad. No pierdas la oportunidad de vivir en este extraordinario espacio que re\u00fane todas las cualidades que un hogar de lujo puede ofrecer en una de las zonas m\u00e1s codiciadas de Buenos Aires. \u00a1Ll\u00e1menos para conocer m\u00e1s en detalle esta propiedad! Tel: Ver datos. Email: Ver datos. De la Torre Propiedades\nPublicado hoy\nContactar", "revised": true, "rejected": false, "data": {"precio": "$ 450.000", "expensas": "$ 50.000 Expensas", "direccion": "Av. Belgrano 1181", "metros": "69 m\u00b2 tot.", "habitaciones": "3 amb.", "hace": "Contactar"}, "image": "https://imgar.zonapropcdn.com/avisos/1/00/53/58/89/79/360x266/1909726994.jpg?isFirstImage=true", "title": "Departamento de 3 ambientes, Monserrat \u00b7 Departamento en Alquiler de 2 Dorm. en Monserrat", "comment": "C\u00f3mo casa. Un poco m\u00e1s fiero"}, "https://www.zonaprop.com.ar/propiedades/clasificado/alclapin-departamento-en-alquiler-de-2-dorm.-en-balvanera-53589220.html": {"date": "06-05-2024\n", "index": 30, "content": "$ 400.000\n$ 35.000 Expensas\nDirecci\u00f3n no informada\nBalvanera, Capital Federal\n60 m\u00b2 tot.\n3 amb.\n2 dorm.\n1 ba\u00f1o\nUbicado en Sarmiento y Montevideo, se encuentra este departamento en alquiler. Con un precio de ar$400. 000. El departamento cuenta con agua corriente, luz, gas natural, y termotanque el\u00e9ctrico. Cocina separada. Ba\u00f1o completo. Pisos porcellanato\nPublicado hoy\nContactar", "revised": false, "rejected": true, "data": {"precio": "$ 400.000", "expensas": "$ 35.000 Expensas", "direccion": "Direcci\u00f3n no informada", "metros": "60 m\u00b2 tot.", "habitaciones": "3 amb.", "hace": "Contactar"}, "image": "https://imgar.zonapropcdn.com/avisos/1/00/53/58/92/20/360x266/1909730570.jpg?isFirstImage=true", "title": "Departamento de 3 ambientes, Balvanera \u00b7 Departamento en Alquiler de 2 Dorm. en Balvanera"}, "https://www.zonaprop.com.ar/propiedades/clasificado/alclphin-ph-en-almagro-lavalle-al-3600-53587802.html": {"date": "06-05-2024\n", "index": 32, "content": "$ 460.000\n$ 33.600 Expensas\nLavalle al 3600\nAlmagro, Capital Federal\n70 m\u00b2 tot.\n3 amb.\n2 dorm.\n1 ba\u00f1o\nPrecioso ph de 3 ambientes ubicado en el coraz\u00f3n de Almagro. Impecable estado, reciclado totalmente, conservando los materiales nobles de la \u00e9poca. Ca\u00f1erias y cableado restaurado. 1er piso por escalera con entrada com\u00fan por un portal magn\u00edfico de madera con hierro forjado con detalles en bronce, palier espectacular con escalinatas de m\u00e1rmol de carrara y techos altos. Super luminoso con un patio con cerramiento vidriado al cielo. Carpinter\u00eda de aberturas y pisos originales restaurados. Techos doble altura sin entrepiso. Se ingresa por el patio con cerramiento vidriado y vitreaux en los laterales, con posibilidad de abrir para que ingrese m\u00e1s luz y sol directo, hoy living-comedor con aire acondicionado fr\u00edo calor y un lavadero con puerta plegable. A la derecha se encuentra la cocina, con mesada de aluminio y bacha de lavar, muebles de melanina sobre y bajo mesada, ventanas de hierro forjado con vitreaux y paredes revestidas con cer\u00e1micos; al lado, est\u00e1 el ba\u00f1o: con ba\u00f1era, paredes revestidas con azulejos vidriados blancos originales, el lavatorio es original, el bidet e inodoro fueron cambiados. Al fondo, est\u00e1n los 2 dormitorios con techos de bovedilla pintados y pisos de pinotea original. Ambos tienen Split frio calor y calefactor a gas. Los pisos son: en el living comedor o patio (exagonal rojo con borde blanco) y en el ba\u00f1o (cuadrados blancos con borde negro) : es piso calc\u00e1reo importado de Inglaterra (original de 100 a\u00f1os) . En los dormitorios el piso es de pinotea original plastificada. En la cocina son baldosas de calc\u00e1reo original con dibujos. Las aberturas son originales, de madera de cedro pintadas, doble altura, casi todas con bandolera, vidrio repartido y persianas individuales. La puerta principal es de cedro barnizada con ventanas cuadradas arriba. Ambientes: living-comedor, 2 dormitorios amplios con techo doble altura; ba\u00f1o principal y cocina restaurados, con grifer\u00eda y artefactos original, cer\u00e1mico esmaltado, vanitory, cocina y calef\u00f3n nuevos, mesada de granito. se alquila sin mueblesedificio antiguo de tan solo 7 departamentos en total. Requisitos de alquiler: -Alquiler adelantado-Dep\u00f3sito 1 mes en d\u00f3lares al valor blue-Garant\u00eda propietaria o seguro de cauci\u00f3n-Contrato 2 a\u00f1os-Actualizaci\u00f3n trimestral seg\u00fan \u00edndice ipc-Ingresos comprobables- Certificaci\u00f3n de firmas y solicitud de informes al Registro Propiedad Inmueble (c/garant\u00eda propietaria) -Seguro del hogar- Locatario abona: luz y gas segun consumo, Aysa y abl\nPublicado hoy\nContactar", "revised": false, "rejected": true, "data": {"precio": "$ 460.000", "expensas": "$ 33.600 Expensas", "direccion": "Lavalle al 3600", "metros": "70 m\u00b2 tot.", "habitaciones": "3 amb.", "hace": "Contactar"}, "image": "https://imgar.zonapropcdn.com/avisos/1/00/53/58/78/02/360x266/1909699993.jpg?isFirstImage=true", "title": "PH \u00b7 50m\u00b2 \u00b7 3 Ambientes \u00b7 PH en Almagro, Lavalle Al 3600"}, "https://www.zonaprop.com.ar/propiedades/clasificado/alclphpa-alquiler-ph-reciclado-a-nuevo-patio-c-parrilla-53592268.html": {"id": "53592268", "date": "07-05-2024\n", "index": 32, "content": "$ 500.000\nConstituci\u00f3n 2644\nSan Cristobal, Capital Federal\n80 m\u00b2 tot.\n3 amb.\n2 dorm.\n1 ba\u00f1o\nDos meses de deposito, Garantia Propietaria Capital o Finaer, 3 Ultimos Recibos de Sueldos. Actualizacion cada 3 meses con Indice ipc. Mascota Consultar\nPublicado hoy\nContactar", "revised": false, "rejected": true, "data": {"precio": "$ 500.000", "expensas": "", "direccion": "Constituci\u00f3n 2644", "metros": "80 m\u00b2 tot.", "habitaciones": "3 amb.", "hace": "Contactar"}, "image": "https://imgar.zonapropcdn.com/avisos/1/00/53/59/22/68/360x266/1909799657.jpg?isFirstImage=true", "title": "PH de 3 ambientes, San Cristobal \u00b7 Alquiler PH Reciclado a Nuevo Patio C/parrilla"}}