{"https://www.zonaprop.com.ar/propiedades/clasificado/alclapin-departamento-en-flores-53645098.html": {"id": "53645098", "date": "16-05-2024\n", "index": 8, "content": "$ 250.000\n$ 40.000 Expensas\nJ. V. Gonzalez al 500\nFlores, Capital Federal\n50 m\u00b2 tot.\n2 amb.\n1 dorm.\n1 ba\u00f1o\nDepartamento de 2 amb con patio. Living. Cocina independiente. Dormitorio con placard Y ba\u00f1o completo. *presentar garant\u00eda propietaria familiar + recibo de sueldo* O garantia finaer O monclair *mas info: suc. Caballito whatsapp: Ver datosCondiciones: Se deja constancia que los metros cuadrados indicados son aproximados, al igual que las medidas parciales de los ambientes. El precio del inmueble puede ser modificado sin previo aviso. Fotos de car\u00e1cter no contractual. Ley 5359 - cabapara los casos de alquiler de vivienda, el monto m\u00e1ximo de comisi\u00f3n que se le puede requerir a los propietarios ser\u00e1 el equivalente al cuatro con quince cent\u00e9simos por ciento (4, 15%) del valor total del respectivo contrato. Se encuentra prohibido cobrar a los inquilinos que sean personas f\u00edsicas comisiones inmobiliarias y gastos de gestor\u00eda de informes.\nDestacado\nPublicado desde ayer\nContactar", "revised": false, "rejected": true, "data": {"precio": "$ 250.000", "expensas": "$ 40.000 Expensas", "direccion": "J. V. Gonzalez al 500", "metros": "50 m\u00b2 tot.", "habitaciones": "2 amb.", "hace": "Contactar"}, "image": "https://imgar.zonapropcdn.com/avisos/1/00/53/64/50/98/360x266/1911000854.jpg?isFirstImage=true", "title": "Departamento \u00b7 50m\u00b2 \u00b7 2 Ambientes \u00b7 Departamento en Flores"}, "https://www.zonaprop.com.ar/propiedades/clasificado/alclapin-2-amb-balvanera-53646189.html": {"id": "53646189", "date": "16-05-2024\n", "index": 11, "content": "$ 250.000\n$ 5.200 Expensas\nRincon al 600\nBalvanera, Capital Federal\n40 m\u00b2 tot.\n2 amb.\n1 dorm.\n1 ba\u00f1o\nDisponible. Departamento de 2 ambientes en alquiler convencional, contrato a 2 a\u00f1os, sin muebles. Vista al frente al pulm\u00f3n de manzana con una hermosa arboleda y un patio muy grande. Balc\u00f3n corrido y compartido con todo el piso. Amplio living comedor con cocina integrada mediante barra desayunadora. Cocina a gas con horno. . Pisos de madera plastificado en el dormitorio y cer\u00e1micos en el resto del depto. Grandes ventanales, techos altos. Ba\u00f1o con bidet y ducha. Luminoso. ac fr\u00edo y calor, calefacci\u00f3n por tiro balanceado. Acceso sobre la calle Rinc\u00f3n. Ascensor de \u00e9poca. Expensas: $40. 000 (actualizadas al mes de Abril 2024) Para el ingreso deber\u00e1n presentar: dni. Recibo de sueldo. Garant\u00eda propietaria de caba o Seguro de Cauci\u00f3n. Muy buena ubicaci\u00f3n a 100 mts de Av. Independencia y a 100 mts de Av. Belgrano, a 300 mts de Av. Entre Rios, a 6 cuadras de Subte L\u00ednea A y E, cerca de las Universidades uade y uai, r\u00e1pido acceso y diferentes l\u00edneas de Colectivos. A 9 cuadras de la Avenida principal de Buenos Aires (9 de Julio) y a 6 cuadras de la Autopista 25 de Mayo. Consultas a Ver datos.\nDestacado\nPublicado desde ayer\nContactar", "revised": false, "rejected": true, "data": {"precio": "$ 250.000", "expensas": "$ 5.200 Expensas", "direccion": "Rincon al 600", "metros": "40 m\u00b2 tot.", "habitaciones": "2 amb.", "hace": "Contactar"}, "image": "https://imgar.zonapropcdn.com/avisos/1/00/53/64/61/89/360x266/1911029401.jpg?isFirstImage=true", "title": "idea con muebles \u00b7 2 Amb - Balvanera"}, "https://www.zonaprop.com.ar/propiedades/clasificado/alclapin-departamento-alquiler-2-ambientes-apto-profesional-53641321.html": {"id": "53641321", "date": "16-05-2024\n", "index": 13, "content": "$ 270.000\n$ 30.000 Expensas\nSarmiento al 2000\nBalvanera, Capital Federal\n59 m\u00b2 tot.\n2 amb.\n1 dorm.\n1 ba\u00f1o\nDepartamento alquiler, sarmiento entre ayacucho Y jun\u00edn, apto profesional. el departamento se entrega con vajillero con estantes Y cajones en el comedor Y comoda con cajones en habitacion. -2 ambientes-balc\u00f3n franc\u00e9s-lavadero independiente conexion para lavarropas-muy luminoso-calefacci\u00f3n por loza radiante -living -cocina separada-ba\u00f1o completo-dormitorio con placardtransportes CercanosColectivos: 5, 6, 7, 8, 12, 24, 26, 37, 50, 56, 60, 64, 86, 90, 95, 98, 105, 115, 124, 146, 150, 151, 180Subtes (Metro): callao (L\u00ednea B), congreso (L\u00ednea A), pasco (L\u00ednea A), pasteur (L\u00ednea B) aviso legal: Se hace saber que las caracter\u00edsticas descriptas del inmueble publicado, calidades y cualidades constructivas y funcionales, valores de expensas, impuestos y servicios, y medidas y superficies, son aproximados y consignadas en base a datos que fueron proporcionados por el propietario y que pueden no ser exactos y/o no estar actualizados a la hora de la visualizaci\u00f3n de este aviso, pudiendo surgir discordancias con los datos que surgen de la documentaci\u00f3n respectiva. Las medidas y superficies exactas son las que surgen de los t\u00edtulos y planos legales del inmueble. Las im\u00e1genes publicadas lo son al mero efecto orientativo de las caracter\u00edsticas generales y circunstancias del inmueble en el momento en que han sido tomadas, pudiendo las mismas diferir del estado y circunstancias actuales del mismo. Asimismo, los mobiliarios, accesorios, elementos, etc, que se visualicen en las imagines publicadas, no integran la oferta de venta. En todos los casos el interesado deber\u00e1 realizar una visita al inmueble y efectuar las verificaciones respectivas previamente a la realizaci\u00f3n de cualquier operaci\u00f3n, requiriendo la documentaci\u00f3n que corresponda. Venta supeditada al cumplimiento por parte del propietario de los requisitos de la resoluci\u00f3n general N\u00ba 2371 de la afip (pedido de coti). -\nPublicado desde ayer\nContactar", "revised": true, "rejected": false, "data": {"precio": "$ 270.000", "expensas": "$ 30.000 Expensas", "direccion": "Sarmiento al 2000", "metros": "59 m\u00b2 tot.", "habitaciones": "2 amb.", "hace": "Contactar"}, "image": "https://imgar.zonapropcdn.com/avisos/1/00/53/64/13/21/360x266/1910919445.jpg?isFirstImage=true", "title": "Departamento \u00b7 59m\u00b2 \u00b7 2 Ambientes \u00b7 Departamento Alquiler 2 Ambientes Apto Profesional Balvanera"}, "https://www.zonaprop.com.ar/propiedades/clasificado/alclapin-3-amb-semipiso-quirno-al-100-flores-53646284.html": {"id": "53646284", "date": "16-05-2024\n", "index": 21, "content": "8\nConsultar precio\nQuirno 100\nFlores, Capital Federal\n68 m\u00b2 tot.\n3 amb.\n1 dorm.\n1 ba\u00f1o\nSemipiso con balc\u00f3n orientado al contrafrente y lateral del edifico vista abierta. 2 Dormitorios con Placards, Ba\u00f1o completo, Amplia cocina comedor, lavadero separado, ubicado a 150 mts de Av Rivadavia y a 100 mts de Av Alberdi, cercano a Subte l\u00ednea A estaci\u00f3n San Pedrito\nPublicado desde ayer\nContactar", "revised": false, "rejected": true, "data": {"precio": "Consultar precio", "expensas": "", "direccion": "Quirno 100", "metros": "68 m\u00b2 tot.", "habitaciones": "3 amb.", "hace": "Contactar"}, "image": "https://imgar.zonapropcdn.com/avisos/1/00/53/64/62/84/360x266/1911031756.jpg?isFirstImage=true", "title": "Departamento de 3 ambientes, Flores \u00b7 3 Amb Semipiso - Quirno Al 100 - Flores"}, "https://www.zonaprop.com.ar/propiedades/clasificado/alclphin-alquiler-de-departamento-tipo-casa-de-2-ambientes-en-53642566.html": {"id": "53642566", "date": "16-05-2024\n", "index": 23, "content": "$ 300.000\nPergamino 1700. Entre Crisostomo alvarez y Santander\nFlores, Capital Federal\n50 m\u00b2 tot.\n2 amb.\n1 dorm.\n1 ba\u00f1o\nSe alquila casa en Capital Federal, en el barrio de Flores. La propiedad tiene una superficie total de 50. 00 metros cuadrados y consta de 2 ambientes, patio semicubierto y ba\u00f1o. No cuenta con cochera. Se acepta la convivencia con mascotas. El valor de alquiler es de $300. 000. xintel(qbm-qb1-568)\nPublicado desde ayer\nContactar", "revised": false, "rejected": true, "data": {"precio": "$ 300.000", "expensas": "", "direccion": "Pergamino 1700. Entre Crisostomo alvarez y Santander", "metros": "50 m\u00b2 tot.", "habitaciones": "2 amb.", "hace": "Contactar"}, "image": "https://imgar.zonapropcdn.com/avisos/1/00/53/64/25/66/360x266/1910945440.jpg?isFirstImage=true", "title": "QBM-QB1-568_2 \u00b7 Alquiler de Departamento Tipo Casa de 2 Ambientes en Flores."}, "https://www.zonaprop.com.ar/propiedades/clasificado/alclapin-san-nicolas-2-ambientes-53645301.html": {"id": "53645301", "date": "16-05-2024\n", "index": 27, "content": "$ 280.000\n$ 73.000 Expensas\nParan\u00e1 400\nSan Nicol\u00e1s, Capital Federal\n36 m\u00b2 tot.\n2 amb.\n1 dorm.\n1 ba\u00f1o\nHermoso 2 ambientes. Estado impecable. 1 dormitorio con placard empotrado. Living comedor con Aire Acondicionado. Cocina Americana con puerta. Ba\u00f1o completo con ba\u00f1adera. Excelente ubicaci\u00f3n, a metros de Av. Corrientes, rodeado de Avenidas, Facultades, Teatros, Medios de transportes Varios. aviso legal: La descripci\u00f3n gr\u00e1fica y escrita en el presente anuncio, como los valores de expensas, impuestos y servicios, fotos y medidas de este inmueble son meramente a t\u00edtulo estimativo y no forma parte de ning\u00fan tipo de documentaci\u00f3n contractual. Las medidas y superficies definitivas surgir\u00e1n del t\u00edtulo de propiedad del inmueble referido. \u201cPara los casos de alquiler de vivienda, el monto m\u00e1ximo de comisi\u00f3n que se le puede requerir a los propietarios ser\u00e1 el equivalente al cuatro con quince cent\u00e9simos por ciento (4, 15%) del valor total del respectivo contrato. Art. 5\u00b0, Ley 5859 (inc. 9 del art. 10, Ley 2340). Se encuentra prohibido cobrar a los inquilinos que sean personas f\u00edsicas comisiones inmobiliarias y gastos de gestor\u00eda de informes\u201d. Art. 4\u00b0, Ley 5859.\nPublicado desde ayer\nContactar", "revised": false, "rejected": true, "data": {"precio": "$ 280.000", "expensas": "$ 73.000 Expensas", "direccion": "Paran\u00e1 400", "metros": "36 m\u00b2 tot.", "habitaciones": "2 amb.", "hace": "Contactar"}, "image": "https://imgar.zonapropcdn.com/avisos/1/00/53/64/53/01/360x266/1911005793.jpg?isFirstImage=true", "title": "Departamento de 2 ambientes, San Nicol\u00e1s \u00b7 San Nicol\u00e1s - 2 Ambientes"}, "https://www.zonaprop.com.ar/propiedades/clasificado/alclapin-congreso-sarmiento-y-ayacucho-53642449.html": {"id": "53642449", "date": "16-05-2024\n", "index": 28, "content": "$ 270.000\n$ 41.000 Expensas\nSARMIENTO 2000\nCongreso, Capital Federal\n35 m\u00b2 tot.\n2 amb.\n1 dorm.\n1 ba\u00f1o\nBonito departamento de 2 ambientes totalmente amoblado Y equipado para una O 2 personas. Luminoso. Cocina independiente. Ba\u00f1o completo. Aire acondicionado en ambos ambientes. Tvs en ambos ambientes. Servicios individuales. No se permite mascota. Cucicba matricula N\u00b0863. alquiler por 2 a\u00f1os. Ajuste cuatrimestral\nPublicado desde ayer\nContactar", "revised": false, "rejected": true, "data": {"precio": "$ 270.000", "expensas": "$ 41.000 Expensas", "direccion": "SARMIENTO 2000", "metros": "35 m\u00b2 tot.", "habitaciones": "2 amb.", "hace": "Contactar"}, "image": "https://imgar.zonapropcdn.com/avisos/1/00/53/64/24/49/360x266/1910943579.jpg?isFirstImage=true", "title": "Departamento de 2 ambientes, Congreso \u00b7 Congreso - Sarmiento y Ayacucho"}, "https://www.zonaprop.com.ar/propiedades/clasificado/alclapin-departamento-en-alquiler-53645086.html": {"id": "53645086", "date": "16-05-2024\n", "index": 33, "content": "$ 290.000\n$ 30.000 Expensas\nGualeguaychu al 2000\nFloresta, Capital Federal\n42 m\u00b2 tot.\n2 amb.\n1 dorm.\n1 ba\u00f1o\nUbicado sobre Gualeguaychu al 2000 entre Av Alvarez Jonte y Lascano - pleno centro comercial de Monte CastroDepartamento 2 Ambientes lateral\u2022 Living comedor\u2022 Cocina independiente\u2022 Hall distribuci\u00f3n\u2022 Dormitorio con placard\u2022 Ba\u00f1o completo Edificio cuenta con estrada para discapacitaos, y terraza en comunAlquiler $290. 000. -Expensas $30. 000. - ( El valor de las expensas es a modo orientativo y son a verificar seg\u00fan \u00faltima liquidaci\u00f3n). Transportes Cercanos\u2022 Colectivos: 53, 85, 106, 109, 114, 124, 135Para mas informaci\u00f3n puede comunicarse con nuestra oficina. En el horario de lunes a viernes 11. 00 a 20. 00 hs, s\u00e1bados de 10. 00 a 13. 00 horas - Tel. 4566 - 2783 / 4568 - 8655 / Ver datos. Para mas informaci\u00f3n puede comun\u00edquese con nuestra oficina. En el horario de lunes a viernes 11 a 19 hs, s\u00e1bados de 10 a 13 horas tel. 4566 - 2783 / 4568 - 8655. WhatsApp Ver datos - cucicba mat 3314/observaciones: Las medidas indicadas son aproximadas y al solo efecto orientativo. Las reales surgir\u00e1n del titulo de propiedad respectivo.\nPublicado desde ayer\nContactar", "revised": false, "rejected": true, "data": {"precio": "$ 290.000", "expensas": "$ 30.000 Expensas", "direccion": "Gualeguaychu al 2000", "metros": "42 m\u00b2 tot.", "habitaciones": "2 amb.", "hace": "Contactar"}, "image": "https://imgar.zonapropcdn.com/avisos/1/00/53/64/50/86/360x266/1911000405.jpg?isFirstImage=true", "title": "Departamento \u00b7 40m\u00b2 \u00b7 2 Ambientes \u00b7 Departamento en Alquiler"}, "https://www.zonaprop.com.ar/propiedades/clasificado/alclapin-excelente-monoambiente-con-balcon-terraza-en-hermosa-53643245.html": {"id": "53643245", "date": "16-05-2024\n", "index": 34, "content": "$ 270.000\n$ 30.000 Expensas\nLavalle 3643\nAlmagro, Capital Federal\n45 m\u00b2 tot.\n1 amb.\n1 dorm.\n1 ba\u00f1o\nMuy buen departamento de ambiente \u00fanico, con un amplio balc\u00f3n terraza, lavadero, muy linda zona cercana a avenidas, plazas, transporte y dem\u00e1s comodidades.\nPublicado desde ayer\nContactar", "revised": false, "rejected": true, "data": {"precio": "$ 270.000", "expensas": "$ 30.000 Expensas", "direccion": "Lavalle 3643", "metros": "45 m\u00b2 tot.", "habitaciones": "1 amb.", "hace": "Contactar"}, "image": "https://imgar.zonapropcdn.com/avisos/1/00/53/64/32/45/360x266/1910960710.jpg?isFirstImage=true", "title": "Departamento de 1 ambiente, Almagro \u00b7 Excelente Monoambiente con Balc\u00f3n Terraza en Hermosa Zona"}, "https://www.zonaprop.com.ar/propiedades/clasificado/alclappa-departameto-en-alquiler-53641267.html": {"id": "53641267", "date": "16-05-2024\n", "index": 35, "content": "$ 300.000\n$ 40.000 Expensas\nSarand\u00ed 650\nBalvanera, Capital Federal\n50 m\u00b2 tot.\n2 amb.\n1 dorm.\n1 ba\u00f1o\nAmplio departamento contrafrente, con aire acondicionado, cocina inustrial y peque\u00f1o patio techado, cerca del subte A y E, gran ubicacion, bajas expensas\nPublicado desde ayer\nContactar", "revised": false, "rejected": true, "data": {"precio": "$ 300.000", "expensas": "$ 40.000 Expensas", "direccion": "Sarand\u00ed 650", "metros": "50 m\u00b2 tot.", "habitaciones": "2 amb.", "hace": "Contactar"}, "image": "https://imgar.zonapropcdn.com/avisos/1/00/53/64/12/67/360x266/1910923247.jpg?isFirstImage=true", "title": "Departamento de 2 ambientes, Balvanera \u00b7 Departameto en Alquiler"}, "https://www.zonaprop.com.ar/propiedades/clasificado/alclapin-2-amb-balcon-alto-luminoso-53638739.html": {"id": "53638739", "date": "16-05-2024\n", "index": 40, "content": "$ 280.000\n$ 60.000 Expensas\nRiobamba 200\nCongreso, Capital Federal\n53 m\u00b2 tot.\n2 amb.\n1 dorm.\n1 ba\u00f1o\nSolido Edificio - Unidad al frente \u2013 Piso Alto - Balc\u00f3n \u2013 Orientaci\u00f3n Este \u2013 2 Ambientes muy amplios y Super Luminoso \u2013 Cocina Completa \u2013 Enorme Lavadero Independiente \u2013 Ba\u00f1o completo \u2013 Agua Caliente Central \u2013 Calefacci\u00f3n Individual \u2013 Impuestos + AySa + Expensas (mayo $ 60. 000. -) Contrato 2 a\u00f1os - Actualizaci\u00f3n trimestral ipc. Requisitos: Garant\u00eda Propietaria caba o Seguro Cauci\u00f3n (Finaer/Monclair) + Comprobante de Ingresos o Recibo de Sueldo. 1 mes de Dep\u00f3sito - 1 mes de Adelanto\nDestacado\nPublicado hace 2 d\u00edas\nContactar", "revised": true, "rejected": false, "data": {"precio": "$ 280.000", "expensas": "$ 60.000 Expensas", "direccion": "Riobamba 200", "metros": "53 m\u00b2 tot.", "habitaciones": "2 amb.", "hace": "Contactar"}, "image": "https://imgar.zonapropcdn.com/avisos/1/00/53/63/87/39/360x266/1910855420.jpg?isFirstImage=true", "title": "Departamento de 2 ambientes, Congreso \u00b7 2 Amb - Balc\u00f3n - Alto Luminoso"}, "https://www.zonaprop.com.ar/propiedades/clasificado/alclapin-alquiler-2-ambientes!-53637313.html": {"id": "53637313", "date": "16-05-2024\n", "index": 42, "content": "11\n$ 280.000\n$ 58.000 Expensas\nLAVALLE 3700. Entre Bulnes y Jeronimo salguero\nAlmagro, Capital Federal\n35 m\u00b2 tot.\n2 amb.\n1 dorm.\n1 ba\u00f1o\nAlquiler de Departamento 2 ambientes en Almagro, Capital Federal. Departamento de 2 ambientes lateral muy luminoso, el mismo cuenta con living comedor, cocina separada, un dormitorio con placard y ba\u00f1o completo. Contrato por 24 meses, incremento cuatrimestral con \u00edndice ipc. Requisitos. - Un mes de adelanto y un mes de dep\u00f3sito. - Garant\u00eda Propietaria de caba o Seguro de cauci\u00f3n. - Ingresos demostrables. lepore propiedades Ver datos Ver datos / Ver datos. lepore Propiedades S. A. Cuit: Ver datos-9 C. U. C. I. C. B. A. Matr\u00edcula N\u00ba 931 (Sucursales Caballito - Palermo - Centro) aviso legal: Las descripciones arquitect\u00f3nicas y funcionales, valores de expensas y/o gastos comunes, impuestos y servicios, fotos y medidas de este inmueble son aproximados. Los datos fueron proporcionados por el propietario y pueden no estar actualizados a la hora de la visualizaci\u00f3n de este aviso por lo cual pueden arrojar inexactitudes y discordancias con las que surgen de las facturas, t\u00edtulos y planos legales del inmueble. El interesado deber\u00e1 realizar las verificaciones respectivas con car\u00e1cter previo a la realizaci\u00f3n de cualquier operaci\u00f3n, requiriendo por s\u00ed o sus profesionales de confianza las copias necesarias de la documentaci\u00f3n que corresponda. Se encuentra prohibido cobrar comisiones inmobiliarias y gastos de gestor\u00eda de informes a los inquilinos que sean personas f\u00edsicas. Para los casos de alquiler de vivienda, el monto m\u00e1ximo de comisi\u00f3n que se le puede requerir a los propietarios ser\u00e1 el equivalente al cuatro con quince cent\u00e9simos por ciento (4, 15%) del valor total del respectivo contrato (conf. El Art. 4 de la Ley 5. 859 de C. A. B. A) xintel(lep-le8-Ver datos)\nPublicado hace 2 d\u00edas\nContactar", "revised": false, "rejected": true, "data": {"precio": "$ 280.000", "expensas": "$ 58.000 Expensas", "direccion": "LAVALLE 3700. Entre Bulnes y Jeronimo salguero", "metros": "35 m\u00b2 tot.", "habitaciones": "2 amb.", "hace": "Contactar"}, "image": "https://imgar.zonapropcdn.com/avisos/1/00/53/63/73/13/360x266/1910818963.jpg?isFirstImage=true", "title": "LEP-LE8-44594_2 \u00b7 Alquiler 2 Ambientes!"}, "https://www.zonaprop.com.ar/propiedades/clasificado/alclappa-2amb-boedo-dueno-directo-53639153.html": {"id": "53639153", "date": "16-05-2024\n", "index": 61, "content": "8\n$ 300.000\n$ 53.000 Expensas\nS\u00e1nchez de Loria 531\nAlmagro Sur, Almagro\n42 m\u00b2 tot.\n2 amb.\n1 dorm.\n1 ba\u00f1o\n2 ambientes con balc\u00f3n franc\u00e9s. Muy luminoso con lavadero. Ba\u00f1o completo, cocina el\u00e9ctrica. Termotanque. Excelente ubicaci\u00f3n, varios medios de transporte. 5 cuadras del Subte A. Apto profesional. No se aceptan mascotas\nPublicado hace 2 d\u00edas\nContactar", "revised": true, "rejected": false, "data": {"precio": "$ 300.000", "expensas": "$ 53.000 Expensas", "direccion": "S\u00e1nchez de Loria 531", "metros": "42 m\u00b2 tot.", "habitaciones": "2 amb.", "hace": "Contactar"}, "image": "https://imgar.zonapropcdn.com/avisos/1/00/53/63/91/53/360x266/1910862056.jpg?isFirstImage=true", "title": "Departamento de 2 ambientes, Almagro \u00b7 2amb Boedo - Due\u00f1o Directo"}, "https://www.zonaprop.com.ar/propiedades/clasificado/alclappa-2-ambientes-con-lavadero-dueno-directo-53639075.html": {"id": "53639075", "date": "16-05-2024\n", "index": 63, "content": "$ 300.000\n$ 36.000 Expensas\nAvenida Rivadavia 2600\nOnce, Capital Federal\n38 m\u00b2 tot.\n2 amb.\n1 dorm.\n1 ba\u00f1o\nLuminoso 2 ambientes a contrafrente. Cocina y lavadero separados. Piso de parquet. Aire acondicionado fr\u00edo calor. Seguridad 24hs. Preno centro de once con m\u00faltiples medios de transporte y comercios cercanos.\nPublicado hace 2 d\u00edas\nContactar", "revised": false, "rejected": true, "data": {"precio": "$ 300.000", "expensas": "$ 36.000 Expensas", "direccion": "Avenida Rivadavia 2600", "metros": "38 m\u00b2 tot.", "habitaciones": "2 amb.", "hace": "Contactar"}, "image": "https://imgar.zonapropcdn.com/avisos/1/00/53/63/90/75/360x266/1910860697.jpg?isFirstImage=true", "title": "Departamento de 2 ambientes, Once \u00b7 2 Ambientes con Lavadero - Due\u00f1o Directo"}, "https://www.zonaprop.com.ar/propiedades/clasificado/alclapin-departamento-alquiler-2-ambientes-con-balcon-53628279.html": {"id": "53628279", "date": "16-05-2024\n", "index": 64, "content": "$ 300.000\n$ 64.000 Expensas\nTucuman al 1500\nBalvanera, Capital Federal\n40 m\u00b2 tot.\n2 amb.\n1 dorm.\n1 ba\u00f1o\nAlquiler de departamento de 2 ambientes con balc\u00f3n, ubicado en Balvanera, posee hall de entrada, living comedor, dormitorio, cocina, lavadero independiente, ascensor y encargado fijo. Corredor interviniente caba, pablo faija cucicba 3964- Corredor Interviniente provincia de buenos aires, pablo faija martillero publico cmycpdjq mat 913 folio 105 tomo ii La tasaci\u00f3n, intermediaci\u00f3n y la conclusi\u00f3n de las operaciones sobre esta propiedad son actividades exclusivas de este corredor matriculado, conforme las previsiones de la ley 20. 266, la ley caba 2340, la ley provincial 10. 973 y sus modif. Y las normas reglamentarias dictadas por los colegios departamentales. Las oficinas asociadas a la red Keller Williams act\u00faan en forma independiente, brindando servicios a corredores, agentes y al p\u00fablico en general, y su intervenci\u00f3n se limita a la prestaci\u00f3n de servicios inmobiliarios que no incluyen actos de corretaje ni intermediaci\u00f3n inmobiliaria.\nSuper destacado\nPublicado hace 3 d\u00edas\nContactar", "revised": false, "rejected": true, "data": {"precio": "$ 300.000", "expensas": "$ 64.000 Expensas", "direccion": "Tucuman al 1500", "metros": "40 m\u00b2 tot.", "habitaciones": "2 amb.", "hace": "Contactar"}, "image": "https://imgar.zonapropcdn.com/avisos/1/00/53/62/82/79/360x266/1910611019.jpg?isFirstImage=true", "title": "Departamento \u00b7 37m\u00b2 \u00b7 2 Ambientes \u00b7 Departamento Alquiler 2 Ambientes con Balcon"}, "https://www.zonaprop.com.ar/propiedades/clasificado/alclapin-departamento-2-ambientes-frente-con-balcon-muy-53626877.html": {"id": "53626877", "date": "16-05-2024\n", "index": 69, "content": "$ 250.000\n$ 41.187 Expensas\nMercedes 606\nFloresta, Capital Federal\n45 m\u00b2 tot.\n2 amb.\n1 dorm.\n1 ba\u00f1o\nHermoso departamento 2 ambientes frente con balcon muy luminoso. Requisitos. Garantia propietaria o seguro de caucion. Ajuste cada 4 meses x icl. 1 mes de deposito. 1 mes de adelanto. M\u00e1s gastos administrativos\nPublicado hace 3 d\u00edas\nContactar", "revised": true, "rejected": false, "data": {"precio": "$ 250.000", "expensas": "$ 41.187 Expensas", "direccion": "Mercedes 606", "metros": "45 m\u00b2 tot.", "habitaciones": "2 amb.", "hace": "Contactar"}, "image": "https://imgar.zonapropcdn.com/avisos/1/00/53/62/68/77/360x266/1910582049.jpg?isFirstImage=true", "title": "Departamento de 2 ambientes, Floresta \u00b7 Departamento 2 Ambientes Frente con Balcon Muy Luminoso"}, "https://www.zonaprop.com.ar/propiedades/clasificado/alclapin-olivera-100-departamento-de-2-ambientes-38-m-esquina-53631911.html": {"id": "53631911", "date": "16-05-2024\n", "index": 70, "content": "$ 230.000\n$ 52.000 Expensas\nOlivera al 100\nFloresta, Capital Federal\n38 m\u00b2 tot.\n2 amb.\n1 dorm.\n1 ba\u00f1o\nDepartamento de 2 Ambientes al frente. Living -comedor. Dormitorio con placard. Cocina con muebles completos y lavadero incorporado. Ba\u00f1o completo. Muy buen estado. Pisos de parquet. Muy buena iluminaci\u00f3n. Edificio en esquina de 8 pisos y 28 unidades funcionales. Colectivos: 1, 2, 4, 5, 8, 36, 46, 49, 55, 63, 86, 88, 92, 96, 104, 107, 113, 114, 126, 136, 163, 180, 182Condiciones de AlquilerDuraci\u00f3n del contrato: 2 a\u00f1osAjuste: Trimestral por ipcley 5859: Art\u00edculo 4\u00b0. - Incorp\u00f3rase como inciso 8 del art\u00edculo 10 de la Ley 2340 (texto consolidado seg\u00fan Ley N\u00b0 5666) el siguiente texto: Hacer constar en todo ofrecimiento publicitario de locaci\u00f3n de inmuebles con destino habitacional que se emita v\u00eda p\u00e1ginas web, propias o de terceros, la siguiente leyenda: \u201cPara los casos de alquiler de vivienda, el monto m\u00e1ximo de comisi\u00f3n que se le puede requerir a los propietarios ser\u00e1 el equivalente al cuatro con quince cent\u00e9simos por ciento (4, 15%) del valor total del respectivo contrato. Se encuentra prohibido cobrar a los inquilinos que sean personas f\u00edsicas comisiones inmobiliarias y gastos de gestor\u00eda de informes\u201d. -Ley 5115: excepto que en la descripci\u00f3n de la propiedad se indique lo contrario, el edificio puede no contar con rampa para personas con movilidad reducida, y no ser Accesible para personas con discapacidades f\u00edsicas. -Se deja constancia que las medidas, superficies y m2 consignados son aproximados, sujetos a verificaci\u00f3n y/o ajuste. El precio del inmueble puede ser modificado sin previo aviso. vremont pisanimatricula cucicba N\u00b0 3747cpi Nicol\u00e1s Pisani\nPublicado hace 3 d\u00edas\nContactar", "revised": true, "rejected": false, "data": {"precio": "$ 230.000", "expensas": "$ 52.000 Expensas", "direccion": "Olivera al 100", "metros": "38 m\u00b2 tot.", "habitaciones": "2 amb.", "hace": "Contactar"}, "image": "https://imgar.zonapropcdn.com/avisos/1/00/53/63/19/11/360x266/1910688210.jpg?isFirstImage=true", "title": "Departamento \u00b7 38m\u00b2 \u00b7 2 Ambientes \u00b7 Olivera 100 Departamento de 2 Ambientes 38 m Esquina en Floresta Alquiler"}, "https://www.zonaprop.com.ar/propiedades/clasificado/alclapin-departamento-2-ambientes-con-balcon-balvanera-53630636.html": {"id": "53630636", "date": "16-05-2024\n", "index": 75, "content": "$ 300.000\n$ 35.114 Expensas\nAv. Jujuy 420 8\u00baC (esq. Av. Belgrano)\nBalvanera, Capital Federal\n38 m\u00b2 tot.\n2 amb.\n1 dorm.\n1 ba\u00f1o\n- totalmente externo muy luminoso. - ambos ambientes con pisos de parquet. - dormitorio con placard. - A mtrs de estaci\u00f3n venezuela subte linea \"H\"\u201cPara los casos de alquiler de vivienda, el monto m\u00e1ximo de comisi\u00f3n que se le puederequerir a los propietarios ser\u00e1 el equivalente al cuatro con quince cent\u00e9simos porciento (4, 15%) del valor total del respectivo contrato. Se encuentra prohibido cobrar alos inquilinos que sean personas f\u00edsicas comisiones inmobiliarias y gastos de gestor\u00edade informes\u201dNo cumple con Ley 5115 (accesibilidad)\nPublicado hace 3 d\u00edas\nContactar", "revised": false, "rejected": true, "data": {"precio": "$ 300.000", "expensas": "$ 35.114 Expensas", "direccion": "Av. Jujuy 420 8\u00baC (esq. Av. Belgrano)", "metros": "38 m\u00b2 tot.", "habitaciones": "2 amb.", "hace": "Contactar"}, "image": "https://imgar.zonapropcdn.com/avisos/1/00/53/63/06/36/360x266/1910665617.jpg?isFirstImage=true", "title": "Departamento \u00b7 34m\u00b2 \u00b7 2 Ambientes \u00b7 Departamento 2 Ambientes con Balc\u00f3n - Balvanera"}, "https://www.zonaprop.com.ar/propiedades/clasificado/alclapin-departamento-en-almagro-53630224.html": {"id": "53630224", "date": "16-05-2024\n", "index": 76, "content": "$ 300.000\n$ 32.000 Expensas\nColombres 33\nAlmagro, Capital Federal\n35 m\u00b2 tot.\n2 amb.\n1 dorm.\n1 ba\u00f1o\nDepartamento en alquiler en el barrio de Almagro. Inmejorable ubicaci\u00f3n, a pasos de Av. Rivadavia (Linea subte A), a pocas cuadras de Av. Medrano, Av. Boedo y Av. Belgrano. El departamento consta de: - Living-Comedor- Cocina con lavadero- Ba\u00f1o completo- DormitorioRequisitos: - Mes de adelanto- 300 usd deposito- Garantia propietaria caba o Seguro Finaer- Ingresos comprobables- Aumentos cuatrimestrales por icl- Contrato 24 mesesPara consultas y visitas comunicarse via whatsapp.\nPublicado hace 3 d\u00edas\nContactar", "revised": false, "rejected": true, "data": {"precio": "$ 300.000", "expensas": "$ 32.000 Expensas", "direccion": "Colombres 33", "metros": "35 m\u00b2 tot.", "habitaciones": "2 amb.", "hace": "Contactar"}, "image": "https://imgar.zonapropcdn.com/avisos/1/00/53/63/02/24/360x266/1910656040.jpg?isFirstImage=true", "title": "Departamento \u00b7 35m\u00b2 \u00b7 2 Ambientes \u00b7 Departamento en Almagro"}, "https://www.zonaprop.com.ar/propiedades/clasificado/alclapin-departamento-de-2-ambientes-con-escritorio-en-alquiler-53629552.html": {"id": "53629552", "date": "16-05-2024\n", "index": 77, "content": "$ 250.000\n$ 64.266 Expensas\nAv. Leandro Alem al 600 - Departamento de 2 Ambientes con Escritorio en Alquiler en San Nicolas\nSan Nicol\u00e1s, Capital Federal\n59 m\u00b2 tot.\n2 amb.\n1 dorm.\n1 ba\u00f1o\nDepartamento de 2 ambientes con escritorio/dependencias en alquiler en San Nicol\u00e1s! Ubicaci\u00f3n: - Sobre Av. Leandro N. Alem- A una cuadra y media de Av. C\u00f3rdoba- A tres cuadras de Av. Corrientes- A dos cuadras de Puerto MaderoMedios de transporte: - Colectivos: 4, 5, 6, 7, 9, 20, 22, 23, 26, 28, 33, 45, 50, 56, 61, 62, 74, 91, 93, 99, 105, 109, 115, 126, 129, 130, 132, 140, 143, 146, 152, 159, 180, 195- Subtes: Catalinas y Correo Central (l\u00ednea E) y Alem (l\u00ednea B) Departamento: - Tercer piso al contrafrente- Muy buena luz natural (orientaci\u00f3n Este) - Living comedor con pisos de parquet y aire acondicionado- Dormitorio de grandes dimensiones con pisos de parquet, aire acondicionado y placard- Cocina completa- Ba\u00f1o completo con ventana al exterior- Escritorio (o dependencia de servicio) con toilette en el lavadero cubierto- No apto mascotasRequisitos: - Garant\u00eda de propietario de Capital Federal (puede ser del conurbano bonaerense si es familiar directo comprobable) . El propietario no acepta seguro de cauci\u00f3n ni garant\u00eda bancaria- Ingresos demostrables- Un mes de dep\u00f3sito ($ 250. 000. -) - Un mes de adelanto ($ 250. 000. -) - Informes de la garant\u00eda- Firmas certificadas por Escribano- Contrato de 2 a\u00f1os de duraci\u00f3n- Aumento trimestral por iclley 5. 859, art. 4: \u201cPara los casos de alquiler de vivienda, el monto m\u00e1ximo de comisi\u00f3n que se le puede requerir a los propietarios ser\u00e1 el equivalente al cuatro con quince cent\u00e9simos por ciento (4, 15%) del valor total del respectivo contrato. Se encuentra prohibido cobrar a los inquilinos que sean personas f\u00edsicas comisiones inmobiliarias y gastos de gestor\u00eda de informes\u201d.\nPublicado hace 3 d\u00edas\nContactar", "revised": false, "rejected": true, "data": {"precio": "$ 250.000", "expensas": "$ 64.266 Expensas", "direccion": "Av. Leandro Alem al 600 - Departamento de 2 Ambientes con Escritorio en Alquiler en San Nicolas", "metros": "59 m\u00b2 tot.", "habitaciones": "2 amb.", "hace": "Contactar"}, "image": "https://imgar.zonapropcdn.com/avisos/1/00/53/62/95/52/360x266/1910639210.jpg?isFirstImage=true", "title": "Departamento \u00b7 59m\u00b2 \u00b7 2 Ambientes \u00b7 Departamento de 2 Ambientes con Escritorio en Alquiler en San Nicolas"}, "https://www.zonaprop.com.ar/propiedades/clasificado/alclapin-2-ambientes-impecable-virrey-cevallos-1000.-53628111.html": {"id": "53628111", "date": "16-05-2024\n", "index": 78, "content": "$ 270.000\n$ 46.725 Expensas\nVirrey Cevallos 1000.-\nMonserrat, Capital Federal\n41 m\u00b2 tot.\n2 amb.\n1 dorm.\n1 ba\u00f1o\nExcelente departamento de dos ambientes. Living comedor, cocina americana con barra desayunadora. Alacena Y bajo mesada. Dormitorio con placard, ba\u00f1o completo, balc\u00f3n. luminoso buena ubicaci\u00f3n. contrato por 24 meses con ajuste semestraltransportes cercanoscolectivos: 6, 8, 12, 23, 37, 39, 46, 50, 53, 57, 60, 84, 90, 91, 96, 102, 126, 129, 150, 151, 168, 195Subtes (Metro): entre rios (L\u00ednea E), san jose (L\u00ednea E) aviso legal: Las descripciones valores de expensas, impuestos y servicios, fotos y medidas de este inmueble son aproximados. Los datos fueron proporcionados por el propietario y pueden no estar actualizados a la hora de la visualizaci\u00f3n de este aviso por lo cual pueden arrojar inexactitudes y discordancias con las que surgen de las facturas, t\u00edtulos y planos. El interesado deber\u00e1 realizar las verificaciones respectivas previamente a la realizaci\u00f3n de cualquier operaci\u00f3n. \"Para los casos de alquiler de vivienda el monto m\u00e1ximo de comisi\u00f3n que se le puede requerir a los propietarios ser\u00e1 el 4, 15 % del valor total del respectivo contrato. Se encuentra prohibido cobrar comisiones inmobiliarias y gastos de gestor\u00eda de informes a los inquilinos, en el caso de ser personas f\u00edsicas\"\nPublicado hace 3 d\u00edas\nContactar", "revised": true, "rejected": false, "data": {"precio": "$ 270.000", "expensas": "$ 46.725 Expensas", "direccion": "Virrey Cevallos 1000.-", "metros": "41 m\u00b2 tot.", "habitaciones": "2 amb.", "hace": "Contactar"}, "image": "https://imgar.zonapropcdn.com/avisos/1/00/53/62/81/11/360x266/1910607071.jpg?isFirstImage=true", "title": "Departamento \u00b7 38m\u00b2 \u00b7 2 Ambientes \u00b7 2 Ambientes Impecable Virrey Cevallos 1000."}, "https://www.zonaprop.com.ar/propiedades/clasificado/alclocin-oficina-de-2-ambientes-con-escritorio-en-alquiler-en-53629578.html": {"id": "53629578", "date": "16-05-2024\n", "index": 81, "content": "12\n$ 250.000\n$ 64.266 Expensas\nAv. Leandro Alem al 600 - Oficina de 2 Ambientes con Escritorio en Alquiler en San Nicolas\nSan Nicol\u00e1s, Capital Federal\n59 m\u00b2 tot.\n2 amb.\n1 dorm.\n1 ba\u00f1o\nOficina de 2 ambientes con escritorio/dependencias en alquiler en San Nicol\u00e1s! Ubicaci\u00f3n: - Sobre Av. Leandro N. Alem- A una cuadra y media de Av. C\u00f3rdoba- A tres cuadras de Av. Corrientes- A dos cuadras de Puerto MaderoMedios de transporte: - Colectivos: 4, 5, 6, 7, 9, 20, 22, 23, 26, 28, 33, 45, 50, 56, 61, 62, 74, 91, 93, 99, 105, 109, 115, 126, 129, 130, 132, 140, 143, 146, 152, 159, 180, 195- Subtes: Catalinas y Correo Central (l\u00ednea E) y Alem (l\u00ednea B) Departamento: - Tercer piso al contrafrente- Muy buena luz natural (orientaci\u00f3n Este) - Living comedor con pisos de parquet y aire acondicionado- Dormitorio de grandes dimensiones con pisos de parquet, aire acondicionado y placard- Cocina completa- Ba\u00f1o completo con ventana al exterior- Escritorio (o dependencia de servicio) con toilette en el lavadero cubiertoRequisitos: - Garant\u00eda de propietario de Capital Federal (puede ser del conurbano bonaerense si es familiar directo comprobable) . El propietario no acepta seguro de cauci\u00f3n ni garant\u00eda bancaria- Ingresos demostrables- Un mes de dep\u00f3sito ($ 250. 000. -) - Un mes de adelanto ($ 250. 000. -) - 6% de honorarios inmobiliarios (incluye firmas certificadas e informes de la garant\u00eda) - Contrato de 2 a\u00f1os de duraci\u00f3n- Aumento trimestral por iclley 5. 859, art. 4: \u201cPara los casos de alquiler de vivienda, el monto m\u00e1ximo de comisi\u00f3n que se le puede requerir a los propietarios ser\u00e1 el equivalente al cuatro con quince cent\u00e9simos por ciento (4, 15%) del valor total del respectivo contrato. Se encuentra prohibido cobrar a los inquilinos que sean personas f\u00edsicas comisiones inmobiliarias y gastos de gestor\u00eda de informes\u201d.\nPublicado hace 3 d\u00edas\nContactar", "revised": false, "rejected": true, "data": {"precio": "$ 250.000", "expensas": "$ 64.266 Expensas", "direccion": "Av. Leandro Alem al 600 - Oficina de 2 Ambientes con Escritorio en Alquiler en San Nicolas", "metros": "59 m\u00b2 tot.", "habitaciones": "2 amb.", "hace": "Contactar"}, "image": "https://imgar.zonapropcdn.com/avisos/1/00/53/62/95/78/360x266/1910639677.jpg?isFirstImage=true", "title": "Oficina comercial \u00b7 59m\u00b2 \u00b7 2 Ambientes \u00b7 Oficina de 2 Ambientes con Escritorio en Alquiler en San Nicolas"}, "https://www.zonaprop.com.ar/propiedades/clasificado/alclappa-2-ambientes-super-luminoso-recien-pintado-carabobo-300-53623181.html": {"id": "53623181", "date": "16-05-2024\n", "index": 90, "content": "$ 280.000\n$ 24.200 Expensas\nAvenida Carabobo 300\nFlores Norte, Flores\n43 m\u00b2 tot.\n2 amb.\n1 dorm.\n1 ba\u00f1o\nDesplegar pesta\u00f1a para leer las condiciones y requisitos debajo de descripci\u00f3n. Departamento de 2 ambientes s\u00faper luminoso, reci\u00e9n pintado, lateral, a 3 cuadras de Rivadavia y de la estaci\u00f3n Carabobo de la l\u00ednea A del subte. Cocina comedor con conexi\u00f3n para lavarropas, calef\u00f3n Orbis a botonera, cocina a gas Orbis, Spar y gran cantidad de muebles sobre y bajo mesada. Living comedor con balc\u00f3n franc\u00e9s y peque\u00f1a vitrina. Dormitorio con placard de 6 puertas de 3 m de ancho y baulera, aire acondicionado fr\u00edo-calor. Ba\u00f1o completo con ba\u00f1era, vanitory, bidet, botiqu\u00edn de 2 puertas y peinador de 3 puertas. Persianas de madera con sistema automatizado Radog en dormitorio y en comedor. No se aceptan mascotas de ning\u00fan tipo. Expensas de mayo: $24. 200. - abl: $2. 881, 28 fijos por mes hasta diciembre 2024 inclusive porque se pag\u00f3 el importe anual que se prorratear\u00e1 mes a mes en forma proporcional. Aysa de mayo: 11. 410, 16. Condiciones: El canon mensual de la locaci\u00f3n es $280. 000. - por mes que se indexar\u00e1 cada tres meses seg\u00fan el ipc que elabora el indec o la entidad que pueda reemplazarlo en el futuro. Contrato a 2 a\u00f1os. Para el ingreso se solicitar\u00e1: 1 mes adelantado. (280. 000. -) 1 mes de dep\u00f3sito en garant\u00eda. (280. 000. -) Una propiedad e en garant\u00eda de caba de familiar y/o empleador, o bien, seguro de cauci\u00f3n de entidad reconocida de plaza. Ingresos comprobables de no menos de $800. 000. - por mes. El contrato de locaci\u00f3n se firmar\u00e1 ante escribano p\u00fablico debiendo pagar el/los locatario/s los gastos de emisi\u00f3n de los certificados de dominio e inhibiciones en caso que se opte por garant\u00eda propietaria. Inmobiliarias e intermediarios abstenerse.\nPublicado hace 4 d\u00edas\nContactar", "revised": false, "rejected": true, "data": {"precio": "$ 280.000", "expensas": "$ 24.200 Expensas", "direccion": "Avenida Carabobo 300", "metros": "43 m\u00b2 tot.", "habitaciones": "2 amb.", "hace": "Contactar"}, "image": "https://imgar.zonapropcdn.com/avisos/1/00/53/62/31/81/360x266/1910501614.jpg?isFirstImage=true", "title": "Departamento de 2 ambientes, Flores \u00b7 2 Ambientes S\u00faper Luminoso Reci\u00e9n Pintado Carabobo 300"}, "https://www.zonaprop.com.ar/propiedades/clasificado/alclappa-se-alquila-excelente-piso-en-floresta-a-metro-de-av-53623537.html": {"id": "53623537", "date": "16-05-2024\n", "index": 91, "content": "$ 290.000\n$ 20.000 Expensas\nDolores 41\nFloresta Sur, Floresta\n50 m\u00b2 tot.\n1 amb.\n1 dorm.\n1 ba\u00f1o\nImportante. Se alquila departamento con excelente luz natural, ubicado en el barrio porte\u00f1o de floresta, calle dolores 41 - 9 Piso, A metros de avenida rivadavia, A dos cuadras de avenida juan bautista alberdi Y A siete cuadras de san pedrito Y nazca ( estaci\u00f3n subte A). El mismo se encuentra en el noveno piso con vista al frente. Consta de un ambiente amplio divisible. Posee piso cer\u00e1mico, cocina con mueble bajo mesada, extractor purificador de aire, anafe de dos hornallas, griferia monocomando, mueble de dos hojas con cajoneras. Balcon aterrazado. Ba\u00f1o completo con ba\u00f1era. Requisitos. Un mes de adelanto. un mes de dep\u00f3sito. garant\u00eda propietaria ( no excluyente) ingresos demostrables. seguro de cauci\u00f3n mg garant\u00edas\nPublicado hace 3 d\u00edas\nContactar", "revised": false, "rejected": true, "data": {"precio": "$ 290.000", "expensas": "$ 20.000 Expensas", "direccion": "Dolores 41", "metros": "50 m\u00b2 tot.", "habitaciones": "1 amb.", "hace": "Contactar"}, "image": "https://imgar.zonapropcdn.com/avisos/1/00/53/62/35/37/360x266/1910509220.jpg?isFirstImage=true", "title": "Departamento de 1 ambiente, Floresta \u00b7 Se Alquila Excelente Piso en Floresta a Metro de Av Ruvadavia"}, "https://www.zonaprop.com.ar/propiedades/clasificado/alclapin-lafuente-al-100-monoambiente-con-balcon-a-la-calle-53620920.html": {"id": "53620920", "date": "16-05-2024\n", "index": 97, "content": "$ 300.000\n$ 47.000 Expensas\nLafuente al 100\nFlores, Capital Federal\n43 m\u00b2 tot.\n1 amb.\n1 dorm.\n1 ba\u00f1o\nMonoambiente en L con balc\u00f3n y placard. Cuenta con aire frio/calor. Cocina a gas con espacio para lavarropasBa\u00f1o completo. Expensas $Ver datosNo se admiten mascotas. Apto profesionalRequisitos: Garant\u00eda de capital o seguro de cauci\u00f3n y justificaci\u00f3n de ingresos. Contrato a dos a\u00f1os con actualizaci\u00f3n trimestral por ipc.\nPublicado hace 5 d\u00edas\nContactar", "revised": false, "rejected": true, "data": {"precio": "$ 300.000", "expensas": "$ 47.000 Expensas", "direccion": "Lafuente al 100", "metros": "43 m\u00b2 tot.", "habitaciones": "1 amb.", "hace": "Contactar"}, "image": "https://imgar.zonapropcdn.com/avisos/1/00/53/62/09/20/360x266/1910442886.jpg?isFirstImage=true", "title": "Departamento \u00b7 40m\u00b2 \u00b7 1 Ambiente \u00b7 Lafuente Al 100 - Monoambiente con Balc\u00f3n a La Calle"}, "https://www.zonaprop.com.ar/propiedades/clasificado/alclapin-alquiler-flores-caracas-300-53614842.html": {"id": "53614842", "date": "16-05-2024\n", "index": 116, "content": "$ 270.000\n$ 42.000 Expensas\nCaracas 300\nFlores Norte, Flores\n42 m\u00b2 tot.\n2 amb.\n1 dorm.\n1 ba\u00f1o\nAlquiler 2 ambientes. ley 5859: Art\u00edculo 4\u00b0. - Incorp\u00f3rase como inciso 8 del art\u00edculo 10 de la Ley 2340 (texto consolidado seg\u00fan Ley N\u00b0 5666) el siguiente texto: Para los casos de alquiler de vivienda, el monto m\u00e1ximo de comisi\u00f3n que se le puede requerir a los propietarios ser\u00e1 el equivalente al cuatro con quince cent\u00e9simos por ciento (4, 15%) del valor total del respectivo contrato. Se encuentra prohibido cobrar a los inquilinos que sean personas f\u00edsicas comisiones inmobiliarias y gastos de gestor\u00eda de informes. - Ley 5115: excepto que en la descripci\u00f3n de la propiedad se indique lo contrario, el edificio puede no contar con rampa para personas con movilidad reducida, y no ser Accesible para personas con discapacidades f\u00edsicas. - Nota importante: Toda la informaci\u00f3n y medidas provistas son aproximadas, deber\u00e1n ratificarse con la documentaci\u00f3n pertinente y no compromete contractualmente a nuestra empresa. Los gastos (expensas, abl) expresados refieren a la \u00faltima informaci\u00f3n recabada y deber\u00e1n confirmarse. Fotograf\u00edas no vinculantes ni contractuales. Torrisi propiedades. eduardo esp\u00edndola. mat. C. U. C. I. C. B. A nro. 26\nPublicado hace 6 d\u00edas\nContactar", "revised": false, "rejected": true, "data": {"precio": "$ 270.000", "expensas": "$ 42.000 Expensas", "direccion": "Caracas 300", "metros": "42 m\u00b2 tot.", "habitaciones": "2 amb.", "hace": "Contactar"}, "image": "https://imgar.zonapropcdn.com/avisos/1/00/53/61/48/42/360x266/1910311100.jpg?isFirstImage=true", "title": "Departamento \u00b7 42m\u00b2 \u00b7 2 Ambientes \u00b7 Alquiler - Flores - Caracas 300"}, "https://www.zonaprop.com.ar/propiedades/clasificado/alclapin-paraguay-2800-pb-2-amb-alquiler-53619100.html": {"id": "53619100", "date": "16-05-2024\n", "index": 120, "content": "$ 280.000\n$ 34.000 Expensas\nParaguay 2800 PB - 2 amb Alquiler\nAlmagro, Capital Federal\n40 m\u00b2 tot.\n2 amb.\n1 dorm.\n1 ba\u00f1o\nDepartamento de 2 amb en Planta Baja con patio de 10m2. Excelente zona. Zarlenga Inmobiliaria - Matricula: 7057 - aviso legal: Las descripciones arquitect\u00f3nicas y funcionales, valores de expensas, impuestos y servicios, fotos y medidas de este inmueble son aproximados. Los datos fueron proporcionados por el propietario y pueden no estar actualizados a la hora de la visualizaci\u00f3n de este aviso por lo cual pueden arrojar inexactitudes y discordancias con las que surgen de las facturas, t\u00ed\u00adtulos y planos legales del inmueble. El interesado deber\u00e1 realizar las verificaciones respectivas previamente a la realizaci\u00f3n de cualquier operaci\u00c3\u00b3n, requiriendo por s\u00fa\u00ad o sus profesionales las copias necesarias de la documentaci\u00f3n que corresponda. Venta supeditada al cumplimiento por parte del propietario de los requisitos de la resoluci\u00f3n general Nro. 2371 de la afip (pedido de coti).\nPublicado hace 6 d\u00edas\nContactar", "revised": false, "rejected": true, "data": {"precio": "$ 280.000", "expensas": "$ 34.000 Expensas", "direccion": "Paraguay 2800 PB - 2 amb Alquiler", "metros": "40 m\u00b2 tot.", "habitaciones": "2 amb.", "hace": "Contactar"}, "image": "https://imgar.zonapropcdn.com/avisos/1/00/53/61/91/00/360x266/1910401194.jpg?isFirstImage=true", "title": "Departamento \u00b7 30m\u00b2 \u00b7 2 Ambientes \u00b7 Paraguay 2800 Pb - 2 Amb Alquiler"}, "https://www.zonaprop.com.ar/propiedades/clasificado/alclappa-alquiler-2-ambientes-en-congreso-sobre-av-de-mayo-53619396.html": {"id": "53619396", "date": "16-05-2024\n", "index": 123, "content": "$ 300.000\nAv. de Mayo 1300\nMonserrat, Capital Federal\n35 m\u00b2 tot.\n2 amb.\n1 dorm.\n1 ba\u00f1o\nDepartamento de 35 m2 - Apto profesional (el encargado abre la puerta de 10 a 20hs) Encargado nocturno. Agua caliente central. $300. 000 (aumento trimestral por ipc) Requisitos: - Contrato a 2 a\u00f1os. - Aumento trimestral por ipc. - Recibo de sueldo con antig\u00fcedad. - Garant\u00eda propietario caba o Seguro de Cauci\u00f3n.\nPublicado hace 6 d\u00edas\nContactar", "revised": false, "rejected": true, "data": {"precio": "$ 300.000", "expensas": "", "direccion": "Av. de Mayo 1300", "metros": "35 m\u00b2 tot.", "habitaciones": "2 amb.", "hace": "Contactar"}, "image": "https://imgar.zonapropcdn.com/avisos/1/00/53/61/93/96/360x266/1910409712.jpg?isFirstImage=true", "title": "Departamento de 2 ambientes, Monserrat \u00b7 Alquiler 2 Ambientes en Congreso Sobre Av de Mayo"}, "https://www.zonaprop.com.ar/propiedades/clasificado/alclappa-excelinte-departamento-muy-luminoso-53614772.html": {"id": "53614772", "date": "16-05-2024\n", "index": 124, "content": "$ 300.000\n$ 40.000 Expensas\nAvenida San Pedrito 200\nFlores Norte, Flores\n49 m\u00b2 tot.\n2 amb.\n1 dorm.\nDue\u00f1o alquila departamento 2 ambientes al frente en flores. Excelente unidad de 49 m2, ubicada en el barrio de Flores a dos cuadras de Av. Rivadavia y dos cuadras de Directorio. Accesibilidad a numerosas l\u00edneas de colectivos. A dos cuadras boca de subte l\u00ednea A y a cuatro cuadras de la estaci\u00f3n Flores del ferrocarril Sarmiento. El departamento consta de living-comedor con salida al balc\u00f3n corrido, un dormitorio con amplio placard, pasillo con placard y un ba\u00f1o completo. Cocina independiente completamente equipada con muebles bajo mesada, alacenas, comedor diario con modular y lavadero Rincorporado. S\u00faper luminoso y aireado. Consultar por watta app O mail. condiciones: Contrato a 2 a\u00f1os con ajuste trimestral por ipc 1 mes por adelantado, 1 mes de dep\u00f3sito, garant\u00eda propietaria en C. A. B. A \u00f3 finaer aprobado. , ingresos comprobables. Expensas, abl- Aysa\nPublicado hace 6 d\u00edas\nContactar", "revised": false, "rejected": true, "data": {"precio": "$ 300.000", "expensas": "$ 40.000 Expensas", "direccion": "Avenida San Pedrito 200", "metros": "49 m\u00b2 tot.", "habitaciones": "2 amb.", "hace": "Contactar"}, "image": "https://imgar.zonapropcdn.com/avisos/1/00/53/61/47/72/360x266/1910335721.jpg?isFirstImage=true", "title": "Departamento de 2 ambientes, Flores \u00b7 Excelinte Departamento Muy Luminoso"}, "https://www.zonaprop.com.ar/propiedades/clasificado/alclapin-alquiler-dos-ambientes-en-microcentro-53612274.html": {"id": "53612274", "date": "16-05-2024\n", "index": 131, "content": "$ 300.000\n$ 20.000 Expensas\nTeniente General Juan Domingo Per\u00f3n 1100\nSan Nicol\u00e1s, Capital Federal\n37 m\u00b2 tot.\n2 amb.\n1 dorm.\n1 ba\u00f1o\nCorredor Responsable: Hernan Perrone cucicba 2792 / mgr 170- Contacto: Mariano Romano - mls id # Ver datos-34. El equipo re/max te presenta este alquiler de dos ambientes en el microcentro. Consta de hall de recepci\u00f3n, cocina a gas con espacio para heladera, habitaci\u00f3n, ba\u00f1o y comedor. Tienes la posibilidad de modificarse para obtener un segundo dormitorio, en tal caso, quedar\u00eda un living comedor chico. Consultanos para concretar una visita. Mudate a la vida que quer\u00e9s! Remax Argentina S. R. L. No ejerce el corretaje inmobiliario. El presente sitio web es una plataforma en donde cada oficina inmobiliaria independiente que contrata los servicios re/max puede publicar las propiedades a su cargo. Cada oficina es de propiedad y gesti\u00f3n independiente, por lo que Remax Argentina S. R. L no interviene en los datos de la publicaci\u00f3n, en la operaci\u00f3n inmobiliaria, ni en la confecci\u00f3n y/o firma del boleto de compraventa y/o escritura y/o contrato de alquiler. En cumplimiento de las leyes vigentes que regulan el corretaje inmobiliario, Ley Nacional 25. 028, Ley 22. 802 de Lealtad Comercial, Ley 24. 240 de Defensa al Consumidor, las normas del C\u00f3digo Civil y Comercial de la Naci\u00f3n y Constitucionales, los agentes/gestores no ejercen el corretaje inmobiliario. Todas las operaciones inmobiliarias son objeto de intermediaci\u00f3n y conclusi\u00f3n por parte del corredor p\u00fablico inmobiliario colegiado a cargo de la publicaci\u00f3n, cuyos datos se exhiben en la presente. La presente publicaci\u00f3n describe las caracter\u00edsticas esenciales del inmueble, debi\u00e9ndose consultar al corredor p\u00fablico inmobiliario responsable de la operaci\u00f3n por la eventual actualizaci\u00f3n de las medidas, descripciones arquitect\u00f3nicas y funcionales, valores de expensas, servicios, impuestos, precios y dem\u00e1s informaci\u00f3n, cuyos valores son aproximados. Para los casos de alquiler de vivienda, el monto m\u00e1ximo de comisi\u00f3n que se le puede requerir a los propietarios ser\u00e1 el equivalente al cuatro con quince cent\u00e9simos por ciento (4, 15%) del valor total del respectivo contrato. Se encuentra prohibido cobrar a los inquilinos que sean personas f\u00edsicas comisiones inmobiliarias y gastos de gestor\u00eda de informes. El inmueble no es accesible para personas con discapacidades f\u00edsicas.\nPublicado hace 7 d\u00edas\nContactar", "revised": false, "rejected": true, "data": {"precio": "$ 300.000", "expensas": "$ 20.000 Expensas", "direccion": "Teniente General Juan Domingo Per\u00f3n 1100", "metros": "37 m\u00b2 tot.", "habitaciones": "2 amb.", "hace": "Contactar"}, "image": "https://imgar.zonapropcdn.com/avisos/1/00/53/61/22/74/360x266/1910234033.jpg?isFirstImage=true", "title": "Departamento \u00b7 37m\u00b2 \u00b7 2 Ambientes \u00b7 Alquiler Dos Ambientes en Microcentro"}}