{"https://www.zonaprop.com.ar/propiedades/clasificado/alclapin-monserrat-4-ambientes-bano-toillette-interno-53585883.html": {"id": "53585883", "date": "07-05-2024\n", "index": 1, "content": "12\n$ 500.000\n$ 35.000 Expensas\nHipolito Yrigoyen al 2500\nMonserrat, Capital Federal\n75 m\u00b2 tot.\n4 amb.\n2 dorm.\n1 ba\u00f1o\nMonserrat 4 ambientes ba\u00f1O toillette interno, igualmente luminoso no tiene balcon, amplia cocina. Sup total 75 M2Queda una heladera y un placard. La vista del patio que se ve en fotos es el camino que hay que cruzar para ir el al segundo cuerpo del edificio que es donde se encuentra el departamento. No paga Expensas ya que es Edificio Patrimonial Con bella arquitectura. Incremento Cuatrimestral por ipc **Corredor Inmobiliario Responsable Adrian Ridelnik cucicba Mat 197. *Se deja constancia que las medidas y superficies indicados son aproximados y al s\u00f3lo efecto orientativo. Las medidas reales surgir\u00e1n del t\u00edtulo de propiedad respectivo. Las medidas parciales y/o de los ambientes y el valor consignado de expensas mensuales, servicios y abl est\u00e1 sujeto a verificaci\u00f3n y/o ajuste. Art. 4 de la Ley 5. 859 de C. A. B. A \"Para los casos de alquiler de vivienda \u00fanica, el monto m\u00e1ximo de comisi\u00f3n que se le puede requerir a los propietarios ser\u00e1 el equivalente al cuatro con quince cent\u00e9simos por ciento (4, 15%) del valor total del respectivo contrato. Se encuentra prohibido cobrar a los inquilinos que sean personas f\u00edsicas comisiones inmobiliarias cuando el destino sea vivienda \u00fanica y permanente \". -\nPublicado desde ayer\nContactar", "revised": false, "rejected": false, "data": {"precio": "$ 500.000", "expensas": "$ 35.000 Expensas", "direccion": "Hipolito Yrigoyen al 2500", "metros": "75 m\u00b2 tot.", "habitaciones": "4 amb.", "hace": "Contactar"}, "image": "https://imgar.zonapropcdn.com/avisos/1/00/53/58/58/83/360x266/1909658948.jpg?isFirstImage=true", "title": "Departamento \u00b7 75m\u00b2 \u00b7 4 Ambientes \u00b7 Monserrat 4 Ambientes Ba\u00f1o Toillette Interno, Igualmente Luminoso No Tiene Balcon"}, "https://www.zonaprop.com.ar/propiedades/clasificado/alclapin-departamento-en-alquiler-de-2-dorm.-en-monserrat-53588979.html": {"id": "53588979", "date": "07-05-2024\n", "index": 2, "content": "11\n$ 450.000\n$ 50.000 Expensas\nAv. Belgrano 1181\nMonserrat, Capital Federal\n69 m\u00b2 tot.\n3 amb.\n2 dorm.\n1 ba\u00f1o\nEn una ubicaci\u00f3n privilegiada en Av. Belgrano, Monserrat, Capital Federal, se encuentra disponible este exclusivo departamento de 3 ambientes para alquiler. Conformado por 2 dormitorios, 1 ba\u00f1o y una cocina equipada, esta propiedad ofrece un espacio elegante y funcional para aquellos que buscan vivir en una zona c\u00e9ntrica de la ciudad. , este departamento se destaca por su disposici\u00f3n contrafrente, brindando tranquilidad y privacidad a sus ocupantes. Adem\u00e1s, cuenta con comodidades como un lavadero, living comedor y conexi\u00f3n para lavarropas, garantizando una experiencia de vida c\u00f3moda y conveniente. Entre las caracter\u00edsticas destacadas de esta propiedad se encuentran la presencia de servicios de agua corriente, gas natural y luz, elementos esenciales para el confort diario. Las expensas mensuales ascienden a $50. 000, lo que asegura el mantenimiento adecuado de las \u00e1reas comunes y servicios del edificio. Con un entorno accesible y una distribuci\u00f3n bien pensada, este departamento en alquiler se presenta como una oportunidad \u00fanica para aquellos que valoran la calidad de vida en un ambiente exclusivo y bien ubicado en la capital. En resumen, este departamento en Av. Belgrano, Monserrat, Capital Federal, ofrece la combinaci\u00f3n perfecta entre elegancia, funcionalidad y ubicaci\u00f3n estrat\u00e9gica. Con sus 3 ambientes bien distribuidos y comodidades modernas, representa una opci\u00f3n ideal para quienes buscan un estilo de vida sofisticado en el coraz\u00f3n de la ciudad. No pierdas la oportunidad de vivir en este extraordinario espacio que re\u00fane todas las cualidades que un hogar de lujo puede ofrecer en una de las zonas m\u00e1s codiciadas de Buenos Aires. \u00a1Ll\u00e1menos para conocer m\u00e1s en detalle esta propiedad! Tel: Ver datos. Email: Ver datos. De la Torre Propiedades\nPublicado desde ayer\nContactar", "revised": false, "rejected": false, "data": {"precio": "$ 450.000", "expensas": "$ 50.000 Expensas", "direccion": "Av. Belgrano 1181", "metros": "69 m\u00b2 tot.", "habitaciones": "3 amb.", "hace": "Contactar"}, "image": "https://imgar.zonapropcdn.com/avisos/1/00/53/58/89/79/360x266/1909726994.jpg?isFirstImage=true", "title": "Departamento de 3 ambientes, Monserrat \u00b7 Departamento en Alquiler de 2 Dorm. en Monserrat"}, "https://www.zonaprop.com.ar/propiedades/clasificado/alclapin-alquiler-dpto-tribunales-3-amb-con-cochera-53589684.html": {"id": "53589684", "date": "07-05-2024\n", "index": 3, "content": "$ 450.000\n$ 150.000 Expensas\nLavalle 1500\nSan Nicol\u00e1s, Capital Federal\n63 m\u00b2 tot.\n3 amb.\n2 dorm.\n1 ba\u00f1o\n1 coch.\nCorredor Responsable: Marcelo Trujillo cucicba 6470 / cmcpdjlm 810- Contacto: Rodrigo Varela - mls id # Ver datos. El equipo Remax Alquila gran departamento de categoria, con cochera, apto tanto para vivienda como para Oficinas. Caracteristicas del edificio: - Expensas $ 150. 000. - Porteria presencial y encargado/seguridad al ingreso del edificio. - 3 modernos ascensores. - Gran recepci\u00f3n con m\u00e1rmol. - Cochera incluida con el alquiler en edificio enfrente. Caracteristicas del departamento: -Doble circulacion entre pulmon del edificio y el contrafrente al pulmon de manzana. -Apto para vivienda con 2 dormitorios o para 3 oficinas y una recepcion. -Agua caliente por calefon. -Calefaccion mediante estufas tiro balanceado. - Muy Buena luminosidad. -La unidad de encuentra en buen estado de conservacion. -La propiedad se alquila amoblada. Condiciones: * Plazo: 24 meses. * Actualizaci\u00f3n: Trimestral seg\u00fan \u00cdndice de Precios al Consumidor (ipc). * Garantia de Caucion. * 1 mes de deposito y 1 mes de adelanto. No dude en consultar lo que necesite y coordinar una visita. Remax Argentina S. R. L. No ejerce el corretaje inmobiliario. El presente sitio web es una plataforma en donde cada oficina inmobiliaria independiente que contrata los servicios re/max puede publicar las propiedades a su cargo. Cada oficina es de propiedad y gesti\u00f3n independiente, por lo que Remax Argentina S. R. L no interviene en los datos de la publicaci\u00f3n, en la operaci\u00f3n inmobiliaria, ni en la confecci\u00f3n y/o firma del boleto de compraventa y/o escritura y/o contrato de alquiler. En cumplimiento de las leyes vigentes que regulan el corretaje inmobiliario, Ley Nacional 25. 028, Ley 22. 802 de Lealtad Comercial, Ley 24. 240 de Defensa al Consumidor, las normas del C\u00f3digo Civil y Comercial de la Naci\u00f3n y Constitucionales, los agentes/gestores no ejercen el corretaje inmobiliario. Todas las operaciones inmobiliarias son objeto de intermediaci\u00f3n y conclusi\u00f3n por parte del corredor p\u00fablico inmobiliario colegiado a cargo de la publicaci\u00f3n, cuyos datos se exhiben en la presente. La presente publicaci\u00f3n describe las caracter\u00edsticas esenciales del inmueble, debi\u00e9ndose consultar al corredor p\u00fablico inmobiliario responsable de la operaci\u00f3n por la eventual actualizaci\u00f3n de las medidas, descripciones arquitect\u00f3nicas y funcionales, valores de expensas, servicios, impuestos, precios y dem\u00e1s informaci\u00f3n, cuyos valores son aproximados. El inmueble no es accesible para personas con discapacidades f\u00edsicas.\nPublicado desde ayer\nContactar", "revised": false, "rejected": true, "data": {"precio": "$ 450.000", "expensas": "$ 150.000 Expensas", "direccion": "Lavalle 1500", "metros": "63 m\u00b2 tot.", "habitaciones": "3 amb.", "hace": "Contactar"}, "image": "https://imgar.zonapropcdn.com/avisos/1/00/53/58/96/84/360x266/1909739428.jpg?isFirstImage=true", "title": "Departamento \u00b7 63m\u00b2 \u00b7 3 Ambientes \u00b7 1 Cochera \u00b7 Alquiler Dpto Tribunales 3 Amb con Cochera"}, "https://www.zonaprop.com.ar/propiedades/clasificado/alclapin-hermoso-y-amplio-departamento-en-san-jose-y-belgrano-53582801.html": {"id": "53582801", "date": "07-05-2024\n", "index": 4, "content": "$ 500.000\n$ 80.000 Expensas\nSAN JOSE 300\nSan Nicol\u00e1s, Capital Federal\n100 m\u00b2 tot.\n3 amb.\n2 dorm.\n1 ba\u00f1o\nSemipiso al frente en edificio de estilo. living Y comedor con pisos de pinotea al frente con balcon frances. escritorio O dormitorio. hall destribuidor. dos habitaciones comodas. amplio placard en pasillo. ba\u00f1o completo con ventilacion. cocina con comedor diario con lavavajillas refaccionado. dependencia con ba\u00f1o. todo en excelente estado. servicios individuales. se requiere sin excepcion garantia caba O finaer Y constancias de ingresos demostrables. contrato con ajuste trimestral\nPublicado desde ayer\nContactar", "revised": false, "rejected": false, "data": {"precio": "$ 500.000", "expensas": "$ 80.000 Expensas", "direccion": "SAN JOSE 300", "metros": "100 m\u00b2 tot.", "habitaciones": "3 amb.", "hace": "Contactar"}, "image": "https://imgar.zonapropcdn.com/avisos/1/00/53/58/28/01/360x266/1909591447.jpg?isFirstImage=true", "title": "Departamento de 3 ambientes, San Nicol\u00e1s \u00b7 Hermoso y Amplio Departamento en San Jose y Belgrano 100 m de Estilo"}, "https://www.zonaprop.com.ar/propiedades/clasificado/alclapin-m-av-belgrano-subte-h-3-amb-con-balcon-cfte-vista-53552379.html": {"id": "53552379", "date": "07-05-2024\n", "index": 7, "content": "$ 440.000\n$ 46.000 Expensas\nALBERTI 355 10 PISO C\nSan Nicol\u00e1s, Capital Federal\n80 m\u00b2 tot.\n3 amb.\n2 dorm.\n1 ba\u00f1o\nSuper luminoso departamento de 3 ambientes en contra-frente, moderno, con 2 equipos de aire acondicionado split frio-calor! Amplio living comedor con salida al balc\u00f3n, 2 dormitorios con placard, ba\u00f1o completo, cocina amplia con comedor diario, lavadero. Adem\u00e1s cuenta con una puerta de acceso blindada, pisos de parquet plastificados. \u00a1oportunidad! Precio: $ 440. 000 mensuales el primer trimestre; luego se actualiza con el indice de precios al consumidor aplicado al 50% Y el indice de ripte (salarios) al 50% condiciones: 1 mes adelantado, un mes de dep\u00f3sito. El locatario y su garante deber\u00e1n poseer ingresos mensuales en relaci\u00f3n de dependencia equivalentes A 2/3 veces el importe del alquiler mensual, no es una exigencia para el garante ser propietario en la ciudad de buenos aires. Para visitar llamar A R. Besada & asociados - Ver datos y/o Ver datos. \"Para los casos de alquiler de vivienda, el monto m\u00e1ximo de comisi\u00f3n que se le puede requerir a los propietarios ser\u00e1 el equivalente al cuatro con quince cent\u00e9simos por ciento (4, 15%) del valor total del respectivo contrato. Se encuentra prohibido cobrar a los inquilinos que sean personas f\u00edsicas comisiones inmobiliarias y gastos de gestar\u00eda de informes\". Ruben M besada - Matricula cucicba N. \u00ba 2645 -\nPublicado hace 7 d\u00edas\nContactar", "revised": false, "rejected": false, "data": {"precio": "$ 440.000", "expensas": "$ 46.000 Expensas", "direccion": "ALBERTI 355 10 PISO C", "metros": "80 m\u00b2 tot.", "habitaciones": "3 amb.", "hace": "Contactar"}, "image": "https://imgar.zonapropcdn.com/avisos/1/00/53/55/23/79/360x266/1908917751.jpg?isFirstImage=true", "title": "Departamento de 3 ambientes, San Nicol\u00e1s \u00b7 M Av Belgrano, Subte \"H\" 3 Amb con Balcon Cfte, Vista Abierta, 2 Split F/c"}, "https://www.zonaprop.com.ar/propiedades/clasificado/alclapin-3-ambientes-al-contra-frente-53557131.html": {"id": "53557131", "date": "07-05-2024\n", "index": 8, "content": "$ 360.000\n$ 45.000 Expensas\nSan Jose 800 6\u00b0\nMonserrat, Capital Federal\n62 m\u00b2 tot.\n3 amb.\n2 dorm.\n1 ba\u00f1o\n3 ambientes comodos al contrafrente. Luz Y sol. cocina amplia con espacio comedor. lavadero independiente con pileta Y espacio para lavarropas. dos amplios doritorios, ambos con placar. living comedor con ventanal al contrafrente. Vista abierta. expensas $Ver datos. aysa. abl. luz. gas. requisitos: garantia propietaria de caba O seguro de caucion argenprop. 1 mes de deposito en garantia. 1 mes adelantado. demostracion de ingresos acordes al alquiler. contrato por 2 a\u00f1os ajustable por ipc cuatrimestralmente. informes comerciales Y laborales. contactenos para visita. Ver datos whatsapp. Ver datos/5. eugenio A ferraro propiedades\nPublicado hace 7 d\u00edas\nContactar", "revised": false, "rejected": false, "data": {"precio": "$ 360.000", "expensas": "$ 45.000 Expensas", "direccion": "San Jose 800 6\u00b0", "metros": "62 m\u00b2 tot.", "habitaciones": "3 amb.", "hace": "Contactar"}, "image": "https://imgar.zonapropcdn.com/avisos/1/00/53/55/71/31/360x266/1909228460.jpg?isFirstImage=true", "title": "Departamento \u00b7 62m\u00b2 \u00b7 3 Ambientes \u00b7 3 Ambientes Al Contra Frente"}, "https://www.zonaprop.com.ar/propiedades/clasificado/alclapin-departamento-en-alquiler-3-amb-con-dep-y-cochera-53547633.html": {"id": "53547633", "date": "07-05-2024\n", "index": 9, "content": "$ 700.000\n$ 145.000 Expensas\nLibertad 800\nSan Nicol\u00e1s, Capital Federal\n83 m\u00b2 tot.\n3 amb.\n2 dorm.\n2 ba\u00f1os\n1 coch.\nCorredor Responsable: Diego Mastrangelo cucicba 7615 csi 6609- Contacto: Dalma Manzi Olivera - mls id # Ver datos-37. Alquiler Residencial departamento 3 amb con dependencia y cochera. Requisitos: - Ingresos demostrables para garantizar un acuerdo de alquiler exitoso y sin complicaciones, requerimos que los solicitantes demuestren ingresos suficientes para cumplir con el pago mensual del alquiler. - Fianza garantor. - Mes de Deposito. - Mes de Alquiler Adelantado. Caracteristicas: Living-Comedor integrado. Hall de Distribuci\u00f3n. Cocina independiente. Lavadero incorporado. Un dormitorio con ropero funcional. Segundo dormitorio con ropero funcional. Ba\u00f1o completo con ba\u00f1era. Dependencia de Servicio. Segundo ba\u00f1o completo. Espacio guarda coche cubierto. Para los casos de alquiler de vivienda, el monto m\u00e1ximo de comisi\u00f3n que se le puede requerir a los propietarios ser\u00e1 el equivalente al cuatro con quince cent\u00e9simos por ciento (4, 15%) del valor total del respectivo contrato. Se encuentra prohibido cobrar a los inquilinos que sean personas f\u00edsicas comisiones inmobiliarias y gastos de gestor\u00eda de informes. Remax Argentina S. R. L. No ejerce el corretaje inmobiliario. El presente sitio web es una plataforma en donde cada oficina inmobiliaria independiente que contrata los servicios re/max puede publicar las propiedades a su cargo. Cada oficina es de propiedad y gesti\u00f3n independiente, por lo que Remax Argentina S. R. L no interviene en los datos de la publicaci\u00f3n, en la operaci\u00f3n inmobiliaria, ni en la confecci\u00f3n y/o firma del boleto de compraventa y/o escritura y/o contrato de alquiler. En cumplimiento de las leyes vigentes que regulan el corretaje inmobiliario, Ley Nacional 25. 028, Ley 22. 802 de Lealtad Comercial, Ley 24. 240 de Defensa al Consumidor, las normas del C\u00f3digo Civil y Comercial de la Naci\u00f3n y Constitucionales, los agentes/gestores no ejercen el corretaje inmobiliario. Todas las operaciones inmobiliarias son objeto de intermediaci\u00f3n y conclusi\u00f3n por parte del corredor p\u00fablico inmobiliario colegiado a cargo de la publicaci\u00f3n, cuyos datos se exhiben en la presente. La presente publicaci\u00f3n describe las caracter\u00edsticas esenciales del inmueble, debi\u00e9ndose consultar al corredor p\u00fablico inmobiliario responsable de la operaci\u00f3n por la eventual actualizaci\u00f3n de las medidas, descripciones arquitect\u00f3nicas y funcionales, valores de expensas, servicios, impuestos, precios y dem\u00e1s informaci\u00f3n, cuyos valores son aproximados. Para los casos de alquiler de vivienda, el monto m\u00e1ximo de comisi\u00f3n que se le puede requerir a los propietarios ser\u00e1 el equivalente al cuatro con quince cent\u00e9simos por ciento (4, 15%) del valor total del respectivo contrato. Se encuentra prohibido cobrar a los inquilinos que sean personas f\u00edsicas comisiones inmobiliarias y gastos de gestor\u00eda de informes. El inmueble no es accesible para personas con discapacidades f\u00edsicas.\nPublicado hace 8 d\u00edas\nContactar", "revised": false, "rejected": true, "data": {"precio": "$ 700.000", "expensas": "$ 145.000 Expensas", "direccion": "Libertad 800", "metros": "83 m\u00b2 tot.", "habitaciones": "3 amb.", "hace": "Contactar"}, "image": "https://imgar.zonapropcdn.com/avisos/1/00/53/54/76/33/360x266/1908805037.jpg?isFirstImage=true", "title": "Departamento \u00b7 83m\u00b2 \u00b7 3 Ambientes \u00b7 1 Cochera \u00b7 Departamento en Alquiler 3 Amb con Dep y Cochera"}, "https://www.zonaprop.com.ar/propiedades/clasificado/alclappa-clasico-y-funcional-53546529.html": {"id": "53546529", "date": "07-05-2024\n", "index": 10, "content": "$ 600\nVenezuela 1100\nMonserrat, Capital Federal\n70 m\u00b2 tot.\n3 amb.\n2 dorm.\n1 ba\u00f1o\nDepartamento luminoso, c\u00f3modo, funcional, a 8 cuadras del obelisco, medios de transporte a mano. Calefacci\u00f3n y Aire acondicionado. Bajas expensas. Ideal\nPublicado hace 8 d\u00edas\nContactar", "revised": false, "rejected": false, "data": {"precio": "$ 600", "expensas": "", "direccion": "Venezuela 1100", "metros": "70 m\u00b2 tot.", "habitaciones": "3 amb.", "hace": "Contactar"}, "image": "https://imgar.zonapropcdn.com/avisos/1/00/53/54/65/29/360x266/1908785083.jpg?isFirstImage=true", "title": "Departamento de 3 ambientes, Monserrat \u00b7 Cl\u00e1sico y Funcional"}, "https://www.zonaprop.com.ar/propiedades/clasificado/alclapin-departamento-en-alquiler-barrio-balvanera-53542165.html": {"id": "53542165", "date": "07-05-2024\n", "index": 11, "content": "$ 400.000\n$ 50.000 Expensas\nIndependencia 1200\nMonserrat, Capital Federal\n70 m\u00b2 tot.\n3 amb.\n2 dorm.\n1 ba\u00f1o\nDepartamento de 70m2, cuenta con un ba\u00f1o con ducha y adem\u00e1s ba\u00f1o privado. Posee un patio descubierto, buen ingreso de luz natural. Muy buena ubicaci\u00f3n, cercano a Avenida 9 de Julio y universidad uade. Muy bien conectado con transporte p\u00fablico: Transportes Cercanos: Colectivos: 2, 9, 10, 17, 23, 39, 45, 53, 57, 59, 60, 67, 70, 91, 96, 98, 100, 102, 126, 129, 168, 195Subtes (Metro) : independencia (L\u00ednea C) , independencia (L\u00ednea E) Datos \u00fatiles: \u00c1rea Hospitalaria: htal. Dr. J. M. Ramos mej\u00edadistrito Escolar: Distrito Escolar iiimatriculado responsable: Roberto Barral matr\u00edcula N\u00ba3006 cucicba. ? En el cumplimiento de la ley nacional 25. 028, ley 22. 802 de lealtad comercial. ? Ley 24. 240 de defensa al consumidor, las normas del c\u00f3digo civil y comercial de la naci\u00f3n y constitucionales. Los agentes no ejercen el corretaje inmobiliario. ? Ley 5859 -Art. 4: \"Para los casos de alquiler de vivienda, el monto m\u00e1ximo de comisi\u00f3n que se le puede requerir a los propietarios ser\u00e1 el equivalente al cuatro con quince cent\u00e9simos por ciento (4, 15%) del valor total del contrato. Se encuentra prohibido cobrar a los inquilinos que sean personas f\u00edsicas comisiones inmobiliarias y gastos de gestor\u00eda de informes\". (En caso de ser alquiler) ? Ley 5115 \u2013 Art. 1: El inmueble publicado no es accesible para personas con capacidades f\u00edsicas reducidas. (En caso de no ser accesible) ? Se deja constancia que las medidas, superficies y m2 consignados son aproximados, sujetos a verificaci\u00f3n y/o ajuste. El precio del inmueble puede ser modificado sin previo aviso.\nDestacado\nPublicado hace 9 d\u00edas\nContactar", "revised": false, "rejected": true, "data": {"precio": "$ 400.000", "expensas": "$ 50.000 Expensas", "direccion": "Independencia 1200", "metros": "70 m\u00b2 tot.", "habitaciones": "3 amb.", "hace": "Contactar"}, "image": "https://imgar.zonapropcdn.com/avisos/1/00/53/54/21/65/360x266/1909681126.jpg?isFirstImage=true", "title": "Departamento \u00b7 70m\u00b2 \u00b7 3 Ambientes \u00b7 Departamento en Alquiler Barrio Balvanera"}, "https://www.zonaprop.com.ar/propiedades/clasificado/alclapin-oficina-monserrat-53501402.html": {"id": "53501402", "date": "07-05-2024\n", "index": 15, "content": "$ 550.000\n$ 76.000 Expensas\nAvenida Belgrano al 500\nMonserrat, Capital Federal\n60 m\u00b2 tot.\n3 amb.\n2 dorm.\n2 ba\u00f1os\nOficina en primer piso. Ascensor. Cableado estructurado ethernet, 7 puestos de trabajo, aire acondicionado en los 3 ambientes. Muy buena zona, excelentes accesos, 4 cuadras de plaza de Mayo. Dos ba\u00f1os. Patio interno. Salon de reuni\u00f3n con ba\u00f1o privado. Cocina. Muebles. muy luminosa, silenciosa y tranquila.\nSuper destacado\nPublicado hace 13 d\u00edas\nContactar", "revised": false, "rejected": true, "data": {"precio": "$ 550.000", "expensas": "$ 76.000 Expensas", "direccion": "Avenida Belgrano al 500", "metros": "60 m\u00b2 tot.", "habitaciones": "3 amb.", "hace": "Contactar"}, "image": "https://imgar.zonapropcdn.com/avisos/1/00/53/50/14/02/360x266/1907721808.jpg?isFirstImage=true", "title": "Departamento \u00b7 60m\u00b2 \u00b7 3 Ambientes \u00b7 Oficina - Monserrat"}, "https://www.zonaprop.com.ar/propiedades/clasificado/alclapin-tte.-gral.-juan-domingo-peron-1700-departamento-en-53481301.html": {"id": "53481301", "date": "07-05-2024\n", "index": 17, "content": "$ 400.000\n$ 130.000 Expensas\nTte. Gral. Juan Domingo Peron al 1700\nSan Nicol\u00e1s, Capital Federal\n60 m\u00b2 tot.\n3 amb.\n2 dorm.\n1 ba\u00f1o\nDepartamento 3 ambientes al frente, en el piso 13 excelente vista abierta a Ciudad. Se ingresa por un elegante hall que te lleva a los 3 ascensores. Apto profesional El edificio cuenta con encargado permanente y personal de seguridad nocturno. Al ingresar al departamento te encontras con un espacioso living comedor con un amplio ventanal que da mucha luminosidad, con piso de parquet de madera y paredes pintadas latex, cuenta con equipo de aire acondicionado. Al ingresar al pasillo con aplios placares con sus interiores, te lleva hacia las dos habitaciones, tambi\u00e9n muy luminosas y con piso de parquet de madera y paredes pintadas al l\u00e1tex. Cuenta cuenta con un ba\u00f1o amplio y completo con lavatorio, inodoro, bidet y ba\u00f1era. Requisitos: Mes de adelanto ($ 420. 000) Mes de dep\u00f3sito (U$S420) Contrato a dos a\u00f1os en Pesos y con ajustes cuatrimestrales. Ajuste por ipcno se cobran honorariosOcupaci\u00f3n m\u00e1xima 4 personas. no apto mascotas. Requisitos para alquilar: no necesita garantia propietaria! Aceptamos Seguro de cauci\u00f3n!! Garantia premier S. A. \u00daltimos dos recibos de sueldo en blanco que triplique el valor del alquiler y no poseer deudas con otras entidades. Consulte los costos del seguro. Cualquier duda o consulta no dude en contactarnos, estamos a disposici\u00f3n. Inmueble accesible para personas con discapacidad f\u00edsica ley 5115.\nPublicado hace 19 d\u00edas\nContactar", "revised": false, "rejected": false, "data": {"precio": "$ 400.000", "expensas": "$ 130.000 Expensas", "direccion": "Tte. Gral. Juan Domingo Peron al 1700", "metros": "60 m\u00b2 tot.", "habitaciones": "3 amb.", "hace": "Contactar"}, "image": "https://imgar.zonapropcdn.com/avisos/1/00/53/48/13/01/360x266/1907274221.jpg?isFirstImage=true", "title": "Departamento \u00b7 60m\u00b2 \u00b7 3 Ambientes \u00b7 Tte. Gral. Juan Domingo Peron 1700 Departamento en Alquiler 3 Ambientes Al Frente"}, "https://www.zonaprop.com.ar/propiedades/clasificado/alclapin-departamento-con-uso-comercial-alquiler-de-3-ambientes-53478539.html": {"id": "53478539", "date": "07-05-2024\n", "index": 18, "content": "$ 500.000\n$ 110.000 Expensas\nDirecci\u00f3n no informada\nMonserrat, Capital Federal\n80 m\u00b2 tot.\n3 amb.\n2 dorm.\n2 ba\u00f1os\nPropiedad en alquiler sobre la calle Moreno, ubicada en Monserrat, Capital Federal. Este departamento, con un precio de ar$550. 000, destaca por su uso comercial, ideal para aquellos que buscan un espacio vers\u00e1til y funcional. Con una orientaci\u00f3n norte que brinda una excelente iluminaci\u00f3n natural, este inmueble de disposici\u00f3n frente cuenta con 3 ambientes distribuidos en 2 dormitorios, 2 ba\u00f1os, cocina y balc\u00f3n, ofreciendo un total de 80 m2, de los cuales 75 m2 son cubiertos y 5 m2 descubiertos. Adem\u00e1s, tiene la ventaja de ser apto profesional, brindando oportunidades comerciales adicionales. Entre las caracter\u00edsticas adicionales, se destacan sus comodidades como agua corriente, gas natural, luz, balc\u00f3n, toilette, ascensor, living comedor y cocina, que garantizan una experiencia de vida confortable y moderna. Con gastos de expensas de $110. 000, este departamento se presenta como una oportunidad \u00fanica para aquellos que buscan combinar espacio residencial con la posibilidad de ejercer actividades comerciales desde la comodidad de su hogar. No pierdas la oportunidad de vivir en un espacio exclusivo y vers\u00e1til en una de las zonas m\u00e1s privilegiadas de la ciudad. En resumen, esta propiedad en alquiler en Monserrat es la elecci\u00f3n perfecta para aquellos que valoran la funcionalidad, el confort y la versatilidad en su estilo de vida. Con una ubicaci\u00f3n estrat\u00e9gica y una distribuci\u00f3n pensada para maximizar el espacio, este departamento con uso comercial ofrece una oportunidad \u00fanica para aquellos que buscan un espacio que se adapte a sus necesidades tanto residenciales como laborales. \u00a1Cont\u00e1ctanos hoy mismo para conocer m\u00e1s detalles y aprovechar esta incre\u00edble oferta!\nPublicado hace 19 d\u00edas\nContactar", "revised": false, "rejected": true, "data": {"precio": "$ 500.000", "expensas": "$ 110.000 Expensas", "direccion": "Direcci\u00f3n no informada", "metros": "80 m\u00b2 tot.", "habitaciones": "3 amb.", "hace": "Contactar"}, "image": "https://imgar.zonapropcdn.com/avisos/1/00/53/47/85/39/360x266/1907216033.jpg?isFirstImage=true", "title": "Departamento de 3 ambientes, Monserrat \u00b7 Departamento con Uso Comercial Alquiler de 3 Ambientes en Monserrat"}, "https://www.zonaprop.com.ar/propiedades/clasificado/alclapin-peru-400-amplio-3-ambientes-53464432.html": {"id": "53464432", "date": "07-05-2024\n", "index": 20, "content": "$ 400.000\n$ 170.000 Expensas\nPeru al 400\nMonserrat, Capital Federal\n70 m\u00b2 tot.\n3 amb.\n2 dorm.\n1 ba\u00f1o\nDepartamento de 3 ambientes con patio. Ba\u00f1o reciclado a nuevo y todo pintado. Pisos de parquet plasticados. Muy buen estado general. Cocina muy amplia y en excelente estado, con comedor diario. Ambientes todos muy amplios. Alquiler actualizado trimestralmente por ipc. Garantia propietaria o seguro de caucion. Ingresos comprobables de por lo menos 3 veces el monto del alquiler (si es un matrimonio o pareja los ingresos se suman)\nPublicado hace 21 d\u00edas\nContactar", "revised": false, "rejected": true, "data": {"precio": "$ 400.000", "expensas": "$ 170.000 Expensas", "direccion": "Peru al 400", "metros": "70 m\u00b2 tot.", "habitaciones": "3 amb.", "hace": "Contactar"}, "image": "https://imgar.zonapropcdn.com/avisos/1/00/53/46/44/32/360x266/1906906660.jpg?isFirstImage=true", "title": "Departamento \u00b7 70m\u00b2 \u00b7 3 Ambientes \u00b7 Peru 400 - Amplio 3 Ambientes"}, "https://www.zonaprop.com.ar/propiedades/clasificado/alclapin-monserrat-departamento-3-amb-apto-profesional.-al-53454711.html": {"id": "53454711", "date": "07-05-2024\n", "index": 21, "content": "14\n$ 550.000\n$ 40.000 Expensas\nAvenida Belgrano 342, Monserrat, Capital Federal, Argentina.\nMonserrat, Capital Federal\n75 m\u00b2 tot.\n3 amb.\n2 dorm.\n1 ba\u00f1o\nDepartamento 3 ambientes, apto profesional. Buena luminosidad. Piso 1\u00ba, al frente. Hall, living, cocina separada, ba\u00f1o completo, doble circulaci\u00f3n. T/Tanque el\u00e9ctrico. Hall: 3. 00x2. 00. Living: 4. 00x3. 50. Dormitorios: 3. 50x3. 50 / 3. 50x3. 50. Cocina: 3. 50x1. 60. Balc\u00f3n: 5. 00x1. 00. Se pide garant\u00eda propietaria / Seguro de cauci\u00f3n. Cucicba Matr. Nro. 1700. Art. 4 de la Ley 5. 859 y Ley 5115 (Ley de accesibilidad) de C. A. B. A. Incorp\u00f3rase como inciso 8 del art\u00edculo 10 de la Ley 2340 (texto consolidado seg\u00fan Ley N\u00b0 5666) \"Para los casos de alquiler de vivienda, el monto m\u00e1ximo de comisi\u00f3n que se le puede requerir a los propietarios ser\u00e1 el equivalente al cuatro con quince cent\u00e9simos por ciento (4, 15%) del valor total del respectivo contrato. Se encuentra prohibido cobrar a los inquilinos que sean personas f\u00edsicas comisiones inmobiliarias y gastos de gestor\u00eda de informes\" Aviso publicado por Pixel Inmobiliario (Servicio de P\u00e1ginas Web para Inmobiliarias). #1554\nPublicado hace 22 d\u00edas\nContactar", "revised": false, "rejected": false, "data": {"precio": "$ 550.000", "expensas": "$ 40.000 Expensas", "direccion": "Avenida Belgrano 342, Monserrat, Capital Federal, Argentina.", "metros": "75 m\u00b2 tot.", "habitaciones": "3 amb.", "hace": "Contactar"}, "image": "https://imgar.zonapropcdn.com/avisos/1/00/53/45/47/11/360x266/1906679104.jpg?isFirstImage=true", "title": "Departamento \u00b7 70m\u00b2 \u00b7 3 Ambientes \u00b7 Monserrat, Departamento 3 Amb, Apto Profesional. Al Frente. C/balcon, 75 m\u00b2. Av Belgrano y Balcarce"}, "https://www.zonaprop.com.ar/propiedades/clasificado/alclappa-departamento-en-planta-baja-muy-luminoso-53443812.html": {"id": "53443812", "date": "07-05-2024\n", "index": 23, "content": "$ 400.000\nEstados Unidos 1400\nMonserrat, Capital Federal\n61 m\u00b2 tot.\n2 amb.\n2 dorm.\n1 ba\u00f1o\nDepartamento sin expensas a 3 cuadras de la Av. 9 de Julio y a 1 de Independencia. 2 Habitaciones, una con vestidor. Gran living-comedor con luz natural y acceso a terraza propia. Ba\u00f1o y Cocina completos.\nDestacado\nPublicado hace 25 d\u00edas\nContactar", "revised": false, "rejected": false, "data": {"precio": "$ 400.000", "expensas": "", "direccion": "Estados Unidos 1400", "metros": "61 m\u00b2 tot.", "habitaciones": "2 amb.", "hace": "Contactar"}, "image": "https://imgar.zonapropcdn.com/avisos/1/00/53/44/38/12/360x266/1906445515.jpg?isFirstImage=true", "title": "Living-comedor c/acceso a terraza y habitaciones \u00b7 Departamento en Planta Baja Muy Luminoso"}, "https://www.zonaprop.com.ar/propiedades/clasificado/alclapin-hermoso-3-ambientes-con-balcon-en-edificio-castell-53441237.html": {"id": "53441237", "date": "07-05-2024\n", "index": 24, "content": "$ 360.000\n$ 53.000 Expensas\nAVENIDA INDEPENDENCIA 1601\nMonserrat, Capital Federal\n65 m\u00b2 tot.\n3 amb.\n2 dorm.\n1 ba\u00f1o\nHermoso 3 amb en edificio castel bajac/ todo externo/balcon corrido/ muy luminodo/calefaccion central/ amplio placard de pared A pared en el pasillo de distribucion/ muy buen estado/ ba\u00f1o completo Y toilette/ amplia cocina de 4, 00 X 3, 00 con conexion para lavarropas/ pisos de parquet en muy buen estado. No accesible seg\u00fan Ley 5115. Para los casos de alquiler de vivienda, el monto m\u00e1ximo de comisi\u00f3n que se le puede requerir a los propietarios ser\u00e1 el equivalente al cuatro con quince cent\u00e9simos por ciento (4, 15%) del valor total del respectivo contrato. Se encuentra prohibido cobrar a los inquilinos que sean personas f\u00edsicas comisiones inmobiliarias y gastos de gestor\u00eda de informes. Aviso legal: Las descripciones arquitect\u00f3nicas y funcionales, valores de expensas, impuestos y servicios, fotos y medidas de este inmueble son aproximados. Los datos fueron proporcionados por el propietario y pueden no estar actualizados a la hora de la visualizaci\u00f3n de este aviso por lo cual pueden arrojar inexactitudes y discordancias con las que surgen de los las facturas, t\u00edtulos y planos legales del inmueble. El interesado deber\u00e1 realizar las verificaciones respectivas previamente a la realizaci\u00f3n de cualquier operaci\u00f3n, requiriendo por s\u00ed o sus profesionales las copias necesarias de la documentaci\u00f3n que corresponda. Guardia natalia. Lino Propiedades. matricula cucicba 8077\nPublicado hace 25 d\u00edas\nContactar", "revised": false, "rejected": false, "data": {"precio": "$ 360.000", "expensas": "$ 53.000 Expensas", "direccion": "AVENIDA INDEPENDENCIA 1601", "metros": "65 m\u00b2 tot.", "habitaciones": "3 amb.", "hace": "Contactar"}, "image": "https://imgar.zonapropcdn.com/avisos/1/00/53/44/12/37/360x266/1906383874.jpg?isFirstImage=true", "title": "Departamento de 3 ambientes, Monserrat \u00b7 Hermoso 3 Ambientes con Balcon en Edificio Castell Bajac"}, "https://www.zonaprop.com.ar/propiedades/clasificado/alclapin-departamento-2-dor.-c-dep-san-nicolas-centro-53411830.html": {"id": "53411830", "date": "07-05-2024\n", "index": 25, "content": "$ 450.000\n$ 114.915 Expensas\nParaguay 1900\nSan Nicol\u00e1s, Capital Federal\n64 m\u00b2 tot.\n3 amb.\n2 dorm.\n2 ba\u00f1os\nMuy buen semipiso de categor\u00eda en muy buen estado, muy luminoso, Living Comedor y los dos Dormitorios a la calle, ba\u00f1o completo y ba\u00f1o de servicio y habitaci\u00f3n de servicio, amplia cocina, lavadero independiente, gran cantidad de bauleras internas elevadas, pisos de parquet plastificados, no tiene balc\u00f3n. Expensas $ 114. 915, 10 abl $ 5. 104, 22 Aysa incluido en las expensas. ver plano Y fotos adjuntas. oferta provista por topinmobiliario. com - codigo: bps2422\nDestacado\nPublicado hace 28 d\u00edas\nContactar", "revised": false, "rejected": false, "data": {"precio": "$ 450.000", "expensas": "$ 114.915 Expensas", "direccion": "Paraguay 1900", "metros": "64 m\u00b2 tot.", "habitaciones": "3 amb.", "hace": "Contactar"}, "image": "https://imgar.zonapropcdn.com/avisos/1/00/53/41/18/30/360x266/1905718582.jpg?isFirstImage=true", "title": "Departamento \u00b7 64m\u00b2 \u00b7 3 Ambientes \u00b7 Departamento 2 Dor. C/dep - San Nicol\u00e1s (Centro Vivienda), Capital Federal"}, "https://www.zonaprop.com.ar/propiedades/clasificado/alclappa-depto-al-frente-en-calle-parana-cerca-obelizco-zona-53370254.html": {"id": "53370254", "date": "07-05-2024\n", "index": 29, "content": "$ 500.000\n$ 60.000 Expensas\nParan\u00e1 300\nSan Nicol\u00e1s, Capital Federal\n67 m\u00b2 tot.\n3 amb.\n2 dorm.\nDepartamento en calle Paran\u00e1 a una media cuadra de corrientes cerca obelisco zona Centro- 3 ambientes con balcon al frente. Luminoso. Con seguridad las 24 hs. Zona de teatros, restaurantes, frente al centro cultural San Mart\u00edn\nPublicado hace 35 d\u00edas\nContactar", "revised": false, "rejected": true, "data": {"precio": "$ 500.000", "expensas": "$ 60.000 Expensas", "direccion": "Paran\u00e1 300", "metros": "67 m\u00b2 tot.", "habitaciones": "3 amb.", "hace": "Contactar"}, "image": "https://imgar.zonapropcdn.com/avisos/1/00/53/37/02/54/360x266/1904804848.jpg?isFirstImage=true", "title": "frente \u00b7 Depto Al Frente en Calle Parana Cerca Obelizco Zona Centro"}, "https://www.zonaprop.com.ar/propiedades/clasificado/alclapin-alquiler-departamento-de-3-ambientes-en-monserrat-53368446.html": {"id": "53368446", "date": "07-05-2024\n", "index": 30, "content": "$ 590.000\n$ 40.000 Expensas\nVenezuela al 1400\nMonserrat, Capital Federal\n70 m\u00b2 tot.\n3 amb.\n2 dorm.\n1 ba\u00f1o\nSe alquila hermoso y luminoso departamento de 3 ambientes en monserrat. Primer piso por escalera. 2 habitaciones, 1 ba\u00f1o completo con ba\u00f1eraCocina abiertaPisos de maderaBalc\u00f3n al frenteSe alquila sin muebles. Contrato de 2 a\u00f1os con aumentos trimestrales por el ipc. 2 meses de deposito en garant\u00edaSe solicita seguro de garant\u00eda (ej: Finaer) Cercano a la uade, a Fundaci\u00f3n FavaloroA pocas cuadras de Av. 9 de Julio y a una cuadra de Av. Belgrano y la Plaza de CongresoCercano a varias lineas de colectivo, linea A, C y E de subte. Muy bien comunicada la zona. Cercana a teatros, colegios, facultades. Zona de comercios y restaurantes. En la esquina se encuentra el restaurante Plaza Mayor. Digno de ver!\nSuper destacado\nPublicado hace 36 d\u00edas\nContactar", "revised": false, "rejected": false, "data": {"precio": "$ 590.000", "expensas": "$ 40.000 Expensas", "direccion": "Venezuela al 1400", "metros": "70 m\u00b2 tot.", "habitaciones": "3 amb.", "hace": "Contactar"}, "image": "https://imgar.zonapropcdn.com/avisos/1/00/53/36/84/46/360x266/1904762472.jpg?isFirstImage=true", "title": "Departamento \u00b7 70m\u00b2 \u00b7 3 Ambientes \u00b7 Alquiler Departamento de 3 Ambientes en Monserrat, Amplio Balc\u00f3n Al Frente, Luminoso"}, "https://www.zonaprop.com.ar/propiedades/clasificado/alclapin-alquiler-amplio-y-luminoso-3-ambientes-en-monserrat-53337678.html": {"id": "53337678", "date": "07-05-2024\n", "index": 33, "content": "$ 500.000\n$ 37.000 Expensas\nVenezuela al 1500\nMonserrat, Capital Federal\n82 m\u00b2 tot.\n3 amb.\n2 dorm.\n1 ba\u00f1o\nSuper luminoso 3 ambientes en Monserrat. Departamento ubicado en inmejorable ubicaci\u00f3n cerca de principales avenidas, y universidades, el mismo cuenta con living comedor con acceso a balc\u00f3n al frente, cocina independiente con espacio lavadero y ba\u00f1o de servicio, por hall de distribuci\u00f3n nos encontramos con dos c\u00f3modas habitaciones, una de ellas con salida a segundo balc\u00f3n y ba\u00f1o completo. Locaci\u00f3n 2 a\u00f1os con ajustes trimestrales seg\u00fan icl. Medidas aproximadas: Living comedor 4, 30 x 7, 30 m2, cocina 3, 70 x 2, 11 m3, hall distribuci\u00f3n 0, 96 x 3, 20 m2, habitaci\u00f3n 1 3, 20 x 3 m2, habitaci\u00f3n 2 3, 52 x 3, 30 m2requisitos: Demostraci\u00f3n de ingresos, garant\u00edas seg\u00fan ley. Condiciones ingreso: mes deposito, mes adelantado, gastos. Las expensas pueden sufrir ajustes y no resultan vinculantes, los datos definitivos son los que surgen del titulo de propiedad y recibo de expensas. En compraventas, las mismas est\u00e1n condicionadas a la obtenci\u00f3n del numero de coti por la parte vendedora. Fotos de car\u00e1cter no contractual.\nDestacado\nPublicado hace 43 d\u00edas\nContactar", "revised": false, "rejected": false, "data": {"precio": "$ 500.000", "expensas": "$ 37.000 Expensas", "direccion": "Venezuela al 1500", "metros": "82 m\u00b2 tot.", "habitaciones": "3 amb.", "hace": "Contactar"}, "image": "https://imgar.zonapropcdn.com/avisos/1/00/53/33/76/78/360x266/1904066627.jpg?isFirstImage=true", "title": "Departamento \u00b7 78m\u00b2 \u00b7 3 Ambientes \u00b7 Alquiler Amplio y Luminoso 3 Ambientes en Monserrat"}, "https://www.zonaprop.com.ar/propiedades/clasificado/alclapin-departamento-en-monserrat-53308249.html": {"id": "53308249", "date": "07-05-2024\n", "index": 34, "content": "$ 550.000\n$ 30.000 Expensas\nVenezuela al 1500\nMonserrat, Capital Federal\n80 m\u00b2 tot.\n3 amb.\n2 dorm.\n1 ba\u00f1o\nMontserrat. D\u00faplex Ubicado sobre la calle Venezuela dentro del Casco Hist\u00f3rico de la Ciudad. A 4 cuadras de Av. 9 de Julio y a 5 cuadras de la distinguida Av. De Mayo. Caminando llegas al Obelisco y a la Av. Corrientes donde se encuentra una gran variedad de teatros y ofertas gastron\u00f3micas. Cercano a los barrios de San Telmo. A 5 cuadras del Subte L\u00ednea A \u201cEstaci\u00f3n S\u00e1enz Pe\u00f1a\u201d y a 4 cuadras del Metrobus sobre la Av. 9 de JulioAmplio departamento de 80 m2. Aprox D\u00faplex con Entrepiso y Balc\u00f3n al FrenteAmplio Living Comedor con salida a Balc\u00f3n al FrenteCocina y Ba\u00f1o CompletoEn el Entrepiso se encuentran 2 espacios separados, uno de ellos se encuentra armado como un dormitorio con una Cama Matrimonial y en el segundo espacio se presentan dos camas individuales. Departamento ideal para 4 personas. Inmueble totalmente amoblado y equipadoExpensas $ 25. 000. -vacis propiedades \u2013 V. Carolina Vacis cucicba Matr\u00edcula N\u00ba 7900Ley 5859 - Art. 4: \u201cPara los casos de alquiler de vivienda, el monto m\u00e1ximo de comisi\u00f3n que se le puede requerir a los propietarios ser\u00e1 el equivalente al cuatro con quince cent\u00e9simos por ciento (4, 15%) del valor total del respectivo contrato. Se encuentra prohibido cobrar a los inquilinos que sean personas f\u00edsicas comisiones inmobiliarias y gastos de gestor\u00eda de informes\u201d. aviso legal: Las descripciones arquitect\u00f3nicas y funcionales, valores de expensas, impuestos y servicios, fotos y medidas de este inmueble son aproximados. Los datos fueron proporcionados por el propietario y pueden no estar actualizados a la hora de la visualizaci\u00f3n de este aviso por lo cual pueden arrojar inexactitudes y discordancias con las que surgen de las facturas, t\u00edtulos y planos legales del inmueble. El interesado deber\u00e1 realizar las verificaciones respectivas previamente a la realizaci\u00f3n de cualquier operaci\u00f3n, requiriendo por s\u00ed o sus profesionales las copias necesarias de la documentaci\u00f3n que corresponda. Venta supeditada al cumplimiento por parte del propietario de los requisitos de la resoluci\u00f3n general N\u00ba 2371 de la afip (pedido de coti) . Accesible para personas con movilidad reducida. (Ley 5115/Gob. De la Ciudad Aut\u00f3noma de Buenos Aires)\nDestacado\nPublicado hace 48 d\u00edas\nContactar", "revised": false, "rejected": false, "data": {"precio": "$ 550.000", "expensas": "$ 30.000 Expensas", "direccion": "Venezuela al 1500", "metros": "80 m\u00b2 tot.", "habitaciones": "3 amb.", "hace": "Contactar"}, "image": "https://imgar.zonapropcdn.com/avisos/1/00/53/30/82/49/360x266/1903303863.jpg?isFirstImage=true", "title": "Departamento \u00b7 80m\u00b2 \u00b7 3 Ambientes \u00b7 Departamento en Monserrat"}, "https://www.zonaprop.com.ar/propiedades/clasificado/alclocin-oficina-en-alquiler-zona-san-nicolas-53303125.html": {"id": "53303125", "date": "07-05-2024\n", "index": 36, "content": "$ 530.000\n$ 50.000 Expensas\nAv. callao 441\nSan Nicol\u00e1s, Capital Federal\n78 m\u00b2 tot.\n3 amb.\n2 dorm.\n1 ba\u00f1o\nAmplio y luminoso departamento amoblado de 3 ambientes solo apto profesional. Ideal consultorio, estudio jur\u00eddico. Cuenta con recepci\u00f3n, 2 oficinas, sala de reuniones, sala de espera y ba\u00f1o. Ubicado sobre Av. Callao, a metros de Av. Corrientes (Estaci\u00f3n callao L\u00ednea B de subtes) y a cuatro cuadras de Av. C\u00f3rdoba (Estaci\u00f3n callao L\u00ednea D de subtes). Martillero responsable: nicolas ortiz. matr\u00edcula cucicba 6337. brokerin servicios inmobiliarios. Conforme la ley 5115 de accesibilidad el inmueble posee acceso para personas con movilidad reducida. Aceptamos garant\u00edA respaldar: -aprobado-express-sin-cargo? i=7fe1f8abaad094e0b5cb1b01d712f708&h=5c86e2d4656c14a3011f3d60b262c35c\nSuper destacado\nPublicado hace 49 d\u00edas\nContactar", "revised": false, "rejected": false, "data": {"precio": "$ 530.000", "expensas": "$ 50.000 Expensas", "direccion": "Av. callao 441", "metros": "78 m\u00b2 tot.", "habitaciones": "3 amb.", "hace": "Contactar"}, "image": "https://imgar.zonapropcdn.com/avisos/1/00/53/30/31/25/360x266/1903199153.jpg?isFirstImage=true", "title": "Oficina comercial de 3 ambientes, San Nicol\u00e1s \u00b7 Oficina en Alquiler - Zona San Nicolas"}, "https://www.zonaprop.com.ar/propiedades/clasificado/alclappa-alquiler-depto-3-amb.-muy-buen-estado.-centro-53267550.html": {"id": "53267550", "date": "07-05-2024\n", "index": 40, "content": "$ 400.000\nDirecci\u00f3n no informada\nSan Nicol\u00e1s, Capital Federal\n60 m\u00b2 tot.\n3 amb.\n2 dorm.\n1 ba\u00f1o\nDepto 3 amb. Muy buen estado. Ubicado en Sarmiento y Montevideo, se encuentra este departamento en alquiler. Con un precio de ar$400. 000. El departamento cuenta con agua corriente, luz, gas natural, y termotanque el\u00e9ctrico. Cocina separada. Ba\u00f1o completo. Pisos porcellanatoCentro. Dejar mensaje al Ver datos \u00f3 Ver datos\nPublicado hace 54 d\u00edas\nContactar", "revised": false, "rejected": false, "data": {"precio": "$ 400.000", "expensas": "", "direccion": "Direcci\u00f3n no informada", "metros": "60 m\u00b2 tot.", "habitaciones": "3 amb.", "hace": "Contactar"}, "image": "https://imgar.zonapropcdn.com/avisos/1/00/53/26/75/50/360x266/1902407999.jpg?isFirstImage=true", "title": "Departamento de 3 ambientes, San Nicol\u00e1s \u00b7 Alquiler Depto 3 Amb. Muy Buen Estado. Centro"}, "https://www.zonaprop.com.ar/propiedades/clasificado/alclapin-departamento-de-4-ambientes-en-san-nicolas-53574454.html": {"id": "53574454", "date": "08-05-2024\n", "index": 6, "content": "$ 600.000\n$ 170.000 Expensas\nDirecci\u00f3n no informada\nSan Nicol\u00e1s, Capital Federal\n140 m\u00b2 tot.\n3 amb.\n3 dorm.\n2 ba\u00f1os\nEste impecable departamento de 4 ambientes ofrece una combinaci\u00f3n perfecta de comodidad y estilo en una de las ubicaciones m\u00e1s estrategicas de la Ciudad Aut\u00f3noma de Buenos Aires. Caracter\u00edsticas principales: Amplio living comedor de generosas dimensiones, ideal para disfrutar de momentos inolvidables en familia o con amigos. Cocina completa con espacio para lavarropas. 3 habitaciones espaciosas que te brindan el confort que necesitas para descansar pl\u00e1cidamente. 2 ba\u00f1os completos, uno de ellos con jacuzzi para que puedas relajarte despu\u00e9s de un largo d\u00eda. Balc\u00f3n cubierto en el contrafrente, ideal como jard\u00edn de invierno, donde podr\u00e1s disfrutar de la tranquilidad y el verde sin salir de casa. Condiciones de alquiler: Contrato a dos a\u00f1os con actualizaciones trimestrales. Se requieren ingresos comprobables que tripliquen el monto del alquiler. Garant\u00eda propietaria o seguro de cauci\u00f3n. hay algunos muebles en inventario que quedan dentro del departamento. \u00a1Cont\u00e1ctanos hoy mismo para programar una visita!\nPublicado hace 4 d\u00edas\nContactar", "revised": false, "rejected": false, "data": {"precio": "$ 600.000", "expensas": "$ 170.000 Expensas", "direccion": "Direcci\u00f3n no informada", "metros": "140 m\u00b2 tot.", "habitaciones": "3 amb.", "hace": "Contactar"}, "image": "https://imgar.zonapropcdn.com/avisos/1/00/53/57/44/54/360x266/1909401776.jpg?isFirstImage=true", "title": "Departamento de 3 ambientes, San Nicol\u00e1s \u00b7 Departamento de 4 Ambientes en San Nicolas"}, "https://www.zonaprop.com.ar/propiedades/clasificado/alclocin-piso-de-6-oficinas-luminosas-con-recepcion-y-2-banos-53564778.html": {"id": "53564778", "date": "08-05-2024\n", "index": 8, "content": "$ 600.000\n$ 296.000 Expensas\nAvenida Presidente Roque S\u00e1enz Pe\u00f1a 852\nSan Nicol\u00e1s, Capital Federal\n155 m\u00b2 tot.\n6 amb.\n6 dorm.\n2 ba\u00f1os\nSemipiso al frente en octavo piso, compuesto por: recepci\u00f3n de 4 x 3. 10 // 4 oficinas al frente de 4. 10 x 3. 30 / 4. 90 x 4. 10 / 4. 10 x 3. 30 / 4. 60 x 4. 10 // 2 oficinas al pulm\u00f3n muy luminosas de 5 x 3. 70. Ba\u00f1os damas y caballeros y peque\u00f1a cocina. Superficies: 154. 97 m2 cubiertos y totales. El edificio es apto profesional y cuenta con vigilancia de lunes a viernes de 7: 30 a 19: 30 Hs. Est\u00e1 conformado por 9 pisos, 2 unidades por piso y 2 ascensores. Sus expensas con vencimiento abril-2024 son de $ 296. 000. - Visitas y mas informaci\u00f3n comunicarse con \"bloise Inmobiliaria desde 1945\" Tel\u00e9fonos 4921. 9984 y 4922. 4683 WhatsApp Ver datos\nPublicado hace 5 d\u00edas\nContactar", "revised": false, "rejected": false, "data": {"precio": "$ 600.000", "expensas": "$ 296.000 Expensas", "direccion": "Avenida Presidente Roque S\u00e1enz Pe\u00f1a 852", "metros": "155 m\u00b2 tot.", "habitaciones": "6 amb.", "hace": "Contactar"}, "image": "https://imgar.zonapropcdn.com/avisos/1/00/53/56/47/78/360x266/1909188912.jpg?isFirstImage=true", "title": "Oficina comercial de 6 ambientes, San Nicol\u00e1s \u00b7 Piso de 6 Oficinas Luminosas con Recepci\u00f3n y 2 Ba\u00f1os"}, "https://www.zonaprop.com.ar/propiedades/clasificado/alclocin-oportunidad-3-despachos-1-area-de-trabajo-bano-53570522.html": {"id": "53570522", "date": "08-05-2024\n", "index": 9, "content": "$ 360.000\n$ 120.000 Expensas\nDirecci\u00f3n no informada\nMonserrat, Capital Federal\n80 m\u00b2 tot.\n4 amb.\n4 dorm.\n1 ba\u00f1o\nG. S brokes. Ofrece oficina en alquiler muy bien conectada. Comercial. 3 despachos, un area de trabajo, ba\u00f1o, cocina. Edificio cuenta con vigilancia Y recepcion 24 hs. Tambien con un area de sum con mesas, gimnacio, piscina, La ubicacion subte, todos los medios de transporte.\nPublicado hace 4 d\u00edas\nContactar", "revised": false, "rejected": false, "data": {"precio": "$ 360.000", "expensas": "$ 120.000 Expensas", "direccion": "Direcci\u00f3n no informada", "metros": "80 m\u00b2 tot.", "habitaciones": "4 amb.", "hace": "Contactar"}, "image": "https://imgar.zonapropcdn.com/avisos/1/00/53/57/05/22/360x266/1909315432.jpg?isFirstImage=true", "title": "Oficina comercial de 4 ambientes, Monserrat \u00b7 Oportunidad 3 Despachos, 1 Area de Trabajo, Ba\u00f1o, Cocina. Comercial."}, "https://www.zonaprop.com.ar/propiedades/clasificado/alclcain-departamento-en-alquiler-en-palermo-de-7-ambientes-53569565.html": {"id": "53569565", "date": "08-05-2024\n", "index": 10, "content": "$ 300.000\nCallao al 2300\nMonserrat, Capital Federal\n400 m\u00b2 tot.\n4 amb.\n3 dorm.\n3 ba\u00f1os\n3 coch.\nLos invitamos a preguntar y a despejar todas las dudas que pudieran surgir respecto al uso de tokko. Pueden depositar sus preguntas en la pesta\u00f1a preguntasestas propiedades son ficticias, no contactar!\nPublicado hace 5 d\u00edas\nContactar", "revised": false, "rejected": false, "data": {"precio": "$ 300.000", "expensas": "", "direccion": "Callao al 2300", "metros": "400 m\u00b2 tot.", "habitaciones": "4 amb.", "hace": "Contactar"}, "image": "https://imgar.zonapropcdn.com/avisos/1/00/53/56/95/65/360x266/1909290579.jpg?isFirstImage=true", "title": "Casa \u00b7 400m\u00b2 \u00b7 4 Ambientes \u00b7 3 Cocheras \u00b7 Departamento en Alquiler, en Palermo de 7 Ambientes"}, "https://www.zonaprop.com.ar/propiedades/clasificado/alclocin-alquiler-de-hermosa-y-luminosa-oficina-comercial-en-53478503.html": {"id": "53478503", "date": "08-05-2024\n", "index": 23, "content": "$ 589.000\n$ 145.000 Expensas\nAv C\u00f3rdoba 475\nSan Nicol\u00e1s, Capital Federal\n85 m\u00b2 tot.\n7 amb.\n6 dorm.\n1 ba\u00f1o\nOficina comercial en Av. C\u00f3rdoba. Al ingresar encontramos un pasillo con gran ventanal, muy luminoso, que nos va guiando a los distintos ambientes, se distribuyen 6 box de oficinas, 1 ba\u00f1o completo, 1 toilette y Cocina. Encontramos 1 0ficina por piso; Las expensas incluyen aysa y abl aprox. 145. 000.\nPublicado hace 18 d\u00edas\nContactar", "revised": false, "rejected": false, "data": {"precio": "$ 589.000", "expensas": "$ 145.000 Expensas", "direccion": "Av C\u00f3rdoba 475", "metros": "85 m\u00b2 tot.", "habitaciones": "7 amb.", "hace": "Contactar"}, "image": "https://imgar.zonapropcdn.com/avisos/1/00/53/47/85/03/360x266/1907414380.jpg?isFirstImage=true", "title": "Oficina comercial de 7 ambientes, San Nicol\u00e1s \u00b7 Alquiler de Hermosa y Luminosa Oficina Comercial en San Nicolas, Caba"}, "https://www.zonaprop.com.ar/propiedades/clasificado/alclapin-alquiler-dpto.-4-amb-al-frente-monserrat-53473209.html": {"id": "53473209", "date": "08-05-2024\n", "index": 26, "content": "$ 600.000\n$ 30.000 Expensas\nSarandi 600 2\u00b0\nMonserrat, Capital Federal\n83 m\u00b2 tot.\n4 amb.\n3 dorm.\n2 ba\u00f1os\nDepartamento en venta de 4 ambientes al frente. Muy luminoso y con todos sus ambientes bien ventilados. El mismo cuanta con Hall de entrada amplio, cocina con lavadero y ba\u00f1o de servicio, living comedor, balcon, 3 dormitorios, dos de ellos con placard y ba\u00f1o completo. 83m2 cubiertos. En el barrio de Monserrat, a una cuadra de Av. Independencia y a diez de Av. 9 de Julio. Es un edificio de estilo conservado en muy buen estado. \u00bfTe interesa? Contactanos para recibir m\u00e1s informaci\u00f3n y coordinar una visita.\nPublicado hace 20 d\u00edas\nContactar", "revised": false, "rejected": false, "data": {"precio": "$ 600.000", "expensas": "$ 30.000 Expensas", "direccion": "Sarandi 600 2\u00b0", "metros": "83 m\u00b2 tot.", "habitaciones": "4 amb.", "hace": "Contactar"}, "image": "https://imgar.zonapropcdn.com/avisos/1/00/53/47/32/09/360x266/1907093085.jpg?isFirstImage=true", "title": "Departamento \u00b7 83m\u00b2 \u00b7 4 Ambientes \u00b7 Alquiler Dpto. 4 Amb | Al Frente | Monserrat"}, "https://www.zonaprop.com.ar/propiedades/clasificado/alclapin-departamento-de-3-dorm.-dependencias-balcon-con-53455039.html": {"id": "53455039", "date": "08-05-2024\n", "index": 29, "content": "$ 500.000\n$ 93.000 Expensas\nEntre Rios 1000\nMonserrat, Capital Federal\n110 m\u00b2 tot.\n4 amb.\n3 dorm.\n3 ba\u00f1os\nAvenida Entre Rios al 1000, esquina Carlos Calvo. A 200 mts. De la avenida San Juan, y la estaci\u00f3n Entre R\u00edos de Subte E. A 100 mts. De la avenida Independencia. Con gran variedad de medios de transporte a todos los puntos de la ciudad. Departamento de 3 dormitorios y dependencias, al frente, con balc\u00f3n. Amplio. Pisos de parquet. Ba\u00f1o completo, toilette de recepci\u00f3n y ba\u00f1o de dependencia. Gran living, 3 dormitorios con placard, cocina con sector de comedor diario, lavadero separado. Totalmente equipado: aunque antiguos, todo el departamento se encuentra equipado. Heladera, lavarropas, camas, mesas, sillones, etc. Las expensas ($ 60. 000. -) incluyen servicio central de agua caliente y calefacci\u00f3n central. No mascotas. Condiciones: Garante propietario. Ingresos comprobables de inquilino y garante. 1 mes de pago adelantado. Dep\u00f3sito de garant\u00eda. Gastos de averiguaci\u00f3n de garant\u00eda y certificaci\u00f3n de firmas. Im\u00e1genes de tipo ilustrativo, no vinculantes. Las medidas, superficies y proporciones anunciados son aproximados, y sujetos a verificaci\u00f3n y/o ajuste. El valor indicado de expensas esta sujeto a variaci\u00f3n. Fotos de car\u00e1cter ilustrativo y no contractual. \u201cPara los casos de alquiler de vivienda, el monto m\u00e1ximo de comisi\u00f3n que se le puede requerir a los propietarios ser\u00e1 el equivalente al cuatro con quince cent\u00e9simos por ciento (4, 15%) del valor total del respectivo contrato. Se encuentra prohibido cobrar a los inquilinos que sean personas f\u00edsicas comisiones inmobiliarias y gastos de gestor\u00eda de informes. \u201d\nPublicado hace 22 d\u00edas\nContactar", "revised": false, "rejected": false, "data": {"precio": "$ 500.000", "expensas": "$ 93.000 Expensas", "direccion": "Entre Rios 1000", "metros": "110 m\u00b2 tot.", "habitaciones": "4 amb.", "hace": "Contactar"}, "image": "https://imgar.zonapropcdn.com/avisos/1/00/53/45/50/39/360x266/1906686290.jpg?isFirstImage=true", "title": "Departamento \u00b7 105m\u00b2 \u00b7 4 Ambientes \u00b7 Departamento de 3 Dorm., Dependencias, Balc\u00f3n, con Muebles y Equipado"}, "https://www.zonaprop.com.ar/propiedades/clasificado/alclcain-casa-en-monserrat-53429469.html": {"id": "53429469", "date": "08-05-2024\n", "index": 33, "content": "$ 650.000\nSalta al 700\nMonserrat, Capital Federal\n144 m\u00b2 tot.\n4 amb.\n3 dorm.\n1 ba\u00f1o\nCasa con entrada independientecomedor diariohabitaci\u00f3n en suitetoilette con duchahabitaci\u00f3nen planta alta hay una habitaci\u00f3n chicala casa esta en una buena ubicaci\u00f3n, a 200 metros de subte, avenida independencia, enfrente de uadepuede alquilarse con los muebles que se ven en la foto (entre los cuales hay heladera grande con frezar nueva) o sin ellosSe puede alquilar como vivienda o comercial, 1 mes de deposito1 mes de alquileractualizaci\u00f3n trimestral por iclpreferentemente seguro de cauci\u00f3n o fianza ( garant\u00eda propietaria de caba a evaluar) para alquiler comercial 5% mas iva de honorariosEn cumplimiento de La Ley N\u00b0 5859 para los casos de alquiler de vivienda, el monto m\u00e1ximo de comisi\u00f3n que se le puede requerir a los propietarios ser\u00e1 el equivalente al cuatro con quince cent\u00e9simos por ciento (4, 15%) del valor total del respectivo contrato. Se encuentra prohibido cobrar a los inquilinos que sean personas f\u00edsicas comisiones inmobiliarias y gastos de gestor\u00eda de informes. En cumplimiento a la ley 5115, se informa que el inmueble no es accesible para personas con movilidad reducida o discapacidad f\u00edsica Corredor interviniente: Milagros Sarachaga cucicba 7799 Paolo Menghi cucicba 9171 cmcpdjlm 1005La tasaci\u00f3n, intermediaci\u00f3n y la conclusi\u00f3n de las operaciones sobre esta propiedad son actividades exclusivas de este corredor matriculado, conforme las previsiones de la ley 20. 266, la ley caba 2340, la ley provincial 10. 973 y sus modif. Y las normas reglamentarias dictadas por los colegios departamentales.\nPublicado hace 26 d\u00edas\nContactar", "revised": false, "rejected": false, "data": {"precio": "$ 650.000", "expensas": "", "direccion": "Salta al 700", "metros": "144 m\u00b2 tot.", "habitaciones": "4 amb.", "hace": "Contactar"}, "image": "https://imgar.zonapropcdn.com/avisos/1/00/53/42/94/69/360x266/1906130181.jpg?isFirstImage=true", "title": "Casa \u00b7 144m\u00b2 \u00b7 4 Ambientes \u00b7 Casa en Monserrat"}, "https://www.zonaprop.com.ar/propiedades/clasificado/alclapin-tres-dorm.-dos-banos-balcon-apto-vigilancia-24-has-53429847.html": {"id": "53429847", "date": "08-05-2024\n", "index": 34, "content": "$ 500.000\n$ 130.000 Expensas\nMoreno 800 6\u00b0\nMonserrat, Capital Federal\n79 m\u00b2 tot.\n4 amb.\n3 dorm.\n2 ba\u00f1os\nDepartamento apto profesional en edificio torre de planta baja y 22 pisos, con cuatro ascensores, porter\u00eda y vigilancia 24 hs. Consta de recepci\u00f3n a estar de 3 metros por 6 metros con salida a balc\u00f3n corrido de 4 mts x 1 mt, tres dormitorios con buenos placards y ventanales al balc\u00f3n corrido, ba\u00f1o completo, toilette y amplia cocina con lavadero cubierto y breakfast (con ventana al balc\u00f3n corrido). Pisos con moquette celeste en buen estado, bien de pintura; todos los ambientes tienen un equipo tipo de climatizaci\u00f3n, el pasillo y el estar comedor tienen una estufa de tiro balanceado. Agua caliente por termotanque. Luminarias; ba\u00f1o y cocina en perfecto estado. Condiciones: mes de dep\u00f3sito, mes anticipado, contrato a 24 meses con ajuste trimestral por ipc, garant\u00edas a satisfacci\u00f3n del locador. Las fotos son ilustrativas. Las medidas y los importes de los servicios y las expensas pueden variar; metraje exacto acorde a t\u00edtulo de propiedad. Unidad en buen estado. Para los casos de alquiler de vivienda, el monto m\u00e1ximo de comisi\u00f3n que se le puede. requerir a los propietarios ser\u00e1 el equivalente al cuatro con quince cent\u00e9simos por. ciento (4, 15%) del valor total del respectivo contrato. Se encuentra prohibido cobrar a. los inquilinos que sean personas f\u00edsicas comisiones inmobiliarias y gastos de gestor\u00eda. de informes\". Cumple con Ley 5115 de accesibilidad\nPublicado hace 26 d\u00edas\nContactar", "revised": false, "rejected": false, "data": {"precio": "$ 500.000", "expensas": "$ 130.000 Expensas", "direccion": "Moreno 800 6\u00b0", "metros": "79 m\u00b2 tot.", "habitaciones": "4 amb.", "hace": "Contactar"}, "image": "https://imgar.zonapropcdn.com/avisos/1/00/53/42/98/47/360x266/1906139365.jpg?isFirstImage=true", "title": "Departamento \u00b7 75m\u00b2 \u00b7 4 Ambientes \u00b7 Tres Dorm., Dos Ba\u00f1os, Balc\u00f3n, Apto, Vigilancia 24 Has"}, "https://www.zonaprop.com.ar/propiedades/clasificado/alclapin-alquiler-4-amb-c-dep-125-m-sup2--mexico-1300-53408957.html": {"id": "53408957", "date": "08-05-2024\n", "index": 37, "content": "$ 600.000\n$ 74.000 Expensas\nMexico 1300\nMonserrat, Capital Federal\n125 m\u00b2 tot.\n5 amb.\n4 dorm.\n1 ba\u00f1o\nCorredor Responsable: Monica Alejandra Mazza cucicba 5609 / Ezequiel Luceti cmcpsi 6635- Contacto: Monica Mazza - mls id # Ver datos. alquiler amplio departamento, calle mexico al 1300 - piso 6 -barrio de monserrat. 2 deptos por piso con ascensor. El depto. Se encuentra en el segundo cuerpo del edificio que cuenta con un jardin. Ficha descriptiva: hall de entrada. - 3 dorm, -1 escritorio, - -dependencia de servicio, -2 ba\u00f1os completos. -cocina comedor, -lavadero. Pisos de madera plastificados, instalacion de estufas de tiro balanceado. Y adaptaciones preparadas para instalar aire acondicionado. Caracteristicas de las habitaciones: -dormitorio principal: 4, 36X3, 47 M2. -dormitorio 2: 2, 84X4, 39 M2. -dormitorio 3: 1, 88X1, 93 M2. -dependencia 5: 2, 27X3, 97 M2. -escritorio: 4, 24X1, 50 M2. -living comedor: 4, 34X4, 36 M2. -comedor: 1, 99X2, 30 M2. -cocina: 3, 21X2, 30 M2. -ba\u00f1o principal: 2, 26X2, 72 M2. -toilette: 2, 35X1, 18 M2. -hall entrada: 2, 98x3, 07M2. -lavadero: 1, 88X 2, 44 M2. valor del alquiler: $ 600. . 000. - valor de ex[ensas: $ 74. 000. - condiciones de contratacion: -1 mes de deposito. -1 mes de adelanto. - garantia seguro de caucion. -ingreso de sueldo comprobable. -informe de dominio sobre la garantia propietaria A cargo del inquilino. -el depto se encuentra A 2 cuadras de av. Independencia Y A 2 cuadras de av. belgrano- -barrio monserrat. - -Transportes Cercanos. Colectivos: 2, 9, 10, 17, 23, 39, 45, 53, 57, 59, 60, 67, 70, 86, 91, 96, 98, 100, 102, 103, 129, 168, 195. Subtes (Metro): independencia (L\u00ednea E) Datos \u00fatiles. Barrio: Monserrat. Comuna: Comuna 1. \u00c1rea Hospitalaria: htal. Dr. J. M. Ramos mej\u00eda. Comisar\u00eda: 4. Distrito Escolar: Distrito Escolar iii. C\u00f3digo Postal: 1097. llamanos estamos para ayudarte!! Martillera publica: monica mazza cel: Ver datos. remax premium 4. Remax Argentina S. R. L. No ejerce el corretaje inmobiliario. El presente sitio web es una plataforma en donde cada oficina inmobiliaria independiente que contrata los servicios re/max puede publicar las propiedades a su cargo. Cada oficina es de propiedad y gesti\u00f3n independiente, por lo que Remax Argentina S. R. L no interviene en los datos de la publicaci\u00f3n, en la operaci\u00f3n inmobiliaria, ni en la confecci\u00f3n y/o firma del boleto de compraventa y/o escritura y/o contrato de alquiler. En cumplimiento de las leyes vigentes que regulan el corretaje inmobiliario, Ley Nacional 25. 028, Ley 22. 802 de Lealtad Comercial, Ley 24. 240 de Defensa al Consumidor, las normas del C\u00f3digo Civil y Comercial de la Naci\u00f3n y Constitucionales, los agentes/gestores no ejercen el corretaje inmobiliario. Todas las operaciones inmobiliarias son objeto de intermediaci\u00f3n y conclusi\u00f3n por parte del corredor p\u00fablico inmobiliario colegiado a cargo de la publicaci\u00f3n, cuyos datos se exhiben en la presente. La presente publicaci\u00f3n describe las caracter\u00edsticas esenciales del inmueble, debi\u00e9ndose consultar al corredor p\u00fablico inmobiliario responsable de la operaci\u00f3n por la eventual actualizaci\u00f3n de las medidas, descripciones arquitect\u00f3nicas y funcionales, valores de expensas, servicios, impuestos, precios y dem\u00e1s informaci\u00f3n, cuyos valores son aproximados. El inmueble no es accesible para personas con discapacidades f\u00edsicas. Remax Argentina S. R. L. No ejerce el corretaje inmobiliario. El presente sitio web es una plataforma en donde cada oficina inmobiliaria independiente que contrata los servicios re/max puede publicar las propiedades a su cargo. Cada oficina es de propiedad y gesti\u00f3n independiente, por lo que Remax Argentina S. R. L no interviene en los datos de la publicaci\u00f3n, en la operaci\u00f3n inmobiliaria, ni en la confecci\u00f3n y/o firma del boleto de compraventa y/o escritura y/o contrato de alquiler. En cumplimiento de las leyes vigentes que regulan el corretaje inmobiliario, Ley Nacional 25. 028, Ley 22. 802 de Lealtad Comercial, Ley 24. 240 de Defensa al Consumidor, las normas del C\u00f3digo Civil y Comercial de la Naci\u00f3n y Constitucionales, los agentes/gestores no ejercen el corretaje inmobiliario. Todas las operaciones inmobiliarias son objeto de intermediaci\u00f3n y conclusi\u00f3n por parte del corredor p\u00fablico inmobiliario colegiado a cargo de la publicaci\u00f3n, cuyos datos se exhiben en la presente. La presente publicaci\u00f3n describe las caracter\u00edsticas esenciales del inmueble, debi\u00e9ndose consultar al corredor p\u00fablico inmobiliario responsable de la operaci\u00f3n por la eventual actualizaci\u00f3n de las medidas, descripciones arquitect\u00f3nicas y funcionales, valores de expensas, servicios, impuestos, precios y dem\u00e1s informaci\u00f3n, cuyos valores son aproximados. Para los casos de alquiler de vivienda, el monto m\u00e1ximo de comisi\u00f3n que se le puede requerir a los propietarios ser\u00e1 el equivalente al cuatro con quince cent\u00e9simos por ciento (4, 15%) del valor total del respectivo contrato. Se encuentra prohibido cobrar a los inquilinos que sean personas f\u00edsicas comisiones inmobiliarias y gastos de gestor\u00eda de informes. El inmueble no es accesible para personas con discapacidades f\u00edsicas.\nPublicado hace 29 d\u00edas\nContactar", "revised": false, "rejected": false, "data": {"precio": "$ 600.000", "expensas": "$ 74.000 Expensas", "direccion": "Mexico 1300", "metros": "125 m\u00b2 tot.", "habitaciones": "5 amb.", "hace": "Contactar"}, "image": "https://imgar.zonapropcdn.com/avisos/1/00/53/40/89/57/360x266/1905658061.jpg?isFirstImage=true", "title": "Departamento \u00b7 125m\u00b2 \u00b7 5 Ambientes \u00b7 Alquiler 4 Amb C/dep - 125 m\u00b2 - Mexico 1300 - Monserrat"}}