{"https://www.zonaprop.com.ar/propiedades/clasificado/alclphin-alquiler-2-ambientes-1er-piso-por-escalera-jose-maria-53604896.html": {"id": "53604896", "date": "08-05-2024\n", "index": 11, "content": "$ 280.000\n$ 10.000 Expensas\nJose Maria Moreno 1300\nParque Chacabuco, Capital Federal\n46 m\u00b2 tot.\n2 amb.\n1 dorm.\n1 ba\u00f1o\nAlquiler 2 ambiente 1er piso por escalera, living, cocina, ba\u00f1o, patio. Requisitos Garant\u00eda propietaria o Seguro de cauci\u00f3n. Ambientes: Dormitorio\nPublicado hoy\nContactar", "revised": false, "rejected": true, "data": {"precio": "$ 280.000", "expensas": "$ 10.000 Expensas", "direccion": "Jose Maria Moreno 1300", "metros": "46 m\u00b2 tot.", "habitaciones": "2 amb.", "hace": "Contactar"}, "image": "https://imgar.zonapropcdn.com/avisos/1/00/53/60/48/96/360x266/1910092210.jpg?isFirstImage=true", "title": "PH \u00b7 40m\u00b2 \u00b7 2 Ambientes \u00b7 Alquiler 2 Ambientes 1er Piso por Escalera Jose Maria Moreno"}, "https://www.zonaprop.com.ar/propiedades/clasificado/alclapin-1-amb-dividido-2-banos-parque-chacabuco-53594918.html": {"id": "53594918", "date": "08-05-2024\n", "index": 17, "content": "$ 270.000\n$ 78.000 Expensas\nAsamblea 100. Entre Senillosa y Doblas\nParque Chacabuco, Capital Federal\n41 m\u00b2 tot.\n1 amb.\n1 dorm.\n2 ba\u00f1os\nAlquiler - 1 ambiente c/ balc\u00f3n, 2 ba\u00f1os, dividido - Parque Chacabuco. Departamento de un ambiente dividido. La unidad se compone por un ambiente con toilette y balc\u00f3n franc\u00e9s, cocina completamente equipada por artefactos el\u00e9ctricos, integrada al living comedor, placard divisorio con espacio de guardado tanto en el frente con en la parte trasera (pose puertas corredizas y espejadas), ba\u00f1o completo y balc\u00f3n externo al contrafrente. Cuenta con dos aires acondicionados frio/calor, persiana y conexi\u00f3n a lavarropas en cocina. Ubicado en Asamblea entre Senillosa y Doblas. A 100 mts de Av. La Plata y a tan solo 5 cuadras de Av. Jose Maria Moreno. Cercano al barrio de Caballito y variedad de l\u00edneas de colectivo. Requisitos: \u0095 Contrato por 2 a\u00f1os de alquiler. \u0095 Deposito: 1 mes del mismo valor del alquiler. \u0095 Ajuste trimestral, seg\u00fan el \u00edndice del precio al consumidor (ipc). \u0095 Garant\u00eda: Garant\u00eda propietaria en caba. (Excluyente). \u0095 Ingresos: Demostraci\u00f3n de ingresos de los inquilinos que triplique el valor del alquiler. (Excluyente). \u0095 abl a cargo del inquilino. \u0095 no acepta ning\u00fan tipo de mascota. (Excluyente). Curcio propiedades matricula en cucicba N\u00ba4852xintel(cuc-cuc-251)\nSuper destacado\nPublicado desde ayer\nContactar", "revised": false, "rejected": true, "data": {"precio": "$ 270.000", "expensas": "$ 78.000 Expensas", "direccion": "Asamblea 100. Entre Senillosa y Doblas", "metros": "41 m\u00b2 tot.", "habitaciones": "1 amb.", "hace": "Contactar"}, "image": "https://imgar.zonapropcdn.com/avisos/1/00/53/59/49/18/360x266/1909853591.jpg?isFirstImage=true", "title": "CUC-CUC-251_2 \u00b7 1 Amb Dividido, 2 Ba\u00f1os - Parque Chacabuco"}, "https://www.zonaprop.com.ar/propiedades/clasificado/alclapin-departamento-en-alquiler-2-amb-al-frente-c-balcon-53595635.html": {"id": "53595635", "date": "08-05-2024\n", "index": 23, "content": "$ 300.000\n$ 83.000 Expensas\nDel Tigre al 3900\nParque Patricios, Capital Federal\n45 m\u00b2 tot.\n2 amb.\n1 dorm.\n1 ba\u00f1o\nDepartamento en alquiler de 1 dormitorio con balc\u00f3n al frente en Del Tigre y Av. S\u00e1enz. Dos ambientes externos que le brindan mucha luz y sol. Cocina separada con espacio para lavarropas. Ba\u00f1o completo con ba\u00f1adera. Impecable estado, todo reci\u00e9n pintado. Edificio de 7 plantas, 3 departamentos por piso. Encargado con vivienda. Alquiler por 24 meses con indexaci\u00f3n cuatrimestral. Demostraci\u00f3n de ingresos.\nPublicado desde ayer\nContactar", "revised": false, "rejected": true, "data": {"precio": "$ 300.000", "expensas": "$ 83.000 Expensas", "direccion": "Del Tigre al 3900", "metros": "45 m\u00b2 tot.", "habitaciones": "2 amb.", "hace": "Contactar"}, "image": "https://imgar.zonapropcdn.com/avisos/1/00/53/59/56/35/360x266/1909866921.jpg?isFirstImage=true", "title": "Departamento \u00b7 45m\u00b2 \u00b7 2 Ambientes \u00b7 Departamento en Alquiler 2 Amb Al Frente C/ Balc\u00f3n"}, "https://www.zonaprop.com.ar/propiedades/clasificado/alclapin-departamento-en-alquiler-de-1-dormitorio-en-parque-53597994.html": {"id": "53597994", "date": "08-05-2024\n", "index": 26, "content": "$ 300.000\n$ 40.000 Expensas\nAv. Saenz 85\nParque Patricios, Capital Federal\n35 m\u00b2 tot.\n2 amb.\n1 dorm.\n1 ba\u00f1o\nUbicado en la zona de Parque Patricios en Capital Federal, se encuentra este elegante departamento en alquiler en la calle Saenz. Con un precio de ar$300. 000 y 2 ambientes bien distribuidos, este inmueble ofrece un dormitorio, un ba\u00f1o y una moderna cocina, ideal para aquellos que buscan confort y estilo en su hogar. Con una superficie total de 35 m2, este departamento cuenta con todas las comodidades necesarias para una vida de lujo y sofisticaci\u00f3n. Este exclusivo departamento destaca por su excelente ubicaci\u00f3n y sus caracter\u00edsticas \u00fanicas, como agua corriente, gas natural, luz, cocina equipada y accesibilidad. Adem\u00e1s, el edificio cuenta con ascensor y un acogedor living comedor, perfecto para disfrutar de momentos de relax y entretenimiento. Con un costo de expensas de $40. 000, este inmueble brinda la oportunidad de vivir en una de las zonas m\u00e1s codiciadas de la ciudad, con todos los servicios y comodidades al alcance de la mano. Con una distribuci\u00f3n funcional y un dise\u00f1o moderno, este departamento en alquiler en Parque Patricios es ideal para aquellos que buscan un estilo de vida sofisticado y exclusivo. No pierdas la oportunidad de vivir en este incre\u00edble espacio que combina elegancia, confort y ubicaci\u00f3n privilegiada en el coraz\u00f3n de la ciudad de Buenos Aires. \u00a1Ll\u00e1menos para conocer m\u00e1s en detalle esta propiedad! Tel: Ver datos. Email: Ver datos. De la Torre Propiedades\nPublicado desde ayer\nContactar", "revised": false, "rejected": true, "data": {"precio": "$ 300.000", "expensas": "$ 40.000 Expensas", "direccion": "Av. Saenz 85", "metros": "35 m\u00b2 tot.", "habitaciones": "2 amb.", "hace": "Contactar"}, "image": "https://imgar.zonapropcdn.com/avisos/1/00/53/59/79/94/360x266/1909917910.jpg?isFirstImage=true", "title": "Departamento de 2 ambientes, Parque Patricios \u00b7 Departamento en Alquiler de 1 Dormitorio en Parque Patricios"}, "https://www.zonaprop.com.ar/propiedades/clasificado/alclapin-departamento-en-alquiler-53594647.html": {"id": "53594647", "date": "08-05-2024\n", "index": 30, "content": "$ 250.000\n$ 40.000 Expensas\nLa Rioja al 1100\nSan Cristobal, Capital Federal\n31 m\u00b2 tot.\n2 amb.\n1 dorm.\n1 ba\u00f1o\nSe trata de un departamento de 2 ambientes al frente, living, cocina comedor con muebles completos, dormitorio con placard. Ba\u00f1o completo, agua caliente central. La propiedad se encuentra en excelente estado, a metros de Av. San Juan y subte E. no se aceptan mascotas. ll 106condiciones Y requisitos- 1 mes por adelantado + 1 mes deposito (igual al valor del primer mes) - Garant\u00eda-El monto de las expensas aqu\u00ed especificado, fueron extra\u00eddos de la liquidaci\u00f3n realizada por el administrador del edificio y corresponden al mes de Abril de 2024, por lo tanto y debido a que sufren fluctuaciones mes a mes, Ud deber\u00e1 solicitarnos el monto actualizado previamente a la realizaci\u00f3n de la operaci\u00f3n. -- Honorarios: seg\u00fan ley 5859 \u201cSe encuentra prohibido cobrar comisiones inmobiliarias y gastos de gestor\u00eda de informes a los inquilinos que sean personas f\u00edsicas. Para los casos de alquiler de vivienda, el monto m\u00e1ximo de comisi\u00f3n que se le puede requerir a los propietarios ser\u00e1 el equivalente al cuatro con quince cent\u00e9simos por ciento (4, 15%) del valor total del respectivo contrato\u201d- Contrato por 2 a\u00f1os- Indexaci\u00f3n trimestral seg\u00fan \u00edndice ipc\nPublicado desde ayer\nContactar", "revised": true, "rejected": false, "data": {"precio": "$ 250.000", "expensas": "$ 40.000 Expensas", "direccion": "La Rioja al 1100", "metros": "31 m\u00b2 tot.", "habitaciones": "2 amb.", "hace": "Contactar"}, "image": "https://imgar.zonapropcdn.com/avisos/1/00/53/59/46/47/360x266/1909848236.jpg?isFirstImage=true", "title": "Departamento \u00b7 31m\u00b2 \u00b7 2 Ambientes \u00b7 Departamento en Alquiler"}, "https://www.zonaprop.com.ar/propiedades/clasificado/alclapin-alquiler-departamento-2-ambientes-san-cristobal-53589548.html": {"id": "53589548", "date": "08-05-2024\n", "index": 42, "content": "19\n$ 265.000\n$ 16.000 Expensas\nEstados Unidos 2200\nSan Cristobal, Capital Federal\n36 m\u00b2 tot.\n2 amb.\n1 dorm.\n1 ba\u00f1o\nCorredor Responsable: guillermo frimet cucicba 4235 / Pablo Anibal Montenegro cpmcal 552- Contacto: Vanesa Conti - mls id # Ver datos-6. alquiler departamento 2 ambientes san crist\u00f3bal. Alquiler Departamento de 2 ambientes con baulera en San Crist\u00f3bal. Departamento 2 ambientes en alquiler! Se encuentra en el 3er piso por escalera. Sobre Estados Unidos al 2200. caracteristicas. Cocina equipada y amoblada. Living/comedor con aire acondicionado y calefactor. Habitaci\u00f3n con placar. Ba\u00f1o completo con ba\u00f1era. Baulera. Se ingresa al living-comedor que tiene una ventana con orientaci\u00f3n norte, el sol le da todo el a\u00f1o. A la izquierda se encuentra la cocina equipada, y hacia la derecha un peque\u00f1o pasillo distribuidor nos lleva al ba\u00f1o completo con ba\u00f1era y a la habitaci\u00f3n con placar. El departamento tiene un lugar de guardado justo al lado del ba\u00f1o donde se puede poner un lavarropas. Tambi\u00e9n posee una terraza de uso com\u00fan y una baulera cerrada que le pertenece al inmueble. Ven\u00ed A visitarlo! Llamanos Y agendamos una visita! Contrato de 24 meses. Aumento cuatrimestral seg\u00fan ipc. Expensas: $ 21. 000 Mes Mayo 2024. Condiciones para el ingreso: - Mes de adelanto. - Mes de dep\u00f3sito. - Seguro de cauci\u00f3n Garantor. Las medidas, superficies y expensas consignadas en la presente son aproximadas; y al solo efecto orientativo. Los datos definitivos son los que surgir\u00e1n del t\u00edtulo de la propiedad y de los comprobantes respaldatorios. El presente Inmueble no es accesible para personas con discapacidad f\u00edsica ley 5115. Remax Argentina S. R. L. No ejerce el corretaje inmobiliario. El presente sitio web es una plataforma en donde cada oficina inmobiliaria independiente que contrata los servicios re/max puede publicar las propiedades a su cargo. Cada oficina es de propiedad y gesti\u00f3n independiente, por lo que Remax Argentina S. R. L no interviene en los datos de la publicaci\u00f3n, en la operaci\u00f3n inmobiliaria, ni en la confecci\u00f3n y/o firma del boleto de compraventa y/o escritura y/o contrato de alquiler. En cumplimiento de las leyes vigentes que regulan el corretaje inmobiliario, Ley Nacional 25. 028, Ley 22. 802 de Lealtad Comercial, Ley 24. 240 de Defensa al Consumidor, las normas del C\u00f3digo Civil y Comercial de la Naci\u00f3n y Constitucionales, los agentes/gestores no ejercen el corretaje inmobiliario. Todas las operaciones inmobiliarias son objeto de intermediaci\u00f3n y conclusi\u00f3n por parte del corredor p\u00fablico inmobiliario colegiado a cargo de la publicaci\u00f3n, cuyos datos se exhiben en la presente. La presente publicaci\u00f3n describe las caracter\u00edsticas esenciales del inmueble, debi\u00e9ndose consultar al corredor p\u00fablico inmobiliario responsable de la operaci\u00f3n por la eventual actualizaci\u00f3n de las medidas, descripciones arquitect\u00f3nicas y funcionales, valores de expensas, servicios, impuestos, precios y dem\u00e1s informaci\u00f3n, cuyos valores son aproximados. Para los casos de alquiler de vivienda, el monto m\u00e1ximo de comisi\u00f3n que se le puede requerir a los propietarios ser\u00e1 el equivalente al cuatro con quince cent\u00e9simos por ciento (4, 15%) del valor total del respectivo contrato. Se encuentra prohibido cobrar a los inquilinos que sean personas f\u00edsicas comisiones inmobiliarias y gastos de gestor\u00eda de informes. El inmueble no es accesible para personas con discapacidades f\u00edsicas.\nPublicado hace 2 d\u00edas\nContactar", "revised": true, "rejected": false, "data": {"precio": "$ 265.000", "expensas": "$ 16.000 Expensas", "direccion": "Estados Unidos 2200", "metros": "36 m\u00b2 tot.", "habitaciones": "2 amb.", "hace": "Contactar"}, "image": "https://imgar.zonapropcdn.com/avisos/1/00/53/58/95/48/360x266/1909737053.jpg?isFirstImage=true", "title": "Departamento \u00b7 36m\u00b2 \u00b7 2 Ambientes \u00b7 Alquiler Departamento 2 Ambientes San Crist\u00f3bal"}, "https://www.zonaprop.com.ar/propiedades/clasificado/alclapin-excelente-unidad-3-anos.-balcon.-ambiente-e-l-53583345.html": {"id": "53583345", "date": "08-05-2024\n", "index": 44, "content": "$ 300.000\n$ 27.000 Expensas\nAv. Chiclana 3229\nParque Patricios, Capital Federal\n40 m\u00b2 tot.\n1 dorm.\n1 ba\u00f1o\nEspectacular ambiente en \"L\" con placard para dividir dormitorio. Caldera individual. Calefacci\u00f3n por radiadores. La mejor! 4 luces de emergencia! Piso 3\u00b0 muy luminoso!! Preferentemente seguro Respaldar o Finaer. Cocina de lujo con campana de acero inoxidable. Cocina a gas! Balc\u00f3n contra frente. Edificio nuevo. Bajas expensas. Para no perder! Daniel Marqu\u00e9s - servicios inmobiliarios. Ver datos / Ver datos\nPublicado hace 2 d\u00edas\nContactar", "revised": false, "rejected": true, "data": {"precio": "$ 300.000", "expensas": "$ 27.000 Expensas", "direccion": "Av. Chiclana 3229", "metros": "40 m\u00b2 tot.", "habitaciones": "1 dorm.", "hace": "Contactar"}, "image": "https://imgar.zonapropcdn.com/avisos/1/00/53/58/33/45/360x266/1909605687.jpg?isFirstImage=true", "title": "Departamento de 1 ambiente, Parque Patricios \u00b7 Excelente Unidad 3 A\u00f1os. Balc\u00f3n. Ambiente E \"L\" Divisible con Placard."}, "https://www.zonaprop.com.ar/propiedades/clasificado/alclapin-departamento-en-alquiler-de-1-dormitorio-en-parque-53590415.html": {"id": "53590415", "date": "08-05-2024\n", "index": 46, "content": "$ 300.000\n$ 20.000 Expensas\nDean Funes 2160\nParque Patricios, Capital Federal\n39 m\u00b2 tot.\n2 amb.\n1 dorm.\n1 ba\u00f1o\nDepartamento en alquiler en la calle Dean Funes, Parque Patricios, Capital Federal. Este inmueble de 2 ambientes ofrece un total de 39 m2 distribuidos de manera inteligente, con un dormitorio, un ba\u00f1o y una cocina, ideal para aquellos que buscan comodidad en un mismo espacio. La propiedad cuenta con todas las comodidades necesarias: agua corriente, luz, gas natural, cocina equipada, lavadero, ascensor y un luminoso living comedor que invita al relax. Con una orientaci\u00f3n lateral, este departamento se destaca por su ambiente acogedor y funcional, perfecto para disfrutar de la vida urbana con todas las comodidades. Adem\u00e1s, este exclusivo departamento en alquiler se encuentra en un edificio con una antig\u00fcedad que garantiza su calidad y durabilidad. Con un costo mensual de $20. 000 en concepto de expensas, esta propiedad es una oportunidad \u00fanica para aquellos que buscan vivir en una de las zonas m\u00e1s exclusivas de la ciudad. . \u00a1Cont\u00e1ctanos para m\u00e1s informaci\u00f3n! \u00a1Ll\u00e1menos para conocer m\u00e1s en detalle esta propiedad! Tel: Ver datos. Email: Ver datos. De la Torre Propiedades\nPublicado hace 2 d\u00edas\nContactar", "revised": false, "rejected": true, "data": {"precio": "$ 300.000", "expensas": "$ 20.000 Expensas", "direccion": "Dean Funes 2160", "metros": "39 m\u00b2 tot.", "habitaciones": "2 amb.", "hace": "Contactar"}, "image": "https://imgar.zonapropcdn.com/avisos/1/00/53/59/04/15/360x266/1909756625.jpg?isFirstImage=true", "title": "Departamento de 2 ambientes, Parque Patricios \u00b7 Departamento en Alquiler de 1 Dormitorio en Parque Patricios"}, "https://www.zonaprop.com.ar/propiedades/clasificado/alclapin-a-pasos-del-subte-b-impecable!-53580855.html": {"id": "53580855", "date": "08-05-2024\n", "index": 60, "content": "$ 300.000\n$ 50.000 Expensas\nAv. Olazabal 5100\nVilla Urquiza, Capital Federal\n43 m\u00b2 tot.\n2 amb.\n1 dorm.\n1 ba\u00f1o\nExcelente dos ambientes! apto profesional! super luminoso! cocina aparteliving comedor// cocina amplia separada // dormitorio con placard// ba\u00f1o completo con ventilacion natural// servicios individuales//aire acondicionadolisto para ingresar\nDestacado\nPublicado hace 4 d\u00edas\nContactar", "revised": false, "rejected": true, "data": {"precio": "$ 300.000", "expensas": "$ 50.000 Expensas", "direccion": "Av. Olazabal 5100", "metros": "43 m\u00b2 tot.", "habitaciones": "2 amb.", "hace": "Contactar"}, "image": "https://imgar.zonapropcdn.com/avisos/1/00/53/58/08/55/360x266/1909544429.jpg?isFirstImage=true", "title": "Departamento \u00b7 43m\u00b2 \u00b7 2 Ambientes \u00b7 A Pasos del Subte B - Impecable!"}, "https://www.zonaprop.com.ar/propiedades/clasificado/alclappa-muy-buen-departamento-de-2-ambientes-en-el-barrio-de-53581083.html": {"id": "53581083", "date": "08-05-2024\n", "index": 62, "content": "21\n$ 290.000\n$ 34.000 Expensas\nIncl\u00e1n 4200\nBoedo, Capital Federal\n33 m\u00b2 tot.\n2 amb.\n1 dorm.\nMuy buen departamento de 2 ambientes en el barrio de Boedo en Inclan a metros de Av. La Plata. Cuenta con cocina independiente y ba\u00f1o con ducha. Piso alto, hermosa vista en los dos ambientes y super luminoso. Dormitorio con placard. Requisitos: recibo de sueldo en blanco y garant\u00eda propietaria en Capital Federal.\nPublicado hace 4 d\u00edas\nContactar", "revised": false, "rejected": true, "data": {"precio": "$ 290.000", "expensas": "$ 34.000 Expensas", "direccion": "Incl\u00e1n 4200", "metros": "33 m\u00b2 tot.", "habitaciones": "2 amb.", "hace": "Contactar"}, "image": "https://imgar.zonapropcdn.com/avisos/1/00/53/58/10/83/360x266/1909967258.jpg?isFirstImage=true", "title": "Departamento 33m\u00b2 Alquiler  \u00b7 Muy Buen Departamento de 2 Ambientes en El Barrio de Boedo"}, "https://www.zonaprop.com.ar/propiedades/clasificado/alclapin-monoambiente-dividido-con-balcon-en-parque-chacabuco-53578505.html": {"id": "53578505", "date": "08-05-2024\n", "index": 65, "content": "$ 280.000\n$ 50.000 Expensas\nVernet 21\nParque Chacabuco, Capital Federal\n42 m\u00b2 tot.\n1 amb.\n1 dorm.\n1 ba\u00f1o\nAmplio monoambiente dividido de 42 m2 totales, con balc\u00f3n al contrafrente. Luminoso, ya que se trata de un 9no piso. Buena ventilaci\u00f3n. Cocina y termotanque a gas. Posee placard en el dormitorio. Muy buena ubicaci\u00f3n, gran conectividad. A metros de Av. La Plata. Contrato por 2 a\u00f1os con actualizaci\u00f3n trimestral, por \u00edndice de alquileres. Requisitos: Demostraci\u00f3n de ingresos. Seguro de cauci\u00f3n. Servicios de agua, luz, gas, expensas a cargo del inquilino. Valores a integrar a la firma del contrato: - 1 mes adelantado (mes de ingreso). - 1 mes dep\u00f3sito en garant\u00eda. Conexi\u00f3n inmobiliaria\nDestacado\nPublicado hace 5 d\u00edas\nContactar", "revised": false, "rejected": true, "data": {"precio": "$ 280.000", "expensas": "$ 50.000 Expensas", "direccion": "Vernet 21", "metros": "42 m\u00b2 tot.", "habitaciones": "1 amb.", "hace": "Contactar"}, "image": "https://imgar.zonapropcdn.com/avisos/1/00/53/57/85/05/360x266/1909489938.jpg?isFirstImage=true", "title": "Departamento de 1 ambiente, Parque Chacabuco \u00b7 Monoambiente Dividido con Balc\u00f3n en Parque Chacabuco"}, "https://www.zonaprop.com.ar/propiedades/clasificado/alclapin-2-ambientes-bajas-expensas-53578075.html": {"id": "53578075", "date": "08-05-2024\n", "index": 66, "content": "$ 300.000\n$ 37.000 Expensas\nPlaza 2778\nVilla Urquiza, Capital Federal\n40 m\u00b2 tot.\n2 amb.\n1 dorm.\n1 ba\u00f1o\nDepartamento de 2 ambientes en 1er piso por escalera, bajas expensas ($37. 000 con aysa), pisos de parquet en ambos ambientes, aire acondicionado frio en el living, estufa tiro balanceado, cocina amplia, gran placard en el dormitorio + placar de ropa blanca en el pasillo. Excelente estado. Requisitos: garant\u00eda inmueble dentro de la capital federal o la provincia de BsAs + justificaci\u00f3n de ingresos. Contrato por 24 meses con ajuste trimestral. Corredor Inmobiliario Responsable. Gabriela Nadia Lassig. cpi 5530. Ley 5115: excepto que en la descripci\u00f3n de la propiedad se indique lo contrario, el edificio puede no contar con rampa para personas con movilidad reducida, y no ser Accesible para personas con discapacidades f\u00edsicas. - ley 5859 \u201cPara los casos de alquiler de vivienda, el monto m\u00e1ximo de comisi\u00f3n que se le puede requerir a los propietarios ser\u00e1 el equivalente al cuatro con quince cent\u00e9simos por ciento (4, 15%) del valor total del respectivo contrato. Se encuentra prohibido cobrar a los inquilinos que sean personas f\u00edsicas comisiones inmobiliarias y gastos de gestor\u00eda de informes\u201d\nDestacado\nPublicado hace 5 d\u00edas\nContactar", "revised": false, "rejected": true, "data": {"precio": "$ 300.000", "expensas": "$ 37.000 Expensas", "direccion": "Plaza 2778", "metros": "40 m\u00b2 tot.", "habitaciones": "2 amb.", "hace": "Contactar"}, "image": "https://imgar.zonapropcdn.com/avisos/1/00/53/57/80/75/360x266/1909479802.jpg?isFirstImage=true", "title": "Departamento de 2 ambientes, Villa Urquiza \u00b7 2 Ambientes Bajas Expensas"}, "https://www.zonaprop.com.ar/propiedades/clasificado/alclapin-monoambiente-divisible-al-frente-balcon-super-luminoso-53578133.html": {"id": "53578133", "date": "08-05-2024\n", "index": 76, "content": "$ 300.000\n$ 35.000 Expensas\nZUVIRIA 851\nParque Chacabuco, Capital Federal\n30 m\u00b2 tot.\n1 amb.\n1 dorm.\n1 ba\u00f1o\nDepartamento monoambiente al frente, balcon, divisible, cocina equipada con lugar para lavarropas, ba\u00f1o completo, placard, super luminoso, excelente estado, amenities, jacuzzi, parrilla, muy buena ubicacion A una cuadra de av directorio linea E subte, consulte. Adrian Ver datos\nPublicado desde ayer\nContactar", "revised": false, "rejected": true, "data": {"precio": "$ 300.000", "expensas": "$ 35.000 Expensas", "direccion": "ZUVIRIA 851", "metros": "30 m\u00b2 tot.", "habitaciones": "1 amb.", "hace": "Contactar"}, "image": "https://imgar.zonapropcdn.com/avisos/1/00/53/57/81/33/360x266/1909481886.jpg?isFirstImage=true", "title": "Departamento de 1 ambiente, Parque Chacabuco \u00b7 Monoambiente Divisible Al Frente Balcon Super Luminoso \"Amenities\" Zuviria 851"}}