{"https://www.zonaprop.com.ar/propiedades/clasificado/alclapin-departamento-en-alquiler-3-amb-al-frente-c-balcon-53595843.html": {"id": "53595843", "date": "07-05-2024\n", "index": 2, "content": "13\n$ 470.000\n$ 140.000 Expensas\nAv. Caseros al 3400\nParque Patricios, Capital Federal\n110 m\u00b2 tot.\n3 amb.\n2 dorm.\n1 ba\u00f1o\nAmplio departamento en torre en alquiler de 3 ambientes al frente. Living comedor con amplio balc\u00f3n. Dos dormitorios con placares. Toilette. Ba\u00f1o completo con ba\u00f1adera. Cocina con espacio para comedor de diario. Lavadero independiente. Se entrega reci\u00e9n pintado en impecable estado. Todos los ambientes son externos con excelente luminosidad y entrada de sol. Dos encargados con vivienda. Incluye cochera A partir de oct24. Contrato por 24 con indexaci\u00f3n cada 4 meses. Garant\u00eda propietaria/seguro de cauci\u00f3n.\nPublicado hoy\nContactar", "revised": false, "rejected": false, "data": {"precio": "$ 470.000", "expensas": "$ 140.000 Expensas", "direccion": "Av. Caseros al 3400", "metros": "110 m\u00b2 tot.", "habitaciones": "3 amb.", "hace": "Contactar"}, "image": "https://imgar.zonapropcdn.com/avisos/1/00/53/59/58/43/360x266/1909871321.jpg?isFirstImage=true", "title": "Departamento \u00b7 110m\u00b2 \u00b7 3 Ambientes \u00b7 Departamento en Alquiler 3 Amb Al Frente C/ Balc\u00f3n"}, "https://www.zonaprop.com.ar/propiedades/clasificado/alclapin-3amb-al-frente-con-balcon-en-plena-av-garay!-vista-53584578.html": {"id": "53584578", "date": "07-05-2024\n", "index": 5, "content": "$ 400.000\n$ 80.000 Expensas\nAv. Garay al 2200\nSan Cristobal, Capital Federal\n65 m\u00b2 tot.\n3 amb.\n2 dorm.\n1 ba\u00f1o\nDepartamento de 3 ambientes en torre con sum y PiletaAv. Garay entre Pichincha y Pasco. Piso alto con vista abierta, balc\u00f3n y luz natural. Asimismo, posee una amplia cocina con lavadero incorporado y placard en dormitorios. Excelente estado de conservaci\u00f3n. Transportes CercanosColectivos: 4, 6, 8, 12, 37, 46, 50, 53, 56, 57, 61, 62, 84, 86, 90, 91, 95, 96, 97, 118, 129, 133, 143, 150, 151, 188, 195Adriana Gentile Propiedades le brinda a sus clientes la posibilidad de una financiaci\u00f3n del 50% de la propiedad y el resto hasta en 84 cuotas igual al 1. 2% mensual.\nPublicado desde ayer\nContactar", "revised": false, "rejected": false, "data": {"precio": "$ 400.000", "expensas": "$ 80.000 Expensas", "direccion": "Av. Garay al 2200", "metros": "65 m\u00b2 tot.", "habitaciones": "3 amb.", "hace": "Contactar"}, "image": "https://imgar.zonapropcdn.com/avisos/1/00/53/58/45/78/360x266/1909630962.jpg?isFirstImage=true", "title": "Departamento \u00b7 65m\u00b2 \u00b7 3 Ambientes \u00b7 3amb Al Frente con Balcon en Plena Av Garay! Vista Abierta y Pura Luz"}, "https://www.zonaprop.com.ar/propiedades/clasificado/alclphpa-alquiler-ph-reciclado-a-nuevo-patio-c-parrilla-53592268.html": {"id": "53592268", "date": "07-05-2024\n", "index": 6, "content": "$ 500.000\nConstituci\u00f3n 2644\nSan Cristobal, Capital Federal\n80 m\u00b2 tot.\n3 amb.\n2 dorm.\n1 ba\u00f1o\nDos meses de deposito, Garantia Propietaria Capital o Finaer, 3 Ultimos Recibos de Sueldos. Actualizacion cada 3 meses con Indice ipc. Mascota Consultar\nPublicado hoy\nContactar", "revised": false, "rejected": false, "data": {"precio": "$ 500.000", "expensas": "", "direccion": "Constituci\u00f3n 2644", "metros": "80 m\u00b2 tot.", "habitaciones": "3 amb.", "hace": "Contactar"}, "image": "https://imgar.zonapropcdn.com/avisos/1/00/53/59/22/68/360x266/1909799657.jpg?isFirstImage=true", "title": "PH de 3 ambientes, San Cristobal \u00b7 Alquiler PH Reciclado a Nuevo Patio C/parrilla"}, "https://www.zonaprop.com.ar/propiedades/clasificado/alclapin-3-amb.-apto-prof.-cohera.-balcon-tza.-amoblado.-muy-53502391.html": {"id": "53502391", "date": "07-05-2024\n", "index": 7, "content": "$ 650.000\n$ 55.000 Expensas\nCHICLANA 3200\nParque Patricios, Capital Federal\n88 m\u00b2 tot.\n3 amb.\n2 dorm.\n2 ba\u00f1os\n1 coch.\n3 amb. Apto prof. cohera. Fte Y cfte. Balcon tza, parrilla Y balcon. 2 ba\u00f1os completos uno es suite. Amoblado. Edificio moderno. Impecable. Muy luminoso. excelente unidad Y zona, proximo A av caseros, av jujuy, av brasil Y subtes Y metrobus.\nDestacado\nPublicado hace 4 d\u00edas\nContactar", "revised": false, "rejected": false, "data": {"precio": "$ 650.000", "expensas": "$ 55.000 Expensas", "direccion": "CHICLANA 3200", "metros": "88 m\u00b2 tot.", "habitaciones": "3 amb.", "hace": "Contactar"}, "image": "https://imgar.zonapropcdn.com/avisos/1/00/53/50/23/91/360x266/1909405518.jpg?isFirstImage=true", "title": "Departamento de 3 ambientes, Parque Patricios \u00b7 3 Amb. Apto Prof. Cohera. Balcon Tza. Amoblado. Muy Luminoso. Excelente Unidad"}, "https://www.zonaprop.com.ar/propiedades/clasificado/alclapin-semipiso-3-ambientes-amoblado-muy-luminoso-53572410.html": {"id": "53572410", "date": "07-05-2024\n", "index": 8, "content": "$ 550.000\n$ 80.000 Expensas\nEstados Unidos 3100\nSan Cristobal, Capital Federal\n72 m\u00b2 tot.\n3 amb.\n2 dorm.\n1 ba\u00f1o\nCorredor Responsable: Rene Vera cucicba 6778 / csi 5848- Contacto: Enrique Barzanti - mls id # Ver datos-9. Contrafrente en 8vo piso, contando con un gran caudal de ventilaci\u00f3n y luz natural durante todo el d\u00eda. Totalmente amoblado y equipado. Amplio balc\u00f3n hacia el este y balc\u00f3n franc\u00e9s hacia el norte. Se aceptan hasta 4 personas!! Actualizaci\u00f3n trimestral acorde a Ley 27. 551 (icl) Zona con amplia oferta de lugares gastron\u00f3micos, educativos y de salud. A 1 cuadra de Av. Independencia y a 3 cuadras de Av. San Juan! Educaci\u00f3n. Facultad De Psicolog\u00eda uba, Sede Independencia_a 150mts. instituto santa cruz_ a 100mts. Instituto Secundario El Taller_a 150mts. colegio mater ter admirabilis_a 200mts. Escuela N\u00b0 15 - Jorge Luis Chinetti_ a 30mts. Escuela Primaria Com\u00fan N\u00b0 03 - Rufino S\u00e1nchez_a 250mts. Escuela Infantil San Francisco de As\u00eds_ a 350mts. Escuela N\u00b011 D. E. 6 - Jos\u00e9 Federico Moreno_a 350mts. Esc. Primaria Com\u00fan N\u00b0 12 Rep\u00fablica del Paraguay_ a 600mts. salud. Hospital C\u00e9sar Milstein_ a 250mts. Hospital General de Agudos Jos\u00e9 Mar\u00eda Ramos Mej\u00eda_a 350mts. Hospital Espa\u00f1ol_a 850mts. colectivos: 31, 31, 88, 41, 101, 75, subte: l\u00ednea \"E\", estaci\u00f3n general urquiza, a 450mts. Remax Argentina S. R. L. No ejerce el corretaje inmobiliario. El presente sitio web es una plataforma en donde cada oficina inmobiliaria independiente que contrata los servicios re/max puede publicar las propiedades a su cargo. Cada oficina es de propiedad y gesti\u00f3n independiente, por lo que Remax Argentina S. R. L no interviene en los datos de la publicaci\u00f3n, en la operaci\u00f3n inmobiliaria, ni en la confecci\u00f3n y/o firma del boleto de compraventa y/o escritura y/o contrato de alquiler. En cumplimiento de las leyes vigentes que regulan el corretaje inmobiliario, Ley Nacional 25. 028, Ley 22. 802 de Lealtad Comercial, Ley 24. 240 de Defensa al Consumidor, las normas del C\u00f3digo Civil y Comercial de la Naci\u00f3n y Constitucionales, los agentes/gestores no ejercen el corretaje inmobiliario. Todas las operaciones inmobiliarias son objeto de intermediaci\u00f3n y conclusi\u00f3n por parte del corredor p\u00fablico inmobiliario colegiado a cargo de la publicaci\u00f3n, cuyos datos se exhiben en la presente. La presente publicaci\u00f3n describe las caracter\u00edsticas esenciales del inmueble, debi\u00e9ndose consultar al corredor p\u00fablico inmobiliario responsable de la operaci\u00f3n por la eventual actualizaci\u00f3n de las medidas, descripciones arquitect\u00f3nicas y funcionales, valores de expensas, servicios, impuestos, precios y dem\u00e1s informaci\u00f3n, cuyos valores son aproximados. Para los casos de alquiler de vivienda, el monto m\u00e1ximo de comisi\u00f3n que se le puede requerir a los propietarios ser\u00e1 el equivalente al cuatro con quince cent\u00e9simos por ciento (4, 15%) del valor total del respectivo contrato. Se encuentra prohibido cobrar a los inquilinos que sean personas f\u00edsicas comisiones inmobiliarias y gastos de gestor\u00eda de informes. El inmueble no es accesible para personas con discapacidades f\u00edsicas.\nPublicado hace 4 d\u00edas\nContactar", "revised": false, "rejected": false, "data": {"precio": "$ 550.000", "expensas": "$ 80.000 Expensas", "direccion": "Estados Unidos 3100", "metros": "72 m\u00b2 tot.", "habitaciones": "3 amb.", "hace": "Contactar"}, "image": "https://imgar.zonapropcdn.com/avisos/1/00/53/57/24/10/360x266/1909358526.jpg?isFirstImage=true", "title": "Departamento \u00b7 67m\u00b2 \u00b7 3 Ambientes \u00b7 Semipiso 3 Ambientes Amoblado Muy Luminoso"}, "https://www.zonaprop.com.ar/propiedades/clasificado/alclapin-av-independencia-y-rincon-3-ambientes-grandes-53571130.html": {"id": "53571130", "date": "07-05-2024\n", "index": 9, "content": "$ 550.000\n$ 85.000 Expensas\nAvenida Independencia 2000\nSan Cristobal, Capital Federal\n80 m\u00b2 tot.\n3 amb.\n2 dorm.\n1 ba\u00f1o\nDepartamento al frente sobre Avenida Independencia - Ampios ambientes. Balc\u00f3n corrido al frente. Hall de entrada - Living-comedor. 2 dormitorios (ambos con placard) Cocina comedor diario. Ba\u00f1o completo + Ba\u00f1o de servicio. Pisos de parquet. Entrega aproximada 20 d\u00edas. 2 ascensores\nPublicado hace 4 d\u00edas\nContactar", "revised": false, "rejected": false, "data": {"precio": "$ 550.000", "expensas": "$ 85.000 Expensas", "direccion": "Avenida Independencia 2000", "metros": "80 m\u00b2 tot.", "habitaciones": "3 amb.", "hace": "Contactar"}, "image": "https://imgar.zonapropcdn.com/avisos/1/00/53/57/11/30/360x266/1909329328.jpg?isFirstImage=true", "title": "Departamento de 3 ambientes, San Cristobal \u00b7 Av Independencia y Rinc\u00f3n - 3 Ambientes Grandes - Balc\u00f3n"}, "https://www.zonaprop.com.ar/propiedades/clasificado/alclapin-3amb-s-av!-ubic-ideal!-sj-y-boe!-coc-recic-lav!-bno!-53562563.html": {"id": "53562563", "date": "07-05-2024\n", "index": 12, "content": "$ 370.000\n$ 20.000 Expensas\nAvenida San Juan 3500\nSan Cristobal, Capital Federal\n61 m\u00b2 tot.\n3 amb.\n2 dorm.\n1 ba\u00f1o\n\u00a1 3 ambientes en san juan Y boedo! \u00a1 listo para ser habitado! #Departamento | #Est\u00e1ndar | #3amb | #Lateral | #SanJuanyboedoAvenida San Juan 3500, Piso 2 - Ciudad Aut\u00f3noma de Buenos Aires\u00b7 Caracter\u00edsticas: ~ Departamento de tres (3) ambientes, en un segundo (2\u00ba) piso por escalera, dispuesto hacia el lateral, ubicado en el centro neur\u00e1lgico del barrio de Boedo. ~ Orientaci\u00f3n N (Norte). Impecable estado de conservaci\u00f3n interior de cada uno de sus ambientes. Vista interior. Gran ventilaci\u00f3n. Distribuci\u00f3n funcional~ Gran afluencia comercial y residencial en la zona. Ubicado en el coraz\u00f3n del emblem\u00e1tico cruce de calles principal del barrio: San Juan y Boedo. ~ Conectividad con medios de transporte. M\u00faltiples colectivos y subte/metro L\u00ednea E - Estaci\u00f3n Boedo. Cercan\u00eda a subida/bajada Autopista (au) 25 de Mayo. ~ Su oferta comercial incluye actividades recreativas y culturales, locales gastron\u00f3micos, farmacias, paseos, instituciones m\u00e9dicas y educativas. \u00b7 Edificio: ~ Antiguo, entre medianeras. Su fachada combina hormig\u00f3n pintado en color beige con planta baja revestida en m\u00e1rmol negro. ~ pb, m\u00e1s dos (2) pisos. No cuenta con ascensor. Baj\u00edsimas expensas. Previsibles gastos de mantenimiento mensuales. \u00b7 Distribuci\u00f3n: ~ Living comedor. ~ Cocina independiente. ~ Lavadero incorporado en cocina. ~ Distribuidor. ~ Ba\u00f1o completo con ba\u00f1era. ~ Dormitorio principal con placard. ~ Dormitorio secundario. \u00b7 Equipamiento: ~ Paredes pintadas en tonalidades claras conservan su natural luminosidad. Pisos de parquet en living comedor, distribuidor y dormitorios. ~ Ba\u00f1o con pisos revestidos en cer\u00e1micas color beige. Artefactos completos y ba\u00f1era instalados. Vanitory nuevo. Hogar en living comedor. Aire acondicionado de pared. ~ Cocina con pisos revestidos mosaicos color borravino claro con granas blancas y paredes revestidas en azulejos blancos con guarda decorativa. ~ Cocina a gas. Agua caliente suministrada a trav\u00e9s de calef\u00f3n a gas. Mobiliario de cocina (bajo mesada y alacena) de melamina/mdf color blanco. ~ Mesada de granito gris mara. Conexi\u00f3n para lavarropas bajo mesada. Turbina de acero inoxidable instalada en cocina como extractor / purificador de aire. ~ Cuenta con placard empotrado con puertas frontales, divisores, cajoneras, barrales y dem\u00e1s interiores a medida instalados en su dormitorio principal. \u00b7 Requisitos solicitados por la parte propietaria: ~ 1 mes de alquiler por adelantado. ~ 1 mes de dep\u00f3sito de garant\u00eda. ~ De la fianza: garant\u00eda propietaria o sistema de garant\u00edas de cauci\u00f3n (Finaer / Fiancor). ~ De los ingresos: \u00faltimos tres (3) recibos de sueldo o certificaci\u00f3n de ingresos por contador p\u00fablico. \u00b7 Condiciones ofrecidas por la parte propietaria: ~ Duraci\u00f3n del contrato: 12 meses (contrato de alquiler temporario sin muebles). ~ Actualizaci\u00f3n: ipc \u00b7 \u00cdndice de Precios al Consumidor publicado por el indec. ~ Periodicidad de actualizaci\u00f3n: Trimestral. #Nota: El edificio no cuenta con accesibilidad para personas con movilidad reducida (Ley 5115). Las im\u00e1genes en este anuncio publicadas son meramente ilustrativas y no poseen car\u00e1cter contractual. El importe de expensas anunciado ha sido extra\u00eddo de su \u00faltima facturaci\u00f3n, es orientativo, no vinculante y est\u00e1 sujeto a modificaciones y/o variaciones sin previa publicidad. Las medidas expresadas en el presente aviso son aproximadas y a t\u00edtulo informativo. Las medidas originales surgir\u00e1n de los respectivos planos y/o escritura del inmueble. El inmueble no es apto para mascotas por expresa solicitud de sus propietarios en el contrato de comercializaci\u00f3n. Somos especialistas en operaciones simult\u00e1neas. Tasamos en los 48 barrios de la Ciudad de Buenos Aires: . ar/tasaciones/spinelli propiedadeswww. spinelliprop. com. ar#Visitas por WhatsApp al +54 9 11 Ver datos#Reservas al Ver datos Ver datos#Consultas a Ver datos#Oficina en Avenida San Juan 3467 - cabadesde 1921 - #OportunidadesGrandesComoUnaCasa\nPublicado hace 6 d\u00edas\nContactar", "revised": false, "rejected": false, "data": {"precio": "$ 370.000", "expensas": "$ 20.000 Expensas", "direccion": "Avenida San Juan 3500", "metros": "61 m\u00b2 tot.", "habitaciones": "3 amb.", "hace": "Contactar"}, "image": "https://imgar.zonapropcdn.com/avisos/1/00/53/56/25/63/360x266/1909140276.jpg?isFirstImage=true", "title": "Departamento de 3 ambientes, San Cristobal \u00b7 3amb S/av! Ubic Ideal! Sj y Boe! Coc Recic Lav! B\u00f1o! Bjas Exp! Listo P/hab!"}, "https://www.zonaprop.com.ar/propiedades/clasificado/alclapin-3amb-nuevo-fte-2-balcones-60-m-sup2--muebles!-aa!-53560258.html": {"id": "53560258", "date": "07-05-2024\n", "index": 13, "content": "$ 500.000\n$ 57.000 Expensas\nAvenida Juan de Garay al 3200\nParque Patricios, Capital Federal\n60 m\u00b2 tot.\n3 amb.\n2 dorm.\n1 ba\u00f1o\n\u00a1 3 amb nuevo C/amenities! \u00a1 2 balcones, frente C/vista panor\u00e1mica! #Alquiler | #Departamento | #Amenities | #ParquePatricios | #3amb | #FrenteAvenida Juan de Garay 3200, Piso 7 - Ciudad Aut\u00f3noma de Buenos Aires\u00b7 Caracter\u00edsticas: ~ Departamento nuevo de tres (3) ambientes nuevo, dispuesto hacia el frente, con dos (2) balcones corridos, ubicado centricamente en el barrio de Parque Patricios. ~ Orientaci\u00f3n hacia el N (Norte). Vista a Ciudad. Ventilaci\u00f3n cruzada. Todos los ambientes cuentan con ventanas al exterior. ~ A 220 metros de Avenida Chiclana. A 410 metros de Avenida San Juan. A 420 metros de Avenida Boedo. A 610 metros de Avenida Jujuy. ~ Conectividad con medios de transporte. M\u00faltiples colectivos y subte/metro L\u00ednea H \u00b7 Estaci\u00f3n La Rioja. Cercan\u00eda a subida Autopista (au) 25 de Mayo. ~ Su oferta comercial incluye actividades recreativas y culturales, locales gastron\u00f3micos, farmacias, paseos, instituciones m\u00e9dicas y educativas. \u00b7 Edificio: ~ Entre medianeras. Su fachada con ladrillo a la vista y barandas de hierro pintadas en color negro. ~ El edificio cuenta con rampa con accesibilidad para personas de movilidad reducida. Acceso por puerta de blindex. Cerradura electr\u00f3nica para el ingreso. ~ Sus palieres comunes garantizan un habitar pac\u00edfico e integran pisos revestidos en porcelanatos color beige claro con terminaci\u00f3n mate y paredes pintadas en blanco. ~ 12 pisos. 3 departamentos por cada uno de sus pisos. 2 ascensores autom\u00e1ticos con cabina de acero inoxidable. Expensas en valores est\u00e1ndar (incluyen Aysa). \u00b7 Distribuci\u00f3n: ~ Living comedor (5. 10m x 3. 95m). ~ Balc\u00f3n 1 desde living comedor (4. 00m x 0. 90m). ~ Cocina sectorizada (2. 65m x 2. 00m). ~ Ba\u00f1o completo con ba\u00f1era (2. 20m x 1. 50m). ~ Dormitorio secundario (3. 05m x 2. 95m). ~ Dormitorio principal (3. 05m x 2. 95m). ~ Balc\u00f3n 2 desde dormitorio principal (1. 40m x 3. 50m). \u00b7 Equipamiento: ~ Paredes pintadas en tonalidades claras conservan su natural luminosidad. Pisos revestidos en porcelanato color gris. Dormitorios revestidos en alfombra. ~ Su cocina cuenta con pisos y paredes revestidos en porcelanato color gris. Mesada de granito. Bacha de acero inoxidable. Anafe, extractor de aire / purificador y cocina, todos el\u00e9ctricos, de acero inoxidable y de marca Domec. ~ Mobiliario de cocina (bajo-mesada y alacenas) de mdf/melamina color wengue. Mesada de m\u00e1rmol marr\u00f3n. Lavadero incorporado a bajo-mesada. Conexi\u00f3n para carga y descarga de lavarropas. ~ Provisi\u00f3n de agua caliente central por termotanques de alta recuperaci\u00f3n. Aire Acondicionado split en living comedor marca Sanyo. ~ Su ba\u00f1o cuenta con pisos y paredes revestidos en porcelanato color gris. Vanitory, artefactos y ba\u00f1era instalados. Calefacci\u00f3n con loza radiante con regulador de temperatura en dormitorios. ~ Cuenta con placares de piso/techo con puertas de apertura frontal, divisores, estantes, barrales, cajoneras y dem\u00e1s interiores a medida instalados en los dos dormitorios. ~ Heladera marca Samsung. Mesa de comedor y silla, de pl\u00e1stico. Cama instalada en dormitorio. \u00b7 Amenities: ~ Sector para parrilleros con equipamiento. ~ Terraza con solarium y espacio de relax. \u00b7 Adicionales: ~ Agua caliente central por termotanques de alta recuperaci\u00f3n. ~ Control de acceso a trav\u00e9s de cerradura electromagn\u00e9tica. \u00b7 Requisitos solicitados por la parte propietaria: ~ 1 mes de alquiler por adelantado. ~ 1 mes de dep\u00f3sito de garant\u00eda. ~ De la fianza: garant\u00eda propietaria o sistema de garant\u00edas de cauci\u00f3n (Finaer / Fiancor). ~ De los ingresos: \u00faltimos tres (3) recibos de sueldo o certificaci\u00f3n de ingresos por contador p\u00fablico. \u00b7 Condiciones ofrecidas por la parte propietaria: ~ Duraci\u00f3n del contrato: 6 \u00f3 12 meses (contrato de alquiler temporario con muebles). ~ Actualizaci\u00f3n: ipc \u00b7 \u00cdndice de Precios al Consumidor publicado por el indec. ~ Periodicidad de actualizaci\u00f3n: Trimestral. #Nota: El edificio no cuenta con accesibilidad para personas con movilidad reducida (Ley 5115). Las im\u00e1genes en este anuncio publicadas son meramente ilustrativas y no poseen car\u00e1cter contractual. El importe de expensas anunciado ha sido extra\u00eddo de su \u00faltima facturaci\u00f3n, es orientativo, no vinculante y est\u00e1 sujeto a modificaciones y/o variaciones sin previa publicidad. Las medidas expresadas en el presente aviso son aproximadas y a t\u00edtulo informativo. Las medidas originales surgir\u00e1n de los respectivos planos y/o escritura del inmueble. El inmueble no es apto para mascotas por expresa solicitud de sus propietarios en el contrato de comercializaci\u00f3n. Somos especialistas en operaciones simult\u00e1neas. Tasamos en los 48 barrios de la Ciudad de Buenos Aires: . ar/tasaciones/spinelli propiedadeswww. spinelliprop. com. ar#Visitas por WhatsApp al +54 9 11 Ver datos#Reservas al Ver datos Ver datos#Consultas a Ver datos#Oficina en Avenida San Juan 3467 - cabadesde 1921 - #OportunidadesGrandesComoUnaCasa\nPublicado hace 5 d\u00edas\nContactar", "revised": false, "rejected": true, "data": {"precio": "$ 500.000", "expensas": "$ 57.000 Expensas", "direccion": "Avenida Juan de Garay al 3200", "metros": "60 m\u00b2 tot.", "habitaciones": "3 amb.", "hace": "Contactar"}, "image": "https://imgar.zonapropcdn.com/avisos/1/00/53/56/02/58/360x266/1909091604.jpg?isFirstImage=true", "title": "Departamento \u00b7 60m\u00b2 \u00b7 3 Ambientes \u00b7 3amb Nuevo Fte 2 Balcones \u00b7 60 m\u00b2 \u00b7 Muebles! Aa! Heladera! Cama! Parr! Amenities!"}, "https://www.zonaprop.com.ar/propiedades/clasificado/alclapin-3amb-nuevo-fte-2-balcones-60-m-sup2--muebles!-aa!-53560254.html": {"id": "53560254", "date": "07-05-2024\n", "index": 14, "content": "$ 500.000\n$ 57.000 Expensas\nAvenida Juan de Garay al 3200\nSan Cristobal, Capital Federal\n60 m\u00b2 tot.\n3 amb.\n2 dorm.\n1 ba\u00f1o\n\u00a1 3 amb nuevo C/amenities! \u00a1 2 balcones, frente C/vista panor\u00e1mica! #Alquiler | #Departamento | #Amenities | #ParquePatricios | #3amb | #FrenteAvenida Juan de Garay 3200, Piso 7 - Ciudad Aut\u00f3noma de Buenos Aires\u00b7 Caracter\u00edsticas: ~ Departamento nuevo de tres (3) ambientes nuevo, dispuesto hacia el frente, con dos (2) balcones corridos, ubicado centricamente en el barrio de Parque Patricios. ~ Orientaci\u00f3n hacia el N (Norte). Vista a Ciudad. Ventilaci\u00f3n cruzada. Todos los ambientes cuentan con ventanas al exterior. ~ A 220 metros de Avenida Chiclana. A 410 metros de Avenida San Juan. A 420 metros de Avenida Boedo. A 610 metros de Avenida Jujuy. ~ Conectividad con medios de transporte. M\u00faltiples colectivos y subte/metro L\u00ednea H \u00b7 Estaci\u00f3n La Rioja. Cercan\u00eda a subida Autopista (au) 25 de Mayo. ~ Su oferta comercial incluye actividades recreativas y culturales, locales gastron\u00f3micos, farmacias, paseos, instituciones m\u00e9dicas y educativas. \u00b7 Edificio: ~ Entre medianeras. Su fachada con ladrillo a la vista y barandas de hierro pintadas en color negro. ~ El edificio cuenta con rampa con accesibilidad para personas de movilidad reducida. Acceso por puerta de blindex. Cerradura electr\u00f3nica para el ingreso. ~ Sus palieres comunes garantizan un habitar pac\u00edfico e integran pisos revestidos en porcelanatos color beige claro con terminaci\u00f3n mate y paredes pintadas en blanco. ~ 12 pisos. 3 departamentos por cada uno de sus pisos. 2 ascensores autom\u00e1ticos con cabina de acero inoxidable. Expensas en valores est\u00e1ndar (incluyen Aysa). \u00b7 Distribuci\u00f3n: ~ Living comedor (5. 10m x 3. 95m). ~ Balc\u00f3n 1 desde living comedor (4. 00m x 0. 90m). ~ Cocina sectorizada (2. 65m x 2. 00m). ~ Ba\u00f1o completo con ba\u00f1era (2. 20m x 1. 50m). ~ Dormitorio secundario (3. 05m x 2. 95m). ~ Dormitorio principal (3. 05m x 2. 95m). ~ Balc\u00f3n 2 desde dormitorio principal (1. 40m x 3. 50m). \u00b7 Equipamiento: ~ Paredes pintadas en tonalidades claras conservan su natural luminosidad. Pisos revestidos en porcelanato color gris. Dormitorios revestidos en alfombra. ~ Su cocina cuenta con pisos y paredes revestidos en porcelanato color gris. Mesada de granito. Bacha de acero inoxidable. Anafe, extractor de aire / purificador y cocina, todos el\u00e9ctricos, de acero inoxidable y de marca Domec. ~ Mobiliario de cocina (bajo-mesada y alacenas) de mdf/melamina color wengue. Mesada de m\u00e1rmol marr\u00f3n. Lavadero incorporado a bajo-mesada. Conexi\u00f3n para carga y descarga de lavarropas. ~ Provisi\u00f3n de agua caliente central por termotanques de alta recuperaci\u00f3n. Aire Acondicionado split en living comedor marca Sanyo. ~ Su ba\u00f1o cuenta con pisos y paredes revestidos en porcelanato color gris. Vanitory, artefactos y ba\u00f1era instalados. Calefacci\u00f3n con loza radiante con regulador de temperatura en dormitorios. ~ Cuenta con placares de piso/techo con puertas de apertura frontal, divisores, estantes, barrales, cajoneras y dem\u00e1s interiores a medida instalados en los dos dormitorios. ~ Heladera marca Samsung. Mesa de comedor y silla, de pl\u00e1stico. Cama instalada en dormitorio. \u00b7 Amenities: ~ Sector para parrilleros con equipamiento. ~ Terraza con solarium y espacio de relax. \u00b7 Adicionales: ~ Agua caliente central por termotanques de alta recuperaci\u00f3n. ~ Control de acceso a trav\u00e9s de cerradura electromagn\u00e9tica. \u00b7 Requisitos solicitados por la parte propietaria: ~ 1 mes de alquiler por adelantado. ~ 1 mes de dep\u00f3sito de garant\u00eda. ~ De la fianza: garant\u00eda propietaria o sistema de garant\u00edas de cauci\u00f3n (Finaer / Fiancor). ~ De los ingresos: \u00faltimos tres (3) recibos de sueldo o certificaci\u00f3n de ingresos por contador p\u00fablico. \u00b7 Condiciones ofrecidas por la parte propietaria: ~ Duraci\u00f3n del contrato: 6 \u00f3 12 meses (contrato de alquiler temporario con muebles). ~ Actualizaci\u00f3n: ipc \u00b7 \u00cdndice de Precios al Consumidor publicado por el indec. ~ Periodicidad de actualizaci\u00f3n: Trimestral. #Nota: El edificio no cuenta con accesibilidad para personas con movilidad reducida (Ley 5115). Las im\u00e1genes en este anuncio publicadas son meramente ilustrativas y no poseen car\u00e1cter contractual. El importe de expensas anunciado ha sido extra\u00eddo de su \u00faltima facturaci\u00f3n, es orientativo, no vinculante y est\u00e1 sujeto a modificaciones y/o variaciones sin previa publicidad. Las medidas expresadas en el presente aviso son aproximadas y a t\u00edtulo informativo. Las medidas originales surgir\u00e1n de los respectivos planos y/o escritura del inmueble. El inmueble no es apto para mascotas por expresa solicitud de sus propietarios en el contrato de comercializaci\u00f3n. Somos especialistas en operaciones simult\u00e1neas. Tasamos en los 48 barrios de la Ciudad de Buenos Aires: . ar/tasaciones/spinelli propiedadeswww. spinelliprop. com. ar#Visitas por WhatsApp al +54 9 11 Ver datos#Reservas al Ver datos Ver datos#Consultas a Ver datos#Oficina en Avenida San Juan 3467 - cabadesde 1921 - #OportunidadesGrandesComoUnaCasa\nPublicado hace 5 d\u00edas\nContactar", "revised": false, "rejected": true, "data": {"precio": "$ 500.000", "expensas": "$ 57.000 Expensas", "direccion": "Avenida Juan de Garay al 3200", "metros": "60 m\u00b2 tot.", "habitaciones": "3 amb.", "hace": "Contactar"}, "image": "https://imgar.zonapropcdn.com/avisos/1/00/53/56/02/54/360x266/1909091479.jpg?isFirstImage=true", "title": "Departamento \u00b7 60m\u00b2 \u00b7 3 Ambientes \u00b7 3amb Nuevo Fte 2 Balcones \u00b7 60 m\u00b2 \u00b7 Muebles! Aa! Heladera! Cama! Parr! Amenities!"}, "https://www.zonaprop.com.ar/propiedades/clasificado/alclappa-alquiler-departamento-3-ambientes-amplios-a-estrenar-53543295.html": {"id": "53543295", "date": "07-05-2024\n", "index": 17, "content": "$ 400.000\nRinc\u00f3n 1510\nSan Cristobal, Capital Federal\n76 m\u00b2 tot.\n3 amb.\n2 dorm.\n1 ba\u00f1o\nSi esta interesado Y cumple con los requisitos mas abajo detallados se le enviara un link para organizar las visitas. amplios 3 ambientes A estrenar. en 1\u00b0 piso por escalera. Expensas casi inexistentes. living cocina integrada, 2 habitaciones, ba\u00f1o completo con ba\u00f1era, - pisos flotante habitaciones. - piso porcelanato pulido en living. - pisos ceramica en ba\u00f1o. - cocina anafe electrico acero inoxidable, - termotanque electrico, 60 litros. - lugar para lavarropas en ba\u00f1o. - placards en habitaciones principal. requisitos. - comprobacion de ingresos. - garantia finaer O garantia propietaria capital federal. Condiciones. - 1 mes adelanto. - 1 mes de deposito. - ajuste trimestral por ipc\nPublicado hace 8 d\u00edas\nContactar", "revised": false, "rejected": true, "data": {"precio": "$ 400.000", "expensas": "", "direccion": "Rinc\u00f3n 1510", "metros": "76 m\u00b2 tot.", "habitaciones": "3 amb.", "hace": "Contactar"}, "image": "https://imgar.zonapropcdn.com/avisos/1/00/53/54/32/95/360x266/1908710766.jpg?isFirstImage=true", "title": "Departamento de 3 ambientes, San Cristobal \u00b7 Alquiler Departamento 3 Ambientes Amplios a Estrenar"}, "https://www.zonaprop.com.ar/propiedades/clasificado/alclapin-departamento-en-barracas-53528858.html": {"id": "53528858", "date": "07-05-2024\n", "index": 19, "content": "$ 370.000\n$ 1 Expensas\nFinochietto 2046 2 Piso\nParque Patricios, Capital Federal\n64 m\u00b2 tot.\n3 amb.\n2 dorm.\n1 ba\u00f1o\nDepartamento de 3 ambientes Sin expensas Amplio y Luminoso living - comedor con acceso a balc\u00f3n Cocina completa con alacenas y muebles bajo mesada. Espacio para lavarropas. 2 dormitorios con placards de piso a techoBa\u00f1o completo \u201cPara los casos de alquiler de vivienda, el monto m\u00e1ximo de comisi\u00f3n que se le puederequerir a los propietarios ser\u00e1 el equivalente al cuatro con quince cent\u00e9simos porciento (4, 15%) del valor total del respectivo contrato. Se encuentra prohibido cobrar alos inquilinos que sean personas f\u00edsicas comisiones inmobiliarias y gastos de gestor\u00edade informes\u201dNo Cumple con Ley 5115 (accesibilidad)\nPublicado hace 12 d\u00edas\nContactar", "revised": false, "rejected": false, "data": {"precio": "$ 370.000", "expensas": "$ 1 Expensas", "direccion": "Finochietto 2046 2 Piso", "metros": "64 m\u00b2 tot.", "habitaciones": "3 amb.", "hace": "Contactar"}, "image": "https://imgar.zonapropcdn.com/avisos/1/00/53/52/88/58/360x266/1908378971.jpg?isFirstImage=true", "title": "Departamento \u00b7 60m\u00b2 \u00b7 3 Ambientes \u00b7 Departamento en Barracas"}, "https://www.zonaprop.com.ar/propiedades/clasificado/alclapin-amplio-departamento-de-2-dorm-con-dependencia-53515368.html": {"id": "53515368", "date": "07-05-2024\n", "index": 20, "content": "$ 400.000\n$ 118.000 Expensas\nAvenida Independencia al 1800\nSan Cristobal, Capital Federal\n105 m\u00b2 tot.\n3 amb.\n2 dorm.\n1 ba\u00f1o\nAmplio 3 ambientes con dependencia, a mts de Av. Callao, 4 cuadras de estaci\u00f3n Entre R\u00edos del Subte \"D\" y 7 de Av. 9 de Julio. Ubicado al frente, con orientaci\u00f3n Norte, con excelentes luz y sol! Consta de: - Entrada principal y de servicio- Living-comedor 8, 5 m x 3, 2 m, con balc\u00f3n de 3 m x 1 m- Dormitorio ppal al frente de 3, 4 m x 3 m con placard- 2do dormitorio de 3, 3 m x 2, 8 m con placard agregado- Dependencia de servicio. -Ba\u00f1o principal y de servicio. - Cocina-comedor de 4, 5 m x 2, 2 m- Lavadero cubierto. Agua caliente central (incluida en expensas) Sup. Ppia: 105 m2. Se requieren ingresos demostrables y garant\u00eda propietaria/finaer.\nDestacado\nPublicado hace 13 d\u00edas\nContactar", "revised": false, "rejected": false, "data": {"precio": "$ 400.000", "expensas": "$ 118.000 Expensas", "direccion": "Avenida Independencia al 1800", "metros": "105 m\u00b2 tot.", "habitaciones": "3 amb.", "hace": "Contactar"}, "image": "https://imgar.zonapropcdn.com/avisos/1/00/53/51/53/68/360x266/1908076403.jpg?isFirstImage=true", "title": "Departamento \u00b7 102m\u00b2 \u00b7 3 Ambientes \u00b7 Amplio Departamento de 2 Dorm con Dependencia"}, "https://www.zonaprop.com.ar/propiedades/clasificado/alclappa-dueno-alquila-parque-patricios-53427493.html": {"id": "53427493", "date": "07-05-2024\n", "index": 22, "content": "13\n$ 530.000\n$ 53.000 Expensas\nCorrales Viejos 74\nParque Patricios, Capital Federal\n100 m\u00b2 tot.\n3 amb.\n2 dorm.\n1 ba\u00f1o\nEn inmejorable zona, frente al subte y centro comercial, 3 amb, 2 dorm, placares, ventiladores de techo, lavadero, patio, cocina, divino para no perder!\nSuper destacado\nPublicado hace 27 d\u00edas\nContactar", "revised": false, "rejected": false, "data": {"precio": "$ 530.000", "expensas": "$ 53.000 Expensas", "direccion": "Corrales Viejos 74", "metros": "100 m\u00b2 tot.", "habitaciones": "3 amb.", "hace": "Contactar"}, "image": "https://imgar.zonapropcdn.com/avisos/1/00/53/42/74/93/360x266/1906092447.jpg?isFirstImage=true", "title": "Departamento de 3 ambientes, Parque Patricios \u00b7 Due\u00f1o Alquila Parque Patricios"}, "https://www.zonaprop.com.ar/propiedades/clasificado/alclphin-reservado-53407883.html": {"id": "53407883", "date": "07-05-2024\n", "index": 23, "content": "$ 330.000\nESTADOS UNIDOS 1760\nSan Cristobal, Capital Federal\n65 m\u00b2 tot.\n2 amb.\n2 dorm.\n1 ba\u00f1o\nPh de 2 amb con 2 entrepisos/ ba\u00f1o completo/ cocina/ lavadero bajo escalera/ patio cubierto/ terraza/ reciclado/ no paga expensas/ excelente ubicacion A mts de av entre rios Y A 1 cuadra de av independencia. No accesible seg\u00fan Ley 5115. Para los casos de alquiler de vivienda, el monto m\u00e1ximo de comisi\u00f3n que se le puede requerir a los propietarios ser\u00e1 el equivalente al cuatro con quince cent\u00e9simos por ciento (4, 15%) del valor total del respectivo contrato. Se encuentra prohibido cobrar a los inquilinos que sean personas f\u00edsicas comisiones inmobiliarias y gastos de gestor\u00eda de informes. Aviso legal: Las descripciones arquitect\u00f3nicas y funcionales, valores de expensas, impuestos y servicios, fotos y medidas de este inmueble son aproximados. Los datos fueron proporcionados por el propietario y pueden no estar actualizados a la hora de la visualizaci\u00f3n de este aviso por lo cual pueden arrojar inexactitudes y discordancias con las que surgen de los las facturas, t\u00edtulos y planos legales del inmueble. El interesado deber\u00e1 realizar las verificaciones respectivas previamente a la realizaci\u00f3n de cualquier operaci\u00f3n, requiriendo por s\u00ed o sus profesionales las copias necesarias de la documentaci\u00f3n que corresponda. Guardia natalia. Lino Propiedades. matricula cucicba 8077\nPublicado hace 29 d\u00edas\nContactar", "revised": false, "rejected": true, "data": {"precio": "$ 330.000", "expensas": "", "direccion": "ESTADOS UNIDOS 1760", "metros": "65 m\u00b2 tot.", "habitaciones": "2 amb.", "hace": "Contactar"}, "image": "https://imgar.zonapropcdn.com/avisos/1/00/53/40/78/83/360x266/1905637461.jpg?isFirstImage=true", "title": "PH de 2 ambientes, San Cristobal \u00b7 Reservado"}, "https://www.zonaprop.com.ar/propiedades/clasificado/alclapin-departamento-en-san-cristobal-53347967.html": {"id": "53347967", "date": "07-05-2024\n", "index": 24, "content": "$ 380.000\n$ 68.000 Expensas\nVirrey Cevallos al 900\nSan Cristobal, Capital Federal\n65 m\u00b2 tot.\n4 amb.\n2 dorm.\n1 ba\u00f1o\nAlquiler monserrat 4 AmbientesAl Frente. Luminosoliving Comedor Amplio2 dormitorios con placard. 3er dormitorio o Escritorio. Cocina Separada. Ba\u00f1o Completo. Galeria con cerramiento. Pintura a NuevoSolo con garantia y recibo de sueldo. Contrato por 2 a\u00f1os con ajuste trimestralNo apto mascotas. No accesible. Para los casos de alquiler de vivienda, el monto m\u00e1ximo de comisi\u00f3n que se le puede requerir a los propietarios ser\u00e1 el equivalente al cuatro con quince cent\u00e9simos por ciento (4, 15%) del valor total del respectivo contrato. Se encuentra prohibido cobrar a los inquilinos que sean personas f\u00edsicas comisiones inmobiliarias y gastos de gestoria de informes\". - Matr\u00edcula cucicba n\u00famero 38. Seguridad en negocios inmobiliariosavda. Independencia 815. Cabawww. maicopropiedades. com. arTe. Ver datos / Ver datos\nPublicado hace 42 d\u00edas\nContactar", "revised": false, "rejected": false, "data": {"precio": "$ 380.000", "expensas": "$ 68.000 Expensas", "direccion": "Virrey Cevallos al 900", "metros": "65 m\u00b2 tot.", "habitaciones": "4 amb.", "hace": "Contactar"}, "image": "https://imgar.zonapropcdn.com/avisos/1/00/53/34/79/67/360x266/1904287266.jpg?isFirstImage=true", "title": "Departamento \u00b7 60m\u00b2 \u00b7 4 Ambientes \u00b7 Departamento en San Cristobal"}, "https://www.zonaprop.com.ar/propiedades/clasificado/alclapin-departamento-parque-patricios-hermoso-dpto-3-amb-a-53315718.html": {"id": "53315718", "date": "07-05-2024\n", "index": 26, "content": "$ 550.000\n$ 77.000 Expensas\nSanchez de Loria al 1700\nParque Patricios, Capital Federal\n63 m\u00b2 tot.\n3 amb.\n2 dorm.\n1 ba\u00f1o\n1 coch.\nHermoso Departamento 3 ambientes a estrenar c/ balc\u00f3n corrido, sum y cochera y excelente distribuci\u00f3n, 2 dormitorio 3x3 m2, living comedor, 6 x3 m2, cocina 3x2m2; separada con alacena y bajo mesa, tope de marmol y lugar para el lavarropa, ba\u00f1o completo 2x2m2 c/ ba\u00f1adera, lavatorio de mano, grifer\u00eda y accesorios impecable a estrenar y Toil, Anafe de 4 hornallas y horno a estrenar el dpto se entrega reci\u00e9n pintado e impecable de 63 m2. Abl y aysa incluido en alquiler. - no mascotasrequisitos: - 1 mes de deposito- 1 mes x adelantado- Garantia propietaria de Capital o seguro de caucion finaer C. A. www. finaersa. com. ar. /telf Ver datos- Ingresos demostrables \u201cPara los casos de alquiler de vivienda, el monto m\u00e1ximo de comisi\u00f3n que se le puede requerir a los propietarios ser\u00e1 el equivalente al cuatro con quince cent\u00e9simos por ciento (4, 15%) del valor total del respectivo contrato. Se encuentra prohibido cobrar a los inquilinos que sean personas f\u00edsicas comisiones inmobiliarias y gastos de gestor\u00eda de informes\u201d. Maria Varela, Matricula 4443\nPublicado hace 7 d\u00edas\nContactar", "revised": false, "rejected": false, "data": {"precio": "$ 550.000", "expensas": "$ 77.000 Expensas", "direccion": "Sanchez de Loria al 1700", "metros": "63 m\u00b2 tot.", "habitaciones": "3 amb.", "hace": "Contactar"}, "image": "https://imgar.zonapropcdn.com/avisos/1/00/53/31/57/18/360x266/1903472172.jpg?isFirstImage=true", "title": "Departamento \u00b7 53m\u00b2 \u00b7 3 Ambientes \u00b7 1 Cochera \u00b7 Departamento - Parque Patricios - Hermoso Dpto 3 Amb a Extenar C/ Balc\u00f3n, Sum y Cochera Impecable"}, "https://www.zonaprop.com.ar/propiedades/clasificado/alclappa-departamento-3-ambientes-parque-patricios-53305798.html": {"id": "53305798", "date": "07-05-2024\n", "index": 27, "content": "$ 380.000\n$ 42.000 Expensas\nRondeau 2942\nParque Patricios, Capital Federal\n70 m\u00b2 tot.\n3 amb.\n2 dorm.\n1 ba\u00f1o\nDue\u00f1o directo alquila 3 ambientes con balcon. Terraza. Escalera emergencia \u2013 380. 000 Pesos C. A. B. A. Departamento de 3 amb. , piso 5, muy luminoso, comedor ampli\u00f3, cocina completa y amplia. Ba\u00f1o completo, 2 dormitorios uno de 4 x 4 con amplio placard y otro con ventana al balc\u00f3n. Terraza com\u00fan. En el coraz\u00f3n de Parque Patricios. M\u00e1s de 10 l\u00edneas de colectivos subte l\u00ednea H. A 20 min del centro. 15 min de Once. Excelente Ubicaci\u00f3n. Superficie Cubierta: 70 m2. Ubicado en Rondeau entre La Ri9ja y Dean Funes. Entre La Rioja y Dean Funes, a 1 cuadra de Av. Caseros. - alquiler: Ver datos. Expensas: $42. 000. Para m\u00e1ximo dos adultos, menores no acepto, jubilados no. Mascotas No. Contrato 2 a\u00f1os con aumento cuatrimestral del ipc. se requiere: * 1 mes de dep\u00f3sito no reembolsable. * El Mes de alquiler. *Gastos aprox 35. 000- * Recibos de sueldo propios y de los garantes nada m\u00e1s. Para mayor informacion. Ver datos. Cuando tenga toda la documentaci\u00f3n pedida. De otra forma no se muestra, no respondo lo detallado* Se deja expresa constancia que las medidas, superficies, m2 y proporciones consignadas son aproximados, al igual que las medidas parciales y/o de los ambientes esta sujeto a verificaci\u00f3n y/o ajuste. Fotos de car\u00e1cter no contractual\nPublicado hace 48 d\u00edas\nContactar", "revised": false, "rejected": false, "data": {"precio": "$ 380.000", "expensas": "$ 42.000 Expensas", "direccion": "Rondeau 2942", "metros": "70 m\u00b2 tot.", "habitaciones": "3 amb.", "hace": "Contactar"}, "image": "https://imgar.zonapropcdn.com/avisos/1/00/53/30/57/98/360x266/1903253126.jpg?isFirstImage=true", "title": "Departamento de 3 ambientes, Parque Patricios \u00b7 Departamento 3 Ambientes Parque Patricios"}, "https://www.zonaprop.com.ar/propiedades/clasificado/alclappa-alquiler-departamento-3-ambientes-53171428.html": {"id": "53171428", "date": "07-05-2024\n", "index": 30, "content": "$ 450.000\n$ 25.000 Expensas\nAvenida Caseros 3100\nParque Patricios, Capital Federal\n60 m\u00b2 tot.\n3 amb.\n2 dorm.\n1 ba\u00f1o\nSe alquila departamento de tres ambientes de ubicaci\u00f3n lateral en el barrio de Parque Patricios. Muy buen estado, muy luminoso. Ubicado en un primer piso, al cual se accede mediante escaleras. Edificio de valor hist\u00f3rico.\nPublicado hace 69 d\u00edas\nContactar", "revised": false, "rejected": false, "data": {"precio": "$ 450.000", "expensas": "$ 25.000 Expensas", "direccion": "Avenida Caseros 3100", "metros": "60 m\u00b2 tot.", "habitaciones": "3 amb.", "hace": "Contactar"}, "image": "https://imgar.zonapropcdn.com/avisos/1/00/53/17/14/28/360x266/1909928761.jpg?isFirstImage=true", "title": "Departamento de 3 ambientes Alquiler $ 450.000 \u00b7 Alquiler Departamento 3 Ambientes"}, "https://www.zonaprop.com.ar/propiedades/clasificado/alclapin-3-ambientes-con-gran-patio-53116022.html": {"id": "53116022", "date": "07-05-2024\n", "index": 31, "content": "$ 500.000\n$ 140.000 Expensas\nC\u00e1tulo Castillo 3230\nParque Patricios, Capital Federal\n120 m\u00b2 tot.\n3 amb.\n2 dorm.\n2 ba\u00f1os\nAmplio departamento de 3 ambientes, con gran patio. 120 m2 totales. Excelente luminosidad y estado. Pintado a nuevo. C\u00f3moda cocina con acceso al patio, artefacto de cocina a gas de 4 hornalla, horno y grill, agua caliente individual con termotanque nuevo a estrenar de 120 lts. Dos amplios dormitorios, dos ba\u00f1os completos, uno en suite. Living comedor con acceso al patio. Dos aires acondicionados. Expensas $ 140. 000. - El precio del alquiler se ajustar\u00e1 trimestralmente segun ipc (\u00cfndice de Precios al Consumidor) que informa mes a mes el indec. Tiempo de contrato: 12 O 24 meses. Requistos: 1 mes de alquiler adelantado / un mes de dep\u00f3sioten garantia (se sugiere hacerlo en el equivalente en d\u00f3lares para evitar la devaluaci\u00f3n). Honorarios de imobiliaria segun tiempo de contrato (consultar). Documentaci\u00f3n A presentar: dni, certificados de ingresos (el monto del alquiler debe ser de un m\u00e1xio de 30% del total del ingreso familiar comprobable. Garantia propietaria O seguro de cauci\u00f3n.\nPublicado hace 78 d\u00edas\nContactar", "revised": false, "rejected": false, "data": {"precio": "$ 500.000", "expensas": "$ 140.000 Expensas", "direccion": "C\u00e1tulo Castillo 3230", "metros": "120 m\u00b2 tot.", "habitaciones": "3 amb.", "hace": "Contactar"}, "image": "https://imgar.zonapropcdn.com/avisos/1/00/53/11/60/22/360x266/1899114193.jpg?isFirstImage=true", "title": "Departamento de 3 ambientes, Parque Patricios \u00b7 3 Ambientes con Gran Patio"}, "https://www.zonaprop.com.ar/propiedades/clasificado/alclapin-alquiler-3-ambientes-parque-patricios-sin-garantia-53095635.html": {"id": "53095635", "date": "07-05-2024\n", "index": 32, "content": "$ 330.000\n$ 1 Expensas\nDirecci\u00f3n no informada\nParque Patricios, Capital Federal\n89 m\u00b2 tot.\n3 amb.\n2 dorm.\nDue\u00f1o alquila departamento 3 ambientes en planta baja - due\u00f1o alquila solo A personal de la fuerzas armadas O empresas de primer nivel - alquiler sin garantia propietaria. ubicado sobre la calle 24 de noviembre, rondeau Y avenida caseros. A metros del subte H estacion \"parque patricios\" excelente ubicacion! Alquiler due\u00f1o directo sin garantia. Comunicarse por whatsapp para mas informacion\nDestacado\nPublicado hace 82 d\u00edas\nContactar", "revised": false, "rejected": false, "data": {"precio": "$ 330.000", "expensas": "$ 1 Expensas", "direccion": "Direcci\u00f3n no informada", "metros": "89 m\u00b2 tot.", "habitaciones": "3 amb.", "hace": "Contactar"}, "image": "https://imgar.zonapropcdn.com/avisos/1/00/53/09/56/35/360x266/1898654869.jpg?isFirstImage=true", "title": "Departamento de 3 ambientes, Parque Patricios \u00b7 Alquiler 3 Ambientes Parque Patricios Sin Garantia"}, "https://www.zonaprop.com.ar/propiedades/clasificado/alclphin-amplio-ph-3-ambientes-con-terraza-en-parque-patricios-53062574.html": {"id": "53062574", "date": "07-05-2024\n", "index": 33, "content": "$ 600.000\nesteban de luca 1961\nParque Patricios, Capital Federal\n70 m\u00b2 tot.\n3 amb.\n2 dorm.\n2 ba\u00f1os\nPh 3 ambientes en dos plantas. Pisos pulidos y plastificados. Al entrar gran recepci\u00f3n/escritorio que comunica con amplio living/comedor con hogar. - Espacioso primer dormitorio. -Ba\u00f1o completo. -Cocina. - Segundo dormitorio en suite. - Lavadero. - Excelente terraza propia con cuarto de guardado y segundo lavadero. Todos los ambientes en planta baja dan al patio. \u201cPara los casos de alquiler de vivienda, el monto m\u00e1ximo de comisi\u00f3n que se le puede requerir a los propietarios ser\u00e1 el equivalente al cuatro con quince cent\u00e9simos por ciento (4, 15%) del valor total del respectivo contrato. Se encuentra prohibido cobrar a los inquilinos que sean personas f\u00edsicas comisiones inmobiliarias y gastos de gestor\u00eda de informes\u201d. - aviso legal: Las descripciones arquitect\u00f3nicas y funcionales, valores de expensas, impuestos y servicios, fotos y medidas de este inmueble son aproximados. Los datos fueron proporcionados por el propietario y pueden no estar actualizados a la hora de la visualizaci\u00f3n de este aviso pro lo cual pueden arrojar inexactitudes y discordancias con las que surgen de las facturas, t\u00edtulos y planos legales del inmueble. El interesado deber\u00e1 realizar las verificaciones respectivas previamente a la realizaci\u00f3n de cualquier operaci\u00f3n, requiriendo por s\u00ed o sus profesionales las copias necesarias de la documentaci\u00f3n que corresponda. Visitar \u00fanicamente con personal de la firma previa coordinaci\u00f3n de cita. Para m\u00e1s informaci\u00f3n comunicarse a los tel\u00e9fonos: Ver datos. Ver datos. Ver datos. Ver datos. Next Management S. A. Matricula cucicba N\u00ba 804.\nDestacado\nPublicado hace 28 d\u00edas\nContactar", "revised": false, "rejected": false, "data": {"precio": "$ 600.000", "expensas": "", "direccion": "esteban de luca 1961", "metros": "70 m\u00b2 tot.", "habitaciones": "3 amb.", "hace": "Contactar"}, "image": "https://imgar.zonapropcdn.com/avisos/1/00/53/06/25/74/360x266/1897947963.jpg?isFirstImage=true", "title": "PH de 3 ambientes, Parque Patricios \u00b7 Amplio PH 3 Ambientes con Terraza en Parque Patricios"}, "https://www.zonaprop.com.ar/propiedades/clasificado/alclapin-carlos-calvo-al-2000-t-al-contrafrente-62-m-sup2-53000345.html": {"id": "53000345", "date": "07-05-2024\n", "index": 34, "content": "$ 430.000\n$ 36.000 Expensas\nCarlos Calvo al 2000\nSan Cristobal, Capital Federal\n62 m\u00b2 tot.\n3 amb.\n2 dorm.\n1 ba\u00f1o\n3 ambientes. Todo al contrafrente. 62 M2. Todo A nuevo. Balcon con red Y en todas las aberturas. Vista abierta. Todo sol. Todo externo. Apto profesional. Ba\u00f1o completo. Cocina comedor. 2 placards. Lavadero independiente cubierto. Pisos de madera. Edificio de 9 pisos, 4 por piso, 2 ascensores. expensas: $ 36. 000. -abl: $ 3. 104. -aysa: $ 4. 846. -entre rincon Y sarandisan cristobalpara los casos de alquiler de vivienda, el monto m\u00e1ximo de comisi\u00f3n que se le puede requerir a los propietarios ser\u00e1 el equivalente al cuatro con quince cent\u00e9simos por ciento (4, 15%) del valor total del respectivo contrato. Se encuentra prohibido cobrar a los inquilinos que sean personas f\u00edsicas comisiones inmobiliarias y gastos de gestor\u00eda de informes. *FichaBrick=Ver datos*\nDestacado\nPublicado hace 99 d\u00edas\nContactar", "revised": false, "rejected": false, "data": {"precio": "$ 430.000", "expensas": "$ 36.000 Expensas", "direccion": "Carlos Calvo al 2000", "metros": "62 m\u00b2 tot.", "habitaciones": "3 amb.", "hace": "Contactar"}, "image": "https://imgar.zonapropcdn.com/avisos/1/00/53/00/03/45/360x266/1896943360.jpg?isFirstImage=true", "title": "Departamento \u00b7 62m\u00b2 \u00b7 3 Ambientes \u00b7 Carlos Calvo Al 2000 - T/al Contrafrente 62 m\u00b2 T/a Nuevo Balcon V/abierta T/sol Apto Prof"}, "https://www.zonaprop.com.ar/propiedades/clasificado/alclapin-san-cristobal-3-ambientes-con-cochera-y-vigilancia-52814561.html": {"id": "52814561", "date": "07-05-2024\n", "index": 37, "content": "$ 420.000\n$ 120.000 Expensas\nDirecci\u00f3n no informada\nSan Cristobal, Capital Federal\n68 m\u00b2 tot.\n3 amb.\n2 dorm.\n1 ba\u00f1o\n1 coch.\nHermoso departamento en torre, 3 ambientes con cochera, vista panoramica, amplio living-comedor con salida al balcon, dos dormitorios con placards, cocina ofi, lavadero. - en planta baja pileta de natacion, solarium, parque de juegos, parrilla, sum. - sobre av. independencia, vigilancia las 24 hs. mrc bienes raices / celilia vicente propiedades. pedro goyena N\u00ba 5Ver datos o Ver datos\nPublicado hace 50 d\u00edas\nContactar", "revised": false, "rejected": false, "data": {"precio": "$ 420.000", "expensas": "$ 120.000 Expensas", "direccion": "Direcci\u00f3n no informada", "metros": "68 m\u00b2 tot.", "habitaciones": "3 amb.", "hace": "Contactar"}, "image": "https://imgar.zonapropcdn.com/avisos/1/00/52/81/45/61/360x266/1892604844.jpg?isFirstImage=true", "title": "Departamento de 3 ambientes, San Cristobal \u00b7 San Cristobal 3 Ambientes con Cochera y Vigilancia (Pileta, Sum, Parque, Ect.)"}, "https://www.zonaprop.com.ar/propiedades/clasificado/alclappa-dueno-directo-duplex-con-piscina-y-cochera-52611134.html": {"id": "52611134", "date": "07-05-2024\n", "index": 38, "content": "$ 500.000\n$ 100.000 Expensas\nAvenida Juan de Garay 2200\nParque Patricios, Capital Federal\n80 m\u00b2 tot.\n3 amb.\n2 dorm.\n2 ba\u00f1os\n1 coch.\nDuplex 3 ambientes piso 11 y 12 Gran living con balc\u00f3n. Vista panor\u00e1mica en todos los ambientes. Ba\u00f1o y toilette. Habitaci\u00f3n principal con vestidor y 2da habitaci\u00f3n con Balc\u00f3n. Tres c\u00f3modos placares. Cocina separada, completa, con alto y bajo mesada de gran capacidad de guardado. Cochera fija descubierta. Edificio con amenities (seguridad 24 hs, Sum, piscina). No se aceptan mascotas\nPublicado hace 29 d\u00edas\nContactar", "revised": false, "rejected": false, "data": {"precio": "$ 500.000", "expensas": "$ 100.000 Expensas", "direccion": "Avenida Juan de Garay 2200", "metros": "80 m\u00b2 tot.", "habitaciones": "3 amb.", "hace": "Contactar"}, "image": "https://imgar.zonapropcdn.com/avisos/1/00/52/61/11/34/360x266/1890947925.jpg?isFirstImage=true", "title": "living, toilette \u00b7 Due\u00f1o Directo Duplex con Piscina y Cochera"}, "https://www.zonaprop.com.ar/propiedades/clasificado/alclapin-departamento-san-cristobal-52403113.html": {"id": "52403113", "date": "07-05-2024\n", "index": 39, "content": "$ 650.000\n$ 115.000 Expensas\nAv. Independencia al 1900\nSan Cristobal, Capital Federal\n110 m\u00b2 tot.\n4 amb.\n2 dorm.\n1 ba\u00f1o\nExcelente dpto. De 3 ambientes con dependencia Y patio, recien pintado!! edificio de categoria, balcon corrido, tiene entrada ppal. Y de servicio. 3 Ambientes ampliosc/Balc\u00f3n corrido al frente y patio en contrafrente, Living comedor. Cocina Comedor, Comedor diario, Dependencia servicio, Hall, Lavadero, PatioMedidashall distribuidor 1. 5 X 2, patio 4 X 4, lavadero 2 X 2, cocina comedor 5 X 2. 30, dormitorio principal 3. 50 X 3. 50, segundo dormitorio 3. 20 X 3, balcon 9X2, living 7 X 4, ba\u00f1o auxiliar 1. 95 X 1. 50, lavadero 3X2, habitacion de servicio 3X2. Super luminoso y C\u00f3modo. Descripci\u00f3n- Al frente- 3 ambientes- Dependencia servicio- Dos amplios dormitorios- Balc\u00f3n corrido- Cocina- Comedor- Living- Superficie Cubierta 95 m\u00b2- Superficie total: 110 m\u00b2\nPublicado hace 224 d\u00edas\nContactar", "revised": false, "rejected": false, "data": {"precio": "$ 650.000", "expensas": "$ 115.000 Expensas", "direccion": "Av. Independencia al 1900", "metros": "110 m\u00b2 tot.", "habitaciones": "4 amb.", "hace": "Contactar"}, "image": "https://imgar.zonapropcdn.com/avisos/1/00/52/40/31/13/360x266/1882907341.jpg?isFirstImage=true", "title": "Departamento \u00b7 95m\u00b2 \u00b7 4 Ambientes \u00b7 Departamento - San Cristobal"}, "https://www.zonaprop.com.ar/propiedades/clasificado/alclapin-departamento-en-alquiler-de-3-dorm.-en-parque-53588872.html": {"id": "53588872", "date": "08-05-2024\n", "index": 5, "content": "$ 600.000\n$ 140.000 Expensas\nAv. Caseros 2454\nParque Patricios, Capital Federal\n116 m\u00b2 tot.\n4 amb.\n3 dorm.\n2 ba\u00f1os\nUbicado en la exclusiva calle Caseros en Parque Patricios, Capital Federal, se encuentra este departamento en alquiler, una verdadera joya en el coraz\u00f3n de la ciudad. Con un precio de ar$600. 000, esta propiedad. con una superficie total de 146 m2, distribuidos en 4 ambientes que incluyen 3 dormitorios, 2 ba\u00f1os, cocina y un encantador balc\u00f3n, Entre las comodidades que ofrece esta exclusiva propiedad se encuentran servicios como agua corriente, luz, gas natural, aire acondicionado, ascensor y conexi\u00f3n para lavarropas, garantizando una experiencia de vida de primer nivel. La disposici\u00f3n frontal del inmueble permite disfrutar de una luminosidad excepcional, mientras que su ubicaci\u00f3n estrat\u00e9gica lo convierte en una oportunidad \u00fanica para aquellos que buscan lo mejor en t\u00e9rminos de ubicaci\u00f3n, dise\u00f1o y confort. Eeste departamento en alquiler en Parque Patricios es ideal para aquellos que buscan un espacio amplio, moderno y lleno de estilo en una de las zonas m\u00e1s exclusivas de la ciudad. \u00a1Cont\u00e1ctanos hoy mismo para conocer m\u00e1s detalles sobre esta espectacular propiedad! \u00a1Ll\u00e1menos para conocer m\u00e1s en detalle esta propiedad! Tel: Ver datos. Email: Ver datos. De la Torre Propiedades\nPublicado desde ayer\nContactar", "revised": false, "rejected": false, "data": {"precio": "$ 600.000", "expensas": "$ 140.000 Expensas", "direccion": "Av. Caseros 2454", "metros": "116 m\u00b2 tot.", "habitaciones": "4 amb.", "hace": "Contactar"}, "image": "https://imgar.zonapropcdn.com/avisos/1/00/53/58/88/72/360x266/1909722827.jpg?isFirstImage=true", "title": "Departamento de 4 ambientes, Parque Patricios \u00b7 Departamento en Alquiler de 3 Dorm. en Parque Patricios"}, "https://www.zonaprop.com.ar/propiedades/clasificado/alclapin-alquiler-4-ambientes-cochera.-120-m-sup2--exp-53547158.html": {"id": "53547158", "date": "08-05-2024\n", "index": 19, "content": "$ 650.000\n$ 88.000 Expensas\nMafalda 900\nParque Patricios, Capital Federal\n120 m\u00b2 tot.\n4 amb.\n3 dorm.\n2 ba\u00f1os\n1 coch.\nCorredor Responsable: Claudio Rudecindo cmcpsi 6807 / Cristian Arnal Ponti cpi 3570- Contacto: Andres Rufino - mls id # Ver datos. Alquiler departamento de 4 ambientes con cochera en el barrio nuevo de Parque Patricios. Esta propiedad es una excelente opci\u00f3n para aquellos que buscan amplitud, comodidad y la conveniencia de tener un lugar para estacionar su veh\u00edculo. Al ingresar a la propiedad, te encontrar\u00e1s con un amplio y luminoso living-comedor, ideal para recibir visitas o disfrutar de momentos en familia. La cocina, totalmente equipada, cuenta con modernos electrodom\u00e9sticos y espacio de almacenamiento m\u00e1s que suficiente para tus utensilios y alimentos. Adem\u00e1s, cuenta con una c\u00f3moda barra desayunadora, perfecta para disfrutar de comidas r\u00e1pidas o tomar un caf\u00e9 por la ma\u00f1ana. La propiedad cuenta con tres dormitorios espaciosos, ideales para descansar y recargar energ\u00edas. Cada uno de ellos cuenta con amplios ventanales que permiten la entrada de luz natural y ofrecen vistas agradables. Adem\u00e1s, la propiedad cuenta con dos ba\u00f1os completos, equipados con todos los elementos necesarios para tu comodidad diaria. La cochera, ubicada en el mismo edificio, te brinda la tranquilidad de tener un lugar seguro y conveniente para estacionar tu veh\u00edculo. En cuanto a la ubicaci\u00f3n, el barrio nuevo de Parque Patricios es una zona en crecimiento y desarrollo, con una gran cantidad de servicios, comercios y espacios verdes cercanos. Adem\u00e1s, cuenta con excelentes conexiones de transporte p\u00fablico, lo que te permitir\u00e1 desplazarte f\u00e1cilmente por la ciudad. En resumen, esta propiedad de 4 ambientes con cochera en el barrio nuevo de Parque Patricios es una excelente opci\u00f3n para aquellos que buscan amplitud, comodidad y una ubicaci\u00f3n conveniente. Cuenta con dos ba\u00f1os completos, lo que brinda mayor comodidad y privacidad para los residentes y sus invitados. Adem\u00e1s, el edificio cuenta con un sum (Sal\u00f3n de Usos M\u00faltiples), un espacio com\u00fan destinado a eventos y reuniones sociales. Este espacio adicional es perfecto para celebrar ocasiones especiales, organizar reuniones con amigos o simplemente disfrutar de momentos de esparcimiento con los vecinos. Pero eso no es todo, la propiedad tambi\u00e9n cuenta con una terraza que ofrece una agradable sorpresa: una plaza con plantas y una vista panor\u00e1mica. Este espacio al aire libre es ideal para relajarse, disfrutar del sol y conectar con la naturaleza sin salir de casa. Puedes aprovecharlo para leer un libro, hacer ejercicio o simplemente contemplar la hermosa vista de los alrededores. En resumen, esta propiedad de 4 ambientes con cochera en el barrio nuevo de Parque Patricios no solo ofrece amplitud y comodidad, sino tambi\u00e9n beneficios adicionales como dos ba\u00f1os completos, un sum para eventos y una terraza con una plaza y una vista encantadora. Si tienes m\u00e1s preguntas o necesitas m\u00e1s detalles, no dudes en consultarme. Expensas $ 68. 000 + $20. 000 de cochera. requisitos para alquilar: * recibo de sueldo O constancia de ingreso ( monotributo) * garantia propietaria O seguro de caucion. * incremetos trimestrales segun el indice ipc ( indicie precio consumidor) Colectivos: 46, 70, 91, 118, 188. Remax Argentina S. R. L. No ejerce el corretaje inmobiliario. El presente sitio web es una plataforma en donde cada oficina inmobiliaria independiente que contrata los servicios re/max puede publicar las propiedades a su cargo. Cada oficina es de propiedad y gesti\u00f3n independiente, por lo que Remax Argentina S. R. L no interviene en los datos de la publicaci\u00f3n, en la operaci\u00f3n inmobiliaria, ni en la confecci\u00f3n y/o firma del boleto de compraventa y/o escritura y/o contrato de alquiler. En cumplimiento de las leyes vigentes que regulan el corretaje inmobiliario, Ley Nacional 25. 028, Ley 22. 802 de Lealtad Comercial, Ley 24. 240 de Defensa al Consumidor, las normas del C\u00f3digo Civil y Comercial de la Naci\u00f3n y Constitucionales, los agentes/gestores no ejercen el corretaje inmobiliario. Todas las operaciones inmobiliarias son objeto de intermediaci\u00f3n y conclusi\u00f3n por parte del corredor p\u00fablico inmobiliario colegiado a cargo de la publicaci\u00f3n, cuyos datos se exhiben en la presente. La presente publicaci\u00f3n describe las caracter\u00edsticas esenciales del inmueble, debi\u00e9ndose consultar al corredor p\u00fablico inmobiliario responsable de la operaci\u00f3n por la eventual actualizaci\u00f3n de las medidas, descripciones arquitect\u00f3nicas y funcionales, valores de expensas, servicios, impuestos, precios y dem\u00e1s informaci\u00f3n, cuyos valores son aproximados. Para los casos de alquiler de vivienda, el monto m\u00e1ximo de comisi\u00f3n que se le puede requerir a los propietarios ser\u00e1 el equivalente al cuatro con quince cent\u00e9simos por ciento (4, 15%) del valor total del respectivo contrato. Se encuentra prohibido cobrar a los inquilinos que sean personas f\u00edsicas comisiones inmobiliarias y gastos de gestor\u00eda de informes. El inmueble es accesible para personas con discapacidades f\u00edsicas.\nPublicado hace 8 d\u00edas\nContactar", "revised": false, "rejected": false, "data": {"precio": "$ 650.000", "expensas": "$ 88.000 Expensas", "direccion": "Mafalda 900", "metros": "120 m\u00b2 tot.", "habitaciones": "4 amb.", "hace": "Contactar"}, "image": "https://imgar.zonapropcdn.com/avisos/1/00/53/54/71/58/360x266/1908796391.jpg?isFirstImage=true", "title": "Departamento \u00b7 105m\u00b2 \u00b7 4 Ambientes \u00b7 1 Cochera \u00b7 Alquiler 4 Ambientes + Cochera. 120 m\u00b2 Exp $88.000"}, "https://www.zonaprop.com.ar/propiedades/clasificado/alclapin-departamento-en-san-cristobal-53523043.html": {"id": "53523043", "date": "08-05-2024\n", "index": 22, "content": "23\n$ 700.000\n$ 54.000 Expensas\nJujuy Av. al 1100\nSan Cristobal, Capital Federal\n87 m\u00b2 tot.\n4 amb.\n3 dorm.\n1 ba\u00f1o\nAmplio departamento de 4 ambientes contrafrente con balc\u00f3n. Consta de living comedor, balc\u00f3n corrido, 3 dormitorios con placards, ba\u00f1o completo, cocina completa, lavadero cubierto. Es muy luminoso y funcional. Esta ubicado en Avda. Jujuy al 1100, entre Humberto I y Avda. San Juan, colectivos, subte E, comercios. Pida tasaci\u00f3n: Efectuada por profesionales, que analizan permanentemente el desenvolvimiento del mercado. Conf\u00ede su patrimonio en una empresa s\u00f3lida con respaldo y prestigio. Conf\u00ede en el L\u00edder. Goldstein propiedades. Se deja constancia que los m2 son aproximados, al igual que las medidas parciales y el valor consignado de las expensas mensuales (en caso que corresponda pago de expensas) y las caracter\u00edsticas est\u00e1n sujetos a verificaci\u00f3n y/o ajustes, el precio del inmueble puede ser modificado sin previo aviso. En el caso de tratarse de un inmueble en construcci\u00f3n los detalles de terminaci\u00f3n y la fecha de entrega est\u00e1n sujetos a revisi\u00f3n. Fotos de car\u00e1cter no contractual. Las unidades publicadas est\u00e1n sujetas a disponibilidad. Goldstein Propiedades srl con domicilio en Avda. Corrientes 4666 act\u00faa solamente en car\u00e1cter de comercializadora de los inmuebles ofrecidos. En caso de tratarse de un terreno, la informaci\u00f3n de m2 construibles y plusval\u00eda es orientativa, debiendo ser constatada por el interesado. Inmueble no accesible para personas con discapacidad f\u00edsica ley 5115. Cucicba matr\u00edcula 37. Cmcpsi matr\u00edcula 6003. \u00danicamente en el caso de tratarse de alquiler de vivienda familiar, rige lo indicado en la ley 5859. Venta supeditada al cumplimiento por parte del propietario de los requisitos de la resoluci\u00f3n general N\u00ba 2371 de la afip (pedido de coti).\nDestacado\nPublicado hace 12 d\u00edas\nContactar", "revised": false, "rejected": false, "data": {"precio": "$ 700.000", "expensas": "$ 54.000 Expensas", "direccion": "Jujuy Av. al 1100", "metros": "87 m\u00b2 tot.", "habitaciones": "4 amb.", "hace": "Contactar"}, "image": "https://imgar.zonapropcdn.com/avisos/1/00/53/52/30/43/360x266/1908248372.jpg?isFirstImage=true", "title": "Departamento \u00b7 87m\u00b2 \u00b7 4 Ambientes \u00b7 Departamento en San Cristobal"}, "https://www.zonaprop.com.ar/propiedades/clasificado/alclcain-casa-en-parque-patricios-53514647.html": {"id": "53514647", "date": "08-05-2024\n", "index": 25, "content": "$ 600.000\nCastro al 2100\nParque Patricios, Capital Federal\n250 m\u00b2 tot.\n5 amb.\n4 dorm.\n1 ba\u00f1o\n1 coch.\nOportunidad! Casa a refaccionar en calle Castro al 2100. Cinco ambientes. Cocina. Ba\u00f1o. Lavadero. Terraza. Garage con espacio para dos veh\u00ecculos. Se deja constancia que las caracter\u00edsticas, medidas y superficies consignadas son aproximadas, sujetas a verificaci\u00f3n y/o ajuste. Fotos de car\u00e1cter no contractual. Apto Cr\u00e9dito, se puede Financiar 30% se toma propiedad en parte de pago, puede ser inferior O superior! tasaciones en el diadenver propiedades - cucicba - Mat. No 7568 denver propiedades\nPublicado hace 13 d\u00edas\nContactar", "revised": false, "rejected": false, "data": {"precio": "$ 600.000", "expensas": "", "direccion": "Castro al 2100", "metros": "250 m\u00b2 tot.", "habitaciones": "5 amb.", "hace": "Contactar"}, "image": "https://imgar.zonapropcdn.com/avisos/1/00/53/51/46/47/360x266/1908058608.jpg?isFirstImage=true", "title": "Casa \u00b7 250m\u00b2 \u00b7 5 Ambientes \u00b7 1 Cochera \u00b7 Casa en Parque Patricios"}, "https://www.zonaprop.com.ar/propiedades/clasificado/alclapin-alquiler-departamento-4-amb-en-parque-patricios-53421652.html": {"id": "53421652", "date": "08-05-2024\n", "index": 29, "content": "$ 620.000\n$ 57.000 Expensas\nMirav\u00e9 3000\nParque Patricios, Capital Federal\n75 m\u00b2 tot.\n4 amb.\n3 dorm.\n1 ba\u00f1o\nCorredor Responsable: guillermo frimet cucicba 4235 / Pablo Anibal Montenegro cpmcal 552- Contacto: Claudia Reale - mls id # Ver datos. alquiler departamento de 4 ambientes con balc\u00f3n en parque patricios. Ubicado en sexto piso al frente. Consta de: 3 dormitorios. Cocina semi integrada. Balc\u00f3n. Living - comedor. Ba\u00f1o completo. Edificio de 8 pisos, tiene un solo ascensor, son 2 departamentos por piso. Requisitos para entrar: -Un mes de adelanto. -Un mes de dep\u00f3sito. -Seguro de cauci\u00f3n de Finaer o Garantia Ya o Garantia Propietaria de caba. -No permite mascotas. -Contrato a 2 a\u00f1os. comun\u00edquese con el equipo remax para coordinar una visita. El presente inmueble es accesible para personas con discapacidades f\u00edsicas. Remax Argentina S. R. L. No ejerce el corretaje inmobiliario. El presente sitio web es una plataforma en donde cada oficina inmobiliaria independiente que contrata los servicios re/max puede publicar las propiedades a su cargo. Cada oficina es de propiedad y gesti\u00f3n independiente, por lo que Remax Argentina S. R. L no interviene en los datos de la publicaci\u00f3n, en la operaci\u00f3n inmobiliaria, ni en la confecci\u00f3n y/o firma del boleto de compraventa y/o escritura y/o contrato de alquiler. En cumplimiento de las leyes vigentes que regulan el corretaje inmobiliario, Ley Nacional 25. 028, Ley 22. 802 de Lealtad Comercial, Ley 24. 240 de Defensa al Consumidor, las normas del C\u00f3digo Civil y Comercial de la Naci\u00f3n y Constitucionales, los agentes/gestores no ejercen el corretaje inmobiliario. Todas las operaciones inmobiliarias son objeto de intermediaci\u00f3n y conclusi\u00f3n por parte del corredor p\u00fablico inmobiliario colegiado a cargo de la publicaci\u00f3n, cuyos datos se exhiben en la presente. La presente publicaci\u00f3n describe las caracter\u00edsticas esenciales del inmueble, debi\u00e9ndose consultar al corredor p\u00fablico inmobiliario responsable de la operaci\u00f3n por la eventual actualizaci\u00f3n de las medidas, descripciones arquitect\u00f3nicas y funcionales, valores de expensas, servicios, impuestos, precios y dem\u00e1s informaci\u00f3n, cuyos valores son aproximados. Para los casos de alquiler de vivienda, el monto m\u00e1ximo de comisi\u00f3n que se le puede requerir a los propietarios ser\u00e1 el equivalente al cuatro con quince cent\u00e9simos por ciento (4, 15%) del valor total del respectivo contrato. Se encuentra prohibido cobrar a los inquilinos que sean personas f\u00edsicas comisiones inmobiliarias y gastos de gestor\u00eda de informes. El inmueble no es accesible para personas con discapacidades f\u00edsicas.\nPublicado hace 27 d\u00edas\nContactar", "revised": false, "rejected": false, "data": {"precio": "$ 620.000", "expensas": "$ 57.000 Expensas", "direccion": "Mirav\u00e9 3000", "metros": "75 m\u00b2 tot.", "habitaciones": "4 amb.", "hace": "Contactar"}, "image": "https://imgar.zonapropcdn.com/avisos/1/00/53/42/16/52/360x266/1905927645.jpg?isFirstImage=true", "title": "Departamento \u00b7 69m\u00b2 \u00b7 4 Ambientes \u00b7 Alquiler Departamento 4 Amb en Parque Patricios"}, "https://www.zonaprop.com.ar/propiedades/clasificado/alclapin-4amb-80-m-sup2--frente!-bn-toiltte!-coc-indep-53421106.html": {"id": "53421106", "date": "08-05-2024\n", "index": 30, "content": "$ 460.000\n$ 65.000 Expensas\nEduardo Acevedo 72\nSan Cristobal, Capital Federal\n80 m\u00b2 tot.\n4 amb.\n3 dorm.\n1 ba\u00f1o\n\u00a1 4 ambientes al frente! \u00a1 en la zona m\u00e1s c\u00e9ntrica de caballito! #Departamento | #Est\u00e1ndar | #4amb | #Caballito | #Frente | #ParqueRivadaviaEduardo Acevedo y Avenida Rivadavia, Piso 1 - Ciudad Aut\u00f3noma de Buenos Aires\u00b7 Caracter\u00edsticas: ~ Departamento de cuatro (4) ambientes, dispuesto hacia el frente, en la ubicaci\u00f3n m\u00e1s c\u00e9ntrica y comercial del barrio de Caballito. ~ Orientaci\u00f3n hacia el E (Este), siendo iluminado cada ma\u00f1ana por el alba. Vista arbolada a calle residencial y tranquila. Ventilaci\u00f3n cruzada. A excepci\u00f3n del toilette, todos sus espacios cuentan con ventanas / ventanales hacia el exterior. ~ Bienvenido a este amplio y luminoso departamento de cuatro (4) ambientes en el encantador barrio de Caballito. Ubicado cerca del emblem\u00e1tico Parque Rivadavia y del animado centro comercial de la zona. ~ Entrada principal por hall de recepci\u00f3n y entrada de servicio por living comedor. Esta propiedad ofrece la combinaci\u00f3n perfecta de comodidad y conveniencia en uno de los barrios m\u00e1s buscados de Buenos Aires, con transporte p\u00fablico cercano que te conecta con el resto de la ciudad de forma r\u00e1pida y conveniente. ~ A 72 metros de Avenida Rivadavia. A 172 metros de Avenida La Plata. A 372 metros de Jos\u00e9 Mar\u00eda Moreno. ~ Conectividad con medios de transporte. M\u00faltiples colectivos y subte/metro l\u00ednea A \u00b7 Estaci\u00f3n R\u00edo de Janeiro. Cercan\u00eda a subida/bajada a Autopista (au) 25 de Mayo y Ferrocarril Sarmiento. ~ Su oferta comercial incluye actividades recreativas y culturales, locales gastron\u00f3micos, farmacias, paseos, instituciones m\u00e9dicas y educativas. \u00b7 Edificio: ~ Edificio entre medianeras, construido en el a\u00f1o 1972. Su fachada combina ladrillo visto con frentines de hormig\u00f3n pintado. ~ 9 pisos. 3 departamentos por piso. 1 ascensor autom\u00e1tico con cabina de acero inoxidable. Previsibles gastos de mantenimiento mensuales. \u00b7 Distribuci\u00f3n: ~ Hall de recepci\u00f3n. ~ Living comedor. ~ Balc\u00f3n franc\u00e9s. ~ Distribuidor. ~ Cocina - desayunador. ~ Lavadero independiente. ~ Ba\u00f1o completo. ~ Toilette. ~ Dormitorio principal. ~ Dormitorio secundario. ~ Dormitorio 3. \u00b7 Equipamiento: ~ Puerta principal de seguridad blindada. Paredes pintadas en tonalidades claras conservan su natural luminosidad. Pisos revestidos en parquet en hall de recepci\u00f3n, living comedor, distribuidor y dormitorios. ~ Su cocina separada con espacio para desayunador diario posee pisos y paredes revestidos en cer\u00e1micas color beige brasilia. ~ Mobiliario de cocina (bajo-mesada y alacenas) enchapado en aglomerado color crema con tiradores de aluminio. Mesada de granito modelo rosa de salto. Bacha simple de acero inoxidable. Cocina a gas instalada. ~ Provisi\u00f3n de agua caliente por calef\u00f3n a gas marca Orbis. Mesada de granito negro brasil instalada en sector lavadero. Conexi\u00f3n para carga y descarga de lavarropas. Espacio para tendido de indumentaria con tendedero de techo instalado. ~ Su ba\u00f1o cuenta con pisos revestidos en baldosas color gris claro y paredes revestidas en cer\u00e1micas color \u00e1mbar. Lavatorio de pie, sanitarios completos, ventana hacia el exterior y ba\u00f1era instalada. ~ Su toilette cuenta con pisos revestidos en cer\u00e1micas color azul raf y paredes revestidas en cer\u00e1micas marmoladas s\u00edmil carrara con guarda decorativa de venecitas azul raf. Vanitory de mdf/melamina laqueada color crema e inodoro instalado. ~ Aire acondicionado split instalado en su living comedor. Cuenta con placares de piso/techo con puertas de apertura frontal, divisores, estantes, barrales, cajoneras y dem\u00e1s interiores a medida instalados en sus dormitorios. \u00b7 Adicionales: ~ Control de acceso por cerradura electromagn\u00e9tica. \u00b7 Requisitos solicitados por la parte propietaria: ~ 1 mes de alquiler por adelantado. ~ 1 mes de dep\u00f3sito de garant\u00eda por cada a\u00f1o contratado. ~ De la fianza: garant\u00eda propietaria o sistema de garant\u00edas de cauci\u00f3n (Finaer / Fiancor). ~ De los ingresos: \u00faltimos tres (3) recibos de sueldo o certificaci\u00f3n de ingresos por contador p\u00fablico. \u00b7 Condiciones ofrecidas por la parte propietaria: ~ Duraci\u00f3n del contrato: 12 meses (contrato de alquiler temporario sin muebles). ~ Actualizaci\u00f3n: ipc \u00b7 \u00cdndice de Precios al Consumidor publicado por el indec. ~ Periodicidad de actualizaci\u00f3n: Trimestral. #Nota: El edificio no cuenta con accesibilidad para personas con movilidad reducida (Ley 5115). Las im\u00e1genes en este anuncio publicadas son meramente ilustrativas y no poseen car\u00e1cter contractual. El importe de expensas anunciado ha sido extra\u00eddo de su \u00faltima facturaci\u00f3n, es orientativo, no vinculante y est\u00e1 sujeto a modificaciones y/o variaciones sin previa publicidad. Las medidas expresadas en el presente aviso son aproximadas y a t\u00edtulo informativo. Las medidas originales surgir\u00e1n de los respectivos planos y/o escritura del inmueble. El inmueble no es apto para mascotas por expresa solicitud de sus propietarios en el contrato de comercializaci\u00f3n. Somos especialistas en operaciones simult\u00e1neas. Tasamos en los 48 barrios de la Ciudad de Buenos Aires: . ar/tasaciones/spinelli propiedadeswww. spinelliprop. com. ar#Visitas por WhatsApp al +54 9 11 Ver datos#Reservas al Ver datos Ver datos#Consultas a Ver datos#Oficina en Avenida San Juan 3467 - cabadesde 1921 - #OportunidadesGrandesComoUnaCasa\nPublicado hace 27 d\u00edas\nContactar", "revised": false, "rejected": false, "data": {"precio": "$ 460.000", "expensas": "$ 65.000 Expensas", "direccion": "Eduardo Acevedo 72", "metros": "80 m\u00b2 tot.", "habitaciones": "4 amb.", "hace": "Contactar"}, "image": "https://imgar.zonapropcdn.com/avisos/1/00/53/42/11/06/360x266/1905916519.jpg?isFirstImage=true", "title": "Departamento de 4 ambientes, San Cristobal \u00b7 4amb \u00b7 80 m\u00b2 \u00b7 Frente! B\u00f1 Toiltte! Coc Indep Lavad! Ubic \u00danica! Parque Rivadavia!"}, "https://www.zonaprop.com.ar/propiedades/clasificado/alclapin-parque-patricios-4-amb-fte-c-balcon-super-luminoso-av-53301174.html": {"id": "53301174", "date": "08-05-2024\n", "index": 34, "content": "$ 460.000\n$ 74.000 Expensas\nav saenz 100\nParque Patricios, Capital Federal\n85 m\u00b2 tot.\n4 amb.\n3 dorm.\n1 ba\u00f1o\nDepartamento al frente con balc\u00f3n saliente a la calle, vista abierta. Muy luminoso. El inmueble cuenta con 3 habitaciones. Dormitorio principal de 3, 44 x 3, 15 con placard y piso de madera. Segundo Dormitorio 3 x 3 con placard y piso de madera. Y el tercer dormitorio de 2, 40 x 3 con placard y piso de madera. Gran living-comedor con estufa y piso de parquet, cuenta con espacio recibidor de 2, 20 x 1. Cocina + comedor diario y conexi\u00f3n para lavarropas. Ba\u00f1o completo renovado, con ba\u00f1adera de 2 x 1, 42. El valor de las Expensas incluyen Aysa. Condiciones: Valor de alquiler inicial $ 460. 000. - con actualizaci\u00f3n Trimestral. Se utilizara para la actualizaci\u00f3n, el \u00cdndice para Contratos de Locaci\u00f3n (icl) compuesto en partes iguales por el \u00cdndice de Precios al Consumidor (ipc) y de la Remuneraci\u00f3n Imponible Promedio de Los Trabajadores Estables (ripte) . Contrato a 2 a\u00f1os, 1 mes de adelanto y 1 mes de Dep\u00f3sito, garant\u00eda propietaria caba o sistema de alquiler Premium. Datos \u00fatiles. Transportes Cercanos. Colectivos: 4, 7, 25, 26, 42, 50, 101, 119, 133, 134, 135. Barrio: Parque Chacabuco. Comuna: Comuna 7. \u00c1rea Hospitalaria: htal. J. M. Penna. Comisar\u00eda Comunal: 7. Comisar\u00eda Vecinal: 7B. Distrito Escolar: Distrito Escolar viii. C\u00f3digo Postal: 1424. C\u00f3digo Postal Argentino: C1424bgg. Latitud/Longitud: -34. Ver datos, -58. Ver datos. \"Para los casos de alquiler de vivienda, el monto m\u00e1ximo de comisi\u00f3n que se le puede. requerir a los propietarios ser\u00e1 el equivalente al cuatro con quince cent\u00e9simos por. ciento (4, 15%) del valor total del respectivo contrato. Se encuentra prohibido cobrar a. los inquilinos que sean personas f\u00edsicas comisiones inmobiliarias y gastos de gestor\u00eda. de informes\". - Patricio Jorge Castro (cucicba Mat 5814)\nDestacado\nPublicado hace 21 d\u00edas\nContactar", "revised": false, "rejected": false, "data": {"precio": "$ 460.000", "expensas": "$ 74.000 Expensas", "direccion": "av saenz 100", "metros": "85 m\u00b2 tot.", "habitaciones": "4 amb.", "hace": "Contactar"}, "image": "https://imgar.zonapropcdn.com/avisos/1/00/53/30/11/74/360x266/1903195222.jpg?isFirstImage=true", "title": "Departamento de 4 ambientes, Parque Patricios \u00b7 Parque Patricios 4 Amb Fte C/balcon Super Luminoso Av Saenz y Av Caseros"}}