{"https://www.zonaprop.com.ar/propiedades/clasificado/alclapin-monoambiente-contra-frente-balcon-doble-placard-53598896.html": {"id": "53598896", "date": "08-05-2024\n", "index": 6, "content": "$ 250.000\n$ 48.000 Expensas\nAlsina 2934\nBalvanera, Capital Federal\n42 m\u00b2 tot.\n1 amb.\n1 dorm.\n1 ba\u00f1o\nDepartamento MonoAmbiente, contra frente, balc\u00f3n, dos placares empotrados, cocina separada con muebles de alto y bajo mesada, barra desayunadora, conexi\u00f3n para lava ropas, ba\u00f1o completo, reci\u00e9n pintado. Aire Acondicionado. Excelente ubicaci\u00f3n a 1 cuadra de Av Jujuy. Expensas $ 48. 000. - con aysa incluido ( liq mes de Abril 2024). - Acepta hasta 2 personas. Condiciones de contrato: Contrato a 2 a\u00f1os. Aumento cuatrimestral bajo el \u00edndice de icl. Deposito en u$s. requisitos: Garant\u00eda Propietaria de caba o Seguro de Cauci\u00f3n (empresa Monclair ya el pre aprobado) mas Ingresos demostrables. Ley 5115 la cual establece que en toda publicaci\u00f3n debe estar indicado si es apta para personas con movilidad reducida. Art. 4 previsto en la ley 5859 de caba. Para los casos de alquiler de vivienda, el monto m\u00e1ximo de comisi\u00f3n que se le puede requerir a los propietarios ser\u00e1 el equivalente al cuatro con quince cent\u00e9simos por ciento (4, 15%) del valor total del respectivo contrato. Se encuentra prohibido cobrar a los inquilinos que sean personas f\u00edsicas comisiones inmobiliarias y gastos de gestor\u00eda de informes. - Te recomendamos que te contactes telef\u00f3nicamente con la Inmobiliaria para que le den prioridad a tu b\u00fasqueda y contestar tus consultas. Sin mas saludo a Usted Atte. MonSan Negocios Inmobiliarios.\nPublicado hoy\nContactar", "revised": false, "rejected": false, "data": {"precio": "$ 250.000", "expensas": "$ 48.000 Expensas", "direccion": "Alsina 2934", "metros": "42 m\u00b2 tot.", "habitaciones": "1 amb.", "hace": "Contactar"}, "image": "https://imgar.zonapropcdn.com/avisos/1/00/53/59/88/96/360x266/1909936305.jpg?isFirstImage=true", "title": "Departamento de 1 ambiente, Balvanera \u00b7 Monoambiente - Contra Frente - Balc\u00f3n - Doble Placard - A/a. Luminoso."}, "https://www.zonaprop.com.ar/propiedades/clasificado/alclapin-dpto-en-2-amb.-alquiler-53584235.html": {"id": "53584235", "date": "08-05-2024\n", "index": 9, "content": "$ 250.000\n$ 23.000 Expensas\nRivadavia al 3000\nBalvanera, Capital Federal\n56 m\u00b2 tot.\n2 amb.\n1 dorm.\n1 ba\u00f1o\nAlquiler departamento en importante zona comercial Muy luminosoEl dpto cuenta con: -Living comedor- 1 Domitorio- Cocina- Ba\u00f1o completo-CocinaEn buen estado de conservaci\u00f3n. El edificio cuenta con seguridad y encargado. Excelente ubicaci\u00f3n con gran variedad de transportes- Colectivos: 2, 5, 7, 8, 19, 24, 31, 32, 41, 56, 57, 61, 62, 64, 68, 71, 75, 86, 88, 90, 98, 101, 103, 104, 105, 115, 118, 124, 129, 132, 146, 151, 164, 168, 180, 188, 194- Subtes (Metro) : plaza de miserere (L\u00ednea A) , plaza once (L\u00ednea H) - Trenes: Estaci\u00f3n Once (sarmiento) Requisitos- Garant\u00eda de capital o seguro de caucion. - Mes de dep\u00f3sito y mes adelantado. - S\u00ed es con garant\u00eda demostraci\u00f3n de ingresos- Ajuste trimestral por Ipc- Aceptan mascotasRealizamos visitas puntuales, cons\u00faltenos y agendamos la suya! Le Bleu Negocios Inmobiliarioscod prop lapVer datos\nPublicado desde ayer\nContactar", "revised": false, "rejected": true, "data": {"precio": "$ 250.000", "expensas": "$ 23.000 Expensas", "direccion": "Rivadavia al 3000", "metros": "56 m\u00b2 tot.", "habitaciones": "2 amb.", "hace": "Contactar"}, "image": "https://imgar.zonapropcdn.com/avisos/1/00/53/58/42/35/360x266/1909623364.jpg?isFirstImage=true", "title": "Departamento \u00b7 56m\u00b2 \u00b7 2 Ambientes \u00b7 Dpto en 2 Amb. Alquiler"}, "https://www.zonaprop.com.ar/propiedades/clasificado/alclappa-departamento-2-ambientes-en-imejorable-ubicacion-de-53579778.html": {"id": "53579778", "date": "08-05-2024\n", "index": 12, "content": "$ 250.000\n$ 50.000 Expensas\nDirecci\u00f3n no informada\nBalvanera, Capital Federal\n33 m\u00b2 tot.\n2 amb.\n1 dorm.\n1 ba\u00f1o\n- Dos ambientes, un dormitorio, un ba\u00f1o, cocina separada, living/comedor. - segundo piso interno, ba\u00f1o completo con ba\u00f1adera, cocina separada con termotanque el\u00e9ctrico, amplio dormitorio con un muy buen placard, pisos cer\u00e1micos. - Cocina separada. - Pisos ceramicos. - El edificio cuenta con encargado con vivienda. - Excelente ubicaci\u00f3n, a una cuadra subte l\u00ednea H, estaci\u00f3n Venezuela, a una cuadra de Avenida Belgrano y a dos cuadras de Avenida Independencia, cerca de muchos medios de transporte. A dos cuadras de la Plaza Manzana 66. Requisitos: un mes de adelanto, un mes de dep\u00f3sito, garant\u00eda propietaria de caba, ingresos demostrables. Contrato de 24 meses, ajuste cuatrimestral por ipc. Se entrega pintado\nPublicado hace 3 d\u00edas\nContactar", "revised": false, "rejected": false, "data": {"precio": "$ 250.000", "expensas": "$ 50.000 Expensas", "direccion": "Direcci\u00f3n no informada", "metros": "33 m\u00b2 tot.", "habitaciones": "2 amb.", "hace": "Contactar"}, "image": "https://imgar.zonapropcdn.com/avisos/1/00/53/57/97/78/360x266/1909524045.jpg?isFirstImage=true", "title": "Departamento de 2 ambientes, Balvanera \u00b7 Departamento 2 Ambientes en Imejorable Ubicaci\u00f3n, de F\u00e1cil Acceso Al Subte H"}, "https://www.zonaprop.com.ar/propiedades/clasificado/alclapin-excelente-depto.-2-ambientes-en-la-calle-moreno-al-53577984.html": {"id": "53577984", "date": "08-05-2024\n", "index": 14, "content": "$ 300.000\n$ 35.000 Expensas\nMORENO 2900\nBalvanera, Capital Federal\n31 m\u00b2 tot.\n2 amb.\n1 dorm.\n1 ba\u00f1o\nMuy lindo Departamento de 2 ambientes lateral en la calle Moreno al 2900, Balvanera. Consta del living comedor de 3. 00 x 3. 50, dormitorio con placard 3. 00 x 3. 00, cocina 3. 70 x 1. 60 y ba\u00f1o completo 1. 60 x 2. 20. Superficie total 31 m2. Muy luminoso y en buen estado. No se aceptan mascotas. A 2 cuadras de Av Jujuy (Subte l\u00ednea H) y a 3 cuadras de Av Rivadavia (Subte l\u00ednea A) y todos los transportes. A metros de Hospital Espa\u00f1ol y a 4 cuadras de Hospital Ramos Mej\u00eda. Alberto Daniel Marincola. cuciba N\u00b0 1898. \u201cPara los casos de alquiler de vivienda el monto m\u00e1ximo que se le puede requerir a los propietarios ser\u00e1 el equivalente al cuatro con quince cent\u00e9simos por ciento (4, 15%) del valor total del respectivo contrato. Se encuentra prohibido cobrar comisiones inmobiliarias y gastos de gestoria de informes a los inquilinos en el caso de ser personas f\u00edsicas. \u201d // Importante: el aviso publicado es al mero efecto informativo y no constituye una oferta ni solicitud de oferta o compra, ni una recomendaci\u00f3n de inversi\u00f3n, y se entiende que presenta informaci\u00f3n resumida, preliminar y no definitiva de un inmueble o negocio. Si el aviso contuviera estimaciones o proyecciones, se entender\u00e1 que las mismas son solo opiniones que reflejan expectativas de buena fe. Im\u00e1genes no contractuales. Medidas aproximadas. Los montos y porcentajes son valores de referencia y pueden variar sin previo aviso.\nSuper destacado\nPublicado hace 4 d\u00edas\nContactar", "revised": false, "rejected": false, "data": {"precio": "$ 300.000", "expensas": "$ 35.000 Expensas", "direccion": "MORENO 2900", "metros": "31 m\u00b2 tot.", "habitaciones": "2 amb.", "hace": "Contactar"}, "image": "https://imgar.zonapropcdn.com/avisos/1/00/53/57/79/84/360x266/1909478303.jpg?isFirstImage=true", "title": "Departamento de 2 ambientes, Balvanera \u00b7 Excelente Depto. 2 Ambientes en La Calle Moreno Al 2900, Balvanera"}, "https://www.zonaprop.com.ar/propiedades/clasificado/alclapin-balvanera-alq.-departamento-venezuela-2900-a-53576317.html": {"id": "53576317", "date": "08-05-2024\n", "index": 16, "content": "$ 250.000\nVenezuela 2900\nBalvanera, Capital Federal\n36 m\u00b2 tot.\n1 amb.\n1 dorm.\n1 ba\u00f1o\nVenezuela 2900, Mono ambiente en excelente ubicaci\u00f3n, A metros de Av. Belgrano, Av Independencia, infinidad de l\u00edneas de colectivo, a 3 cuadras subte H. Precio alquiler $ Ver datos. todo incluido, expensas, luz, agua! **Ante cualquier duda comunicarse al Ver datos** Requisitos comprobante de ingresos. Garant\u00eda propietaria, o, seguro de cauci\u00f3n\nDestacado\nPublicado hace 4 d\u00edas\nContactar", "revised": false, "rejected": false, "data": {"precio": "$ 250.000", "expensas": "", "direccion": "Venezuela 2900", "metros": "36 m\u00b2 tot.", "habitaciones": "1 amb.", "hace": "Contactar"}, "image": "https://imgar.zonapropcdn.com/avisos/1/00/53/57/63/17/360x266/1909442031.jpg?isFirstImage=true", "title": "Departamento de 1 ambiente, Balvanera \u00b7 Balvanera - Alq. Departamento - Venezuela 2900 - a Pasos Subte H!"}, "https://www.zonaprop.com.ar/propiedades/clasificado/alclapin-1-ambiente-dividido-impecable-53574375.html": {"id": "53574375", "date": "08-05-2024\n", "index": 19, "content": "$ 280.000\n$ 20.000 Expensas\nDirecci\u00f3n no informada\nBalvanera, Capital Federal\n31 m\u00b2 tot.\n1 amb.\n1 dorm.\n1 ba\u00f1o\nFacultad: 1 Amb. Impecable, dividido, luminoso, c /aire acondicionado Viamonte 2100 y Jose E. Uriburu\nPublicado hace 4 d\u00edas\nContactar", "revised": false, "rejected": false, "data": {"precio": "$ 280.000", "expensas": "$ 20.000 Expensas", "direccion": "Direcci\u00f3n no informada", "metros": "31 m\u00b2 tot.", "habitaciones": "1 amb.", "hace": "Contactar"}, "image": "https://imgar.zonapropcdn.com/avisos/1/00/53/57/43/75/360x266/1909398748.jpg?isFirstImage=true", "title": "Departamento de 1 ambiente, Balvanera \u00b7 1 Ambiente Dividido Impecable"}, "https://www.zonaprop.com.ar/propiedades/clasificado/alclapin-departamento-en-alquiler-2-ambientes-balvanera.-53576157.html": {"id": "53576157", "date": "08-05-2024\n", "index": 20, "content": "$ 300.000\n$ 60.000 Expensas\nAvenida Belgrano al 2600\nBalvanera, Capital Federal\n36 m\u00b2 tot.\n2 amb.\n1 dorm.\n1 ba\u00f1o\nDepartamento en Alquiler en Balvanera-Avda. Belgrano y Saavedra. 8 piso. Muy luminoso. Balc\u00f3n al frente. Requisitos: Garante propietario en caba o Seguro de Cauci\u00f3n. 1 mes de dep\u00f3sitoContrato por dos a\u00f1os. Ajustes trimestrales por ipc.\nPublicado hace 4 d\u00edas\nContactar", "revised": false, "rejected": true, "data": {"precio": "$ 300.000", "expensas": "$ 60.000 Expensas", "direccion": "Avenida Belgrano al 2600", "metros": "36 m\u00b2 tot.", "habitaciones": "2 amb.", "hace": "Contactar"}, "image": "https://imgar.zonapropcdn.com/avisos/1/00/53/57/61/57/360x266/1909438315.jpg?isFirstImage=true", "title": "Departamento \u00b7 36m\u00b2 \u00b7 2 Ambientes \u00b7 Departamento en Alquiler - 2 Ambientes - Balvanera."}}