{"https://www.zonaprop.com.ar/propiedades/clasificado/alclapin-departamento-de-2-ambientes-en-alquiler-en-villa-53581480.html": {"date": "05-05-2024\n", "content": "$ 250.000\nLEOPOLDO MARECHAL 1300\nVilla Crespo, Capital Federal\n37 m\u00b2 tot.\n2 amb.\n1 dorm.\n1 ba\u00f1o\nDepartamento 2 ambientes lateral - excelente ubicacion - Se deja constancia que las caracteristicas, medidas, expensas y superficies consignadas son aproximadas, sujetos a verificacion y/o ajuste. El precio del inmueble puede ser modificado sin previo aviso. Fotos de caracter no contractual. Las unidades publicadas estan sujetas a disponibilidad. Comercializa Migliorisi de Corrientes 4599 srl Profesional responsable Jorge Daniel Gomez cpi 261. Publicado por Migliorisi P. Centenario a traves de Inmomap\nPublicado hoy\nContactar", "revised": true, "rejected": true, "data": {"precio": "$ 250.000", "direccion": "LEOPOLDO MARECHAL 1300", "metros": "37 m\u00b2 tot.", "habitaciones": "2 amb.", "hace": "Publicado hoy"}, "comment": "fiero. parque centenario"}, "https://www.zonaprop.com.ar/propiedades/clasificado/alclappa-2-ambientes-super-luminoso-piso-17-53581944.html": {"date": "05-05-2024\n", "content": "$ 330.000\n$ 58.000 Expensas\nAv. Rivadavia 4006\nAlmagro Sur, Almagro\n50 m\u00b2 tot.\n2 amb.\n1 dorm.\n1 ba\u00f1o\nExcelente estado, muy luminoso, a pasos del subte A estaci\u00f3n Castro Barros. Edificio torre en excelente estado y mantenimiento, piso 17. Ajuste trimestral por ipc\nPublicado hoy\nContactar", "revised": true, "rejected": false, "data": {"precio": "$ 330.000", "expensas": "$ 58.000 Expensas", "direccion": "Av. Rivadavia 4006", "metros": "50 m\u00b2 tot.", "habitaciones": "2 amb.", "hace": "Contactar"}, "comment": "don bosco. balcon. cuidado"}, "https://www.zonaprop.com.ar/propiedades/clasificado/alclapin-2-ambientes-2-personas-sin-mascotas-garantia-de-53443187.html": {"date": "05-05-2024\n", "content": "$ 290.000\n12%\n$ 37.000 Expensas\nPRINGLES 591\nAlmagro, Capital Federal\n42 m\u00b2 tot.\n2 amb.\n1 dorm.\n1 ba\u00f1o\nDos ambientes apto profesional Y/O vivienda. En excelente estado. Cocina Y ba\u00f1o completos Y lavadero independiente. Si es vivienda solamente 2 personas Y sin mascotas. En excelente ubicaci\u00f3n: A 2 cuadras de avenidas: corrientes Y diaz velez Y A 1 cuadra del hospital italiano Y con todo el transporte cerca - toma garant\u00eda propietaria O caucion de finaer. Primeros 4 meses: $330. 000 por mes. Actualiza cada 4 meses segun I. C. L.\nDestacado\nPublicado desde ayer\nContactar", "revised": true, "rejected": false, "data": {"precio": "$ 290.000", "expensas": "$ 37.000 Expensas", "direccion": "PRINGLES 591", "metros": "42 m\u00b2 tot.", "habitaciones": "2 amb.", "hace": "Destacado\nPublicado desde ayer"}, "comment": "hospital italiano. esta bien"}, "https://www.zonaprop.com.ar/propiedades/clasificado/alclapin-av-jujuy-y-av-belgrano-dos-ambientes-muy-luminoso!apto-53581135.html": {"date": "05-05-2024\n", "content": "$ 320.000\n$ 52.000 Expensas\nAv. Jujuy al 500\nSan Cristobal, Capital Federal\n38 m\u00b2 tot.\n2 amb.\n1 dorm.\n1 ba\u00f1o\nSobre Av. Jujuy a 1c. Del Subte H, con muchos medios de comunicaci\u00f3n, C\u00f3modo 2 ambientes lateral en prolijo Edificio con seguridad 24 hs. (totem) . - apto para uso profesional. Se ingresa directamente al living-Comedor con pisos parquet y ventanal a pulm\u00f3n abierto muy luminoso; cocina office con muebles sobre y bajo mesada (todo a nuevo) ; artefacto de cocinar convencional a gas (nuevo) lavadero contiguo con calef\u00f3n a gas. Peque\u00f1o hall de distribuci\u00f3n con vestidor, 1 amplio dormitorio con pisos parquet y ba\u00f1o completo con ba\u00f1era y aireaci\u00f3n natural. Reci\u00e9n pintado y muy buen estado general. . Subte: H y m\u00faltiples l\u00edneas de colectivos. Excelentes accesos. Plaza a 1 cuadra(espacio verde y de esparcimiento, ideal ni\u00f1os) Ideal m\u00e1ximo 2 personas. medida de los ambientes: Living-Comedor: 5. 00x3. 00Cocina office: 3. 30x1. 50 con lavaderohall de distribuci\u00f3n 0. 80x0. 75 con acceso a peque\u00f1o vestidor 1. 00x1. 40dormitorio: 3. 00x3. 00 con ventana a pulm\u00f3n\u00f1o completo con ba\u00f1era: 1. 90x1. 80condiciones: Contrato x 24 meses con ajuste trimestral x ipc. 1 mes adelantado1 mes deposito (en d\u00f3lares) 1 garant\u00eda propietaria de caba \u00f3 garant\u00eda de Alquiler. Demostraci\u00f3n de ingresos tanto del garante como del inquilino. **Corredor Inmobiliario Responsable Adrian Ridelnik cucicba Mat 197. *Se deja constancia que las medidas y superficies indicados son aproximados y al s\u00f3lo efecto orientativo. Las medidas reales surgir\u00e1n del t\u00edtulo de propiedad respectivo. Las medidas parciales y/o de los ambientes y el valor consignado de expensas mensuales, servicios y abl est\u00e1 sujeto a verificaci\u00f3n y/o ajuste. Art. 4 de la Ley 5. 859 de C. A. B. A \"Para los casos de alquiler de vivienda \u00fanica, el monto m\u00e1ximo de comisi\u00f3n que se le puede requerir a los propietarios ser\u00e1 el equivalente al cuatro con quince cent\u00e9simos por ciento (4, 15%) del valor total del respectivo contrato. Se encuentra prohibido cobrar a los inquilinos que sean personas f\u00edsicas comisiones inmobiliarias cuando el destino sea vivienda \u00fanica y permanente \". -\nPublicado desde ayer\nContactar", "revised": true, "rejected": false, "data": {"precio": "$ 320.000", "expensas": "$ 52.000 Expensas", "direccion": "Av. Jujuy al 500", "metros": "38 m\u00b2 tot.", "habitaciones": "2 amb.", "hace": "Publicado desde ayer"}, "comment": "lindo. moderno. luz. cerca de saavedra\r\nmonolito de seguridad"}, "https://www.zonaprop.com.ar/propiedades/clasificado/alclphin-ph-de-2-ambientes-en-venta-53580319.html": {"date": "05-05-2024\n", "content": "$ 280.000\nSalcedo al 3200\nBoedo, Capital Federal\n50 m\u00b2 tot.\n2 amb.\n1 dorm.\n1 ba\u00f1o\n\u2022 Gran living-comedor con salida a peque\u00f1o patio \u2022 Cocina incorporada con alacena\u2022 Amplio dormitorio con placard\u2022 Lavadero\u2022 Ba\u00f1o completobuena ubicaci\u00f3n a metros de Av. Chiclana, a 4 cuadras de Av. Boedo, 2 de Av. Juan de Garay y a 3 de Av. Pav\u00f3n. 50 Metros totalesmuy buen estado de conservaci\u00f3n Y usoventa directa\nPublicado desde ayer\nContactar", "revised": false, "rejected": true, "data": {"precio": "$ 280.000", "direccion": "Salcedo al 3200", "metros": "50 m\u00b2 tot.", "habitaciones": "2 amb.", "hace": "Publicado desde ayer"}, "comment": "En Venta "}, "https://www.zonaprop.com.ar/propiedades/clasificado/alclappa-departamento-de-2-ambientes-en-el-barrio-de-boedo-53581083.html": {"date": "05-05-2024\n", "content": "$ 290.000\n$ 34.000 Expensas\nIncl\u00e1n 4200\nBoedo, Capital Federal\n33 m\u00b2 tot.\n2 amb.\n1 dorm.\nDepartamento de 2 ambientes en el barrio de Boedo en Inclan a metros de Av. La Plata. Cuenta con cocina independiente y ba\u00f1o con ducha. Piso alto, hermosa vista en los dos ambientes y super luminoso. Dormitorio con placard. Requisitos: recibo de sueldo en blanco y garant\u00eda propietaria en Capital Federal.\nPublicado desde ayer\nContactar", "revised": true, "rejected": true, "data": {"precio": "$ 290.000", "expensas": "$ 34.000 Expensas", "direccion": "Incl\u00e1n 4200", "metros": "33 m\u00b2 tot.", "habitaciones": "2 amb.", "hace": "Contactar"}, "comment": "No hay gas"}, "https://www.zonaprop.com.ar/propiedades/clasificado/alclappa-alquiler-de-depto-53581052.html": {"date": "05-05-2024\n", "content": "$ 350.000\n$ 20.000 Expensas\nOnce, Capital Federal\n47 m\u00b2 tot.\n2 amb.\n1 dorm.\n1 ba\u00f1o\nAlquilo departamento de estilo franc\u00e9s. Muy luminoso y espacioso. Tiene un balc\u00f3n en la habitaci\u00f3n con vista a la calle y en el living dos ventanas. Una de ellas, tambi\u00e9n con vista a la calle. La cocina es grande, el ba\u00f1o chico, pero funcional. Posee un aire acondicionado frio/calor. El edificio est\u00e0 a diez pasos de, la linea b de subte y cuatro cuadras de la facultad de medicina y el hospital de cl\u00ednicas.\nPublicado desde ayer\nContactar", "revised": false, "rejected": true, "data": {"precio": "$ 350.000", "expensas": "$ 20.000 Expensas", "direccion": "", "metros": "47 m\u00b2 tot.", "habitaciones": "2 amb.", "hace": "Contactar"}, "comment": "Fea zona"}, "https://www.zonaprop.com.ar/propiedades/clasificado/alclappa-departamento-2-ambientes-en-imejorable-ubicacion-de-53579778.html": {"date": "05-05-2024\n", "content": "$ 250.000\n$ 50.000 Expensas\nBalvanera, Capital Federal\n33 m\u00b2 tot.\n2 amb.\n1 dorm.\n1 ba\u00f1o\n- Dos ambientes, un dormitorio, un ba\u00f1o, cocina separada, living/comedor. - segundo piso interno, ba\u00f1o completo con ba\u00f1adera, cocina separada con termotanque el\u00e9ctrico, amplio dormitorio con un muy buen placard, pisos cer\u00e1micos. - Cocina separada. - Pisos ceramicos. - El edificio cuenta con encargado con vivienda. - Excelente ubicaci\u00f3n, a una cuadra subte l\u00ednea H, estaci\u00f3n Venezuela, a una cuadra de Avenida Belgrano y a dos cuadras de Avenida Independencia, cerca de muchos medios de transporte. A dos cuadras de la Plaza Manzana 66. Requisitos: un mes de adelanto, un mes de dep\u00f3sito, garant\u00eda propietaria de caba, ingresos demostrables. Contrato de 24 meses, ajuste cuatrimestral por ipc. Se entrega pintado\nPublicado desde ayer\nContactar", "revised": true, "rejected": false, "data": {"precio": "$ 250.000", "expensas": "$ 50.000 Expensas", "direccion": "", "metros": "33 m\u00b2 tot.", "habitaciones": "2 amb.", "hace": "Contactar"}, "comment": "Cerca de Saavedra. Frio"}, "https://www.zonaprop.com.ar/propiedades/clasificado/alclappa-alquiler-temporario-dueno-directo-53580920.html": {"date": "05-05-2024\n", "content": "$ 300.000\n$ 40.000 Expensas\nAvenida Santa Fe 2600\nBarrio Norte, Capital Federal\n365 m\u00b2 tot.\n2 amb.\n1 dorm.\n1 ba\u00f1o\n2 amb, balc\u00f3n, cocina, ba\u00f1o en suite. Muy luminoso. Sobre Avenida Santa Fe y Aguero. Vigilancia. Edificio con cochera. Oportunidad. 1 mes de deposito. Ver datos due\u00f1o directo\nPublicado desde ayer\nContactar", "revised": false, "rejected": true, "data": {"precio": "$ 300.000", "expensas": "$ 40.000 Expensas", "direccion": "Avenida Santa Fe 2600", "metros": "365 m\u00b2 tot.", "habitaciones": "2 amb.", "hace": "Contactar"}}, "https://www.zonaprop.com.ar/propiedades/clasificado/alclapin-alquiler-2-ambientes-almagro-apto-profesional-53573313.html": {"date": "05-05-2024\n", "content": "$ 280.000\n$ 80.000 Expensas\nSalguero y Av Corrientes\nAlmagro, Capital Federal\n50 m\u00b2 tot.\n2 amb.\n1 dorm.\nSolo uso profesional. almagro venta departamento 2 ambientes amplios, A metros de av. Corrientes. Cuenta con c\u00f3modo living comedor con ventana de doble vidrio al frente. Amplios placares. Dormitorio a la calle. Cocina semi integrada. Ba\u00f1o con ducha. Servicios individuales. Por escalera 1 piso. Ubicado en Salguero al 500 casi esquina Av. Corrientes. Apto profesional! A metros del Subte Linea B Estaci\u00f3n Medrano.\nSuper destacado\nPublicado hace 2 d\u00edas\nContactar", "revised": false, "rejected": true, "data": {"precio": "$ 280.000", "expensas": "$ 80.000 Expensas", "direccion": "Salguero y Av Corrientes", "metros": "50 m\u00b2 tot.", "habitaciones": "2 amb.", "hace": "Super destacado\nPublicado hace 2 d\u00edas"}}, "https://www.zonaprop.com.ar/propiedades/clasificado/alclapin-alquiler-departamento-2-ambientes-villa-crespo-parque-53571695.html": {"date": "05-05-2024\n", "content": "$ 300.000\n$ 50.000 Expensas\nVilla Crespo, Capital Federal\n45 m\u00b2 tot.\n2 amb.\n1 dorm.\n1 ba\u00f1o\nEn alquiler Departamento 2 ambientes en Parque Centenario. Cuenta con Comedor, dormitorio, ba\u00f1o, cocina independiente y lavadero cubierto. Lateral. Total 45m2. Aumentos trimestrales. Se solicitar\u00e1 ingresos comprobables, garant\u00eda de causi\u00f3n Finaer/ Garant\u00eda propietaria\nSuper destacado\nPublicado hace 2 d\u00edas\nContactar", "revised": true, "rejected": false, "data": {"precio": "$ 300.000", "expensas": "$ 50.000 Expensas", "direccion": "", "metros": "45 m\u00b2 tot.", "habitaciones": "2 amb.", "hace": "Super destacado\nPublicado hace 2 d\u00edas"}, "comment": "Centenario. Fr\u00edo. Grande "}, "https://www.zonaprop.com.ar/propiedades/clasificado/alclapin-excelente-depto.-2-ambientes-en-la-calle-moreno-al-53577984.html": {"date": "05-05-2024\n", "content": "$ 300.000\n$ 35.000 Expensas\nMORENO 2900\nBalvanera, Capital Federal\n31 m\u00b2 tot.\n2 amb.\n1 dorm.\n1 ba\u00f1o\nMuy lindo Departamento de 2 ambientes lateral en la calle Moreno al 2900, Balvanera. Consta del living comedor de 3. 00 x 3. 50, dormitorio con placard 3. 00 x 3. 00, cocina 3. 70 x 1. 60 y ba\u00f1o completo 1. 60 x 2. 20. Superficie total 31 m2. Muy luminoso y en buen estado. A 2 cuadras de Av Jujuy (Subte l\u00ednea H) y a 3 cuadras de Av Rivadavia (Subte l\u00ednea A) y todos los transportes. A metros de Hospital Espa\u00f1ol y a 4 cuadras de Hospital Ramos Mej\u00eda. Alberto Daniel Marincola. cuciba N\u00b0 1898. \u201cPara los casos de alquiler de vivienda el monto m\u00e1ximo que se le puede requerir a los propietarios ser\u00e1 el equivalente al cuatro con quince cent\u00e9simos por ciento (4, 15%) del valor total del respectivo contrato. Se encuentra prohibido cobrar comisiones inmobiliarias y gastos de gestoria de informes a los inquilinos en el caso de ser personas f\u00edsicas. \u201d // Importante: el aviso publicado es al mero efecto informativo y no constituye una oferta ni solicitud de oferta o compra, ni una recomendaci\u00f3n de inversi\u00f3n, y se entiende que presenta informaci\u00f3n resumida, preliminar y no definitiva de un inmueble o negocio. Si el aviso contuviera estimaciones o proyecciones, se entender\u00e1 que las mismas son solo opiniones que reflejan expectativas de buena fe. Im\u00e1genes no contractuales. Medidas aproximadas. Los montos y porcentajes son valores de referencia y pueden variar sin previo aviso.\nSuper destacado\nPublicado hace 2 d\u00edas\nContactar", "revised": true, "rejected": false, "data": {"precio": "$ 300.000", "expensas": "$ 35.000 Expensas", "direccion": "MORENO 2900", "metros": "31 m\u00b2 tot.", "habitaciones": "2 amb.", "hace": "Super destacado\nPublicado hace 2 d\u00edas"}, "comment": "Manzana 66. Est\u00e1 bien No tiene balc\u00f3n "}, "https://www.zonaprop.com.ar/propiedades/clasificado/alclapin-alquiler-2-ambientes-en-zona-de-teatros-53577825.html": {"date": "05-05-2024\n", "content": "$ 350.000\n$ 50.000 Expensas\nRodriguez Pe\u00f1a al 300\nSan Nicol\u00e1s, Capital Federal\n41 m\u00b2 tot.\n2 amb.\n1 dorm.\n1 ba\u00f1o\nAlquiler 2 ambientes a media cuadra de Av. Corrientes, zona de teatros y dem\u00e1s atracciones tur\u00edsticas. La unidad cuenta con un amplio living con balc\u00f3n franc\u00e9s, cocina separada, un ba\u00f1o completo y un dormitorio de amplias dimensiones. El edificio cuenta con encargado con vivienda en el edificio, y dos ascensores para la unidad. Esta ubicado en una zona c\u00e9ntrica de la Ciudad de Buenos Aires, con conectividad tanto de lineas de subte (Lineas A, B y C), como as\u00ed tambi\u00e9n de m\u00faltiples lineas de colectivos. Esta a pocas cuadras de los principales teatros de C. A. B. A. Las expensas son de $50. 000. La presente publicaci\u00f3n describe las caracter\u00edsticas esenciales del inmueble, debi\u00e9ndose consultar al corredor p\u00fablico inmobiliario responsable de la operaci\u00f3n por la eventual actualizaci\u00f3n de las medidas, descripciones arquitect\u00f3nicas y funcionales, valores de expensas, servicios, impuestos, precios y dem\u00e1s informaci\u00f3n, cuyos valores son aproximados. El inmueble es accesible para personas con discapacidades f\u00edsicas. grupo moldes cucicba 6694 - cmcpsi 6228C\u00f3digo de referencia de propiedad: gapVer datos\nSuper destacado\nPublicado hace 2 d\u00edas\nContactar", "revised": true, "rejected": true, "data": {"precio": "$ 350.000", "expensas": "$ 50.000 Expensas", "direccion": "Rodriguez Pe\u00f1a al 300", "metros": "41 m\u00b2 tot.", "habitaciones": "2 amb.", "hace": "Super destacado\nPublicado hace 2 d\u00edas"}, "comment": "Me parece caro"}, "https://www.zonaprop.com.ar/propiedades/clasificado/alclapin-2-amb-en-alquiler-villa-crespo-53573901.html": {"date": "05-05-2024\n", "content": "$ 300.000\n$ 29.300 Expensas\nav corrientes 4664\nVilla Crespo, Capital Federal\n51 m\u00b2 tot.\n2 amb.\n1 dorm.\n1 ba\u00f1o\nAmplio departamento de dos ambientes con dependencia. Balc\u00f3n al frente, todo luz. Cocina con lavadero independiente. Ba\u00f1o con ducha. El edificio se encuentra sobre Av. Corrientes, a una cuadra de \u00c1ngel Gallardo (Estaci\u00f3n Angel Gallardo de la linea B de subtes), pr\u00f3ximo al Parque Centenario. Martillero responsable: nicolas ortiz. Matr\u00edcula cucicba 6337. brokerin servicios inmobiliarios. Conforme la ley 5115 de accesibilidad el inmueble posee acceso para personas con movilidad reducida. Aceptamos garant\u00eda respaldar: -aprobado-express-sin-cargo? i=7fe1f8abaad094e0b5cb1b01d712f708&h=5c86e2d4656c14a3011f3d60b262c35c\nDestacado\nPublicado hace 2 d\u00edas\nContactar", "revised": false, "rejected": true, "data": {"precio": "$ 300.000", "expensas": "$ 29.300 Expensas", "direccion": "av corrientes 4664", "metros": "51 m\u00b2 tot.", "habitaciones": "2 amb.", "hace": "Destacado\nPublicado hace 2 d\u00edas"}}, "https://www.zonaprop.com.ar/propiedades/clasificado/alclapin-departamento-2-ambientes-apto-profesional-53573862.html": {"date": "05-05-2024\n", "content": "$ 300.000\n$ 21.700 Expensas\nACEVEDO 0\nVilla Crespo, Capital Federal\n36 m\u00b2 tot.\n2 amb.\n1 dorm.\n1 ba\u00f1o\nDepartamento 2 ambientes - apto profesional - living comedor - dormitorio con placard - cocina Y ba\u00f1o completo - lavadero independiente - pisos de parquet - excelente ubicaci\u00f3n. david peijovich propiedades Ver datos. C. U. C. I. C. B. A. Matr\u00edcula N\u00ba 5078. \"Para los casos de alquiler de vivienda, el monto m\u00e1ximo de comisi\u00f3n que se le puede requerir a los propietarios ser\u00e1 el equivalente al cuatro con quince cent\u00e9simos por ciento (4, 15%) del valor total del respectivo contrato. Se encuentra prohibido cobrar a los inquilinos que sean personas f\u00edsicas comisiones inmobiliarias y gastos de gestor\u00eda de informes\". Inmueble no accesible para personas con discapacidad f\u00edsica ley 5115.\nDestacado\nPublicado hace 2 d\u00edas\nContactar", "revised": true, "rejected": true, "data": {"precio": "$ 300.000", "expensas": "$ 21.700 Expensas", "direccion": "ACEVEDO 0", "metros": "36 m\u00b2 tot.", "habitaciones": "2 amb.", "hace": "Destacado\nPublicado hace 2 d\u00edas"}, "comment": "No me cabe la zona"}, "https://www.zonaprop.com.ar/propiedades/clasificado/alclapin-departamento-en-alquiler-2amb-en-monserrat-53578361.html": {"date": "05-05-2024\n", "content": "$ 250.000\n$ 20.000 Expensas\nVirrey Cevallos 500\nMonserrat, Capital Federal\n40 m\u00b2 tot.\n2 amb.\n1 dorm.\n1 ba\u00f1o\nDepartamento de dos ambientes, buen ingreso de luz natural y ventilaci\u00f3n. Piso parquet en buen estado, cocina c\u00f3moda con mesada de granito y ba\u00f1o con ba\u00f1era. Disposici\u00f3n lateral. Cercano a universidad uade y restaurantes t\u00edpicos de comida regional espa\u00f1ola e italiana. Transportes Cercanos: Colectivos: 2, 6, 8, 12, 23, 37, 50, 56, 57, 60, 84, 86, 90, 96, 98, 102, 103, 150, 151, 168Datos \u00fatilesBarrio: MonserratComuna: Comuna 1\u00c1rea Hospitalaria: htal. Dr. J. M. Ramos mej\u00edadistrito Escolar: Distrito Escolar iiic\u00f3digo Postal: 1100C\u00f3digo Postal Argentino: C1100accvremont R. Barral e HijosMatriculado responsable: Roberto Barral matr\u00edcula N\u00ba3006 cucicba. ? En el cumplimiento de la ley nacional 25. 028, ley 22. 802 de lealtad comercial. ? Ley 24. 240 de defensa al consumidor, las normas del c\u00f3digo civil y comercial de la naci\u00f3n y constitucionales. Los agentes no ejercen el corretaje inmobiliario. ? Ley 5859 -Art. 4: \"Para los casos de alquiler de vivienda, el monto m\u00e1ximo de comisi\u00f3n que se le puede requerir a los propietarios ser\u00e1 el equivalente al cuatro con quince cent\u00e9simos por ciento (4, 15%) del valor total del contrato. Se encuentra prohibido cobrar a los inquilinos que sean personas f\u00edsicas comisiones inmobiliarias y gastos de gestor\u00eda de informes\". (En caso de ser alquiler) ? Ley 5115 \u2013 Art. 1: El inmueble publicado no es accesible para personas con capacidades f\u00edsicas reducidas. (En caso de no ser accesible) ? Se deja constancia que las medidas, superficies y m2 consignados son aproximados, sujetos a verificaci\u00f3n y/o ajuste. El precio del inmueble puede ser modificado sin previo aviso.\nDestacado\nPublicado hace 2 d\u00edas\nContactar", "revised": true, "rejected": true, "data": {"precio": "$ 250.000", "expensas": "$ 20.000 Expensas", "direccion": "Virrey Cevallos 500", "metros": "40 m\u00b2 tot.", "habitaciones": "2 amb.", "hace": "Contactar"}, "comment": "Chernobyl "}, "https://www.zonaprop.com.ar/propiedades/clasificado/alclapin-alquiler-2-ambientes-amplio-balcon-luz-balvanera-53572273.html": {"date": "05-05-2024\n", "content": "$ 300.000\n$ 70.000 Expensas\nAv. Belgrano 1600\nMonserrat, Capital Federal\n71 m\u00b2 tot.\n2 amb.\n1 dorm.\n1 ba\u00f1o\nCorredor Responsable: Ariel Champanier cucicba 4330 / Andrea Berr\u00e9 cmcpsi 6763- Contacto: Damian Ferrari Halliday - mls id # Ver datos. C\u00f3modo alquiler de 2 ambientes de amplio metraje (71m2 por escritura) con balc\u00f3n al frente, en Monserrat casi Balvanera (a pasos de Av. Entre R\u00edos). A su vez: a 500 metros de Av. 9 de Julio y cercano a subtes y cantidad de otros medios de transporte. Unidad y edificio de categor\u00eda, con ba\u00f1o completo y toilette. Metraje generoso. Gran potencial para refaccionar. Edificio de porte, muy bien mantenido. * ver video: ve3bVyPjlCc. La unidad cuenta cuenta con un gran balc\u00f3n al frente y tiene muy buena luminosidad. El edificio es tradicional, de excelente calidad constructiva, con 2 ascensores. La cocina es completa, con lavadero anexo con conexi\u00f3n para lavarropas, y toilette de recepci\u00f3n. Desde la cocina hay una doble circulaci\u00f3n hacia el corredor o living comedor. Los servicios son individuales a trav\u00e9s de termotanque. El living comedor es muy amplio con espacio inclusive, para escritorio, con un hermoso parquet. La habitaci\u00f3n es generosa en sus dimensiones, con cantidad de espacio de guardado y balc\u00f3n cubierto como plus de metraje funcional. El ba\u00f1o tambi\u00e9n es c\u00f3modo, con ventilaci\u00f3n al pulm\u00f3n del edificio y ba\u00f1era. Condiciones: Alquiler por 2 a\u00f1os para el que se requiere seguro de cauci\u00f3n / Ingresos Comprobables / 1 Mes de dep\u00f3sito + 1 Mes de alquiler adelantado. \u201cEn cumplimiento de la Ley 2340 cucicba, Ley 10. 973 de la Prov. Bs. As. , Ley Nacional 25. 028, Ley 22. 802 de Lealtad Comercial, Ley 24. 240 de Defensa al Consumidor, las normas del C\u00f3digo Civil y Comercial de la Naci\u00f3n y Constitucionales, los agentes no ejercen el corretaje inmobiliario. Todas las operaciones inmobiliarias son objeto de intermediaci\u00f3n y conclusi\u00f3n por parte de los martilleros y corredores colegiados, cuyos datos se exhiben debajo del nombre de la inmobiliaria. \u201d *Medidas, caracter\u00edsticas y gastos aproximados, mencionados como referencia. \"El presente inmueble no es accesible para personas con discapacidades f\u00edsicas\u201d * Accede a un prestamo por hasta el 30% del valor de esta propiedad. Simula tu cuota en Lendar* Remax Argentina S. R. L. No ejerce el corretaje inmobiliario. El presente sitio web es una plataforma en donde cada oficina inmobiliaria independiente que contrata los servicios re/max puede publicar las propiedades a su cargo. Cada oficina es de propiedad y gesti\u00f3n independiente, por lo que Remax Argentina S. R. L no interviene en los datos de la publicaci\u00f3n, en la operaci\u00f3n inmobiliaria, ni en la confecci\u00f3n y/o firma del boleto de compraventa y/o escritura y/o contrato de alquiler. En cumplimiento de las leyes vigentes que regulan el corretaje inmobiliario, Ley Nacional 25. 028, Ley 22. 802 de Lealtad Comercial, Ley 24. 240 de Defensa al Consumidor, las normas del C\u00f3digo Civil y Comercial de la Naci\u00f3n y Constitucionales, los agentes/gestores no ejercen el corretaje inmobiliario. Todas las operaciones inmobiliarias son objeto de intermediaci\u00f3n y conclusi\u00f3n por parte del corredor p\u00fablico inmobiliario colegiado a cargo de la publicaci\u00f3n, cuyos datos se exhiben en la presente. La presente publicaci\u00f3n describe las caracter\u00edsticas esenciales del inmueble, debi\u00e9ndose consultar al corredor p\u00fablico inmobiliario responsable de la operaci\u00f3n por la eventual actualizaci\u00f3n de las medidas, descripciones arquitect\u00f3nicas y funcionales, valores de expensas, servicios, impuestos, precios y dem\u00e1s informaci\u00f3n, cuyos valores son aproximados. Para los casos de alquiler de vivienda, el monto m\u00e1ximo de comisi\u00f3n que se le puede requerir a los propietarios ser\u00e1 el equivalente al cuatro con quince cent\u00e9simos por ciento (4, 15%) del valor total del respectivo contrato. Se encuentra prohibido cobrar a los inquilinos que sean personas f\u00edsicas comisiones inmobiliarias y gastos de gestor\u00eda de informes. El inmueble no es accesible para personas con discapacidades f\u00edsicas.\nPublicado hace 2 d\u00edas\nContactar", "revised": true, "rejected": false, "data": {"precio": "$ 300.000", "expensas": "$ 70.000 Expensas", "direccion": "Av. Belgrano 1600", "metros": "71 m\u00b2 tot.", "habitaciones": "2 amb.", "hace": "Publicado hace 2 d\u00edas"}, "comment": "Grande. Fiero no tan feo. Vintage "}, "https://www.zonaprop.com.ar/propiedades/clasificado/alclapin-departamento-en-almagro-53572237.html": {"date": "05-05-2024\n", "content": "$ 300.000\n$ 40.000 Expensas\nAcu\u00f1a de Figueroa al 300\nAlmagro, Capital Federal\n40 m\u00b2 tot.\n2 amb.\n1 dorm.\n1 ba\u00f1o\nEste hermoso departamento de dos ambientes ofrece una atm\u00f3sfera luminosa y acogedora, con una distribuci\u00f3n que aprovecha al m\u00e1ximo el espacio disponible. Ubicado en una zona privilegiada, a solo una cuadra de la transitada avenida Medrano, ofrece una excelente conexi\u00f3n con una variedad de medios de transporte p\u00fablico. Al ingresar, te recibe un living comedor, de dimensiones generosas, mide alrededor de 4 metros de ancho por 3 metros de largo. Este espacio se caracteriza por su luminosidad y su accesibilidad al balc\u00f3n, ofreciendo mucha luz y vista abierta. Luego tenemos una cocina independiente de aproximadamente 3 metros de ancho por 2. 50 metros de largo, que adem\u00e1s cuenta con un pr\u00e1ctico lavadero incorporado, lo que garantiza comodidad y funcionalidad en cada tarea dom\u00e9stica. Desde aqu\u00ed, puedes disfrutar de una vista al exterior que asegura una agradable iluminaci\u00f3n natural. El dormitorio principal, ubicado al frente al igual que el resto del departamento, cuenta con unas amplias dimensiones de aproximadamente 4 metros de ancho por 3. 50 metros de largo. Adem\u00e1s, incluye un espacioso placard que brinda una soluci\u00f3n de almacenamiento conveniente y organizada. El ba\u00f1o completo, equipado con ba\u00f1era, nos ofrece un espacio funcional y confortableEn resumen, este departamento combina comodidad, luminosidad y una ubicaci\u00f3n privilegiada, lo que lo convierte en una excelente opci\u00f3n para aquellos que buscan un lugar para vivir. **Corredor Inmobiliario Responsable Adrian Ridelnik cucicba Mat 197. *Se deja constancia que las medidas y superficies indicados son aproximados y al s\u00f3lo efecto orientativo. Las medidas reales surgir\u00e1n del t\u00edtulo de propiedad respectivo. Las medidas parciales y/o de los ambientes y el valor consignado de expensas mensuales, servicios y abl est\u00e1 sujeto a verificaci\u00f3n y/o ajuste. Art. 4 de la Ley 5. 859 de C. A. B. A \"Para los casos de alquiler de vivienda \u00fanica, el monto m\u00e1ximo de comisi\u00f3n que se le puede requerir a los propietarios ser\u00e1 el equivalente al cuatro con quince cent\u00e9simos por ciento (4, 15%) del valor total del respectivo contrato. Se encuentra prohibido cobrar a los inquilinos que sean personas f\u00edsicas comisiones inmobiliarias cuando el destino sea vivienda \u00fanica y permanente \". -\nPublicado hace 2 d\u00edas\nContactar", "revised": true, "rejected": false, "data": {"precio": "$ 300.000", "expensas": "$ 40.000 Expensas", "direccion": "Acu\u00f1a de Figueroa al 300", "metros": "40 m\u00b2 tot.", "habitaciones": "2 amb.", "hace": "Publicado hace 2 d\u00edas"}, "comment": "Plaza Almagro. Grande y luminoso "}, "https://www.zonaprop.com.ar/propiedades/clasificado/alclapin-departamento-en-alquiler-san-nicolas-53573546.html": {"date": "05-05-2024\n", "content": "$ 320.000\n$ 52.000 Expensas\nTucuman al 1700\nSan Nicol\u00e1s, Capital Federal\n37 m\u00b2 tot.\n2 amb.\n1 dorm.\n1 ba\u00f1o\nDepartamento en alquiler en San Nicolas! A metros de Avenida Callao2 Ambientes al frentePiso de parquet plastificadoAire acondicionado frio/calorCocina separadanota: Se deja constancia que los metros parciales, as\u00ed como el monto de las expensas e impuestos son aproximados a t\u00edtulo orientativo sujetos a verificaci\u00f3n y/o ajustes. cucicba N\u00ba 2996\nPublicado hace 2 d\u00edas\nContactar", "revised": true, "rejected": true, "data": {"precio": "$ 320.000", "expensas": "$ 52.000 Expensas", "direccion": "Tucuman al 1700", "metros": "37 m\u00b2 tot.", "habitaciones": "2 amb.", "hace": "Publicado hace 2 d\u00edas"}, "comment": "Caro y zona fea "}, "https://www.zonaprop.com.ar/propiedades/clasificado/alclapin-departamento-en-venta-almagro-2-ambientes-53577658.html": {"date": "05-05-2024\n", "content": "8\n$ 260.000\n$ 30.000 Expensas\nYatay 700\nAlmagro, Capital Federal\n35 m\u00b2 tot.\n2 amb.\n1 dorm.\n1 ba\u00f1o\nDepartamento en alquiler almagro 2 ambientes luminoso. Tasaciones sin compromiso efurio. Luminoso Departamento 2 ambientes en excelente estado! Departamento con pisos de parquet. Living-comedor, cocina y lavadero separado, dormitorio con placard empotrado, ba\u00f1o con ba\u00f1adera. Excelente ubicaci\u00f3n, a pasos de la Av. Corrientes con m\u00faltiples medios de transporte y a dos cuadras del subte linea B, estaci\u00f3n \u00c1ngel GallardoNo apto para personas con movilidad reducida-Se deja constancia que las medidas y superficies indicados son aproximados y al s\u00f3lo efecto orientativo. Las medidas reales surgir\u00e1n del t\u00edtulo de propiedad respectivo. Las medidas parciales y/o de los ambientes y el valor consignado de expensas mensuales est\u00e1 sujeto a verificaci\u00f3n y/o ajuste. Fotos de car\u00e1cter no contractual. El precio del inmueble puede ser modificado sin previo aviso. Venta sujeta al pedido del coti por parte del propietario, si corresponde. \"e-furio S. R. L. \" Bienes y Servicios Inmobiliarios Enrique D. Furio C. U. C. I. C. B. A Mat. N 439\nPublicado hace 2 d\u00edas\nContactar", "revised": true, "rejected": false, "data": {"precio": "$ 260.000", "expensas": "$ 30.000 Expensas", "direccion": "Yatay 700", "metros": "35 m\u00b2 tot.", "habitaciones": "2 amb.", "hace": "Publicado hace 2 d\u00edas"}, "comment": "Bien. Chico y barato . Poca luz "}, "https://www.zonaprop.com.ar/propiedades/clasificado/alclapin-departamento-en-alquiler-2-ambientes-balvanera.-53576157.html": {"date": "05-05-2024\n", "content": "$ 300.000\n$ 60.000 Expensas\nAvenida Belgrano al 2600\nBalvanera, Capital Federal\n36 m\u00b2 tot.\n2 amb.\n1 dorm.\n1 ba\u00f1o\nDepartamento en Alquiler en Balvanera-Avda. Belgrano y Saavedra. 8 piso. Muy luminoso. Balc\u00f3n al frente. Requisitos: Garante propietario en caba o Seguro de Cauci\u00f3n. 1 mes de dep\u00f3sitoContrato por dos a\u00f1os. Ajustes trimestrales por ipc.\nPublicado hace 2 d\u00edas\nContactar", "revised": false, "rejected": true, "data": {"precio": "$ 300.000", "expensas": "$ 60.000 Expensas", "direccion": "Avenida Belgrano al 2600", "metros": "36 m\u00b2 tot.", "habitaciones": "2 amb.", "hace": "Publicado hace 2 d\u00edas"}}, "https://www.zonaprop.com.ar/propiedades/clasificado/alclapin-muy-lindo-2-ambientes-con-cochera-al-frente-con-53577007.html": {"date": "05-05-2024\n", "content": "$ 350.000\n$ 57.000 Expensas\nIndependencia 3150\nSan Cristobal, Capital Federal\n48 m\u00b2 tot.\n2 amb.\n1 dorm.\n1 ba\u00f1o\n1 coch.\nExcelente Departamentos de 2 ambientes con Cochera (48 m2 Totales) . Muy bien ubicado en plena Av Independencia con acceso a toda la Ciudad muy r\u00e1pidamente entre las calles 24 de Noviembre y Urquiza. Cocina amplia y c\u00f3moda. LivingComedor y el resto del depto esta reci\u00e9n pintado. Ba\u00f1o Completo. Pisos de parquet de pinotea en living, Habitaci\u00f3n y cer\u00e1mico en cocina. Calef\u00f3n a botonera. El edificio est\u00e1 dividido en 2 cuerpos. Departamento super tranquilo al frente. Todos los medios de transporte al alcance (Subtes cerca y l\u00edneas de colectivos 7, 23, 31, 32, 41, 53, 56, 75, 84, 88, 96, 97, 98, 101, 126, 127, 129) . Encargado tiempo completo. Unidad en muy buen estado. Expensas: $ 57. 000 por mes. No se aceptan mascotas. Grupo Gaona Operadores Inmobiliarios Tel Ver datos. Para los casos de alquiler de vivienda, el monto m\u00e1ximo de comisi\u00f3n que se le puede requerir a los propietarios ser\u00e1 el equivalente al cuatro con quince cent\u00e9simos por ciento (4, 15%) del valor total del respectivo contrato. Se encuentra prohibido cobrar a los inquilinos que sean personas f\u00edsicas, comisiones inmobiliarias y gastos de gestor\u00eda de informes. Cucicba mat 4113.\nPublicado hace 2 d\u00edas\nContactar", "revised": false, "rejected": true, "data": {"precio": "$ 350.000", "expensas": "$ 57.000 Expensas", "direccion": "Independencia 3150", "metros": "48 m\u00b2 tot.", "habitaciones": "2 amb.", "hace": "Publicado hace 2 d\u00edas"}}, "https://www.zonaprop.com.ar/propiedades/clasificado/alclphin-2amb-frente-balcon-bajas-exp-50-m-53577781.html": {"date": "05-05-2024\n", "content": "$ 270.000\n$ 17.000 Expensas\nLas Casas 3600\nBoedo, Capital Federal\n51 m\u00b2 tot.\n2 amb.\n1 dorm.\n1 ba\u00f1o\n2ambiente al frente con balcon corrido 50mts cuadrados 2do piso por escalera. Gran living comedor con cocina integrada ( con gas) mueble bajo mesada y lacena, estufa tiro balanceado. Dormitorio con placard de 3, 9x3, 8mts. ba\u00f1o completo con ba\u00f1era, balcon corrido al frente. Bajas expensas, a 20mts Av. Boedo. *se entrega recien pintado*\nPublicado hace 2 d\u00edas\nContactar", "revised": true, "rejected": false, "data": {"precio": "$ 270.000", "expensas": "$ 17.000 Expensas", "direccion": "Las Casas 3600", "metros": "51 m\u00b2 tot.", "habitaciones": "2 amb.", "hace": "Publicado hace 2 d\u00edas"}, "comment": "Fiero. Grande. Parque patricios "}, "https://www.zonaprop.com.ar/propiedades/clasificado/alclapin-alquiler-2-ambientes-billinghurst-2100-barrio-53574469.html": {"date": "05-05-2024\n", "content": "$ 350.000\n$ 58.000 Expensas\nBillinghurst al 2100\nBarrio Norte, Capital Federal\n36 m\u00b2 tot.\n2 amb.\n1 dorm.\n1 ba\u00f1o\nDepartamento dos ambientes en alquiler. Tercer piso. Interno. Cocina separada, espacio lavadero, living comedor, ba\u00f1o completo y dormitorio con placard. Agua caliente individual por calef\u00f3n. Gas natural. Aire acondicionado frio/calor. Edificio con seguridad. Para ingresar: 1 mes de adelanto, 1 mes de deposito. Garant\u00eda propietaria y justificaci\u00f3n de ingresos tanto inquilino como garante. Contrato por 24 meses con ajustes trimestrales por ipc. -\"En cumplimiento de la Ley 10. 973 de la Provincia de Buenos Aires, Ley Nacional 25. 028, Ley Nacional 20. 266, Ley 22. 802 de Lealtad Comercial, Ley 24. 240 de Defensa al Consumidor, las normas del C\u00f3digo Civil y Comercial de la Naci\u00f3n y Constitucionales, los asesores no ejercen el corretaje inmobiliario. \"Ley 5115: \"excepto que en la descripci\u00f3n de la propiedad se indique lo contrario, el edificio puede no contar con rampa para personas con movilidad reducida, y no ser Accesible para personas con discapacidades f\u00edsicas. \"En cumplimiento de la Ley 5859, Art. 4\u00b0, se deja constancia que \u201cPara los casos de alquiler de vivienda, el monto m\u00e1ximo de comisi\u00f3n que se le puede requerir a los propietarios ser\u00e1 el equivalente al cuatro con quince cent\u00e9simos porciento (4, 15%) del valor total del respectivo contrato. Se encuentra prohibido cobrar a los inquilinos que sean personas f\u00edsicas comisiones inmobiliarias y gastos de gestor\u00eda de informes\u201d. -\"Las superficies y medidas expresadas son aproximadas y se exponen al solo efecto orientativo, las definitivas surgen de la escritura y/o planos aprobados de la propiedad. Las medidas son orientativas, las reales surgen del titulo de propiedad. Las expensas pueden sufrir variaciones. Las im\u00e1genes son ilustrativas. La presenta oferta de venta esta condicionada a la obtenci\u00f3n del coti por parte del propietario (resol afip 2371). \"cpi 6084 / cmcpsi 6264 Devia Inmuebles\nPublicado hace 2 d\u00edas\nContactar", "revised": false, "rejected": true, "data": {"precio": "$ 350.000", "expensas": "$ 58.000 Expensas", "direccion": "Billinghurst al 2100", "metros": "36 m\u00b2 tot.", "habitaciones": "2 amb.", "hace": "Publicado hace 2 d\u00edas"}}, "https://www.zonaprop.com.ar/propiedades/clasificado/alclapin-2amb-en-pleno-villa-crespo!-53576088.html": {"date": "05-05-2024\n", "content": "$ 350.000\nFRIAS, EUSTOQUIO 400. Entre Aguirre\nVilla Crespo, Capital Federal\n45 m\u00b2 tot.\n2 amb.\n1 dorm.\n1 ba\u00f1o\nAlquiler de Departamento 2 ambientes en pleno Villa Crespo a metros de Parque Centenario, rodeada de numerosos locales comerciales, bares, restaurantes y medios de transporte como subte y colectivo. El departamento cuenta con living comedor, ba\u00f1o completo renovado, lavadero y cocina separada del ambiente. Cuenta con aire acondicionado! Condiciones: -1 mes de renta. -1 mes de deposito reembolsable. -dni + comprobante de ingreso. -Garantia en caba o seguro de caucion. -precio actualizado trimestralmente por ipcxintel(mdt-mdt-1864)\nPublicado hace 2 d\u00edas\nContactar", "revised": false, "rejected": true, "data": {"precio": "$ 350.000", "direccion": "FRIAS, EUSTOQUIO 400. Entre Aguirre", "metros": "45 m\u00b2 tot.", "habitaciones": "2 amb.", "hace": "Publicado hace 2 d\u00edas"}}, "https://www.zonaprop.com.ar/propiedades/clasificado/alclapin-2-ambientes-amplio-al-contrafrente-53573027.html": {"date": "05-05-2024\n", "content": "$ 290.000\n$ 40.000 Expensas\nMoreno 1800 3\u00b0\nCongreso, Capital Federal\n43 m\u00b2 tot.\n2 amb.\n1 dorm.\n1 ba\u00f1o\n2 ambientes en tercer piso al contrafrente. Lavadero independiente. Pisos de parquet. Amplios pacares. Optimo estado. Proximo A avenidas entre rios, rivadavia Y belgrano. Servicios: Electricidad, Pavimento, Cloacas, Gas, Agua Corriente. plazo de contrato 24 meses. Ajustes trimestrales conforme indice de precios al consumidor. Damian garcia duscio cpi matricula 56 Se deja constancia que los m2 son aproximados, al igual que las medidas parciales y el valor consignado de las expensas mensuales (en caso que corresponda pago de expensas) est\u00e1n sujetos a verificaci\u00f3n y/o ajustes, el precio del inmueble puede ser modificado sin previo aviso. Fotos de car\u00e1cter no contractual. Las unidades publicadas est\u00e1n sujetas a disponibilidad. Inmueble no accesible para personas con discapacidad f\u00edsica ley 5115. \u201cPara los casos de alquiler de vivienda ubicada en C. A. B. A. , el monto m\u00e1ximo de comisi\u00f3n que se le puede requerir a los propietarios ser\u00e1 el equivalente al cuatro con quince cent\u00e9simos por ciento (4, 15%) del valor del respectivo contrato. Se encuentra prohibido cobrar comisiones inmobiliarias y gastos de gestor\u00eda de informes a los inquilinos, en el caso de ser personas f\u00edsicas\u201d. -\nPublicado hace 2 d\u00edas\nContactar", "revised": false, "rejected": true, "data": {"precio": "$ 290.000", "expensas": "$ 40.000 Expensas", "direccion": "Moreno 1800 3\u00b0", "metros": "43 m\u00b2 tot.", "habitaciones": "2 amb.", "hace": "Publicado hace 2 d\u00edas"}}, "https://www.zonaprop.com.ar/propiedades/clasificado/alclphpa-almagro-dueno-directo-alquila-2-ambientes-53572774.html": {"date": "05-05-2024\n", "content": "$ 300.000\n$ 42.000 Expensas\nBulnes 945\nAlmagro, Capital Federal\n45 m\u00b2 tot.\n2 amb.\n1 dorm.\n1 ba\u00f1o\nDue\u00f1o directo- 300. 000 $ m\u00e1s servicios y expensasVer datos. pta baja con patio - 2 ambientes - ba\u00f1o y cocina completos. cerca de universidad de palermo. hospital italiano. estacion medrano - subte B. requisitos: recibo de sueldo - garant\u00eda propietaria caba- 1 mes de adelanto. 1 mes de deposito. mi whatsapp 11 Ver datos\nPublicado hace 2 d\u00edas\nContactar", "revised": false, "rejected": true, "data": {"precio": "$ 300.000", "expensas": "$ 42.000 Expensas", "direccion": "Bulnes 945", "metros": "45 m\u00b2 tot.", "habitaciones": "2 amb.", "hace": "Contactar"}}, "https://www.zonaprop.com.ar/propiedades/clasificado/alclappa-dueno-alquila-dpto-2-amb-53572902.html": {"date": "05-05-2024\n", "content": "$ 320.000\n$ 21.000 Expensas\nAv. D\u00edaz V\u00e9lez 4000\nAlmagro Norte, Almagro\n30 m\u00b2 tot.\n2 amb.\n1 dorm.\n1 ba\u00f1o\nDue\u00f1o alquila dpto dos ambientes, reci\u00e9n pintado, piso de parquet reci\u00e9n pulido y plastificado, en dormitorio placard empotrado, estufa tiro balanceado, cocina separada completa, muebles bajo y sobre mesada, Ba\u00f1o en suite completo con ba\u00f1era, conexi\u00f3n para lavarropas. Aa fr\u00edo/calor a colocar. 2 ascensores con bajas expensas (no incluyen aysa). Excelente ubicaci\u00f3n, a dos cdas Hosp. Italiano, 3 cdas Av. Rivadavia Subte A y 4 cdas Av. Corrientes subte B, 6 cdas de Pque Centenario m\u00faltiples l\u00edneas de colectivos. Capacidad maxi 2 personas adultas, Requisitos: Recibo de sueldo y/o comprob ingresos. Garant\u00eda familiar de capital o seguro de cauci\u00f3n que cubra todos las obligaciones del contrato o dos garantes con recibo de sueldo, deposito: 1 mes y medio, 1 adelantado. No Mascotas. Nota: Se deja constancia que los metros parciales as\u00ed como el monto de las expensas e. impuestos son aproximados, a t\u00edtulo informativo sujetos a verificaci\u00f3n y/o ajustes.\nPublicado hace 2 d\u00edas\nContactar", "revised": false, "rejected": true, "data": {"precio": "$ 320.000", "expensas": "$ 21.000 Expensas", "direccion": "Av. D\u00edaz V\u00e9lez 4000", "metros": "30 m\u00b2 tot.", "habitaciones": "2 amb.", "hace": "Contactar"}}, "https://www.zonaprop.com.ar/propiedades/clasificado/alclapin-suipacha-y-av-cordoba-alquiler-residencial-o-apto-53566187.html": {"date": "05-05-2024\n", "content": "$ 350.000\n$ 60.000 Expensas\nSuipacha al 700\nSan Nicol\u00e1s, Capital Federal\n45 m\u00b2 tot.\n2 amb.\n1 dorm.\n1 ba\u00f1o\nSuipacha y Av. CordobaExcelente ubicaci\u00f3n, cercano a Plaza San Martin, retiro, Galerias Pacifico. Pr\u00f3ximo a muchas lineas de colectivo y subteEdificio con seguridad 24 hsApto profesional2 ambientesInternoCocinaLiving/ comedor con aire acondicionado frio calorBa\u00f1o con ba\u00f1eraDormitorio con ventilador y amplio placardAmbos ambientes son internos no tiene balc\u00f3n. Opcion alquiler equipado y amoblado como se muestra en la foto (consultar valor) Consultar requisitos Las medidas son aproximadas, las reales surgir\u00e1n de la corespondiente documentaci\u00f3n.\nSuper destacado\nPublicado hace 3 d\u00edas\nContactar", "revised": false, "rejected": true, "data": {"precio": "$ 350.000", "expensas": "$ 60.000 Expensas", "direccion": "Suipacha al 700", "metros": "45 m\u00b2 tot.", "habitaciones": "2 amb.", "hace": "Super destacado\nPublicado hace 3 d\u00edas"}}, "https://www.zonaprop.com.ar/propiedades/clasificado/alclapin-2-ambientes-super-luminosos-y-soleados-53566669.html": {"date": "05-05-2024\n", "content": "$ 270.000\n$ 42.000 Expensas\nVilla Crespo, Capital Federal\n35 m\u00b2 tot.\n2 amb.\n1 dorm.\n1 ba\u00f1o\nDepartamento super funcional. Muy comodo. Dormitorio con amplio placard. Ba\u00f1o y cocina completos. Living comedor con Balcon frances. Excelente ubicacion. Varios medios de transporte. Se deja expresamente aclarado que las medidas son orientativas, las reales surgir\u00e1n del t\u00edtulo de propiedad respectivo y que el valor de las expensas queda sujeto a verificaci\u00f3n y/o ajustes. - Fotos de car\u00e1cter no contractual. - Requisitos del propietario. - Demostraci\u00f3n de ingresos. - Ajuste trimestral por ipc\nDestacado\nPublicado hace 3 d\u00edas\nContactar", "revised": true, "rejected": false, "data": {"precio": "$ 270.000", "expensas": "$ 42.000 Expensas", "direccion": "", "metros": "35 m\u00b2 tot.", "habitaciones": "2 amb.", "hace": "Destacado\nPublicado hace 3 d\u00edas"}, "comment": "Alfombra. Villa crespo "}, "https://www.zonaprop.com.ar/propiedades/clasificado/alclocin-suipacha-y-av-cordoba-alquiler-apto-profesional-2-53566497.html": {"date": "05-05-2024\n", "content": "$ 350.000\n$ 60.000 Expensas\nSuipacha al 700\nSan Nicol\u00e1s, Capital Federal\n45 m\u00b2 tot.\n2 amb.\n1 dorm.\n1 ba\u00f1o\nSuipacha y Av. CordobaExcelente ubicaci\u00f3n, cercano a Plaza San Martin, retiro, Galerias Pacifico. Proximo a muchas lineas de colectivo y subteEdificio con segurisad 24 hsApto profesional2 ambientesInternoCocinaLiving/ comedor con aire acondicionado frio calorBa\u00f1o con ba\u00f1eraDormitorio con ventilador y amplio placardAmbos ambientes son internos no tiene balc\u00f3n. Consultar requisitos Las medidas son aproximadas, las reales surgir\u00e1n de la corespondiente documentaci\u00f3n.\nDestacado\nPublicado hace 3 d\u00edas\nContactar", "revised": false, "rejected": true, "data": {"precio": "$ 350.000", "expensas": "$ 60.000 Expensas", "direccion": "Suipacha al 700", "metros": "45 m\u00b2 tot.", "habitaciones": "2 amb.", "hace": "Destacado\nPublicado hace 3 d\u00edas"}}, "https://www.zonaprop.com.ar/propiedades/clasificado/alclapin-departamento-balvanera-53566812.html": {"date": "05-05-2024\n", "content": "$ 280.000\n$ 38.000 Expensas\nCatamarca al 200\nBalvanera, Capital Federal\n54 m\u00b2 tot.\n2 amb.\n1 dorm.\n1 ba\u00f1o\nDepartamento de 2 ambientes en alquilerAlquiler $280. 000. -Expensas $38. 000. -Depto ubicado en un sexto piso, interno. Recien pintado. Totalmente electrico. Al ingresar lo hacermos al comedor diarios, que nos coneta directamente con la cocina independiente y el lavadero. Desde el comedor tambien accedemos a la abitacion principal con placar y desde la misma tambien al ba\u00f1o comoleto con ba\u00f1era. Requisitos: - Contar con ingresos comprobables- Mes de adelanto- Mes de deposito- Seguro de cacucion o garantia propietaria- Contrato a 2 a\u00f1os con ajustes cuatrimestrales segun ipcLas medidas de este inmueble son aproximadas. Las definitivas surgir\u00e1n del t\u00edtulo de propiedad. Corredores Inmobiliarios Matriculados: Cristian Guirin cpi 6042Diego Lo Nigro csm 2708 - cpi 7530\nPublicado hace 3 d\u00edas\nContactar", "revised": false, "rejected": true, "data": {"precio": "$ 280.000", "expensas": "$ 38.000 Expensas", "direccion": "Catamarca al 200", "metros": "54 m\u00b2 tot.", "habitaciones": "2 amb.", "hace": "Publicado hace 3 d\u00edas"}}, "https://www.zonaprop.com.ar/propiedades/clasificado/alclapin-almagro-2amb-don-bosco-al-2800-super-luminosos-53563708.html": {"date": "05-05-2024\n", "content": "$ 330.000\n$ 38.000 Expensas\nDON BOSCO 2880 7\u00b0 E\nVilla Crespo, Capital Federal\n45 m\u00b2 tot.\n2 amb.\n1 dorm.\n1 ba\u00f1o\n2 lindos ambientes en el barrio de almagro - super luminosos - cocina completa - excelente edificio - expensas bajas. Requisitos de alquiler: demostraci\u00f3n de ingresos que dupliquen valor alquiler y garant\u00eda propietaria o Fianza Finaer. Cont\u00e1ctanos hoy mismo por whatsapp al 11 Ver datos - ** para m\u00e1s detalles y programar una visita. inmobiliaria santana consulting group\nPublicado hace 3 d\u00edas\nContactar", "revised": false, "rejected": true, "data": {"precio": "$ 330.000", "expensas": "$ 38.000 Expensas", "direccion": "DON BOSCO 2880 7\u00b0 E", "metros": "45 m\u00b2 tot.", "habitaciones": "2 amb.", "hace": "Publicado hace 3 d\u00edas"}}, "https://www.zonaprop.com.ar/propiedades/clasificado/alclapin-departamento-2-ambientes-barrio-norte-capital-53570475.html": {"date": "05-05-2024\n", "content": "$ 330.000\n$ 120.580 Expensas\nLarrea 1300\nBarrio Norte, Capital Federal\n47 m\u00b2 tot.\n2 amb.\n1 dorm.\n1 ba\u00f1o\nMuy buen departamento contrafrente vista abierta gran balc\u00f3n Hall de entrada con placard de 3 hojas, Amplio Living con Aire Acondicionado Frio Calor, al balc\u00f3n, Dormitorio con cuatro hojas de placard y vista abierta, Ba\u00f1o completo con ventana, Cocina chica, lavadero chico, pisos de parquet, losa radiante central y agua caliente por calef\u00f3n. Expensas $ 120. 580 abl $ 12. 910, 12 Aysa $ 22. 881, 75. ver plano Y fotos adjuntas. oferta provista por topinmobiliario. com - codigo: bps2429\nPublicado hace 3 d\u00edas\nContactar", "revised": false, "rejected": true, "data": {"precio": "$ 330.000", "expensas": "$ 120.580 Expensas", "direccion": "Larrea 1300", "metros": "47 m\u00b2 tot.", "habitaciones": "2 amb.", "hace": "Publicado hace 3 d\u00edas"}}, "https://www.zonaprop.com.ar/propiedades/clasificado/alclapin-imperdible-en-alquiler-moreno-al-2294-53566718.html": {"date": "05-05-2024\n", "content": "$ 340.000\n$ 25.000 Expensas\nmoreno 2294\nBalvanera, Capital Federal\n39 m\u00b2 tot.\n2 amb.\n1 dorm.\nEste exclusivo departamento en alquiler en Moreno, Balvanera, Capital Federal, es una verdadera joya en el mercado inmobiliario. Con un precio de ar$340. 000, esta propiedad destaca por su excelente estado y su proximidad a las l\u00edneas de subte H y A, lo cual brinda una excelente conexi\u00f3n con toda la ciudad. Con 2 ambientes que incluyen 1 dormitorio y 1 ba\u00f1o, este departamento es ideal para quienes buscan comodidad y estilo en una ubicaci\u00f3n privilegiada. Adem\u00e1s, cuenta con todas las comodidades necesarias para una vida de lujo, como gas natural, agua corriente, luz, un acogedor patio y un total de 39 m2, de los cuales 37 m2 son cubiertos y 2 m2 descubiertos. Con un costo de expensas de $25. 000, esta propiedad es una oportunidad \u00fanica para vivir en una de las zonas m\u00e1s exclusivas de la ciudad. No pierdas la oportunidad de hacer tuyo este magn\u00edfico departamento y disfrutar de todo lo que tiene para ofrecer. Su moderna construcci\u00f3n y su cuidado dise\u00f1o hacen de este departamento en Moreno una opci\u00f3n ideal para aquellos que buscan calidad, confort y una ubicaci\u00f3n privilegiada en la vibrante ciudad de Buenos Aires. \u00a1Ven a descubrir tu nuevo hogar en esta espectacular propiedad de lujo!\nPublicado hace 3 d\u00edas\nContactar", "revised": false, "rejected": true, "data": {"precio": "$ 340.000", "expensas": "$ 25.000 Expensas", "direccion": "moreno 2294", "metros": "39 m\u00b2 tot.", "habitaciones": "2 amb.", "hace": "Contactar"}}, "https://www.zonaprop.com.ar/propiedades/clasificado/alclapin-2-ambientes-muy-luminoso-almagro-53568184.html": {"date": "05-05-2024\n", "content": "16\n$ 250.000\n$ 40.000 Expensas\nAvenida la Plata 400\nAlmagro, Capital Federal\n37 m\u00b2 tot.\n2 amb.\n1 dorm.\n1 ba\u00f1o\nCorredor Responsable: Grupo Village S. R. L. Maria guerrero cucicba 5154 / gonzalo guerrero cmcpsi 6271- Contacto: Brigitte Eberlin - mls id # Ver datos. Excelente ubicaci\u00f3n tiene nuestro 2 ambientes. Sobre Av. La Plata este luminoso y tranquilo departamento cuenta con cocina independiente con area de lavadero, living con ventanal, ba\u00f1o completo y dormitorio con placar. El mismo es interno, lo que brinda una hermosa tranquilidad. Solicite hoy su visita. Remax Argentina S. R. L. No ejerce el corretaje inmobiliario. El presente sitio web es una plataforma en donde cada oficina inmobiliaria independiente que contrata los servicios re/max puede publicar las propiedades a su cargo. Cada oficina es de propiedad y gesti\u00f3n independiente, por lo que Remax Argentina S. R. L no interviene en los datos de la publicaci\u00f3n, en la operaci\u00f3n inmobiliaria, ni en la confecci\u00f3n y/o firma del boleto de compraventa y/o escritura y/o contrato de alquiler. En cumplimiento de las leyes vigentes que regulan el corretaje inmobiliario, Ley Nacional 25. 028, Ley 22. 802 de Lealtad Comercial, Ley 24. 240 de Defensa al Consumidor, las normas del C\u00f3digo Civil y Comercial de la Naci\u00f3n y Constitucionales, los agentes/gestores no ejercen el corretaje inmobiliario. Todas las operaciones inmobiliarias son objeto de intermediaci\u00f3n y conclusi\u00f3n por parte del corredor p\u00fablico inmobiliario colegiado a cargo de la publicaci\u00f3n, cuyos datos se exhiben en la presente. La presente publicaci\u00f3n describe las caracter\u00edsticas esenciales del inmueble, debi\u00e9ndose consultar al corredor p\u00fablico inmobiliario responsable de la operaci\u00f3n por la eventual actualizaci\u00f3n de las medidas, descripciones arquitect\u00f3nicas y funcionales, valores de expensas, servicios, impuestos, precios y dem\u00e1s informaci\u00f3n, cuyos valores son aproximados. Para los casos de alquiler de vivienda, el monto m\u00e1ximo de comisi\u00f3n que se le puede requerir a los propietarios ser\u00e1 el equivalente al cuatro con quince cent\u00e9simos por ciento (4, 15%) del valor total del respectivo contrato. Se encuentra prohibido cobrar a los inquilinos que sean personas f\u00edsicas comisiones inmobiliarias y gastos de gestor\u00eda de informes. El inmueble no es accesible para personas con discapacidades f\u00edsicas.\nPublicado hace 3 d\u00edas\nContactar", "revised": false, "rejected": true, "data": {"precio": "$ 250.000", "expensas": "$ 40.000 Expensas", "direccion": "Avenida la Plata 400", "metros": "37 m\u00b2 tot.", "habitaciones": "2 amb.", "hace": "Publicado hace 3 d\u00edas"}}, "https://www.zonaprop.com.ar/propiedades/clasificado/alclapin-departamento-2-ambientes.-uriarte-al-1000-53569175.html": {"date": "05-05-2024\n", "content": "$ 340.000\n$ 20.000 Expensas\nURIARTE 1000. Entre Jufre y Castillo\nVilla Crespo, Capital Federal\n46 m\u00b2 tot.\n2 amb.\n1 dorm.\nAlquiler de Departamento 2 ambientes en Villa Crespo, Capital Federal. alquiler departamento dos ambientes al frente, en planta baja con patio. Living comedor, dormitorio con placard. Ba\u00f1o completo. Cocina con muebles sobre Y bajo mesada. Espacio para mesa chica. Todo con ventilacion al exterior. Recien pintado de color blanco. Pisos ceramicos en living, Y parquet en dormitorio. Expensas vto abril: $20. 000 aproximadamente. Aysa: $3. 800. ubicado en villa crespo, A una cuadra de av. Cordoba. Cercano A plaza serrano, zona de oulets de villa crespo. Transportes cercanos. colectivos: 19, 34, 55, 90, 108, 127, 140, 151, 166, 168. Condiciones de contrato seg\u00fan dnu 70/2023: - Demostraci\u00f3n de ingresos acorde a valor locativo inicial. - Impuestos, servicios y expensas comunes a cargo del locatario. - Contrato a dos a\u00f1os. - Actualizaci\u00f3n trimestral seg\u00fan Indice icl. - Garant\u00eda propietaria en Capital Federal o seguro de cauci\u00f3n de la empresa Premium Group. - Deposito de garant\u00eda: $ 340. 000, actualizado anualmente, y al a\u00f1o y medio. Ley 5115 art. 1. \"Edificio sin accesibilidad para discapacitados\" ley 5859 - art. 5. \"Se encuentra prohibido cobrar Honorarios/comisiones inmobiliarias y gastos de gestor\u00eda de informes a los inquilinos que sean personas f\u00edsicas. Para los casos de alquiler de vivienda, el monto m\u00e1ximo de comisi\u00f3n/honorarios que se le puede cobrar a los propietarios ser\u00e1 el equivalente al cuatro con quince cent\u00e9simos por ciento (4, 15%) del valor total del respectivo contrato. \" aviso legal: Las descripciones arquitect\u00f3nicas y funcionales, valores de expensas, impuestos y servicios, fotos y medidas de este inmueble son aproximados. Los datos fueron proporcionados por el propietario y pueden no estar actualizados a la hora de la visualizaci\u00f3n de este aviso por lo cual pueden arrojar inexactitudes y discordancias con las que surgen de los las facturas, t\u00edtulos y planos legales del inmueble. El interesado deber\u00e1 realizar las verificaciones respectivas previamente a la realizaci\u00f3n de cualquier operaci\u00f3n, requiriendo por s\u00ed o sus profesionales las copias necesarias de la documentaci\u00f3n que corresponda. Venta supeditada al cumplimiento por parte del propietario de los requisitos de la resoluci\u00f3n general N\u00ba 2371 de la afip (pedido de coti). Corredor responsable: H\u00e9ctor Rodolfo Men\u00e9ndez. C. U. C. I. C. B. A 3423xintel(mez-mez-77)\nPublicado hace 3 d\u00edas\nContactar", "revised": false, "rejected": true, "data": {"precio": "$ 340.000", "expensas": "$ 20.000 Expensas", "direccion": "URIARTE 1000. Entre Jufre y Castillo", "metros": "46 m\u00b2 tot.", "habitaciones": "2 amb.", "hace": "Publicado hace 3 d\u00edas"}}, "https://www.zonaprop.com.ar/propiedades/clasificado/alclapin-uriburu-al-500-2-amb-facultad-alquiler-53569755.html": {"date": "05-05-2024\n", "content": "$ 290.000\n$ 45.000 Expensas\nUriburu al 500\nBalvanera, Capital Federal\n38 m\u00b2 tot.\n2 amb.\n1 dorm.\n1 ba\u00f1o\nDepartamento de 2 ambientes - facultad - AlquilerPr\u00f3ximo a Facultad de Medicina y Econ\u00f3micas. A pocas cuadras de Subte \u201cB\u201d y \u201cD\u201d Pisos de parquet Lateral. Luminoso. Living-comedor con placardDormitorio con placardCocina Lavadero en cocina. Calef\u00f3n a gasCocina de 4 hornallas y horno a gasBa\u00f1o con ba\u00f1era.\nPublicado hace 3 d\u00edas\nContactar", "revised": false, "rejected": true, "data": {"precio": "$ 290.000", "expensas": "$ 45.000 Expensas", "direccion": "Uriburu al 500", "metros": "38 m\u00b2 tot.", "habitaciones": "2 amb.", "hace": "Publicado hace 3 d\u00edas"}}, "https://www.zonaprop.com.ar/propiedades/clasificado/alclappa-alquiler-deparatamento-2-ambientes-53569063.html": {"date": "05-05-2024\n", "content": "$ 280.000\n$ 51.000 Expensas\nTeniente General Juan Domingo Per\u00f3n 2200\nBalvanera, Capital Federal\n42 m\u00b2 tot.\n2 amb.\n1 dorm.\n1 ba\u00f1o\nAlquiler departamento 2 ambientes. Departamento en 7mo piso contrafrente de 2 ambientes. Living con aire acondicionado, cocina separada con espacio para lavarropa, balc\u00f3n cubierto/lavadero exterior, pisos de parquet, placard en pasillo de distribuci\u00f3n, amplio dormitorio con placard a lo ancho y alto de la pared y aire acondicionado. Ba\u00f1o completo con ba\u00f1era y duchador. Departamento ubicado en zona c\u00e9ntrica, cercano a los medios de transporte, subte y comercios. El edificio cuenta con 2 ascensores, lobby remodelado a nuevo, personal de porter\u00eda fija, c\u00e1maras de seguridad en edificio. No apto mascota. Condiciones de alquiler: - Contrato a 2 a\u00f1os. - Ajuste trimestral seg\u00fan indice ipc. - Demostraci\u00f3n de ingresos. - Garant\u00eda propietaria familiar directo (ideal caba) o seguro de causi\u00f3n (Propuesto por propietario) - Mes en garant\u00eda. - Gastos: Verificaci\u00f3n de documentaci\u00f3n presentada y Certificaci\u00f3n de Firmas, expensas / abl / aysa / Edesur / Metrogas a cargo del inquilino.\nPublicado hace 3 d\u00edas\nContactar", "revised": false, "rejected": true, "data": {"precio": "$ 280.000", "expensas": "$ 51.000 Expensas", "direccion": "Teniente General Juan Domingo Per\u00f3n 2200", "metros": "42 m\u00b2 tot.", "habitaciones": "2 amb.", "hace": "Contactar"}}, "https://www.zonaprop.com.ar/propiedades/clasificado/alclappa-alquilo-dpto-2amb-luminoso-53563768.html": {"date": "05-05-2024\n", "content": "$ 290.000\n$ 30.000 Expensas\nR\u00edo de Janeiro 781\nParque Centenario, Capital Federal\n31 m\u00b2 tot.\n2 amb.\n1 dorm.\n1 ba\u00f1o\nDepartamento de dos ambientes en perfecto estado. Orientaci\u00f3n lateral. Balc\u00f3n con lavadero. Ba\u00f1o completo. Pisos de parquet. Dormitorio con placard. Muy luminoso. Bajas expensas. Apto profesional.\nPublicado hace 3 d\u00edas\nContactar", "revised": false, "rejected": true, "data": {"precio": "$ 290.000", "expensas": "$ 30.000 Expensas", "direccion": "R\u00edo de Janeiro 781", "metros": "31 m\u00b2 tot.", "habitaciones": "2 amb.", "hace": "Contactar"}}, "https://www.zonaprop.com.ar/propiedades/clasificado/alclappa-departamento-de-2-amb-a-estrenar!-53567100.html": {"date": "05-05-2024\n", "content": "$ 330.000\n$ 25.000 Expensas\nBoedo, Capital Federal\n34 m\u00b2 tot.\n2 amb.\n1 dorm.\n1 ba\u00f1o\nExcelente dto de 2 amb Reciclado a Nuevo. Muy Luminoso con vista a la terraza de todos sus ambientes orientacion Oeste. . Pisos ceramicos, Placard empotrado. Cocina con alacena, bajo mesada espacio para heladera y coneccion de lavarropas. Termotanque electrico con termica independiente. Ba\u00f1o completo y espacio de guardado. bajas expensas!! Terraza Compartida con Lavadero. A 200 mts de Av. Boedo e Av. Independencia. Polo Gastronomico y cultural de la Ciudad. Muchas Lineas de colectivos y Subtes al alcance. 400 mts Hospital Ramos Mejia. inmejorable ubicacion. Contacto Inmobiliaria\nPublicado hace 3 d\u00edas\nContactar", "revised": false, "rejected": true, "data": {"precio": "$ 330.000", "expensas": "$ 25.000 Expensas", "direccion": "", "metros": "34 m\u00b2 tot.", "habitaciones": "2 amb.", "hace": "Contactar"}}, "https://www.zonaprop.com.ar/propiedades/clasificado/alclappa-alquiler-departamento-2-ambientes-villa-crespo-53562662.html": {"date": "05-05-2024\n", "content": "$ 300.000\nAvenida Corrientes & Juli\u00e1n \u00c1lvarez\nVilla Crespo, Capital Federal\n40 m\u00b2 tot.\n2 amb.\n1 dorm.\n1 ba\u00f1o\nDisfruta de la comodidad y el encanto de este espacioso apartamento de 2 ambientes. Alquiler: Contrato a 2 A\u00f1os (24 meses). Situado en una ubicaci\u00f3n ideal. Departamento luminoso. Caracter\u00edsticas destacadas: - Dos ambientes amplios y luminosos. - Dormitorio amplio. - Ubicaci\u00f3n conveniente, con acceso a tiendas, restaurantes y transporte p\u00fablico a pocos pasos de distancia. - Servicios: Luz y Agua Corriente. - Expensas Incluidas. Requisitos: - Demostraci\u00f3n de ingresos. - Seguro de cauci\u00f3n y/o Garant\u00eda propietaria. - 1 mes de dep\u00f3sito en garant\u00eda. - 1 mes de adelanto.\nDestacado\nPublicado hace 4 d\u00edas\nContactar", "revised": false, "rejected": true, "data": {"precio": "$ 300.000", "direccion": "Avenida Corrientes & Juli\u00e1n \u00c1lvarez", "metros": "40 m\u00b2 tot.", "habitaciones": "2 amb.", "hace": "Contactar"}}, "https://www.zonaprop.com.ar/propiedades/clasificado/alclapin-departamento-de-2-ambientes-en-alquiler-en-villa-53560778.html": {"date": "05-05-2024\n", "content": "$ 300.000\n$ 70.000 Expensas\nLEMOS 0\nVilla Crespo, Capital Federal\n35 m\u00b2 tot.\n2 amb.\n1 dorm.\n1 ba\u00f1o\nDos ambientes muy luminoso, contrafrente con excelente vista, en pleno corredor de corrientes. Cocina y lavadero independiente. Cerca del Subte B. Sin mascotas y solo con Garantia Propietaria de caba, propia o de Garante. Comercializa Migliorisi de Corrientes 5500 srl Profesional responsable Diego F Migliorisi cpi263. Ver datos Se deja constancia que las caracteristicas, medidas, expensas y superficies consignadas son aproximadas, sujetos a verificaci\u00f3n y/o ajuste. El precio del inmueble puede ser modificado sin previo aviso. Fotos de car\u00e1cter no contractual. Las unidades publicadas est\u00e1n sujetas a disponibilidad. . Publicado por Migliorisi Villa Crespo a traves de Inmomap\nPublicado hace 4 d\u00edas\nContactar", "revised": false, "rejected": true, "data": {"precio": "$ 300.000", "expensas": "$ 70.000 Expensas", "direccion": "LEMOS 0", "metros": "35 m\u00b2 tot.", "habitaciones": "2 amb.", "hace": "Publicado hace 4 d\u00edas"}}, "https://www.zonaprop.com.ar/propiedades/clasificado/alclappa-alquiler-2-ambientes-san-cristobal-saavedra-700-53562870.html": {"date": "05-05-2024\n", "content": "$ 270.000\n$ 45.000 Expensas\nSaavedra 700\nSan Cristobal, Capital Federal\n30 m\u00b2 tot.\n2 amb.\n1 dorm.\n1 ba\u00f1o\nDescripci\u00f3n: Alquiler de Departamento de 2 ambientes, muy c\u00f3modos, localizado en el Barrio de San Crist\u00f3bal, en excelente ubicaci\u00f3n sobre la calle Saavedra al 700, a metros de Av. Independencia y a una cuadra de Av. Jujuy, muchos medios de transporte, zona comercial (Farmacity, ypf, Diarco, Dia, restaurantes, pizzer\u00edas, caf\u00e9, colegios, uba-Psicologia) y en constante expansi\u00f3n con mucha construcci\u00f3n nueva sobre Av. Independencia. A 1 cuadra de la Plaza Velazco Ibarra. El departamento se ubica en un sexto piso, lo que le permite buena entrada de luz la mayor parte del d\u00eda. Todos los ambientes cuentan con ventanas al exterior lo que lo hace s\u00faper aireado. Cuenta con Cocina que ventila al exterior, donde se encuentra el Lavadero independiente, semi-cubierto con conexi\u00f3n y espacio para lavarropas. Living con ventanal estilo franc\u00e9s, pisos de cer\u00e1mica. El Dormitorio tiene un amplio placard (con cajonera) y de buena profundidad. Ba\u00f1o completo con ba\u00f1era, que tambi\u00e9n ventila al exterior a trav\u00e9s de una amplia ventana rebatible de 3 hojas. Servicios individuales, agua por calef\u00f3n. La unidad se encuentra \"reci\u00e9n pintada\" y con bajo mesada y alacena \"a estrenar\". El edificio cuenta con 2 (dos) Ascensores. Medios de transporte: l\u00edneas 23, 61, 62, 88, 96, 101, 118, 129, Subte l\u00ednea \u201cH\u201d. Superficie total: 29. 5 m\u00b2 Superficie cubierta: 28. 5 m\u00b2 Superficie semicubierta: 1 m\u00b2 Ambientes: 2. Ba\u00f1os: 1. Dormitorios: 1. Expensas: $ 45. 000. - Pisos de la propiedad: 10. Requisitos para Alquilar: 1) A la firma deben abonar un mes y medio en concepto de deposito de garant\u00eda, mas el mes de Alquiler adelantado. 2) Garant\u00eda propietaria de Capital Federal y dni del garante; o bien Seguro de Cauci\u00f3n de Alquiler. 3) Fotocopia del dni (frente y dorso) de cada persona que firma. 4) Contrato de Locaci\u00f3n por 2 a\u00f1os y reajustes Trimestrales en funci\u00f3n del \u00edndice del costo de vida que publica el indec (ipc). 5) \u00daltimos 3 (tres) recibos de Sueldo de cada persona que firma.\nPublicado hace 3 d\u00edas\nContactar", "revised": false, "rejected": true, "data": {"precio": "$ 270.000", "expensas": "$ 45.000 Expensas", "direccion": "Saavedra 700", "metros": "30 m\u00b2 tot.", "habitaciones": "2 amb.", "hace": "Contactar"}}, "https://www.zonaprop.com.ar/propiedades/clasificado/alclapin-departamento-almagro-53556827.html": {"date": "05-05-2024\n", "content": "11\n$ 300.000\n$ 35.000 Expensas\nMedrano 57\nAlmagro, Capital Federal\n40 m\u00b2 tot.\n2 amb.\n1 dorm.\n1 ba\u00f1o\nDepartamento de 2 ambientes con lavadero independiente con conexi\u00f3n para lavarropas, Ba\u00f1o completo con Ba\u00f1aderay Buenos espacios de guardado. Zona Estrat\u00e9gica: Transporte publico lineas 5, 8, 19, 26, 86, 88, 90, 103, 104, 105, 127, 128, 132, 146, 151, 160, 164, 180 y Subte (L\u00ednea A) Estaci\u00f3n \" castro barros\". Requisitos para ingresar: -Garant\u00eda capital preferentemente, si es de provincia tiene que ser de familiar directo. -Recibo de sueldo o ingresos comprobables. -1 mes de deposito-1 mes de adelantohomes inmobiliariamatricula 7362 homes InmobiliariaMatricula C. U. C. I. C. B. A. N\u00b0 7362 Colegio Profesional InmobiliarioAv. Juan B. Alberdi 665 C. A. B. A. Ver datosTel. : Ver datos Rotativas - Movil Ver datoswww. homesinmobiliaria. com. arSeguinos en! Facebook: Homes InmobiliariaInstagram: @homes. inmobiliaria\nSuper destacado\nPublicado hace 5 d\u00edas\nContactar", "revised": false, "rejected": true, "data": {"precio": "$ 300.000", "expensas": "$ 35.000 Expensas", "direccion": "Medrano 57", "metros": "40 m\u00b2 tot.", "habitaciones": "2 amb.", "hace": "Super destacado\nPublicado hace 5 d\u00edas"}}, "https://www.zonaprop.com.ar/propiedades/clasificado/alclapin-alquiler-departamento-2-amb-en-gascon-y-corrientes-53553658.html": {"date": "05-05-2024\n", "content": "12\n$ 350.000\n$ 80.000 Expensas\nGascon y Corrientes\nAlmagro, Capital Federal\n45 m\u00b2 tot.\n2 amb.\n1 dorm.\n1 ba\u00f1o\nAlquiler departamento de 2 ambientes semipiso. contra frente super luminoso con balcon. ba\u00f1o completo. cocina independiente super amplia con lavadero incorporado. mucho espacio de guardado. 2 aire acondicionado. estufa A gas\nSuper destacado\nPublicado hace 5 d\u00edas\nContactar", "revised": false, "rejected": true, "data": {"precio": "$ 350.000", "expensas": "$ 80.000 Expensas", "direccion": "Gascon y Corrientes", "metros": "45 m\u00b2 tot.", "habitaciones": "2 amb.", "hace": "Contactar"}}, "https://www.zonaprop.com.ar/propiedades/clasificado/alclapin-excelente-dos-ambientes-en-villa-crespo-53553465.html": {"date": "05-05-2024\n", "content": "$ 280.000\n$ 20.000 Expensas\nserrano 387\nVilla Crespo, Capital Federal\n34 m\u00b2 tot.\n2 amb.\n1 dorm.\n1 ba\u00f1o\nExcelente dos ambientes en Villa Crespo a pocas cuadras del subte b. Cerca de el Mercat de Villa Crespo un lugar emblem\u00e1tico de gastronom\u00eda internacional. A pocas cuadras se encuentra el Metrob\u00fas sobre la av. Juan B Justo. \u00c1rea Hospitalaria: Hospital General de Agudos Carlos G. Durand. Ideal para profesionales y estudiantes\nSuper destacado\nPublicado hace 4 d\u00edas\nContactar", "revised": false, "rejected": true, "data": {"precio": "$ 280.000", "expensas": "$ 20.000 Expensas", "direccion": "serrano 387", "metros": "34 m\u00b2 tot.", "habitaciones": "2 amb.", "hace": "Super destacado\nPublicado hace 4 d\u00edas"}}, "https://www.zonaprop.com.ar/propiedades/clasificado/alclapin-excelente-2-ambientes-con-2-balcones-53556591.html": {"date": "05-05-2024\n", "content": "$ 350.000\n$ 25.000 Expensas\nMAZA 820\nBoedo, Capital Federal\n55 m\u00b2 tot.\n2 amb.\n1 dorm.\n1 ba\u00f1o\nAmplio 2 ambientes en dos plantas - A nuevo - dos balcones - lavadero - expensas $25. 000. requisiots: mes de alquiler mas mes de deposito mas gastos total $750. 000. garante con propiedad O seguro de caucion - contrato A 2 a\u00f1os con ajuste trimestral por ipc -para entrar 1 de junio\nDestacado\nPublicado hace 5 d\u00edas\nContactar", "revised": true, "rejected": true, "data": {"precio": "$ 350.000", "expensas": "$ 25.000 Expensas", "direccion": "MAZA 820", "metros": "55 m\u00b2 tot.", "habitaciones": "2 amb.", "hace": "Destacado\nPublicado hace 5 d\u00edas"}, "comment": "Parece grande"}, "https://www.zonaprop.com.ar/propiedades/clasificado/alclapin-departamento-en-alquiler-53558213.html": {"date": "05-05-2024\n", "content": "$ 280.000\n$ 55.000 Expensas\nPaso al 200\nOnce, Capital Federal\n47 m\u00b2 tot.\n2 amb.\n1 dorm.\n1 ba\u00f1o\nSe trata de un departamento de 2 ambientes al frente con balc\u00f3n, lavadero incorporado, balc\u00f3n corrido. no se aceptan mascotas. ll 118condiciones Y requisitos- 1 mes por adelantado + 1 mes deposito (igual al valor del primer mes) - Garant\u00eda-El monto de las expensas aqu\u00ed especificado, fueron extra\u00eddos de la liquidaci\u00f3n realizada por el administrador del edificio y corresponden al mes de Febrero de 2024, por lo tanto y debido a que sufren fluctuaciones mes a mes, Ud deber\u00e1 solicitarnos el monto actualizado previamente a la realizaci\u00f3n de la operaci\u00f3n. -- Honorarios: seg\u00fan ley 5859 \u201cSe encuentra prohibido cobrar comisiones inmobiliarias y gastos de gestor\u00eda de informes a los inquilinos que sean personas f\u00edsicas. Para los casos de alquiler de vivienda, el monto m\u00e1ximo de comisi\u00f3n que se le puede requerir a los propietarios ser\u00e1 el equivalente al cuatro con quince cent\u00e9simos por ciento (4, 15%) del valor total del respectivo contrato\u201d- Contrato por 2 a\u00f1os- Indexaci\u00f3n trimestral seg\u00fan \u00edndice icl\nPublicado hace 5 d\u00edas\nContactar", "revised": false, "rejected": true, "data": {"precio": "$ 280.000", "expensas": "$ 55.000 Expensas", "direccion": "Paso al 200", "metros": "47 m\u00b2 tot.", "habitaciones": "2 amb.", "hace": "Publicado hace 5 d\u00edas"}}, "https://www.zonaprop.com.ar/propiedades/clasificado/alclapin-2amb-40-m-sup2--tv!-heladera!-juego-de-comedor!-53560257.html": {"date": "05-05-2024\n", "content": "$ 295.000\n$ 33.800 Expensas\nAvenida Boedo al 1300\nAlmagro, Capital Federal\n40 m\u00b2 tot.\n2 amb.\n1 dorm.\n1 ba\u00f1o\n\u00a1 2 ambientes S/avenida! \u00a1 C/balc\u00f3n al contrafrente! #Departamento | #Est\u00e1ndar | #2amb | #Contrafrente | #BoedoAvenida Boedo 1300, Piso 4 - Ciudad Aut\u00f3noma de Buenos Aires\u00b7 Caracter\u00edsticas: ~ Departamento de dos (2) ambientes con balc\u00f3n, dispuesto hacia el contrafrente, ubicado en el barrio de Boedo sobre la avenida principal del vecindario. ~ Orientaci\u00f3n O (Oeste). Vista a ciudad. Ventilaci\u00f3n cruzada. Excelente estado de mantenimiento, propios del buen uso y habitaci\u00f3n del inmueble. ~ Ubicado sobre Avenida Boedo. A 47 metros de Avenida Pav\u00f3n. A 179 metros de Avenida Juan de Garay. A 353 metros de Avenida San Juan. ~ Conectividad con medios de transporte. M\u00faltiples colectivos y subte/metro L\u00ednea E - Boedo. Cercan\u00eda a subida/bajada Autopista (au) 25 de Mayo. ~ Su oferta comercial incluye actividades recreativas y culturales, locales gastron\u00f3micos, farmacias, paseos, instituciones m\u00e9dicas y educativas. \u00b7 Edificio: ~ Entre medianeras. Su fachada combina ladrillo visto, frentines de hormig\u00f3n pintado en color blanco y barandas de hierro forjado en sus balcones. ~ Su planta baja (pb) se encuentra revestida en m\u00e1rmol travertino y cuenta con entrada por puerta con marco de madera, vidrio repartido y manij\u00f3n de bronce. ~ Su hall de entrada posee un cantero hacia el interior, pisos revestidos en m\u00e1rmol, ladrillo a la vista, detalles en madera y paredes espejadas. ~ Sus palieres comunes garantizan un habitar pac\u00edfico, e integran pisos revestidos en mosaicos gran\u00edticos marrones modelo nevados y paredes de salpicr\u00e9. ~ Cuenta con 10 pisos. 4 departamentos por cada uno de sus pisos. 1 ascensor automatizado. Previsibles gastos de mantenimiento mensuales. \u00b7 Distribuci\u00f3n: ~ Hall de recepci\u00f3n (2. 00m x 1. 15m). ~ Cocina semi-integrada (3. 90m x 1. 50m). ~ Lavadero / balc\u00f3n (3. 75m x 1. 00m). ~ Living comedor (4. 00m x 3. 00m). ~ Hall / Distribuidor (1. 10m x 0. 80m). ~ Ba\u00f1o (2. 15m x 1. 00m). ~ Dormitorio (3. 00m x 3. 00m). \u00b7 Equipamiento: ~ Paredes revestidas en fibra de vidrio conservan su natural luminosidad. Pisos revestidos en parquet en hall de recepci\u00f3n, living comedor, distribuidor y dormitorio. ~ Su cocina semi-integrada cuenta con pisos revestidos en cer\u00e1micas color gris y paredes revestidas en cer\u00e1micas blancas combinadas con guarda decorativa. ~ Mobiliario de cocina (bajo-mesada y alacenas) de mdf/melamina blanca. Mesada de granito modelo negro boreal. Bacha doble de acero inoxidable instalada. ~ Cocina a gas. Extractor / purificador de aire. Conexi\u00f3n para carga y descarga de lavarropas. Agua caliente individual a trav\u00e9s de calef\u00f3n. Barra desayunadora. ~ Su ba\u00f1o cuenta con pisos revestidos en cer\u00e1micas color gris y paredes revestidas en cer\u00e1micas. Vanitory en blanco, artefactos completos y recept\u00e1culo de ducha. ~ Cuenta con placard de piso/techo con puertas de apertura frontal, divisores, estantes, barrales, cajoneras y dem\u00e1s interiores a medida instalado dormitorio. ~ Juego de comedor compuesto por mesa de madera con cuatro (4) sillas. Mesa de tv de madera pintada en verde agua. Cama con sommier. Heladera. \u00b7 Requisitos solicitados por la parte propietaria: ~ 1 mes de alquiler por adelantado. ~ 1 mes de dep\u00f3sito de garant\u00eda por cada a\u00f1o contratado. ~ De la fianza: garant\u00eda propietaria o sistema de garant\u00edas de cauci\u00f3n (Finaer / Fiancor). ~ De los ingresos: \u00faltimos tres (3) recibos de sueldo o certificaci\u00f3n de ingresos por contador p\u00fablico. \u00b7 Condiciones ofrecidas por la parte propietaria: ~ Duraci\u00f3n del contrato: 18 meses (contrato de alquiler temporario con muebles). ~ Actualizaci\u00f3n: ipc \u00b7 \u00cdndice de Precios al Consumidor publicado por el indec. ~ Periodicidad de actualizaci\u00f3n: Trimestral. #Nota: El edificio no cuenta con accesibilidad para personas con movilidad reducida (Ley 5115). Las im\u00e1genes en este anuncio publicadas son meramente ilustrativas y no poseen car\u00e1cter contractual. El importe de expensas anunciado ha sido extra\u00eddo de su \u00faltima facturaci\u00f3n, es orientativo, no vinculante y est\u00e1 sujeto a modificaciones y/o variaciones sin previa publicidad. Las medidas expresadas en el presente aviso son aproximadas y a t\u00edtulo informativo. Las medidas originales surgir\u00e1n de los respectivos planos y/o escritura del inmueble. El inmueble no es apto para mascotas por expresa solicitud de sus propietarios en el contrato de comercializaci\u00f3n. Somos especialistas en operaciones simult\u00e1neas. Tasamos en los 48 barrios de la Ciudad de Buenos Aires: . ar/tasaciones/spinelli propiedadeswww. spinelliprop. com. ar#Visitas por WhatsApp al +54 9 11 Ver datos#Reservas al Ver datos Ver datos#Consultas a Ver datos#Oficina en Avenida San Juan 3467 - cabadesde 1921 - #OportunidadesGrandesComoUnaCasa\nPublicado hace 3 d\u00edas\nContactar", "revised": false, "rejected": true, "data": {"precio": "$ 295.000", "expensas": "$ 33.800 Expensas", "direccion": "Avenida Boedo al 1300", "metros": "40 m\u00b2 tot.", "habitaciones": "2 amb.", "hace": "Publicado hace 3 d\u00edas"}}, "https://www.zonaprop.com.ar/propiedades/clasificado/alclapin-once-alq-2-amb-apto-profesional-av-corrientes-y-53551885.html": {"date": "05-05-2024\n", "content": "$ 270.000\n$ 47.000 Expensas\nAv Corrientes 2560\nOnce, Capital Federal\n40 m\u00b2 tot.\n2 amb.\n1 dorm.\n1 ba\u00f1o\nAv Corrientes entre Azcu\u00e9naga y Pasteur - Todos los transportes - Subte B / Subte A - Apto Profesional Ideal Actividad Comercial - 2 Ambientes muy c\u00f3modos - Dormitorio con placard - Hall \u00edntimo con placard - Ba\u00f1o con ducha - Cocina separada - Heladera y Microondas optativo - Buen Estado - Bajas expensas - alquilo hoy $270. 000. - Consulte condiciones\nPublicado hace 5 d\u00edas\nContactar", "revised": false, "rejected": true, "data": {"precio": "$ 270.000", "expensas": "$ 47.000 Expensas", "direccion": "Av Corrientes 2560", "metros": "40 m\u00b2 tot.", "habitaciones": "2 amb.", "hace": "Publicado hace 5 d\u00edas"}}, "https://www.zonaprop.com.ar/propiedades/clasificado/alclapin-departamento-en-alquiler-53558181.html": {"date": "05-05-2024\n", "content": "$ 320.000\nEcuardor 1300\nBarrio Norte, Capital Federal\n37 m\u00b2 tot.\n2 amb.\n1 dorm.\n1 ba\u00f1o\nAlquiler de departamento en Barrio Norte, Caba2 ambientes al frente en alquilerLiving comedorHabitaci\u00f3n con espacio de guardadoBalc\u00f3n a la calleCocina completaBa\u00f1o completoExcelente ubicaci\u00f3nA 100 metros de Subte linea D y H estaci\u00f3n Pueyrred\u00f3nA 100 metros de Avenida PueyrredonAlquiler: $ 320. 000Expensas: A confirmar aviso legal: Las descripciones arquitect\u00f3nicas y funcionales, valores de expensas, impuestos y servicios, fotos y medidas de este inmueble son aproximados. Los datos fueron proporcionados por el propietario y pueden no estar actualizados a la hora de la visualizaci\u00f3n de este aviso por lo cual pueden arrojar inexactitudes y discordancias con las que surgen de las facturas, t\u00edtulos y planos legales del inmueble. El interesado deber\u00e1 realizar las verificaciones respectivas previamente a la realizaci\u00f3n de cualquier operaci\u00f3n, requiriendo por si o sus profesionales las copias necesarias de la documentaci\u00f3n que corresponda. Auge Propiedades Av. C\u00f3rdoba 1698. C. A. B. A. cucicba Matricula: 1263Telefono: Ver datosley 5859 \u2013 art. 4\u201cPara los casos de alquiler de vivienda, el monto m\u00e1ximo de comisi\u00f3n que se le puede requerir a los propietarios ser\u00e1 el equivalente al cuatro con quince cent\u00e9simos por ciento (4, 15%) del valor total del respectivo contrato. Se encuentra prohibido cobrar a los inquilinos que sean personas f\u00edsicas comisiones inmobiliarias y gastos de gestor\u00eda de informes\u201d.\nPublicado hace 5 d\u00edas\nContactar", "revised": false, "rejected": true, "data": {"precio": "$ 320.000", "direccion": "Ecuardor 1300", "metros": "37 m\u00b2 tot.", "habitaciones": "2 amb.", "hace": "Publicado hace 5 d\u00edas"}}, "https://www.zonaprop.com.ar/propiedades/clasificado/alclapin-2amb-40-m-sup2--tv!-heladera!-juego-de-comedor!-53560255.html": {"date": "05-05-2024\n", "content": "$ 295.000\n$ 33.800 Expensas\nAvenida Boedo al 1300\nBoedo, Capital Federal\n40 m\u00b2 tot.\n2 amb.\n1 dorm.\n1 ba\u00f1o\n\u00a1 2 ambientes S/avenida! \u00a1 C/balc\u00f3n al contrafrente! #Departamento | #Est\u00e1ndar | #2amb | #Contrafrente | #BoedoAvenida Boedo 1300, Piso 4 - Ciudad Aut\u00f3noma de Buenos Aires\u00b7 Caracter\u00edsticas: ~ Departamento de dos (2) ambientes con balc\u00f3n, dispuesto hacia el contrafrente, ubicado en el barrio de Boedo sobre la avenida principal del vecindario. ~ Orientaci\u00f3n O (Oeste). Vista a ciudad. Ventilaci\u00f3n cruzada. Excelente estado de mantenimiento, propios del buen uso y habitaci\u00f3n del inmueble. ~ Ubicado sobre Avenida Boedo. A 47 metros de Avenida Pav\u00f3n. A 179 metros de Avenida Juan de Garay. A 353 metros de Avenida San Juan. ~ Conectividad con medios de transporte. M\u00faltiples colectivos y subte/metro L\u00ednea E - Boedo. Cercan\u00eda a subida/bajada Autopista (au) 25 de Mayo. ~ Su oferta comercial incluye actividades recreativas y culturales, locales gastron\u00f3micos, farmacias, paseos, instituciones m\u00e9dicas y educativas. \u00b7 Edificio: ~ Entre medianeras. Su fachada combina ladrillo visto, frentines de hormig\u00f3n pintado en color blanco y barandas de hierro forjado en sus balcones. ~ Su planta baja (pb) se encuentra revestida en m\u00e1rmol travertino y cuenta con entrada por puerta con marco de madera, vidrio repartido y manij\u00f3n de bronce. ~ Su hall de entrada posee un cantero hacia el interior, pisos revestidos en m\u00e1rmol, ladrillo a la vista, detalles en madera y paredes espejadas. ~ Sus palieres comunes garantizan un habitar pac\u00edfico, e integran pisos revestidos en mosaicos gran\u00edticos marrones modelo nevados y paredes de salpicr\u00e9. ~ Cuenta con 10 pisos. 4 departamentos por cada uno de sus pisos. 1 ascensor automatizado. Previsibles gastos de mantenimiento mensuales. \u00b7 Distribuci\u00f3n: ~ Hall de recepci\u00f3n (2. 00m x 1. 15m). ~ Cocina semi-integrada (3. 90m x 1. 50m). ~ Lavadero / balc\u00f3n (3. 75m x 1. 00m). ~ Living comedor (4. 00m x 3. 00m). ~ Hall / Distribuidor (1. 10m x 0. 80m). ~ Ba\u00f1o (2. 15m x 1. 00m). ~ Dormitorio (3. 00m x 3. 00m). \u00b7 Equipamiento: ~ Paredes revestidas en fibra de vidrio conservan su natural luminosidad. Pisos revestidos en parquet en hall de recepci\u00f3n, living comedor, distribuidor y dormitorio. ~ Su cocina semi-integrada cuenta con pisos revestidos en cer\u00e1micas color gris y paredes revestidas en cer\u00e1micas blancas combinadas con guarda decorativa. ~ Mobiliario de cocina (bajo-mesada y alacenas) de mdf/melamina blanca. Mesada de granito modelo negro boreal. Bacha doble de acero inoxidable instalada. ~ Cocina a gas. Extractor / purificador de aire. Conexi\u00f3n para carga y descarga de lavarropas. Agua caliente individual a trav\u00e9s de calef\u00f3n. Barra desayunadora. ~ Su ba\u00f1o cuenta con pisos revestidos en cer\u00e1micas color gris y paredes revestidas en cer\u00e1micas. Vanitory en blanco, artefactos completos y recept\u00e1culo de ducha. ~ Cuenta con placard de piso/techo con puertas de apertura frontal, divisores, estantes, barrales, cajoneras y dem\u00e1s interiores a medida instalado dormitorio. ~ Juego de comedor compuesto por mesa de madera con cuatro (4) sillas. Mesa de tv de madera pintada en verde agua. Cama con sommier. Heladera. \u00b7 Requisitos solicitados por la parte propietaria: ~ 1 mes de alquiler por adelantado. ~ 1 mes de dep\u00f3sito de garant\u00eda por cada a\u00f1o contratado. ~ De la fianza: garant\u00eda propietaria o sistema de garant\u00edas de cauci\u00f3n (Finaer / Fiancor). ~ De los ingresos: \u00faltimos tres (3) recibos de sueldo o certificaci\u00f3n de ingresos por contador p\u00fablico. \u00b7 Condiciones ofrecidas por la parte propietaria: ~ Duraci\u00f3n del contrato: 18 meses (contrato de alquiler temporario con muebles). ~ Actualizaci\u00f3n: ipc \u00b7 \u00cdndice de Precios al Consumidor publicado por el indec. ~ Periodicidad de actualizaci\u00f3n: Trimestral. #Nota: El edificio no cuenta con accesibilidad para personas con movilidad reducida (Ley 5115). Las im\u00e1genes en este anuncio publicadas son meramente ilustrativas y no poseen car\u00e1cter contractual. El importe de expensas anunciado ha sido extra\u00eddo de su \u00faltima facturaci\u00f3n, es orientativo, no vinculante y est\u00e1 sujeto a modificaciones y/o variaciones sin previa publicidad. Las medidas expresadas en el presente aviso son aproximadas y a t\u00edtulo informativo. Las medidas originales surgir\u00e1n de los respectivos planos y/o escritura del inmueble. El inmueble no es apto para mascotas por expresa solicitud de sus propietarios en el contrato de comercializaci\u00f3n. Somos especialistas en operaciones simult\u00e1neas. Tasamos en los 48 barrios de la Ciudad de Buenos Aires: . ar/tasaciones/spinelli propiedadeswww. spinelliprop. com. ar#Visitas por WhatsApp al +54 9 11 Ver datos#Reservas al Ver datos Ver datos#Consultas a Ver datos#Oficina en Avenida San Juan 3467 - cabadesde 1921 - #OportunidadesGrandesComoUnaCasa\nPublicado hace 3 d\u00edas\nContactar", "revised": false, "rejected": true, "data": {"precio": "$ 295.000", "expensas": "$ 33.800 Expensas", "direccion": "Avenida Boedo al 1300", "metros": "40 m\u00b2 tot.", "habitaciones": "2 amb.", "hace": "Publicado hace 3 d\u00edas"}}, "https://www.zonaprop.com.ar/propiedades/clasificado/alclapin-2amb-40-m-sup2--tv!-heladera!-juego-de-comedor!-53560259.html": {"date": "05-05-2024\n", "content": "$ 295.000\n$ 33.800 Expensas\nAvenida Boedo al 1300\nSan Cristobal, Capital Federal\n40 m\u00b2 tot.\n2 amb.\n1 dorm.\n1 ba\u00f1o\n\u00a1 2 ambientes S/avenida! \u00a1 C/balc\u00f3n al contrafrente! #Departamento | #Est\u00e1ndar | #2amb | #Contrafrente | #BoedoAvenida Boedo 1300, Piso 4 - Ciudad Aut\u00f3noma de Buenos Aires\u00b7 Caracter\u00edsticas: ~ Departamento de dos (2) ambientes con balc\u00f3n, dispuesto hacia el contrafrente, ubicado en el barrio de Boedo sobre la avenida principal del vecindario. ~ Orientaci\u00f3n O (Oeste). Vista a ciudad. Ventilaci\u00f3n cruzada. Excelente estado de mantenimiento, propios del buen uso y habitaci\u00f3n del inmueble. ~ Ubicado sobre Avenida Boedo. A 47 metros de Avenida Pav\u00f3n. A 179 metros de Avenida Juan de Garay. A 353 metros de Avenida San Juan. ~ Conectividad con medios de transporte. M\u00faltiples colectivos y subte/metro L\u00ednea E - Boedo. Cercan\u00eda a subida/bajada Autopista (au) 25 de Mayo. ~ Su oferta comercial incluye actividades recreativas y culturales, locales gastron\u00f3micos, farmacias, paseos, instituciones m\u00e9dicas y educativas. \u00b7 Edificio: ~ Entre medianeras. Su fachada combina ladrillo visto, frentines de hormig\u00f3n pintado en color blanco y barandas de hierro forjado en sus balcones. ~ Su planta baja (pb) se encuentra revestida en m\u00e1rmol travertino y cuenta con entrada por puerta con marco de madera, vidrio repartido y manij\u00f3n de bronce. ~ Su hall de entrada posee un cantero hacia el interior, pisos revestidos en m\u00e1rmol, ladrillo a la vista, detalles en madera y paredes espejadas. ~ Sus palieres comunes garantizan un habitar pac\u00edfico, e integran pisos revestidos en mosaicos gran\u00edticos marrones modelo nevados y paredes de salpicr\u00e9. ~ Cuenta con 10 pisos. 4 departamentos por cada uno de sus pisos. 1 ascensor automatizado. Previsibles gastos de mantenimiento mensuales. \u00b7 Distribuci\u00f3n: ~ Hall de recepci\u00f3n (2. 00m x 1. 15m). ~ Cocina semi-integrada (3. 90m x 1. 50m). ~ Lavadero / balc\u00f3n (3. 75m x 1. 00m). ~ Living comedor (4. 00m x 3. 00m). ~ Hall / Distribuidor (1. 10m x 0. 80m). ~ Ba\u00f1o (2. 15m x 1. 00m). ~ Dormitorio (3. 00m x 3. 00m). \u00b7 Equipamiento: ~ Paredes revestidas en fibra de vidrio conservan su natural luminosidad. Pisos revestidos en parquet en hall de recepci\u00f3n, living comedor, distribuidor y dormitorio. ~ Su cocina semi-integrada cuenta con pisos revestidos en cer\u00e1micas color gris y paredes revestidas en cer\u00e1micas blancas combinadas con guarda decorativa. ~ Mobiliario de cocina (bajo-mesada y alacenas) de mdf/melamina blanca. Mesada de granito modelo negro boreal. Bacha doble de acero inoxidable instalada. ~ Cocina a gas. Extractor / purificador de aire. Conexi\u00f3n para carga y descarga de lavarropas. Agua caliente individual a trav\u00e9s de calef\u00f3n. Barra desayunadora. ~ Su ba\u00f1o cuenta con pisos revestidos en cer\u00e1micas color gris y paredes revestidas en cer\u00e1micas. Vanitory en blanco, artefactos completos y recept\u00e1culo de ducha. ~ Cuenta con placard de piso/techo con puertas de apertura frontal, divisores, estantes, barrales, cajoneras y dem\u00e1s interiores a medida instalado dormitorio. ~ Juego de comedor compuesto por mesa de madera con cuatro (4) sillas. Mesa de tv de madera pintada en verde agua. Cama con sommier. Heladera. \u00b7 Requisitos solicitados por la parte propietaria: ~ 1 mes de alquiler por adelantado. ~ 1 mes de dep\u00f3sito de garant\u00eda por cada a\u00f1o contratado. ~ De la fianza: garant\u00eda propietaria o sistema de garant\u00edas de cauci\u00f3n (Finaer / Fiancor). ~ De los ingresos: \u00faltimos tres (3) recibos de sueldo o certificaci\u00f3n de ingresos por contador p\u00fablico. \u00b7 Condiciones ofrecidas por la parte propietaria: ~ Duraci\u00f3n del contrato: 18 meses (contrato de alquiler temporario con muebles). ~ Actualizaci\u00f3n: ipc \u00b7 \u00cdndice de Precios al Consumidor publicado por el indec. ~ Periodicidad de actualizaci\u00f3n: Trimestral. #Nota: El edificio no cuenta con accesibilidad para personas con movilidad reducida (Ley 5115). Las im\u00e1genes en este anuncio publicadas son meramente ilustrativas y no poseen car\u00e1cter contractual. El importe de expensas anunciado ha sido extra\u00eddo de su \u00faltima facturaci\u00f3n, es orientativo, no vinculante y est\u00e1 sujeto a modificaciones y/o variaciones sin previa publicidad. Las medidas expresadas en el presente aviso son aproximadas y a t\u00edtulo informativo. Las medidas originales surgir\u00e1n de los respectivos planos y/o escritura del inmueble. El inmueble no es apto para mascotas por expresa solicitud de sus propietarios en el contrato de comercializaci\u00f3n. Somos especialistas en operaciones simult\u00e1neas. Tasamos en los 48 barrios de la Ciudad de Buenos Aires: . ar/tasaciones/spinelli propiedadeswww. spinelliprop. com. ar#Visitas por WhatsApp al +54 9 11 Ver datos#Reservas al Ver datos Ver datos#Consultas a Ver datos#Oficina en Avenida San Juan 3467 - cabadesde 1921 - #OportunidadesGrandesComoUnaCasa\nPublicado hace 3 d\u00edas\nContactar", "revised": false, "rejected": true, "data": {"precio": "$ 295.000", "expensas": "$ 33.800 Expensas", "direccion": "Avenida Boedo al 1300", "metros": "40 m\u00b2 tot.", "habitaciones": "2 amb.", "hace": "Publicado hace 3 d\u00edas"}}, "https://www.zonaprop.com.ar/propiedades/clasificado/alclapin-dto.-de-2-amb.-c-balcon-luminoso-1-piso-san-53559786.html": {"date": "05-05-2024\n", "content": "$ 350.000\n$ 38.000 Expensas\nDean Funes 1100 1\u00b0\nSan Cristobal, Capital Federal\n48 m\u00b2 tot.\n2 amb.\n1 dorm.\n1 ba\u00f1o\nExcelente ubicaci\u00f3n en la zona ya que tiene a 1 cuadra y media el subte E, varias l\u00edneas de colectivos y el acceso a la autopista 25 de mayo a tan solo 3 cuadras. Departamento de 2 ambientes con salida al balc\u00f3n desde el living - dormitorio con placard y ventanal- ba\u00f1o completo - cocina con ventanal y lavadero incorporado. Excelente luminosidad - pisos flotantes - el balc\u00f3n posee una baulera muy \u00fatil. *contrato de 1 a\u00f1o -aumento trimestral con indice icl. *servicios A abonar luz, gas, aysa, abl Y expensas (el valor de expensas publicado podra ser modificado) *garantia de caucion ingresar al link para ver si califica Y ahi tambien obtendra el calculador para ver el costo de la garantia (https: //respaldar. com. ar/formulario-express-44-inmobiliaria-377) *debe presentar recibos de sueldo A satisfaccion del locador. *dni. * deposito de 1 mes Y medio. * 1 mes de alquiler. *para los alquileres de vivienda en caba no deben abonar honorarios ley 5859. Comercializa Estudio Sorensen Mat. 2969 cucicba\nPublicado hace 5 d\u00edas\nContactar", "revised": false, "rejected": true, "data": {"precio": "$ 350.000", "expensas": "$ 38.000 Expensas", "direccion": "Dean Funes 1100 1\u00b0", "metros": "48 m\u00b2 tot.", "habitaciones": "2 amb.", "hace": "Publicado hace 5 d\u00edas"}}, "https://www.zonaprop.com.ar/propiedades/clasificado/alclapin-excelente-depto.-2-amb.-c-balcon-en-la-calle-moreno-al-53557995.html": {"date": "05-05-2024\n", "content": "$ 300.000\n$ 40.000 Expensas\nMORENO 3000\nBalvanera, Capital Federal\n40 m\u00b2 tot.\n2 amb.\n1 dorm.\n1 ba\u00f1o\nMuy lindo Departamento de 2 ambientes con balc\u00f3n en la calle Moreno al 3000, Balvanera. Consta de living-comedor con cocina incorporada 4. 40 x 5. 00, dormitorio con placard 2. 90 x 3. 00, ba\u00f1o completo 2. 00 x 1. 70, balc\u00f3n 4. 45 x 1. 00 y pasillo integrador 1. 70 x 1. 00. Superficie total 40 m2. Muy luminoso y en buen estado. A 3 cuadras de Av Rivadavia (Subte l\u00ednea A) y todos los transportes. A 3 cuadras de Av Jujuy (Subte l\u00ednea H). A 1 cuadra del Hospital Espa\u00f1ol y a 3 cuadras de Hopital Ramos Mej\u00eda. Alberto Daniel Marincola. cuciba N\u00b0 1898. \u201cPara los casos de alquiler de vivienda el monto m\u00e1ximo que se le puede requerir a los propietarios ser\u00e1 el equivalente al cuatro con quince cent\u00e9simos por ciento (4, 15%) del valor total del respectivo contrato. Se encuentra prohibido cobrar comisiones inmobiliarias y gastos de gestoria de informes a los inquilinos en el caso de ser personas f\u00edsicas. \u201d // Importante: el aviso publicado es al mero efecto informativo y no constituye una oferta ni solicitud de oferta o compra, ni una recomendaci\u00f3n de inversi\u00f3n, y se entiende que presenta informaci\u00f3n resumida, preliminar y no definitiva de un inmueble o negocio. Si el aviso contuviera estimaciones o proyecciones, se entender\u00e1 que las mismas son solo opiniones que reflejan expectativas de buena fe. Im\u00e1genes no contractuales. Medidas aproximadas. Los montos y porcentajes son valores de referencia y pueden variar sin previo aviso.\nPublicado hace 5 d\u00edas\nContactar", "revised": true, "rejected": true, "data": {"precio": "$ 300.000", "expensas": "$ 40.000 Expensas", "direccion": "MORENO 3000", "metros": "40 m\u00b2 tot.", "habitaciones": "2 amb.", "hace": "Publicado hace 5 d\u00edas"}, "comment": "Muy bien. Frio"}, "https://www.zonaprop.com.ar/propiedades/clasificado/alclapin-barrio-norte.-2-ambientes-amoblado.-french-2800.u$s-53560279.html": {"date": "05-05-2024\n", "content": "$ 630\nBarrio Norte, Capital Federal\n48 m\u00b2 tot.\n2 amb.\n1 dorm.\n1 ba\u00f1o\nFrench 2800. Excelente ubicaci\u00f3n Recoleta. Frente con balc\u00f3n. Heladera con freezer, cocina con lavarropas. Muy luminoso. Dormitorio 2 camas individuales. Aire acondicionado. Amoblado y equipado. Ba\u00f1o completo. Pisos parque. U$S 630 todo incluido. A 2 cuadras Avenida Santa Fe. Pleno Recoleta. Cerca Universidad Barcelo y Universidad Palermo.\nPublicado hace 4 d\u00edas\nContactar", "revised": false, "rejected": true, "data": {"precio": "$ 630", "direccion": "", "metros": "48 m\u00b2 tot.", "habitaciones": "2 amb.", "hace": "Publicado hace 4 d\u00edas"}}, "https://www.zonaprop.com.ar/propiedades/clasificado/alclapin-2amb-37-m-sup2--parquet!-gr-distrib!-lav-inc!-53560252.html": {"date": "05-05-2024\n", "content": "$ 260.000\n$ 37.523 Expensas\nMoreno 2900\nBalvanera, Capital Federal\n37 m\u00b2 tot.\n2 amb.\n1 dorm.\n1 ba\u00f1o\n\u00a1 2 ambientes bien distribuido! \u00a1 ubicaci\u00f3n funcional! #Departamento | #Est\u00e1ndar | #2amb | #Lateral | #BalvaneraMoreno 2900, Piso 4 - Ciudad Aut\u00f3noma de Buenos Aires\u00b7 Caracter\u00edsticas: ~ Departamento de dos (2) ambientes, dispuesto hacia el lateral, ubicado en la zona c\u00e9ntrica de la Ciudad de Buenos Aires. ~ Orientaci\u00f3n E (Este). Vista a pulm\u00f3n interior con apertura de luz. Ventilaci\u00f3n cruzada. Su estado de conservaci\u00f3n es excelente, listo para ser habitado. ~ A 125 metros Avenida Belgrano. A 125 metros de Avenida Jujuy. A 325 metros de Avenida Rivadavia. A 525 metros de Avenida Independencia. ~ Conectividad con medios de transporte. M\u00faltiples colectivos y subte/metro L\u00edneas A y H. Cercan\u00eda a subida/bajada Autopista (au) 25 de Mayo. ~ Su oferta comercial incluye actividades recreativas y culturales, locales gastron\u00f3micos, farmacias, paseos, instituciones m\u00e9dicas y educativas. \u00b7 Edificio: ~ Entre medianeras. Su fachada combina venecitas de color blanco liso con frentines de hormig\u00f3n pintado en verde musk. ~ Su planta baja (pb) se encuentra revestida en azulejos color blanco. Puerta de acceso de madera maciza con vidrio repartido. ~ Cuenta con 9 pisos. 5 departamentos por cada uno de sus pisos. 2 ascensores automatizados. Previsibles gastos de mantenimiento mensuales. \u00b7 Distribuci\u00f3n: ~ Hall de recepci\u00f3n (1. 00m x 2. 00m). ~ Living comedor (3. 00m x 4. 00m). ~ Cocina separada (3. 00m x 1. 50m). ~ Lavadero incorporado (1. 00m x 1. 50m). ~ Distribuidor (2. 00m x 1. 00m). ~ Ba\u00f1o completo con ba\u00f1era (1. 80m x 2. 00m). ~ Dormitorio (3. 00m x 3. 00m). \u00b7 Equipamiento: ~ Paredes pintadas en tonalidades claras conservan su natural luminosidad. Pisos revestidos en parquet pulido y plastificado en hall de recepci\u00f3n, living comedor, distribuidor y dormitorio. ~ Su cocina cuenta con pisos revestidos mosaicos gran\u00edticos color gris modelo nevado y paredes azulejadas en amarillo suave. ~ Mobiliario de cocina (bajo-mesada y alacenas) enchapado en melamina / mdf s\u00edmil madera. Mesada de acero inoxidable. Cocina a gas marca Zenith. Termotanque Se\u00f1orial. ~ Ba\u00f1o con pisos revestidos en mosaicos gran\u00edticos color negro modelo nevado y paredes revestidas en azulejos color gris petr\u00f3leo. Lavatorio, artefactos completos y ba\u00f1era instalados. ~ Cuenta con placard empotrado con puertas frontales, divisores, cajoneras, barrales y dem\u00e1s interiores a medida instalados en su dormitorio. \u00b7 Requisitos solicitados por la parte propietaria: ~ 1 mes de alquiler por adelantado. ~ 1 mes de dep\u00f3sito de garant\u00eda. ~ De la fianza: garant\u00eda propietaria o sistema de garant\u00edas de cauci\u00f3n (Finaer / Fiancor). ~ De los ingresos: \u00faltimos tres (3) recibos de sueldo o certificaci\u00f3n de ingresos por contador p\u00fablico. \u00b7 Condiciones ofrecidas por la parte propietaria: ~ Duraci\u00f3n del contrato: 12 meses (contrato de alquiler temporario sin muebles). ~ Actualizaci\u00f3n: ipc \u00b7 \u00cdndice de Precios al Consumidor publicado por el indec. ~ Periodicidad de actualizaci\u00f3n: Trimestral. #Nota: El edificio no cuenta con accesibilidad para personas con movilidad reducida (Ley 5115). Las im\u00e1genes en este anuncio publicadas son meramente ilustrativas y no poseen car\u00e1cter contractual. El importe de expensas anunciado ha sido extra\u00eddo de su \u00faltima facturaci\u00f3n, es orientativo, no vinculante y est\u00e1 sujeto a modificaciones y/o variaciones sin previa publicidad. Las medidas expresadas en el presente aviso son aproximadas y a t\u00edtulo informativo. Las medidas originales surgir\u00e1n de los respectivos planos y/o escritura del inmueble. El inmueble no es apto para mascotas por expresa solicitud de sus propietarios en el contrato de comercializaci\u00f3n. Somos especialistas en operaciones simult\u00e1neas. Tasamos en los 48 barrios de la Ciudad de Buenos Aires: . ar/tasaciones/spinelli propiedadeswww. spinelliprop. com. ar#Visitas por WhatsApp al +54 9 11 Ver datos#Reservas al Ver datos Ver datos#Consultas a Ver datos#Oficina en Avenida San Juan 3467 - cabadesde 1921 - #OportunidadesGrandesComoUnaCasa\nPublicado hace 3 d\u00edas\nContactar", "revised": false, "rejected": true, "data": {"precio": "$ 260.000", "expensas": "$ 37.523 Expensas", "direccion": "Moreno 2900", "metros": "37 m\u00b2 tot.", "habitaciones": "2 amb.", "hace": "Publicado hace 3 d\u00edas"}}, "https://www.zonaprop.com.ar/propiedades/clasificado/alclappa-luminoso-dpto-2-ambientes-con-2-balcones-53560180.html": {"date": "05-05-2024\n", "content": "$ 300.000\n$ 36.000 Expensas\nHumberto Primo 2796\nSan Cristobal, Capital Federal\n37 m\u00b2 tot.\n2 amb.\n1 dorm.\n1 ba\u00f1o\nAlquiler depto 2 ambientes -barrio san cristobal- Tenemos el agrado de presentarles este luminoso departamento de 2 ambientes que consta de: * Dormitorio con placard y balc\u00f3n al frente. * Living-comedor con balc\u00f3n al frente. * Cocina con artefacto de cocina y extractor. * Ba\u00f1o. * Lavadero. Cuenta con todos los servicios (gas, agua, luz), se encuentra ubicado en el barrio San Crist\u00f3bal pr\u00f3ximo (una cuadra) a la l\u00ednea H ( Estaci\u00f3n Jujuy) y a una cuadra de la l\u00ednea E (estaci\u00f3n Humberto Primo) del subterr\u00e1neo. Condiciones. Contrato por dos a\u00f1os con ajuste trimestral del ipc. Requisitos. Inquilino: dni, 2 \u00faltimos recibos de sueldo (recibo de sueldo superiores al valor de alquiler), servicio a su nombre. Garant\u00eda: garant\u00eda propietaria Caba, seguro de Cauci\u00f3n, o 4 garantes con recibos de sueldo (recibo superiores al valor de alquiler).\nPublicado hace 4 d\u00edas\nContactar", "revised": false, "rejected": true, "data": {"precio": "$ 300.000", "expensas": "$ 36.000 Expensas", "direccion": "Humberto Primo 2796", "metros": "37 m\u00b2 tot.", "habitaciones": "2 amb.", "hace": "Contactar"}}, "https://www.zonaprop.com.ar/propiedades/clasificado/alclappa-departamento-2-ambientes.-impecable-muy-luminoso-53556177.html": {"date": "05-05-2024\n", "content": "$ 260.000\n$ 50.000 Expensas\nAlmagro Norte, Almagro\n35 m\u00b2 tot.\n2 amb.\n1 dorm.\n1 ba\u00f1o\nDepartamento de dos ambientes, muy luminoso, Cocina completa con desayunador, ba\u00f1o completo. Ubicado en un 6 piso con vista a la calle. Excelente ubicaci\u00f3n, cerca de distintos medios de locomoci\u00f3n.\nPublicado hace 5 d\u00edas\nContactar", "revised": false, "rejected": true, "data": {"precio": "$ 260.000", "expensas": "$ 50.000 Expensas", "direccion": "", "metros": "35 m\u00b2 tot.", "habitaciones": "2 amb.", "hace": "Contactar"}}, "https://www.zonaprop.com.ar/propiedades/clasificado/alclappa-dueno-alquila-departamento-2-amb-53559353.html": {"date": "05-05-2024\n", "content": "$ 340.000\n$ 35.000 Expensas\nCastillo 549\nVilla Crespo, Capital Federal\n34 m\u00b2 tot.\n2 amb.\n1 dorm.\nPiso 14, excelente vista. 2 ambientes. 34 m2. Muy luminoso. Ventilaci\u00f3n cruzada. Living Comedor, armario, habitaci\u00f3n con placard, Cocina separada con muebles de bajo mesada y alacenas, Lavadero, Ba\u00f1o Completo. Expensas (abril) $ 45. 000. Contrato por 2 a\u00f1os, ajuste semestral x ipc. Condiciones: 1) 1 mes de alquiler por adelantado, 2) dep\u00f3sito en garant\u00eda 1 mes (se ajusta en la misma proporci\u00f3n y plazo que el alquiler), 3) acreditaci\u00f3n de ingresos, 4) garante propietario en caba o deposito de U$3000,\nPublicado hace 5 d\u00edas\nContactar", "revised": false, "rejected": true, "data": {"precio": "$ 340.000", "expensas": "$ 35.000 Expensas", "direccion": "Castillo 549", "metros": "34 m\u00b2 tot.", "habitaciones": "2 amb.", "hace": "Contactar"}}, "https://www.zonaprop.com.ar/propiedades/clasificado/alclappa-departamento-de-2-ambientes-en-alquiler-53553722.html": {"date": "05-05-2024\n", "content": "$ 280.000\nParque Centenario, Capital Federal\n36 m\u00b2 tot.\n2 amb.\n1 dorm.\n1 ba\u00f1o\nContrafrente muy luminoso con vista panor\u00e1mica al parque. F\u00e1cil acceso a transporte publico, subte y colectivo. Sobre Diaz V\u00e9lez a 1 cuadra de Jos\u00e9 Mar\u00eda Moreno. Cuenta con balc\u00f3n y lavadero cubierto\nPublicado hace 5 d\u00edas\nContactar", "revised": false, "rejected": true, "data": {"precio": "$ 280.000", "direccion": "", "metros": "36 m\u00b2 tot.", "habitaciones": "2 amb.", "hace": "Contactar"}}, "https://www.zonaprop.com.ar/propiedades/clasificado/alclapin-departamento-2-amb.-lateral-en-alquiler-53556976.html": {"date": "05-05-2024\n", "content": "$ 300.000\n$ 40.000 Expensas\nYapeyu al 100\nAlmagro, Capital Federal\n38 m\u00b2 tot.\n2 amb.\n1 dorm.\n1 ba\u00f1o\nComodo 2 ambientes lateral, luminoso Y ventilado, cocina, lavadero independiente, ba\u00f1o completo, dormitorio con placard, muy buen estado. -\nPublicado hace 5 d\u00edas\nContactar", "revised": false, "rejected": true, "data": {"precio": "$ 300.000", "expensas": "$ 40.000 Expensas", "direccion": "Yapeyu al 100", "metros": "38 m\u00b2 tot.", "habitaciones": "2 amb.", "hace": "Publicado hace 5 d\u00edas"}}, "https://www.zonaprop.com.ar/propiedades/clasificado/alclapin-depto-2-amb-en-alquiler-en-barrio-norte-charcas-2700-53551858.html": {"date": "05-05-2024\n", "content": "13\n$ 300.000\n$ 30.000 Expensas\nCHARCAS 2700. Entre Anchorena y Quirno costa\nBarrio Norte, Capital Federal\n55 m\u00b2 tot.\n2 amb.\n1 dorm.\n1 ba\u00f1o\nAlquiler de departamento de 2 ambientes en Barrio Norte. Primer piso. Living comedor con pisos de parquet y salida a patio interno con lavadero incorporado. Dormitorio con pisos de parquet con amplio placard y salida a segundo patio interno. Cocina completa. Ba\u00f1o completo con ba\u00f1era. A 100 metros de Av. Santa F\u00e9 y 200 metros de Av. Pueyrredon. Transportes cercanos: Subte: Ag\u00fcero (L\u00ednea D), Pueyrredon (L\u00ednea D), C\u00f3rdoba (L\u00ednea H), Santa Fe (L\u00ednea H). Colectivos: 12, 29, 39, 41, 57, 61, 62, 64, 68, 99, 101, 106, 109, 111, 118, 132, 140, 152, 188, 194. Mat. N\u00ba 2798 cucicba. \"Para los casos de alquiler de vivienda, el monto m\u00e1ximo de comisi\u00f3n que se le puede requerir a los propietarios ser\u00e1 el equivalente al cuatro con quince cent\u00e9simos por ciento (4, 15%) del valor total del respectivo contrato. Se encuentra prohibido cobrar a los inquilinos que sean personas f\u00edsicas comisiones inmobiliarias y gastos de gestor\u00eda de informes\". -xintel(cob-cob-564) [apto garantia finaer]\nDestacado\nPublicado hace 5 d\u00edas\nContactar", "revised": false, "rejected": true, "data": {"precio": "$ 300.000", "expensas": "$ 30.000 Expensas", "direccion": "CHARCAS 2700. Entre Anchorena y Quirno costa", "metros": "55 m\u00b2 tot.", "habitaciones": "2 amb.", "hace": "Destacado\nPublicado hace 5 d\u00edas"}}, "https://www.zonaprop.com.ar/propiedades/clasificado/alclapin-alquiler-departamento-2-ambientes-$325.000.-sanchez-53551147.html": {"date": "05-05-2024\n", "content": "$ 325.000\n$ 47.000 Expensas\nAlmagro Sur, Almagro\n37 m\u00b2 tot.\n2 amb.\n1 dorm.\n1 ba\u00f1o\nDepartamento en alquiler en un segundo piso por ascensor con disposici\u00f3n contrafrente, vista abierta s\u00faper luminoso. Ubicado en la calle S\u00e1nchez de Loria al 500 a metros de la Av Belgrano. Cocina independiente con alacenas altas y bajas, mesada y bacha de acero inoxidable. Mesa rebatible, cocina de 4 hornallas + horno a gas. Calef\u00f3n. Lavadero independiente con pileta y conexi\u00f3n para lavarropas. Ba\u00f1o completo con ba\u00f1adera. Habitaci\u00f3n con placard empotrado en pared, ventana y Aire acondicionado fr\u00edo calor. Comedor con pisos de madera y ventana al exterior. Requisitos: contrato por 2 a\u00f1os. demostraci\u00f3n de ingresos. Seguro de Cauci\u00f3n. Mascotas consultar. Indexaci\u00f3n trimestral por ipc. El ingreso al edificio no cuenta con rampa de acceso para personas con movilidad reducida. Ley 5859 art 5 para los casos de alquiler de vivienda, el monto m\u00e1ximo de comisi\u00f3n que se le puede requerir a los propietarios es el equivalente al 4, 15% del total del contrato. Se encuentra prohibido cobrar comisiones a los inquilinos que sean personas f\u00edsicas. El departamento se alquila sin muebles. Las fotos de la publicaci\u00f3n: el mobiliario no est\u00e1 incluido. El departamento se entrega vac\u00edo. Se deja constancia que las medidas, superficies, m2 y proporciones consignadas son aproximados, al igual que las medidas parciales y/o de los ambientes esta sujeto a verificaci\u00f3n y/o ajuste. El valor indicado de expensas esta sujeto a variaci\u00f3n. El precio del inmueble puede ser modificado sin previo aviso. Fotos de car\u00e1cter no contractual. Aviso legal: Se hace saber que las caracter\u00edsticas descriptas del inmueble publicado, calidades y cualidades constructivas y funcionales, valores de los impuestos y servicios, y medidas y superficies, son aproximados y consignadas en base a datos que fueron proporcionados por el propietario y que pueden no ser exactos y/o estar actualizados a la hora de la visualizaci\u00f3n de este aviso, pudiendo surgir discordancias con los datos que surgen de la documentaci\u00f3n respectiva. Las medidas y superficies exactas son las que surgen de los t\u00edtulos y planos legales del inmueble. Las im\u00e1genes publicadas lo son a mero efecto orientativo de las caracter\u00edsticas generales y circunstancias del inmueble en el momento que fueron tomadas, pudiendo diferir del estado actual del mismo. Asimismo los mobiliarios, accesorios, elementos, etc, que se visualicen en la imagen no integran la oferta. En todo los casos el interesado deber\u00e1 efectuar una visita al inmueble y efectuar la verificaci\u00f3n previamente a cualquier operaci\u00f3n, requiriendo la documentaci\u00f3n que corresponda. En cumplimiento con las leyes que regulan el corretaje inmobiliario, todas las operaciones inmobiliarias son objeto de intermediaci\u00f3n y conclusi\u00f3n por parte del matriculado, cuyos datos se exhiben debajo del nombre de la inmobiliaria. La informaci\u00f3n gr\u00e1fica y escrita contenida en el presente aviso como son; las medidas, superficies, valores de expensas, antig\u00fcedad, cualidades constructivas, valor de impuestos y servicios es meramente a t\u00edtulo estimativo y no forma parte ning\u00fan tipo de documentaci\u00f3n contractual. Las medidas y superficies definitivas surgir\u00e1n del t\u00edtulo de propiedad del inmueble referido. Asimismo, los importes de impuestos, tasas, servicios y expensas aqu\u00ed indicados est\u00e1n sujetos a verificaci\u00f3n por parte del potencial comprador. El valor del inmueble indicado en el presente puede ser modificado sin previo aviso. Operaci\u00f3n supeditada a que el propietario cumplimente con la R. G. N\u00b0 2371/07 de la afip. Accesibilidad: si (Ley 5. 115). Ley 10. 973 de la Prov. Bs. As. , Ley 22. 802 de Lealtad Comercial, Ley 24. 240 de Defensa al Consumidor, las normas del C\u00f3digo Civil y Comercial de la Naci\u00f3n y Constitucionales, los agentes no ejercen el corretaje inmobiliario. Todas las operaciones inmobiliarias son concluidas por los martilleros y corredores colegiados, cuyos datos se exhiben debajo del. Colectivos: 2, 5, 7, 8, 31, 32, 41, 56, 75, 84, 86, 88, 96, 98, 101, 103, 115, 128, 129, 132, 160, 164, 180\nPublicado hace 3 d\u00edas\nContactar", "revised": true, "rejected": false, "data": {"precio": "$ 325.000", "expensas": "$ 47.000 Expensas", "direccion": "", "metros": "37 m\u00b2 tot.", "habitaciones": "2 amb.", "hace": "Publicado hace 3 d\u00edas"}, "comment": "Muy bien!"}, "https://www.zonaprop.com.ar/propiedades/clasificado/alclapin-amplio-2-ambientes-con-cochera-53546671.html": {"date": "05-05-2024\n", "content": "$ 350.000\n$ 140.000 Expensas\nFrancisco Acu\u00f1a Figueroa 900\nAlmagro, Capital Federal\n50 m\u00b2 tot.\n2 amb.\n1 dorm.\n1 ba\u00f1o\n1 coch.\n-Amplio 2 ambientes con cochera. -Muy luminoso. -Servicios Individuales. -Balc\u00f3n Corrido. -Cocina y ba\u00f1o completo.\nPublicado hace 6 d\u00edas\nContactar", "revised": false, "rejected": true, "data": {"precio": "$ 350.000", "expensas": "$ 140.000 Expensas", "direccion": "Francisco Acu\u00f1a Figueroa 900", "metros": "50 m\u00b2 tot.", "habitaciones": "2 amb.", "hace": "Publicado hace 6 d\u00edas"}}, "https://www.zonaprop.com.ar/propiedades/clasificado/alclapin-cordoba-y-gallo-2-amb-piso-14-muy-luminoso-excelente-53550227.html": {"date": "05-05-2024\n", "content": "$ 350.000\n$ 19.200 Expensas\nCordoba 3280\nBarrio Norte, Capital Federal\n40 m\u00b2 tot.\n2 amb.\n1 dorm.\n1 ba\u00f1o\nCordoba y Gallo 2 amb piso 14 muy Luminoso excelente estado cocina y ba\u00f1o completo, espacio para lavarropas, vestidor\nPublicado hace 6 d\u00edas\nContactar", "revised": false, "rejected": true, "data": {"precio": "$ 350.000", "expensas": "$ 19.200 Expensas", "direccion": "Cordoba 3280", "metros": "40 m\u00b2 tot.", "habitaciones": "2 amb.", "hace": "Publicado hace 6 d\u00edas"}}, "https://www.zonaprop.com.ar/propiedades/clasificado/alclapin-departamento-en-alquiler-dos-ambientes-al-lateral-de-53549556.html": {"date": "05-05-2024\n", "content": "$ 270.000\n$ 19.600 Expensas\nAvenida San Juan 3968\nBoedo, Capital Federal\n31 m\u00b2 tot.\n2 amb.\n1 dorm.\n1 ba\u00f1o\nDepartamento en alquiler dos ambientes de 31 mts2 cubiertos Y totales al lateral de vista abierta en tercer piso de edificio. Living comedor con amplio placard en pared, balc\u00f3n tipo franc\u00e9s, cocina independiente de muebles completos Y lavadero incorporado. Dormotorio con ventana Y placard en pared, ba\u00f1o completo. Las expensas incuyen el servicio agua. Av. San juan al 3900, entre castro Y quintino bocayuba. A cuatro cuadras del subterr\u00e1neo linea E, estaci\u00f3n boedo. Contrato de dos a\u00f1os. Aumento trimestral ipc. Cucicba Mat. 94.\nPublicado hace 6 d\u00edas\nContactar", "revised": false, "rejected": true, "data": {"precio": "$ 270.000", "expensas": "$ 19.600 Expensas", "direccion": "Avenida San Juan 3968", "metros": "31 m\u00b2 tot.", "habitaciones": "2 amb.", "hace": "Publicado hace 6 d\u00edas"}}, "https://www.zonaprop.com.ar/propiedades/clasificado/alclapin-2-amb-guemes-y-av-coronel-diaz-frente-c.-a.-b.-a.-53547590.html": {"date": "05-05-2024\n", "content": "$ 280.000\n$ 34.000 Expensas\nGUEMES 3200\nBarrio Norte, Capital Federal\n34 m\u00b2 tot.\n2 amb.\n1 dorm.\n1 ba\u00f1o\nSilver propiedades ofrece un departamento de 2 ambientes en alquiler. Excelente ubicacion! Sobre la calle guemes entre av. Coronel diaz Y billinghurst, cerca de av. Santa fe (subte linea D), shopping alto palermo. 5to piso al frente, muy luminoso. Living comedor, dormitorio al frente con 2 placards amplios, cocina con lugar para lavarropas Y heladera, ba\u00f1o completo en suite. pisos de parquet roble. Impecable estado!\nPublicado hace 6 d\u00edas\nContactar", "revised": true, "rejected": false, "data": {"precio": "$ 280.000", "expensas": "$ 34.000 Expensas", "direccion": "GUEMES 3200", "metros": "34 m\u00b2 tot.", "habitaciones": "2 amb.", "hace": "Publicado hace 6 d\u00edas"}, "comment": "Bien. Sin balcon"}, "https://www.zonaprop.com.ar/propiedades/clasificado/alclapin-departamento-2-ambientes-en-parque-patricios-53548583.html": {"date": "05-05-2024\n", "content": "$ 280.000\nLuna 127 1\u00ba C\nParque Patricios, Capital Federal\n55 m\u00b2 tot.\n2 amb.\n1 dorm.\n1 ba\u00f1o\nambientes 1\u00ba piso por escaleraLiving Comedor con Aire Acondicionado splitDormitorio con placardCocina completa, con muebles bajomesada y alacenasBa\u00f1o completo. Patio con pileta de lavar. \u201cPara los casos de alquiler de vivienda, el monto m\u00e1ximo de comisi\u00f3n que se le puederequerir a los propietarios ser\u00e1 el equivalente al cuatro con quince cent\u00e9simos porciento (4, 15%) del valor total del respectivo contrato. Se encuentra prohibido cobrar alos inquilinos que sean personas f\u00edsicas comisiones inmobiliarias y gastos de gestor\u00edade informes\u201dNo cumple con Ley 5115 (accesibilidad)\nPublicado hace 6 d\u00edas\nContactar", "revised": true, "rejected": false, "data": {"precio": "$ 280.000", "direccion": "Luna 127 1\u00ba C", "metros": "55 m\u00b2 tot.", "habitaciones": "2 amb.", "hace": "Publicado hace 6 d\u00edas"}, "comment": "Muy bien. Frio"}, "https://www.zonaprop.com.ar/propiedades/clasificado/alclapin-departamento-dos-ambientes-en-alquiler-parque-53551368.html": {"date": "05-05-2024\n", "content": "11\n$ 290.000\n$ 34.000 Expensas\nWarnes 2\u00b0\nVilla Crespo, Capital Federal\n39 m\u00b2 tot.\n2 amb.\n1 dorm.\n1 ba\u00f1o\nDos ambientes en alquiler contrafrente luminoso. Living comedor. dormitorio con placard. Ba\u00f1o. Cocina y lavadero. Requisitos: dep\u00f3sito de garant\u00eda. ingresos demostrables acordes al alquiler. seguro de cauci\u00f3n, garantia propietaria familiar directo. Actualizacion cuatrimestral ipc. Transportes Cercanos. Colectivos: 15, 19, 24, 36, 42, 55, 57, 65, 71, 76, 90, 92, 99, 105, 106, 109, 110, 119, 124, 127, 135, 141, 146\nPublicado hace 6 d\u00edas\nContactar", "revised": false, "rejected": true, "data": {"precio": "$ 290.000", "expensas": "$ 34.000 Expensas", "direccion": "Warnes 2\u00b0", "metros": "39 m\u00b2 tot.", "habitaciones": "2 amb.", "hace": "Publicado hace 6 d\u00edas"}}, "https://www.zonaprop.com.ar/propiedades/clasificado/alclappa-departamento-de-2-ambientes-en-alquiler-en-almagro-53542897.html": {"date": "05-05-2024\n", "content": "$ 220.000\n$ 50.000 Expensas\nSarmiento 4226\nAlmagro, Capital Federal\n32 m\u00b2 tot.\n2 amb.\n1 dorm.\n1 ba\u00f1o\nC\u00f3modo departamento de 2 ambientes en el Barrio de Almagro a mts. Estaciones subte linea B, estaciones Medrano y Angel Gallardo. El departamento posee living comedor con placard embutido, dormitorio con mucha luminosidad, y ba\u00f1o completo con ba\u00f1era. La cocina es independiente y de buenas dimensiones. Todos los ambientes son ventilados. Pisos de parquet. Condiciones: Ajustes trimestrales seg\u00fan ipc - Deposito: u$s 220. A cargo del inquilino: Agip-abl, Aysa, luz, gas y expensas Ordinarias. A cargo del propietario: Expensas extraordinarios. Plazo de contrato: 2 a\u00f1os. Garant\u00eda Propietaria o Recibos de sueldo\nPublicado hace 6 d\u00edas\nContactar", "revised": true, "rejected": false, "data": {"precio": "$ 220.000", "expensas": "$ 50.000 Expensas", "direccion": "Sarmiento 4226", "metros": "32 m\u00b2 tot.", "habitaciones": "2 amb.", "hace": "Publicado hace 6 d\u00edas"}, "comment": "Barato. Lo \u00fanico bueno"}, "https://www.zonaprop.com.ar/propiedades/clasificado/alclappa-excelente-departamento-dueno-directo-uade-uai-53551352.html": {"date": "05-05-2024\n", "content": "$ 350.000\n$ 50.000 Expensas\nAv. San Juan 1445\nMonserrat, Capital Federal\n52 m\u00b2 tot.\n2 amb.\n1 dorm.\n1 ba\u00f1o\nDue\u00f1o directo! Excelente dpto de 48m2 sobre Av. San Juan al 1400 - Monoambiente con divisi\u00f3n con puerta, balc\u00f3n, aire acondicionado, conexi\u00f3n lavarropa, pileta y parrilla. Apto Estudiantes / Profesionales / Particulares. Piso N\u00ba 2 muy luminoso. A 1 (una) cuadra del Subte \"E\", estaci\u00f3n san jose. Pr\u00f3ximo a la uade y uai, a pasos de 9 de Julio y Cerrito. Muchos medios de transportes. Amenities: Piscina y sum. Incluye aire acondicionado frio y calor. Requisitos: Deposito, mes de alquiler adelantado, Garant\u00eda propietaria y/o recibos de sueldo Acreditaci\u00f3n de ingresos comprobables con certificado de trabajo actual y dos garantes con recibos de sueldo. En caso de no tener lo anterior se puede ingresar con meses como garant\u00eda. Aumento trimestral por ipc. Contrato de locaci\u00f3n a 12 meses o 24 meses.\nPublicado hace 6 d\u00edas\nContactar", "revised": false, "rejected": true, "data": {"precio": "$ 350.000", "expensas": "$ 50.000 Expensas", "direccion": "Av. San Juan 1445", "metros": "52 m\u00b2 tot.", "habitaciones": "2 amb.", "hace": "Contactar"}}, "https://www.zonaprop.com.ar/propiedades/clasificado/alclapin-av-jujuy-y-av-belgrano-2-ambientes-super-luminoso-53542530.html": {"date": "05-05-2024\n", "content": "$ 285.000\n$ 55.000 Expensas\nAv. Jujuy 300\nBalvanera, Capital Federal\n42 m\u00b2 tot.\n2 amb.\n1 dorm.\n1 ba\u00f1o\nMuy buena ubicacion, buenos medios de transporte publico, A metros de la estacion de subte linea \u00a8 H\u00a8. - el departamento es muy luminoso, living comedor con salida el balcon, dormitorio con placard, cocina hecha A nuevo, con lugar para el lavarropa, ba\u00f1o completo. -requisitos: 1 mes de deposito, 1 mes A delantado, demostracion de ingresos en forma fehacient E, garantia propietaria O seguro de caucion de finaer. -\nSuper destacado\nPublicado hace 6 d\u00edas\nContactar", "revised": false, "rejected": true, "data": {"precio": "$ 285.000", "expensas": "$ 55.000 Expensas", "direccion": "Av. Jujuy 300", "metros": "42 m\u00b2 tot.", "habitaciones": "2 amb.", "hace": "Super destacado\nPublicado hace 6 d\u00edas"}}, "https://www.zonaprop.com.ar/propiedades/clasificado/alclapin-2-ambientes-con-balcon-frances-amoblado-en-almagro-53542751.html": {"date": "05-05-2024\n", "content": "$ 320.000\n$ 50.000 Expensas\nBillinghurst 400\nAlmagro, Capital Federal\n36 m\u00b2 tot.\n2 amb.\n1 dorm.\n1 ba\u00f1o\nAlquiler de departamento 2 ambientes amoblado en almagro, capital federal. Lindo departamento de 2 ambientes totalmente amoblado como figura en las fotos con cocina integrada, balc\u00f3n frances, piso 5. Ubicado a media cuadra de la importante Avenida Corrientes, a metros de innumerables lineas de colectivo. Aclaraci\u00f3n: Propietario no acepta perros. - Contacto para Visitas: Para agendar una visita, comun\u00edcate por WhatsApp al Ver datos o al Ver datos. - Contrato 2 a\u00f1os. Requisitos: 1) Contar con garant\u00eda propietaria (el propietario no acepta seguro de cauci\u00f3n) ; 2) Contar con ingresos demostrables; 3) Contrato 2 a\u00f1os; 4) Actualizaci\u00f3n trimestral ipc; 5) Deposito, 6) un mes de adelanto y 7) Contratar seguro contra incendios. - avisos legales: 1) Se encuentra prohibido cobrar comisiones inmobiliarias y gastos de gestor\u00eda de informes a los inquilinos que sean personas f\u00edsicas. Para los casos de alquiler de vivienda, el monto m\u00e1ximo de comisi\u00f3n que se le puede requerir a los propietarios ser\u00e1 el equivalente al cuatro con quince cent\u00e9simos por cientos (4, 15%) del valor total del respectivo contrato. 2) Las descripciones arquitect\u00f3nicas y funcionales, valores de expensas, impuestos y servicios, fotos y medidas de este inmueble son aproximados. Los datos fueron proporcionados por el propietario y pueden no estar actualizados a la hora de la visualizaci\u00f3n de este aviso por lo cual puede arrojar inexactitudes y discordancias con las que surgen de las facturas, t\u00edtulos y planos legales del inmueble. El interesado debe realizar las verificaciones respectivas previamente a la realizaci\u00f3n de cualquier operaci\u00f3n, requiriendo por si o sus profesionales las copias necesarias de la documentaci\u00f3n que corresponda. corredores inmobiliarios: Juan Carlos Sardi Cucicba 2174 Luciano Lance Cucicba 2173xintel(mup-mup-908)\nPublicado hace 6 d\u00edas\nContactar", "revised": false, "rejected": true, "data": {"precio": "$ 320.000", "expensas": "$ 50.000 Expensas", "direccion": "Billinghurst 400", "metros": "36 m\u00b2 tot.", "habitaciones": "2 amb.", "hace": "Publicado hace 6 d\u00edas"}}, "https://www.zonaprop.com.ar/propiedades/clasificado/alclapin-departamento-2-ambientes.-tucuman-al-1500-53542484.html": {"date": "05-05-2024\n", "content": "$ 350.000\nTucum\u00e1n 1500. Entre Paran\u00e1 y Montevideo\nBarrio Norte, Capital Federal\n35 m\u00b2 tot.\n2 amb.\n1 dorm.\nAlquiler temporario de Departamento en Barrio Norte, Capital Federalxintel(mdt-mdt-1860)\nPublicado hace 6 d\u00edas\nContactar", "revised": false, "rejected": true, "data": {"precio": "$ 350.000", "direccion": "Tucum\u00e1n 1500. Entre Paran\u00e1 y Montevideo", "metros": "35 m\u00b2 tot.", "habitaciones": "2 amb.", "hace": "Publicado hace 6 d\u00edas"}}, "https://www.zonaprop.com.ar/propiedades/clasificado/alclappa-dueno-alquila-departamento-2-ambientes-congreso-53542497.html": {"date": "05-05-2024\n", "content": "$ 280.000\n$ 75.000 Expensas\nAv. de Mayo & Santiago del Estero\nCongreso, Capital Federal\n43 m\u00b2 tot.\n2 amb.\n1 dorm.\n1 ba\u00f1o\nExcelente edificio ubicado sobre Av. De Mayo, vecino a emblem\u00e1ticos edificios de Buenos Aires (Palacio Barolo, Diario Cr\u00edtica, Caf\u00e9 Tortoni, etc. ) ; a dos cuadras de Av. 9 de Julio y dos de Plaza Congreso. Inmejorable comunicaci\u00f3n con toda la Capital Federal: a escasos metros de estaci\u00f3n S\u00e1enz Pe\u00f1a de subte l\u00ednea A; 2 cuadras del metrob\u00fas y numerosas l\u00edneas de colectivos en los alrededores del edificio. Seguridad las 24 hs. Luminoso - 3er piso. 43 m2 (ambientes de buenas dimensiones) Agua caliente central. Ba\u00f1o y cocina completos. Lavadero independiente c/ instalaci\u00f3n para lavarropas. Habitaci\u00f3n con amplio placard. Departamento en excelente estado de conservaci\u00f3n. Condiciones: Alquiler $280. 000 ajustable cada 3 meses seg\u00fan el icl del Banco Central. Expensas $75. 000. Contrato a 2 a\u00f1os. abl y servicios a cargo del inquilino. Requisitos: Un mes de adelanto. Dep\u00f3sito en garant\u00eda: un mes y medio del importe del alquiler. Garant\u00eda: propiedad inmueble en caba \u00f3 Pcia. De BsAs (m\u00e1s gastos administrativos por informes de dominio e inhibici\u00f3n de la prop. En garant\u00eda) Dado que somos propietarios del departamento no hay gastos por intermediaci\u00f3n de inmobiliarias ni comisiones por tr\u00e1mites y/o firma del contrato\nPublicado hace 6 d\u00edas\nContactar", "revised": false, "rejected": true, "data": {"precio": "$ 280.000", "expensas": "$ 75.000 Expensas", "direccion": "Av. de Mayo & Santiago del Estero", "metros": "43 m\u00b2 tot.", "habitaciones": "2 amb.", "hace": "Contactar"}}, "https://www.zonaprop.com.ar/propiedades/clasificado/alclappa-departamento-de-2-ambientes.-sin-expensas.-monserrat.-53542069.html": {"date": "05-05-2024\n", "content": "$ 260.000\nM\u00e9xico 1500\nMonserrat, Capital Federal\n40 m\u00b2 tot.\n2 amb.\n1 dorm.\n1 ba\u00f1o\nCaracter\u00edsticas de la unidad: Es un departamento de dos ambientes ubicado en un tercer piso por escalera, al contrafrente. Consta de un living comedor, un dormitorio, un ba\u00f1o y una cocina. No posee balc\u00f3n. No posee expensas. Valor del alquiler: $260. 000. Garant\u00eda: Se acepta garant\u00eda laboral, inmobiliaria, y/o bancaria (seguro de cauci\u00f3n). Gran cantidad de l\u00edneas de colectivos: 6, 50, 150, 168, 151, 60, 37, 29, 12, 2 y subtes: A, B, C, E. Las medidas son aproxiamdas, se informaran las definitivas al momento del contrato. Para m\u00e1s informaci\u00f3n comunicarse al siguiente mail: Ver datos\nPublicado hace 7 d\u00edas\nContactar", "revised": true, "rejected": false, "data": {"precio": "$ 260.000", "direccion": "M\u00e9xico 1500", "metros": "40 m\u00b2 tot.", "habitaciones": "2 amb.", "hace": "Contactar"}, "comment": "Barato y buen barrio "}, "https://www.zonaprop.com.ar/propiedades/clasificado/alclappa-alquiler-2-ambientes-planta-baja-53542561.html": {"date": "05-05-2024\n", "content": "$ 330.000\nMaza 100\nAlmagro Sur, Almagro\n38 m\u00b2 tot.\n2 amb.\n1 dorm.\n1 ba\u00f1o\nAtenci\u00f3n leer bien. debido A las estafas, no se pide se\u00f1a de ning\u00fan tipo para ver \u00e9l departamento. Se nuestra el mi\u00e9rcoles 1 feriado de 13hrs. A 16hrs. Se alquila dto. En el barrio de Almagro, maza al 100 a una cuadra de Av Rivadavia, es un dos ambientes c/ gran Placard a la calle, cocina separada, ba\u00f1o grande, conexi\u00f3n para lavarropas, con patio, una parte del patio que ser\u00edan 4 mtrs cuadrado, est\u00e1n cerrados con mamparas como se ve en las fotos. Requisitos. El alquiler es para una o dos personas adultas no m\u00e1s. Se acepta una mascota chica o mediana. Contrato por 2 a\u00f1os. Aumento cada 6 meses, con el \u00edndice de ipc. El valor es de $330. 000,, incluye expensas, abl, Aysa, Luz y gas quedan a cargo del inquilino. Presentar documentos de las personas a alquilar y vivir en el dto. Garant\u00eda de capital federal, o pueden dejar dos mes m\u00e1s como garant\u00eda. Recibos de sueldo. Un mes de alquiler. Uno de dep\u00f3sito. No recibo se\u00f1a al momento de verlo, solo al entregar la documentaci\u00f3n para realizar el contrato. Se pide una se\u00f1a de 30. 000$ para averiguar todo, si saltar\u00e1 que la garant\u00eda es comprada, i recibos truchos pierden la se\u00f1a, cualquier duda por privado. Si los recibos de sueldo o garant\u00eda, saltar\u00e1 que son truchos pierde la se\u00f1a. Un mes de alquiler $330. 000. Un mes dep\u00f3sito. $330. 000. Solo WhatsApp Ver datos para pasar la direcci\u00f3n exacta\nPublicado hace 6 d\u00edas\nContactar", "revised": false, "rejected": true, "data": {"precio": "$ 330.000", "direccion": "Maza 100", "metros": "38 m\u00b2 tot.", "habitaciones": "2 amb.", "hace": "Contactar"}}, "https://www.zonaprop.com.ar/propiedades/clasificado/alclappa-2-ambientes-super-patio-parque-centenario.-cerca-53541829.html": {"date": "05-05-2024\n", "content": "$ 350.000\n$ 53.000 Expensas\nPotos\u00ed 4456\nParque Centenario, Capital Federal\n50 m\u00b2 tot.\n2 amb.\n1 dorm.\n1 ba\u00f1o\n* Due\u00f1o directo. * Edificio de per\u00edmetro libre con seguridad. * 1er piso contrafrente. * Living con aire acondicionado tipo split. * Habitaci\u00f3n con ventilador de techo. * Ba\u00f1o y cocina completos. * Reci\u00e9n pintado. * Espectacular patio con vista abierta. * Se aceptan mascotas. * Requisitos de ingreso: mes adelantado, dep\u00f3sito equivalente a un mes de alquiler en d\u00f3lar billete, recibo de sueldo o comprobante de ingresos del inquilino, garant\u00eda propietaria de caba, seguro de cauci\u00f3n o garantes personas con recibo de sueldo que tripliquen el monto del alquiler. * Aumentos trimestrales seg\u00fan ipc. * El alquiler no incluye los muebles que se ven en las fotos.\nPublicado hoy\nContactar", "revised": true, "rejected": false, "data": {"precio": "$ 350.000", "expensas": "$ 53.000 Expensas", "direccion": "Potos\u00ed 4456", "metros": "50 m\u00b2 tot.", "habitaciones": "2 amb.", "hace": "Contactar"}}, "https://www.zonaprop.com.ar/propiedades/clasificado/alclappa-dueno-alquila-2-ambientes-luminosos-con-balcon-en-53542450.html": {"date": "05-05-2024\n", "content": "$ 300.000\n$ 38.000 Expensas\nQuito 4035\nAlmagro Sur, Almagro\n43 m\u00b2 tot.\n2 amb.\n1 dorm.\n1 ba\u00f1o\n\u00a1Alquila hermoso departamento de 2 ambientes en Almagro! Ubicaci\u00f3n privilegiada: * A 3 cuadras Av. Rivadavia, a 4 cuadras de Av. La Plata y a 4 cuadras de Av. Independencia. * Rodeado de comercios, supermercados, restaurantes, caf\u00e9s, cines, colegios y bancos. * Cerca de colectivos: 2, 5, 7, 8, 15, 26, 56, 65, 84, 85, 86, 88, 96, 103, 104, 105, 119, 127, 128, 132, 160, 181. * A 5 cuadras de la estaci\u00f3n Castro Barros (Subte A). Caracter\u00edsticas del departamento: * Muy luminoso y ventilado. * Reci\u00e9n pintado paredes y puertas. * Dormitorio con estufa tiro balanceado, ventilador de techo, cortinas Roller nuevas y amplio placar empotrado. * Living con desayunador, cortinas Roller nuevas y aire acondicionado fr\u00edo/calor. * Cocina concepto abierto con muebles bajo mesada y alacena. * Ba\u00f1o completo con ba\u00f1era y mampara. * Primer piso al frente, con balc\u00f3n a la calle y cerramiento. * Edificio con ascensor, terraza, lavadero y espacio para residuos. condiciones del alquiler: * Contrato a 2 a\u00f1os. * Precio: 300Mil Pesos. * Expensas bajas: 38Mil (abril 2024) requisitos: * Garant\u00eda propietaria de familiar directo en caba (excluyente) * Recibo de sueldo acorde al alquiler. * Un mes de alquiler adelantado. * Un mes de dep\u00f3sito (se devuelve al finalizar el contrato) * no se permiten mascotas. \u00a1No te pierdas esta oportunidad! Para coordinar visita Contactar por WhatsApp: ii4I59-3499. \u00a1Muchas gracias!\nPublicado hace 7 d\u00edas\nContactar", "revised": false, "rejected": true, "data": {"precio": "$ 300.000", "expensas": "$ 38.000 Expensas", "direccion": "Quito 4035", "metros": "43 m\u00b2 tot.", "habitaciones": "2 amb.", "hace": "Contactar"}}, "https://www.zonaprop.com.ar/propiedades/clasificado/alclapin-departamento-de-2-ambientes-en-alquiler-en-villa-53539316.html": {"date": "05-05-2024\n", "content": "$ 350.000\nCASTILLO 500\nVilla Crespo, Capital Federal\n35 m\u00b2 tot.\n2 amb.\n1 dorm.\n1 ba\u00f1o\n2 luminosos ambientes con vista panoramica 2 aires acondic muy buenos placards proximo avenidas Y diversos medio de transportes castillo al 500 informes Ver datosComercializa Migliorisi de Corrientes 5500 srl Profesional responsable Diego F Migliorisi cpi263. Ver datos Se deja constancia que las caracteristicas, medidas, expensas y superficies consignadas son aproximadas, sujetos a verificaci\u00f3n y/o ajuste. El precio del inmueble puede ser modificado sin previo aviso. Fotos de car\u00e1cter no contractual. Las unidades publicadas est\u00e1n sujetas a disponibilidad. . Publicado por Migliorisi Villa Crespo a traves de Inmomap\nPublicado hace 8 d\u00edas\nContactar", "revised": false, "rejected": true, "data": {"precio": "$ 350.000", "direccion": "CASTILLO 500", "metros": "35 m\u00b2 tot.", "habitaciones": "2 amb.", "hace": "Publicado hace 8 d\u00edas"}}, "https://www.zonaprop.com.ar/propiedades/clasificado/alclappa-2-ambientes-luminosos-al-frente-con-balcon-53541499.html": {"date": "05-05-2024\n", "content": "$ 350.000\n$ 50.000 Expensas\nRamirez de Velasco 25\nVilla Crespo, Capital Federal\n45 m\u00b2 tot.\n2 amb.\n1 dorm.\n1 ba\u00f1o\nEs un departamento de 2 ambientes muy bien ubicado, al frente con balcon corrido muy luminoso, aire acondicionado en el living, cocina independiente con lavadero incorporado\nPublicado hace 7 d\u00edas\nContactar", "revised": false, "rejected": true, "data": {"precio": "$ 350.000", "expensas": "$ 50.000 Expensas", "direccion": "Ramirez de Velasco 25", "metros": "45 m\u00b2 tot.", "habitaciones": "2 amb.", "hace": "Contactar"}}, "https://www.zonaprop.com.ar/propiedades/clasificado/alclappa-alquiler-2-ambientes-dueno-directo-parque-centenario-53582269.html": {"date": "05-05-2024\n", "content": "$ 275.000\n$ 40.000 Expensas\nR\u00edo de Janeiro 1056\nParque Centenario, Capital Federal\n40 m\u00b2 tot.\n2 amb.\n1 dorm.\n1 ba\u00f1o\nDue\u00f1o directo alquila departamento de 2 ambientes, 1er piso interno, en parque centenario. Cuenta con living comedor con estufa de tiro balanceado Y ventilador de techo, un dormitorio con placard Y aire acondicionado frio-calor, cocina independiente con lavadero incorporado, ba\u00f1o completo Y patio interno. Apto profesional. Ubicado en rio de janeiro al 1000. Se aceptan mascotas. Excelente ubicacion A una cuadra de av. Corrientes subte linea B, A dos cuadras del parque centenario. Alquiler por 24 meses con ajuste trimestral por ipc. Requisitos: *1 mes adelantado + 1 mes de deposito. *ingresos comprobables. *garantia propietaria caba O seguro de cauci\u00f3n finaer O gtias ya. Se deja constancia que los m2 son aproximados, al igual que las medidas parciales y el valor consignado de las expensas mensuales (en caso que corresponda pago de expensas) y las caracter\u00edsticas est\u00e1n sujetos a verificaci\u00f3n y/o ajustes.\nPublicado hoy\nContactar", "revised": true, "rejected": false, "data": {"precio": "$ 275.000", "expensas": "$ 40.000 Expensas", "direccion": "R\u00edo de Janeiro 1056", "metros": "40 m\u00b2 tot.", "habitaciones": "2 amb.", "hace": "Contactar"}, "comment": "Muy bien. 1 er piso. Patio. Parque Centenario "}, "https://www.zonaprop.com.ar/propiedades/clasificado/alclapin-departamento-en-alquiler-2-ambientes-barrio-norte-53582758.html": {"date": "06-05-2024\n", "content": "$ 320.000\n$ 20.000 Expensas\nSanta Fe al 2200\nBarrio Norte, Capital Federal\n35 m\u00b2 tot.\n2 amb.\n1 dorm.\n1 ba\u00f1o\nDepartamento en alquiler 2 ambientes en Barrio Norte, Capital FederalDepartamento de 2 ambientes reciclado. Luminoso y tranquilo, ya que da al contrafrente y no sobre Av. Santa Fe- Piso 8vo. Sobre Av. Santa Fe entre Uriburu y Azcuenaga, zona con facil acceso a todos los puntos de la ciudad. -Aire acondicionado fr\u00edo/calor-Calefacci\u00f3n eco sol en el dormitorio. -Ba\u00f1o completo con ba\u00f1era. -Placares de pared a pared. Piso de madera parquet (pulidos y plastificados). -Cocina independiente a gas, con espacio para heladera. -Agua caliente con calef\u00f3n el\u00e9ctrico. Apto profesional. Requisitos: *Mes de adelanto*2 meses de deposito en garant\u00eda*Garant\u00eda propietaria o seguro de cauci\u00f3n*Contrato a 2 a\u00f1os *Ingresos comprobables aviso legal: Se hace saber que las caracter\u00edsticas descriptas del inmueble publicado, calidades y cualidades constructivas y funcionales, valores de expensas, impuestos y servicios, y medidas y superficies, son aproximados y consignadas en base a datos que fueron proporcionados por el propietario y que pueden no ser exactos y/o no estar actualizados a la hora de la visualizaci\u00f3n de este aviso, pudiendo surgir discordancias con los datos que surgen de la documentaci\u00f3n respectiva. Las medidas y superficies exactas son las que surgen de los t\u00edtulos y planos legales del inmueble. Las im\u00e1genes publicadas lo son al mero efecto orientativo de las caracter\u00edsticas generales y circunstancias del inmueble en el momento en que han sido tomadas, pudiendo las mismas diferir del estado y circunstancias actuales del mismo. Asimismo, los mobiliarios, accesorios, elementos, etc, que se visualicen en las imagines publicadas, no integran la oferta de venta. En todos los casos el interesado deber\u00e1 realizar una visita al inmueble y efectuar las verificaciones respectivas previamente a la realizaci\u00f3n de cualquier operaci\u00f3n, requiriendo la documentaci\u00f3n que corresponda. Venta supeditada al cumplimiento por parte del propietario de los requisitos de la resoluci\u00f3n general N\u00ba 2371 de la afip (pedido de coti). -\nPublicado hoy\nContactar", "revised": false, "rejected": true, "data": {"precio": "$ 320.000", "expensas": "$ 20.000 Expensas", "direccion": "Santa Fe al 2200", "metros": "35 m\u00b2 tot.", "habitaciones": "2 amb.", "hace": "Publicado hoy"}}, "https://www.zonaprop.com.ar/propiedades/clasificado/alclapin-departamento-2-ambientes-contrafrente-villa-crespo-53582844.html": {"date": "06-05-2024\n", "content": "$ 295.000\n$ 119.000 Expensas\nCamargo 300\nVilla Crespo, Capital Federal\n32 m\u00b2 tot.\n2 amb.\n1 dorm.\n1 ba\u00f1o\nCorredor Responsable: Ariel Champanier cucicba 4330 / Andrea Berre cmcpsi 6763- Contacto: Mart\u00edn Vidal - mls id # Ver datos-7. Departamento de 2 ambientes en alquiler ubicado en Villa Crespo. Primer piso al contrafrente, por ascensor. Cocina integrada al comedor, separados por una barra desayunadora. Cocina equipada con muebles de bajo mesada y alacena, conexion para lavarropas. Comedor con pisos de ceramico, equipo de aire acondicionado frio. Ba\u00f1o con ba\u00f1era. Dormitorio con pisos de parquet y dos placard empotrados con interior. Requisitos: Garantia Seguro de caucion Finaer. Ingresos demostrables. 1 mes en concepto de deposito. 1 mes de adelanto. No se aceptan mascotas. Remax Argentina S. R. L. No ejerce el corretaje inmobiliario. El presente sitio web es una plataforma en donde cada oficina inmobiliaria independiente que contrata los servicios re/max puede publicar las propiedades a su cargo. Cada oficina es de propiedad y gesti\u00f3n independiente, por lo que Remax Argentina S. R. L no interviene en los datos de la publicaci\u00f3n, en la operaci\u00f3n inmobiliaria, ni en la confecci\u00f3n y/o firma del boleto de compraventa y/o escritura y/o contrato de alquiler. En cumplimiento de las leyes vigentes que regulan el corretaje inmobiliario, Ley Nacional 25. 028, Ley 22. 802 de Lealtad Comercial, Ley 24. 240 de Defensa al Consumidor, las normas del C\u00f3digo Civil y Comercial de la Naci\u00f3n y Constitucionales, los agentes/gestores no ejercen el corretaje inmobiliario. Todas las operaciones inmobiliarias son objeto de intermediaci\u00f3n y conclusi\u00f3n por parte del corredor p\u00fablico inmobiliario colegiado a cargo de la publicaci\u00f3n, cuyos datos se exhiben en la presente. La presente publicaci\u00f3n describe las caracter\u00edsticas esenciales del inmueble, debi\u00e9ndose consultar al corredor p\u00fablico inmobiliario responsable de la operaci\u00f3n por la eventual actualizaci\u00f3n de las medidas, descripciones arquitect\u00f3nicas y funcionales, valores de expensas, servicios, impuestos, precios y dem\u00e1s informaci\u00f3n, cuyos valores son aproximados. Para los casos de alquiler de vivienda, el monto m\u00e1ximo de comisi\u00f3n que se le puede requerir a los propietarios ser\u00e1 el equivalente al cuatro con quince cent\u00e9simos por ciento (4, 15%) del valor total del respectivo contrato. Se encuentra prohibido cobrar a los inquilinos que sean personas f\u00edsicas comisiones inmobiliarias y gastos de gestor\u00eda de informes. El inmueble no es accesible para personas con discapacidades f\u00edsicas.\nPublicado hoy\nContactar", "revised": false, "rejected": true, "data": {"precio": "$ 295.000", "expensas": "$ 119.000 Expensas", "direccion": "Camargo 300", "metros": "32 m\u00b2 tot.", "habitaciones": "2 amb.", "hace": "Publicado hoy"}}, "https://www.zonaprop.com.ar/propiedades/clasificado/alclapin-alquiler-de-2-amb-de-30-m-sup2--muy-luminoso-en-53583135.html": {"date": "06-05-2024\n", "content": "$ 300.000\n$ 46.000 Expensas\nAv. Corrientes al 700\nSan Nicol\u00e1s, Capital Federal\n30 m\u00b2 tot.\n2 amb.\n1 dorm.\n1 ba\u00f1o\nDisponible para ingresar el 01 de mayo del 2024Excelente Departamento de 2 Amb al contra frente, Muy luminoso!! Edificio antiguo. caracteristicas: living: amplio, luminoso. dormitorio: con placard, ventana. cocina: cocina con dos hornallas anafe, bajo mesada y alacena, barra desayunadora. ba\u00f1o: con ducha, inodoro, vanitory. todos los ambientes con pisos de parquet. servicios: - Agua caliente. - Aysa $7. 000- Abl $2. 700ubicacion: centroa metros de Galer\u00edas pac\u00edficos, Centro cultural Borges, Peatonal florida, Retiro (plaza San Mart\u00edn) . Limita con los barrios de Puerto Madero al sureste, San Nicol\u00e1s al sur, Recoleta al oeste y con la zona portuaria al noreste. El barrio abarca una zona de oficinas lindera con el \u00e1rea conocida como la City, centro financiero de Buenos Aires, y otra de perfil marcadamente residencial con edificaciones de alta categor\u00eda. En cercan\u00edas del centro de transporte se ubica un \u00e1rea administrativa donde funcionan varias dependencias judiciales. La Plaza San Mart\u00edn es uno de sus principales espacios verdes y uno de los m\u00e1s tradicionales de Buenos Aires. En el barrio se podr\u00eda apreciar de: Museos, Plazas, Edificios y Arquitectura, Cultura, Templos, Calles y Pasajes, Fuentes. Masivos medios de transporte: Colectivos: 6, 9, 10, 17, 23, 24, 26, 29, 45, 50, 59, 67, 70, 91, 99, 100, 105, 109, 111, 115, 129, 140, 146, 180Subtes (Metro) : 9 de julio (L\u00ednea D) , C. Pellegrini (L\u00ednea B) , diagonal norte (L\u00ednea C) , florida (L\u00ednea B) , lavalle (L\u00ednea C) Condiciones y requisitos: Alquileres caba * Fotocopia dni de todas las partes (inquilinos Y garantes) * Una Garant\u00eda propietaria / o Garant\u00edas laborales / o Seguro de cauci\u00f3n* Mes adelantado de alquiler* Mes de Deposito en garant\u00eda* Gastos administrativos de informes y certificaciones nota: Excelente oportunidad, Las medidas, superficies y datos contenidos en esta ficha son estimativos, y al solo efecto orientativo, Los originales surgir\u00e1n del titulo de propiedad.\nPublicado hoy\nContactar", "revised": false, "rejected": true, "data": {"precio": "$ 300.000", "expensas": "$ 46.000 Expensas", "direccion": "Av. Corrientes al 700", "metros": "30 m\u00b2 tot.", "habitaciones": "2 amb.", "hace": "Publicado hoy"}}, "https://www.zonaprop.com.ar/propiedades/clasificado/alclappa-dueno-directo-alquila-2-ambientes-sin-comision-53582685.html": {"date": "06-05-2024\n", "content": "$ 250.000\n$ 30.000 Expensas\nAvenida Rivadavia 3959\nAlmagro Norte, Almagro\n35 m\u00b2 tot.\n2 amb.\n1 dorm.\n1 ba\u00f1o\nLa propiedad se encuentra ubicada sobre la calle Av. Rivadavia, entre Medrano y Gasc\u00f3n, en el barrio de Almagro lindante con Caballito en la Ciudad Aut\u00f3noma de Buenos Aires. Se trata de un departamento 2 ambientes al contrafrente que consta de: 1 dormitorio, 1 ba\u00f1o completo muy amplio, living comedor y cocina separada. La unidad tiene amplios ventanales que le otorgan a todos los ambientes plena luz durante todo el d\u00eda. La cocina tiene mueble bajo mesada y alacena, espacio para lavarropas y termotanque para agua caliente. En el hall distribuidor tiene un placard de guardado y el dormitorio tambi\u00e9n cuenta con placard empotrado. El living cuenta con una estufa tiro balanceado para calefacci\u00f3n. La venta es due\u00f1o directo sin comisi\u00f3n. Superficie total: 35 m2 aprox. Barrio: La propiedad se encuentra en la calle Av. Rivadavia entre Medrano y Gasc\u00f3n en Almagro, en la Ciudad Aut\u00f3noma de Buenos Aires. Este barrio pertenece a la Comuna 5. El barrio se caracteriza por ser tranquilo, de casas bajas y en pleno desarrollo. Est\u00e1 ubicado enfrente del subte A. Cerca del Parque Rivadavia, confiter\u00eda Las Violetas, Parque Centenario, Bas\u00edlica Mar\u00eda Auxiliadora, zona comercial de Acoyte y Rivadavia, polo gastron\u00f3mico de Pedro Goyena, Club Italiano, Comisar\u00eda Comunal 5 y diversos negocios de cercan\u00eda. A tan s\u00f3lo 3 cuadras de la esquina de Av.. La Plata y Av. Rivadavia. Zona de amplia conectividad con el resto de la ciudad y zonas del Gran Buenos Aires. Paradas de colectivos: l\u00edneas 132, 26, 2, 103, 8, 5, 56, 65, 15, 85, 84, 88, 160, 128, 181, 112, entre otras. Subte: R\u00edo de Janeiro (L\u00ednea A).\nPublicado hoy\nContactar", "revised": false, "rejected": true, "data": {"precio": "$ 250.000", "expensas": "$ 30.000 Expensas", "direccion": "Avenida Rivadavia 3959", "metros": "35 m\u00b2 tot.", "habitaciones": "2 amb.", "hace": "Contactar"}}, "https://www.zonaprop.com.ar/propiedades/clasificado/alclapin-precioso-dos-ambientes-amoblado-con-balcon!-por-53584451.html": {"date": "06-05-2024\n", "content": "$ 350.000\n$ 9.000 Expensas\nJunin al 200\nBalvanera, Capital Federal\n30 m\u00b2 tot.\n2 amb.\n1 dorm.\n1 ba\u00f1o\nSe trata de un dos ambientes precioso totalmente reciclado y amoblado hace un a\u00f1o. Impecable! Se accede por un segundo piso por escalera. Hall de recpecion. Ba\u00f1o con ducha. Living con cocina integrada. Cuenta con anafe doble, hornito electrico y microondas. Dormitorio con placard. Balcon a la calle. Aire acondicionado split. Todo es electrico en el departamento. Agua caliente individual. A una cuadra y media de Av. Corrientes. A tres cuadras de Av. Rivadavia. El contrato es a dos a\u00f1os. Los requisitos son garantia y recibo de sueldo o acreditacion de ingresos.\nPublicado hoy\nContactar", "revised": false, "rejected": true, "data": {"precio": "$ 350.000", "expensas": "$ 9.000 Expensas", "direccion": "Junin al 200", "metros": "30 m\u00b2 tot.", "habitaciones": "2 amb.", "hace": "Contactar"}, "comment": "Fea zona"}, "https://www.zonaprop.com.ar/propiedades/clasificado/alclapin-dpto-en-3-amb.-alquiler-53584235.html": {"date": "06-05-2024\n", "content": "$ 250.000\n$ 23.000 Expensas\nRivadavia al 3000\nBalvanera, Capital Federal\n56 m\u00b2 tot.\n2 amb.\n1 dorm.\n1 ba\u00f1o\nAlquiler departamento en importante zona comercial Muy luminosoEl dpto cuenta con: -Living comedor- 1 Domitorio- Cocina- Ba\u00f1o completo-CocinaEn buen estado de conservaci\u00f3n. El edificio cuenta con seguridad y encargado. Excelente ubicaci\u00f3n con gran variedad de transportes- Colectivos: 2, 5, 7, 8, 19, 24, 31, 32, 41, 56, 57, 61, 62, 64, 68, 71, 75, 86, 88, 90, 98, 101, 103, 104, 105, 115, 118, 124, 129, 132, 146, 151, 164, 168, 180, 188, 194- Subtes (Metro) : plaza de miserere (L\u00ednea A) , plaza once (L\u00ednea H) - Trenes: Estaci\u00f3n Once (sarmiento) Requisitos- Garant\u00eda de capital o seguro de caucion. - Mes de dep\u00f3sito y mes adelantado. - S\u00ed es con garant\u00eda demostraci\u00f3n de ingresos- Ajuste trimestral por Ipc- Aceptan mascotasRealizamos visitas puntuales, cons\u00faltenos y agendamos la suya! Le Bleu Negocios Inmobiliarioscod prop lapVer datos\nPublicado hoy\nContactar", "revised": false, "rejected": true, "data": {"precio": "$ 250.000", "expensas": "$ 23.000 Expensas", "direccion": "Rivadavia al 3000", "metros": "56 m\u00b2 tot.", "habitaciones": "2 amb.", "hace": "Contactar"}}, "https://www.zonaprop.com.ar/propiedades/clasificado/alclapin-departamento-2-ambientes-en-almagro-alquiler-53585228.html": {"date": "06-05-2024\n", "content": "$ 290.000\n$ 40.000 Expensas\nColombres al 100\nAlmagro, Capital Federal\n40 m\u00b2 tot.\n2 amb.\n1 dorm.\n1 ba\u00f1o\nDepartamento 2 ambientes en Almagro alquiler. Se encuentra ubicado sobre la calle Colombres en el barrio de Almagro, a 50 mts de la Av. Hipolito Yrigoyen, 150 mts de Av. Belgrano y a 100 mts de la Av. Medrano. Se trata de un departamento de 2 ambientes. Cuenta con living comedor, cocina, lavadero separado, dormitorio con placard y ba\u00f1o completo. Mat. Cucicba N\u00b0 8518.\nPublicado hoy\nContactar", "revised": true, "rejected": false, "data": {"precio": "$ 290.000", "expensas": "$ 40.000 Expensas", "direccion": "Colombres al 100", "metros": "40 m\u00b2 tot.", "habitaciones": "2 amb.", "hace": "Contactar"}, "comment": "Sin balc\u00f3n. Safa"}, "https://www.zonaprop.com.ar/propiedades/clasificado/alclapin-dos-ambientes-lateral-balcon-53584520.html": {"date": "06-05-2024\n", "content": "$ 280.000\n$ 35.000 Expensas\nDirecci\u00f3n no informada\nVilla Crespo, Capital Federal\n32 m\u00b2 tot.\n2 amb.\n1 dorm.\n1 ba\u00f1o\nDepartamento de dos ambientes Lateral, balcon, Muy luminosos, cocina con barra desayunadora, ba\u00f1o completo, dormitorio con placard. Ubicado en un piso 7. El incremento es trimestral segun el ipc. Cerca del Parque Centenario, Medios de transportes. Las medidas y valores de expensas abl y aysa son estimativos, pueden variar al momentp de alquilarlo. Para mayor informaci\u00f3n comuniquese con arenales consultora 1Ver datos / 1Ver datos. cucicba 5522\nPublicado hoy\nContactar", "revised": false, "rejected": true, "data": {"precio": "$ 280.000", "expensas": "$ 35.000 Expensas", "direccion": "Direcci\u00f3n no informada", "metros": "32 m\u00b2 tot.", "habitaciones": "2 amb.", "hace": "Contactar"}}, "https://www.zonaprop.com.ar/propiedades/clasificado/alclapin-departamento-de-2-amb-en-alquiler-piso-alto-53569752.html": {"date": "06-05-2024\n", "content": "10\n$ 350.000\n$ 30.000 Expensas\nPasco al 100\nBalvanera, Capital Federal\n40 m\u00b2 tot.\n2 amb.\n1 dorm.\n1 ba\u00f1o\nSe trata de un 2 amb amplio al frente piso 8voCon balconA 2 cuadras del subte, a 1 cuadra de Av Rivadavia y a 4 cuadras de Av Entre RiosCondiciones: Seguro de caucionAumentos cuatrimestralesDeposito 1 mesMatr\u00edcula y colegio: cucicba 5761 cmcpsm 2899\nPublicado hace 4 d\u00edas\nContactar", "revised": false, "rejected": true, "data": {"precio": "$ 350.000", "expensas": "$ 30.000 Expensas", "direccion": "Pasco al 100", "metros": "40 m\u00b2 tot.", "habitaciones": "2 amb.", "hace": "Contactar"}}, "https://www.zonaprop.com.ar/propiedades/clasificado/alclapin-alquiler-departamento-dos-ambientes-villa-crespo-53589456.html": {"id": "53589456", "date": "07-05-2024\n", "index": 9, "content": "$ 330.000\n$ 22.000 Expensas\nAguirre 700\nVilla Crespo, Capital Federal\n44 m\u00b2 tot.\n2 amb.\n1 dorm.\n1 ba\u00f1o\nCorredor Responsable: Diego Mastrangelo cucicba 7615 csi 6609- Contacto: Fabi\u00e1n Szlafsztein - mls id # Ver datos-57. Conoces Villa Crespo? Quisieras vivir en este tradicional barrio de buenos aires que tiene una ubicaci\u00f3n privilegiada en la ciudad? Disfruta este Alquiler de un muy lindo dos ambientes con patio en villa crespo. Se encuentra en la planta baja, siendo el consorcio de solo planta baja y primer piso. Cuenta con un Dormitorio con gran placar, cocina, living, un ba\u00f1o completo y patio. Todos los ambientes salvo el ba\u00f1o dan al patio, sea con una buena ventana como el dormitorio, ventanal de dos hojas como el living o puerta y ventana como la cocina. El departamentos se encuentra en perfecto estado listo para ingresar. Esta pintado recientemente, cuenta con un aire split frio / calor nuevo en el living para abastecer los dos ambientes. El solo tener primer piso hace que el patio sea agradable y valorado ( para nada es esos patios encajonados en edificios de altura). Nota: all\u00ed se cuenta con el espacio e instalaci\u00f3n para colocar un lavarropas en caso de querer hacerlo. Expensas: Es para resaltar las bajas expensas que se abonan: al mes de Mayo 2024 este departamento: $Ver datos. - instalaciones: tambi\u00e9n en el patio esta instalado el termotanque de 80 L Escorial. La cocina es un espacio independiente con alacenas superiores e inferiores, espacio para microondas, cocina y horno escorial. Las grifer\u00edas tanto en el ba\u00f1o como en la cocina son mono comando. Puerta de ingreso a la unidad es met\u00e1lica con una llave normal mas otra de seguridad. Tablero de electricidad en dos secciones con llaves t\u00e9rmicas y un disyuntor. Aire acondicionado en el living, frio calor, marca bgh, nuevo reci\u00e9n instalado. Luminaria de aluminio en cocina, plafones de vidrio fume en el dormitorio y dos en el living y aplique de dos luces en el ba\u00f1o. Muy lindo espejo redondo en el ba\u00f1o y vanitory de calidad. Para mayor tranquilidad al ausentarse uno de casa, cuenta con rejas en todas las ventanas y puertas de acceso. Tipo de contrato: Contrato de 24 meses con ajuste del canon locativo de forma trimestral tomando como \u00edndice de actualizaci\u00f3n el ipc (\u00cdndice de precios al consumidor). Requisitos: Ingresos suficientes para comprobar puede afrontar el pago del alquiler. El propietario prioriza y prefiere el seguro de Fianza garantor, el cual una vez se acepte la oferta por el alquiler, el futuro inquilino debe contratar el seguro a su cargo. ( similar a seguro de cauci\u00f3n) Opci\u00f3n garant\u00edas propietarias en caba a consideraci\u00f3n del locador. Certificaci\u00f3n de firmas al momento del contrato. Para ingresar debe abonar: Un mes de pago adelantado. ( $330. 000) Como deposito en garant\u00eda $Ver datos. ( El deposito se deja en d\u00f3lares billete estadounidenses billetes equivalentes y se devuelve en la misma moneda). Ubicacion: En la zona conviven lo comercial ( zona de outlet de indumentaria y accesorios de moda), las viviendas, colegios, barcitos. El departamento en si esta equidistante a tres cuadras de la Av Corrientes ( Linea subte B), Av. Ra\u00fal Scalabrini Ortiz y Av. Juan B. Justo. Mudate A la vida que queres! Remax Argentina S. R. L. No ejerce el corretaje inmobiliario. El presente sitio web es una plataforma en donde cada oficina inmobiliaria independiente que contrata los servicios re/max puede publicar las propiedades a su cargo. Cada oficina es de propiedad y gesti\u00f3n independiente, por lo que Remax Argentina S. R. L no interviene en los datos de la publicaci\u00f3n, en la operaci\u00f3n inmobiliaria, ni en la confecci\u00f3n y/o firma del boleto de compraventa y/o escritura y/o contrato de alquiler. En cumplimiento de las leyes vigentes que regulan el corretaje inmobiliario, Ley Nacional 25. 028, Ley 22. 802 de Lealtad Comercial, Ley 24. 240 de Defensa al Consumidor, las normas del C\u00f3digo Civil y Comercial de la Naci\u00f3n y Constitucionales, los agentes/gestores no ejercen el corretaje inmobiliario. Todas las operaciones inmobiliarias son objeto de intermediaci\u00f3n y conclusi\u00f3n por parte del corredor p\u00fablico inmobiliario colegiado a cargo de la publicaci\u00f3n, cuyos datos se exhiben en la presente. La presente publicaci\u00f3n describe las caracter\u00edsticas esenciales del inmueble, debi\u00e9ndose consultar al corredor p\u00fablico inmobiliario responsable de la operaci\u00f3n por la eventual actualizaci\u00f3n de las medidas, descripciones arquitect\u00f3nicas y funcionales, valores de expensas, servicios, impuestos, precios y dem\u00e1s informaci\u00f3n, cuyos valores son aproximados. Para los casos de alquiler de vivienda, el monto m\u00e1ximo de comisi\u00f3n que se le puede requerir a los propietarios ser\u00e1 el equivalente al cuatro con quince cent\u00e9simos por ciento (4, 15%) del valor total del respectivo contrato. Se encuentra prohibido cobrar a los inquilinos que sean personas f\u00edsicas comisiones inmobiliarias y gastos de gestor\u00eda de informes. El inmueble no es accesible para personas con discapacidades f\u00edsicas.\nPublicado hoy\nContactar", "revised": true, "rejected": false, "data": {"precio": "$ 330.000", "expensas": "$ 22.000 Expensas", "direccion": "Aguirre 700", "metros": "44 m\u00b2 tot.", "habitaciones": "2 amb.", "hace": "Contactar"}, "image": "https://imgar.zonapropcdn.com/avisos/1/00/53/58/94/56/360x266/1909734606.jpg?isFirstImage=true", "title": "Departamento \u00b7 38m\u00b2 \u00b7 2 Ambientes \u00b7 Alquiler Departamento Dos Ambientes Villa Crespo", "comment": "Bueno. Frio. Patio"}, "https://www.zonaprop.com.ar/propiedades/clasificado/alclapin-depto.-ambientes-planta-baja-con-2-banos-y-amplio-53590286.html": {"id": "53590286", "date": "07-05-2024\n", "index": 10, "content": "$ 350.000\n$ 38.500 Expensas\nM\u00e9xico 3973\nAlmagro, Capital Federal\n60 m\u00b2 tot.\n2 amb.\n1 dorm.\n1 ba\u00f1o\nAmplio Depto. 2 Ambientes Planta baja Contrafrente, Living Comedor 5x4, Cocina Americana, Toilet, Dormitorio 3x3 con Placard y Ba\u00f1o en Suite, Patio 5x5 con Lavadero. Artefacto de cocina y Termotanque a gas. Muy Luminoso. Excelente Estado. A 1 cd. Av. Independencia. Actualizaci\u00f3n trimestral por ipc. Se requiere garant\u00eda propietaria o seguro de cauci\u00f3n finaer. En el edificio no aceptan mascotas.\nPublicado hoy\nContactar", "revised": true, "rejected": false, "data": {"precio": "$ 350.000", "expensas": "$ 38.500 Expensas", "direccion": "M\u00e9xico 3973", "metros": "60 m\u00b2 tot.", "habitaciones": "2 amb.", "hace": "Contactar"}, "image": "https://imgar.zonapropcdn.com/avisos/1/00/53/59/02/86/360x266/1909753692.jpg?isFirstImage=true", "title": "Departamento de 2 ambientes, Almagro \u00b7 Depto. Ambientes Planta Baja con 2 Ba\u00f1os y Amplio Patio y Lavadero", "comment": "Fr\u00edo. Patio. Caro"}, "https://www.zonaprop.com.ar/propiedades/clasificado/alclapin-2-ambientes-balcon-luminoso-53586553.html": {"id": "53586553", "date": "07-05-2024\n", "index": 14, "content": "$ 300.000\n$ 50.000 Expensas\nDirecci\u00f3n no informada\nParque Centenario, Capital Federal\n38 m\u00b2 tot.\n2 amb.\n1 dorm.\n1 ba\u00f1o\n2 ambientes luminosos excelente estado balc\u00d2N\nPublicado hoy\nContactar", "revised": false, "rejected": true, "data": {"precio": "$ 300.000", "expensas": "$ 50.000 Expensas", "direccion": "Direcci\u00f3n no informada", "metros": "38 m\u00b2 tot.", "habitaciones": "2 amb.", "hace": "Contactar"}, "image": "https://imgar.zonapropcdn.com/avisos/1/00/53/58/65/53/360x266/1909673683.jpg?isFirstImage=true", "title": "Departamento de 2 ambientes, Parque Centenario \u00b7 2 Ambientes Balc\u00f2n Luminoso"}, "https://www.zonaprop.com.ar/propiedades/clasificado/alclapin-dpto-en-2-amb.-alquiler-53584235.html": {"id": "53584235", "date": "07-05-2024\n", "index": 15, "content": "$ 250.000\n$ 23.000 Expensas\nRivadavia al 3000\nBalvanera, Capital Federal\n56 m\u00b2 tot.\n2 amb.\n1 dorm.\n1 ba\u00f1o\nAlquiler departamento en importante zona comercial Muy luminosoEl dpto cuenta con: -Living comedor- 1 Domitorio- Cocina- Ba\u00f1o completo-CocinaEn buen estado de conservaci\u00f3n. El edificio cuenta con seguridad y encargado. Excelente ubicaci\u00f3n con gran variedad de transportes- Colectivos: 2, 5, 7, 8, 19, 24, 31, 32, 41, 56, 57, 61, 62, 64, 68, 71, 75, 86, 88, 90, 98, 101, 103, 104, 105, 115, 118, 124, 129, 132, 146, 151, 164, 168, 180, 188, 194- Subtes (Metro) : plaza de miserere (L\u00ednea A) , plaza once (L\u00ednea H) - Trenes: Estaci\u00f3n Once (sarmiento) Requisitos- Garant\u00eda de capital o seguro de caucion. - Mes de dep\u00f3sito y mes adelantado. - S\u00ed es con garant\u00eda demostraci\u00f3n de ingresos- Ajuste trimestral por Ipc- Aceptan mascotasRealizamos visitas puntuales, cons\u00faltenos y agendamos la suya! Le Bleu Negocios Inmobiliarioscod prop lapVer datos\nPublicado hoy\nContactar", "revised": false, "rejected": true, "data": {"precio": "$ 250.000", "expensas": "$ 23.000 Expensas", "direccion": "Rivadavia al 3000", "metros": "56 m\u00b2 tot.", "habitaciones": "2 amb.", "hace": "Contactar"}, "image": "https://imgar.zonapropcdn.com/avisos/1/00/53/58/42/35/360x266/1909623364.jpg?isFirstImage=true", "title": "Departamento \u00b7 56m\u00b2 \u00b7 2 Ambientes \u00b7 Dpto en 2 Amb. Alquiler"}, "https://www.zonaprop.com.ar/propiedades/clasificado/alclapin-departamento-de-2-ambientes-en-alquiler-en-almagro-53589073.html": {"id": "53589073", "date": "07-05-2024\n", "index": 16, "content": "$ 240.000\n$ 31.200 Expensas\nSarmiento al 4000 - Departamento de 2 Ambientes en Alquiler en Almagro\nAlmagro, Capital Federal\n37 m\u00b2 tot.\n2 amb.\n1 dorm.\n1 ba\u00f1o\nDepartamento de 2 ambientes en alquiler en Almagro! Ubicaci\u00f3n: - Sobre la calle Sarmiento- A media cuadra de Av. Medrano- A dos cuadras de Av. Corrientes- A tres cuadras de Av. D\u00edaz V\u00e9lez- A seis cuadras del Parque CentenarioMedios de transporte: - Colectivos: 19, 24, 26, 36, 71, 90, 92, 99, 105, 109, 124, 127, 128, 146, 151, 160, 168, 180- Subtes: Medrano (l\u00ednea B) Departamento: - Segundo piso (por ascensor) - Interno pero muy luminoso- Ba\u00f1o completo- Cocina completa con posibilidad de conectar lavarropas- Amplio dormitorio con placard- Otro peque\u00f1o placard en el hall distribuidor- Reci\u00e9n pintadoRequisitos: - Garant\u00eda de propietario de Capital Federal (puede ser del conurbano bonaerense si es familiar directo comprobable) . El propietario no acepta seguro de cauci\u00f3n ni garant\u00eda bancaria- Ingresos demostrables- Un mes de dep\u00f3sito ($ 265. 000. -) - Un mes de adelanto ($ 265. 000. -) - Informes de la garant\u00eda- Firmas certificadas por Escribano- Dos a\u00f1os de duraci\u00f3n- Aumento trimestral por iclley 5. 859, art. 4: \u201cPara los casos de alquiler de vivienda, el monto m\u00e1ximo de comisi\u00f3n que se le puede requerir a los propietarios ser\u00e1 el equivalente al cuatro con quince cent\u00e9simos por ciento (4, 15%) del valor total del respectivo contrato. Se encuentra prohibido cobrar a los inquilinos que sean personas f\u00edsicas comisiones inmobiliarias y gastos de gestor\u00eda de informes\u201d\nPublicado hoy\nContactar", "revised": true, "rejected": false, "data": {"precio": "$ 240.000", "expensas": "$ 31.200 Expensas", "direccion": "Sarmiento al 4000 - Departamento de 2 Ambientes en Alquiler en Almagro", "metros": "37 m\u00b2 tot.", "habitaciones": "2 amb.", "hace": "Contactar"}, "image": "https://imgar.zonapropcdn.com/avisos/1/00/53/58/90/73/360x266/1909726309.jpg?isFirstImage=true", "title": "Departamento \u00b7 37m\u00b2 \u00b7 2 Ambientes \u00b7 Departamento de 2 Ambientes en Alquiler en Almagro", "comment": "Bueno. Fea zona "}, "https://www.zonaprop.com.ar/propiedades/clasificado/alclapin-alquiler-2-ambientes-barrio-norte-fac.-medicina-53588135.html": {"id": "53588135", "date": "07-05-2024\n", "index": 20, "content": "$ 320.000\n$ 51.000 Expensas\nPresidente Jose E. Uriburu 1000\nBarrio Norte, Capital Federal\n30 m\u00b2 tot.\n2 amb.\n1 dorm.\n1 ba\u00f1o\nCorredor Responsable: graciela menazzi cmcpdjlm 841 / cpi 6344- Contacto: Mariano Castiglione - mls id # Ver datos-4. departamento reciclado 2 ambientes facultad de medicina. Contrato tradicional. ideal! Departamento 2 ambientes recientemente reciclado en su totalidad. Se acepta seguro de caucion. Cocina integrada al comedor, termotanque nuevo, artefacto de cocina a Gas, living comedor con preinstalaci\u00f3n de aire acondicionado, dormitorio con ventilador de techo y ba\u00f1o completo con lavarropas con todas sus conexiones. El departamento es muy acogedor. Solo tenes que mirar las fotos! Requisitos: Recibo de sueldo o demostraci\u00f3n de ingresos y seguro de Caucion. Contrato por 2 a\u00f1os con ajuste trimestral segun ipc. Valor del alquiler $ 320. 000. Expensas $ 51. 000. Para ingresar debes abonar un mes adelantado. Deposito usd 500. Llamanos y mudate a la vida que queres! *si tienes que vender para comprar, podemos ayudarte Y realizar la operaci\u00f3n simult\u00e1nea* beneficio para clientes. Si te falta hasta un 30% del valor de esta propiedad, te ofrecemos solicitar un pr\u00e9stamo a trav\u00e9s de Lendar, servicio exclusivo para clientes re/max. Hace la simulaci\u00f3n de tu cuota a trav\u00e9s del simulador. ar/quiero-un-prestamo/ Las medidas, superficies y expensas consignadas en la presente son aproximadas; y al solo efecto orientativo. Los datos definitivos son los que surgir\u00e1n del t\u00edtulo de la propiedad y de los comprobantes respaldatorios. \" Venta supeditada al cumplimiento por parte del propietario de los requisitos de la resoluci\u00f3n general N\u00ba 2371 de la afip (pedido de coti). Remax Argentina S. R. L. No ejerce el corretaje inmobiliario. El presente sitio web es una plataforma en donde cada oficina inmobiliaria independiente que contrata los servicios re/max puede publicar las propiedades a su cargo. Cada oficina es de propiedad y gesti\u00f3n independiente, por lo que Remax Argentina S. R. L no interviene en los datos de la publicaci\u00f3n, en la operaci\u00f3n inmobiliaria, ni en la confecci\u00f3n y/o firma del boleto de compraventa y/o escritura y/o contrato de alquiler. En cumplimiento de las leyes vigentes que regulan el corretaje inmobiliario, Ley Nacional 25. 028, Ley 22. 802 de Lealtad Comercial, Ley 24. 240 de Defensa al Consumidor, las normas del C\u00f3digo Civil y Comercial de la Naci\u00f3n y Constitucionales, los agentes/gestores no ejercen el corretaje inmobiliario. Todas las operaciones inmobiliarias son objeto de intermediaci\u00f3n y conclusi\u00f3n por parte del corredor p\u00fablico inmobiliario colegiado a cargo de la publicaci\u00f3n, cuyos datos se exhiben en la presente. La presente publicaci\u00f3n describe las caracter\u00edsticas esenciales del inmueble, debi\u00e9ndose consultar al corredor p\u00fablico inmobiliario responsable de la operaci\u00f3n por la eventual actualizaci\u00f3n de las medidas, descripciones arquitect\u00f3nicas y funcionales, valores de expensas, servicios, impuestos, precios y dem\u00e1s informaci\u00f3n, cuyos valores son aproximados. Para los casos de alquiler de vivienda, el monto m\u00e1ximo de comisi\u00f3n que se le puede requerir a los propietarios ser\u00e1 el equivalente al cuatro con quince cent\u00e9simos por ciento (4, 15%) del valor total del respectivo contrato. Se encuentra prohibido cobrar a los inquilinos que sean personas f\u00edsicas comisiones inmobiliarias y gastos de gestor\u00eda de informes. El inmueble no es accesible para personas con discapacidades f\u00edsicas.\nPublicado hoy\nContactar", "revised": false, "rejected": true, "data": {"precio": "$ 320.000", "expensas": "$ 51.000 Expensas", "direccion": "Presidente Jose E. Uriburu 1000", "metros": "30 m\u00b2 tot.", "habitaciones": "2 amb.", "hace": "Contactar"}, "image": "https://imgar.zonapropcdn.com/avisos/1/00/53/58/81/35/360x266/1909706291.jpg?isFirstImage=true", "title": "Departamento \u00b7 30m\u00b2 \u00b7 2 Ambientes \u00b7 Alquiler 2 Ambientes Barrio Norte Fac. Medicina"}, "https://www.zonaprop.com.ar/propiedades/clasificado/alclapin-alquiler-departamento-2-ambientes-muy-buena-53591284.html": {"id": "53591284", "date": "07-05-2024\n", "index": 21, "content": "13\n$ 280.000\n$ 40.000 Expensas\nSarmiento 1542\nSan Nicol\u00e1s, Capital Federal\n35 m\u00b2 tot.\n2 amb.\n1 dorm.\n1 ba\u00f1o\nAlquiler departamento de 2 ambientes, 35 metros\u00b2, lateral, todo reci\u00e9n pintado, Living comedor con piso de parquet plastificado, aire acondicionado y placard. Cocina completa con muebles bajo mesada y alacena. Dormitorio con piso de parquet plastificado. Ba\u00f1o completo con vaniroty y ventana. Expensas $40. 000. Apto profesional. Pr\u00f3ximo a l\u00ednea de subre \"A\", \"B\" y \"C\" y muchas L\u00edneas de colectivos. Se alquila con garantia propietaria de capital federal O fianza Y demostracion de ingresos. Suma estudio jurico inmobiliario.\nPublicado hoy\nContactar", "revised": false, "rejected": true, "data": {"precio": "$ 280.000", "expensas": "$ 40.000 Expensas", "direccion": "Sarmiento 1542", "metros": "35 m\u00b2 tot.", "habitaciones": "2 amb.", "hace": "Contactar"}, "image": "https://imgar.zonapropcdn.com/avisos/1/00/53/59/12/84/360x266/1909776262.jpg?isFirstImage=true", "title": "Departamento de 2 ambientes, San Nicol\u00e1s \u00b7 Alquiler - Departamento 2 Ambientes - Muy Buena Ubicacion - Recien Pintado"}, "https://www.zonaprop.com.ar/propiedades/clasificado/alclapin-departamento-en-alquiler-de-1-dormitorio-en-parque-53590415.html": {"id": "53590415", "date": "07-05-2024\n", "index": 26, "content": "$ 300.000\n$ 20.000 Expensas\nDean Funes 2160\nParque Patricios, Capital Federal\n39 m\u00b2 tot.\n2 amb.\n1 dorm.\n1 ba\u00f1o\nDepartamento en alquiler en la calle Dean Funes, Parque Patricios, Capital Federal. Este inmueble de 2 ambientes ofrece un total de 39 m2 distribuidos de manera inteligente, con un dormitorio, un ba\u00f1o y una cocina, ideal para aquellos que buscan comodidad en un mismo espacio. La propiedad cuenta con todas las comodidades necesarias: agua corriente, luz, gas natural, cocina equipada, lavadero, ascensor y un luminoso living comedor que invita al relax. Con una orientaci\u00f3n lateral, este departamento se destaca por su ambiente acogedor y funcional, perfecto para disfrutar de la vida urbana con todas las comodidades. Adem\u00e1s, este exclusivo departamento en alquiler se encuentra en un edificio con una antig\u00fcedad que garantiza su calidad y durabilidad. Con un costo mensual de $20. 000 en concepto de expensas, esta propiedad es una oportunidad \u00fanica para aquellos que buscan vivir en una de las zonas m\u00e1s exclusivas de la ciudad. . \u00a1Cont\u00e1ctanos para m\u00e1s informaci\u00f3n! \u00a1Ll\u00e1menos para conocer m\u00e1s en detalle esta propiedad! Tel: Ver datos. Email: Ver datos. De la Torre Propiedades\nPublicado hoy\nContactar", "revised": false, "rejected": true, "data": {"precio": "$ 300.000", "expensas": "$ 20.000 Expensas", "direccion": "Dean Funes 2160", "metros": "39 m\u00b2 tot.", "habitaciones": "2 amb.", "hace": "Contactar"}, "image": "https://imgar.zonapropcdn.com/avisos/1/00/53/59/04/15/360x266/1909756625.jpg?isFirstImage=true", "title": "Departamento de 2 ambientes, Parque Patricios \u00b7 Departamento en Alquiler de 1 Dormitorio en Parque Patricios"}, "https://www.zonaprop.com.ar/propiedades/clasificado/alclapin-dpto-2-ambientes-amplios-frente-jean-jaures-y-mansilla-53577826.html": {"id": "53577826", "date": "07-05-2024\n", "index": 27, "content": "$ 350.000\n$ 82.000 Expensas\nJean Jaures 1140\nBarrio Norte, Capital Federal\n48 m\u00b2 tot.\n2 amb.\n1 dorm.\n1 ba\u00f1o\nDepartamento de 2 ambientes amplios 48m2 doble circulaci\u00f3n al frente con balc\u00f3n 1er piso, living comedor en L, dormitorio con placares, ba\u00f1o completo, cocina con puerta de salida. , en living aire acondicionado frio/calor. Buena zona con mucha movilidad cerca de Av. Pueyrred\u00f3n y Av. Cordoba. El departamento se encuentra en buen estado de pintura. Requisitos contrato por 2 a\u00f1os con incremento cada 4 meses. Garantia Propietaria de Capital Federal o seguro de Cauci\u00f3n de Finaer. Lirot propiedades. graciela beatriz lisanti. matricula 4655 cucicba\nPublicado hoy\nContactar", "revised": false, "rejected": true, "data": {"precio": "$ 350.000", "expensas": "$ 82.000 Expensas", "direccion": "Jean Jaures 1140", "metros": "48 m\u00b2 tot.", "habitaciones": "2 amb.", "hace": "Contactar"}, "image": "https://imgar.zonapropcdn.com/avisos/1/00/53/57/78/26/360x266/1909475357.jpg?isFirstImage=true", "title": "Departamento de 2 ambientes, Barrio Norte \u00b7 Dpto 2 Ambientes Amplios Frente Jean Jaures y Mansilla Barrio Norte"}, "https://www.zonaprop.com.ar/propiedades/clasificado/alclappa-alquiler-2-amb.-tucuman-entre-r.-pena-y-callao-53585430.html": {"id": "53585430", "date": "07-05-2024\n", "index": 31, "content": "$ 280.000\nTucum\u00e1n 1772\nSan Nicol\u00e1s, Capital Federal\n30 m\u00b2 tot.\n2 amb.\n1 dorm.\n1 ba\u00f1o\nDepartamento de 2 ambientes en excelente ubicaci\u00f3n. A pocos metros del Subte. Zona facultades. Apto profesional. Ideal para vivienda, oficina o consultorio. Superficie aprox. 30 m2. Balc\u00f3n franc\u00e9s. Interno pero muy ventilado. Piso 6\u00ba. Ba\u00f1o completo (ducha, sin ba\u00f1era). Cocina peque\u00f1a. Agua caliente central. Pisos de madera. Gran placard. * Valor del Mes. + Expensas (ref. $37. 093 - 05/2024) + Servicios. Contrato x 2 a\u00f1os. Ajuste cuatrimestral por icl. * Condiciones para ingresar: - Mes de ingreso. - Dep\u00f3sito: 2 meses reembolsable (se puede pagar en cuotas) - Garant\u00eda: Propietaria familiar o Seguro de Cauci\u00f3n o Garantes con recibos de sueldo. - Demostraci\u00f3n de ingresos. - Gastos de contrato (seg\u00fan garant\u00eda ofrecida) visitas A partir del 1 de junio 2024\nPublicado hoy\nContactar", "revised": false, "rejected": true, "data": {"precio": "$ 280.000", "expensas": "", "direccion": "Tucum\u00e1n 1772", "metros": "30 m\u00b2 tot.", "habitaciones": "2 amb.", "hace": "Contactar"}, "image": "https://imgar.zonapropcdn.com/avisos/1/00/53/58/54/30/360x266/1909653312.jpg?isFirstImage=true", "title": "Departamento de 2 ambientes, San Nicol\u00e1s \u00b7 Alquiler 2 Amb. (Tucum\u00e1n Entre R. Pe\u00f1a y Callao - Caba)"}}