{"https://www.argenprop.com/departamento-en-alquiler-en-parque-patricios-2-ambientes--15646143": {"date": "05-05-2024\n", "content": "1\n/7\n1.150\n$ 280.000 + $38.000 expensas\nSanta cruz 100, Piso 1\nDepartamento en Alquiler en Parque Patricios, Capital Federal\n40 m\u00b2 cubie.\n1 dorm.\n50 a\u00f1os\nDepartamento en alquiler en Parque Patricios\nDepartamento 2 ambientes amplios, muy luminoso, con ba\u00f1o a estrenar. Primer piso por escaleras y en excelente estado. Due\u00f1o directo con 1 mes de deposito y mes por adelantado con garantia o similar\nWhatsApp\nContactar", "revised": true, "rejected": false, "data": {"precio": "$ 280.000 + $38.000 expensas", "expensas": "+ $38.000 expensas", "direccion": "Santa cruz 100, Piso 1", "metros": "40 m\u00b2 cubie.", "habitaciones": "1 dorm."}, "comment": "bien. sin balcon. parque patricios. 2 amb"}, "https://www.argenprop.com/departamento-en-alquiler-en-parque-centenario-1-ambiente--15204728": {"date": "05-05-2024\n", "content": "1\n/7\n0\n$ 270.000 + $20.000 expensas\nAGUIRRE 100\nDepartamento en Alquiler en Parque Centenario, Capital Federal\n30 m\u00b2 cubie.\n7 a\u00f1os\n1 ba\u00f1o\nDepartamento de 1 ambiente en Alquiler en Parque centenario\n1 ambientes nuevo, moderno edificio de viviendas y estudios apto profesional . Edificado sobre un lote de 20 metros de frente . Importante hall de acceso. Todas las unidades dan al frente. Ubicado a pasos de av corrientes y estado de israel . Subte b y parque centenario. Comercializa migliorisi corrientes 5500 srl direccion legal corrientes 5500 caba - se deja constancia que las caracteristicas,\nWhatsApp\nContactar", "revised": true, "rejected": true, "data": {"precio": "$ 270.000 + $20.000 expensas", "expensas": "+ $20.000 expensas", "direccion": "AGUIRRE 100", "metros": "30 m\u00b2 cubie.", "habitaciones": "7 a\u00f1os"}, "comment": "mono lindo. no hay gas", "image": "https://static1.sosiva451.com/82740251/71bc7f15-a10e-41db-a635-704e71bb7494_u_small.jpg"}, "https://www.argenprop.com/departamento-en-alquiler-en-balvanera-1-ambiente--15446033": {"date": "05-05-2024\n", "content": "1\n/10\n0\n$ 300.000 + $50.000 expensas\nCORRIENTES 3300\nDepartamento en Alquiler en Balvanera, Capital Federal\n30 m\u00b2 cubie.\n8 a\u00f1os\n1 ba\u00f1o\nDepartamento de 1 ambiente en Alquiler en Balvanera\nHermosa y moderna unidad monoambiente al frente de 34m2 totales con balcon - cocina con anafe electrico integrada al ambiente - ba\u00f1o completo - edificio con piscina, gym, s.U.M. - A metros del shopping abasto - ideal alquiler a estudiante - amplios medios de transporte - para visitas - comercializa migliorisi palermo av. Cordoba 3401 - comercializa migliorisi ,profesional responsable pablo\nWhatsApp\nContactar", "revised": true, "rejected": true, "data": {"precio": "$ 300.000 + $50.000 expensas", "expensas": "+ $50.000 expensas", "direccion": "CORRIENTES 3300", "metros": "30 m\u00b2 cubie.", "habitaciones": "8 a\u00f1os"}, "comment": "Caro. Ni lo vi", "image": null}, "https://www.argenprop.com/departamento-en-alquiler-en-almagro-1-ambiente--15446021": {"date": "05-05-2024\n", "content": "1\n/10\n0\n$ 300.000 + $50.000 expensas\nCORRIENTES 3300\nDepartamento en Alquiler en Almagro, Capital Federal\n30 m\u00b2 cubie.\n8 a\u00f1os\n1 ba\u00f1o\nDepartamento de 1 ambiente en Alquiler en Almagro\nHermosa y moderna unidad monoambiente al frente de 34m2 totales con balcon - cocina con anafe electrico integrada al ambiente - ba\u00f1o completo - edificio con piscina, gym y s.U.M. - A metros del shopping abasto - ideal alquiler a estudiante - amplios medios de transporte - comercializa migliorisi av. Cordoba 3401 - comercializa migliorisi ,profesional responsable pablo sebastian migliorisi cpi\nWhatsApp\nContactar", "revised": false, "rejected": true, "data": {"precio": "$ 300.000 + $50.000 expensas", "expensas": "+ $50.000 expensas", "direccion": "CORRIENTES 3300", "metros": "30 m\u00b2 cubie.", "habitaciones": "8 a\u00f1os"}, "image": "https://static1.sosiva451.com/12064451/e489d7bb-a879-413d-93a6-f1409a68ba66_u_small.jpg"}, "https://www.argenprop.com/departamento-en-alquiler-en-almagro-1-ambiente--15617755": {"date": "05-05-2024\n", "content": "1\n/10\n0\n$ 250.000 + $25.000 expensas\nPRINGLES 700\nDepartamento en Alquiler en Almagro, Capital Federal\n30 m\u00b2 cubie.\n40 a\u00f1os\n1 ba\u00f1o\nDepartamento de 1 ambiente en Alquiler en Almagro\nMonoambiente en alquiler, 30 m2, a 3 cuadras de subte b, con placard amplio, cocina independiente, ba\u00f1o completo con ba\u00f1era y ventilacion natural, expensas: $ 25.000 - comercializa migliorisi de corrientes 4599 srl profesional responsable jorge daniel gomez cpi 261 a30112 se deja constancia que las caracteristicas, medidas, expensas y superficies consignadas son aproximadas, sujetos a\nWhatsApp\nContactar", "revised": true, "rejected": true, "data": {"precio": "$ 250.000 + $25.000 expensas", "expensas": "+ $25.000 expensas", "direccion": "PRINGLES 700", "metros": "30 m\u00b2 cubie.", "habitaciones": "40 a\u00f1os"}, "comment": "Bien. Fr\u00edo. Oscuro", "image": "https://static1.sosiva451.com/55771651/e3d972f8-501f-4bcb-9902-c941910751bc_u_small.jpg"}, "https://www.argenprop.com/departamento-en-alquiler-en-congreso-2-ambientes--15603643": {"date": "05-05-2024\n", "content": "1\n/1\n0\n$ 300.000 + $35.000 expensas\nRIVADAVIA 2300\nDepartamento en Alquiler en Congreso, Capital Federal\n45 m\u00b2 cubie.\n1 dorm.\n50 a\u00f1os\nDepartamento de 2 ambientes en Alquiler en Congreso\nEn alquiler, interesante 2 ambientes de generosa superficie. Ventilacion en todos los ambientes. Sobre avenida. Acceso a transporte a todas direcciones,por la zona. Amplio movimiento comercial,peatonal,vehicular. Comercializa corrientes 721894/..A28196 se deja constancia que las caracteristicas, medidas, expensas y superficies consignadas son aproximadas, sujetos a verificaci\u00f3n y/o ajuste. El\nWhatsApp\nContactar", "revised": false, "rejected": true, "data": {"precio": "$ 300.000 + $35.000 expensas", "expensas": "+ $35.000 expensas", "direccion": "RIVADAVIA 2300", "metros": "45 m\u00b2 cubie.", "habitaciones": "1 dorm."}, "image": "https://static1.sosiva451.com/34630651/d22e656c-6a04-4c45-a614-83b492abf005_u_small.jpg"}, "https://www.argenprop.com/departamento-en-alquiler-en-almagro-norte-1-ambiente--14684945": {"date": "05-05-2024\n", "content": "1\n/12\n0\n$ 300.000 + $67.000 expensas\nValent\u00edn G\u00f3mez 3700, Piso 3\nDepartamento en Alquiler en Almagro Norte, Almagro\n33 m\u00b2 cubie.\n15 a\u00f1os\n1 ba\u00f1o\nAlmagro Valentin Gomez 3700 5\u00b0 Todo Luz y Sol Coc Barra Lav\nHermoso monoambiente sumamente luminoso y soleado al contrafrente (orientaci\u00f3n ne), ubicado en valent\u00edn gomez entre bulnes y mario bravo, 3\u00b0 piso. Edificio de 15 a\u00f1os es excelente estado. Posee 33mts cubiertos y 2 mts de balc\u00f3n. Se compone de hall de ingreso, acceso a cocina semintegrada con barra (posee lugar para lavarropas), ambiente amplio f\u00e1cilmente divisible, vestidor con c\u00f3modo lugar de\nWhatsApp\nContactar", "revised": true, "rejected": false, "data": {"precio": "$ 300.000 + $67.000 expensas", "expensas": "+ $67.000 expensas", "direccion": "Valent\u00edn G\u00f3mez 3700, Piso 3", "metros": "33 m\u00b2 cubie.", "habitaciones": "15 a\u00f1os"}, "comment": "Lindo. Luz. Cerca de plaza Almagro. Mono"}, "https://www.argenprop.com/departamento-en-alquiler-en-almagro-2-ambientes--15397076": {"date": "05-05-2024\n", "content": "1\n/10\n2\n$ 320.000 + $30.000 expensas\nAvenida D\u00edaz V\u00e9lez 3700, Piso 4\nDepartamento en Alquiler en Almagro, Capital Federal\n40 m\u00b2 cubie.\n1 dorm.\n40 a\u00f1os\nDepartamento 2 ambientes zona Almagro\nHermoso departamento de 2 ambientes 4to piso c/fte con balc\u00f3n corrido -living comedor de 5 x 3 mts con modular, mesa con sillas y m\u00e1s comodidades -dormitorio de 3,10 x 3 mts con placard empotrado juego de dormitorio con colch\u00f3n nuevo - ba\u00f1o con ducha - cocina con mesa libro utensilios de cocina - lavadero independiente consultas: (no se aceptan mascotas) mariela alberto diego (solo\nWhatsApp\nContactar", "revised": false, "rejected": true, "data": {"precio": "$ 320.000 + $30.000 expensas", "expensas": "+ $30.000 expensas", "direccion": "Avenida D\u00edaz V\u00e9lez 3700, Piso 4", "metros": "40 m\u00b2 cubie.", "habitaciones": "1 dorm."}, "image": "https://static1.sosiva451.com/67079351/e5dc0cf0-ee92-4105-9907-88bd9893e1c9_u_small.jpg"}, "https://www.argenprop.com/departamento-en-alquiler-en-villa-crespo-2-ambientes--15645326": {"date": "05-05-2024\n", "content": "1\n/9\n0\n$ 250.000\nLEOPOLDO MARECHAL 1300\nDepartamento en Alquiler en Villa Crespo, Capital Federal\n37 m\u00b2 cubie.\n1 dorm.\n40 a\u00f1os\nDepartamento de 2 ambientes en Alquiler en Villa crespo\nDepartamento 2 ambientes lateral - excelente ubicacion - se deja constancia que las caracteristicas, medidas, expensas y superficies consignadas son aproximadas, sujetos a verificacion y/o ajuste. El precio del inmueble puede ser modificado sin previo aviso. Fotos de caracter no contractual. Las unidades publicadas estan sujetas a migliorisi de corrientes 4599 srl profesional responsable jorge\nWhatsApp\nContactar", "revised": false, "rejected": true, "data": {"precio": "$ 250.000", "direccion": "LEOPOLDO MARECHAL 1300", "metros": "37 m\u00b2 cubie.", "habitaciones": "1 dorm."}, "image": "https://static1.sosiva451.com/62354651/b29c5f6f-0a73-4195-804b-89b4af3194eb_u_small.jpg"}, "https://www.argenprop.com/departamento-en-alquiler-en-almagro-2-ambientes--15417859": {"date": "05-05-2024\n", "content": "1\n/9\n0\n$ 300.000 + $45.000 expensas\nHUMAHUACA 4300\nDepartamento en Alquiler en Almagro, Capital Federal\n35 m\u00b2 cubie.\n1 dorm.\n45 a\u00f1os\nDepartamento de 2 ambientes en Alquiler en Almagro\nDepartamento 2 ambientes a frente con balcon - apto profesional - luz y sol en todos los ambientes- excelente ubiacion - multiples medios de transporte -\nWhatsApp\nContactar", "revised": true, "rejected": false, "data": {"precio": "$ 300.000 + $45.000 expensas", "expensas": "+ $45.000 expensas", "direccion": "HUMAHUACA 4300", "metros": "35 m\u00b2 cubie.", "habitaciones": "1 dorm."}, "comment": "Fiero. 2amb", "image": "https://static1.sosiva451.com/95871451/be92938f-c4ec-499f-b954-83ba0a46502c_u_small.jpg"}, "https://www.argenprop.com/departamento-en-alquiler-en-villa-crespo-2-ambientes--15633344": {"date": "05-05-2024\n", "content": "1\n/6\n0\n$ 300.000 + $70.000 expensas\nLEMOS 100\nDepartamento en Alquiler en Villa Crespo, Capital Federal\n35 m\u00b2 cubie.\n1 dorm.\n40 a\u00f1os\nDepartamento de 2 ambientes en Alquiler en Villa crespo\nDos ambientes muy luminoso, contrafrente con excelente vista, en pleno corredor de corrientes. Cocina y lavadero independiente. Cerca del subte b. Sin mascotas y solo con garantia propietaria de caba, propia o de garante. Comercializa migliorisi de corrientes 5500 srl profesional responsable diego f migliorisi cpi263 a30141 se deja constancia que las caracteristicas, medidas, expensas y\nWhatsApp\nContactar", "revised": true, "rejected": true, "data": {"precio": "$ 300.000 + $70.000 expensas", "expensas": "+ $70.000 expensas", "direccion": "LEMOS 100", "metros": "35 m\u00b2 cubie.", "habitaciones": "1 dorm."}, "image": "https://static1.sosiva451.com/44333651/f98b791b-08d1-414a-82ab-cf5e3e611fc7_u_small.jpg"}, "https://www.argenprop.com/departamento-en-alquiler-en-villa-crespo-1-ambiente--15623890": {"date": "05-05-2024\n", "content": "1\n/11\n0\n$ 245.000 + $37.300 expensas\nCORRIENTES 5700\nDepartamento en Alquiler en Villa Crespo, Capital Federal\n41 m\u00b2 cubie.\n30 a\u00f1os\n1 ba\u00f1o\nDepartamento de 1 ambiente en Alquiler en Villa crespo\n..........................Muy buen departamento de 1 y 1/2 amb con cocina independiente. Living en l divisible. Lavadero independiente, el edificio siempre muy bien conservado se encuentra ubcado en pleno centro comercial de villa crespo con numerosos comercio, medios de transporte a todos los puntos y a 4 cuadras de subte \"b\". Najas expensas . Se acepta seguro de caucion acreditado por la\nWhatsApp\nContactar", "revised": false, "rejected": true, "data": {"precio": "$ 245.000 + $37.300 expensas", "expensas": "+ $37.300 expensas", "direccion": "CORRIENTES 5700", "metros": "41 m\u00b2 cubie.", "habitaciones": "30 a\u00f1os"}, "image": "https://static1.sosiva451.com/09832651/0058f4d1-a491-48c6-917b-1d49424ae5f5_u_small.jpg"}, "https://www.argenprop.com/departamento-en-alquiler-en-villa-crespo-2-ambientes--15620925": {"date": "05-05-2024\n", "content": "1\n/11\n0\n$ 350.000\nCASTILLO 500\nDepartamento en Alquiler en Villa Crespo, Capital Federal\n35 m\u00b2 cubie.\n1 dorm.\n45 a\u00f1os\nDepartamento de 2 ambientes en Alquiler en Villa crespo\n2 luminosos ambientes con vista panoramica 2 aires acondic muy buenos placards proximo avenidas y diversos medio de transportes castillo al 500 informes comercializa migliorisi de corrientes 5500 srl profesional responsable diego f migliorisi cpi263 a30153 se deja constancia que las caracteristicas, medidas, expensas y superficies consignadas son aproximadas, sujetos a verificaci\u00f3n y/o ajuste.\nWhatsApp\nContactar", "revised": true, "rejected": true, "data": {"precio": "$ 350.000", "direccion": "CASTILLO 500", "metros": "35 m\u00b2 cubie.", "habitaciones": "1 dorm."}, "comment": "2 amb. Sin balc\u00f3n ", "image": "https://static1.sosiva451.com/52902651/22841d5c-7a76-4b26-8341-5309cdbbaf55_u_small.jpg"}, "https://www.argenprop.com/departamento-en-alquiler-en-villa-crespo-2-ambientes--15645984": {"date": "05-05-2024\n", "content": "1\n/6\n500\n$ 250.000\nDiego De Rojas 1800, Piso 2\u00ba\nDepartamento en Alquiler en Villa Crespo, Capital Federal\n35 m\u00b2 cubie.\n1 dorm.\n45 a\u00f1os\nDEPARTAMENTO DE DOS AMBIENTES LUMINOSO\nDeparamento muy luminoso a metros de av. Juan b. Justo recin pintado recepcion 4,50x3,50 dormiotiro c3x3 con placard ba\u00f1o completo cocina 2,90x1,50 con desayunador\nWhatsApp\nContactar", "revised": true, "rejected": true, "data": {"precio": "$ 250.000", "direccion": "Diego De Rojas 1800, Piso 2\u00ba", "metros": "35 m\u00b2 cubie.", "habitaciones": "1 dorm."}}, "https://www.argenprop.com/departamento-en-alquiler-en-almagro-norte-2-ambientes--15529136": {"date": "05-05-2024\n", "content": "1\n/9\n1\n$ 300\nLAVALLE 3700\nDepartamento en Alquiler en Almagro Norte, Almagro\n34 m\u00b2 cubie.\n1 dorm.\n1 ba\u00f1o\nDEPARTAMENTO 2 AMBIENTES EN LAVALLE 3700\nHermoso departamento en alquiler en almagro 2 ambientes contrafrente, muy luminoso, posee placard empotrado. \u00a1Muy buena ubicaci\u00f2n! A 2 cuadras de la utn de medrano, 1 cuadra de c\u00f2rdoba, 4 cuadras de corrientes, subte l\u00ecnea b, varias l\u00ecneas de colectivo, zona comercial. Mariela echeverr\u00eca negocios inmobiliarios matr\u00eccula cucicba n.\u00ba 6.941. - Kp311130 - kpd050510 - - publicado v\u00eda kiteprop crm\nContactar", "revised": false, "rejected": true, "data": {"precio": "$ 300", "direccion": "LAVALLE 3700", "metros": "34 m\u00b2 cubie.", "habitaciones": "1 dorm."}}, "https://www.argenprop.com/departamento-en-alquiler-en-almagro-2-ambientes--6068409": {"date": "05-05-2024\n", "content": "1\n/5\n2\n$ 290.000 + $50.000 expensas\nSan Luis 3300, Piso 4\nDepartamento en Alquiler en Almagro, Capital Federal\n30 m\u00b2 cubie.\n1 dorm.\n35 a\u00f1os\nAMOBLADO\nAmoblado. Piso 4 interno, muy luminoso. Cocina americana, ba\u00f1o completo. Expensas: $ 50.000. A 4 cuadras de la universidad de palermo. Seguinos por instagram arguellesasociadosinmobiliaria visite nuestro sitio web , en donde podr\u00e1 encontrar otras alternativas de departamentos amoblados.\nWhatsApp\nContactar", "revised": true, "rejected": false, "data": {"precio": "$ 290.000 + $50.000 expensas", "expensas": "+ $50.000 expensas", "direccion": "San Luis 3300, Piso 4", "metros": "30 m\u00b2 cubie.", "habitaciones": "1 dorm."}, "comment": "Safa. Sin balc\u00f3n "}, "https://www.argenprop.com/departamento-en-alquiler-en-san-nicolas-2-ambientes--15437576": {"date": "05-05-2024\n", "content": "1\n/9\n3.812\n$ 320.000 + $38.000 expensas\nRodr\u00edguez Pe\u00f1a 400, Piso 9\nDepartamento en Alquiler en San Nicol\u00e1s, Centro\n48 m\u00b2 cubie.\n1 dorm.\n45 a\u00f1os\nAMOBLADO - BALCON CORRIDO - MUY LUMINOSO - COCINA con COMEDOR DIARIO\nAmoblado. Piso 9\u00b0 al frente, muy luminoso. Balc\u00f3n corrido. Cocina con comedor diario. Lavadero independiente. Expensas: $ 38.000. Servicios individuales. Seguinos por instagram arguellesasociadosinmobiliaria visita nuestro sitio web\nWhatsApp\nContactar", "revised": true, "rejected": true, "data": {"precio": "$ 320.000 + $38.000 expensas", "expensas": "+ $38.000 expensas", "direccion": "Rodr\u00edguez Pe\u00f1a 400, Piso 9", "metros": "48 m\u00b2 cubie.", "habitaciones": "1 dorm."}, "comment": "Fea zona"}, "https://www.argenprop.com/departamento-en-alquiler-en-boedo-2-ambientes--15575536": {"date": "05-05-2024\n", "content": "1\n/13\n0\n$ 300.000 + $40.000 expensas\nSanchez de Loria al 1100\nDepartamento en Alquiler en Boedo, Capital Federal\n40 m\u00b2 cubie.\n1 dorm.\n6 a\u00f1os\n2 ambientes alquiler tradicional en Boedo\nSalaya romera propiedades ofrece en alquiler tradicional impecable departamento de 2 ambientes al contrafrente . El edificio, de muy buena calidad constructiva, tiene unos 6 a\u00f1os de antiguedad; es moderno en impecable estado. - 1 ascensor. - Amenities en el edificio ; presenta en la terraza comun : parrilla, solarium, pileta con hidromasaje, laundry con maquinas para lavar y\nWhatsApp\nContactar", "revised": true, "rejected": false, "data": {"precio": "$ 300.000 + $40.000 expensas", "expensas": "+ $40.000 expensas", "direccion": "Sanchez de Loria al 1100", "metros": "40 m\u00b2 cubie.", "habitaciones": "1 dorm."}, "comment": "Moderno. Fr\u00edo. Luminoso. Plaza boedo"}, "https://www.argenprop.com/departamento-en-alquiler-en-almagro-2-ambientes--15568619": {"date": "05-05-2024\n", "content": "1\n/8\n905\n$ 350.000 + $25.000 expensas\nPANAM\u00c1 900\nDepartamento en Alquiler en Almagro, Capital Federal\n32 m\u00b2 cubie.\n1 dorm.\n50 a\u00f1os\nALQUILER DEPARTAMENTO ALMAGRO 2 AMBIENTES\nAlquiler de departamento 2 ambientes en almagro, capital federal c\u00e1lido departamento a dos cuadras de parque centenario, en ante\u00faltimo piso, con buena luz y ventilaci\u00f3n. Cuenta con living comedor con balc\u00f3n franc\u00e9s y habitaci\u00f3n con espacio de guardado incorporado. Ba\u00f1o completo con ventilaci\u00f3n directa y cocina con lavadero incorporado. Ubicaci\u00f3n excepcional  - actualizaci\u00f3n trimestral seg\u00fan\nWhatsApp\nContactar", "revised": true, "rejected": true, "data": {"precio": "$ 350.000 + $25.000 expensas", "expensas": "+ $25.000 expensas", "direccion": "PANAM\u00c1 900", "metros": "32 m\u00b2 cubie.", "habitaciones": "1 dorm."}, "comment": "Est\u00e1 bien pero es caro"}, "https://www.argenprop.com/departamento-en-alquiler-en-balvanera-1-ambiente--15631898": {"date": "05-05-2024\n", "content": "1\n/53\n0\n$ 220.000 + $20.000 expensas\n24 de Noviembre al 1600\nDepartamento en Alquiler en Balvanera, Capital Federal\n30 m\u00b2 cubie.\n1 dorm.\n20 a\u00f1os\n1AMB \u00b7 30M\u00b2 \u00b7 f\u00e1cilmente divisible! placard! abert nvas! coc lav! td a estrenar!\nDepartamento 1 ambiente ! Totalmente reciclado a nuevo! #Alquiler | #departamento | #est\u00e1ndar | #1amb | #parquepatricios | #contrafrente 24 de noviembre y avenida juan de garay - ciudad aut\u00f3noma de buenos aires caracter\u00edsticas: ~departamento de un (1) ambiente totalmente reciclado a nuevo tanto est\u00e9tica como estructuralmente, en el l\u00edmite de los barrios de parque patricios y san\nWhatsApp\nContactar", "revised": false, "rejected": true, "data": {"precio": "$ 220.000 + $20.000 expensas", "expensas": "+ $20.000 expensas", "direccion": "24 de Noviembre al 1600", "metros": "30 m\u00b2 cubie.", "habitaciones": "1 dorm."}, "image": "https://static1.sosiva451.com/89813651/06a51a72-e74d-4233-81c2-ce703af2abb4_u_small.jpg"}, "https://www.argenprop.com/departamento-en-alquiler-en-boedo-1-ambiente--15631890": {"date": "05-05-2024\n", "content": "1\n/53\n0\n$ 220.000 + $20.000 expensas\n24 de Noviembre al 1600\nDepartamento en Alquiler en Boedo, Capital Federal\n30 m\u00b2 cubie.\n1 dorm.\n20 a\u00f1os\n1AMB \u00b7 30M\u00b2 \u00b7 f\u00e1cilmente divisible! placard! abert nvas! coc lav! td a estrenar!\nDepartamento 1 ambiente ! Totalmente reciclado a nuevo! #Alquiler | #departamento | #est\u00e1ndar | #1amb | #parquepatricios | #contrafrente 24 de noviembre y avenida juan de garay - ciudad aut\u00f3noma de buenos aires caracter\u00edsticas: ~departamento de un (1) ambiente totalmente reciclado a nuevo tanto est\u00e9tica como estructuralmente, en el l\u00edmite de los barrios de parque patricios y san\nWhatsApp\nContactar", "revised": false, "rejected": true, "data": {"precio": "$ 220.000 + $20.000 expensas", "expensas": "+ $20.000 expensas", "direccion": "24 de Noviembre al 1600", "metros": "30 m\u00b2 cubie.", "habitaciones": "1 dorm."}}, "https://www.argenprop.com/departamento-en-alquiler-en-san-cristobal-1-ambiente--15631902": {"date": "05-05-2024\n", "content": "1\n/53\n0\n$ 220.000 + $20.000 expensas\n24 de Noviembre al 1600\nDepartamento en Alquiler en San Cristobal, Capital Federal\n30 m\u00b2 cubie.\n1 dorm.\n20 a\u00f1os\n1AMB \u00b7 30M\u00b2 \u00b7 f\u00e1cilmente divisible! placard! abert nvas! coc lav! td a estrenar!\nDepartamento 1 ambiente ! Totalmente reciclado a nuevo! #Alquiler | #departamento | #est\u00e1ndar | #1amb | #parquepatricios | #contrafrente 24 de noviembre y avenida juan de garay - ciudad aut\u00f3noma de buenos aires caracter\u00edsticas: ~departamento de un (1) ambiente totalmente reciclado a nuevo tanto est\u00e9tica como estructuralmente, en el l\u00edmite de los barrios de parque patricios y san\nWhatsApp\nContactar", "revised": false, "rejected": true, "data": {"precio": "$ 220.000 + $20.000 expensas", "expensas": "+ $20.000 expensas", "direccion": "24 de Noviembre al 1600", "metros": "30 m\u00b2 cubie.", "habitaciones": "1 dorm."}}, "https://www.argenprop.com/departamento-en-alquiler-en-almagro-1-ambiente--15631894": {"date": "05-05-2024\n", "content": "1\n/53\n0\n$ 220.000 + $20.000 expensas\n24 de Noviembre al 1600\nDepartamento en Alquiler en Almagro, Capital Federal\n30 m\u00b2 cubie.\n1 dorm.\n20 a\u00f1os\n1AMB \u00b7 30M\u00b2 \u00b7 f\u00e1cilmente divisible! placard! abert nvas! coc lav! td a estrenar!\nDepartamento 1 ambiente ! Totalmente reciclado a nuevo! #Alquiler | #departamento | #est\u00e1ndar | #1amb | #parquepatricios | #contrafrente 24 de noviembre y avenida juan de garay - ciudad aut\u00f3noma de buenos aires caracter\u00edsticas: ~departamento de un (1) ambiente totalmente reciclado a nuevo tanto est\u00e9tica como estructuralmente, en el l\u00edmite de los barrios de parque patricios y san\nWhatsApp\nContactar", "revised": false, "rejected": true, "data": {"precio": "$ 220.000 + $20.000 expensas", "expensas": "+ $20.000 expensas", "direccion": "24 de Noviembre al 1600", "metros": "30 m\u00b2 cubie.", "habitaciones": "1 dorm."}}, "https://www.argenprop.com/departamento-en-alquiler-en-parque-patricios-1-ambiente--15631889": {"date": "05-05-2024\n", "content": "1\n/53\n0\n$ 220.000 + $20.000 expensas\n24 de Noviembre al 1600\nDepartamento en Alquiler en Parque Patricios, Capital Federal\n30 m\u00b2 cubie.\n1 dorm.\n20 a\u00f1os\n1AMB \u00b7 30M\u00b2 \u00b7 f\u00e1cilmente divisible! placard! abert nvas! coc lav! td a estrenar!\nDepartamento 1 ambiente ! Totalmente reciclado a nuevo! #Alquiler | #departamento | #est\u00e1ndar | #1amb | #parquepatricios | #contrafrente 24 de noviembre y avenida juan de garay - ciudad aut\u00f3noma de buenos aires caracter\u00edsticas: ~departamento de un (1) ambiente totalmente reciclado a nuevo tanto est\u00e9tica como estructuralmente, en el l\u00edmite de los barrios de parque patricios y san\nWhatsApp\nContactar", "revised": false, "rejected": true, "data": {"precio": "$ 220.000 + $20.000 expensas", "expensas": "+ $20.000 expensas", "direccion": "24 de Noviembre al 1600", "metros": "30 m\u00b2 cubie.", "habitaciones": "1 dorm."}}, "https://www.argenprop.com/departamento-en-alquiler-en-villa-crespo-2-ambientes--15646429": {"date": "05-05-2024\n", "content": "1\n/16\n0\n$ 295.000 + $119.000 expensas\nCamargo 300\nDepartamento en Alquiler en Villa Crespo, Capital Federal\n31 m\u00b2 cubie.\n1 dorm.\n44 a\u00f1os\nDEPARTAMENTO 2 AMBIENTES CONTRAFRENTE VILLA CRESPO\nDepartamento de 2 ambientes en alquiler ubicado en villa crespo. Primer piso al contrafrente, por ascensor. Cocina integrada al comedor, separados por una barra desayunadora. Cocina equipada con muebles de bajo mesada y alacena, conexion para lavarropas. Comedor con pisos de ceramico, equipo de aire acondicionado frio. Ba\u00f1o con ba\u00f1era. Dormitorio con pisos de parquet y dos placard\nWhatsApp\nContactar", "revised": false, "rejected": true, "data": {"precio": "$ 295.000 + $119.000 expensas", "expensas": "+ $119.000 expensas", "direccion": "Camargo 300", "metros": "31 m\u00b2 cubie.", "habitaciones": "1 dorm."}, "image": "https://static1.sosiva451.com/92464651/7aa457a4-65f1-47cb-a19d-5397f097eb5f_u_small.jpg"}, "https://www.argenprop.com/departamento-en-alquiler-en-balvanera-2-ambientes--15647124": {"date": "06-05-2024\n", "content": "1\n/5\n0\n$ 250.000 + $23.000 expensas\nRivadavia al 3000\nDepartamento en Alquiler en Balvanera, Capital Federal\n56 m\u00b2 cubie.\n1 dorm.\n11 a\u00f1os\nDPTO EN 3 AMB. ALQUILER\nAlquiler departamento en importante zona comercial muy luminoso el dpto cuenta con: -living comedor - 1 domitorio - cocina - ba\u00f1o completo -cocina en buen estado de conservaci\u00f3n. El edificio cuenta con seguridad y encargado. Excelente ubicaci\u00f3n con gran variedad de transportes -\nWhatsApp\nContactar", "revised": false, "rejected": true, "data": {"precio": "$ 250.000 + $23.000 expensas", "expensas": "+ $23.000 expensas", "direccion": "Rivadavia al 3000", "metros": "56 m\u00b2 cubie.", "habitaciones": "1 dorm."}, "image": "https://static1.sosiva451.com/42174651/6340653b-3869-4f03-ae06-9de94aaee04d_u_small.jpg"}, "https://www.argenprop.com/departamento-en-alquiler-en-congreso-2-ambientes--15632215": {"date": "06-05-2024\n", "content": "1\n/13\n0\n$ 250.000 + $55.000 expensas\nSARANDI 400\nDepartamento en Alquiler en Congreso, Capital Federal\n40 m\u00b2 cubie.\n1 dorm.\n2 ambientes\nDEPARTAMENTO 2 AMBIENTES - CONGRESO, CAPITAL FEDERAL\nAtencion: esta oferta se encuentra reservada. Excelente distribuci\u00f3n, recien pintado. Dormitorio con placard. Ba\u00f1o completo. Cocina, lavadero. Contrato a 2 a\u00f1os, con aumento cuatrimestral icl. 1 mes de deposito y 1 mes de alquiler adelantado. Garantia propietaria y . Superficie total uso propio uf: 40 m2 categor\u00eda del edificio: muy buena mes de expensas: abril oferta provista por sistema som\nWhatsApp\nContactar", "revised": false, "rejected": true, "data": {"precio": "$ 250.000 + $55.000 expensas", "expensas": "+ $55.000 expensas", "direccion": "SARANDI 400", "metros": "40 m\u00b2 cubie.", "habitaciones": "1 dorm."}, "comment": "Reservada", "image": "https://static1.sosiva451.com/51223651/67b09c1d-dcf6-4b64-806d-b0df6c78b22f_u_small.jpg"}, "https://www.argenprop.com/departamento-en-alquiler-en-monserrat-1-ambiente--15607541": {"date": "06-05-2024\n", "content": "1\n/13\n0\n$ 200.000 + $134.000 expensas\nCALVO CARLOS 1500\nDepartamento en Alquiler en Monserrat, Centro\n35 m\u00b2 cubie.\nMonoam.\nExcelente\nDEPARTAMENTO 1 AMBIENTE - MONSERRAT, CAPITAL FEDERAL\nRetasadooo excelente edificio con amenities, pileta, laundry, gimnasio, salon de fiestas, en perfecto funcionamiento. Un ambiente con kichinette, super luminoso y excelente vista a pileta. Todo el\u00e9ctrico. Balcon el l con parrilla. A 200 de av. Independencia y cercano a facultades, (uade y uba sociales) impecable superficie total uso propio uf: 38.56 m2 aire acondicionado: equip.Individ. Agua\nWhatsApp\nContactar", "revised": false, "rejected": true, "data": {"precio": "$ 200.000 + $134.000 expensas", "expensas": "+ $134.000 expensas", "direccion": "CALVO CARLOS 1500", "metros": "35 m\u00b2 cubie.", "habitaciones": "Monoam."}, "comment": "Muchas expensas ", "image": "https://static1.sosiva451.com/14570651/16e20cf8-c986-4ca5-a486-8fa32478bffa_u_small.jpg"}, "https://www.argenprop.com/departamento-en-alquiler-en-balvanera-2-ambientes--15603332": {"date": "06-05-2024\n", "content": "1\n/18\n0\n$ 295.000 + $96.000 expensas\nSan Luis al 2700\nDepartamento en Alquiler en Balvanera, Capital Federal\n40 m\u00b2 cubie.\n1 dorm.\n42 a\u00f1os\nAlquiler departamento de 2 ambientes en Balvanera\nAlquiler departamento 2 ambientes muy luminoso en balvanera (existe la posibilidad de alquilar la unidad amoblada a $/mes 350.000) - el valor mensual del alquiler se ajustar\u00e1 cada tres meses seg\u00fan \u00edndice ipc. - Departamento de 2 ambientes semipiso. Muy luminoso. Piso alto. Excelente ubicaci\u00f3n en la esquina de san luis y av. Pueyrred\u00f3n. - Medios de transportes\nWhatsApp\nContactar", "revised": false, "rejected": true, "data": {"precio": "$ 295.000 + $96.000 expensas", "expensas": "+ $96.000 expensas", "direccion": "San Luis al 2700", "metros": "40 m\u00b2 cubie.", "habitaciones": "1 dorm."}, "comment": "Caro", "image": "https://static1.sosiva451.com/23330651/ce5bbaf7-571d-4534-89b7-c414db86b3c1_u_small.jpg"}, "https://www.argenprop.com/departamento-en-alquiler-en-villa-crespo-1-ambiente--15647629": {"date": "06-05-2024\n", "content": "1\n/13\n0\n$ 300.000 + $105.000 expensas\nGurruchaga al 400\nDepartamento en Alquiler en Villa Crespo, Capital Federal\n31 m\u00b2 cubie.\n7 a\u00f1os\n1 ba\u00f1o\nAlquiler - Monoambiente - Villa Crespo\nHermoso monoambiente divisible en alquiler en la mejor zona de villa crespo. La unidad se puede optimizar colocando un mueble divisible en el living comedor, de tal forma de poder generar 2 ambientes separados. Cuenta con cocina el\u00e9ctrica integrada, ba\u00f1o completo y equipo de frio-calor ya instalado y balc\u00f3n al frente sobre calle gurruchaga. Ya tiene todos los artefactos\nWhatsApp\nContactar", "revised": false, "rejected": true, "data": {"precio": "$ 300.000 + $105.000 expensas", "expensas": "+ $105.000 expensas", "direccion": "Gurruchaga al 400", "metros": "31 m\u00b2 cubie.", "habitaciones": "7 a\u00f1os"}, "comment": "Caro", "image": "https://static1.sosiva451.com/92674651/7614d5d9-ea4a-4860-94b0-e7ca2248c5fa_u_small.jpg"}, "https://www.argenprop.com/departamento-en-alquiler-en-congreso-1-ambiente--15513656": {"date": "06-05-2024\n", "content": "1\n/15\n1\n$ 230.000\nURUGUAY 300\nDepartamento en Alquiler en Congreso, Capital Federal\n33 m\u00b2 cubie.\n1 dorm.\n40 a\u00f1os\nTRIBUNALES 1AMB MEDIO DIVISBLE FRENTE SUBTE: B, OPORTUNIDAD, USO VIVIENDA/ COMERCIAL\n# Tribunales oportunidad, de inversion para locacion comercial/ vivienda excelente 1 ambiente y medio divisible, casi esquina, frente banco ciudad y avenida corrientes inmejorable ubicacion uso dual- centros de ense\u00f1anza, comercios, establecimientos educacionales, tribunales apto vivienda y/ uso comercial valor del alquiler 240000 $ expsas 50.000 $ 6 piso al frente luminoso, 33 metros,\nContactar", "revised": false, "rejected": true, "data": {"precio": "$ 230.000", "direccion": "URUGUAY 300", "metros": "33 m\u00b2 cubie.", "habitaciones": "1 dorm."}, "comment": "Fea zona", "image": "https://static1.sosiva451.com/65631551/30f93f14-1081-4836-a1b1-ade4840866ea_u_small.jpg"}, "https://www.argenprop.com/departamento-en-alquiler-en-balvanera-2-ambientes--15637182": {"date": "06-05-2024\n", "content": "1\n/10\n1\n$ 350.000 + $30.000 expensas\nPasco al 100\nDepartamento en Alquiler en Balvanera, Capital Federal\n40 m\u00b2 cubie.\n1 dorm.\n40 a\u00f1os\nDepartamento de 2 amb en alquiler piso alto\nSe trata de un 2 amb amplio al frente piso 8vo con balcon a 2 cuadras del subte, a 1 cuadra de av rivadavia y a 4 cuadras de av entre rios condiciones: seguro de caucion aumentos cuatrimestrales deposito 1 mes matr\u00edcula y colegio: cucicba 5761 cmcpsm 2899\nWhatsApp\nContactar", "revised": true, "rejected": false, "data": {"precio": "$ 350.000 + $30.000 expensas", "expensas": "+ $30.000 expensas", "direccion": "Pasco al 100", "metros": "40 m\u00b2 cubie.", "habitaciones": "1 dorm."}, "comment": "Safa", "image": null}, "https://www.argenprop.com/departamento-en-alquiler-en-balvanera-1-ambiente--15612663": {"date": "06-05-2024\n", "content": "1\n/22\n200\n$ 350.000\nCHILE al 2200\nDepartamento en Alquiler en Balvanera, Capital Federal\n30 m\u00b2 cubie.\n6 a\u00f1os\n1 ba\u00f1o\nDepartamento - Balvanera\nMuy buen departamento de 1 ambiente con balcon en balvanera - 5o piso contrafrente - con baulera - todo electrico - super luminoso - superficie 33m2 - equipo de aire acondicionado frio/calor - a 1 cuadra de av independencia y rincon - alquiler con ajuste trimestral segun icl - atencion: el alquiler incluye expensas, abl, aguas y luz\nWhatsApp\nContactar", "revised": true, "rejected": true, "data": {"precio": "$ 350.000", "direccion": "CHILE al 2200", "metros": "30 m\u00b2 cubie.", "habitaciones": "6 a\u00f1os"}, "comment": "No hay gas", "image": null}, "https://www.argenprop.com/departamento-en-alquiler-en-almagro-2-ambientes--15308693": {"date": "06-05-2024\n", "content": "1\n/21\n0\n$ 280.000 + $35.000 expensas\nSANCHEZ DE BUSTAMANTE 200, Piso 6\nDepartamento en Alquiler en Almagro, Capital Federal\n40 m\u00b2 cubie.\n1 dorm.\n1 ba\u00f1o\nHERMOSO 2 AMBIENTES VISTA ABIERTA EN ALMAGRO.\nHermoso 2 ambientes vista abierta en almagro. En excelente ubicacion a 2 cuadras de av. Corrientes (subte b), a 2 cuadras de av. Diaz velez, a 7 cuadras de av. Pueyrredon y proximo a plaza almagro y al shopping abasto. Semipiso al contrafrente de 45 mts2 aprox., Todo externo y luminoso con amplios ambientes y sol de ma\u00f1ana en ambos ambientes, living comedor\nContactar", "revised": true, "rejected": false, "data": {"precio": "$ 280.000 + $35.000 expensas", "expensas": "+ $35.000 expensas", "direccion": "SANCHEZ DE BUSTAMANTE 200, Piso 6", "metros": "40 m\u00b2 cubie.", "habitaciones": "1 dorm."}, "comment": "Mono. Gran balcon. Frio", "image": "https://static1.sosiva451.com/39680351/ed9ca49e-07c7-4281-98d6-d4b8d943f9d8_u_small.jpg"}, "https://www.argenprop.com/departamento-en-alquiler-en-san-nicolas-1-ambiente--15524914": {"date": "06-05-2024\n", "content": "1\n/17\n1\n$ 250.000\nURUGUAY 300\nDepartamento en Alquiler en San Nicol\u00e1s, Centro\n33 m\u00b2 cubie.\n1 dorm.\n40 a\u00f1os\nTRIBUNALES,1AMB,MEDIO,DIVISIBLE frente,6piso,metros subte. buenas condiciones ingreso\n# Tribunales 1 ambiente digno de ver, frente luminoso 33 metros 6 piso; frente alquiler comercial 1 ambiente al frente tribunales, 1 ambiente medio, divisible, uso comercial vivienda :condiciones de ingreso: 1 mes de adelanto, 1 mes de dep\u00f2sito , ingresos reales demostrables ajuste trimestral del alquiler, con ipc garant\u00eca propietaria; /seguro de cauci\u00f2n o bien : 3 garantes m\u00ecnimo con\nContactar", "revised": false, "rejected": true, "data": {"precio": "$ 250.000", "direccion": "URUGUAY 300", "metros": "33 m\u00b2 cubie.", "habitaciones": "1 dorm."}, "comment": "Fea zona", "image": "https://static1.sosiva451.com/41942551/34e5e1e8-bc73-4da2-bbe9-bc2c24c9d8dd_u_small.jpg"}, "https://www.argenprop.com/departamento-en-alquiler-en-san-cristobal-2-ambientes--15635399": {"date": "06-05-2024\n", "content": "1\n/20\n50\n$ 350.000 + $48.000 expensas\nMatheu 900, Piso 5\nDepartamento en Alquiler en San Cristobal, Capital Federal\n38 m\u00b2 cubie.\n1 dorm.\nA Estrenar\n2 ambientes a estrenar con TERRAZA PROPIA - balcon, cocina americana, espacio para lavarropas\nLindo 2 ambientes a estrenar - semipiso cocina americana - ba\u00f1o completo - balcon corrido y terraza propia. - Aproximadamente 38 mts cubiertos mas balcon mas terraza propia. - Super luminoso.. Electrico. Buena ubicacion a 2 cuadras de av independencia y dos cuadras av. Jujuy. Un mes deposito y un mes adelanto - acrualizacion trimestral ( ipc. ). Garantia propietaris cap. Fed. O seguro de\nWhatsApp\nContactar", "revised": true, "rejected": false, "data": {"precio": "$ 350.000 + $48.000 expensas", "expensas": "+ $48.000 expensas", "direccion": "Matheu 900, Piso 5", "metros": "38 m\u00b2 cubie.", "habitaciones": "1 dorm."}, "comment": "Caro. Fr\u00edo. Terrazon", "image": "https://static1.sosiva451.com/99353651/57e44922-febf-46cb-b01b-af1e889c6fab_u_small.jpg"}, "https://www.argenprop.com/ph-en-alquiler-en-balvanera-2-ambientes--15542678": {"date": "06-05-2024\n", "content": "1\n/16\n1\n$ 300.000\nCATAMARCA 600\nPH en Alquiler en Balvanera, Capital Federal\n32 m\u00b2 cubie.\n1 dorm.\n42 a\u00f1os\nBALVANERA 2AMB PB PH EXC UBICACION BUEN ESTADO APTO PROFESIONAL/VIVIENDA/\n# Ph comercial o vivienda uso mixto# # alquiler# alquiler balvanera digno de ver , oportunidad alquiler digno de visitar #oportunidad# # magnifico departamento oportunidad digno de visitar# alquiler con seguro de caucion o garantia propietaria ph de 2 ambientes con patio bajo mantenimiento cerca subte h y avenidas buen estado general; sin gas electrico, o cocina a gas con garrafas\nContactar", "revised": false, "rejected": true, "data": {"precio": "$ 300.000", "direccion": "CATAMARCA 600", "metros": "32 m\u00b2 cubie.", "habitaciones": "1 dorm."}, "image": "https://static1.sosiva451.com/87624551/ecbc1479-c1f7-4663-b96a-c402e214fe61_u_small.jpg"}, "https://www.argenprop.com/departamento-en-alquiler-en-villa-crespo-1-ambiente--15536265": {"date": "06-05-2024\n", "content": "1\n/22\n0\n$ 350.000 + $56.000 expensas\nAvenida Corrientes 5500\nDepartamento en Alquiler en Villa Crespo, Capital Federal\n34 m\u00b2 cubie.\n2 a\u00f1os\n1 ba\u00f1o\nAlquiler Monoambiente con balc\u00f3n en Villa Crespo\nAlquiler departamento monoambiente con balc\u00f3n en villa crespo. 8vo piso al frente - muy luminoso cocina semi-integrada ba\u00f1o completo con ba\u00f1era balc\u00f3n al frente el edificio posee: gym - sum - terraza - laundry expensas mayo 2024: 64.000 ( incluye aysa) el abl y gas tambien estan incluidos actualmente en expensas hasta que vengan discriminados) requisitos: - contrato a 2 a\u00f1os - garantia caba o\nContactar", "revised": false, "rejected": true, "data": {"precio": "$ 350.000 + $56.000 expensas", "expensas": "+ $56.000 expensas", "direccion": "Avenida Corrientes 5500", "metros": "34 m\u00b2 cubie.", "habitaciones": "2 a\u00f1os"}, "image": "https://static1.sosiva451.com/56263551/6e1f2be4-f1b4-4f15-9bac-25c0745ac64e_u_small.jpg"}, "https://www.argenprop.com/departamento-en-alquiler-en-villa-crespo-1-ambiente--15557807": {"date": "06-05-2024\n", "content": "1\n/17\n959\n$ 300.000 + $37.000 expensas\nCamargo 100, Piso 2\nDepartamento en Alquiler en Villa Crespo, Capital Federal\n30 m\u00b2 cubie.\n2 a\u00f1os\n1 ba\u00f1o\nHermoso Monoamb, apenas dos a\u00f1os de uso, extraordinaria ubicaci\u00f3n\nDepartamento de un ambiente, apenas dos a\u00f1os de uso. Posee la ventana que permite el paso al balc\u00f3n y otra ventana m\u00e1s, que permite disponer de una divisi\u00f3n interesante para la cama. Ba\u00f1o compartimentado. Calefacci\u00f3n por piso radiante individual. Edificio con pileta y parrilla. Ubicaci\u00f3n verdaderamente privilegiada, a un paso del parque centenario, subte \"b\" y m\u00faltiples combinaciones.\nContactar", "revised": true, "rejected": true, "data": {"precio": "$ 300.000 + $37.000 expensas", "expensas": "+ $37.000 expensas", "direccion": "Camargo 100, Piso 2", "metros": "30 m\u00b2 cubie.", "habitaciones": "2 a\u00f1os"}, "comment": "Mono", "image": "https://static1.sosiva451.com/70875551/22726e2b-ffc5-4cc4-8a8d-7ab32e5123a6_u_small.jpg"}, "https://www.argenprop.com/departamento-en-alquiler-en-almagro-2-ambientes--15646983": {"date": "06-05-2024\n", "content": "1\n/21\n1\n$ 320.000 + $40.000 expensas\nPanama 900\nDepartamento en Alquiler en Almagro, Capital Federal\n35 m\u00b2 cubie.\n1 dorm.\n35 a\u00f1os\nPROPIEDAD RESERVADA 2 AMBIENTES | PANAMA al 900\nDepartamento en alquiler de dos ambientes contrafrente. Consta de living comedor con salida al balc\u00f3n, dormitorio con placards, ba\u00f1o completo, cocina completa, lavadero cubierto. Excelente ubicaci\u00f3n panama al 900 entre avda. Corrientes y sarmiento, proximo al subte b estaci\u00f3n angel gallardo, colectivos, comercios, parque centenario. Pida tasaci\u00f3n: efectuada por profesionales,\nWhatsApp\nContactar", "revised": true, "rejected": false, "data": {"precio": "$ 320.000 + $40.000 expensas", "expensas": "+ $40.000 expensas", "direccion": "Panama 900", "metros": "35 m\u00b2 cubie.", "habitaciones": "1 dorm."}, "comment": "Bueno. Caro", "image": "https://static1.sosiva451.com/38964651/b470056e-3b2b-477f-9258-14a7a5529608_u_small.jpg"}, "https://www.argenprop.com/departamento-en-alquiler-en-almagro-2-ambientes--15614840": {"date": "06-05-2024\n", "content": "1\n/14\n2\n$ 350.000 + $29.600 expensas\nSALGUERO, JERONIMO 600\nDepartamento en Alquiler en Almagro, Capital Federal\n38 m\u00b2 cubie.\n1 dorm.\n40 a\u00f1os\nAlquiler 2 Amb Lateral Luminoso en Almagro\nAlquiler de departamento 2 ambientes en octavo piso lateral luminoso! Hall de entrada, living comedor, cocina completa, lavadero externo, dormitorio con placard y ba\u00f1o completo. Todo electrico.  Magnifica ubicacion sobre la calle salguero entre av. Corrientes y humahuaca. A mts de principales lineas de colectivo, subte linea \"b\" estacion medrano y a siete cuadras de av. Rivadavia. Almagro,\nWhatsApp\nContactar", "revised": false, "rejected": true, "data": {"precio": "$ 350.000 + $29.600 expensas", "expensas": "+ $29.600 expensas", "direccion": "SALGUERO, JERONIMO 600", "metros": "38 m\u00b2 cubie.", "habitaciones": "1 dorm."}, "comment": "No hay gas", "image": "https://static1.sosiva451.com/04841651/425fee33-9f46-4caa-8658-504c9c490c73_u_small.jpg"}, "https://www.argenprop.com/departamento-en-alquiler-en-congreso-2-ambientes--15652080": {"id": "19068879", "date": "07-05-2024\n", "index": 1, "content": "1\n/19\n100\n$ 290.000 + $38.000 expensas\nAv Rivadavia 2300, Piso 2\u00ba\nDepartamento en Alquiler en Congreso, Capital Federal\n45 m\u00b2 cubie.\n1 dorm.\n55 a\u00f1os\n2 AMB 45 M2 SOBRE AV RIVADAVIA! CON O SIN MUEBLES\n2 amb,amplio contrafrente ,muy luminoso,muy bien ubicado-boca subte a-muy buen edificio! Orve inmobiliaria :cucicba matr\u00edcula 838 servicios: cloacas, gas\nContactar", "revised": false, "rejected": true, "data": {"precio": "$ 290.000 + $38.000 expensas", "expensas": "+ $38.000 expensas", "direccion": "Av Rivadavia 2300, Piso 2\u00ba", "metros": "45 m\u00b2 cubie.", "habitaciones": "1 dorm."}, "image": "https://static1.sosiva451.com/08025651/ff1d3b7c-3071-41ac-8740-f34b96ac2755_u_small.jpg", "title": "2 AMB  45 M2 SOBRE AV RIVADAVIA! CON O SIN MUEBLES"}, "https://www.argenprop.com/departamento-en-alquiler-en-once-2-ambientes--15651467": {"id": "19068266", "date": "07-05-2024\n", "index": 2, "content": "1\n/8\n1.150\n$ 280.000 + $40.000 expensas\nTucuman 2200\nDepartamento en Alquiler en Once, Capital Federal\n35 m\u00b2 cubie.\n1 dorm.\n1 ba\u00f1o\nLuminoso y silencioso departamento en alquiler en Once\nDepartamento de dos ambientes con mucha luz y aireado a dos cuadras de estaci\u00f3n de subte b pasteur, dos de avenida c\u00f3rdoba muy bien conectado. Terraza escaleras arriba de uso compartido.\nWhatsApp\nContactar", "revised": false, "rejected": true, "data": {"precio": "$ 280.000 + $40.000 expensas", "expensas": "+ $40.000 expensas", "direccion": "Tucuman 2200", "metros": "35 m\u00b2 cubie.", "habitaciones": "1 dorm."}, "image": "https://static1.sosiva451.com/76415651/72eb744a-6f8a-43a5-b6e6-301aef97c5f5_u_small.jpg", "title": "luminoso y silencioso departamento en alquiler en Once"}, "https://www.argenprop.com/departamento-en-alquiler-en-congreso-2-ambientes--15651568": {"id": "19068368", "date": "07-05-2024\n", "index": 8, "content": "1\n/12\n156\n$ 300.000 + $36.500 expensas\nCombate De Los Pozos 400, Piso 2\u00ba\nDepartamento en Alquiler en Congreso, Capital Federal\n40 m\u00b2 cubie.\n1 dorm.\n50 a\u00f1os\n2AMB COCINA,BA\u00d1O COMPLETO Y LAVADERO - POZOS Y BELGRANO\n2 amb 40 m2 cte de los pozos y belgrano ,muy buen estado,cocina equipada,ba\u00f1o completo y lavadero - muy buena ubicaci\u00f3n y estado\nContactar", "revised": false, "rejected": true, "data": {"precio": "$ 300.000 + $36.500 expensas", "expensas": "+ $36.500 expensas", "direccion": "Combate De Los Pozos 400, Piso 2\u00ba", "metros": "40 m\u00b2 cubie.", "habitaciones": "1 dorm."}, "image": null, "title": "2AMB COCINA,BA\u00d1O COMPLETO Y LAVADERO - POZOS Y BELGRANO"}, "https://www.argenprop.com/departamento-en-alquiler-en-almagro-sur-1-ambiente--15651560": {"id": "19068360", "date": "07-05-2024\n", "index": 9, "content": "1\n/16\n15\n$ 350.000 + $39.100 expensas\nVenezuela 3500, Piso 4\nDepartamento en Alquiler en Almagro Sur, Almagro\n35 m\u00b2 cubie.\n5 a\u00f1os\n1 ba\u00f1o\nMonoambiente a estrenar con balc\u00f3n, terraza y lavadero.\nMonoambiente 4er piso al contrafrente con balc\u00f3n y terraza, muy luminoso. Ba\u00f1o completo con ducha. Cocina integrada. Todo el\u00e9ctrico. Agua caliente por termo tanque el\u00e9ctrico. Aysa se pagan por expensas (no incluido en el valor informado) expensas $39100 perido abril 2024 aceptamos garant\u00eda respaldar: para iniciar su tramite copie y pegue el siguiente linck o cons\u00faltenos por whatsapp\nContactar", "revised": false, "rejected": true, "data": {"precio": "$ 350.000 + $39.100 expensas", "expensas": "+ $39.100 expensas", "direccion": "Venezuela 3500, Piso 4", "metros": "35 m\u00b2 cubie.", "habitaciones": "5 a\u00f1os"}, "image": "https://static1.sosiva451.com/06515651/0c433740-cc3f-4874-8f0f-d6e67d272218_u_small.jpg", "title": "Monoambiente a estrenar con balc\u00f3n, terraza y lavadero."}, "https://www.argenprop.com/departamento-en-alquiler-en-almagro-sur-1-ambiente--15651552": {"id": "19068352", "date": "07-05-2024\n", "index": 11, "content": "1\n/15\n15\n$ 260.000 + $19.300 expensas\nVenezuela 3500, Piso 3\nDepartamento en Alquiler en Almagro Sur, Almagro\n32 m\u00b2 cubie.\n5 a\u00f1os\n1 ba\u00f1o\nMonoambiente con balc\u00f3n muy bueno\nMonoambiente en tercer piso al contrafrente con balc\u00f3n, muy luminoso. Ba\u00f1o completo con ducha. Cocina integrada con espacios para heladera. Todo el\u00e9ctrico. Agua caliente por termo tanque el\u00e9ctrico. Aysa se pagan por expensas (no incluido en el valor informado) bajas expensas $19300 perido abril 2024 aceptamos garant\u00eda respaldar: para iniciar su tramite copie y pegue el siguiente linck o\nContactar", "revised": false, "rejected": true, "data": {"precio": "$ 260.000 + $19.300 expensas", "expensas": "+ $19.300 expensas", "direccion": "Venezuela 3500, Piso 3", "metros": "32 m\u00b2 cubie.", "habitaciones": "5 a\u00f1os"}, "image": null, "title": "Monoambiente con balc\u00f3n muy bueno"}, "https://www.argenprop.com/departamento-en-alquiler-en-villa-crespo-2-ambientes--15651478": {"id": "19068277", "date": "07-05-2024\n", "index": 14, "content": "1\n/15\n427\n$ 350.000 + $63.000 expensas\nMalabia 100\nDepartamento en Alquiler en Villa Crespo, Capital Federal\n38 m\u00b2 cubie.\n1 dorm.\n20 a\u00f1os\n2 ambientes balc\u00f3n vista abierta\nHermoso depto de 2 ambientes gran balcon con una vista abierta en piso 17 , cocina grande y totalmente equipada con amoblamientos de categoria. La cocina posee ventana al exterior. Todos los ambientes son abiertos y con ventanales lo que proporciona mucha luz y ventilacion. Placares grandes con interiores bien completos. Pisos de madera en excelente estado. Las expensas incluyen aysa con lo cual\nWhatsApp\nContactar", "revised": false, "rejected": true, "data": {"precio": "$ 350.000 + $63.000 expensas", "expensas": "+ $63.000 expensas", "direccion": "Malabia 100", "metros": "38 m\u00b2 cubie.", "habitaciones": "1 dorm."}, "image": "https://static1.sosiva451.com/87415651/6a8b8d9b-632e-4f8a-89d8-dc93280c2d90_u_small.jpg", "title": "2 ambientes balc\u00f3n vista abierta "}, "https://www.argenprop.com/departamento-en-alquiler-en-parque-centenario-1-ambiente--15575898": {"id": "18992814", "date": "07-05-2024\n", "index": 15, "content": "1\n/28\n2\n$ 350.000 + $35.000 expensas\nAntezana 500, Piso 4\nDepartamento en Alquiler en Parque Centenario, Capital Federal\n32 m\u00b2 cubie.\n1 dorm.\nA Estrenar\nEXC.MONO-AMB.A ESTRENAR EDIFICIO PREMIUM AMNITIES 0R NORTE VISTA PLAZA (GIM, SPA, PISCINA, ETC)\nEl mejor mono-ambiente, edificio premium en amenities varios balcon con vista a plaza totalmente departamento totalmente equipado, edificio posee laundry , sala de masajes, spa, gimnasio totalmente equipado, salon coworking, 2 salones de usos mutiples amueblados con living tv parrilla y horno pizzero, piscina con vista apaisajada super equipada, sauna, micro cine, salon de juegos varios. Expensas\nContactar", "revised": false, "rejected": true, "data": {"precio": "$ 350.000 + $35.000 expensas", "expensas": "+ $35.000 expensas", "direccion": "Antezana 500, Piso 4", "metros": "32 m\u00b2 cubie.", "habitaciones": "1 dorm."}, "image": "https://static1.sosiva451.com/89857551/8ce15980-2202-4a10-8e4b-bdc8b80e6244_u_small.jpg", "title": "EXC.MONO-AMB.A ESTRENAR EDIFICIO PREMIUM AMNITIES 0R NORTE VISTA PLAZA (GIM, SPA, PISCINA, ETC)"}, "https://www.argenprop.com/departamento-en-alquiler-en-san-nicolas-2-ambientes--15651363": {"id": "19068162", "date": "07-05-2024\n", "index": 17, "content": "1\n/13\n34\n$ 280.000 + $40.000 expensas\nSarmiento 1500, Piso 5\nDepartamento en Alquiler en San Nicol\u00e1s, Centro\n35 m\u00b2 cubie.\n1 dorm.\n50 a\u00f1os\nALQUILER - DEPARTAMENTO 2 AMBIENTES - MUY BUENA UBICACION - RECIEN PINTADO\nAlquiler departamento de 2 ambientes, 35 metros\u00b2, lateral, todo reci\u00e9n pintado, living comedor con piso de parquet plastificado, aire acondicionado y placard. Cocina completa con muebles bajo mesada y alacena. Dormitorio con piso de parquet plastificado. Ba\u00f1o completo con vaniroty y ventana. Expensas $40.000. Apto profesional. Pr\u00f3ximo a l\u00ednea de subre \"a\", \"b\" y \"c\" y muchas l\u00edneas de\nWhatsApp\nContactar", "revised": false, "rejected": true, "data": {"precio": "$ 280.000 + $40.000 expensas", "expensas": "+ $40.000 expensas", "direccion": "Sarmiento 1500, Piso 5", "metros": "35 m\u00b2 cubie.", "habitaciones": "1 dorm."}, "image": "https://static1.sosiva451.com/36315651/a5541e9f-7b19-4027-afee-9bf11853e224_u_small.jpg", "title": "ALQUILER - DEPARTAMENTO 2 AMBIENTES - MUY BUENA UBICACION - RECIEN PINTADO"}, "https://www.argenprop.com/departamento-en-alquiler-en-villa-crespo-1-ambiente--15415831": {"id": "18850731", "date": "07-05-2024\n", "index": 19, "content": "1\n/8\n2\n$ 330.000\nHumboldt al 800\nDepartamento en Alquiler en Villa Crespo, Capital Federal\n31 m\u00b2 cubie.\nA Estrenar\n1 ba\u00f1o\nMuy lindo monoambiente a estrenar con balc\u00f3n y ba\u00f1o completo. Todo luz\nAmplio monoambiente al contrafrente con balc\u00f3n. Vista abierta, muy luminoso. Cocina integrada con conexi\u00f3n para lavarropas. Ba\u00f1o completo. Edifico con terraza com\u00fan y parrilla. Servicios individuales. Cochera optativa valor $ 40.000.- Como el edificio a estrenar a\u00fan no hay valor de expensas disponible.\nWhatsApp\nContactar", "revised": false, "rejected": true, "data": {"precio": "$ 330.000", "direccion": "Humboldt al 800", "metros": "31 m\u00b2 cubie.", "habitaciones": "A Estrenar"}, "image": "https://static1.sosiva451.com/13851451/e898d67b-0d51-455a-9f7a-d5481b6e5342_u_small.jpg", "title": "Muy lindo monoambiente a estrenar con balc\u00f3n y ba\u00f1o completo. Todo luz "}, "https://www.argenprop.com/departamento-en-alquiler-en-almagro-2-ambientes--15491114": {"id": "18916994", "date": "07-05-2024\n", "index": 22, "content": "1\n/14\n2\n$ 280.000 + $74.000 expensas\nBillinghurst 400\nDepartamento en Alquiler en Almagro, Capital Federal\n36 m\u00b2 cubie.\n1 dorm.\n1 ba\u00f1o\n2 AMBIENTES CON BALCON FRANCES - AMOBLADO EN ALMAGRO\nAlquiler de departamento 2 ambientes amoblado en almagro, capital federal lindo departamento de 2 ambientes totalmente amoblado como figura en las fotos con cocina integrada, balc\u00f3n frances, piso 5. Ubicado a media cuadra de la importante avenida corrientes,  a metros de innumerables lineas de colectivo.  Aclaraci\u00f3n: - el propietario no acepta perros.  Contacto para visitas: para agendar una\nWhatsApp\nContactar", "revised": false, "rejected": true, "data": {"precio": "$ 280.000 + $74.000 expensas", "expensas": "+ $74.000 expensas", "direccion": "Billinghurst 400", "metros": "36 m\u00b2 cubie.", "habitaciones": "1 dorm."}, "image": "https://static1.sosiva451.com/41119451/5fbe6c5a-c9f3-4cb7-a30b-1cdffb991e67_u_small.jpg", "title": "2 AMBIENTES  CON BALCON FRANCES - AMOBLADO  EN ALMAGRO"}, "https://www.argenprop.com/departamento-en-alquiler-en-balvanera-2-ambientes--15540307": {"id": "18966227", "date": "07-05-2024\n", "index": 24, "content": "1\n/14\n0\n$ 290.000 + $65.000 expensas\nViamonte al 2400\nDepartamento en Alquiler en Balvanera, Capital Federal\n34 m\u00b2 cubie.\n1 dorm.\n60 a\u00f1os\nViamonte al 2400 - 2 amb - FACULTAD - Alquiler\nDepartamento de 2 ambientes - facultad - luminoso. Muy buen estado. Pisos parquet plastificados agua caliente central calefaccion por estufas electricas aire acondicionado living con estufa dormitorio con placard y aire acondicionado split cocina con cocina 4 hornallas con horno bajo mesada y alacenas ba\u00f1o completo con ba\u00f1era servicios individuales.\nContactar", "revised": false, "rejected": true, "data": {"precio": "$ 290.000 + $65.000 expensas", "expensas": "+ $65.000 expensas", "direccion": "Viamonte al 2400", "metros": "34 m\u00b2 cubie.", "habitaciones": "1 dorm."}, "image": "https://static1.sosiva451.com/70304551/0f008765-6000-413a-a4d9-ed331905e962_u_small.jpg", "title": "Viamonte al 2400 - 2 amb - FACULTAD - Alquiler"}, "https://www.argenprop.com/departamento-en-alquiler-en-almagro-2-ambientes--15559880": {"id": "18976803", "date": "07-05-2024\n", "index": 25, "content": "1\n/9\n1.092\n$ 350.000 + $50.000 expensas\nAvenida Corrientes 3100, Piso 14\nDepartamento en Alquiler en Almagro, Capital Federal\n41 m\u00b2 cubie.\n1 dorm.\n40 a\u00f1os\nCORRIENTES 3150 - 2 AMB CFTE - SUPER LUM - PISO ALTO\nCorrientes 3150 2 ambientes al contrafrente super luminoso piso alto cocina grande schwartz estudio inmobiliario srl j. Alvarez 2410 caba - 1425 48 21 - 22 00 w w w . S c h w a r t z . C o m . A r ii5060.6378whatsapp horario de atenci\u00f3n: de lunes a viernes de 14:00 a 19:00hs. Art. 4\u00b0 - hacer constar en todo ofrecimiento publicitario de locaci\u00f3n de inmuebles con destino habitacional que\nContactar", "revised": false, "rejected": true, "data": {"precio": "$ 350.000 + $50.000 expensas", "expensas": "+ $50.000 expensas", "direccion": "Avenida Corrientes 3100, Piso 14", "metros": "41 m\u00b2 cubie.", "habitaciones": "1 dorm."}, "image": "https://static1.sosiva451.com/08895551/c7265546-868d-4dc3-a3d9-84357eab003b_u_small.jpg", "title": "CORRIENTES 3150 - 2 AMB CFTE - SUPER LUM - PISO ALTO"}, "https://www.argenprop.com/departamento-en-alquiler-en-villa-crespo-1-ambiente--15651139": {"id": "19067937", "date": "07-05-2024\n", "index": 29, "content": "1\n/19\n0\n$ 250.000 + $27.000 expensas\nAV. CORRIENTES 5800, Piso 11\nDepartamento en Alquiler en Villa Crespo, Capital Federal\n30 m\u00b2 cubie.\n1 ba\u00f1o\nMonoam.\nHERMOSO DEPARTAMENTO DE 1 AMBIENTE EN ALQUILER\nHermoso departamento de 1 ambiente en alquiler en excelente ubicacion sobre av. Corrientes (subte b) a metros de av. Juan b. Justo (metrobus), proximo al ferrocarril san martin y al estadio movistar arena. Excelente departamento de 1 ambiente, doble entrada (principal y de servicio), cocina separada completa con muebles bajo mesada y alacena, lavadero independiente, ba\u00f1o completo. Todo\nContactar", "revised": false, "rejected": true, "data": {"precio": "$ 250.000 + $27.000 expensas", "expensas": "+ $27.000 expensas", "direccion": "AV. CORRIENTES 5800, Piso 11", "metros": "30 m\u00b2 cubie.", "habitaciones": "1 ba\u00f1o"}, "image": "https://static1.sosiva451.com/93115651/2489e98e-43ce-476b-bc37-69cd28dc162e_u_small.jpg", "title": "HERMOSO DEPARTAMENTO DE 1 AMBIENTE EN ALQUILER "}, "https://www.argenprop.com/departamento-en-alquiler-en-villa-crespo-1-ambiente--15651133": {"id": "19067931", "date": "07-05-2024\n", "index": 31, "content": "1\n/15\n1\n$ 300.000 + $39.000 expensas\nThames al 600\nDepartamento en Alquiler en Villa Crespo, Capital Federal\n35 m\u00b2 cubie.\nA Estrenar\n1 ba\u00f1o\nDepartamento - Villa Crespo\nMartillero responsable de esta propiedad romina cippolini, matr\u00edcula cucicba 7307. Oportunidad excelente departamento de un ambiente con amplia cocina separada, en excelente estado y cerca del subte y otros medios de transporte. Ar negocios inmobiliarios srl cucicba 7307 / cmzc 573 todas las propiedades publicadas est\u00e1n a cargo del profesional\nWhatsApp\nContactar", "revised": false, "rejected": true, "data": {"precio": "$ 300.000 + $39.000 expensas", "expensas": "+ $39.000 expensas", "direccion": "Thames al 600", "metros": "35 m\u00b2 cubie.", "habitaciones": "A Estrenar"}, "image": "https://static1.sosiva451.com/33115651/a2523360-f3ca-40fb-9baf-4a189a0fa5be_u_small.jpg", "title": "Departamento - Villa Crespo"}, "https://www.argenprop.com/departamento-en-alquiler-en-congreso-2-ambientes--15650808": {"id": "19067606", "date": "07-05-2024\n", "index": 35, "content": "1\n/16\n0\n$ 300.000 + $30.000 expensas\nJunin 300\nDepartamento en Alquiler en Congreso, Capital Federal\n35 m\u00b2 cubie.\n1 dorm.\n50 a\u00f1os\nHermoso departamento muy luminoso\nMuy buen departamento, monoambiente dividido con vestidor y cocina concepto abierto, con balc\u00f3n a la calle con vista al oeste, listo para habitar, reci\u00e9n reciclado .Apto profesional. Servicios: cloacas, gas otros servicios: balc\u00f3n terraza dep\u00f3sito (meses): 1 impuestos a cargo de: inquilino agua a cargo de: inquilino\nContactar", "revised": false, "rejected": true, "data": {"precio": "$ 300.000 + $30.000 expensas", "expensas": "+ $30.000 expensas", "direccion": "Junin 300", "metros": "35 m\u00b2 cubie.", "habitaciones": "1 dorm."}, "image": "https://static1.sosiva451.com/80805651/904196c8-eecd-4395-ba98-f49a7e4e3d84_u_small.jpg", "title": "Hermoso departamento muy luminoso "}, "https://www.argenprop.com/departamento-en-alquiler-en-san-cristobal-1-ambiente--15634239": {"id": "19051199", "date": "07-05-2024\n", "index": 36, "content": "1\n/17\n0\n$ 270.000 + $45.000 expensas\nAvenida Independencia al 2500\nDepartamento en Alquiler en San Cristobal, Capital Federal\n30 m\u00b2 cubie.\n5 a\u00f1os\n1 ba\u00f1o\nDepartamento en San Cristobal\nUral bienes ra\u00edces ofrece en alquiler departamento en edificio con frente a la avenida independencia entre calles alberti y saavedra en el barrio de san crist\u00f3bal la unidad en cuesti\u00f3n trata de un luminoso monoambiente ubicado en un 6to piso con balc\u00f3n al frente, este tiene cocina con muebles en alto y bajo mesada y ba\u00f1o completo. El edificio cuenta con sum, jacuzzi, sol\u00e1rium y parrilla excelente\nWhatsApp\nContactar", "revised": false, "rejected": true, "data": {"precio": "$ 270.000 + $45.000 expensas", "expensas": "+ $45.000 expensas", "direccion": "Avenida Independencia al 2500", "metros": "30 m\u00b2 cubie.", "habitaciones": "5 a\u00f1os"}, "image": "https://static1.sosiva451.com/93243651/54c3b09b-b54e-460a-a560-8e6f4d64976f_u_small.jpg", "title": "Departamento en San Cristobal"}, "https://www.argenprop.com/departamento-en-alquiler-en-balvanera-2-ambientes--15635683": {"id": "19052643", "date": "07-05-2024\n", "index": 40, "content": "1\n/8\n0\n$ 280.000 + $38.000 expensas\nCatamarca al 200\nDepartamento en Alquiler en Balvanera, Capital Federal\n54 m\u00b2 cubie.\n1 dorm.\n50 a\u00f1os\nALQUILER DPTO 2 AMB EN BALVANERA\nDepartamento de 2 ambientes en alquiler alquiler $280.000.- Expensas $38.000.- Depto ubicado en un sexto piso, interno. Reci\u00e9n pintado. Totalmente el\u00e9ctrico. Al ingresar lo hacemos al comedor diarios, que nos conecta directamente con la cocina independiente y el lavadero. Desde el comedor tambi\u00e9n accedemos a la habitaci\u00f3n principal con placard y desde la misma tambi\u00e9n al ba\u00f1o\nWhatsApp\nContactar", "revised": false, "rejected": true, "data": {"precio": "$ 280.000 + $38.000 expensas", "expensas": "+ $38.000 expensas", "direccion": "Catamarca al 200", "metros": "54 m\u00b2 cubie.", "habitaciones": "1 dorm."}, "image": "https://static1.sosiva451.com/38653651/4fc0a1a6-74cf-47fd-9138-cb63a9078fe8_u_small.jpg", "title": "ALQUILER DPTO 2 AMB EN BALVANERA"}, "https://www.argenprop.com/departamento-en-alquiler-en-balvanera-1-ambiente--15636788": {"id": "19053744", "date": "07-05-2024\n", "index": 48, "content": "1\n/11\n10\n$ 220.000 + $30.000 expensas\nSarmiento 1300\nDepartamento en Alquiler en Balvanera, Capital Federal\n30 m\u00b2 cubie.\n50 a\u00f1os\n1 ba\u00f1o\nMuy lindo y c\u00f3modo mono-ambiente super luminoso y en impecable estado.\nAmplio y luminoso mono-ambiente. Ubicado en piso alto al contra-frente con vista abierta. El ambiente posee dos amplios ventanales con persianas de madera. El ba\u00f1o es completo con ducha. La cocina posee horno y anafe el\u00e9ctrico y lugar para heladera. (No posee lugar para lavarropas) el departamento se encuentra en excelente estado; la cocina y el ba\u00f1os fueron refaccionados, el piso del ambiente\nWhatsApp\nContactar", "revised": false, "rejected": true, "data": {"precio": "$ 220.000 + $30.000 expensas", "expensas": "+ $30.000 expensas", "direccion": "Sarmiento 1300", "metros": "30 m\u00b2 cubie.", "habitaciones": "50 a\u00f1os"}, "image": "https://static1.sosiva451.com/88763651/0b26b869-e9e3-4706-b4c5-92354c755c66_u_small.jpg", "title": "Muy lindo y c\u00f3modo mono-ambiente super luminoso y en impecable estado."}, "https://www.argenprop.com/departamento-en-alquiler-en-congreso-2-ambientes--15612519": {"id": "19029463", "date": "07-05-2024\n", "index": 49, "content": "1\n/14\n3\n$ 350.000 + $60.000 expensas\nJUNIN 100, Piso 6\nDepartamento en Alquiler en Congreso, Capital Federal\n38 m\u00b2 cubie.\n1 dorm.\n50 a\u00f1os\nSEMIPISO AL FRENTE CON 2 BALCONES - MUY LUMINOSO, CONEXION LAVARROPA\nMuy luminoso living de 6.00 x 3.20 mts con acceso a balc\u00f3n de 2.00 x 1.20 mts y un placar de 2 puertas, pisos de parquet cocina de 2.50 x1.70 mts, conexi\u00f3n para lavarropas, con alacena y bajo mesada, aparato de cocina nueva dormitorio de 3.00 x 3.00 mts con amplio placard, con balc\u00f3n de 2.00 x 1.20 mts ba\u00f1o completo de 2.00 x1.60 mts todo reci\u00e9n pintado y acondicionado a nuevo edificio de 50\nWhatsApp\nContactar", "revised": false, "rejected": true, "data": {"precio": "$ 350.000 + $60.000 expensas", "expensas": "+ $60.000 expensas", "direccion": "JUNIN 100, Piso 6", "metros": "38 m\u00b2 cubie.", "habitaciones": "1 dorm."}, "image": "https://static1.sosiva451.com/91521651/3b56c818-2ae7-46b8-94eb-9cd580310355_u_small.jpg", "title": "SEMIPISO AL FRENTE CON 2 BALCONES - MUY LUMINOSO, CONEXION LAVARROPA"}, "https://www.argenprop.com/departamento-en-alquiler-en-san-cristobal-2-ambientes--15649711": {"id": "19066511", "date": "07-05-2024\n", "index": 50, "content": "1\n/11\n2\n$ 250.000 + $28.300 expensas\nLa Rioja 1200, Piso 2\nDepartamento en Alquiler en San Cristobal, Capital Federal\n33 m\u00b2 cubie.\n1 dorm.\n1 ba\u00f1o\n2 AMB,33 M2 TOT(APX),INTERNO,COCINA INDPTE,ESP P/LAVARROPA,BA\u00d1O COMP.,PLACARD,A PASOS AV. SAN JUAN\nInmueble en alquiler ubicado en el barrio de san crist\u00f3bal, frente a calle la rioja al 1200, a pasos de av. San juan, pr\u00f3ximo a la avenida jujuy. Transportes cercanos: colectivos: 4, 8, 23, 31, 32, 41, 46, 53, 56, 57, 62, 75, 86, 88, 91, 96, 97, 101, 118, 126, 127, 129, 143, 188, 195, y subtes (metro):humberto 1\u00b0 (l\u00ednea h), jujuy (l\u00ednea e), urquiza (l\u00ednea e).- Departamento de 2 ambientes, 33\nWhatsApp\nContactar", "revised": false, "rejected": true, "data": {"precio": "$ 250.000 + $28.300 expensas", "expensas": "+ $28.300 expensas", "direccion": "La Rioja 1200, Piso 2", "metros": "33 m\u00b2 cubie.", "habitaciones": "1 dorm."}, "image": "https://static1.sosiva451.com/11794651/f5cd7435-5a15-420f-b6dd-470d17a0d746_u_small.jpg", "title": "2 AMB,33 M2 TOT(APX),INTERNO,COCINA INDPTE,ESP P/LAVARROPA,BA\u00d1O COMP.,PLACARD,A PASOS AV. SAN JUAN"}, "https://www.argenprop.com/departamento-en-alquiler-en-villa-crespo-2-ambientes--15649910": {"id": "19066710", "date": "07-05-2024\n", "index": 53, "content": "1\n/21\n0\n$ 330.000 + $22.000 expensas\nAguirre 700\nDepartamento en Alquiler en Villa Crespo, Capital Federal\n38 m\u00b2 cubie.\n1 dorm.\n19 a\u00f1os\nAlquiler departamento dos ambientes villa crespo\nConoces villa crespo ? Quisieras vivir en este tradicional barrio de buenos aires que tiene una ubicaci\u00f3n privilegiada en la ciudad ? Disfruta este alquiler de un muy lindo dos ambientes con patio en villa crespo. Se encuentra en la planta baja , siendo el consorcio de solo planta baja y primer piso . Cuenta con un dormitorio con gran placar , cocina , living , un ba\u00f1o completo y patio . Todos\nContactar", "revised": false, "rejected": false, "data": {"precio": "$ 330.000 + $22.000 expensas", "expensas": "+ $22.000 expensas", "direccion": "Aguirre 700", "metros": "38 m\u00b2 cubie.", "habitaciones": "1 dorm."}, "image": "https://static1.sosiva451.com/01994651/c8f29dae-24fe-4887-8691-c561628091be_u_small.jpg", "title": "Alquiler departamento dos ambientes villa crespo"}, "https://www.argenprop.com/departamento-en-alquiler-en-almagro-1-ambiente--15489699": {"id": "18915578", "date": "07-05-2024\n", "index": 56, "content": "1\n/9\n0\n$ 300.000 + $29.010 expensas\nTte. Juan Domingo Per\u00f3n 4000\nDepartamento en Alquiler en Almagro, Capital Federal\n35 m\u00b2 cubie.\n10 a\u00f1os\n1 ba\u00f1o\nALQUILER MONOAMBIENTE C/ BALCON LUMINOSO - ALMAGRO\nAlquiler monoambiente con balcon luminoso en almagro monoambiente en alquiler, ubicado en piso 1\u00b0 al frente y muy luminoso. Todos sus ambientes ventilas al exterior. El departamento se encuentra dividido de la siguiente manera: - amplio ambiente con salida al balc\u00f3n - cocina integrada - balc\u00f3n - ba\u00f1o completo con ba\u00f1era expensas de referencia: $29.010.- Mes de febrero 2024 transportes\nContactar", "revised": false, "rejected": true, "data": {"precio": "$ 300.000 + $29.010 expensas", "expensas": "+ $29.010 expensas", "direccion": "Tte. Juan Domingo Per\u00f3n 4000", "metros": "35 m\u00b2 cubie.", "habitaciones": "10 a\u00f1os"}, "image": null, "title": "ALQUILER MONOAMBIENTE C/ BALCON LUMINOSO - ALMAGRO"}, "https://www.argenprop.com/departamento-en-alquiler-en-almagro-2-ambientes--15538022": {"id": "18963943", "date": "07-05-2024\n", "index": 58, "content": "1\n/16\n8\n$ 290.000 + $21.500 expensas\nDr J Valentin Gomez 3400, Piso 1\nDepartamento en Alquiler en Almagro, Capital Federal\n50 m\u00b2 cubie.\n1 dorm.\n35 a\u00f1os\nDepartamento en Alquiler 2 Ambientes amplios Lavadero independiente\nMuy buen departamento de 2 ambientes amplios cocina bien equipada con salida a lavadero lugar para lavarropa.-Comedor con equipo de aire acondicionado split frio/calor. Pisos de parquet plastificados.. Ba\u00f1o completo con ba\u00f1era en dormitorio amplio placard reci\u00e9n pintado. A 2 cuadras de shoping abasto, estaci\u00f3n de subte b carlos gardel,y 1 cuadra de av. Corrientes inmobiliaria kleiner de 10 a\nWhatsApp\nContactar", "revised": false, "rejected": true, "data": {"precio": "$ 290.000 + $21.500 expensas", "expensas": "+ $21.500 expensas", "direccion": "Dr J Valentin Gomez 3400, Piso 1", "metros": "50 m\u00b2 cubie.", "habitaciones": "1 dorm."}, "image": "https://static1.sosiva451.com/22083551/d1f20497-ba5a-4922-8122-ef4b1a81de3b_u_small.jpg", "title": "Departamento en Alquiler 2 Ambientes amplios Lavadero independiente"}, "https://www.argenprop.com/departamento-en-alquiler-en-monserrat-2-ambientes--8456738": {"id": "11969343", "date": "07-05-2024\n", "index": 61, "content": "1\n/13\n1\n$ 280.000 + $28.000 expensas\nBol\u00edvar 600, Piso 1\nDepartamento en Alquiler en Monserrat, Centro\n36 m\u00b2 cubie.\n1 dorm.\n60 a\u00f1os\nDepartamento 2 ambientes\nDepartamento 2 ambientes en duplex. Luminoso. Bajas expensas. Contrato por dos a\u00f1os con aumento cuatrimestral por ipc requisitos: - mes de adelanto - mes de dep\u00f3sito - garant\u00eda de caba (exclusivamente) - demostraci\u00f3n de ingresos servicios: gas dep\u00f3sito (meses): 1 impuestos a cargo de: propietario agua a cargo de: inquilino para los casos de alquiler de vivienda, el monto m\u00e1ximo de comisi\u00f3n\nWhatsApp\nContactar", "revised": false, "rejected": false, "data": {"precio": "$ 280.000 + $28.000 expensas", "expensas": "+ $28.000 expensas", "direccion": "Bol\u00edvar 600, Piso 1", "metros": "36 m\u00b2 cubie.", "habitaciones": "1 dorm."}, "image": "https://static1.sosiva451.com/8376548/3d36196b-a883-4dd7-95da-671efbe1111d_u_small.jpg", "title": "Departamento 2 ambientes "}, "https://www.argenprop.com/departamento-en-alquiler-en-san-nicolas-2-ambientes--15613349": {"id": "19030293", "date": "07-05-2024\n", "index": 67, "content": "1\n/7\n500\n$ 300.000 + $50.862 expensas\nUruguay 800, Piso 1\nDepartamento en Alquiler en San Nicol\u00e1s, Centro\n35 m\u00b2 cubie.\n1 dorm.\n50 a\u00f1os\n3290ID- alquiler/venta 2 ambientes Uruguay 800 San Nicolas\nDepartamento de dos ambientes amoblados con quitchenette y ba\u00f1o completo. Interno, luz 8. Se alquila por 1 a\u00f1o con opci\u00f3n a m\u00e1s. Dos personas solas. Sin chicos y sin mascotas. Reajustable cada tres meses por el \u00edndice de precios al consumidor. Venta u$s 80.000\nWhatsApp\nContactar", "revised": false, "rejected": false, "data": {"precio": "$ 300.000 + $50.862 expensas", "expensas": "+ $50.862 expensas", "direccion": "Uruguay 800, Piso 1", "metros": "35 m\u00b2 cubie.", "habitaciones": "1 dorm."}, "image": "https://static1.sosiva451.com/94331651/5aad6755-7a5e-4b4e-a0a2-cea6d3a445ba_u_small.jpg", "title": "3290ID- alquiler/venta 2 ambientes Uruguay 800 San Nicolas"}, "https://www.argenprop.com/departamento-en-alquiler-en-villa-crespo-2-ambientes--15604628": {"id": "19021567", "date": "07-05-2024\n", "index": 69, "content": "1\n/28\n0\n$ 350.000 + $72.452 expensas\nVelasco al 900 Piso 3\u00ba\nDepartamento en Alquiler en Villa Crespo, Capital Federal\n40 m\u00b2 cubie.\n1 dorm.\n5 a\u00f1os\n2 ambientes en alquiler con balc\u00f3n apto mascota en Villa Crespo\nDepartamento de 2 ambientes con cocina americana, balc\u00f3n y ba\u00f1o completo. Todos los ambientes con luz natural. Contrafrente edificio ubicado en el l\u00edmite entre palermo y villa crespo. Zona de outlets y distrito gastron\u00f3mico. Se entrega con artefactos de luz en todos los ambientes, rollers en dormitorio, living y 2 aires acondicionado fr\u00edo/calor. Todo\nWhatsApp\nContactar", "revised": false, "rejected": false, "data": {"precio": "$ 350.000 + $72.452 expensas", "expensas": "+ $72.452 expensas", "direccion": "Velasco al 900 Piso 3\u00ba", "metros": "40 m\u00b2 cubie.", "habitaciones": "1 dorm."}, "image": "https://static1.sosiva451.com/82640651/25de989f-2c07-4ecc-84d4-c236f437b750_u_small.jpg", "title": "2 ambientes  en alquiler con balc\u00f3n apto mascota en Villa Crespo"}, "https://www.argenprop.com/departamento-en-alquiler-en-almagro-sur-2-ambientes--15542415": {"id": "18968335", "date": "07-05-2024\n", "index": 72, "content": "1\n/19\n20\n$ 280.000 + $65.000 expensas\nAvenida Boedo 100, Piso 2\nDepartamento en Alquiler en Almagro Sur, Almagro\n38 m\u00b2 cubie.\n1 dorm.\n60 a\u00f1os\nEXCELENTE UBICACI\u00d3N \"Boedo 105\", DEPARTAMENTO 2 AMBIENTES CON BALC\u00d3N FRANCES AL FRENTE\nHermoso departamento 2 ambientes, 2do. Piso por escalera, living comedor, 1 habitaci\u00f3n con gran disponibilidad de placares, cocina completa con anafe y horno el\u00e9ctricos, barra desayunadora, ba\u00f1o completo, pisos de parquet y flotante. Excelente ubicaci\u00f3n, a 1 cuadra de av. Rivadavia, a 2 cuadras del subte linea a estaci\u00f3n \"castro barros\" m\u00e1s de 10 lineas de colectivo por la\nWhatsApp\nContactar", "revised": false, "rejected": false, "data": {"precio": "$ 280.000 + $65.000 expensas", "expensas": "+ $65.000 expensas", "direccion": "Avenida Boedo 100, Piso 2", "metros": "38 m\u00b2 cubie.", "habitaciones": "1 dorm."}, "image": "https://static1.sosiva451.com/51424551/667dfb9f-0396-4b54-8fde-61266f5b7e3b_u_small.jpg", "title": "EXCELENTE UBICACI\u00d3N \"Boedo 105\", DEPARTAMENTO 2 AMBIENTES CON BALC\u00d3N FRANCES AL FRENTE"}, "https://www.argenprop.com/departamento-en-alquiler-en-congreso-2-ambientes--15641036": {"id": "19057988", "date": "07-05-2024\n", "index": 77, "content": "1\n/7\n100\n$ 300.000\nBartolom\u00e9 Mitre 1900, Piso 9\nDepartamento en Alquiler en Congreso, Capital Federal\n35 m\u00b2 cubie.\n1 dorm.\n1 ba\u00f1o\n2 AMB BARTOLOME MITRE 1949 9 ( BARRIO:CONGRESO)\n2 amb bartolome mitre 1949 9 ( barrio:congreso), departamento con vista panoramica, 100%luminoso, entre ayacucho y riobamba, pisos parquet, living comedor, dormitorio y, cocina y ba\u00f1o completo.\nContactar", "revised": false, "rejected": false, "data": {"precio": "$ 300.000", "direccion": "Bartolom\u00e9 Mitre 1900, Piso 9", "metros": "35 m\u00b2 cubie.", "habitaciones": "1 dorm."}, "image": "https://static1.sosiva451.com/63014651/b9ced328-3da4-48fe-a02f-155bf89e9654_u_small.jpg", "title": "2 AMB BARTOLOME MITRE 1949 9 ( BARRIO:CONGRESO)"}, "https://www.argenprop.com/departamento-en-alquiler-en-balvanera-2-ambientes--15649067": {"id": "19065865", "date": "07-05-2024\n", "index": 81, "content": "1\n/19\n0\n$ 250.000 + $19.000 expensas\nAV. BELGRANO 2600, Piso 9\nDepartamento en Alquiler en Balvanera, Capital Federal\n33 m\u00b2 cubie.\n1 dorm.\n30 a\u00f1os\nSUPER LUMINOSO EN EXC ESTADO Y EN INMEJORABLE UBICACI\u00d3N\nDos ambientes en alquiler en balvanera ingreso al living comedor, super amplio y luminoso  \u00a1Hall de distribuci\u00f3n el cual nos dirige a la habitaci\u00f3n, muy luminosa con amplio espacio de guardado!  Cocina completa con muebles bajo mesada y alacena, artefacto de cocina a gas, lavadero independiente con conexi\u00f3n para lavaropas ba\u00f1o completo con ventilaci\u00f3n natural  todo en excelente estado,\nContactar", "revised": false, "rejected": false, "data": {"precio": "$ 250.000 + $19.000 expensas", "expensas": "+ $19.000 expensas", "direccion": "AV. BELGRANO 2600, Piso 9", "metros": "33 m\u00b2 cubie.", "habitaciones": "1 dorm."}, "image": "https://static1.sosiva451.com/76094651/478f11d8-a7d5-46b5-a920-3d3e4a464706_u_small.jpg", "title": " SUPER LUMINOSO EN EXC ESTADO Y EN INMEJORABLE UBICACI\u00d3N "}, "https://www.argenprop.com/departamento-en-alquiler-en-parque-patricios-2-ambientes--15649046": {"id": "19065844", "date": "07-05-2024\n", "index": 82, "content": "1\n/15\n0\n$ 330.000 + $35.000 expensas\nAv. Jujuy al 2000\nDepartamento en Alquiler en Parque Patricios, Capital Federal\n35 m\u00b2 cubie.\n1 dorm.\n38 a\u00f1os\nDos ambientes con patio a metros del Subte.\nCl\u00e1sico departamento de 2 ambientes interno con patio. Dormitorio con placard; living comedor; cocina independiente equipada (con salida al lavadero y patio totalmente) , ba\u00f1o completo con ducha; patio con lavadero. Muy buen estado general, pisos de parquet y cer\u00e1micos. A metros del subterr\u00e1neo l\u00ednea h estaci\u00f3n caseros. Digno de ver.\nWhatsApp\nContactar", "revised": false, "rejected": false, "data": {"precio": "$ 330.000 + $35.000 expensas", "expensas": "+ $35.000 expensas", "direccion": "Av. Jujuy al 2000", "metros": "35 m\u00b2 cubie.", "habitaciones": "1 dorm."}, "image": "https://static1.sosiva451.com/64094651/3cb9fe5f-7ad0-440b-8815-dfbd3d4ce27c_u_small.jpg", "title": "Dos ambientes con patio a metros del Subte."}, "https://www.argenprop.com/departamento-en-alquiler-en-balvanera-2-ambientes--14765135": {"id": "18209947", "date": "07-05-2024\n", "index": 92, "content": "1\n/18\n1\n$ 350.000\nCastelli 100\nDepartamento en Alquiler en Balvanera, Capital Federal\n38 m\u00b2 cubie.\n1 dorm.\n35 a\u00f1os\nAlquiler dos ambientes amoblado temporario\nDepartamento 2 ambientes amoblado - balbanera amplio departamento de dos ambientes ubicado en el coraz\u00f3n de barrio de balvanera ,rodeado de numerosos restaurantes, bares y todo tipo de comercios. El departamento cuenta con un c\u00f3modo living comedor, con pisos de parquet, el cual cuenta con un juego de comedor para 4 comensales, sof\u00e1 de dos cuerpos . La cocina se encuentra completamente equipada,\nContactar", "revised": false, "rejected": false, "data": {"precio": "$ 350.000", "direccion": "Castelli 100", "metros": "38 m\u00b2 cubie.", "habitaciones": "1 dorm."}, "image": null, "title": "Alquiler dos ambientes amoblado temporario"}, "https://www.argenprop.com/departamento-en-alquiler-en-san-cristobal-2-ambientes--8124043": {"id": "11698535", "date": "07-05-2024\n", "index": 94, "content": "1\n/12\n94\n$ 280.000 + $59.000 expensas\nLa Rioja 1600, Piso 5\nDepartamento en Alquiler en San Cristobal, Capital Federal\n36 m\u00b2 cubie.\n1 dorm.\n40 a\u00f1os\nDepartamento 2 ambientes Reciclado a metros del Metrobus\n\u00a1Descubre tu nuevo departamento en el vibrante barrio de san crist\u00f3bal! Este departamento de 2 ambientes, se ofrece en alquiler completamente reciclado, te brinda la oportunidad de disfrutar de la comodidad y la belleza en un solo lugar. Ubicado a pocos metros del metrob\u00fas y a unas cuadras del subte h, tendr\u00e1s un acceso inigualable a todas las atracciones que la ciudad tiene para ofrecer. Desde\nWhatsApp\nContactar", "revised": false, "rejected": false, "data": {"precio": "$ 280.000 + $59.000 expensas", "expensas": "+ $59.000 expensas", "direccion": "La Rioja 1600, Piso 5", "metros": "36 m\u00b2 cubie.", "habitaciones": "1 dorm."}, "image": "https://static1.sosiva451.com/3404218/76532c29-3f55-4db3-8f66-7753fc11b0c0_u_small.jpg", "title": "Departamento 2 ambientes Reciclado a metros del Metrobus"}, "https://www.argenprop.com/departamento-en-alquiler-en-monserrat-1-ambiente--15648436": {"id": "19065232", "date": "07-05-2024\n", "index": 95, "content": "1\n/15\n0\n$ 260.000 + $35.000 expensas\nAV.BELGRANO 1600, Piso 12\nDepartamento en Alquiler en Monserrat, Centro\n35 m\u00b2 cubie.\n15 a\u00f1os\n1 ba\u00f1o\nDepartamento - Alquiler - Argentina, Capital Federal - AV.BELGRANO 1600\nAlquiler - monoambiente - momserrat  av belgrano y solis monoambiente 7 x 4  con ventanal , balcon al contrafrente hermosa vista abierta  ba\u00f1o completo cocina incorporada , con espacio para conectar lavarropa  departamento con muy buena ubicacion a metros de la estacion de subte linea c y varias lineas de colectivos se alquila con seguro de caucion premium group, recibos de sueldo\nWhatsApp\nContactar", "revised": false, "rejected": false, "data": {"precio": "$ 260.000 + $35.000 expensas", "expensas": "+ $35.000 expensas", "direccion": "AV.BELGRANO 1600, Piso 12", "metros": "35 m\u00b2 cubie.", "habitaciones": "15 a\u00f1os"}, "image": "https://static1.sosiva451.com/63484651/2bec7c68-10bd-4560-bac8-8f81db1a3a2d_u_small.jpg", "title": "Departamento - Alquiler - Argentina, Capital Federal - AV.BELGRANO 1600"}, "https://www.argenprop.com/departamento-en-alquiler-en-almagro-2-ambientes--15617484": {"id": "19034434", "date": "07-05-2024\n", "index": 96, "content": "1\n/12\n0\n$ 280.000 + $32.000 expensas\nDiaz V\u00e9lez 4100, Piso 7\nDepartamento en Alquiler en Almagro, Capital Federal\n35 m\u00b2 cubie.\n1 dorm.\n55 a\u00f1os\n2 ambientes al frente con balc\u00f3n y lavadero, todo luz y sol.\n2 ambientes al frente con balc\u00f3n y lavadero independiente s\u00faper luminoso y aireado. Muy buena zona, cerca de todo. Ajuste cuatrimestral por ipc. Para los casos de alquiler de vivienda, el monto m\u00e1ximo de comisi\u00f3n que se le puede requerir a los propietarios ser\u00e1 el equivalente al cuatro con quince cent\u00e9simos por ciento (4,15%) del valor total del respectivo contrato. Se encuentra prohibido cobrar\nWhatsApp\nContactar", "revised": false, "rejected": false, "data": {"precio": "$ 280.000 + $32.000 expensas", "expensas": "+ $32.000 expensas", "direccion": "Diaz V\u00e9lez 4100, Piso 7", "metros": "35 m\u00b2 cubie.", "habitaciones": "1 dorm."}, "image": "https://static1.sosiva451.com/48471651/87212cd4-2d5b-4c64-a326-ad75d9a9c603_u_small.jpg", "title": "2 ambientes al frente con balc\u00f3n y lavadero, todo luz y sol."}, "https://www.argenprop.com/departamento-en-alquiler-en-almagro-2-ambientes--15556689": {"id": "18973608", "date": "07-05-2024\n", "index": 97, "content": "1\n/23\n0\n$ 340.000 + $35.000 expensas\nAv. Juan B. Alberdi 500, Piso 3\nDepartamento en Alquiler en Almagro, Capital Federal\n42 m\u00b2 cubie.\n1 dorm.\n1 ba\u00f1o\n2 amb. Av. Juan B. Alberdi 500, lateral, 45m2 balcon\nAlquiler amplio departamento de 2 ambientes, 3\u00ba piso al lateral con balc\u00f3n, en buen estado, 45 m2 totales. Ubicado en av. Juan b. Alberdi 500, entre av. Jos\u00e9 m. Moreno y riglos, en el barrio de caballito, caba el mismo se complone de living comedor con ventilador y salida al balc\u00f3n, muy amplia cocina con comedor diario y lavadero integrado, hall de distribuci\u00f3n, ba\u00f1o completo y dormitorio con\nWhatsApp\nContactar", "revised": false, "rejected": false, "data": {"precio": "$ 340.000 + $35.000 expensas", "expensas": "+ $35.000 expensas", "direccion": "Av. Juan B. Alberdi 500, Piso 3", "metros": "42 m\u00b2 cubie.", "habitaciones": "1 dorm."}, "image": "https://static1.sosiva451.com/98665551/f2c51cbd-bdd6-4bfb-a06a-f837cbbcb1c0_u_small.jpg", "title": "2 amb. Av. Juan B. Alberdi 500, lateral, 45m2 balcon"}, "https://www.argenprop.com/departamento-en-alquiler-en-boedo-2-ambientes--15556695": {"id": "18973614", "date": "07-05-2024\n", "index": 98, "content": "1\n/23\n0\n$ 340.000 + $35.000 expensas\nAv. Juan B. Alberdi 500, Piso 3\nDepartamento en Alquiler en Boedo, Capital Federal\n42 m\u00b2 cubie.\n1 dorm.\n1 ba\u00f1o\n2 amb. Av. Juan B. Alberdi 500, lateral, 45m2\nAlquiler amplio departamento de 2 ambientes, 3\u00ba piso al lateral con balc\u00f3n, en buen estado, 45 m2 totales. Ubicado en av. Juan b. Alberdi 500, entre av. Jos\u00e9 m. Moreno y riglos, en el barrio de caballito, caba el mismo se complone de living comedor con ventilador y salida al balc\u00f3n, muy amplia cocina con comedor diario y lavadero integrado, hall de distribuci\u00f3n, ba\u00f1o completo y dormitorio con\nWhatsApp\nContactar", "revised": false, "rejected": false, "data": {"precio": "$ 340.000 + $35.000 expensas", "expensas": "+ $35.000 expensas", "direccion": "Av. Juan B. Alberdi 500, Piso 3", "metros": "42 m\u00b2 cubie.", "habitaciones": "1 dorm."}, "image": "https://static1.sosiva451.com/59665551/688b2174-627d-43d1-84da-50f9a38672c0_u_small.jpg", "title": "2 amb. Av. Juan B. Alberdi 500, lateral, 45m2"}, "https://www.argenprop.com/departamento-en-alquiler-en-congreso-2-ambientes--15648135": {"id": "19064932", "date": "07-05-2024\n", "index": 103, "content": "1\n/12\n1\n$ 280.000\nRivadavia 2396 100\nDepartamento en Alquiler en Congreso, Capital Federal\n42 m\u00b2 cubie.\n1 dorm.\n44 a\u00f1os\n2 Ambientes luminosos, amplio, con lavadero incorporado y balc\u00f3n franc\u00e9s\nAmplio departamento de dos ambientes con balc\u00f3n franc\u00e9s, ba\u00f1o completo, cocina con lavadero, placar en ambos ambientes, todo luz, para ingresar se necesita mes de dep\u00f3sito, mes de alquiler y seguro de cauci\u00f3n https: formulario-express-60-inmobiliaria-486 - kp322023 - kpd050612 - - publicado v\u00eda kiteprop crm inmobiliario.\nContactar", "revised": false, "rejected": false, "data": {"precio": "$ 280.000", "direccion": "Rivadavia 2396 100", "metros": "42 m\u00b2 cubie.", "habitaciones": "1 dorm."}, "image": "https://static1.sosiva451.com/53184651/0dba1008-ecf5-428f-aafa-876b2ebb53db_u_small.jpg", "title": "2 Ambientes luminosos, amplio, con lavadero incorporado y balc\u00f3n franc\u00e9s"}}