{"https://www.zonaprop.com.ar/propiedades/clasificado/alclapin-alquiler-venta-3-amb-balvanera-bajas-expensas-53595063.html": {"id": "53595063", "date": "07-05-2024\n", "index": 7, "content": "USD 400\n$ 27.000 Expensas\nBoulogne Sur Mer 700\nBalvanera, Capital Federal\n68 m\u00b2 tot.\n3 amb.\n2 dorm.\n1 ba\u00f1o\nSe entrega en octubreimperdible alquiler 3 ambientes muy luminoso con doble balc\u00f3n! Ba\u00f1o recicladoSemi amobladoLavadero y cocina independiente con ventilaci\u00f3n natural. Cercano a todos los medios de transporte, colectivos y subtes (linea H y B) A 1 cuadra de Av. Pueyrredon, 2 cuadras de Av. Cordoba y 2 de Av. CorrientesAceptamos Garant\u00eda Respaldar, consultanos para gestionar la garant\u00eda en 2hs y sin costohttps: //respaldar. com. ar/formulario-express-355-inmobiliaria-909\nDestacado\nPublicado hoy\nContactar", "revised": false, "rejected": false, "data": {"precio": "USD 400", "expensas": "$ 27.000 Expensas", "direccion": "Boulogne Sur Mer 700", "metros": "68 m\u00b2 tot.", "habitaciones": "3 amb.", "hace": "Contactar"}, "image": "https://imgar.zonapropcdn.com/avisos/1/00/53/59/50/63/360x266/1909856332.jpg?isFirstImage=true", "title": "Departamento \u00b7 68m\u00b2 \u00b7 3 Ambientes \u00b7 Alquiler - Venta - 3 Amb - Balvanera - Bajas Expensas - Luminoso - Subte Linea H y B"}, "https://www.zonaprop.com.ar/propiedades/clasificado/alclapin-departamento-en-alquiler-con-gran-balcon-terraza-53598877.html": {"id": "53598877", "date": "07-05-2024\n", "index": 22, "content": "19\nUSD 450\n$ 31.000 Expensas\nPasco 100\nBalvanera, Capital Federal\n73 m\u00b2 tot.\n3 amb.\n2 dorm.\n1 ba\u00f1o\nImpecable e impactante 3 ambientes con balcon terraza al frente con vista a la plazael departamento se alquila semi amoblado (heladera, lavarropas, mesa con silla en la cocina, un televisor y aires acondicionado), recien pintado en optimas condicionesContrato por 2 a\u00f1os. Requisitos: Garantia de Capital o FinaerIngresos demostrables. \u201cPara los casos de alquiler de vivienda, el monto m\u00e1ximo de comisi\u00f3n que se le puede requerir a los propietarios ser\u00e1 el equivalente al cuatro con quince cent\u00e9simos por ciento (4, 15%) del valor total del respectivo contrato. Se encuentra prohibido cobrar a los inquilinos que sean personas f\u00edsicas comisiones inmobiliarias y gastos de gestor\u00eda de informes\u201d. Maria Varela, Matricula 4443\nPublicado hoy\nContactar", "revised": false, "rejected": false, "data": {"precio": "USD 450", "expensas": "$ 31.000 Expensas", "direccion": "Pasco 100", "metros": "73 m\u00b2 tot.", "habitaciones": "3 amb.", "hace": "Contactar"}, "image": "https://imgar.zonapropcdn.com/avisos/1/00/53/59/88/77/360x266/1909935281.jpg?isFirstImage=true", "title": "Departamento \u00b7 47m\u00b2 \u00b7 3 Ambientes \u00b7 Departamento en Alquiler con Gran Balcon Terraza"}, "https://www.zonaprop.com.ar/propiedades/clasificado/alclapin-departamento-3-ambientes-barrio-norte-capital-53595625.html": {"id": "53595625", "date": "07-05-2024\n", "index": 24, "content": "USD 1.400\nAyacucho 2100\nBarrio Norte, Capital Federal\n120 m\u00b2 tot.\n3 amb.\n2 dorm.\n1 ba\u00f1o\nPisos tarugados - 120mts. Con terraza 8. 66X3. 2 con parrilla - cochera en alquiler A 50mts. $ 90. 000. - - ba\u00f1o Y toil A nuevo- Hall: 2X1 | Living: 4X7 | Cocina: 7X2. 20 | Dormitorio: 5X3. 5 | Dormitorio: 3X3 | Superficie de terrazas: 27. oferta provista por topinmobiliario. com - codigo: fre3669\nPublicado hoy\nContactar", "revised": false, "rejected": true, "data": {"precio": "USD 1.400", "expensas": "", "direccion": "Ayacucho 2100", "metros": "120 m\u00b2 tot.", "habitaciones": "3 amb.", "hace": "Contactar"}, "image": "", "title": ""}, "https://www.zonaprop.com.ar/propiedades/clasificado/alclapin-palermo-arenales-y-araoz-alquiler-3-ambientes-con-53587188.html": {"id": "53587188", "date": "07-05-2024\n", "index": 26, "content": "USD 1.000\n$ 70.000 Expensas\nArenales al 3700\nBarrio Norte, Capital Federal\n93 m\u00b2 tot.\n3 amb.\n2 dorm.\n1 ba\u00f1o\n1 coch.\nPalermo Alquiler de lind\u00edsimo departamento Piso 12 Soleado todo luminoso contrafrente 3 Ambientes mas dependencias y Cochera Fija Cubierta! Excelente Ubicaci\u00f3n, cerca de todo! Arenales al 3700 entre Araoz y Av. Scalabrini Ortiz, a una cuadra de Av Santa Fe, l\u00ednea D de subte, todos los colectivos, zona de restaurants comercios y a la vez zona Residencial. A una Cuadra del Bot\u00e1nico, a 3 de Av Las Heras, y de Plaza Las Heras, a 7 de Av. Libertador. Pisos de parquet en todos los ambientes inclusive en la dependencia. Servicios Individuales: Calefacci\u00f3n por aire central y Agua caliente por Termotanque nuevo 02. 2024 a gas. Edificio con encargado. Tiene dos cuerpos separados (A y B), cada uno con su ascensor y Palier Privado. Es todo luminoso y soleado e todos los ambientes, los \u00fanicos ambientes internos son los 2 ba\u00f1os que tiene. Living Comedor con vista y salida a Balc\u00f3n corrido, soleado y super luminoso, con cortinas y persianas en todas sus ventanas, la principal es el\u00e9ctrica, pisos de parquet y 1 aire acondicionado en el comedor y otro en el living. 1\u00ba Dormitorio con Placard doble y baulera. Aire Acondicionado, persianas y cortinas blancas. 2\u00ba Dormitorio, con un placard para colgar en ambos lados de la cama, mas otro placard doble al frente con Baulera. Aire Acondicionado, persianas y cortinas blancas. Ba\u00f1o completo con lugar para guarda ToallasCocina Completa ventilada, con alacenas y bajo mesadaLavadero con pileta y lugar para lavarropas y tenderDependencias de Servicio con placards y Baulera y ba\u00f1o. Mar\u00eda P\u00eda Carrera Pereyra inmobiliaria matriculas: cucicba N\u00ba 3819 /cmcpsi N\u00ba 6188contacto: Ver datos // Ver datos\nSuper destacado\nPublicado desde ayer\nContactar", "revised": false, "rejected": true, "data": {"precio": "USD 1.000", "expensas": "$ 70.000 Expensas", "direccion": "Arenales al 3700", "metros": "93 m\u00b2 tot.", "habitaciones": "3 amb.", "hace": "Contactar"}, "image": "https://imgar.zonapropcdn.com/avisos/1/00/53/58/71/88/360x266/1909685562.jpg?isFirstImage=true", "title": "Departamento \u00b7 83m\u00b2 \u00b7 3 Ambientes \u00b7 1 Cochera \u00b7 Palermo Arenales y Araoz Alquiler 3 Ambientes con Depenendencias y Cochera Piso 12 Super Soleado!"}, "https://www.zonaprop.com.ar/propiedades/clasificado/alclapin-alquiler-con-muebles-3-amb-con-escritorio-53590000.html": {"id": "53590000", "date": "07-05-2024\n", "index": 27, "content": "USD 700\n$ 100.000 Expensas\nBillinghurst 1941\nBarrio Norte, Capital Federal\n94 m\u00b2 tot.\n3 amb.\n2 dorm.\n2 ba\u00f1os\nAlquiler amoblado: Plazo minimo 6 meses. Departamento de 3 ambientes al frente amoblado. Muy luminoso!! Zona Alto Palermo. A una cuadra de Av. Santa Fe, Av. Coronel Diaz, Parque Las Heras, subte y medios de transporte, comercios, etc. Excelente barrio. Living comedor al frente, con pisos de parquet. 2 dormitorios, uno al frente y el otro hacia el aire y luz. Uno de los dormitorios con placard. Actualmente posee un ambiente tipo escritorio que podria transformarse en 3er dormitorio o dependencia. Cocina y dos ba\u00f1os (uno completo) Muy buen hall de distribuci\u00f3n. 1 ascensor. Muy buen edificio y calidad de construcci\u00f3n. \u00a1Coordinar visita! - \u25a0consultar condiciones. requisito excluyente: - Garantia propietaria en caba o Seguro Finaer o Seguro Garantina. - Se ingresa con 1 mes de adelanto. - 1 mes de dep\u00f3sito. Alquiler U$S700 d\u00f3lares por mes m\u00e1s servicios. Ideal para grupo familiar de 2 o 3 personas m\u00e1ximo.\nDestacado\nPublicado desde ayer\nContactar", "revised": false, "rejected": false, "data": {"precio": "USD 700", "expensas": "$ 100.000 Expensas", "direccion": "Billinghurst 1941", "metros": "94 m\u00b2 tot.", "habitaciones": "3 amb.", "hace": "Contactar"}, "image": "https://imgar.zonapropcdn.com/avisos/1/00/53/59/00/00/360x266/1909747323.jpg?isFirstImage=true", "title": "Departamento de 3 ambientes, Barrio Norte \u00b7 Alquiler con Muebles - 3 Amb con Escritorio - Luminoso. Edificio de Categoria"}, "https://www.zonaprop.com.ar/propiedades/clasificado/alclapin-alquiler-temporario-3-ambientes-barrio-norte-mansilla-53588469.html": {"id": "53588469", "date": "07-05-2024\n", "index": 41, "content": "8\nUSD 600\nDirecci\u00f3n no informada\nBarrio Norte, Capital Federal\n70 m\u00b2 tot.\n3 amb.\n2 dorm.\n1 ba\u00f1o\nExcelente departamento de 3 ambientes con dependencia para 4 personas con seguridad 24hs en excelente estado, completamente amueblado. Se encuentra ubicado en uno de los mejores barrios de la Ciudad de Buenos Aires a metros de varias l\u00edneas de subte, colectivos, etc. Esta muy cerca de Puerto Madero, Obelisco, el planetario, la Rural, El jard\u00edn Bot\u00e1nico, Hip\u00f3dromo de Palermo, Bosques de Palermo, etc. El precio del alquiler por mes es de u$s600\nPublicado desde ayer\nContactar", "revised": false, "rejected": false, "data": {"precio": "USD 600", "expensas": "", "direccion": "Direcci\u00f3n no informada", "metros": "70 m\u00b2 tot.", "habitaciones": "3 amb.", "hace": "Contactar"}, "image": "https://imgar.zonapropcdn.com/avisos/1/00/53/58/84/69/360x266/1909713550.jpg?isFirstImage=true", "title": "Departamento de 3 ambientes, Barrio Norte \u00b7 Alquiler Temporario 3 Ambientes Barrio Norte Mansilla 2700"}, "https://www.zonaprop.com.ar/propiedades/clasificado/alclapin-departamento-en-alquiler-de-3-ambientes-en-villa-53589594.html": {"id": "53589594", "date": "07-05-2024\n", "index": 45, "content": "USD 500\n$ 90.000 Expensas\nav scalabrini ortiz 520\nVilla Crespo, Capital Federal\n60 m\u00b2 tot.\n3 amb.\n2 dorm.\n1 ba\u00f1o\nUbicado en Scalabrini Ortiz 520, en el \u00faltimo piso, este departamento te ofrece privacidad y tranquilidad, adem\u00e1s de una vista hacia la avenida desde su amplio balc\u00f3n corrido. Totalmente amoblado y equipado con buen gusto, este hogar cuenta con todo lo necesario para que te sientas c\u00f3modo desde el primer d\u00eda. Luminoso living, dos habitaciones confortables y tranquilas, cocina y ba\u00f1o completos. Excelente ubicaci\u00f3n, a pocos pasos de las principales avenidas, transporte p\u00fablico, tiendas, restaurantes y todo lo que necesitas para una vida c\u00f3moda y din\u00e1mica en la ciudad. Condiciones de alquiler: Contrato a un a\u00f1o con actualizaciones trimestrales. Se requieren ingresos comprobables que tripliquen el monto del alquiler. Garant\u00eda propietaria o seguro de cauci\u00f3n. \u00a1Cont\u00e1ctanos hoy mismo para programar una visita!\nPublicado hoy\nContactar", "revised": false, "rejected": false, "data": {"precio": "USD 500", "expensas": "$ 90.000 Expensas", "direccion": "av scalabrini ortiz 520", "metros": "60 m\u00b2 tot.", "habitaciones": "3 amb.", "hace": "Contactar"}, "image": "https://imgar.zonapropcdn.com/avisos/1/00/53/58/95/94/360x266/1909741269.jpg?isFirstImage=true", "title": "Departamento de 3 ambientes, Villa Crespo \u00b7 Departamento en Alquiler de 3 Ambientes en Villa Crespo"}, "https://www.zonaprop.com.ar/propiedades/clasificado/alclapin-departamento-en-alquiler-en-barrio-norte-capital-53580085.html": {"id": "53580085", "date": "07-05-2024\n", "index": 56, "content": "USD 1.000\nAv. Santa Fe 1900\nBarrio Norte, Capital Federal\n100 m\u00b2 tot.\n3 amb.\n2 dorm.\n1 ba\u00f1o\n1 coch.\nExcelente departamento alquiler tradicional - barrio norte caba. Departamento 3 ambientes con dependencia, 2 ba\u00f1os, 2 habitaciones, amplio living comedor. La unidad tiene la cochera incluida. Apto profesional. Mes deposito + mes adelanto y garant\u00eda propietaria. La publicaci\u00f3n de este inmueble es a t\u00edtulo informativo, la venta de la propiedad est\u00e1 supeditada a que el propietario cumplimente el tr\u00e1mite ante la afip para la obtenci\u00f3n del N\u00famero de coti correspondiente. Asimismo en cumplimiento con la Ley 10. 973 de la Prov. Bs. As. , Ley 22. 802 de Lealtad Comercial, Ley 24. 240 de Defensa al Consumidor, las normas del C\u00f3digo Civil y Comercial de la Naci\u00f3n y Constitucionales, los agentes y/o vendedores no ejercen el corretaje inmobiliario. Todas las operaciones inmobiliarias son concluidas por los martilleros y corredores colegiados, cuyos datos se exhiben debajo del nombre de la inmobiliaria. Martillera responsable: Paula Lorena Mendez cmcpsi 6263. Todas las operaciones son a cargo del Martillero y Corredor responsable: Paula Mendez cmcpsi 6263 cucicba 7579. Toda la informaci\u00f3n y medidas provistas son aproximadas y deber\u00e1n ratificarse con la documentaci\u00f3n pertinente y no compromete contractualmente a nuestra empresa. Los gastos expresados (expensas, abl) se refieren a la \u00faltima informaci\u00f3n recabada y deber\u00e1n confirmarse. Fotograf\u00edas no vinculantes ni contractuales. . Todas las operaciones son a cargo del Martillero y Corredor responsable: Paula Mendez cmcpsi 6263 cucicba 7579. Toda la informaci\u00f3n y medidas provistas son aproximadas y deber\u00e1n ratificarse con la documentaci\u00f3n pertinente y no compromete contractualmente a nuestra empresa. Los gastos expresados (expensas, abl) se refieren a la \u00faltima informaci\u00f3n recabada y deber\u00e1n confirmarse. Fotograf\u00edas no vinculantes ni contractuales.\nPublicado hace 3 d\u00edas\nContactar", "revised": false, "rejected": true, "data": {"precio": "USD 1.000", "expensas": "", "direccion": "Av. Santa Fe 1900", "metros": "100 m\u00b2 tot.", "habitaciones": "3 amb.", "hace": "Contactar"}, "image": "https://imgar.zonapropcdn.com/avisos/1/00/53/58/00/85/360x266/1909527757.jpg?isFirstImage=true", "title": "Departamento \u00b7 100m\u00b2 \u00b7 3 Ambientes \u00b7 1 Cochera \u00b7 Departamento en Alquiler en Barrio Norte, Capital Federal, Buenos Aires"}, "https://www.zonaprop.com.ar/propiedades/clasificado/alclappa-alquiler-depto-3-ambientes-piso-12-con-vista-en-av-53579554.html": {"id": "53579554", "date": "07-05-2024\n", "index": 59, "content": "USD 550\nCastelli 376\nOnce, Capital Federal\n63 m\u00b2 tot.\n3 amb.\n2 dorm.\n1 ba\u00f1o\nEste luminoso departamento de 3 ambientes, situado en el vibrante barrio de Balvanera, brinda una impresionante panor\u00e1mica de la ciudad desde su ubicaci\u00f3n en el piso 12. Con una atm\u00f3sfera animada y din\u00e1mica, se encuentra rodeado de diversos centros comerciales de moda. Su proximidad al emblem\u00e1tico Obelisco asegura un acceso f\u00e1cil a los principales destinos tur\u00edsticos de Buenos Aires.\nPublicado hace 3 d\u00edas\nContactar", "revised": false, "rejected": false, "data": {"precio": "USD 550", "expensas": "", "direccion": "Castelli 376", "metros": "63 m\u00b2 tot.", "habitaciones": "3 amb.", "hace": "Contactar"}, "image": "https://imgar.zonapropcdn.com/avisos/1/00/53/57/95/54/360x266/1909520780.jpg?isFirstImage=true", "title": "Departamento de 3 ambientes, Once \u00b7 Alquiler Depto 3 Ambientes Piso 12 con Vista en Av Corrientes y Av Pueyrredon"}, "https://www.zonaprop.com.ar/propiedades/clasificado/alclapin-alquiler-duplex-3-ambientes-90-m-sup2--microcentro-53565857.html": {"id": "53565857", "date": "07-05-2024\n", "index": 86, "content": "USD 600\n$ 170.085 Expensas\nFlorida 600\nSan Nicol\u00e1s, Capital Federal\n90 m\u00b2 tot.\n3 amb.\n2 dorm.\n1 ba\u00f1o\nCorredor Responsable: Claudio Rudecindo cmcpsi 6807 / Cristian Arnal Ponti cpi 3570- Contacto: Lucas Fulla - mls id # Ver datos-17. alquiler - duplex 3 ambientes 90m\u00b2 - microcentro. apto profesional. balc\u00f3n terraza descubierto + balc\u00f3n terraza cubierto. ambientes luminosos por tratarse de unidad en el ultimo piso. Buenas vistas panor\u00e1micas de la ciudad. La unidad se encuentra equipada con 2 aires acondicionados. Los dormitorios tienen piso flotante Y mucho espacio de guardado. La unidad cuenta con caja fuerte con combinaci\u00f3n. Comunicate para que combinemos una visita. Requisitos: mes de adelanto. mes de dep\u00f3sito. garant\u00eda por seguro de cauci\u00f3n. honorarios del 5% + iva sobre el total del contrato. Si te falta hasta un 30% del valor de esta propiedad, te ofrecemos solicitar un pr\u00e9stamo a trav\u00e9s de Lendar, servicio exclusivo para clientes re/max. Ingresa a. ar/ y realiza una simulaci\u00f3n de pr\u00e9stamo. Aprobaciones crediticias en solo 7 d\u00edas. *los corredores p\u00fablicos intermedian Y concluyen todas las operaciones. *los agentes operan bajo el control Y supervisi\u00f3n de los corredores. *las oficinas son de propiedad Y gesti\u00f3n independiente. El equipo Remax a cargo de los profesionales matriculados Cristi\u00e1n Arnal Ponti C. P. I. 3570 / Claudio Rudecindo csi 6807 ofrece esta propiedad. Remax Argentina S. R. L. No ejerce el corretaje inmobiliario. El presente sitio web es una plataforma en donde cada oficina inmobiliaria independiente que contrata los servicios re/max puede publicar las propiedades a su cargo. Cada oficina es de propiedad y gesti\u00f3n independiente, por lo que Remax Argentina S. R. L no interviene en los datos de la publicaci\u00f3n, en la operaci\u00f3n inmobiliaria, ni en la confecci\u00f3n y/o firma del boleto de compraventa y/o escritura y/o contrato de alquiler. En cumplimiento de las leyes vigentes que regulan el corretaje inmobiliario, Ley Nacional 25. 028, Ley 22. 802 de Lealtad Comercial, Ley 24. 240 de Defensa al Consumidor, las normas del C\u00f3digo Civil y Comercial de la Naci\u00f3n y Constitucionales, los agentes/gestores no ejercen el corretaje inmobiliario. Todas las operaciones inmobiliarias son objeto de intermediaci\u00f3n y conclusi\u00f3n por parte del corredor p\u00fablico inmobiliario colegiado a cargo de la publicaci\u00f3n, cuyos datos se exhiben en la presente. La presente publicaci\u00f3n describe las caracter\u00edsticas esenciales del inmueble, debi\u00e9ndose consultar al corredor p\u00fablico inmobiliario responsable de la operaci\u00f3n por la eventual actualizaci\u00f3n de las medidas, descripciones arquitect\u00f3nicas y funcionales, valores de expensas, servicios, impuestos, precios y dem\u00e1s informaci\u00f3n, cuyos valores son aproximados. Para los casos de alquiler de vivienda, el monto m\u00e1ximo de comisi\u00f3n que se le puede requerir a los propietarios ser\u00e1 el equivalente al cuatro con quince cent\u00e9simos por ciento (4, 15%) del valor total del respectivo contrato. Se encuentra prohibido cobrar a los inquilinos que sean personas f\u00edsicas comisiones inmobiliarias y gastos de gestor\u00eda de informes. El inmueble no es accesible para personas con discapacidades f\u00edsicas.\nPublicado hace 5 d\u00edas\nContactar", "revised": false, "rejected": false, "data": {"precio": "USD 600", "expensas": "$ 170.085 Expensas", "direccion": "Florida 600", "metros": "90 m\u00b2 tot.", "habitaciones": "3 amb.", "hace": "Contactar"}, "image": "https://imgar.zonapropcdn.com/avisos/1/00/53/56/58/57/360x266/1909209151.jpg?isFirstImage=true", "title": "Departamento \u00b7 70m\u00b2 \u00b7 3 Ambientes \u00b7 Alquiler - Duplex 3 Ambientes 90 m\u00b2 - Microcentro"}, "https://www.zonaprop.com.ar/propiedades/clasificado/alclapin-departamento-3-ambientes-en-alquielr-palermo-buenos-53520270.html": {"id": "53520270", "date": "07-05-2024\n", "index": 127, "content": "USD 1.350\nDepartamento 3 Ambientes EN Alquielr Palermo Buenos Aires\nBarrio Norte, Capital Federal\n90 m\u00b2 tot.\n3 amb.\n2 dorm.\n2 ba\u00f1os\nDepartamento en alquiler temporal Juan Mar\u00eda Guti\u00e9rrez y Ag\u00fcero - Barrio NorteSup. Construida: 70m\u00b2 aprox. Dos dormitoriosCocina comedorEstar comedorDos ba\u00f1os completosBalc\u00f3nAire acondicionado en todos los ambientes. Totalmente amobladoDoble accesoEstadia m\u00ednima: 3 meses. Disponible 24 de abril(At)\nPublicado hace 8 d\u00edas\nContactar", "revised": false, "rejected": true, "data": {"precio": "USD 1.350", "expensas": "", "direccion": "Departamento 3 Ambientes EN Alquielr Palermo Buenos Aires", "metros": "90 m\u00b2 tot.", "habitaciones": "3 amb.", "hace": "Contactar"}, "image": "https://imgar.zonapropcdn.com/avisos/1/00/53/52/02/70/360x266/1908772386.jpg?isFirstImage=true", "title": "Departamento \u00b7 90m\u00b2 \u00b7 3 Ambientes \u00b7 Departamento 3 Ambientes en Alquielr Palermo Buenos Aires"}, "https://www.zonaprop.com.ar/propiedades/clasificado/alclapin-departamento-3-ambientes.-corrientes-avda.-al-4800-53546211.html": {"id": "53546211", "date": "07-05-2024\n", "index": 131, "content": "USD 600\nCORRIENTES, AVDA. 4800. Entre Lavalleja y Teniente general eustoquio fri\nVilla Crespo, Capital Federal\n72 m\u00b2 tot.\n3 amb.\n2 dorm.\nAlquiler Temporario: Departamento de 3 ambientes en Av. Corrientes 4894, Villa Crespo. Bienvenido a tu hogar temporal en el coraz\u00f3n de Villa Crespo. Este encantador departamento, ubicado en Av. Corrientes 4894, Ofrece una experiencia \u00fanica de alquiler temporario. Con una superficie de 72 metros cuadrados y balc\u00f3n, Esta propiedad es la elecci\u00f3n perfecta para aquellos que buscan comodidad durante su estancia en Buenos Aires. No se aceptan mascotas. no apto fumador ni sustancias recreativas (detector de mon\u00f3xido de carbono) con gas Y electricidad. el valor del alquiler incluye: 1. Wifi Y cable telecentro. 2. A. B. L. 3. Aysa. 4. Un dia por semana, A convenir dia Y horario, limpieza general. No incluye: lavado de ropa, cama, toalla, toallones, utensillos de cocina. xintel(mnr-mnr-383)\nPublicado hace 8 d\u00edas\nContactar", "revised": false, "rejected": false, "data": {"precio": "USD 600", "expensas": "", "direccion": "CORRIENTES, AVDA. 4800. Entre Lavalleja y Teniente general eustoquio fri", "metros": "72 m\u00b2 tot.", "habitaciones": "3 amb.", "hace": "Contactar"}, "image": "https://imgar.zonapropcdn.com/avisos/1/00/53/54/62/11/360x266/1908772685.jpg?isFirstImage=true", "title": "MNR-MNR-383_2 \u00b7 Departamento 3 Ambientes. | Corrientes, Avda. Al 4800"}, "https://www.zonaprop.com.ar/propiedades/clasificado/alclapin-departamento-almagro-53574909.html": {"id": "53574909", "date": "08-05-2024\n", "index": 8, "content": "USD 600\n$ 42.000 Expensas\nPeron al 3800\nAlmagro, Capital Federal\n118 m\u00b2 tot.\n4 amb.\n3 dorm.\n1 ba\u00f1o\nEste encantador departamento semi piso, ubicado en el coraz\u00f3n de Almagro, ofrece una amplia gama de posibilidades tanto para vivienda como para oficina. Con una superficie total de 118m\u00b2, este espacio presenta una distribuci\u00f3n inteligente que se adapta perfectamente a diversas necesidades. Al ingresar al departamento, te recibir\u00e1 un gran hall de entrada que te brinda una sensaci\u00f3n de amplitud y bienvenida. Los techos altos y los pisos de pinotea a\u00f1aden un toque de encanto y calidez a todo el ambiente. El living es generoso en tama\u00f1o, ofreciendo un espacio vers\u00e1til para reuniones o actividades cotidianas. La propiedad cuenta con tres dormitorios de generosas dimensiones, uno de los cuales tiene acceso directo a un balc\u00f3n con vista al frente, perfecto para disfrutar de momentos de tranquilidad al aire libre. Adem\u00e1s, un ba\u00f1o completo garantiza comodidad y funcionalidad para los residentes o usuarios del espacio. La cocina, separada del \u00e1rea de estar, est\u00e1 equipada con todo lo necesario para preparar deliciosas comidas, y cuenta con un lavadero que anteriormente funcionaba como un toilette, ofreciendo practicidad adicional. Con expensas bajas de $42. 000, este departamento proporciona una excelente relaci\u00f3n calidad-precio. El sistema de agua caliente es individual, y una estufa en el living garantiza confort durante los meses m\u00e1s frescos del a\u00f1o. Su ubicaci\u00f3n estrat\u00e9gica brinda f\u00e1cil acceso a una amplia variedad de servicios y transporte p\u00fablico. Con numerosas l\u00edneas de colectivo y la estaci\u00f3n de subte Medrano (L\u00ednea B) a pocos minutos de distancia, la conectividad es inmejorable. Adem\u00e1s, su aptitud profesional lo convierte en una opci\u00f3n ideal para consultorios m\u00e9dicos, despachos de profesionales u oficinas. Los aumentos de alquiler est\u00e1n sujetos a coordinaci\u00f3n entre las partes, lo que brinda flexibilidad y seguridad para ambas partes. \u00a1No dudes en contactarme para m\u00e1s informaci\u00f3n sobre los requisitos de alquiler y para programar una visita a esta incre\u00edble propiedad en Almagro! medidas: Hall de ingreso: 1. 65 x 4. 58Living: 6. 34 x 3. 48Hall de distribuci\u00f3n: 5. 73 x 1. 01Dormitorio 1: 3. 79 x 3. 97Dormitorio 2: 2. 93 x 3. 94Dormitorio 3: 3. 88 x 2. 96Cocina: 2. 35 x 2. 45Lavadero: 0. 87 x 1. 46. por favor leer bien antes de consultarrequisitos alquiler vivienda: -1 mes de deposito-1 mes de adelanto-Seguro de cauci\u00f3n-Demostraci\u00f3n de ingresos-Ajustes a coordinar entre las partes. -Duraci\u00f3n del contrato 12 meses. -Valor locaci\u00f3n vivienda usd 600 -Expensas 42. 000. Requisitos alquiler Comercial: -2 meses de deposito-1 mes de adelanto-seguro de cauci\u00f3n-Demostraci\u00f3n de ingresos-Duraci\u00f3n del contrato a coordinar entre partes-Ajustes a coordinar entre las partes. - Valor locaci\u00f3n comercial usd 750. Ley 5859-art. 5Se encuentra prohibido cobrar comisiones inmobiliarias y gastos de gestor\u00eda de informes a los inquilinos que sean personas f\u00edsicas. Para los casos de alquiler de vivienda, el m\u00e1ximo de comisi\u00f3n que se le puede requerir a los propietarios ser\u00e1 el equivalente al cuatro con quince cent\u00e9simos por ciento (4, 15%) del valor total del respectivo contrato. ym Real Estate cucicba 7636 - cmcpsi 7075Todas las operaciones son a cargo del Martillero y Corredor responsable. Toda la informaci\u00f3n y medidas provistas son aproximadas y deber\u00e1n ratificarse con la documentaci\u00f3n pertinente y no compromete contractualmente a nuestra empresa. Los gastos expresados (expensas, abl) se refieren a la \u00faltima informaci\u00f3n recabada y deber\u00e1n confirmarse. Fotograf\u00edas no vinculantes ni contractuales. seguinos en las redesinstagram: @ym. real. estatefacebook: ym Real Estate\nDestacado\nPublicado hoy\nContactar", "revised": false, "rejected": false, "data": {"precio": "USD 600", "expensas": "$ 42.000 Expensas", "direccion": "Peron al 3800", "metros": "118 m\u00b2 tot.", "habitaciones": "4 amb.", "hace": "Contactar"}, "image": "https://imgar.zonapropcdn.com/avisos/1/00/53/57/49/09/360x266/1909410453.jpg?isFirstImage=true", "title": "Departamento \u00b7 118m\u00b2 \u00b7 4 Ambientes \u00b7 Departamento - Almagro"}, "https://www.zonaprop.com.ar/propiedades/clasificado/alclapin-barrio-norte-av-pueyrredon-y-juncal-53598678.html": {"id": "53598678", "date": "08-05-2024\n", "index": 9, "content": "USD 1.500\n$ 200.000 Expensas\nDirecci\u00f3n no informada\nBarrio Norte, Capital Federal\n160 m\u00b2 tot.\n4 amb.\n3 dorm.\n1 ba\u00f1o\nBarrio Norte. Piso de categor\u00eda se\u00f1orial, amoblado. Balc\u00f3n, 3 dormitorios, ba\u00f1o y toilette de recepcion. Nuevo, con lavadero y patio. Con cochera fija a media cuadra\nDestacado\nPublicado hoy\nContactar", "revised": false, "rejected": false, "data": {"precio": "USD 1.500", "expensas": "$ 200.000 Expensas", "direccion": "Direcci\u00f3n no informada", "metros": "160 m\u00b2 tot.", "habitaciones": "4 amb.", "hace": "Contactar"}, "image": "https://imgar.zonapropcdn.com/avisos/1/00/53/59/86/78/360x266/1909930809.jpg?isFirstImage=true", "title": "Departamento de 4 ambientes, Barrio Norte \u00b7 Barrio Norte - Av Pueyrredon y Juncal"}, "https://www.zonaprop.com.ar/propiedades/clasificado/alclapin-departamento-en-barrio-norte-piso-con-cochera-53596537.html": {"id": "53596537", "date": "08-05-2024\n", "index": 13, "content": "USD 1.500\n$ 162.455 Expensas\nArenales 3200 - 4 Ambientes CON Cochera - Balc\u00f3n AL Frente\nBarrio Norte, Capital Federal\n138 m\u00b2 tot.\n4 amb.\n3 dorm.\n2 ba\u00f1os\n1 coch.\nDepartamento en alquiler - 4 Ambientes con Cochera - Balcon Aterrazado - Luminoso en Barrio Nortearenales al 3200 entre av. cnel d\u00edaz Y billinghursten la mejor zona de Alto Palermo! ! A metros de la estaci\u00f3n \u00a8Bulnes\u00a8 del subte l\u00ednea D y multiples transportesCerca del Parque Las Heras, cl\u00ednicas, colegios, supermercados y comercios de todos los rubros. Se trata de un excelente piso en Semitorre, 4 ambientes al frente sobre calle Arenales con cochera fija! Impecable estado, conservando detalles de categor\u00eda. Muy luminoso y silencioso. Living comedor de amplias dimensiones con balc\u00f3n aterrazado, vista parcial al shopping! caracter\u00edsticas depto: -Superficie Cub. 125 / Total: 138 m2-Palier privado-Luminoso-Cocina completa con comedor diario-3 dormitorios (uno en suite con jacuzzi y vestidor) y una habitacion de servicio/dependencia-Entrada principal y de servicio; doble circulaci\u00f3n. -Dos ba\u00f1os completos -Toilette de recepci\u00f3n. -Lavadero Independiente-Termotanque agua caliente-Calefacci\u00f3n individual-Aires acondicionados-Expensas: $170. 000 (febrero 2024) edificio: -Antig\u00fcedad: 25 a\u00f1os-Pisos: 11-Unidades por piso 1-2 ascensores (uno al palier privado) -Portero visor-Guarda bicicletas-Cochera fija y bauleracondiciones alquiler: -valor: 1500 usd valor fijo mensual (sin indexar) -no incluye los gastos ( Expensas, abl, luz, gas, cable, internet a cargo del locatario) -garant\u00eda propietaria en caba O seguro de cauci\u00f3n (s\u00f3lo garantiaya) -ingresos demostrables-mes de deposito Y mes por adelantado para ingresar-contrato de 2 a\u00f1os vivienda permanente-mascotas A conversar -Se deja constancia que las medidas, superficies, m2 y proporciones consignadas son aproximados, al igual que las medidas parciales y/o de los ambientes esta sujeto a verificaci\u00f3n y/o ajuste. El valor indicado de expensas esta sujeto a variaci\u00f3n. El precio del inmueble puede ser modificado sin previo aviso. Fotos de car\u00e1cter no contractual. ezequiel wierzba martillero publico, C. U. C. I. C. B. A 6383. eduardo percy fernandez davila coquinche C. M. Z. C 578. -click aparts Cont\u00e1ctenos: Oficina: +Ver datosCelular: +Ver datos 5 Ver datosE-mail: Ver datos: Facebook: /click. apartsInstagram: /click. aparts\nPublicado hoy\nContactar", "revised": false, "rejected": false, "data": {"precio": "USD 1.500", "expensas": "$ 162.455 Expensas", "direccion": "Arenales 3200 - 4 Ambientes CON Cochera - Balc\u00f3n AL Frente", "metros": "138 m\u00b2 tot.", "habitaciones": "4 amb.", "hace": "Contactar"}, "image": "https://imgar.zonapropcdn.com/avisos/1/00/53/59/65/37/360x266/1909886052.jpg?isFirstImage=true", "title": "Departamento \u00b7 125m\u00b2 \u00b7 4 Ambientes \u00b7 1 Cochera \u00b7 Departamento en Barrio Norte - Piso con Cochera"}, "https://www.zonaprop.com.ar/propiedades/clasificado/alclapin-alquiler-4-ambientes-almagro-totalmente-reciclado-53596876.html": {"id": "53596876", "date": "08-05-2024\n", "index": 24, "content": "USD 650\nPotos\u00ed 4100\nAlmagro, Capital Federal\n83 m\u00b2 tot.\n4 amb.\n3 dorm.\n2 ba\u00f1os\nCorredor Responsable: rmx 1 sas - Lucas Norman cucicba 8008 / cmcpsi 6743- Contacto: Fabian Elias - mls id # Ver datos. Alquiler de 4 ambientes en Almagro totalmente reciclado. El departamento tiene 3 amplias habitaciones y un hall de recepci\u00f3n que puede utilizarse como un ambiente m\u00e1s. Se ubica en frente del hospital Italiano y es un primer piso por escalera. La cocina es super amplia y tiene un gran espacio para ser utilizado como comedor diario. A la vez como up grade la terraza es de uso compartido con otro vecino y tiene una parrilla que se puede utilizar y el espacio es como un sum al aire libre y solarium. Se trata de un departamento muy vers\u00e1til y super adaptable. Se entrega totalmente pintado. Se ofrece contrato por dos a\u00f1os y como requisitos se solicitan un mes de adelanto, un mes de dep\u00f3sito y una garant\u00eda propietaria o seguro de cauci\u00f3n. Esta listo para entrar. Remax Argentina S. R. L. No ejerce el corretaje inmobiliario. El presente sitio web es una plataforma en donde cada oficina inmobiliaria independiente que contrata los servicios re/max puede publicar las propiedades a su cargo. Cada oficina es de propiedad y gesti\u00f3n independiente, por lo que Remax Argentina S. R. L no interviene en los datos de la publicaci\u00f3n, en la operaci\u00f3n inmobiliaria, ni en la confecci\u00f3n y/o firma del boleto de compraventa y/o escritura y/o contrato de alquiler. En cumplimiento de las leyes vigentes que regulan el corretaje inmobiliario, Ley Nacional 25. 028, Ley 22. 802 de Lealtad Comercial, Ley 24. 240 de Defensa al Consumidor, las normas del C\u00f3digo Civil y Comercial de la Naci\u00f3n y Constitucionales, los agentes/gestores no ejercen el corretaje inmobiliario. Todas las operaciones inmobiliarias son objeto de intermediaci\u00f3n y conclusi\u00f3n por parte del corredor p\u00fablico inmobiliario colegiado a cargo de la publicaci\u00f3n, cuyos datos se exhiben en la presente. La presente publicaci\u00f3n describe las caracter\u00edsticas esenciales del inmueble, debi\u00e9ndose consultar al corredor p\u00fablico inmobiliario responsable de la operaci\u00f3n por la eventual actualizaci\u00f3n de las medidas, descripciones arquitect\u00f3nicas y funcionales, valores de expensas, servicios, impuestos, precios y dem\u00e1s informaci\u00f3n, cuyos valores son aproximados. Para los casos de alquiler de vivienda, el monto m\u00e1ximo de comisi\u00f3n que se le puede requerir a los propietarios ser\u00e1 el equivalente al cuatro con quince cent\u00e9simos por ciento (4, 15%) del valor total del respectivo contrato. Se encuentra prohibido cobrar a los inquilinos que sean personas f\u00edsicas comisiones inmobiliarias y gastos de gestor\u00eda de informes. El inmueble no es accesible para personas con discapacidades f\u00edsicas.\nPublicado hoy\nContactar", "revised": false, "rejected": false, "data": {"precio": "USD 650", "expensas": "", "direccion": "Potos\u00ed 4100", "metros": "83 m\u00b2 tot.", "habitaciones": "4 amb.", "hace": "Contactar"}, "image": "https://imgar.zonapropcdn.com/avisos/1/00/53/59/68/76/360x266/1909893555.jpg?isFirstImage=true", "title": "Departamento \u00b7 83m\u00b2 \u00b7 4 Ambientes \u00b7 Alquiler 4 Ambientes Almagro Totalmente Reciclado"}, "https://www.zonaprop.com.ar/propiedades/clasificado/alclapin-alquiler-4-ambientes-3-dorm.-cochera-palermo-53588390.html": {"id": "53588390", "date": "08-05-2024\n", "index": 42, "content": "14\nUSD 1.250\n$ 300.000 Expensas\nJuan Maria Gutierrez al 3900\nBarrio Norte, Capital Federal\n115 m\u00b2 tot.\n4 amb.\n3 dorm.\n3 ba\u00f1os\n1 coch.\nB\"H alquiler - 4 ambientes - 3 dormitorios - dependencia -luminoso - cochera - palermo datos de relevancia: gran oportunidad unica en zona de alta gama opcion de alquiler con Y sin mueblesla unidad posee cochera propialos gastos Y servicios son aparteactualmente la dependencia se saco para ampliar la cocina pero rapidamente Y sin problema puede volver A efectuarse unidad: ( Plano general de la unidad) living comedor - 3 dormitorios(1 Suite) - cocina - 2 ba\u00f1os - balc\u00f3n-toilette-lavadero. metros: (Metraje Aproximado) 115 m2 Totales110 m2 Cubiertosdistribuci\u00f3n: amplio living comedor super espacioso Y luminoso, amplio balc\u00f3n semi aterrazado, cocina super completa c/ bajo y sobre mesada. , comedor diario, dormitorio principal en suite + vestidor, 2do dormitorio c/ placard piso-techo, 3er dormitorio c/ placard piso-techo, 2 Ba\u00f1os completo, Toilette, Gran Lavadero independiente, ba\u00f1o de serviciodetalles: muy luminoso, todos los ambientes son de excelente dimensiones. Excelente distribuciones, piso de madera, Balc\u00f3n conectado al living comedor con excelente iluminaci\u00f3n, Aires acondicionados en gran mayor\u00eda de ambientes, Calefacci\u00f3n, Placards, Agua caliente, Agua corriente, Ascensor, Gas naturalzona: palermo, Ubicado en uno de los barrios m\u00e1s elegantes y exclusivos de la Ciudad de Buenos Aires. Medio transportes: Colectivos: 10, 12, 15, 29, 36, 37, 39, 41, 57, 59, 60, 64, 67, 68, 93, 95, 108, 110, 111, 118, 128, 141, 152, 160, 188, 194Consulta por esta propiedad ahora. WhatsApp: Ver datosOficina: Ver datosvende y compra con lexinton, inmobiliaria lider en realizar compra / venta simultanea. Tasaciones profesionales. Las medidas, superficies y valores de esta ficha son aproximadas y a t\u00edtulo informativo \u00fanicamente. Martillera y Corredor Responsable: nora levi cmcpsi 6006 y cucicba 5059Todas las propiedades que figuran en el perfil de Lexinton se encuentran a cargo del profesional matriculado que corresponda, la intermediaci\u00f3n y la conclusi\u00f3n de las operaciones ser\u00e1n llevadas exclusivamente por esta persona. Lexinton Propiedades es una marca registrada. Matricula Provincia de Buenos Aires: nora levi cmcpsi 6006Matricula Ciudad de Buenos Aires: cucicba 5059\nPublicado desde ayer\nContactar", "revised": false, "rejected": false, "data": {"precio": "USD 1.250", "expensas": "$ 300.000 Expensas", "direccion": "Juan Maria Gutierrez al 3900", "metros": "115 m\u00b2 tot.", "habitaciones": "4 amb.", "hace": "Contactar"}, "image": "https://imgar.zonapropcdn.com/avisos/1/00/53/58/83/90/360x266/1909711439.jpg?isFirstImage=true", "title": "Departamento \u00b7 110m\u00b2 \u00b7 4 Ambientes \u00b7 1 Cochera \u00b7 Alquiler - 4 Ambientes - 3 Dorm. - Cochera - Palermo Chico"}, "https://www.zonaprop.com.ar/propiedades/clasificado/alclapin-espectacular-4-amb-a-estrenar-con-amenities-en-palermo-53584382.html": {"id": "53584382", "date": "08-05-2024\n", "index": 47, "content": "USD 1.800\n$ 100.000 Expensas\nAcevedo 1089\nVilla Crespo, Capital Federal\n120 m\u00b2 tot.\n4 amb.\n3 dorm.\n2 ba\u00f1os\n1 coch.\nDepartamento de 4 ambientes A estrenar, amenities, con cochera cubierta en un edificio \u00fanico en el coraz\u00f3n de palermo crespo, rodeado de verde para disfrutar Y relajarse ya que cuenta con los mejores servicios. Inmejorable Ubicaci\u00f3n, Av. Cordoba a 100 Mts. , Av. Raul Scalabrini Ortis a 250 Mts. , Av. Juan B. Justo y metro bus a 500 Mts. , Plaza Serrano y Plaza Armenia a 700 Mts. Av. Corrientes a 750 Mts, y Subte Linea \"B\" estaci\u00f3n Malabia a 800 Mts. , pr\u00f3ximo a los mejores centros educativos. Sup. Total: 120 m2110 m2 cubiertos10 m2 balc\u00f3n terrazacaracter\u00edsticas: - 4 ambientes (total 3 dormitorios) - 2 dormitorios- 1 dormitorio en suitre- 1 ba\u00f1o en suite- 1 ba\u00f1o completo- balcon terraza con parrilla- lavadero independiente- cocina el\u00e9ctrica- agua caliente central A gas- pisos electricos en todos los ambientes- luminoso Y silencioso- cochera cubiertaamenities: - piscina- jardin- solarium- sum- parrilla - seguridad 24hs por totemTenemos m\u00e1s propiedades y emprendimientos en capital federal. En cumplimiento de la leyes provinciales vigentes que regulan el corretaje inmobiliario, Ley Nacional 25. 028, Ley 22. 802 de Lealtad Comercial, Ley 24. 240 de Defensa al Consumidor, las normas del C\u00f3digo Civil y Comercial de la Naci\u00f3n y Constitucionales, los agentes/gestores no ejercen el corretaje inmobiliario. Todas las operaciones inmobiliarias son objeto de intermediaci\u00f3n y conclusi\u00f3n por parte de los martilleros y corredores colegiados, cuyos datos se exhiben debajo del nombre de la inmobiliaria. Todas las propiedades que figuran en mi perfil se encuentran a cargo del profesional matriculado de la oficina, la intermediaci\u00f3n y la conclusi\u00f3n de las operaciones ser\u00e1n llevadas exclusivamente por \u00e9l. Martillero: alejandro mart\u00edn stern - Matr\u00edcula 5762 aviso legal: Las descripciones arquitect\u00f3nicas y funcionales, valores de expensas, impuestos y servicios, fotos y medidas de este inmueble son aproximados. Los datos fueron proporcionados por el propietario y pueden no estar actualizados a la hora de la visualizaci\u00f3n de este aviso por lo cual pueden arrojar inexactitudes y discordancias con las que surgen de los las facturas, t\u00edtulos y planos legales del inmueble. El interesado deber\u00e1 realizar las verificaciones respectivas previamente a la realizaci\u00f3n de cualquier operaci\u00f3n, requiriendo por s\u00ed o sus profesionales las copias necesarias de la documentaci\u00f3n que corresponda.\nPublicado desde ayer\nContactar", "revised": false, "rejected": false, "data": {"precio": "USD 1.800", "expensas": "$ 100.000 Expensas", "direccion": "Acevedo 1089", "metros": "120 m\u00b2 tot.", "habitaciones": "4 amb.", "hace": "Contactar"}, "image": "https://imgar.zonapropcdn.com/avisos/1/00/53/58/43/82/360x266/1909626458.jpg?isFirstImage=true", "title": "Departamento \u00b7 110m\u00b2 \u00b7 4 Ambientes \u00b7 1 Cochera \u00b7 Espectacular 4 Amb a Estrenar con Amenities en Palermo Crespo"}, "https://www.zonaprop.com.ar/propiedades/clasificado/alclcain-alquiler-casa-ph-en-parque-centenario-53590150.html": {"id": "53590150", "date": "08-05-2024\n", "index": 58, "content": "USD 1.700\nDirecci\u00f3n no informada\nParque Centenario, Capital Federal\n143 m\u00b2 tot.\n4 amb.\n3 dorm.\n2 ba\u00f1os\nAmplio 4 ambientes reciclado en Parque Centenario en Planta Baja amoblado con hermoso patio al fondo. Living comedor, 3 dormitorios, cocina con comedor de diario y lavadero aparte en otro patio. 2 ba\u00f1os completos, 1 con ba\u00f1era y el otro con ducha. Superficie cubierta total 119m2 y 24m2 de patios. Calefacci\u00f3n por radiadores. Alquiler U$S1700 m\u00e1s gastos. Contrato m\u00ednimo 6 meses.\nPublicado desde ayer\nContactar", "revised": false, "rejected": false, "data": {"precio": "USD 1.700", "expensas": "", "direccion": "Direcci\u00f3n no informada", "metros": "143 m\u00b2 tot.", "habitaciones": "4 amb.", "hace": "Contactar"}, "image": "https://imgar.zonapropcdn.com/avisos/1/00/53/59/01/50/360x266/1909750938.jpg?isFirstImage=true", "title": "Casa de 4 ambientes, Parque Centenario \u00b7 Alquiler Casa/ph en Parque Centenario"}, "https://www.zonaprop.com.ar/propiedades/clasificado/alclcapa-amplio-duplex-con-cochera-patio-y-jardin-53580255.html": {"id": "53580255", "date": "08-05-2024\n", "index": 79, "content": "USD 1.900\nCastro 776\nAlmagro Sur, Almagro\n350 m\u00b2 tot.\n5 amb.\n3 dorm.\n2 ba\u00f1os\n2 coch.\nDue\u00f1o directo alquila amplio d\u00faplex de 5 ambientes distribuido en 3 plantas. La propiedad es super luminosa en una cuadra de casas bajas. Cuenta con cochera con port\u00f3n el\u00e9ctrico para 2 veh\u00edculos, patio, terraza y balc\u00f3n. Habitaci\u00f3n principal con sector vestidor y ba\u00f1o en suite con hidromasaje. Propiedad construida con materiales de alta calidad, posee aire acondicionado en todos los ambientes. Sin expensas. Disponible a partir de junio. Se entrega pintada y en \u00f3ptimas condiciones generales. Contrato a 2 a\u00f1os. Precio de referencia. Moneda de pago y cl\u00e1usulas de ajustes a negociar. Para el ingreso se solicita a los inquilinos: Garant\u00eda propietaria (de caba preferentemente) o seguro de cauci\u00f3n. Acreditaci\u00f3n de ingresos. Mes de dep\u00f3sito.\nPublicado hace 3 d\u00edas\nContactar", "revised": false, "rejected": false, "data": {"precio": "USD 1.900", "expensas": "", "direccion": "Castro 776", "metros": "350 m\u00b2 tot.", "habitaciones": "5 amb.", "hace": "Contactar"}, "image": "https://imgar.zonapropcdn.com/avisos/1/00/53/58/02/55/360x266/1909533733.jpg?isFirstImage=true", "title": "Casa de 5 ambientes, Almagro \u00b7 Amplio Duplex con Cochera, Patio y Jard\u00edn"}, "https://www.zonaprop.com.ar/propiedades/clasificado/alclapin-alquiler-departamento-4-ambientes-con-muebles-cochera-53575379.html": {"id": "53575379", "date": "08-05-2024\n", "index": 101, "content": "28\nUSD 1.400\n$ 136.000 Expensas\nArenales 2295\nBarrio Norte, Capital Federal\n130 m\u00b2 tot.\n4 amb.\n3 dorm.\n2 ba\u00f1os\n1 coch.\nHermoso departamento con muebles. 4 ambientes al frente con balc\u00f3n corrido. Cochera. Excelente estado. Living comedor Amplio. Cocina con Isla. 3 dormitorios con placard. Patio con Ducha. 2 ba\u00f1os. 1 Toilette. Excelente zona pr\u00f3ximo Av. Santa Fe. Numerosas lineas de colectivos. Pr\u00f3ximo subte Linea D Estaci\u00f3n Pueyrredon\nPublicado desde ayer\nContactar", "revised": false, "rejected": false, "data": {"precio": "USD 1.400", "expensas": "$ 136.000 Expensas", "direccion": "Arenales 2295", "metros": "130 m\u00b2 tot.", "habitaciones": "4 amb.", "hace": "Contactar"}, "image": "https://imgar.zonapropcdn.com/avisos/1/00/53/57/53/79/360x266/1909440088.jpg?isFirstImage=true", "title": "Departamento de 4 ambientes, Barrio Norte \u00b7 Alquiler Departamento 4 Ambientes con Muebles, Cochera"}}