{"https://www.zonaprop.com.ar/propiedades/clasificado/alclapin-departamento-villa-crespo-53592720.html": {"id": "53592720", "date": "07-05-2024\n", "index": 1, "content": "16\n$ 600.000\n$ 100.000 Expensas\nEstado De Israel Av. al 4400\nVilla Crespo, Capital Federal\n60 m\u00b2 tot.\n3 amb.\n2 dorm.\n1 ba\u00f1o\n1 coch.\nC\u00f3modo departamento 3 ambientes al frente con balc\u00f3n corrido y cochera fija descubierta nro 8. Consta de living comedor con pisos de parquet y salida a balc\u00f3n, dos dormitorios, ambos con placard, cocina con lavadero independiente, ba\u00f1o completo con ventilaci\u00f3n al exterior, calefacci\u00f3n y agua por caldera individual, 2 aires acondicionados frio. Excelente ubicaci\u00f3n Avda. Estado de Israel 4400, entre Jufre y Lerma, pr\u00f3ximo Avda. C\u00f3rdoba, Avda. \u00c1ngel Gallardo, Avda. Corrientes, subte B estaci\u00f3n \u00c1ngel Gallardo, colectivos, comercios. Pida tasaci\u00f3n: Efectuada por profesionales, que analizan permanentemente el desenvolvimiento del mercado. Conf\u00ede su patrimonio en una empresa s\u00f3lida con respaldo y prestigio. Conf\u00ede en el L\u00edder. Goldstein propiedades. Se deja constancia que los m2 son aproximados, al igual que las medidas parciales y el valor consignado de las expensas mensuales (en caso que corresponda pago de expensas) y las caracter\u00edsticas est\u00e1n sujetos a verificaci\u00f3n y/o ajustes, el precio del inmueble puede ser modificado sin previo aviso. En el caso de tratarse de un inmueble en construcci\u00f3n los detalles de terminaci\u00f3n y la fecha de entrega est\u00e1n sujetos a revisi\u00f3n. Fotos de car\u00e1cter no contractual. Las unidades publicadas est\u00e1n sujetas a disponibilidad. Goldstein Propiedades srl con domicilio en Avda. Corrientes 4666 act\u00faa solamente en car\u00e1cter de comercializadora de los inmuebles ofrecidos. En caso de tratarse de un terreno, la informaci\u00f3n de m2 construibles y plusval\u00eda es orientativa, debiendo ser constatada por el interesado. Inmueble no accesible para personas con discapacidad f\u00edsica ley 5115. Cucicba matr\u00edcula 37. Cmcpsi matr\u00edcula 6003. \u00danicamente en el caso de tratarse de alquiler de vivienda familiar, rige lo indicado en la ley 5859. Venta supeditada al cumplimiento por parte del propietario de los requisitos de la resoluci\u00f3n general N\u00ba 2371 de la afip (pedido de coti).\nSuper destacado\nPublicado hoy\nContactar", "revised": false, "rejected": false, "data": {"precio": "$ 600.000", "expensas": "$ 100.000 Expensas", "direccion": "Estado De Israel Av. al 4400", "metros": "60 m\u00b2 tot.", "habitaciones": "3 amb.", "hace": "Contactar"}, "image": "https://imgar.zonapropcdn.com/avisos/1/00/53/59/27/20/360x266/1909808666.jpg?isFirstImage=true", "title": "Departamento \u00b7 51m\u00b2 \u00b7 3 Ambientes \u00b7 1 Cochera \u00b7 Departamento - Villa Crespo"}, "https://www.zonaprop.com.ar/propiedades/clasificado/alclapin-departamento-3-ambientes-con-dependencias-al-frente-53592717.html": {"id": "53592717", "date": "07-05-2024\n", "index": 2, "content": "16\n$ 600.000\n$ 49.000 Expensas\nSarmiento al 4600\nAlmagro, Capital Federal\n75 m\u00b2 tot.\n3 amb.\n2 dorm.\n1 ba\u00f1o\nSemipiso de 3 ambientes con dependencias al frente, con aire luz y sol. Consta de living comedor, balc\u00f3n corrido, 2 dormitorios con placards, cocina con muebles altos y bajos, lavadero cubierto. Excelente ubicaci\u00f3n Sarmiento 4600 esquina Lambar\u00e9, proximo a Parque Centenario, Avda. Corrientes, comercios, colectivos, subte B estaci\u00f3n Angel Gallardo. pida tasaci\u00f3n: Efectuada por profesionales, que analizan permanentemente el desenvolvimiento del mercado. Conf\u00ede su patrimonio en una empresa s\u00f3lida con respaldo y prestigio. Conf\u00ede en el L\u00edder. Goldstein propiedades. Se deja constancia que los m2 son aproximados, al igual que las medidas parciales y el valor consignado de las expensas mensuales (en caso que corresponda pago de expensas) y las caracter\u00edsticas est\u00e1n sujetos a verificaci\u00f3n y/o ajustes, el precio del inmueble puede ser modificado sin previo aviso. En el caso de tratarse de un inmueble en construcci\u00f3n los detalles de terminaci\u00f3n y la fecha de entrega est\u00e1n sujetos a revisi\u00f3n. Fotos de car\u00e1cter no contractual. Las unidades publicadas est\u00e1n sujetas a disponibilidad. Goldstein Propiedades srl con domicilio en Avda. Corrientes 4666 act\u00faa solamente en car\u00e1cter de comercializadora de los inmuebles ofrecidos. En caso de tratarse de un terreno, la informaci\u00f3n de m2 construibles y plusval\u00eda es orientativa, debiendo ser constatada por el interesado. Inmueble no accesible para personas con discapacidad f\u00edsica ley 5115. Cucicba matr\u00edcula 37. Cmcpsi matr\u00edcula 6003. \u00danicamente en el caso de tratarse de alquiler de vivienda familiar, rige lo indicado en la ley 5859. Venta supeditada al cumplimiento por parte del propietario de los requisitos de la resoluci\u00f3n general N\u00ba 2371 de la afip (pedido de coti).\nSuper destacado\nPublicado hoy\nContactar", "revised": false, "rejected": false, "data": {"precio": "$ 600.000", "expensas": "$ 49.000 Expensas", "direccion": "Sarmiento al 4600", "metros": "75 m\u00b2 tot.", "habitaciones": "3 amb.", "hace": "Contactar"}, "image": "https://imgar.zonapropcdn.com/avisos/1/00/53/59/27/17/360x266/1909808646.jpg?isFirstImage=true", "title": "Departamento \u00b7 65m\u00b2 \u00b7 3 Ambientes \u00b7 Departamento 3 Ambientes con Dependencias Al Frente con Balcon - Almagro"}, "https://www.zonaprop.com.ar/propiedades/clasificado/alclapin-alquiler-3-ambientes-contra-frente-sin-balcon-sin-53597702.html": {"id": "53597702", "date": "07-05-2024\n", "index": 3, "content": "$ 450.000\n$ 51.000 Expensas\nHipolito Yrigoyen 4200\nAlmagro, Capital Federal\n62 m\u00b2 tot.\n3 amb.\n2 dorm.\n1 ba\u00f1o\nMuy Buen departamento en Alquiler de 3 Ambientes al Contra frente Sin Balc\u00f3n- Ubicado a 1 cuadra de Avenida Rivadavi y a dos Cuadras de Avenida La plata. Todos los medios de transportes. Piso de parquet - Puerta Blindada Pent\u00e1gono - Living Comedor con gran ventanal con sus cortinas y Ventilador de techo con Apliques y espejo empotrado en Pared Cocina C\u00f3moda con muebles completos Lavadero Independiente con tender colgante Hall de Distribuci\u00f3n con puertas corredizas 1 Ba\u00f1o Completo 2 Dormitorios con Placares c\u00f3modos con ventanales y cortinados - Todo en buen estado - Agua Caliente por Calef\u00f3n Calefacci\u00f3n Individual. contrato por 2 a\u00f1os valor de Inicio de Alquiler $ Ver datos. - M\u00e1s Expensas comunes, $ Ver datos. - servicios de Luz - Gas y Tel\u00e9fono - Aysa $ 13. 300. - y Barrido Alumbrado y limpieza el 50% del Abl Vigente mensual ( no el Inmobiliario) * Aumento Trimestral del ipc indec - Se pedir\u00e1 por contrato un seguro de incendio Yy Responsabilidad Civil a elecci\u00f3n del Inquilino la empresa aseguradora- requisitos: Comprobantes de Ingresos comprobables prioritario Con recibos de sueldos de 2 a\u00f1os m\u00ednimo de antiguedad comprobable- prioridad** Garant\u00eda Propietaria de Capital Federal caba - Seguro de Garant\u00eda finaer. *no mascotas de ninguna \u00edndole* condiciones: 1 Mes de Alquiler - 1 Mes de dep\u00f3sito en D\u00f3lares Billetes Estadounidensas U$S 500. Las medidas indicadas, son a efecto orientativo, las medidas reales surgen del t\u00edtulo de propiedad El valor de expensas mencionadas, pueden sufrir ajuste o modificaci\u00f3n sin previo aviso, valor vigente ser\u00e1 informado por el titular del inmueble. Monta\u00f1a inmobiliaria sa. Matr\u00edcula cucicba N\u00ba 412 *Ley 5859 - Art. 4: \"Para los casos de alquiler de vivienda, el monto m\u00e1ximo de comisi\u00f3n que se le puede requerir a los propietarios ser\u00e1 el equivalente al cuatro con quince cent\u00e9simos por ciento (4, 15%) del valor total del respectivo contrato. Se encuentra prohibido cobrar a los inquilinos que sean personas f\u00edsicas comisiones inmobiliarias\". - Datos de contacto: Local Barrio Norte - Av Santa Fe 2309 - Ver datos Local Caballito - Av. Rivadavia 4621 - Ver datos Local Boedo - Av. Pav\u00f3n 4024 - Ver datos\nSuper destacado\nPublicado hoy\nContactar", "revised": false, "rejected": false, "data": {"precio": "$ 450.000", "expensas": "$ 51.000 Expensas", "direccion": "Hipolito Yrigoyen 4200", "metros": "62 m\u00b2 tot.", "habitaciones": "3 amb.", "hace": "Contactar"}, "image": "https://imgar.zonapropcdn.com/avisos/1/00/53/59/77/02/360x266/1909911191.jpg?isFirstImage=true", "title": "Departamento \u00b7 62m\u00b2 \u00b7 3 Ambientes \u00b7 Alquiler 3 Ambientes Contra Frente Sin Balc\u00f3n Sin Mascotas"}, "https://www.zonaprop.com.ar/propiedades/clasificado/alclapin-departamento-en-alquiler-53595518.html": {"id": "53595518", "date": "07-05-2024\n", "index": 8, "content": "$ 480.000\n$ 40.000 Expensas\nCastro Barros al 900\nBoedo, Capital Federal\n60 m\u00b2 tot.\n3 amb.\n2 dorm.\n1 ba\u00f1o\nSe trata de un departamento de 3 ambientes al frente con balc\u00f3n. Orientaci\u00f3n Este, muy luminoso, muy buena vista. Amplio living, ba\u00f1o completo, cocina con muebles completos, lavadero incorporado, dormitorios con placard. Muy buen estado. no se aceptan mascotas. ll 111condiciones Y requisitos- 1 mes por adelantado + 1 mes deposito (igual al valor del primer mes) - Garant\u00eda-El monto de las expensas aqu\u00ed especificado, fueron extra\u00eddos de la liquidaci\u00f3n realizada por el administrador del edificio y corresponden al mes de Enero de 2024, por lo tanto y debido a que sufren fluctuaciones mes a mes, Ud deber\u00e1 solicitarnos el monto actualizado previamente a la realizaci\u00f3n de la operaci\u00f3n. -- Honorarios: seg\u00fan ley 5859 \u201cSe encuentra prohibido cobrar comisiones inmobiliarias y gastos de gestor\u00eda de informes a los inquilinos que sean personas f\u00edsicas. Para los casos de alquiler de vivienda, el monto m\u00e1ximo de comisi\u00f3n que se le puede requerir a los propietarios ser\u00e1 el equivalente al cuatro con quince cent\u00e9simos por ciento (4, 15%) del valor total del respectivo contrato\u201d- Contrato por 2 a\u00f1os- Indexaci\u00f3n trimestral seg\u00fan \u00edndice icl\nPublicado hoy\nContactar", "revised": false, "rejected": false, "data": {"precio": "$ 480.000", "expensas": "$ 40.000 Expensas", "direccion": "Castro Barros al 900", "metros": "60 m\u00b2 tot.", "habitaciones": "3 amb.", "hace": "Contactar"}, "image": "https://imgar.zonapropcdn.com/avisos/1/00/53/59/55/18/360x266/1909864569.jpg?isFirstImage=true", "title": "Departamento \u00b7 60m\u00b2 \u00b7 3 Ambientes \u00b7 Departamento en Alquiler"}, "https://www.zonaprop.com.ar/propiedades/clasificado/alclapin-excelente-depto-de-3-ambientes-con-quincho-balcon-53584890.html": {"id": "53584890", "date": "07-05-2024\n", "index": 9, "content": "$ 510.000\n$ 70.000 Expensas\nQuintino bocayuva 1097\nBoedo, Capital Federal\n76 m\u00b2 tot.\n3 amb.\n2 dorm.\n1 ba\u00f1o\nExcelente departamento de 3 amientes. Se ingresa a un living comedor el cual tiene salida a un balcon aterrazado cubierto que sirve como jardin de invierno. Cocina apaisada con muebles completos y salida al lavadero cubierto. 2 dormitorios con placard. Ba\u00f1o completo. Balcon aterrazado descubierto y quincho cubierto con parrilla! Todo luz y ventilacion. Al frente! Buen estado general. Se alquila sin mascotas. Aceptamos seguro de caucion finaer.\nDestacado\nPublicado desde ayer\nContactar", "revised": false, "rejected": false, "data": {"precio": "$ 510.000", "expensas": "$ 70.000 Expensas", "direccion": "Quintino bocayuva 1097", "metros": "76 m\u00b2 tot.", "habitaciones": "3 amb.", "hace": "Contactar"}, "image": "https://imgar.zonapropcdn.com/avisos/1/00/53/58/48/90/360x266/1909639861.jpg?isFirstImage=true", "title": "Departamento de 3 ambientes, Boedo \u00b7 Excelente Depto de 3 Ambientes con Quincho, Balcon Aterrazado y Excelente Luz!"}, "https://www.zonaprop.com.ar/propiedades/clasificado/alclphin-ph-en-almagro-lavalle-al-3600-53587802.html": {"id": "53587802", "date": "07-05-2024\n", "index": 15, "content": "$ 460.000\n$ 33.600 Expensas\nLavalle al 3600\nAlmagro, Capital Federal\n70 m\u00b2 tot.\n3 amb.\n2 dorm.\n1 ba\u00f1o\nPrecioso ph de 3 ambientes ubicado en el coraz\u00f3n de Almagro. Impecable estado, reciclado totalmente, conservando los materiales nobles de la \u00e9poca. Ca\u00f1erias y cableado restaurado. 1er piso por escalera con entrada com\u00fan por un portal magn\u00edfico de madera con hierro forjado con detalles en bronce, palier espectacular con escalinatas de m\u00e1rmol de carrara y techos altos. Super luminoso: patio con cerramiento vidriado al cielo abierto. Carpinter\u00eda de aberturas y pisos originales restaurados. Techos doble altura sin entrepiso. Se ingresa por el patio con cerramiento vidriado y vitreaux en los laterales, con posibilidad de abrir para que ingrese m\u00e1s luz y sol directo, hoy living-comedor con aire acondicionado fr\u00edo calor y lavadero con puerta plegable. A la derecha se encuentra la cocina, con mesada de aluminio y bacha de lavar, mesa corrediza de madera maciza, muebles de melanina sobre y bajo mesada, ventanas de hierro forjado con vitreaux y paredes revestidas con cer\u00e1micos; ba\u00f1o: con ba\u00f1era, paredes revestidas con azulejos vidriados blancos originales, el lavatorio es original, el bidet e inodoro fueron cambiados y 2 dormitorios con techos de bovedilla pintados y pisos de pinotea original. Ambos tienen Split frio calor y calefactor a gas. Los pisos son: en el living comedor o patio (exagonal rojo con borde blanco) y en el ba\u00f1o (cuadrados blancos con borde negro) : es piso calc\u00e1reo importado de Inglaterra (original de 100 a\u00f1os) . En los dormitorios el piso es de pinotea original plastificada. En la cocina son baldosas de calc\u00e1reo original con dibujos. Las aberturas son originales, de madera de cedro pintadas, doble altura, casi todas con bandolera, vidrio repartido y persianas individuales. La puerta principal es de cedro barnizada con ventanas cuadradas arriba. Ambientes: living-comedor, 2 dormitorios amplios con techo doble altura; ba\u00f1o principal y cocina restaurados, con grifer\u00eda y artefactos original, cer\u00e1mico esmaltado, vanitory, cocina y calef\u00f3n nuevos, mesada de granito. se alquila sin mueblesedificio antiguo de tan solo 7 departamentos en total. Requisitos de alquiler: -Alquiler adelantado-Dep\u00f3sito 1 mes en d\u00f3lares al valor blue-Garant\u00eda propietaria o seguro de cauci\u00f3n-Contrato 2 a\u00f1os-Actualizaci\u00f3n trimestral seg\u00fan \u00edndice ipc-Ingresos comprobables- Certificaci\u00f3n de firmas y solicitud de informes al Registro Propiedad Inmueble (c/garant\u00eda propietaria) -Seguro del hogar- Locatario abona: luz y gas segun consumo, Aysa y abl\nPublicado desde ayer\nContactar", "revised": false, "rejected": false, "data": {"precio": "$ 460.000", "expensas": "$ 33.600 Expensas", "direccion": "Lavalle al 3600", "metros": "70 m\u00b2 tot.", "habitaciones": "3 amb.", "hace": "Contactar"}, "image": "https://imgar.zonapropcdn.com/avisos/1/00/53/58/78/02/360x266/1909699993.jpg?isFirstImage=true", "title": "PH \u00b7 50m\u00b2 \u00b7 3 Ambientes \u00b7 PH en Almagro, Lavalle Al 3600"}, "https://www.zonaprop.com.ar/propiedades/clasificado/alclappa-departamento-en-almagro-3-ambientes-excelente-53581226.html": {"id": "53581226", "date": "07-05-2024\n", "index": 17, "content": "$ 600.000\n$ 102.000 Expensas\nDirecci\u00f3n no informada\nAlmagro, Capital Federal\n92 m\u00b2 tot.\n3 amb.\n2 dorm.\n1 ba\u00f1o\nDepartamento 3 ambientes en Avenida Corrientes 4700, Almagro. Amplio y c\u00f3modo departamento de 92 m\u00b2 con capacidad para 4 personas totalmente amoblado en un 8no piso. Excelente ubicaci\u00f3n, cerca de Parque Centenario, y de varios medios de transporte, rodeado de comercios, restaurantes, bares y supermercados. El cuenta con: Dormitorio con cama matrimonial. Dormitorio con cama marinera. Cocina completa con cocina a gas, microondas, heladera con freezer y utensilios necesarios. Ba\u00f1o completo con ba\u00f1era y bidet. Living comedor con sof\u00e1, mesa y sillas. Tambi\u00e9n cuenta con calefacci\u00f3n y wifi. Balc\u00f3n con vista al frente. Lavadero con Lavarropas. Valor mensual: $600. 000. - Requisitos: 1er mes de alquiler, mes de dep\u00f3sito en garant\u00eda reembolsable al finalizar el contrato\nPublicado hace 3 d\u00edas\nContactar", "revised": false, "rejected": false, "data": {"precio": "$ 600.000", "expensas": "$ 102.000 Expensas", "direccion": "Direcci\u00f3n no informada", "metros": "92 m\u00b2 tot.", "habitaciones": "3 amb.", "hace": "Contactar"}, "image": "https://imgar.zonapropcdn.com/avisos/1/00/53/58/12/26/360x266/1909554352.jpg?isFirstImage=true", "title": "Departamento de 3 ambientes, Almagro \u00b7 Departamento en Almagro 3 Ambientes, Excelente Ubicaci\u00f3n (Due\u00f1o Directo)"}, "https://www.zonaprop.com.ar/propiedades/clasificado/alclapin-alquiler-3-ambientes-almagro-frente-balcon-53573547.html": {"id": "53573547", "date": "07-05-2024\n", "index": 18, "content": "$ 450.000\n$ 82.000 Expensas\nPalestina 600\nAlmagro, Capital Federal\n65 m\u00b2 tot.\n3 amb.\n2 dorm.\n1 ba\u00f1o\nAlquiler departamento de 3 ambientes al frente con balcon. Cuenta con living comedor, dos dormitorios con placard, cocina independiente con lavadero incorporado. Toilette de recepcion Y ba\u00f1o principal completo. Ubicado en palestina al 600 esquina sarmiento. Requisitos: ingresos en blanco + gtia propietaria caba O finaer. no se aceptan mascotas.\nSuper destacado\nPublicado hace 4 d\u00edas\nContactar", "revised": false, "rejected": false, "data": {"precio": "$ 450.000", "expensas": "$ 82.000 Expensas", "direccion": "Palestina 600", "metros": "65 m\u00b2 tot.", "habitaciones": "3 amb.", "hace": "Contactar"}, "image": "https://imgar.zonapropcdn.com/avisos/1/00/53/57/35/47/360x266/1909383962.jpg?isFirstImage=true", "title": "Departamento de 3 ambientes, Almagro \u00b7 Alquiler 3 Ambientes Almagro Frente Balcon"}, "https://www.zonaprop.com.ar/propiedades/clasificado/alclapin-departamento-en-alquiler-almagro-caballito-53575119.html": {"id": "53575119", "date": "07-05-2024\n", "index": 19, "content": "$ 600.000\n33 Orientales 40\nAlmagro, Capital Federal\n70 m\u00b2 tot.\n3 amb.\n2 dorm.\n2 ba\u00f1os\nAsesor: agustina miranda 11. 4. 475. 7784departamento en alquiler 3 ambientes, Almagro, Caballito - Capital FederalMuy buen estado, excelente luz, en zona residencial, pr\u00f3ximo a satsaid, Av Rivadavia y variedad de medios de transporte. Consta de amplio living comedor, cocina abierta al living, toilette, espacio de lavadero y ventanal, dormitorio grande con amplio placard, ba\u00f1o completo y segundo dormitorio con excelentes vistas, salida al balc\u00f3n. Cuenta con calefacci\u00f3n por radiadores, agua caliente por caldera, pisos cer\u00e1micos. En edificio de 7 pisos, 4 departamentos por piso, 1 ascensor. Valor de Alquiler $ 600. 000 + gastosConsultar condiciones. Llamame o enviame whatsapp. Los metros publicados son aproximados, las medidas exactas surgir\u00e1n de la escritura traslativa de dominio. La venta de este inmueble est\u00e1 sujeta a la tramitaci\u00f3n del C\u00f3digo de Transferencia de Inmuebles (coti), de conformidad con la normativa vigente (Res. Afip 2371/08, 2439/08 y ccs. ) por parte del propietario. En cumplimiento de las leyes provinciales vigentes que regulan elcorretaje inmobiliario, Ley Nacional 25. 028, Ley 22. 802 de Lealtad Comercial, Ley 24. 240 de Defensa al Consumidor, las normas del C\u00f3digo Civil y Comercial de la Naci\u00f3n y Constitucionales, los asesores no ejercen el corretaje inmobiliario. Codigoinmatricula Cucicba 4263\nSuper destacado\nPublicado hace 4 d\u00edas\nContactar", "revised": false, "rejected": false, "data": {"precio": "$ 600.000", "expensas": "", "direccion": "33 Orientales 40", "metros": "70 m\u00b2 tot.", "habitaciones": "3 amb.", "hace": "Contactar"}, "image": "https://imgar.zonapropcdn.com/avisos/1/00/53/57/51/19/360x266/1909415302.jpg?isFirstImage=true", "title": "Departamento \u00b7 70m\u00b2 \u00b7 3 Ambientes \u00b7 Departamento en Alquiler | Almagro, Caballito - Capital Federal | 3 Ambientes"}, "https://www.zonaprop.com.ar/propiedades/clasificado/alclapin-departamento-3-ambientes.-aguirre-al-300-53574488.html": {"id": "53574488", "date": "07-05-2024\n", "index": 20, "content": "$ 430.000\n$ 32.000 Expensas\nAGUIRRE 300. Entre Araoz y Alvarez julian\nVilla Crespo, Capital Federal\n61 m\u00b2 tot.\n3 amb.\n2 dorm.\n1 ba\u00f1o\n3 ambientes, en alquiler, villa crespo! Excelente ubicaci\u00f3n, a 1 cuadra de Av. Scalabrini Ortiz y a 3 cuadras de Av. Corrientes! Subte B estacion malabia. Living comedor con salida a balc\u00f3n corrido al frente, dos dormitorios con placard, cocina completa con conexi\u00f3n para lavarropas y lavadero independiente y ba\u00f1o completo! Living y dormitorios con pisos de parquet! Muy luminoso! Edificio con entrada y ascensores renovados! \"Se deja constancia que los m2 indicados son aproximados, al igual. que las medidas parciales de los ambientes, y el valor consignado de. expensas mensuales esta sujeta a verificacion y/o ajustes. Fotos de. cartacter no contractual. \"xintel(ber-ber-Ver datos)\nDestacado\nPublicado hace 4 d\u00edas\nContactar", "revised": false, "rejected": false, "data": {"precio": "$ 430.000", "expensas": "$ 32.000 Expensas", "direccion": "AGUIRRE 300. Entre Araoz y Alvarez julian", "metros": "61 m\u00b2 tot.", "habitaciones": "3 amb.", "hace": "Contactar"}, "image": "https://imgar.zonapropcdn.com/avisos/1/00/53/57/44/88/360x266/1909400903.jpg?isFirstImage=true", "title": "BER-BER-14987_2 \u00b7 Departamento 3 Ambientes. | Aguirre Al 300"}, "https://www.zonaprop.com.ar/propiedades/clasificado/alclphin-ph-en-1er-piso-de-3-ambientes-con-patio-y-terraza-53573812.html": {"id": "53573812", "date": "07-05-2024\n", "index": 21, "content": "34\n$ 550.000\nPADILLA 600. Entre Malabia y Acevedo\nVilla Crespo, Capital Federal\n104 m\u00b2 tot.\n3 amb.\n2 dorm.\n1 ba\u00f1o\nPh 3 ambientes con terraza, en alquiler, en villa crespo!. Excelente ubicaci\u00f3n!. A 1 cuadra de la Av. Scalabrini Ortiz, a 2 cuadras de Av. Corrientes (Subte B) y a 2 cuadras de Av. Warnes. Primer piso por escaleras. Ingreso por amplio living comedor con aire acondicionado. Dos dormitorios con doble acceso. Patio cubierto de 3. 60 x 1. 70. Cocina completa con espacio para comedor diario. Ba\u00f1o completo con ventilaci\u00f3n natural. Todo con doble circulaci\u00f3n. En planta alta: terraza propia de acceso compartido, con quincho y lavadero independiente. Todo en excelente estado. Muy luminoso!. Solo dos unidades en el piso. No apto mascotas, ni piscinaen la terraza! \"Se deja constancia que los m2 indicados son aproximados, al igual que las medidas parciales de los ambientes, y el valor consignado de expensas mensuales est\u00e1 sujeto a verificaci\u00f3n y/o ajustes. Fotos de car\u00e1cter no contractual. \"xintel(ber-ber-Ver datos)\nDestacado\nPublicado hace 4 d\u00edas\nContactar", "revised": false, "rejected": false, "data": {"precio": "$ 550.000", "expensas": "", "direccion": "PADILLA 600. Entre Malabia y Acevedo", "metros": "104 m\u00b2 tot.", "habitaciones": "3 amb.", "hace": "Contactar"}, "image": "https://imgar.zonapropcdn.com/avisos/1/00/53/57/38/12/360x266/1909387670.jpg?isFirstImage=true", "title": "BER-BER-14983_2 \u00b7 PH en 1er Piso de 3 Ambientes con Patio y Terraza Propia!"}, "https://www.zonaprop.com.ar/propiedades/clasificado/alclapin-departamento-3-ambientes-amplio-y-luminoso-53573112.html": {"id": "53573112", "date": "07-05-2024\n", "index": 22, "content": "5\n$ 650.000\nRivadavia 4011\nAlmagro, Capital Federal\n120 m\u00b2 tot.\n3 amb.\n2 dorm.\n1 ba\u00f1o\nDepartamento de 3 ambientes. Gran living. Balc\u00f3n con vista abierta. Cocina comedor. Ba\u00f1o y toilette. Muy bueno\nDestacado\nPublicado hace 4 d\u00edas\nContactar", "revised": false, "rejected": false, "data": {"precio": "$ 650.000", "expensas": "", "direccion": "Rivadavia 4011", "metros": "120 m\u00b2 tot.", "habitaciones": "3 amb.", "hace": "Contactar"}, "image": "https://imgar.zonapropcdn.com/avisos/1/00/53/57/31/12/360x266/1909374602.jpg?isFirstImage=true", "title": "Departamento de 3 ambientes, Almagro \u00b7 Departamento 3 Ambientes Amplio y Luminoso"}, "https://www.zonaprop.com.ar/propiedades/clasificado/alclapin-alquiler-3-ambientes-en-villa-crespo-53572670.html": {"id": "53572670", "date": "07-05-2024\n", "index": 23, "content": "$ 490.000\n$ 25.000 Expensas\nSerrano al 800\nVilla Crespo, Capital Federal\n70 m\u00b2 tot.\n3 amb.\n2 dorm.\n2 ba\u00f1os\nAlquiler hermoso departamento en Villa Crespo. Departamento en edificio de estilo ubicado al frente, sobre calle Serrano esquina Loyola. El departamento cuenta con dos dormitorios amplios con pisos de pinoteas pulidos y plastificados, living con pisos de pinotea, distribuidor con pisos de cemento alisado, dos ba\u00f1o, uno completo y un toilette, cocina con barra desayunador. Actualmente el departamento es El\u00e9ctrico ya que no cuenta con servicio de gas. Edificio de solo 3 pisos con 2 departamentos por piso y ascensor. Bajas expensas. Requisitos: contar con garant\u00eda en Capital o seguro de cauci\u00f3n y acreditaci\u00f3n de ingresos. Valor Inicial $490. 000Reajuste Trimestral por ipcerranti PropiedadesAlejandra Ver datos.\nPublicado hace 4 d\u00edas\nContactar", "revised": false, "rejected": false, "data": {"precio": "$ 490.000", "expensas": "$ 25.000 Expensas", "direccion": "Serrano al 800", "metros": "70 m\u00b2 tot.", "habitaciones": "3 amb.", "hace": "Contactar"}, "image": "https://imgar.zonapropcdn.com/avisos/1/00/53/57/26/70/360x266/1909363904.jpg?isFirstImage=true", "title": "Departamento \u00b7 70m\u00b2 \u00b7 3 Ambientes \u00b7 Alquiler 3 Ambientes en Villa Crespo"}, "https://www.zonaprop.com.ar/propiedades/clasificado/alclapin-esnaola-600-3-amb-60-m-amoblado-equipado-luminoso-53565338.html": {"id": "53565338", "date": "07-05-2024\n", "index": 24, "content": "$ 600.000\n$ 70.000 Expensas\nEsnaola 600\nParque Centenario, Capital Federal\n63 m\u00b2 tot.\n3 amb.\n2 dorm.\n1 ba\u00f1o\nEsnaola 600 y Av. Diaz Velez. Parque Centenario. 3 ambientes 60 mts. Living comedor. Balcon luminoso! Dormitorio principal con cama Queen. Dormitorio 2 con 1 cama de 1 plaza. Ba\u00f1o completo. Cocina equipada. Lavadero. Ropa blanca opcional. Losa radiante. Termotanque agua caliente. Aire acondicionado en el living. Ventiladores de techo en los dormitorios. 2 Televisores\nDestacado\nPublicado hace 5 d\u00edas\nContactar", "revised": false, "rejected": false, "data": {"precio": "$ 600.000", "expensas": "$ 70.000 Expensas", "direccion": "Esnaola 600", "metros": "63 m\u00b2 tot.", "habitaciones": "3 amb.", "hace": "Contactar"}, "image": "https://imgar.zonapropcdn.com/avisos/1/00/53/56/53/38/360x266/1909199052.jpg?isFirstImage=true", "title": "Departamento de 3 ambientes, Parque Centenario \u00b7 Esnaola 600 3 Amb 60 m Amoblado Equipado Luminoso"}, "https://www.zonaprop.com.ar/propiedades/clasificado/alclapin-3-ambientes-c-balcon-equipado-en-almagro-53565796.html": {"id": "53565796", "date": "07-05-2024\n", "index": 25, "content": "$ 700.000\n$ 80.000 Expensas\nDirecci\u00f3n no informada\nAlmagro, Capital Federal\n76 m\u00b2 tot.\n3 amb.\n2 dorm.\n1 ba\u00f1o\nSalguero Propiedades alquila departamento de 3 amb c/ balc\u00f3n, equipado, en Almagro. Ubicado en primer piso, al contrafrente. La unidad se encuentra completamente amoblada. Consta de: Living comedor con pisos de madera, aire acondicionado. Toilette para invitados. Cocina completa con muebles de alto y bajo mesada, espacio para lavarropas. Ba\u00f1o completo con ba\u00f1era. Dos dormitorios, ambos con placard y salida al balc\u00f3n. Patio interno. Edificio con piscina en planta baja. Condiciones: Contrato a 2 a\u00f1os. Ajustes cuatrimestralespor ipc. Disponibilidad inmediata. Capacidad m\u00e1xima: 4personas. Requisitos: Seguro de cauci\u00f3n Respaldar o Finaer y comprobantes de ingreso. 1 mes de deposito. 1 mes adelantado. Para visitas coordinar al Ver datos. - Para los casos de alquiler de vivienda, el monto m\u00e1ximo de comisi\u00f3n que se le puede requerir a los propietarios ser\u00e1 el equivalente al cuatro con quince cent\u00e9simos por ciento (4, 15%) del valor total del respectivo contrato. Se encuentra prohibido cobrar a los inquilinos que sean personas f\u00edsicas comisiones inmobiliarias y gastos de gestor\u00eda de informes\u009d. -\nDestacado\nPublicado hace 5 d\u00edas\nContactar", "revised": false, "rejected": false, "data": {"precio": "$ 700.000", "expensas": "$ 80.000 Expensas", "direccion": "Direcci\u00f3n no informada", "metros": "76 m\u00b2 tot.", "habitaciones": "3 amb.", "hace": "Contactar"}, "image": "https://imgar.zonapropcdn.com/avisos/1/00/53/56/57/96/360x266/1909208220.jpg?isFirstImage=true", "title": "Departamento de 3 ambientes, Almagro \u00b7 3 Ambientes C/ Balc\u00f3n Equipado en Almagro"}, "https://www.zonaprop.com.ar/propiedades/clasificado/alclapin-bulnes-111-3-ambientes-amoblado-y-equipado-en-53565392.html": {"id": "53565392", "date": "07-05-2024\n", "index": 26, "content": "$ 620.000\n$ 69.000 Expensas\nBulnes 111\nAlmagro, Capital Federal\n64 m\u00b2 tot.\n3 amb.\n2 dorm.\n1 ba\u00f1o\n3 ambientes amoblado y equipado super luminoso. Living comedor con salida al balcon. Cocina separada. 2 dormitorios con amplios placards. Ba\u00f1o completo.\nDestacado\nPublicado hace 5 d\u00edas\nContactar", "revised": false, "rejected": false, "data": {"precio": "$ 620.000", "expensas": "$ 69.000 Expensas", "direccion": "Bulnes 111", "metros": "64 m\u00b2 tot.", "habitaciones": "3 amb.", "hace": "Contactar"}, "image": "https://imgar.zonapropcdn.com/avisos/1/00/53/56/53/92/360x266/1909200087.jpg?isFirstImage=true", "title": "Departamento de 3 ambientes, Almagro \u00b7 Bulnes 111 - 3 Ambientes Amoblado y Equipado en Almagro!"}, "https://www.zonaprop.com.ar/propiedades/clasificado/alclapin-departamento-en-villa-crespo-3-ambientes-con-balcon-53568815.html": {"id": "53568815", "date": "07-05-2024\n", "index": 31, "content": "$ 500.000\n$ 65.000 Expensas\nPanama al 933 11 A\nVilla Crespo, Capital Federal\n66 m\u00b2 tot.\n3 amb.\n2 dorm.\n1 ba\u00f1o\nPanam\u00e1 933 11\u00b0 AEntre Sarmiento y Avda. Corrientes. Barrio: Almagro. Zona de f\u00e1cil acceso. A 1 cuadra del subte B (estaci\u00f3n Angel Gallardo) y cerca del Parque Centenario. - Living: 4. 45 x 3. 00- Balc\u00f3n: 3. 50 x 1. 20- Pasillo: 4. 00 x 0. 75- Dormitorio 1: 2. 95 x 2. 95- Dormitorio 2: 3. 50 x 2. 45- Cocina: 3. 50 x 1. 45- Lavadero: 1. 45 x 0. 80- 3 Ambientes al frente con balc\u00f3n. - Muy luminoso. - Living comedor. - 2 Dormitorios con placards. - Pisos flotante. - Cocina equipada con alacena y bajo mesada. - Ba\u00f1o completo con una ventana con salida al exterior. - Lavadero independiente. - Agua caliente por termotanque. - Calefacci\u00f3n individual. El edificio tiene 14 pisos. - Del 1\u00b0 al 14\u00b0: 6 deptos por piso. - 2 Ascensores. - Estado gral: Bueno. - Expensas: . - Tiene equipo de aire acondicionado en el living y en las habitaciones. - El termotanque a gas. - El dormitorio principal tiene salida al balc\u00f3n. requisitos: seguro de caucion respaldar finaer O garantiayames de adelanto $500. 000mes de deposito $500. 000contrato A 2 a\u00f1os aumento cuatrimestral por ipccorredor Inmobiliario David L. Polonsky cpi 3275 vremont pronin En el cumplimiento de la ley nacional 25. 028, ley 22. 802 de lealtad comercial. Ley 24. 240 de defensa al consumidor, las normas del c\u00f3digo civil y comercial de la naci\u00f3n y constitucionales. Los agentes no ejercen el corretaje inmobiliario. Ley 5859 - Art. 4: \"Para los casos de alquiler de vivienda, el monto m\u00e1ximo de comisi\u00f3n que se le puede requerir a los propietarios ser\u00e1 el equivalente al cuatro con quince cent\u00e9simos por ciento (4, 15%) del valor total del contrato. Se encuentra prohibido cobrar a los inquilinos que sean personas f\u00edsicas comisiones inmobiliarias y gastos de gestor\u00eda de informes\". (En caso de ser alquiler) Ley 5115 \u2013 Art. 1: El inmueble publicado no es accesible para personas con capacidades f\u00edsicas reducidas. (En caso de no ser accesible) Se deja constancia que las medidas, superficies y m2 consignados son aproximados, sujetos a verificaci\u00f3n y/o ajuste. El precio del inmueble puede ser modificado sin previo aviso.\nPublicado hace 5 d\u00edas\nContactar", "revised": false, "rejected": false, "data": {"precio": "$ 500.000", "expensas": "$ 65.000 Expensas", "direccion": "Panama al 933 11 A", "metros": "66 m\u00b2 tot.", "habitaciones": "3 amb.", "hace": "Contactar"}, "image": "https://imgar.zonapropcdn.com/avisos/1/00/53/56/88/15/360x266/1909275462.jpg?isFirstImage=true", "title": "Departamento \u00b7 60m\u00b2 \u00b7 3 Ambientes \u00b7 Departamento en Villa Crespo 3 Ambientes con Balcon"}, "https://www.zonaprop.com.ar/propiedades/clasificado/alclapin-alquiler-3-ambientes-constitucion-3800-boedo-53565447.html": {"id": "53565447", "date": "07-05-2024\n", "index": 32, "content": "$ 490.000\nConstitucion 3800 1\u00b0\nBoedo, Capital Federal\n85 m\u00b2 tot.\n3 amb.\n2 dorm.\n1 ba\u00f1o\nExcelente departamento 3 ambientes en alquiler en boedo. living comedor c\u00f3modo con balc\u00f3n corrido A la calle. cocina amplia con lavadero (conexi\u00f3n P/lavarropas) hall distribuci\u00f3n con cerramiento. habitaci\u00f3n principal con A/A. ambas habitaciones con placard. ba\u00f1o completo. ambientes ventilados. excelente luminosidad. pisos parquet. bajas expensas. pr\u00f3ximo A avenida san juan - subte. requisitos: . Actualizaci\u00f3n trimestral por indice ipc. . 1 mes dep\u00f3sito. . 1 mes alquiler adelantado. . Garant\u00eda propietaria caba o seguro de garant\u00eda Finaer (aprobado). . Antig\u00fcedad 1 a\u00f1o en relaci\u00f3n de dependencia. . Justificativo de ingresos que triplique valor de alquiler. . Contrato por 2 a\u00f1os. . No apto mascota. Comunicate Y agend\u00e1 tu visita. ley 5859: Art\u00edculo 4\u00b0. - Incorp\u00f3rase como inciso 8 del art\u00edculo 10 de la Ley 2340 (texto consolidado seg\u00fan Ley N\u00b0 5666) el siguiente texto: Para los casos de alquiler de vivienda, el monto m\u00e1ximo de comisi\u00f3n que se le puede requerir a los propietarios ser\u00e1 el equivalente al cuatro con quince cent\u00e9simos por ciento (4, 15%) del valor total del respectivo contrato. Se encuentra prohibido cobrar a los inquilinos que sean personas f\u00edsicas comisiones inmobiliarias y gastos de gestor\u00eda de informes. - Ley 5115: excepto que en la descripci\u00f3n de la propiedad se indique lo contrario, el edificio puede no contar con rampa para personas con movilidad reducida, y no ser Accesible para personas con discapacidades f\u00edsicas. - Nota importante: Toda la informaci\u00f3n y medidas provistas son aproximadas, deber\u00e1n ratificarse con la documentaci\u00f3n pertinente y no compromete contractualmente a nuestra empresa. Los gastos (expensas, abl) expresados refieren a la \u00faltima informaci\u00f3n recabada y deber\u00e1n confirmarse. Fotograf\u00edas no vinculantes ni contractuales. Torrisi propiedades. eduardo esp\u00edndola. mat. C. U. C. I. C. B. A nro. 26\nPublicado hace 5 d\u00edas\nContactar", "revised": false, "rejected": false, "data": {"precio": "$ 490.000", "expensas": "", "direccion": "Constitucion 3800 1\u00b0", "metros": "85 m\u00b2 tot.", "habitaciones": "3 amb.", "hace": "Contactar"}, "image": "https://imgar.zonapropcdn.com/avisos/1/00/53/56/54/47/360x266/1909200543.jpg?isFirstImage=true", "title": "Departamento \u00b7 83m\u00b2 \u00b7 3 Ambientes \u00b7 Alquiler - 3 Ambientes - Constituci\u00f3n 3800 - Boedo"}, "https://www.zonaprop.com.ar/propiedades/clasificado/alclapin-amplio-3-ambientes-en-villa-crespo-53563925.html": {"id": "53563925", "date": "07-05-2024\n", "index": 33, "content": "$ 470.000\n$ 43.000 Expensas\nDirecci\u00f3n no informada\nVilla Crespo, Capital Federal\n65 m\u00b2 tot.\n3 amb.\n2 dorm.\n1 ba\u00f1o\nDepartamento de 3 ambientes en excelente ubicaci\u00f3n en Villa Crespo. Dos dormitorios con placard, ba\u00f1o completo, living, cocina y lavadero independiente. No se admiten mascotas. Contrato a 2 a\u00f1os con ajuste trimestral seg\u00fan ipc. Requisitos: Garant\u00eda propietaria de caba o seguro de cauci\u00f3n Finaer. Justificaci\u00f3n de ingresos. Mes + deposito. Para visitar esta propiedad contactarse por whatsapp al 11*4949*8667. Carlos Mario Blum. Corredor Inmobiliario. Matr\u00edcula N\u00ba 88 folio 344 libro 377. cucicba N\u00b0 0272\nPublicado hace 5 d\u00edas\nContactar", "revised": false, "rejected": false, "data": {"precio": "$ 470.000", "expensas": "$ 43.000 Expensas", "direccion": "Direcci\u00f3n no informada", "metros": "65 m\u00b2 tot.", "habitaciones": "3 amb.", "hace": "Contactar"}, "image": "https://imgar.zonapropcdn.com/avisos/1/00/53/56/39/25/360x266/1909167577.jpg?isFirstImage=true", "title": "Departamento de 3 ambientes, Villa Crespo \u00b7 Amplio 3 Ambientes en Villa Crespo"}, "https://www.zonaprop.com.ar/propiedades/clasificado/alclapin-alquiler-dpto-3-amb-hip.-yrigoyen-3700-almagro-53569700.html": {"id": "53569700", "date": "07-05-2024\n", "index": 34, "content": "$ 600.000\n$ 76.000 Expensas\nHip\u00f3lito Yrigoyen 3700\nAlmagro, Capital Federal\n64 m\u00b2 tot.\n3 amb.\n2 dorm.\n1 ba\u00f1o\nCorredor Responsable: Marcelo Trujillo cucicba 6470 / cmcpdjlm 810- Contacto: Mart\u00edn Orso - mls id # Ver datos. Alquiler de departamento de 3 ambientes con amenities. *posibilidad de alquiler de cochera en el edificio ($45. 000) Hermoso Departamento en Almagro, Apto Profesional, en excelente ubicaci\u00f3n, de 3 ambientes, con balc\u00f3n al frente, en segundo piso. Consta de un living comedor, cocina, 2 dormitorios, ba\u00f1o completo, y toilette. La superficie total es de 64 metros. El edificio, en el amplio hall de entrada, posee 2 ascensores, sum en la terraza, con pileta. Las expensas incluyen Aysa. no se aceptan mascotas. Consultanos y coordinamos una visita. Transportes Cercanos. Colectivos: 2, 5, 7, 8, 19, 26, 84, 86, 88, 90, 103, 104, 105, 115, 127, 128, 132, 151, 160, 165, 180. Subtes (Metro): castro barros (L\u00ednea A) Remax Argentina S. R. L. No ejerce el corretaje inmobiliario. El presente sitio web es una plataforma en donde cada oficina inmobiliaria independiente que contrata los servicios re/max puede publicar las propiedades a su cargo. Cada oficina es de propiedad y gesti\u00f3n independiente, por lo que Remax Argentina S. R. L no interviene en los datos de la publicaci\u00f3n, en la operaci\u00f3n inmobiliaria, ni en la confecci\u00f3n y/o firma del boleto de compraventa y/o escritura y/o contrato de alquiler. En cumplimiento de las leyes vigentes que regulan el corretaje inmobiliario, Ley Nacional 25. 028, Ley 22. 802 de Lealtad Comercial, Ley 24. 240 de Defensa al Consumidor, las normas del C\u00f3digo Civil y Comercial de la Naci\u00f3n y Constitucionales, los agentes/gestores no ejercen el corretaje inmobiliario. Todas las operaciones inmobiliarias son objeto de intermediaci\u00f3n y conclusi\u00f3n por parte del corredor p\u00fablico inmobiliario colegiado a cargo de la publicaci\u00f3n, cuyos datos se exhiben en la presente. La presente publicaci\u00f3n describe las caracter\u00edsticas esenciales del inmueble, debi\u00e9ndose consultar al corredor p\u00fablico inmobiliario responsable de la operaci\u00f3n por la eventual actualizaci\u00f3n de las medidas, descripciones arquitect\u00f3nicas y funcionales, valores de expensas, servicios, impuestos, precios y dem\u00e1s informaci\u00f3n, cuyos valores son aproximados. Para los casos de alquiler de vivienda, el monto m\u00e1ximo de comisi\u00f3n que se le puede requerir a los propietarios ser\u00e1 el equivalente al cuatro con quince cent\u00e9simos por ciento (4, 15%) del valor total del respectivo contrato. Se encuentra prohibido cobrar a los inquilinos que sean personas f\u00edsicas comisiones inmobiliarias y gastos de gestor\u00eda de informes. El inmueble no es accesible para personas con discapacidades f\u00edsicas.\nPublicado hace 5 d\u00edas\nContactar", "revised": false, "rejected": false, "data": {"precio": "$ 600.000", "expensas": "$ 76.000 Expensas", "direccion": "Hip\u00f3lito Yrigoyen 3700", "metros": "64 m\u00b2 tot.", "habitaciones": "3 amb.", "hace": "Contactar"}, "image": "https://imgar.zonapropcdn.com/avisos/1/00/53/56/97/00/360x266/1909293600.jpg?isFirstImage=true", "title": "Departamento \u00b7 58m\u00b2 \u00b7 3 Ambientes \u00b7 Alquiler Dpto 3 Amb Hip. Yrigoyen 3700 (Almagro)"}, "https://www.zonaprop.com.ar/propiedades/clasificado/alclappa-alquiler-departamento-3amb-con-balcon-y-patio-53565001.html": {"id": "53565001", "date": "07-05-2024\n", "index": 35, "content": "$ 600.000\n$ 140.000 Expensas\nJufr\u00e9 153\nVilla Crespo, Capital Federal\n83 m\u00b2 tot.\n3 amb.\n2 dorm.\n1 ba\u00f1o\nDepartamento de 3 ambientes, primer piso a la calle. Living comedor con salida al balc\u00f3n corrido con protecci\u00f3n. Dormitorio principal con placard empotrado y salida al balc\u00f3n corrido. Segundo dormitorio con ventana al balc\u00f3n corrido y placard empotrado. Ba\u00f1o completo. Cocina completa con espacio para mesa y salida al patio cubierto. Agua caliente central. Requisitos para la renta: - Seguro de cauci\u00f3n finaer. - 1 mes de adelanto de alquiler. - 1 mes de dep\u00f3sito. - Demostraci\u00f3n de ingresos\nPublicado hace 5 d\u00edas\nContactar", "revised": false, "rejected": false, "data": {"precio": "$ 600.000", "expensas": "$ 140.000 Expensas", "direccion": "Jufr\u00e9 153", "metros": "83 m\u00b2 tot.", "habitaciones": "3 amb.", "hace": "Contactar"}, "image": "https://imgar.zonapropcdn.com/avisos/1/00/53/56/50/01/360x266/1909202796.jpg?isFirstImage=true", "title": "Departamento de 3 ambientes, Villa Crespo \u00b7 Alquiler Departamento 3amb con Balc\u00f3n y Patio"}, "https://www.zonaprop.com.ar/propiedades/clasificado/alclbgin-departamento-en-villa-crespo-53561562.html": {"id": "53561562", "date": "07-05-2024\n", "index": 37, "content": "$ 550.000\n$ 86.000 Expensas\nRamirez De Velasco, Juan al 500\nVilla Crespo, Capital Federal\n87 m\u00b2 tot.\n3 amb.\n2 dorm.\n1 ba\u00f1o\n3 ambientes al contra frente super luminoso. Consta de comodo living comedor con salida al balcon, 2 dormitorios con placards, ba\u00f1o y toillete, cocina con muebles altos y bajos, puerta blindada pent\u00e1gono, calefaccion por estufa. Excelente ubicacion Velasco al 500 entre Malabia y Avda. R. S. Ortiz, colecitvos, subte B estaci\u00f3n Malabia, comercios. Visitascombinar 24 hs antes visitas. Srta Naomi o Sr. Roberto 11 Ver datos. Pida tasaci\u00f3n: Efectuada por profesionales, que analizan permanentemente el desenvolvimiento del mercado. Conf\u00ede su patrimonio en una empresa s\u00f3lida con respaldo y prestigio. Conf\u00ede en el L\u00edder. Goldstein propiedades. Se deja constancia que los m2 son aproximados, al igual que las medidas parciales y el valor consignado de las expensas mensuales (en caso que corresponda pago de expensas) y las caracter\u00edsticas est\u00e1n sujetos a verificaci\u00f3n y/o ajustes, el precio del inmueble puede ser modificado sin previo aviso. En el caso de tratarse de un inmueble en construcci\u00f3n los detalles de terminaci\u00f3n y la fecha de entrega est\u00e1n sujetos a revisi\u00f3n. Fotos de car\u00e1cter no contractual. Las unidades publicadas est\u00e1n sujetas a disponibilidad. Goldstein Propiedades srl con domicilio en Avda. Corrientes 4666 act\u00faa solamente en car\u00e1cter de comercializadora de los inmuebles ofrecidos. En caso de tratarse de un terreno, la informaci\u00f3n de m2 construibles y plusval\u00eda es orientativa, debiendo ser constatada por el interesado. Inmueble no accesible para personas con discapacidad f\u00edsica ley 5115. Cucicba matr\u00edcula 37. Cmcpsi matr\u00edcula 6003. \u00danicamente en el caso de tratarse de alquiler de vivienda familiar, rige lo indicado en la ley 5859. Venta supeditada al cumplimiento por parte del propietario de los requisitos de la resoluci\u00f3n general N\u00ba 2371 de la afip (pedido de coti).\nPublicado hace 6 d\u00edas\nContactar", "revised": false, "rejected": false, "data": {"precio": "$ 550.000", "expensas": "$ 86.000 Expensas", "direccion": "Ramirez De Velasco, Juan al 500", "metros": "87 m\u00b2 tot.", "habitaciones": "3 amb.", "hace": "Contactar"}, "image": "https://imgar.zonapropcdn.com/avisos/1/00/53/56/15/62/360x266/1909118394.jpg?isFirstImage=true", "title": "Bodega-Galp\u00f3n \u00b7 80m\u00b2 \u00b7 3 Ambientes \u00b7 Departamento en Villa Crespo"}, "https://www.zonaprop.com.ar/propiedades/clasificado/alclapin-3amb-s-av!-ubic-ideal!-sj-y-boe!-coc-recic-lav!-bno!-53562562.html": {"id": "53562562", "date": "07-05-2024\n", "index": 39, "content": "$ 370.000\n$ 20.000 Expensas\nAvenida San Juan 3500\nBoedo, Capital Federal\n61 m\u00b2 tot.\n3 amb.\n2 dorm.\n1 ba\u00f1o\n\u00a1 3 ambientes en san juan Y boedo! \u00a1 listo para ser habitado! #Departamento | #Est\u00e1ndar | #3amb | #Lateral | #SanJuanyboedoAvenida San Juan 3500, Piso 2 - Ciudad Aut\u00f3noma de Buenos Aires\u00b7 Caracter\u00edsticas: ~ Departamento de tres (3) ambientes, en un segundo (2\u00ba) piso por escalera, dispuesto hacia el lateral, ubicado en el centro neur\u00e1lgico del barrio de Boedo. ~ Orientaci\u00f3n N (Norte). Impecable estado de conservaci\u00f3n interior de cada uno de sus ambientes. Vista interior. Gran ventilaci\u00f3n. Distribuci\u00f3n funcional~ Gran afluencia comercial y residencial en la zona. Ubicado en el coraz\u00f3n del emblem\u00e1tico cruce de calles principal del barrio: San Juan y Boedo. ~ Conectividad con medios de transporte. M\u00faltiples colectivos y subte/metro L\u00ednea E - Estaci\u00f3n Boedo. Cercan\u00eda a subida/bajada Autopista (au) 25 de Mayo. ~ Su oferta comercial incluye actividades recreativas y culturales, locales gastron\u00f3micos, farmacias, paseos, instituciones m\u00e9dicas y educativas. \u00b7 Edificio: ~ Antiguo, entre medianeras. Su fachada combina hormig\u00f3n pintado en color beige con planta baja revestida en m\u00e1rmol negro. ~ pb, m\u00e1s dos (2) pisos. No cuenta con ascensor. Baj\u00edsimas expensas. Previsibles gastos de mantenimiento mensuales. \u00b7 Distribuci\u00f3n: ~ Living comedor. ~ Cocina independiente. ~ Lavadero incorporado en cocina. ~ Distribuidor. ~ Ba\u00f1o completo con ba\u00f1era. ~ Dormitorio principal con placard. ~ Dormitorio secundario. \u00b7 Equipamiento: ~ Paredes pintadas en tonalidades claras conservan su natural luminosidad. Pisos de parquet en living comedor, distribuidor y dormitorios. ~ Ba\u00f1o con pisos revestidos en cer\u00e1micas color beige. Artefactos completos y ba\u00f1era instalados. Vanitory nuevo. Hogar en living comedor. Aire acondicionado de pared. ~ Cocina con pisos revestidos mosaicos color borravino claro con granas blancas y paredes revestidas en azulejos blancos con guarda decorativa. ~ Cocina a gas. Agua caliente suministrada a trav\u00e9s de calef\u00f3n a gas. Mobiliario de cocina (bajo mesada y alacena) de melamina/mdf color blanco. ~ Mesada de granito gris mara. Conexi\u00f3n para lavarropas bajo mesada. Turbina de acero inoxidable instalada en cocina como extractor / purificador de aire. ~ Cuenta con placard empotrado con puertas frontales, divisores, cajoneras, barrales y dem\u00e1s interiores a medida instalados en su dormitorio principal. \u00b7 Requisitos solicitados por la parte propietaria: ~ 1 mes de alquiler por adelantado. ~ 1 mes de dep\u00f3sito de garant\u00eda. ~ De la fianza: garant\u00eda propietaria o sistema de garant\u00edas de cauci\u00f3n (Finaer / Fiancor). ~ De los ingresos: \u00faltimos tres (3) recibos de sueldo o certificaci\u00f3n de ingresos por contador p\u00fablico. \u00b7 Condiciones ofrecidas por la parte propietaria: ~ Duraci\u00f3n del contrato: 12 meses (contrato de alquiler temporario sin muebles). ~ Actualizaci\u00f3n: ipc \u00b7 \u00cdndice de Precios al Consumidor publicado por el indec. ~ Periodicidad de actualizaci\u00f3n: Trimestral. #Nota: El edificio no cuenta con accesibilidad para personas con movilidad reducida (Ley 5115). Las im\u00e1genes en este anuncio publicadas son meramente ilustrativas y no poseen car\u00e1cter contractual. El importe de expensas anunciado ha sido extra\u00eddo de su \u00faltima facturaci\u00f3n, es orientativo, no vinculante y est\u00e1 sujeto a modificaciones y/o variaciones sin previa publicidad. Las medidas expresadas en el presente aviso son aproximadas y a t\u00edtulo informativo. Las medidas originales surgir\u00e1n de los respectivos planos y/o escritura del inmueble. El inmueble no es apto para mascotas por expresa solicitud de sus propietarios en el contrato de comercializaci\u00f3n. Somos especialistas en operaciones simult\u00e1neas. Tasamos en los 48 barrios de la Ciudad de Buenos Aires: . ar/tasaciones/spinelli propiedadeswww. spinelliprop. com. ar#Visitas por WhatsApp al +54 9 11 Ver datos#Reservas al Ver datos Ver datos#Consultas a Ver datos#Oficina en Avenida San Juan 3467 - cabadesde 1921 - #OportunidadesGrandesComoUnaCasa\nPublicado hace 6 d\u00edas\nContactar", "revised": false, "rejected": false, "data": {"precio": "$ 370.000", "expensas": "$ 20.000 Expensas", "direccion": "Avenida San Juan 3500", "metros": "61 m\u00b2 tot.", "habitaciones": "3 amb.", "hace": "Contactar"}, "image": "https://imgar.zonapropcdn.com/avisos/1/00/53/56/25/62/360x266/1909140248.jpg?isFirstImage=true", "title": "Departamento \u00b7 61m\u00b2 \u00b7 3 Ambientes \u00b7 3amb S/av! Ubic Ideal! Sj y Boe! Coc Recic Lav! B\u00f1o! Bjas Exp! Listo P/hab!"}, "https://www.zonaprop.com.ar/propiedades/clasificado/alclapin-3amb-s-av!-ubic-ideal!-sj-y-boe!-coc-recic-lav!-bno!-53562566.html": {"id": "53562566", "date": "07-05-2024\n", "index": 41, "content": "21\n$ 370.000\n$ 20.000 Expensas\nAvenida San Juan 3500\nAlmagro, Capital Federal\n61 m\u00b2 tot.\n3 amb.\n2 dorm.\n1 ba\u00f1o\n\u00a1 3 ambientes en san juan Y boedo! \u00a1 listo para ser habitado! #Departamento | #Est\u00e1ndar | #3amb | #Lateral | #SanJuanyboedoAvenida San Juan 3500, Piso 2 - Ciudad Aut\u00f3noma de Buenos Aires\u00b7 Caracter\u00edsticas: ~ Departamento de tres (3) ambientes, en un segundo (2\u00ba) piso por escalera, dispuesto hacia el lateral, ubicado en el centro neur\u00e1lgico del barrio de Boedo. ~ Orientaci\u00f3n N (Norte). Impecable estado de conservaci\u00f3n interior de cada uno de sus ambientes. Vista interior. Gran ventilaci\u00f3n. Distribuci\u00f3n funcional~ Gran afluencia comercial y residencial en la zona. Ubicado en el coraz\u00f3n del emblem\u00e1tico cruce de calles principal del barrio: San Juan y Boedo. ~ Conectividad con medios de transporte. M\u00faltiples colectivos y subte/metro L\u00ednea E - Estaci\u00f3n Boedo. Cercan\u00eda a subida/bajada Autopista (au) 25 de Mayo. ~ Su oferta comercial incluye actividades recreativas y culturales, locales gastron\u00f3micos, farmacias, paseos, instituciones m\u00e9dicas y educativas. \u00b7 Edificio: ~ Antiguo, entre medianeras. Su fachada combina hormig\u00f3n pintado en color beige con planta baja revestida en m\u00e1rmol negro. ~ pb, m\u00e1s dos (2) pisos. No cuenta con ascensor. Baj\u00edsimas expensas. Previsibles gastos de mantenimiento mensuales. \u00b7 Distribuci\u00f3n: ~ Living comedor. ~ Cocina independiente. ~ Lavadero incorporado en cocina. ~ Distribuidor. ~ Ba\u00f1o completo con ba\u00f1era. ~ Dormitorio principal con placard. ~ Dormitorio secundario. \u00b7 Equipamiento: ~ Paredes pintadas en tonalidades claras conservan su natural luminosidad. Pisos de parquet en living comedor, distribuidor y dormitorios. ~ Ba\u00f1o con pisos revestidos en cer\u00e1micas color beige. Artefactos completos y ba\u00f1era instalados. Vanitory nuevo. Hogar en living comedor. Aire acondicionado de pared. ~ Cocina con pisos revestidos mosaicos color borravino claro con granas blancas y paredes revestidas en azulejos blancos con guarda decorativa. ~ Cocina a gas. Agua caliente suministrada a trav\u00e9s de calef\u00f3n a gas. Mobiliario de cocina (bajo mesada y alacena) de melamina/mdf color blanco. ~ Mesada de granito gris mara. Conexi\u00f3n para lavarropas bajo mesada. Turbina de acero inoxidable instalada en cocina como extractor / purificador de aire. ~ Cuenta con placard empotrado con puertas frontales, divisores, cajoneras, barrales y dem\u00e1s interiores a medida instalados en su dormitorio principal. \u00b7 Requisitos solicitados por la parte propietaria: ~ 1 mes de alquiler por adelantado. ~ 1 mes de dep\u00f3sito de garant\u00eda. ~ De la fianza: garant\u00eda propietaria o sistema de garant\u00edas de cauci\u00f3n (Finaer / Fiancor). ~ De los ingresos: \u00faltimos tres (3) recibos de sueldo o certificaci\u00f3n de ingresos por contador p\u00fablico. \u00b7 Condiciones ofrecidas por la parte propietaria: ~ Duraci\u00f3n del contrato: 12 meses (contrato de alquiler temporario sin muebles). ~ Actualizaci\u00f3n: ipc \u00b7 \u00cdndice de Precios al Consumidor publicado por el indec. ~ Periodicidad de actualizaci\u00f3n: Trimestral. #Nota: El edificio no cuenta con accesibilidad para personas con movilidad reducida (Ley 5115). Las im\u00e1genes en este anuncio publicadas son meramente ilustrativas y no poseen car\u00e1cter contractual. El importe de expensas anunciado ha sido extra\u00eddo de su \u00faltima facturaci\u00f3n, es orientativo, no vinculante y est\u00e1 sujeto a modificaciones y/o variaciones sin previa publicidad. Las medidas expresadas en el presente aviso son aproximadas y a t\u00edtulo informativo. Las medidas originales surgir\u00e1n de los respectivos planos y/o escritura del inmueble. El inmueble no es apto para mascotas por expresa solicitud de sus propietarios en el contrato de comercializaci\u00f3n. Somos especialistas en operaciones simult\u00e1neas. Tasamos en los 48 barrios de la Ciudad de Buenos Aires: . ar/tasaciones/spinelli propiedadeswww. spinelliprop. com. ar#Visitas por WhatsApp al +54 9 11 Ver datos#Reservas al Ver datos Ver datos#Consultas a Ver datos#Oficina en Avenida San Juan 3467 - cabadesde 1921 - #OportunidadesGrandesComoUnaCasa\nPublicado hace 6 d\u00edas\nContactar", "revised": false, "rejected": false, "data": {"precio": "$ 370.000", "expensas": "$ 20.000 Expensas", "direccion": "Avenida San Juan 3500", "metros": "61 m\u00b2 tot.", "habitaciones": "3 amb.", "hace": "Contactar"}, "image": "https://imgar.zonapropcdn.com/avisos/1/00/53/56/25/66/360x266/1909140354.jpg?isFirstImage=true", "title": "Departamento 61m\u00b2 Alquiler  \u00b7 3amb S/av! Ubic Ideal! Sj y Boe! Coc Recic Lav! B\u00f1o! Bjas Exp! Listo P/hab!"}, "https://www.zonaprop.com.ar/propiedades/clasificado/alclapin-departamento-villa-crespo-53560404.html": {"id": "53560404", "date": "07-05-2024\n", "index": 42, "content": "11\n$ 500.000\n$ 53.000 Expensas\nCorrientes al 5600\nVilla Crespo, Capital Federal\n60 m\u00b2 tot.\n3 amb.\n2 dorm.\n1 ba\u00f1o\nDepartamento de 3 ambientes muy bien ubicado, muy luminoso. Gaed negocios inmobiliarios, cucicba mat. 226Contrato por dos a\u00f1os con actualizaci\u00f3n trimestral por icl\"Se deja constancia que los m2 son aproximados, al igual que las medidas parciales y el valor consignado de las expensas mensuales (en caso que corresponda pago de expensas) est\u00e1n sujetos a verificaci\u00f3n y/o ajustes, el precio del inmueble puede ser modificado sin previo aviso. Fotos de car\u00e1cter no contractual. Las unidades publicadas est\u00e1n sujetas a disponibilidad. Gaed Inmobiliaria act\u00faa solamente en car\u00e1cter de comercializadora de los inmuebles ofrecidos. Inmueble no accesible para personas con discapacidad f\u00edsica ley 5115. \u00danicamente en el caso de tratarse de alquiler de vivienda familiar, rige lo indicado en la ley 5859. \"gaed inmobiliaria. Cucicba matricula 226\nSuper destacado\nPublicado hace 6 d\u00edas\nContactar", "revised": false, "rejected": false, "data": {"precio": "$ 500.000", "expensas": "$ 53.000 Expensas", "direccion": "Corrientes al 5600", "metros": "60 m\u00b2 tot.", "habitaciones": "3 amb.", "hace": "Contactar"}, "image": "https://imgar.zonapropcdn.com/avisos/1/00/53/56/04/04/360x266/1909094688.jpg?isFirstImage=true", "title": "Departamento \u00b7 55m\u00b2 \u00b7 3 Ambientes \u00b7 Departamento - Villa Crespo"}, "https://www.zonaprop.com.ar/propiedades/clasificado/alclapin-3amb-nuevo-fte-2-balcones-60-m-sup2--muebles!-aa!-53560253.html": {"id": "53560253", "date": "07-05-2024\n", "index": 44, "content": "$ 500.000\n$ 57.000 Expensas\nAvenida Juan de Garay al 3200\nBoedo, Capital Federal\n60 m\u00b2 tot.\n3 amb.\n2 dorm.\n1 ba\u00f1o\n\u00a1 3 amb nuevo C/amenities! \u00a1 2 balcones, frente C/vista panor\u00e1mica! #Alquiler | #Departamento | #Amenities | #ParquePatricios | #3amb | #FrenteAvenida Juan de Garay 3200, Piso 7 - Ciudad Aut\u00f3noma de Buenos Aires\u00b7 Caracter\u00edsticas: ~ Departamento nuevo de tres (3) ambientes nuevo, dispuesto hacia el frente, con dos (2) balcones corridos, ubicado centricamente en el barrio de Parque Patricios. ~ Orientaci\u00f3n hacia el N (Norte). Vista a Ciudad. Ventilaci\u00f3n cruzada. Todos los ambientes cuentan con ventanas al exterior. ~ A 220 metros de Avenida Chiclana. A 410 metros de Avenida San Juan. A 420 metros de Avenida Boedo. A 610 metros de Avenida Jujuy. ~ Conectividad con medios de transporte. M\u00faltiples colectivos y subte/metro L\u00ednea H \u00b7 Estaci\u00f3n La Rioja. Cercan\u00eda a subida Autopista (au) 25 de Mayo. ~ Su oferta comercial incluye actividades recreativas y culturales, locales gastron\u00f3micos, farmacias, paseos, instituciones m\u00e9dicas y educativas. \u00b7 Edificio: ~ Entre medianeras. Su fachada con ladrillo a la vista y barandas de hierro pintadas en color negro. ~ El edificio cuenta con rampa con accesibilidad para personas de movilidad reducida. Acceso por puerta de blindex. Cerradura electr\u00f3nica para el ingreso. ~ Sus palieres comunes garantizan un habitar pac\u00edfico e integran pisos revestidos en porcelanatos color beige claro con terminaci\u00f3n mate y paredes pintadas en blanco. ~ 12 pisos. 3 departamentos por cada uno de sus pisos. 2 ascensores autom\u00e1ticos con cabina de acero inoxidable. Expensas en valores est\u00e1ndar (incluyen Aysa). \u00b7 Distribuci\u00f3n: ~ Living comedor (5. 10m x 3. 95m). ~ Balc\u00f3n 1 desde living comedor (4. 00m x 0. 90m). ~ Cocina sectorizada (2. 65m x 2. 00m). ~ Ba\u00f1o completo con ba\u00f1era (2. 20m x 1. 50m). ~ Dormitorio secundario (3. 05m x 2. 95m). ~ Dormitorio principal (3. 05m x 2. 95m). ~ Balc\u00f3n 2 desde dormitorio principal (1. 40m x 3. 50m). \u00b7 Equipamiento: ~ Paredes pintadas en tonalidades claras conservan su natural luminosidad. Pisos revestidos en porcelanato color gris. Dormitorios revestidos en alfombra. ~ Su cocina cuenta con pisos y paredes revestidos en porcelanato color gris. Mesada de granito. Bacha de acero inoxidable. Anafe, extractor de aire / purificador y cocina, todos el\u00e9ctricos, de acero inoxidable y de marca Domec. ~ Mobiliario de cocina (bajo-mesada y alacenas) de mdf/melamina color wengue. Mesada de m\u00e1rmol marr\u00f3n. Lavadero incorporado a bajo-mesada. Conexi\u00f3n para carga y descarga de lavarropas. ~ Provisi\u00f3n de agua caliente central por termotanques de alta recuperaci\u00f3n. Aire Acondicionado split en living comedor marca Sanyo. ~ Su ba\u00f1o cuenta con pisos y paredes revestidos en porcelanato color gris. Vanitory, artefactos y ba\u00f1era instalados. Calefacci\u00f3n con loza radiante con regulador de temperatura en dormitorios. ~ Cuenta con placares de piso/techo con puertas de apertura frontal, divisores, estantes, barrales, cajoneras y dem\u00e1s interiores a medida instalados en los dos dormitorios. ~ Heladera marca Samsung. Mesa de comedor y silla, de pl\u00e1stico. Cama instalada en dormitorio. \u00b7 Amenities: ~ Sector para parrilleros con equipamiento. ~ Terraza con solarium y espacio de relax. \u00b7 Adicionales: ~ Agua caliente central por termotanques de alta recuperaci\u00f3n. ~ Control de acceso a trav\u00e9s de cerradura electromagn\u00e9tica. \u00b7 Requisitos solicitados por la parte propietaria: ~ 1 mes de alquiler por adelantado. ~ 1 mes de dep\u00f3sito de garant\u00eda. ~ De la fianza: garant\u00eda propietaria o sistema de garant\u00edas de cauci\u00f3n (Finaer / Fiancor). ~ De los ingresos: \u00faltimos tres (3) recibos de sueldo o certificaci\u00f3n de ingresos por contador p\u00fablico. \u00b7 Condiciones ofrecidas por la parte propietaria: ~ Duraci\u00f3n del contrato: 6 \u00f3 12 meses (contrato de alquiler temporario con muebles). ~ Actualizaci\u00f3n: ipc \u00b7 \u00cdndice de Precios al Consumidor publicado por el indec. ~ Periodicidad de actualizaci\u00f3n: Trimestral. #Nota: El edificio no cuenta con accesibilidad para personas con movilidad reducida (Ley 5115). Las im\u00e1genes en este anuncio publicadas son meramente ilustrativas y no poseen car\u00e1cter contractual. El importe de expensas anunciado ha sido extra\u00eddo de su \u00faltima facturaci\u00f3n, es orientativo, no vinculante y est\u00e1 sujeto a modificaciones y/o variaciones sin previa publicidad. Las medidas expresadas en el presente aviso son aproximadas y a t\u00edtulo informativo. Las medidas originales surgir\u00e1n de los respectivos planos y/o escritura del inmueble. El inmueble no es apto para mascotas por expresa solicitud de sus propietarios en el contrato de comercializaci\u00f3n. Somos especialistas en operaciones simult\u00e1neas. Tasamos en los 48 barrios de la Ciudad de Buenos Aires: . ar/tasaciones/spinelli propiedadeswww. spinelliprop. com. ar#Visitas por WhatsApp al +54 9 11 Ver datos#Reservas al Ver datos Ver datos#Consultas a Ver datos#Oficina en Avenida San Juan 3467 - cabadesde 1921 - #OportunidadesGrandesComoUnaCasa\nPublicado hace 6 d\u00edas\nContactar", "revised": false, "rejected": false, "data": {"precio": "$ 500.000", "expensas": "$ 57.000 Expensas", "direccion": "Avenida Juan de Garay al 3200", "metros": "60 m\u00b2 tot.", "habitaciones": "3 amb.", "hace": "Contactar"}, "image": "https://imgar.zonapropcdn.com/avisos/1/00/53/56/02/53/360x266/1909091410.jpg?isFirstImage=true", "title": "Departamento Alquiler de 3 ambientes \u00b7 3amb Nuevo Fte 2 Balcones \u00b7 60 m\u00b2 \u00b7 Muebles! Aa! Heladera! Cama! Parr! Amenities!"}, "https://www.zonaprop.com.ar/propiedades/clasificado/alclphin-humahuaca-3800-ph-3-ambientes-en-alquiler-almagro-53545911.html": {"id": "53545911", "date": "07-05-2024\n", "index": 49, "content": "$ 300.000\nHumahuaca al 3800\nAlmagro, Capital Federal\n60 m\u00b2 tot.\n3 amb.\n2 dorm.\n1 ba\u00f1o\nExcelente ph de Estilo, con techos altos de 3 Ambientes, Ubicado en Almagro 3 Er Piso por EscaleraValor Final, incluye abl y expesas Requisito Excluyente Garant\u00eda Propietaria de Capital y Recibo de Sueldo. Living Comedor y + 2 DormitoriosBa\u00f1o con DuchaCocina Independiente con lavadero integradoNo se aceptan mascotasExcelente Ubicaci\u00f3n, sobre Av Medrano, a 100mts de Av corrientes, Subte btodos los medios de Transportecons\u00faltenosjumo inmobiliariatelf: Ver datos - Ver datos - Ver datos\"Para los casos de alquiler de vivienda, el monto m\u00e1ximo de comisi\u00f3n que se le puede requerir a los propietarios ser\u00e1 el equivalente al cuatro con quince cent\u00e9simos por ciento (4, 15%) del valor total del respectivo contrato. Se encuentra prohibido cobrar a los inquilinos que sean personas f\u00edsicas comisiones inmobiliarias y gastos de gestor\u00eda de informes\".\nPublicado hace 8 d\u00edas\nContactar", "revised": false, "rejected": false, "data": {"precio": "$ 300.000", "expensas": "", "direccion": "Humahuaca al 3800", "metros": "60 m\u00b2 tot.", "habitaciones": "3 amb.", "hace": "Contactar"}, "image": "https://imgar.zonapropcdn.com/avisos/1/00/53/54/59/11/360x266/1908765618.jpg?isFirstImage=true", "title": "PH \u00b7 55m\u00b2 \u00b7 3 Ambientes \u00b7 Humahuaca 3800, PH 3 Ambientes, en Alquiler, Almagro"}, "https://www.zonaprop.com.ar/propiedades/clasificado/alclphin-villa-crespo-ph-espectacular-3-amb-terraza-propia-53539335.html": {"id": "53539335", "date": "07-05-2024\n", "index": 54, "content": "$ 680.000\nVICENTE CAMARGO 266\nVilla Crespo, Capital Federal\n140 m\u00b2 tot.\n3 amb.\n2 dorm.\n1 ba\u00f1o\nVilla crespo/parque centenario: 3 ambientes depto tipo casa ph en planta baja entrada por pasillo camargo Y julian alvarez A mts del parque centenario lindo living comedor 4, 50 X 4, 50 mts dos dormitorios con placard dos patios cubiertos con toldo met\u00e1lico cocina amplia con comedor diario ba\u00f1o completo - terraza propia muy grande parrilla Y quincho en terraza sin expensas rodeado de avenidas angel gallardo - warnes - corrientes Y raul scalabrini ortiz - cerca de estaciones subte B zona muy lina barrio residencial. - cel Ver datos jaime \u00d3 Ver datos silvia\nPublicado hace 10 d\u00edas\nContactar", "revised": false, "rejected": false, "data": {"precio": "$ 680.000", "expensas": "", "direccion": "VICENTE CAMARGO 266", "metros": "140 m\u00b2 tot.", "habitaciones": "3 amb.", "hace": "Contactar"}, "image": "https://imgar.zonapropcdn.com/avisos/1/00/53/53/93/35/360x266/1908616665.jpg?isFirstImage=true", "title": "PH de 3 ambientes, Villa Crespo \u00b7 Villa Crespo PH Espectacular 3 Amb Terraza Propia Quincho Parrilla"}, "https://www.zonaprop.com.ar/propiedades/clasificado/alclapin-billinghurst-y-corrientes-vista-abierta-3-amb-53533913.html": {"id": "53533913", "date": "07-05-2024\n", "index": 57, "content": "$ 470.000\n$ 45.200 Expensas\nBILLINGHURST 500\nAlmagro, Capital Federal\n80 m\u00b2 tot.\n3 amb.\n2 dorm.\n1 ba\u00f1o\nDepartamento de 3 amb. + dependencia de servicio- piso alto- vista abierta- muy luminoso Y aireado - cocina separada- lavadero incorporado - living comedor con salida al balc\u00f3n- 2 dormitorios con placard Y dep. De serv. (opci\u00f3n 3\u00b0 dorm. ) - ba\u00f1o completo - agua caliente central - bajas expensas- sobre Av. Corrientes- linea de subte \"B\"- varias lineas de colectivo. - no se aceptan mascotas. - grupo mega recoleta. tel. Ver datos\nSuper destacado\nPublicado hace 11 d\u00edas\nContactar", "revised": false, "rejected": false, "data": {"precio": "$ 470.000", "expensas": "$ 45.200 Expensas", "direccion": "BILLINGHURST 500", "metros": "80 m\u00b2 tot.", "habitaciones": "3 amb.", "hace": "Contactar"}, "image": "https://imgar.zonapropcdn.com/avisos/1/00/53/53/39/13/360x266/1908495916.jpg?isFirstImage=true", "title": "LIVING COMEDOR \u00b7 Billinghurst y Corrientes - Vista Abierta - 3 Amb + Dep"}, "https://www.zonaprop.com.ar/propiedades/clasificado/alclapin-departamento-3-ambientes-en-alquiler!-53537746.html": {"id": "53537746", "date": "07-05-2024\n", "index": 59, "content": "$ 540.000\n$ 75.000 Expensas\nAv. Diaz Velez al 4300\nAlmagro, Capital Federal\n61 m\u00b2 tot.\n3 amb.\n2 dorm.\n1 ba\u00f1o\nDepartamento de 3 ambientes al frente, muy luminoso y en excelente estado. Consta de cocina separada con espacio de lavadero, living comedor de buenas dimensiones, dos dormitorios y ba\u00f1o completo. condiciones de ingreso: -Garantia propietaria y demostracion de ingresos-Un mes de deposito + un mes de adelanto-Contrato por 2 a\u00f1os con aumentos trimestrales por indice icl (indice de contratos de locacion) \"Se deja constancia que los m2 son aproximados, al igual que las medidas parciales y el valor consignado de las expensas mensuales (en caso que corresponda pago de expensas) est\u00e1n sujetos a verificaci\u00f3n y/o ajustes, el precio del inmueble puede ser modificado sin previo aviso. Fotos de car\u00e1cter no contractual. Las unidades publicadas est\u00e1n sujetas a disponibilidad. Gaed Inmobiliaria act\u00faa solamente en car\u00e1cter de comercializadora de los inmuebles ofrecidos. Inmueble no accesible para personas con discapacidad f\u00edsica ley 5115. \u00danicamente en el caso de tratarse de alquiler de vivienda familiar, rige lo indicado en la ley 5859. \"gaed inmobiliaria. Cucicba matricula 226\nPublicado hace 11 d\u00edas\nContactar", "revised": false, "rejected": false, "data": {"precio": "$ 540.000", "expensas": "$ 75.000 Expensas", "direccion": "Av. Diaz Velez al 4300", "metros": "61 m\u00b2 tot.", "habitaciones": "3 amb.", "hace": "Contactar"}, "image": "https://imgar.zonapropcdn.com/avisos/1/00/53/53/77/46/360x266/1908573764.jpg?isFirstImage=true", "title": "Departamento \u00b7 53m\u00b2 \u00b7 3 Ambientes \u00b7 Departamento 3 Ambientes en Alquiler!"}, "https://www.zonaprop.com.ar/propiedades/clasificado/alclapin-hermoso-depto-3-ambientes-al-frente-cocina-separada-53533648.html": {"id": "53533648", "date": "07-05-2024\n", "index": 60, "content": "$ 499.999\n$ 36.200 Expensas\nVera 132\nVilla Crespo, Capital Federal\n65 m\u00b2 tot.\n3 amb.\n2 dorm.\n1 ba\u00f1o\nExcelente depto de 3 ambientes, super luminoso, balcon corrido al frente, cocina seprada, y ba\u00f1o, living y habitacion principal dan al frente. Cerca de todo. A 100 metros de Av corrientes y estacion B Del subte. A 200 metros Parque Centenario. Se muestra y esta disponible para su ingreso a partir del 1-5-24. Contactar x whatsapp\nPublicado hace 11 d\u00edas\nContactar", "revised": false, "rejected": false, "data": {"precio": "$ 499.999", "expensas": "$ 36.200 Expensas", "direccion": "Vera 132", "metros": "65 m\u00b2 tot.", "habitaciones": "3 amb.", "hace": "Contactar"}, "image": "https://imgar.zonapropcdn.com/avisos/1/00/53/53/36/48/360x266/1908494839.jpg?isFirstImage=true", "title": "Departamento de 3 ambientes, Villa Crespo \u00b7 Hermoso Depto 3 Ambientes Al Frente - Cocina Separada"}, "https://www.zonaprop.com.ar/propiedades/clasificado/alclphin-ph-en-almagro-53595026.html": {"id": "53595026", "date": "08-05-2024\n", "index": 4, "content": "$ 650.000\nZelaya al 3100\nAlmagro, Capital Federal\n100 m\u00b2 tot.\n4 amb.\n3 dorm.\n1 ba\u00f1o\nAlquiler 4 ambientes ph con Terraza, Amueblado Sin Expensas! ! excelente ph T/casa en AlmagroAlquiler 4 ambientes ph con terraza, amuebladosin expensas! excelente ph / casa con patio Y terraza! ! En una ubicaci\u00f3n estrat\u00e9gica, sobre el pasaje zelaya al 3100, a 1 cuadra del shopping abasto y del subte l\u00ednea \"B\", a 3 cuadras de Av. C\u00f3rdoba, a 6 cuadras del subte \u201cD\u201d, a solo 10 min del Obelisco. El Pasaje Zelaya tiene un importante movimiento cultural y social, en \u00e9l se encuentran Teatro El Cubo, Teatro Asterion y Puerta 18. El ph tiene una superficie total 120 m2 distribuido en dos plantas, incluyendo terrarza y balc\u00f3n. Es muy c\u00f3modo y funcional, totalmente luminoso y ventilado, con calefacci\u00f3n y dos aires fr\u00edo/calor, escritorios de trabajo o estudio \u00a1Ideal para quien quiera vivir en un barrio bohemio y cerca de todo! Descripci\u00f3n de la Unidad: Primera planta: Living comedor y con ventanal, con aire frio/calor. Cocina integrada totalmente equipada (cocina a gas, heladera, microondas, vajilla), con muebles sobre y bajo mesada. Ba\u00f1o de completo con ba\u00f1era. Dormitorio principal de 4 x 4 m, al frente balc\u00f3n, pisos cer\u00e1micos, placard de pared, balc\u00f3n, cama de una plaza, ventilador de techo, calefacci\u00f3n el\u00e9ctrica, televisor. Segundo dormitorio: 4 x 4 m al frente, pisos de Cer\u00e1micos, balc\u00f3n, cama de dos plazas, placard, escritorio de trabajo, ventilador de pie, calefacci\u00f3n el\u00e9ctrica. Segunda planta: Amplio dormitorio de 5 x 5 m con cama de dos plazas y zona de estudio, con escritorio amplio, excelente iluminaci\u00f3n, techos altos, aire frio/calor, biblioteca, salida a la terraza. Terraza amplia con sol todo el a\u00f1o (orientaci\u00f3n norte), mesa y sillas de exterior, macetas y plantas. Alquiler Tradicional por 24 mesesValor: $650. 000, ajuste cuatrimestral por ipc-Servicio a Cargo del Locatario: agua (Aysa), electricidad (Edseur), suministro de gas (Metrogas), Internet (ya instalado Personal 100mb, posibilidad de cambio). requisitos de ingreso: Contar con garant\u00eda propietaria a satisfacci\u00f3n del locador, comprobantes de ingresos, sujeto a la aprobaci\u00f3n del sector correspondiente y del propietario. *Montos para ingresar: 1 Mes por adelantado- Monto de Deposito; un mes y medio u opcional un mes actualizable. El inquilino no abona comisi\u00f3n inmobiliaria. \u201cPara los casos de alquiler de vivienda, el monto m\u00e1ximo de comisi\u00f3n que se le puede requerir a los propietarios ser\u00e1 el equivalente al cuatro con quince cent\u00e9simos por ciento (4, 15%) del valor total del respectivo contrato. Se encuentra prohibido cobrar a los inquilinos que sean personas f\u00edsicas comisiones inmobiliarias y gastos de gestar\u00eda de informes\u201d. C. P. I Matr\u00edcula 2914/ 8879solicite entrevista hoy mismo. Seg\u00fan Ley 5115, se informa que el presente inmueble no cumple con las condiciones de accesibilidad para personas con discapacidades f\u00edsicas\nSuper destacado\nPublicado hoy\nContactar", "revised": true, "rejected": false, "data": {"precio": "$ 650.000", "expensas": "", "direccion": "Zelaya al 3100", "metros": "100 m\u00b2 tot.", "habitaciones": "4 amb.", "hace": "Contactar"}, "image": "https://imgar.zonapropcdn.com/avisos/1/00/53/59/50/26/360x266/1909855615.jpg?isFirstImage=true", "title": "PH \u00b7 90m\u00b2 \u00b7 4 Ambientes \u00b7 PH en Almagro", "comment": "test"}, "https://www.zonaprop.com.ar/propiedades/clasificado/alclphin-ph-de-3-amb-con-terraza-parrilla-y-pileta-en-villa-53599405.html": {"id": "53599405", "date": "08-05-2024\n", "index": 11, "content": "$ 700.000\nAngel Justiniano Carranza 998\nVilla Crespo, Capital Federal\n86 m\u00b2 tot.\n3 amb.\n2 dorm.\n1 ba\u00f1o\nPh, entrada individual. 3 amb con terraza, parrilla y pileta. Pisos parquet de madera. Calefaccion x tiro balanceado en cada ambiente. 1 ba\u00f1o completo en 1 er piso. pb living comedor con cocina integrada. 1era Planta 2 dormitorios con placard con interiores completos con ventanas al frente y ba\u00f1o completo. Hall dsitribuidor. 2do piso-Terraza con parrilla y peque\u00f1a piscina de fibra de vidrio. Requisitos. Comprobantes de ingresos. Garantia propietaria en caba. Mes de deposito. Condiciones del contrato. 2 a\u00f1os. Actualizaciones trimestrales a \u00ecndice icl. 30% de comisi\u00f3n inmobiliaria. coordinar visita x wsp Ver datos\nPublicado hoy\nContactar", "revised": false, "rejected": true, "data": {"precio": "$ 700.000", "expensas": "", "direccion": "Angel Justiniano Carranza 998", "metros": "86 m\u00b2 tot.", "habitaciones": "3 amb.", "hace": "Contactar"}, "image": "https://imgar.zonapropcdn.com/avisos/1/00/53/59/94/05/360x266/1909959979.jpg?isFirstImage=true", "title": "living comedor cocina PB \u00b7 PH de 3 Amb con Terraza Parrilla y Pileta en Villa Crespo. Sin Expensas"}, "https://www.zonaprop.com.ar/propiedades/clasificado/alclapin-departamento-en-almagro-53593605.html": {"id": "53593605", "date": "08-05-2024\n", "index": 13, "content": "$ 520.000\n$ 92.000 Expensas\nPanama al 900\nAlmagro, Capital Federal\n70 m\u00b2 tot.\n4 amb.\n3 dorm.\n1 ba\u00f1o\nComodo departamento de 4 ambientes a media cuadra de Av Corrientes al 4600. En piso 10\u00aa con vista abiertaCuenta con tres habitaciones, un ba\u00f1o completo, cocina separada con lavadero, Living comendor con balc\u00f3n y toilete de recepci\u00f3n. Edificio con dos ascensores. Comercializa Gomez servicios inmobiliarios cucicba Mat. 7397 // cmcpsi Mat. 6629Realizamos tasaciones en caba, gba norte.\nPublicado hoy\nContactar", "revised": false, "rejected": false, "data": {"precio": "$ 520.000", "expensas": "$ 92.000 Expensas", "direccion": "Panama al 900", "metros": "70 m\u00b2 tot.", "habitaciones": "4 amb.", "hace": "Contactar"}, "image": "https://imgar.zonapropcdn.com/avisos/1/00/53/59/36/05/360x266/1909827935.jpg?isFirstImage=true", "title": "Living comedor \u00b7 Departamento en Almagro"}, "https://www.zonaprop.com.ar/propiedades/clasificado/alclappa-alquiler-de-hermoso-y-gran-dto.-de-4am.-c-balcon-53579421.html": {"id": "53579421", "date": "08-05-2024\n", "index": 28, "content": "$ 1.000.000\n$ 100.000 Expensas\nAv. Independencia 3700\nBoedo, Capital Federal\n85 m\u00b2 tot.\n4 amb.\n3 dorm.\n1 ba\u00f1o\n1 coch.\nExcelente Dto. De 4 Amb. Con Balcon al frente. Orientacion Norte s/Avenida, con Puerta de Ingreso blindada, ubicado sobre Av. Independencia, cerca de Av. Boedo, muy luminoso y con muy buena ventilacion cruzada, piso flotante en todos los ambientes y ceramico en la cocina y en los dos ba? os. Cocina Amplia y lavadero. El alquiler incluye la cochera fija y baulera. Contrato por dos a\u00f1os, Actualizaci\u00f3n cuatrimestral, seg\u00fan ipc. Condiciones: Garant\u00eda propietaria de Capital. Recibo de Sueldo. Un mes de deposito y un mes de alquiler. No se admiten mascotas.\nPublicado hace 3 d\u00edas\nContactar", "revised": false, "rejected": false, "data": {"precio": "$ 1.000.000", "expensas": "$ 100.000 Expensas", "direccion": "Av. Independencia 3700", "metros": "85 m\u00b2 tot.", "habitaciones": "4 amb.", "hace": "Contactar"}, "image": "https://imgar.zonapropcdn.com/avisos/1/00/53/57/94/21/360x266/1909518488.jpg?isFirstImage=true", "title": "FOTO 1. ENTRADA AL DTO. \u00b7 Alquiler de Hermoso y Gran Dto. de 4am. C/balcon, Cochera y Baulera"}, "https://www.zonaprop.com.ar/propiedades/clasificado/alclapin-3-amb-c-dep-en-alq.-villa-crespo-53574058.html": {"id": "53574058", "date": "08-05-2024\n", "index": 33, "content": "$ 600.000\n$ 45.100 Expensas\nav corrientes 4664\nVilla Crespo, Capital Federal\n71 m\u00b2 tot.\n3 amb.\n3 dorm.\n1 ba\u00f1o\nPintoresco departamento de 3 ambientes con dependencia, al frente con balc\u00f3n. Cuenta con entrada de servicio. Cocina con lavadero independiente. Ba\u00f1o con ducha. Toilette. El edificio se encuentra sobre Av. Corrientes, a una cuadra de \u00c1ngel Gallardo (Estaci\u00f3n Angel Gallardo de la linea B de subtes), pr\u00f3ximo al Parque Centenario. Martillero responsable: nicolas ortiz. Matr\u00edcula cucicba 6337. brokerin servicios inmobiliarios. Conforme la ley 5115 de accesibilidad el inmueble posee acceso para personas con movilidad reducida. Aceptamos garant\u00eda respaldar: -aprobado-express-sin-cargo? i=7fe1f8abaad094e0b5cb1b01d712f708&h=5c86e2d4656c14a3011f3d60b262c35c\nDestacado\nPublicado hace 4 d\u00edas\nContactar", "revised": false, "rejected": false, "data": {"precio": "$ 600.000", "expensas": "$ 45.100 Expensas", "direccion": "av corrientes 4664", "metros": "71 m\u00b2 tot.", "habitaciones": "3 amb.", "hace": "Contactar"}, "image": "https://imgar.zonapropcdn.com/avisos/1/00/53/57/40/58/360x266/1909392691.jpg?isFirstImage=true", "title": "Departamento de 3 ambientes, Villa Crespo \u00b7 3 Amb C/dep en Alq. - Villa Crespo"}, "https://www.zonaprop.com.ar/propiedades/clasificado/alclocin-oficina-en-alquiler-en-almagro-53571713.html": {"id": "53571713", "date": "08-05-2024\n", "index": 36, "content": "$ 600.000\n$ 91.200 Expensas\nAv. Hip\u00f3lito Yrigoyen 4000 PB\nAlmagro, Capital Federal\n90 m\u00b2 tot.\n4 amb.\n3 dorm.\n2 ba\u00f1os\nDepartamento de 4 ambientes con dependencia en pb al frente exclusivo para uso profesional. 2 ventanas a la calle. Living comedor, 3 dormitorios con placares, ba\u00f1o completo, cocina equipada, lavadero, dependencia de servicio o comedor diario, toilette de servicio, patio, baulera. Puerta blindada. Pisos de parquet. Expensas con agua incluida. Ubicado en edificio de esquina a metros de Av. Rivadavia, cercano al subte l\u00ednea A. Requisitos: - Contrato por 2 a\u00f1os. - Ajuste trimestral seg\u00fan \u00edndice de precios al consumidor publicado por el indec. - Seguro de cauci\u00f3n o garant\u00eda propietaria de caba. - Ingresos demostrables. - 1 mes de dep\u00f3sito. - Comisi\u00f3n inmobiliaria 5% del total del contrato + iva\nPublicado hace 4 d\u00edas\nContactar", "revised": false, "rejected": false, "data": {"precio": "$ 600.000", "expensas": "$ 91.200 Expensas", "direccion": "Av. Hip\u00f3lito Yrigoyen 4000 PB", "metros": "90 m\u00b2 tot.", "habitaciones": "4 amb.", "hace": "Contactar"}, "image": "https://imgar.zonapropcdn.com/avisos/1/00/53/57/17/13/360x266/1909342361.jpg?isFirstImage=true", "title": "Oficina comercial \u00b7 78m\u00b2 \u00b7 4 Ambientes \u00b7 Oficina en Alquiler en Almagro"}, "https://www.zonaprop.com.ar/propiedades/clasificado/alclapin-departamento-en-alquiler-en-almagro-solo-uso-53566156.html": {"id": "53566156", "date": "08-05-2024\n", "index": 42, "content": "34\n$ 600.000\n$ 91.200 Expensas\nAv. Hip\u00f3lito Yrigoyen 4000 PB\nAlmagro, Capital Federal\n90 m\u00b2 tot.\n4 amb.\n3 dorm.\n2 ba\u00f1os\nDepartamento de 4 ambientes con dependencia en pb al frente exclusivo para uso profesional. 2 ventanas a la calle. Living comedor, 3 dormitorios con placares, ba\u00f1o completo, cocina equipada, lavadero, dependencia de servicio o comedor diario, toilette de servicio, patio, baulera. Puerta blindada. Pisos de parquet. Expensas con agua incluida. Ubicado en edificio de esquina a metros de Av. Rivadavia, cercano al subte l\u00ednea A. Requisitos: - Contrato por 2 a\u00f1os. - Ajuste trimestral seg\u00fan \u00edndice de precios al consumidor publicado por el indec. - Seguro de cauci\u00f3n o garant\u00eda propietaria de caba. - Ingresos demostrables. - 1 mes de dep\u00f3sito. - Comisi\u00f3n inmobiliaria 5% del total del contrato + iva\nDestacado\nPublicado hace 5 d\u00edas\nContactar", "revised": false, "rejected": false, "data": {"precio": "$ 600.000", "expensas": "$ 91.200 Expensas", "direccion": "Av. Hip\u00f3lito Yrigoyen 4000 PB", "metros": "90 m\u00b2 tot.", "habitaciones": "4 amb.", "hace": "Contactar"}, "image": "https://imgar.zonapropcdn.com/avisos/1/00/53/56/61/56/360x266/1909215247.jpg?isFirstImage=true", "title": "Departamento \u00b7 78m\u00b2 \u00b7 4 Ambientes \u00b7 Departamento en Alquiler en Almagro S\u00f3lo Uso Profesional"}}