{"https://www.zonaprop.com.ar/propiedades/clasificado/alclapin-departamento-en-viamonte-1800-piso-12-3-ambientes-53597235.html": {"id": "53597235", "date": "07-05-2024\n", "index": 4, "content": "$ 700.000\n$ 200.000 Expensas\nViamonte al 1800\nBarrio Norte, Capital Federal\n82 m\u00b2 tot.\n3 amb.\n2 dorm.\n1 ba\u00f1o\n1 coch.\nBarrio norteViamonte 1815 piso 12departamento de 3 ambientes con balcon a la callesuper luminosocochera fija cubiertavigilanciaaire acondicionado frio caloringresos mensuales comprobables / garantia propietaria o seguro de caucion Por cualquier duda por favor comunicarse de lunes a viernes de 10 a 18 hs kerr propiedadescucicba 2941\"Para los casos de alquiler de vivienda, el monto m\u00e1ximo de comisi\u00f3n que se le puederequerir a los propietarios ser\u00e1 el equivalente al cuatro con quince cent\u00e9simos porciento (4, 15%) del valor total del respectivo contrato. Se encuentra prohibido cobrar alos inquilinos que sean personas f\u00edsicas comisiones inmobiliarias y gastos de gestor\u00edade informes\"\nPublicado hoy\nContactar", "revised": false, "rejected": true, "data": {"precio": "$ 700.000", "expensas": "$ 200.000 Expensas", "direccion": "Viamonte al 1800", "metros": "82 m\u00b2 tot.", "habitaciones": "3 amb.", "hace": "Contactar"}, "image": "https://imgar.zonapropcdn.com/avisos/1/00/53/59/72/35/360x266/1909901083.jpg?isFirstImage=true", "title": "Departamento \u00b7 75m\u00b2 \u00b7 3 Ambientes \u00b7 1 Cochera \u00b7 Departamento en Viamonte 1800 Piso 12 3 Ambientes Alquiler Cochera Super Luminoso"}, "https://www.zonaprop.com.ar/propiedades/clasificado/alclapin-departamento-3-ambientes-en-uriburu-y-av-corrientes-53595092.html": {"id": "53595092", "date": "07-05-2024\n", "index": 5, "content": "$ 420.000\n$ 45.000 Expensas\nUriburu 400 y Av. Corrientes. Subte B, 3 Ambientes de 70m2 al Frente. muy Luminoso.\nBalvanera, Capital Federal\n70 m\u00b2 tot.\n3 amb.\n2 dorm.\n1 ba\u00f1o\nUriburu y Corrientes. Subte B, 3 ambientes de 70m2 al frente. Muy luminoso. Todo El\u00e9ctricoDepartamento c\u00f3modo y amplio. Doble circulaci\u00f3nLiving Comedor2 Dormitorios, 1 con balc\u00f3nCocina completa todo el\u00e9ctricoTermotanque el\u00e9ctricoBano completoLavadero independienteZona Facultades, Subte, a 5 minutos de zona de Teatrossambra propiedadescarolina L. SternMatr\u00edcula N\u00b05539cucicba\nPublicado hoy\nContactar", "revised": false, "rejected": false, "data": {"precio": "$ 420.000", "expensas": "$ 45.000 Expensas", "direccion": "Uriburu 400 y Av. Corrientes. Subte B, 3 Ambientes de 70m2 al Frente. muy Luminoso.", "metros": "70 m\u00b2 tot.", "habitaciones": "3 amb.", "hace": "Contactar"}, "image": "https://imgar.zonapropcdn.com/avisos/1/00/53/59/50/92/360x266/1909857891.jpg?isFirstImage=true", "title": "Departamento \u00b7 70m\u00b2 \u00b7 3 Ambientes \u00b7 Departamento 3 Ambientes en Uriburu y Av Corrientes"}, "https://www.zonaprop.com.ar/propiedades/clasificado/alclapin-alquiler-de-departamento-3-ambientes-en-barrio-53591599.html": {"id": "53591599", "date": "07-05-2024\n", "index": 6, "content": "$ 480.000\nViamonte al 2100\nBalvanera, Capital Federal\n70 m\u00b2 tot.\n3 amb.\n2 dorm.\n1 ba\u00f1o\nAlquiler de departamento 3 ambientes muy luminoso apto profesional. Departamento ubicado sobre la calle Viamonte entre Junin y Pdte. Jos\u00e9 Evaristo Uriburu, a 1 cuadra de la estaci\u00f3n Facultad de Medicina, linea subte D y a 3 cuadras de la estaci\u00f3n Pasteur linea subte B, cercano y con acceso a otros medios de transporte p\u00fablico, cerca de la Plaza Houssay, Hospital de Cl\u00ednicas y de la Facultad de Medicina (uba). Zona con variedad de Locales comerciales de distintos rubros. La unidad cuenta con: 2 habitaciones una de ellas puede ser usado como escritorioPlacares1 ba\u00f1o completoCocina separada con artefacto de 4 hornallas a gasAgua caliente por termo tanque centralAscensorExpensas febrero 2024 $ 50. 000valor del alquiler $ 480. 000Esta Propiedad es apta para personas con movilidad reducida, Los montos de expensas, tasas e impuestos deben ser confirmados ya que dependen de la fecha en la que se obtuvo la informaci\u00f3n. Los metros publicados son aproximados, las medidas exactas surgir\u00e1n de la escritura traslativa de dominio. Los metros publicados son aproximados, las medidas exactas surgir\u00e1n de la escritura traslativa de dominio. La venta de este inmueble est\u00e1 sujeta a la tramitaci\u00f3n del C\u00f3digo de Transferencia de Inmuebles (coti), de conformidad con la normativa vigente (Res. Afip 2371/08, 2439/08 y ccs. ) por parte del propietario. Sumatres Prop\u00f3sito InmobiliarioMatricula Cucicba 4293\u201d.\nPublicado hoy\nContactar", "revised": false, "rejected": true, "data": {"precio": "$ 480.000", "expensas": "", "direccion": "Viamonte al 2100", "metros": "70 m\u00b2 tot.", "habitaciones": "3 amb.", "hace": "Contactar"}, "image": "https://imgar.zonapropcdn.com/avisos/1/00/53/59/15/99/360x266/1909782128.jpg?isFirstImage=true", "title": "Departamento \u00b7 70m\u00b2 \u00b7 3 Ambientes \u00b7 Alquiler de Departamento 3 Ambientes en Barrio Balvanera"}, "https://www.zonaprop.com.ar/propiedades/clasificado/alclapin-departamento-semi-amoblado-en-av-corrientes-al-2900-53589957.html": {"id": "53589957", "date": "07-05-2024\n", "index": 14, "content": "$ 400.000\n$ 65.000 Expensas\nAv. Corrientes al 2900\nBalvanera, Capital Federal\n60 m\u00b2 tot.\n3 amb.\n2 dorm.\n1 ba\u00f1o\nBuen departamento de 3 ambientes ubicado en Avenida Corrientes al 2900. Pr\u00f3ximo al Abasto Shopping. Ba\u00f1o completo, cocina y lavadero independiente, dos dormitorios con placar. Pisos de madera en dormitorios y estar comedor. El departamento cuenta con los muebles que se ven en las im\u00e1genes. no se aceptan mascotas\nDestacado\nPublicado desde ayer\nContactar", "revised": false, "rejected": true, "data": {"precio": "$ 400.000", "expensas": "$ 65.000 Expensas", "direccion": "Av. Corrientes al 2900", "metros": "60 m\u00b2 tot.", "habitaciones": "3 amb.", "hace": "Contactar"}, "image": "https://imgar.zonapropcdn.com/avisos/1/00/53/58/99/57/360x266/1909898006.jpg?isFirstImage=true", "title": "Departamento \u00b7 60m\u00b2 \u00b7 3 Ambientes \u00b7 Departamento Semi - Amoblado en Av Corrientes Al 2900"}, "https://www.zonaprop.com.ar/propiedades/clasificado/alclapin-alquiler-semipiso-3-amb-palermo-53591459.html": {"id": "53591459", "date": "07-05-2024\n", "index": 16, "content": "$ 600.000\n$ 135.000 Expensas\nAraoz al 2800\nBarrio Norte, Capital Federal\n89 m\u00b2 tot.\n3 amb.\n2 dorm.\n2 ba\u00f1os\nExcelente 3 ambientes. PalermoSemipiso al contrafrente con balc\u00f3n corrido, living comedor y dormitorios con pisos de parquet, cocina c/ comedor diario, 2 ba\u00f1os, lavadero independiente. Excelente ubicaci\u00f3n! A 2 cuadras de Jardin Botanico y Parque Las Heras. A 4 cuadras de Subte D, estaci\u00f3n Scalabrini Ortiz. requisitos*1 mes A delantado + 2 meses de deposito (en dolares) *ingresos comprobables*garantia propietaria (caba, prov. Bs. As. ) O seguro caucion*contrato A 2 a\u00f1os*incremento mensual por ipc\"Para los casos de alquiler de vivienda, el monto m\u00e1ximo de comisi\u00f3n que se le puede requerir a los propietarios ser\u00e1 el equivalente al cuatro con quince cent\u00e9simos por ciento (4, 15%) del valor total del respectivo contrato. Se encuentra prohibido cobrar a los inquilinos que sean personas f\u00edsicas comisiones inmobiliarias y gastos de gestor\u00eda de informes\". - Constructora e Inmobiliaria Crecer S. A. H\u00e9ctor Gonzalez - Matricula Cucicba 5189.\nPublicado desde ayer\nContactar", "revised": false, "rejected": true, "data": {"precio": "$ 600.000", "expensas": "$ 135.000 Expensas", "direccion": "Araoz al 2800", "metros": "89 m\u00b2 tot.", "habitaciones": "3 amb.", "hace": "Contactar"}, "image": "https://imgar.zonapropcdn.com/avisos/1/00/53/59/14/59/360x266/1909779395.jpg?isFirstImage=true", "title": "Departamento \u00b7 81m\u00b2 \u00b7 3 Ambientes \u00b7 Alquiler Semipiso 3 Amb Palermo"}, "https://www.zonaprop.com.ar/propiedades/clasificado/alclapin-departamento-en-alquiler-de-2-dorm.-en-balvanera-53589220.html": {"id": "53589220", "date": "07-05-2024\n", "index": 19, "content": "$ 400.000\n$ 35.000 Expensas\nDirecci\u00f3n no informada\nBalvanera, Capital Federal\n60 m\u00b2 tot.\n3 amb.\n2 dorm.\n1 ba\u00f1o\nUbicado en Sarmiento y Montevideo, se encuentra este departamento en alquiler. Con un precio de ar$400. 000. El departamento cuenta con agua corriente, luz, gas natural, y termotanque el\u00e9ctrico. Cocina separada. Ba\u00f1o completo. Pisos porcellanato\nPublicado desde ayer\nContactar", "revised": false, "rejected": false, "data": {"precio": "$ 400.000", "expensas": "$ 35.000 Expensas", "direccion": "Direcci\u00f3n no informada", "metros": "60 m\u00b2 tot.", "habitaciones": "3 amb.", "hace": "Contactar"}, "image": "https://imgar.zonapropcdn.com/avisos/1/00/53/58/92/20/360x266/1909730570.jpg?isFirstImage=true", "title": "Departamento de 3 ambientes, Balvanera \u00b7 Departamento en Alquiler de 2 Dorm. en Balvanera"}, "https://www.zonaprop.com.ar/propiedades/clasificado/alclapin-departamento-3-ambientes-en-uriburu-y-av-corrientes.-53590716.html": {"id": "53590716", "date": "07-05-2024\n", "index": 21, "content": "20\n$ 420.000\n$ 45.000 Expensas\nUriburu 400 y Av. Corrientes. Subte B, 3 Ambientes de 70m2 al Frente. muy Luminoso. Todo El\u00e9ctrico\nOnce, Capital Federal\n70 m\u00b2 tot.\n3 amb.\n2 dorm.\n1 ba\u00f1o\nUriburu y Corrientes. Subte B, 3 ambientes de 70m2 al frente. Muy luminoso. Todo El\u00e9ctricoDepartamento c\u00f3modo y amplio. Doble circulaci\u00f3nLiving Comedor2 Dormitorios, 1 con balc\u00f3nCocina completa todo el\u00e9ctricoTermotanque el\u00e9ctricoBano completoLavadero independienteZona Facultades, Subte, a 5 minutos de zona de Teatrossambra propiedadescarolina L. SternMatr\u00edcula N\u00b05539cucicba\nPublicado desde ayer\nContactar", "revised": false, "rejected": false, "data": {"precio": "$ 420.000", "expensas": "$ 45.000 Expensas", "direccion": "Uriburu 400 y Av. Corrientes. Subte B, 3 Ambientes de 70m2 al Frente. muy Luminoso. Todo El\u00e9ctrico", "metros": "70 m\u00b2 tot.", "habitaciones": "3 amb.", "hace": "Contactar"}, "image": "https://imgar.zonapropcdn.com/avisos/1/00/53/59/07/16/360x266/1909762928.jpg?isFirstImage=true", "title": "Departamento \u00b7 70m\u00b2 \u00b7 3 Ambientes \u00b7 Departamento 3 Ambientes en Uriburu y Av Corrientes."}, "https://www.zonaprop.com.ar/propiedades/clasificado/alclocin-departamento-de-3-ambientes-con-dependencia-en-primer-53579490.html": {"id": "53579490", "date": "07-05-2024\n", "index": 25, "content": "$ 380.000\n$ 78.600 Expensas\nHipolito Yrigoyen y Rincon\nCongreso, Capital Federal\n105 m\u00b2 tot.\n3 amb.\n2 dorm.\n2 ba\u00f1os\nAmplio departamento de tres ambientes con dependencia. Al ingreso c\u00f3moda recepci\u00f3n de 4, 5 x 3. 4 con pisos plastificados. En paralelo otro ambiente de 3. 4 x 2. 4 que podr\u00eda destinarse a comedor. Sala de grandes dimensiones de 8, 5 x 3, 7. Ideal para clases o exposiciones. Posibilidad de subidividir para hacer otra habitaci\u00f3n. Sector de cocina separada. Ba\u00f1o con ducha y espejo de cuerpo completo. Hacia el fondo del pasillo de distribuci\u00f3n un toilette. En segunda planta, dependencia alfombrada. Edificio se\u00f1orial, ubicado a tres cuadras de la estaci\u00f3n de subte A, a una cuadra de Av. Rivadavia en pleno barrio de Congreso. \u00c1rea con gran desarrollo comercial y variedad de l\u00edneas de transporte hacia toda la ciudad. Apto para uso profesional. No se admiten mascotas. Requisitos: garant\u00eda de Caba o seguro de cauci\u00f3n y justificaci\u00f3n de ingresos. Contrato a 2 a\u00f1os con actualizaci\u00f3n trimestral por ipc (\u00cdndice de precios al consumidor)\nPublicado hace 3 d\u00edas\nContactar", "revised": false, "rejected": true, "data": {"precio": "$ 380.000", "expensas": "$ 78.600 Expensas", "direccion": "Hipolito Yrigoyen y Rincon", "metros": "105 m\u00b2 tot.", "habitaciones": "3 amb.", "hace": "Contactar"}, "image": "https://imgar.zonapropcdn.com/avisos/1/00/53/57/94/90/360x266/1909515513.jpg?isFirstImage=true", "title": "Oficina comercial \u00b7 105m\u00b2 \u00b7 3 Ambientes \u00b7 Departamento de 3 Ambientes con Dependencia en Primer Piso - Apto Profesional"}, "https://www.zonaprop.com.ar/propiedades/clasificado/alclapin-departamento-de-3-ambientes-con-dependencia-en-primer-53579487.html": {"id": "53579487", "date": "07-05-2024\n", "index": 27, "content": "$ 380.000\n$ 78.600 Expensas\nHipolito Yrigoyen y Rincon\nCongreso, Capital Federal\n105 m\u00b2 tot.\n3 amb.\n2 dorm.\n2 ba\u00f1os\nAmplio departamento de tres ambientes con dependencia. Al ingreso c\u00f3moda recepci\u00f3n de 4, 5 x 3. 4 con pisos plastificados. En paralelo otro ambiente de 3. 4 x 2. 4 que podr\u00eda destinarse a comedor. Sala de grandes dimensiones de 8, 5 x 3, 7. Ideal para clases o exposiciones. Posibilidad de subidividir para hacer otra habitaci\u00f3n. Sector de cocina separada. Ba\u00f1o con ducha y espejo de cuerpo completo. Hacia el fondo del pasillo de distribuci\u00f3n un toilette. En segunda planta, dependencia alfombrada. Edificio se\u00f1orial, ubicado a tres cuadras de la estaci\u00f3n de subte A, a una cuadra de Av. Rivadavia en pleno barrio de Congreso. \u00c1rea con gran desarrollo comercial y variedad de l\u00edneas de transporte hacia toda la ciudad. Apto para uso profesional. No se admiten mascotas. Requisitos: garant\u00eda de Caba o seguro de cauci\u00f3n y justificaci\u00f3n de ingresos. Contrato a 2 a\u00f1os con actualizaci\u00f3n trimestral por ipc (\u00cdndice de precios al consumidor)\nPublicado hace 3 d\u00edas\nContactar", "revised": false, "rejected": true, "data": {"precio": "$ 380.000", "expensas": "$ 78.600 Expensas", "direccion": "Hipolito Yrigoyen y Rincon", "metros": "105 m\u00b2 tot.", "habitaciones": "3 amb.", "hace": "Contactar"}, "image": "https://imgar.zonapropcdn.com/avisos/1/00/53/57/94/87/360x266/1909515483.jpg?isFirstImage=true", "title": "Departamento \u00b7 105m\u00b2 \u00b7 3 Ambientes \u00b7 Departamento de 3 Ambientes con Dependencia en Primer Piso - Apto Profesional"}, "https://www.zonaprop.com.ar/propiedades/clasificado/alclappa-alquiler-3-amb.-frente-balcon-corrido-luminoso-53581036.html": {"id": "53581036", "date": "07-05-2024\n", "index": 29, "content": "$ 450.000\n$ 70.000 Expensas\nDirecci\u00f3n no informada\nBalvanera, Capital Federal\n71 m\u00b2 tot.\n3 amb.\n2 dorm.\n1 ba\u00f1o\nPeron Y azcuenaga - 71 m totales. 67 m cubiertos. 5to piso con un amplio balc\u00f3n al frente. Vista abierta. Muy luminoso, Dos dormitorios, Ba\u00f1o y Toilete, Cocina, Lavadero. A 300 metros de la estaci\u00f3n de Once. A 200 metros de Av. Rivadavia. (Subte L\u00ednea A). A 200 metros de Av. Corrientes (Subte L\u00ednea B). El valor consignado de expensas est\u00e1 sujeto a variaci\u00f3n y/o ajuste. Las medidas, superficies y los m2 indicados son aproximados y solo a t\u00edtulo informativo.\nPublicado hace 3 d\u00edas\nContactar", "revised": false, "rejected": false, "data": {"precio": "$ 450.000", "expensas": "$ 70.000 Expensas", "direccion": "Direcci\u00f3n no informada", "metros": "71 m\u00b2 tot.", "habitaciones": "3 amb.", "hace": "Contactar"}, "image": "https://imgar.zonapropcdn.com/avisos/1/00/53/58/10/36/360x266/1909549602.jpg?isFirstImage=true", "title": "Living Comedor \u00b7 Alquiler 3 Amb. - Frente - Balc\u00f3n Corrido - Luminoso - Balvanera"}, "https://www.zonaprop.com.ar/propiedades/clasificado/alclappa-impecable-departamento-con-vista-panoramica-en-torre-53579574.html": {"id": "53579574", "date": "07-05-2024\n", "index": 30, "content": "$ 700.000\n$ 150.000 Expensas\nGallo 955\nBarrio Norte, Capital Federal\n68 m\u00b2 tot.\n3 amb.\n2 dorm.\n2 ba\u00f1os\nEn Torre Premium con Vigilancia las 24hs, 2 Piscinas, Gimnasio, Parrillas, Jardines, juegos infantiles, sum, sauna Calefaci\u00f2n y agua caliente por caldera individual. Requisitos: Ingresos acordes demostrables-Gtias personales o seguro de cauci\u00f2n. Actualizaci\u00f2n trimestral por icl. M\u00e0ximo 2 adultos y 1 menor.\nPublicado hace 3 d\u00edas\nContactar", "revised": false, "rejected": true, "data": {"precio": "$ 700.000", "expensas": "$ 150.000 Expensas", "direccion": "Gallo 955", "metros": "68 m\u00b2 tot.", "habitaciones": "3 amb.", "hace": "Contactar"}, "image": "https://imgar.zonapropcdn.com/avisos/1/00/53/57/95/74/360x266/1909519502.jpg?isFirstImage=true", "title": "Departamento de 3 ambientes, Barrio Norte \u00b7 Impecable Departamento con Vista Panor\u00e0mica en Torre con Amenities"}, "https://www.zonaprop.com.ar/propiedades/clasificado/alclapin-alquiler-3-ambientes-con-dos-patios-congreso-53573894.html": {"id": "53573894", "date": "07-05-2024\n", "index": 31, "content": "$ 400.000\n$ 45.000 Expensas\nTTE GRAL PERON 1300\nCongreso, Capital Federal\n70 m\u00b2 tot.\n3 amb.\n2 dorm.\n1 ba\u00f1o\nAlquiler departamento de 3 ambientes con 2 patios. apto profesional. cocina independiente. ba\u00f1o completo. requisitos: ingresos en blanco + gtia propietaria caba O finaer\nSuper destacado\nPublicado hace 4 d\u00edas\nContactar", "revised": false, "rejected": false, "data": {"precio": "$ 400.000", "expensas": "$ 45.000 Expensas", "direccion": "TTE GRAL PERON 1300", "metros": "70 m\u00b2 tot.", "habitaciones": "3 amb.", "hace": "Contactar"}, "image": "https://imgar.zonapropcdn.com/avisos/1/00/53/57/38/94/360x266/1909389331.jpg?isFirstImage=true", "title": "Departamento de 3 ambientes, Congreso \u00b7 Alquiler 3 Ambientes con Dos Patios Congreso"}, "https://www.zonaprop.com.ar/propiedades/clasificado/alclapin-tres-amb-y-depcias-al-frente.-pueyrredon-y-pena.-53571286.html": {"id": "53571286", "date": "07-05-2024\n", "index": 32, "content": "$ 650.000\n$ 160.000 Expensas\nAv Pueyrred\u00f3n 1913 3\u00b0 \"C\" - CABA -\nBarrio Norte, Capital Federal\n70 m\u00b2 tot.\n3 amb.\n2 dorm.\n2 ba\u00f1os\nExcelente tres ambientes con depcias al frente. -Todo luz y sol. -Amplio Balc\u00f3n corrido. -Cocina comedor diario con entrada de servicio. -Dos dormitorios con placard. -Un ba\u00f1o completo con ba\u00f1adera (luz y ventilaci\u00f3n natural). -Lavadero cubierto independiente. -Ba\u00f1o de servicio. -Pisos de parquet plastificados. -Agua caliente individual por calef\u00f3n. -Calefacci\u00f3n central por losa radiante. -Categor\u00eda. -Impecable. -(villafa\u00f1e propiedades Ver datos Ver datos). -\nDestacado\nPublicado hace 4 d\u00edas\nContactar", "revised": false, "rejected": true, "data": {"precio": "$ 650.000", "expensas": "$ 160.000 Expensas", "direccion": "Av Pueyrred\u00f3n 1913 3\u00b0 \"C\" - CABA -", "metros": "70 m\u00b2 tot.", "habitaciones": "3 amb.", "hace": "Contactar"}, "image": "https://imgar.zonapropcdn.com/avisos/1/00/53/57/12/86/360x266/1909335342.jpg?isFirstImage=true", "title": "Departamento de 3 ambientes, Barrio Norte \u00b7 Tres Amb y Depcias Al Frente. - Pueyrred\u00f3n y Pe\u00f1a. - Balc\u00f3n Corrido. - Todo Luz. - Impec"}, "https://www.zonaprop.com.ar/propiedades/clasificado/alclapin-3amb-al-fte-com-balcon-53576911.html": {"id": "53576911", "date": "07-05-2024\n", "index": 36, "content": "$ 600.000\n$ 120.000 Expensas\nguemes 3806\nBarrio Norte, Capital Federal\n73 m\u00b2 tot.\n3 amb.\n2 dorm.\n1 ba\u00f1o\nGuemes 3806. 3 ambientes con lavadero. Ba\u00f1o completo. Balcon hacia el frente. schwartz estudio inmobiliario. J. Alvarez 2410 caba - 1425. 48 24 - 70 77 / 48 23 - 82 88 (14hs a 19hs) w w w. S c h w a r t z. C o m. A r. ii5060. 6378Whatsapp. Art. 4\u00b0 - Hacer constar en todo ofrecimiento publicitario de locaci\u00f3n de inmuebles con destino habitacional que se emita v\u00eda p\u00e1ginas web, propias o de terceros, la siguiente leyenda: \"Para los casos de alquiler de vivienda, el monto m\u00e1ximo de comisi\u00f3n que se le puede requerir a los propietarios ser\u00e1 el equivalente al cuatro con quince cent\u00e9simos por ciento (4, 15%) del valor total del respectivo contrato. Se encuentra prohibido cobrar a los inquilinos que sean personas f\u00edsicas comisiones inmobiliarias y gastos de gestor\u00eda de informes \" (incorporado como inciso 8 del art\u00edculo 10 de la Ley 2340). Accesibilidad: Se puede recorrer desde la vereda hasta el ascensor por tramos horizontales o por rampa con anchos adecuados, luego en forma vertical por ascensor que tiene dimensiones adecuadas para circular con sillas de ruedas y luego hasta la propiedad por pasillo con ancho adecuado tambi\u00e9n. Matricula cucicba N\u00ba579 F\u00ba23 L1\nPublicado hace 4 d\u00edas\nContactar", "revised": false, "rejected": true, "data": {"precio": "$ 600.000", "expensas": "$ 120.000 Expensas", "direccion": "guemes 3806", "metros": "73 m\u00b2 tot.", "habitaciones": "3 amb.", "hace": "Contactar"}, "image": "https://imgar.zonapropcdn.com/avisos/1/00/53/57/69/11/360x266/1909454914.jpg?isFirstImage=true", "title": "Departamento de 3 ambientes, Barrio Norte \u00b7 3amb Al Fte Com Balcon"}, "https://www.zonaprop.com.ar/propiedades/clasificado/alclapin-b.-norte-3-amb-c-dep-y-cochera-53566200.html": {"id": "53566200", "date": "07-05-2024\n", "index": 38, "content": "$ 650.000\n$ 120.014 Expensas\nGallo al 1500\nBarrio Norte, Capital Federal\n78 m\u00b2 tot.\n4 amb.\n2 dorm.\n1 ba\u00f1o\n1 coch.\nC\u00f3modo semipiso C/espacio guardacoche m\u00f3vil. Excelente ubicaci\u00f3n A pasos de av. Santa fe Y subte D. Cfte C/balc\u00f3n A pulm\u00f3n de manzana. Todo luz. Muy buen estado. Lc apaisado C/aa F/C. 2 dormitorios C/placard. Amplia cocina C/comedor diario Y lavadero incorporado. Dependencia O escritorio C/ba\u00f1o de servicio. Entrada principal Y de servicio. Puerta blindada. No es apto prof. sup cub 75m2 + 5m2 balc\u00f3n. expensas vto abril $ 120. 014 aysa vto mayo $ 20. 272 tasa abl $ 4063. *para informaci\u00f3n O coordinar visita, contactarse al +54 9 11 Ver datos*condiciones** - Contrato de 24 meses - Ajuste trimestral por icl (\u00edndice para contratos de locaci\u00f3n bcra) - 1 mes adelantado - 1 mes de dep\u00f3sito en garant\u00eda. *requisitos* -Ingresos comprobables y acordes a los gastos que se asumen. -Garant\u00eda: inmueble de caba \u00f3 pba libre de grav\u00e1menes, o seguro de cauci\u00f3n que cubra todas las obligaciones del inquilino. Ley 5115 Art. 1: Accesible Ley 5859 Art. 4 (inciso 8 del art\u00edculo 10 de la Ley 2340, texto consolidado seg\u00fan Ley Nro. 5666): \"Para los casos de alquiler de vivienda, el monto m\u00e1ximo de comisi\u00f3n que se le puede requerir a los propietarios ser\u00e1 el equivalente al cuatro con quince cent\u00e9simos por ciento (4, 15%) del valor total del respectivo contrato. Se encuentra prohibido obrar a los inquilinos que sean personas f\u00edsicas comisiones inmobiliarias y gastos de gestor\u00eda de informes. \" Ley 2340 Art. 10: Matr\u00edcula cucicba 929 Nota: Las medidas (tanto totales como parciales), superficies, m2 y proporciones indicadas en el presente son aproximadas. El valor de expensas y tasas, var\u00eda mensualmente.\nPublicado hace 5 d\u00edas\nContactar", "revised": false, "rejected": true, "data": {"precio": "$ 650.000", "expensas": "$ 120.014 Expensas", "direccion": "Gallo al 1500", "metros": "78 m\u00b2 tot.", "habitaciones": "4 amb.", "hace": "Contactar"}, "image": "https://imgar.zonapropcdn.com/avisos/1/00/53/56/62/00/360x266/1909216137.jpg?isFirstImage=true", "title": "Departamento \u00b7 75m\u00b2 \u00b7 4 Ambientes \u00b7 1 Cochera \u00b7 B. Norte 3 Amb C/dep y Cochera"}, "https://www.zonaprop.com.ar/propiedades/clasificado/alclapin-san-luis-2800-balvanera-alquiler-3-amb.-caba-53565352.html": {"id": "53565352", "date": "07-05-2024\n", "index": 39, "content": "$ 400.000\n$ 100.000 Expensas\nSan Luis\nBalvanera, Capital Federal\n60 m\u00b2 tot.\n3 amb.\n2 dorm.\n1 ba\u00f1o\nAlquiler 3 ambientes contrafrente muy luminoso. Ba\u00f1o y cocina completos. Se entrega con 2 camas de 1 plaza y 1 futon\nPublicado hace 4 d\u00edas\nContactar", "revised": false, "rejected": false, "data": {"precio": "$ 400.000", "expensas": "$ 100.000 Expensas", "direccion": "San Luis", "metros": "60 m\u00b2 tot.", "habitaciones": "3 amb.", "hace": "Contactar"}, "image": "https://imgar.zonapropcdn.com/avisos/1/00/53/56/53/52/360x266/1909341278.jpg?isFirstImage=true", "title": "Departamento de 3 ambientes, Balvanera \u00b7 San Luis 2800 - Balvanera - Alquiler 3 Amb. - Caba"}, "https://www.zonaprop.com.ar/propiedades/clasificado/alclapin-alquiler-3-amb-barrio-norte-53562573.html": {"id": "53562573", "date": "07-05-2024\n", "index": 44, "content": "$ 530.000\n$ 78.000 Expensas\nJuncal al 2700\nBarrio Norte, Capital Federal\n68 m\u00b2 tot.\n3 amb.\n2 dorm.\n1 ba\u00f1o\nSe alquila 3 ambientes contrafrente. Excelente ubicaci\u00f3n. Apto profesional. 2 Aires acondicionados. Contrato de 2 a\u00f1os. Luciano Trajtenbergcucicba 8130\nPublicado hace 6 d\u00edas\nContactar", "revised": false, "rejected": true, "data": {"precio": "$ 530.000", "expensas": "$ 78.000 Expensas", "direccion": "Juncal al 2700", "metros": "68 m\u00b2 tot.", "habitaciones": "3 amb.", "hace": "Contactar"}, "image": "https://imgar.zonapropcdn.com/avisos/1/00/53/56/25/73/360x266/1909140565.jpg?isFirstImage=true", "title": "Departamento \u00b7 68m\u00b2 \u00b7 3 Ambientes \u00b7 Alquiler 3 Amb Barrio Norte"}, "https://www.zonaprop.com.ar/propiedades/clasificado/alclapin-tres-ambientes-en-congreso-mitre-y-libertad-53560407.html": {"id": "53560407", "date": "07-05-2024\n", "index": 47, "content": "$ 450.000\n$ 80.000 Expensas\nBARTOLOME MITRE 1200\nCongreso, Capital Federal\n70 m\u00b2 tot.\n3 amb.\n2 dorm.\n1 ba\u00f1o\nEdificio clasico. departamento al contrafrente de tres ambientes. muy luminoso. amplia cocina independiente con conexion lavarropas. dos habitaciones. balcon corrido. comodo living. pisos de madera todos plastificados. amplios placards. requisitos garantia caba O finaer Y constanciasde ingresos. alquiler mas gastos. apto porfesional\nPublicado hace 6 d\u00edas\nContactar", "revised": false, "rejected": true, "data": {"precio": "$ 450.000", "expensas": "$ 80.000 Expensas", "direccion": "BARTOLOME MITRE 1200", "metros": "70 m\u00b2 tot.", "habitaciones": "3 amb.", "hace": "Contactar"}, "image": "https://imgar.zonapropcdn.com/avisos/1/00/53/56/04/07/360x266/1909094792.jpg?isFirstImage=true", "title": "Departamento de 3 ambientes, Congreso \u00b7 Tres Ambientes en Congreso Mitre y Libertad"}, "https://www.zonaprop.com.ar/propiedades/clasificado/alclapin-departamento-en-alquiler-3-ambientes-con-balcon-53556815.html": {"id": "53556815", "date": "07-05-2024\n", "index": 51, "content": "$ 580.000\n$ 60.000 Expensas\nLavalle al 2900\nBalvanera, Capital Federal\n80 m\u00b2 tot.\n3 amb.\n2 dorm.\n1 ba\u00f1o\n** se alquila **Departamento de 3 ambientes con balcon. Se encuentra en un 9no piso, amplio departamento de 3 ambientes: cuenta con living comedor con salida al balc\u00f3n, cocina separada, sala comedor, lavadero con ba\u00f1o, dormitorio principal con salida al balc\u00f3n y placard, dormitorio secundario con placard, ba\u00f1o completo. Expensas $60. 000requisitos comerciales *garantia propietaria O garant\u00eda de finaer *demostracion de ingresos *contrato por 2 a\u00f1os *aumento trimestral por icl *deposito 2 mesesmuy buena ubicaci\u00f3n sobre la calle Lavalle al 2900 a 1 cuadra de Av. Corrientes. Si te interesa coordinar una visita para ver \u00e9sta y otras propiedades, por favor, no dejes de contactarte. fama PropiedadesCasa Central: Av. Emilio Castro 7371 - caba / Tel. : 4642. 5600\nPublicado hace 7 d\u00edas\nContactar", "revised": false, "rejected": true, "data": {"precio": "$ 580.000", "expensas": "$ 60.000 Expensas", "direccion": "Lavalle al 2900", "metros": "80 m\u00b2 tot.", "habitaciones": "3 amb.", "hace": "Contactar"}, "image": "https://imgar.zonapropcdn.com/avisos/1/00/53/55/68/15/360x266/1909015458.jpg?isFirstImage=true", "title": "LIVING \u00b7 Departamento en Alquiler 3 Ambientes con Balcon"}, "https://www.zonaprop.com.ar/propiedades/clasificado/alclapin-3-ambientes-con-cochera-53544115.html": {"id": "53544115", "date": "07-05-2024\n", "index": 52, "content": "$ 450.000\n$ 99.500 Expensas\nIndependencia al 2200\nBalvanera, Capital Federal\n62 m\u00b2 tot.\n3 amb.\n2 dorm.\n1 ba\u00f1o\n1 coch.\n3 Ambientes con cochera en Independencia 2200Al frente muy luminoso en 7\u00ba pisoLiving comedor de 4. 72 x 4. 68Pisos de Parquet Balc\u00f3n de 4 M2Dormitorio principal de 3. 03 x 2. 96 con placardSegundo dormitorio de 2. 94 x 3. 02 con placard Ba\u00f1o completoConexi\u00f3n para lavarropas: siservicios Individuales: sicochera fija: sibalc\u00f3n: SiApto mascotas: NoA/A: NoCalefacci\u00f3n: Nocondiciones de alquiler: Contrato de 2 a\u00f1os en pesosAjuste cada 6 meses por ipc (\u00edndice de precios al consumidor) Finaer o garant\u00eda propietaria de capital (familiar directo) 1 mes adelantado y 1 mes de dep\u00f3sitoDemostraci\u00f3n de ingresos por el triple del precio y del garanteGastos de certificaci\u00f3n de firmas a cargo del inquilino\nSuper destacado\nPublicado hace 8 d\u00edas\nContactar", "revised": false, "rejected": true, "data": {"precio": "$ 450.000", "expensas": "$ 99.500 Expensas", "direccion": "Independencia al 2200", "metros": "62 m\u00b2 tot.", "habitaciones": "3 amb.", "hace": "Contactar"}, "image": "https://imgar.zonapropcdn.com/avisos/1/00/53/54/41/15/360x266/1908726456.jpg?isFirstImage=true", "title": "Departamento \u00b7 58m\u00b2 \u00b7 3 Ambientes \u00b7 1 Cochera \u00b7 3 Ambientes con Cochera"}, "https://www.zonaprop.com.ar/propiedades/clasificado/alclapin-departamento-en-alquiler-barrio-balvanera-53542166.html": {"id": "53542166", "date": "07-05-2024\n", "index": 56, "content": "$ 400.000\n$ 50.000 Expensas\nIndependencia 1200\nBalvanera, Capital Federal\n70 m\u00b2 tot.\n3 amb.\n2 dorm.\n1 ba\u00f1o\nDepartamento de 70m2, cuenta con un ba\u00f1o con ducha y adem\u00e1s ba\u00f1o privado. Posee un patio descubierto, buen ingreso de luz natural. Muy buena ubicaci\u00f3n, cercano a Avenida 9 de Julio y universidad uade. Muy bien conectado con transporte p\u00fablico: Transportes Cercanos: Colectivos: 2, 9, 10, 17, 23, 39, 45, 53, 57, 59, 60, 67, 70, 91, 96, 98, 100, 102, 126, 129, 168, 195Subtes (Metro) : independencia (L\u00ednea C) , independencia (L\u00ednea E) Datos \u00fatiles: \u00c1rea Hospitalaria: htal. Dr. J. M. Ramos mej\u00edadistrito Escolar: Distrito Escolar iiimatriculado responsable: Roberto Barral matr\u00edcula N\u00ba3006 cucicba. ? En el cumplimiento de la ley nacional 25. 028, ley 22. 802 de lealtad comercial. ? Ley 24. 240 de defensa al consumidor, las normas del c\u00f3digo civil y comercial de la naci\u00f3n y constitucionales. Los agentes no ejercen el corretaje inmobiliario. ? Ley 5859 -Art. 4: \"Para los casos de alquiler de vivienda, el monto m\u00e1ximo de comisi\u00f3n que se le puede requerir a los propietarios ser\u00e1 el equivalente al cuatro con quince cent\u00e9simos por ciento (4, 15%) del valor total del contrato. Se encuentra prohibido cobrar a los inquilinos que sean personas f\u00edsicas comisiones inmobiliarias y gastos de gestor\u00eda de informes\". (En caso de ser alquiler) ? Ley 5115 \u2013 Art. 1: El inmueble publicado no es accesible para personas con capacidades f\u00edsicas reducidas. (En caso de no ser accesible) ? Se deja constancia que las medidas, superficies y m2 consignados son aproximados, sujetos a verificaci\u00f3n y/o ajuste. El precio del inmueble puede ser modificado sin previo aviso.\nSuper destacado\nPublicado hace 9 d\u00edas\nContactar", "revised": false, "rejected": true, "data": {"precio": "$ 400.000", "expensas": "$ 50.000 Expensas", "direccion": "Independencia 1200", "metros": "70 m\u00b2 tot.", "habitaciones": "3 amb.", "hace": "Contactar"}, "image": "https://imgar.zonapropcdn.com/avisos/1/00/53/54/21/66/360x266/1908679132.jpg?isFirstImage=true", "title": "Departamento \u00b7 70m\u00b2 \u00b7 3 Ambientes \u00b7 Departamento en Alquiler Barrio Balvanera"}, "https://www.zonaprop.com.ar/propiedades/clasificado/alclapin-alquiler-departamento-3-ambientes-balvanera-53539391.html": {"id": "53539391", "date": "07-05-2024\n", "index": 59, "content": "$ 550.000\n$ 98.000 Expensas\nPichincha 500\nBalvanera, Capital Federal\n70 m\u00b2 tot.\n3 amb.\n2 dorm.\n1 ba\u00f1o\nCorredor Responsable: guillermo frimet cucicba 4235 / Pablo Anibal Montenegro cpmcal 552- Contacto: Carla Vasti - mls id # Ver datos. Excelente departamento al frente, con balcon corrido de tres ambientes con dependencia muy luminoso. Pisos de madera. Ba\u00f1o completo. Ba\u00f1o de servicio. Cocina separda. lavadero. Excelente ubicacion, cerca de medios de transporte. Requisitos: Mes de alquiler. Mes de deposito de Garantia. Seguro de caucion por Finaer, Garantor o Garantia Ya. Transportes Cercanos. Colectivos: 2, 8, 23, 56, 57, 61, 62, 64, 84, 86, 88, 95, 96, 98, 101, 103, 118, 129, 168, Remax Argentina S. R. L. No ejerce el corretaje inmobiliario. El presente sitio web es una plataforma en donde cada oficina inmobiliaria independiente que contrata los servicios re/max puede publicar las propiedades a su cargo. Cada oficina es de propiedad y gesti\u00f3n independiente, por lo que Remax Argentina S. R. L no interviene en los datos de la publicaci\u00f3n, en la operaci\u00f3n inmobiliaria, ni en la confecci\u00f3n y/o firma del boleto de compraventa y/o escritura y/o contrato de alquiler. En cumplimiento de las leyes vigentes que regulan el corretaje inmobiliario, Ley Nacional 25. 028, Ley 22. 802 de Lealtad Comercial, Ley 24. 240 de Defensa al Consumidor, las normas del C\u00f3digo Civil y Comercial de la Naci\u00f3n y Constitucionales, los agentes/gestores no ejercen el corretaje inmobiliario. Todas las operaciones inmobiliarias son objeto de intermediaci\u00f3n y conclusi\u00f3n por parte del corredor p\u00fablico inmobiliario colegiado a cargo de la publicaci\u00f3n, cuyos datos se exhiben en la presente. La presente publicaci\u00f3n describe las caracter\u00edsticas esenciales del inmueble, debi\u00e9ndose consultar al corredor p\u00fablico inmobiliario responsable de la operaci\u00f3n por la eventual actualizaci\u00f3n de las medidas, descripciones arquitect\u00f3nicas y funcionales, valores de expensas, servicios, impuestos, precios y dem\u00e1s informaci\u00f3n, cuyos valores son aproximados. Para los casos de alquiler de vivienda, el monto m\u00e1ximo de comisi\u00f3n que se le puede requerir a los propietarios ser\u00e1 el equivalente al cuatro con quince cent\u00e9simos por ciento (4, 15%) del valor total del respectivo contrato. Se encuentra prohibido cobrar a los inquilinos que sean personas f\u00edsicas comisiones inmobiliarias y gastos de gestor\u00eda de informes. El inmueble no es accesible para personas con discapacidades f\u00edsicas.\nPublicado hace 10 d\u00edas\nContactar", "revised": false, "rejected": true, "data": {"precio": "$ 550.000", "expensas": "$ 98.000 Expensas", "direccion": "Pichincha 500", "metros": "70 m\u00b2 tot.", "habitaciones": "3 amb.", "hace": "Contactar"}, "image": "https://imgar.zonapropcdn.com/avisos/1/00/53/53/93/91/360x266/1908611695.jpg?isFirstImage=true", "title": "Departamento \u00b7 65m\u00b2 \u00b7 3 Ambientes \u00b7 Alquiler Departamento 3 Ambientes Balvanera"}, "https://www.zonaprop.com.ar/propiedades/clasificado/alclapin-departamento-en-barrio-norte-53592706.html": {"id": "53592706", "date": "08-05-2024\n", "index": 1, "content": "22\n$ 650.000\n$ 150.000 Expensas\nJunin al 1300\nBarrio Norte, Capital Federal\n90 m\u00b2 tot.\n4 amb.\n3 dorm.\n2 ba\u00f1os\nSemi piso en alquiler en Recoleta. Consta de palier semi privado, hall de distribuci\u00f3n, living comedor, balc\u00f3n corrido, 3 dormitorios con amplios placares, ba\u00f1o completo y toilette, cocina con lavadero. Requiere reparaci\u00f3n de alba\u00f1iler\u00eda y pintura. Esta ubicado en Junin al 1300 entre Pe\u00f1a y French, proximo a Avda. Pueyrred\u00f3n, Avda. Las Heras, Avda. Callao, colectivos, subte, comercios. Pida tasaci\u00f3n: Efectuada por profesionales, que analizan permanentemente el desenvolvimiento del mercado. Conf\u00ede su patrimonio en una empresa s\u00f3lida con respaldo y prestigio. Conf\u00ede en el L\u00edder. Goldstein propiedades. Se deja constancia que los m2 son aproximados, al igual que las medidas parciales y el valor consignado de las expensas mensuales (en caso que corresponda pago de expensas) y las caracter\u00edsticas est\u00e1n sujetos a verificaci\u00f3n y/o ajustes, el precio del inmueble puede ser modificado sin previo aviso. En el caso de tratarse de un inmueble en construcci\u00f3n los detalles de terminaci\u00f3n y la fecha de entrega est\u00e1n sujetos a revisi\u00f3n. Fotos de car\u00e1cter no contractual. Las unidades publicadas est\u00e1n sujetas a disponibilidad. Goldstein Propiedades srl con domicilio en Avda. Corrientes 4666 act\u00faa solamente en car\u00e1cter de comercializadora de los inmuebles ofrecidos. En caso de tratarse de un terreno, la informaci\u00f3n de m2 construibles y plusval\u00eda es orientativa, debiendo ser constatada por el interesado. Inmueble no accesible para personas con discapacidad f\u00edsica ley 5115. Cucicba matr\u00edcula 37. Cmcpsi matr\u00edcula 6003. \u00danicamente en el caso de tratarse de alquiler de vivienda familiar, rige lo indicado en la ley 5859. Venta supeditada al cumplimiento por parte del propietario de los requisitos de la resoluci\u00f3n general N\u00ba 2371 de la afip (pedido de coti).\nSuper destacado\nPublicado hoy\nContactar", "revised": false, "rejected": false, "data": {"precio": "$ 650.000", "expensas": "$ 150.000 Expensas", "direccion": "Junin al 1300", "metros": "90 m\u00b2 tot.", "habitaciones": "4 amb.", "hace": "Contactar"}, "image": "https://imgar.zonapropcdn.com/avisos/1/00/53/59/27/06/360x266/1909808353.jpg?isFirstImage=true", "title": "Departamento \u00b7 82m\u00b2 \u00b7 4 Ambientes \u00b7 Departamento en Barrio Norte"}, "https://www.zonaprop.com.ar/propiedades/clasificado/alclapin-3-ambientes-semipiso-balcon-garantia-propietaria-53598563.html": {"id": "53598563", "date": "08-05-2024\n", "index": 4, "content": "$ 400.000\n$ 48.000 Expensas\nJUNIN 658\nBarrio Norte, Capital Federal\n77 m\u00b2 tot.\n3 amb.\n2 dorm.\n1 ba\u00f1o\nSemipiso amplio Y muy luminoso - entrada principal Y de servicio - balc\u00f3n - cocina Y ba\u00f1o completos - gran living comedor - amplios dormitorios con vestidores - otorga 1 mes de gracia para pintura - edificio con vigilancia - 2 ascensores autom\u00e1ticos - cercano A avenidas c\u00f3rdoba Y corrientes Y facultades - todo el transporte A pasos - Condiciones: Primeros 4 meses: $400. 000 mensuales. Actualizaci\u00f3n cada 4 meses seg\u00fan I. C. L. - Otorga mes sin cargo de alquiler para pintura - toma garant\u00eda propietaria de ciudad de buenos aires o caucion de finaer\nDestacado\nPublicado hoy\nContactar", "revised": false, "rejected": false, "data": {"precio": "$ 400.000", "expensas": "$ 48.000 Expensas", "direccion": "JUNIN 658", "metros": "77 m\u00b2 tot.", "habitaciones": "3 amb.", "hace": "Contactar"}, "image": "https://imgar.zonapropcdn.com/avisos/1/00/53/59/85/63/360x266/1909930217.jpg?isFirstImage=true", "title": "Departamento de 3 ambientes, Barrio Norte \u00b7 3 Ambientes - Semipiso - Balc\u00f3n - Garant\u00eda Propietaria C. A. b. A. o Finaer"}, "https://www.zonaprop.com.ar/propiedades/clasificado/alclapin-alquiler-3-amb-amplios-cfte-patio-aterrazado-excelente-53595156.html": {"id": "53595156", "date": "08-05-2024\n", "index": 15, "content": "$ 680.000\n$ 160.000 Expensas\nDirecci\u00f3n no informada\nBarrio Norte, Capital Federal\n120 m\u00b2 tot.\n3 amb.\n2 dorm.\n1 ba\u00f1o\n. *solo se alquila con acreditacion de ingresos O garantia caba prov O seguro caucion. * no se acepta mascotas. 3 amb en alquiler. contrafrente. living cocina Y banos completos. lavadero. toillet. 2 patios. no es planta baja. para ver el depto mandar un whatsaap al Ver datos\nPublicado hoy\nContactar", "revised": false, "rejected": false, "data": {"precio": "$ 680.000", "expensas": "$ 160.000 Expensas", "direccion": "Direcci\u00f3n no informada", "metros": "120 m\u00b2 tot.", "habitaciones": "3 amb.", "hace": "Contactar"}, "image": "https://imgar.zonapropcdn.com/avisos/1/00/53/59/51/56/360x266/1909960752.jpg?isFirstImage=true", "title": "Departamento de 3 ambientes, Barrio Norte \u00b7 Alquiler 3 Amb Amplios Cfte Patio Aterrazado Excelente - Mansilla y Ecuador"}, "https://www.zonaprop.com.ar/propiedades/clasificado/alclocin-hermoso-4-amb-112-m-sup2--en-balvanera!-bajas-53591141.html": {"id": "53591141", "date": "08-05-2024\n", "index": 20, "content": "$ 700.000\n$ 45.000 Expensas\nJuan D Peron 2200\nBalvanera, Capital Federal\n112 m\u00b2 tot.\n4 amb.\n3 dorm.\n1 ba\u00f1o\nHermoso departamento de 4 ambientes amplios y luminosos con 112m2 totales en Balvanera! Edificio antiguo con estilo muy bien mantenido. Hall. Sala de estar. Despacho 1 4, 15m x 3, 90m. Despacho 2 4m x 3, 90m con placard. Despacho 3 3m x 3, 90m con placard. Despacho 4 4m x 3m. Ba\u00f1o completo y toilet de servicio. Cocina y lavadero independiente. Excelente Ubicaci\u00f3n: - en el mismo edificio del Instituto Otorrino Arauz. - cercan\u00eda a numerosos sanatorios y cl\u00ednicas. - a 2 cuadras de Estaci\u00f3n Pasteur de Subte B. - a 2 cuadras de Estaci\u00f3n Pasco de Subte A. - cercan\u00eda a numerosos negocios comerciales. muy baja expensas! Uso profesional\nSuper destacado\nPublicado desde ayer\nContactar", "revised": false, "rejected": false, "data": {"precio": "$ 700.000", "expensas": "$ 45.000 Expensas", "direccion": "Juan D Peron 2200", "metros": "112 m\u00b2 tot.", "habitaciones": "4 amb.", "hace": "Contactar"}, "image": "https://imgar.zonapropcdn.com/avisos/1/00/53/59/11/41/360x266/1909772619.jpg?isFirstImage=true", "title": "Oficina comercial de 4 ambientes, Balvanera \u00b7 Hermoso 4 Amb 112 m\u00b2 en Balvanera! Bajas Expensas! Uso Profesional!"}, "https://www.zonaprop.com.ar/propiedades/clasificado/alclapin-av-del-libertador-250-departamento-retiro-53582654.html": {"id": "53582654", "date": "08-05-2024\n", "index": 32, "content": "$ 650.000\n$ 170.000 Expensas\ndel Libertador al 200\nBarrio Norte, Capital Federal\n85 m\u00b2 tot.\n4 amb.\n3 dorm.\n1 ba\u00f1o\n1 coch.\nRetiro - alquiler Av. Del Libertador 250 piso 7moEntre Esmeralda y Basavilbaso4 Amb con Dependencia y cochera - FrenteSuperficie cubierta: 85m\u00b2Superficie total: 85m\u00b2Plantas: 1Cantidad Ba\u00f1os: 2Balc\u00f3n: FrancesLavadero: SiCochera: sidependencia: SiCantidad Deptos x Piso: 4Cantidad Pisos Edificio: 20cochera Y dependencia. Zarlenga Inmobiliaria - Matricula: 7057 - aviso legal: Las descripciones arquitect\u00f3nicas y funcionales, valores de expensas, impuestos y servicios, fotos y medidas de este inmueble son aproximados. Los datos fueron proporcionados por el propietario y pueden no estar actualizados a la hora de la visualizaci\u00f3n de este aviso por lo cual pueden arrojar inexactitudes y discordancias con las que surgen de las facturas, t\u00ed\u00adtulos y planos legales del inmueble. El interesado deber\u00e1 realizar las verificaciones respectivas previamente a la realizaci\u00f3n de cualquier operaci\u00c3\u00b3n, requiriendo por s\u00fa\u00ad o sus profesionales las copias necesarias de la documentaci\u00f3n que corresponda. Venta supeditada al cumplimiento por parte del propietario de los requisitos de la resoluci\u00f3n general Nro. 2371 de la afip (pedido de coti).\nPublicado hace 2 d\u00edas\nContactar", "revised": false, "rejected": false, "data": {"precio": "$ 650.000", "expensas": "$ 170.000 Expensas", "direccion": "del Libertador al 200", "metros": "85 m\u00b2 tot.", "habitaciones": "4 amb.", "hace": "Contactar"}, "image": "https://imgar.zonapropcdn.com/avisos/1/00/53/58/26/54/360x266/1909588496.jpg?isFirstImage=true", "title": "Departamento \u00b7 85m\u00b2 \u00b7 4 Ambientes \u00b7 1 Cochera \u00b7 Av del Libertador 250 - Departamento - Retiro"}, "https://www.zonaprop.com.ar/propiedades/clasificado/alclapin-alq-3-amb-frente-al-parque-las-heras-apto-prof-53573277.html": {"id": "53573277", "date": "08-05-2024\n", "index": 48, "content": "$ 700.000\n$ 135.000 Expensas\nDirecci\u00f3n no informada\nBarrio Norte, Capital Federal\n79 m\u00b2 tot.\n4 amb.\n3 dorm.\n1 ba\u00f1o\n1 coch.\nExcelente ubicacion, edificio ubicado frente al parque las heras, departamento de 4 ambientes con vista al parque las heras, balcon, muy luminoso, living comedor, 3 dormitorios ( uno es la dependencia, adaptado como 3 dormitorio), cocina office, ba\u00f1o completo Y ba\u00f1o de servicio, cochera fija en planta baja, apto profesional. El valor de las expensas esta sujeto A variacion Y/O ajuste. Las medidas son aproximadas en caracter orientativo.\nPublicado hace 4 d\u00edas\nContactar", "revised": false, "rejected": false, "data": {"precio": "$ 700.000", "expensas": "$ 135.000 Expensas", "direccion": "Direcci\u00f3n no informada", "metros": "79 m\u00b2 tot.", "habitaciones": "4 amb.", "hace": "Contactar"}, "image": "https://imgar.zonapropcdn.com/avisos/1/00/53/57/32/77/360x266/1909378108.jpg?isFirstImage=true", "title": "Departamento de 4 ambientes, Barrio Norte \u00b7 Alq 3 Amb, Frente Al Parque Las Heras, Apto Prof"}, "https://www.zonaprop.com.ar/propiedades/clasificado/alclapin-excelente-depto-125-m-sup2--al-frente-tres-dorm.-53567497.html": {"id": "53567497", "date": "08-05-2024\n", "index": 51, "content": "$ 1.200.000\n$ 110.000 Expensas\nFrench 2400\nBarrio Norte, Capital Federal\n125 m\u00b2 tot.\n4 amb.\n3 dorm.\n2 ba\u00f1os\n1 coch.\nSemipiso al frente de 125 m2, palier privado, hall, recepci\u00f3n en L a balc\u00f3n corrido, tres dormitorios (uno en suite), ventanal doble vidrio, dos ba\u00f1os, toilette, cocina office, lavadero independiente, dependencia de servicio, muy luminoso, profusi\u00f3n de placards, calefacci\u00f3n por losa radiante, caldera individual, tres aparatos de A/A fr\u00edo/calor, guardacoches fijo, excelente estado. Expensas $ 110. 000. - (\u00daltimas) informes cel. Ver datos\nDestacado\nPublicado hace 5 d\u00edas\nContactar", "revised": false, "rejected": false, "data": {"precio": "$ 1.200.000", "expensas": "$ 110.000 Expensas", "direccion": "French 2400", "metros": "125 m\u00b2 tot.", "habitaciones": "4 amb.", "hace": "Contactar"}, "image": "https://imgar.zonapropcdn.com/avisos/1/00/53/56/74/97/360x266/1909248950.jpg?isFirstImage=true", "title": "Departamento de 4 ambientes, Barrio Norte \u00b7 Excelente Depto, 125 m\u00b2 Al Frente, Tres Dorm., Dep. Guardacoches Fijo"}, "https://www.zonaprop.com.ar/propiedades/clasificado/alclapin-french-y-larrea-frente-125-m-sup2--tres-dorm.-dep.-53569904.html": {"id": "53569904", "date": "08-05-2024\n", "index": 52, "content": "$ 1.200.000\n$ 110.000 Expensas\nFrench 2400\nBarrio Norte, Capital Federal\n125 m\u00b2 tot.\n4 amb.\n3 dorm.\n2 ba\u00f1os\n1 coch.\nExcelente propiedad de 125 m2 - Palier privado, hall, livingcomedor en L con salida a balc\u00f3n corrido, tres dormitorios (uno en suite) dos ba\u00f1os, toilette, cocina, office, lavadero, dependencia de servicio, tres A/A fr\u00edo/calor, caldera propia para calefacci\u00f3n y agua caliente, guardacoche fijo. Expensas $ 110. 000. - informes Ver datos\nDestacado\nPublicado hace 5 d\u00edas\nContactar", "revised": false, "rejected": false, "data": {"precio": "$ 1.200.000", "expensas": "$ 110.000 Expensas", "direccion": "French 2400", "metros": "125 m\u00b2 tot.", "habitaciones": "4 amb.", "hace": "Contactar"}, "image": "https://imgar.zonapropcdn.com/avisos/1/00/53/56/99/04/360x266/1909301598.jpg?isFirstImage=true", "title": "Departamento de 4 ambientes, Barrio Norte \u00b7 French y Larrea - Frente 125 m\u00b2 - Tres Dorm. Dep. Serv. Guardacoche Fijo"}, "https://www.zonaprop.com.ar/propiedades/clasificado/alclapin-alquiler-arenales-1600-4-ant.-frances-amplio-y-muy-53563997.html": {"id": "53563997", "date": "08-05-2024\n", "index": 56, "content": "Consultar precio\n$ 130.000 Expensas\nArenales al 1600 y Montevideo\nBarrio Norte, Capital Federal\n252 m\u00b2 tot.\n6 amb.\n4 dorm.\n3 ba\u00f1os\nEdificio Antiguo Frances de 5 pisos, a media cuadra de Plaza Vicente Lopez. Piso 4 Super amplio y Luminoso!! 252m2. Hall de entrada con una barra, living y comedor amplio al frente sobre la calle Arenales. Pisos de pinotea, aberturas originales, techos altos. Playroom/ escritorio. Toilette de recepci\u00f3n. Doble circulaci\u00f3n. Cocina con comedor diario, lavadero independiente y dependencia de servicio con su ba\u00f1o. Toilette de recepci\u00f3n. 4 dormitorios amplios (dos en suite y los otros dos comparten un ba\u00f1o). Cfte vista verde super silencioso y luminosos. Servicios individuales, aa, calefacci\u00f3n por radiadores individuales y agua caliente individual. Expensas bajas $130. 000, encargado vive en el edificio pero trabaja 4 hrs diarias. Aysa $20. 000. Observaciones: se entrega pintado y artefacto cocina a nuevo. Actualmente alquilan cochera sobre Montevideo a media cuadra en $40. 000. Opci\u00f3n con muebles\nPublicado hace 5 d\u00edas\nContactar", "revised": false, "rejected": false, "data": {"precio": "Consultar precio", "expensas": "$ 130.000 Expensas", "direccion": "Arenales al 1600 y Montevideo", "metros": "252 m\u00b2 tot.", "habitaciones": "6 amb.", "hace": "Contactar"}, "image": "https://imgar.zonapropcdn.com/avisos/1/00/53/56/39/97/360x266/1909168706.jpg?isFirstImage=true", "title": "Departamento \u00b7 252m\u00b2 \u00b7 6 Ambientes \u00b7 Alquiler - Arenales 1600 4 Ant. Frances Amplio y Muy Luminoso 252 m\u00b2 Opc Muebles"}, "https://www.zonaprop.com.ar/propiedades/clasificado/alclocin-oficina-en-balvanera-300-m-53563623.html": {"id": "53563623", "date": "08-05-2024\n", "index": 59, "content": "$ 400.000\nGeneral Urquiza al 100\nBalvanera, Capital Federal\n350 m\u00b2 tot.\n8 amb.\n8 dorm.\n1 ba\u00f1o\nOficina comercial en primer piso por escalera en excelente ubicacionLa oficina cuenta con varias aulas independientes y ba\u00f1osIdeal Instituto. **Corredor Inmobiliario Responsable Adrian Ridelnik cucicba Mat 197. *Se deja constancia que las medidas y superficies indicados son aproximados y al s\u00f3lo efecto orientativo. Las medidas reales surgir\u00e1n del t\u00edtulo de propiedad respectivo. Las medidas parciales y/o de los ambientes y el valor consignado de expensas mensuales, servicios y abl est\u00e1 sujeto a verificaci\u00f3n y/o ajuste. Art. 4 de la Ley 5. 859 de C. A. B. A \"Para los casos de alquiler de vivienda \u00fanica, el monto m\u00e1ximo de comisi\u00f3n que se le puede requerir a los propietarios ser\u00e1 el equivalente al cuatro con quince cent\u00e9simos por ciento (4, 15%) del valor total del respectivo contrato. Se encuentra prohibido cobrar a los inquilinos que sean personas f\u00edsicas comisiones inmobiliarias cuando el destino sea vivienda \u00fanica y permanente \". -\nPublicado hace 5 d\u00edas\nContactar", "revised": false, "rejected": false, "data": {"precio": "$ 400.000", "expensas": "", "direccion": "General Urquiza al 100", "metros": "350 m\u00b2 tot.", "habitaciones": "8 amb.", "hace": "Contactar"}, "image": "https://imgar.zonapropcdn.com/avisos/1/00/53/56/36/23/360x266/1909160421.jpg?isFirstImage=true", "title": "Oficina comercial \u00b7 350m\u00b2 \u00b7 8 Ambientes \u00b7 Oficina en Balvanera 300 m"}}